Workbook

Sheet SCPR2022
A2: SIDLAK CHRISTIAN CHILDREN FUND SAVINGS AND CREDIT COOPERATIVE
A3: CDA Registration No. 9520-1080000000036399 Dated: November 16, 2016
A4: P-2, Brgy. Linao, Ormoc City
A6: COMPUTATION OF SHARES AND PATRONAGE REFUND
A7: As of FY 2023
A9: Members | C9: From 2022 | D9: Jan | E9: Feb | F9: Mar | G9: Apr | H9: May | I9: Jun | J9: Jul | K9: Aug | L9: Sep | M9: Oct | N9: Nov | O9: Dec | P9: TSM | Q9: ASM | R9: IOSC | S9: Int. on Loans | T9: Patronage Refund | U9: Total (IOSC+PR) | V9: Signature
A11: 1 | B11: Allen L. Gubalane | C11: =2154.73+13.01 -> 2167.74 | P11: =C11+D11+E11+F11+G11+H11+I11+J11+K11+L11+M11+N11+O11 -> 2167.74 | Q11: =P11/12 -> 180.645
A12: 2 | B12: April A. Hubahib | C12: 1300 | P12: =C12+D12+E12+F12+G12+H12+I12+J12+K12+L12+M12+N12+O12 -> 1300 | Q12: =P12/12 -> 108.33333
A13: 3 | B13: Arnold C. Gonzales | C13: =2238.34+13.51 -> 2251.85 | P13: =C13+D13+E13+F13+G13+H13+I13+J13+K13+L13+M13+N13+O13 -> 2251.85 | Q13: =P13/12 -> 187.65417
A14: 4 | B14: Elina Empimo | C14: 750 | P14: =C14+D14+E14+F14+G14+H14+I14+J14+K14+L14+M14+N14+O14 -> 750 | Q14: =P14/12 -> 62.5
A15: 5 | B15: Crisencia R. Ruiz | C15: 7000 | P15: =C15+D15+E15+F15+G15+H15+I15+J15+K15+L15+M15+N15+O15 -> 7000 | Q15: =P15/12 -> 583.33333
A16: 6 | B16: Dennis M. Tolibao | C16: 150 | P16: =C16+D16+E16+F16+G16+H16+I16+J16+K16+L16+M16+N16+O16 -> 150 | Q16: =P16/12 -> 12.5
A17: 7 | B17: Dexter B. Jumao-as | C17: 7000 | P17: =C17+D17+E17+F17+G17+H17+I17+J17+K17+L17+M17+N17+O17 -> 7000 | Q17: =P17/12 -> 583.33333
A18: 8 | B18: Dorotea Jumao-as | C18: 7000 | P18: =C18+D18+E18+F18+G18+H18+I18+#REF!+J18+L18+M18+N18+O18 -> #REF! | Q18: =P18/12 -> #REF!
A19: 9 | B19: Edgardo P. Nodalo | C19: =2021.27+12.03 -> 2033.3 | P19: =C19+D19+E19+F19+G19+H19+I19+J19+K19+L19+M19+N19+O19 -> 2033.3 | Q19: =P19/12 -> 169.44167
A20: 10 | B20: Eloisa E. Williams | C20: =2728.71+16.24 -> 2744.95 | P20: =C20+D20+E20+F20+G20+H20+I20+J20+K20+L20+M20+N20+O20 -> 2744.95 | Q20: =P20/12 -> 228.74583
A21: 11 | B21: Emmanuel C. Orellano | C21: 700 | P21: =C21+D21+E21+F21+G21+H21+I21+J21+K21+L21+M21+N21+O21 -> 700 | Q21: =P21/12 -> 58.333333
A22: 12 | B22: Emmanuel S. Quilantang | C22: =2081.27+12.39 -> 2093.66 | P22: =C22+D22+E22+F22+G22+H22+I22+J22+K22+L22+M22+N22+O22 -> 2093.66 | Q22: =P22/12 -> 174.47167
A23: 13 | B23: Erlinda E. Quilantang | C23: =2122.33+12.63 -> 2134.96 | P23: =C23+D23+E23+F23+G23+H23+I23+J23+K23+L23+M23+N23+O23 -> 2134.96 | Q23: =P23/12 -> 177.91333
A24: 14 | B24: Eunicelle S. Samson | C24: =5560+33.09 -> 5593.09 | P24: =C24+D24+E24+F24+G24+H24+I24+J24+K24+L24+M24+N24+O24 -> 5593.09 | Q24: =P24/12 -> 466.09083
A25: 15 | B25: Genelyn N. Ymas | C25: 150 | P25: =C25+D25+E25+F25+G25+H25+I25+J25+K25+L25+M25+N25+O25 -> 150 | Q25: =P25/12 -> 12.5
A26: 16 | B26: Junel A. Pagay | C26: 1200 | P26: =C26+D26+E26+F26+G26+H26+I26+J26+K26+L26+M26+N26+O26 -> 1200 | Q26: =P26/12 -> 100
A27: 17 | B27: Limuel P. Omega | C27: 200 | P27: =C27+D27+E27+F27+G27+H27+I27+J27+K27+L27+M27+N27+O27 -> 200 | Q27: =P27/12 -> 16.666667
A28: 18 | B28: Ma. Ella P. Solano | C28: =2420+14.4 -> 2434.4 | P28: =C28+D28+E28+F28+G28+H28+I28+J28+K28+L28+M28+N28+O28 -> 2434.4 | Q28: =P28/12 -> 202.86667
A29: 19 | B29: Maria Genia C. Seguido | C29: 7000 | P29: =C29+D29+E29+F29+G29+H29+I29+J29+K29+L29+M29+N29+O29 -> 7000 | Q29: =P29/12 -> 583.33333
A30: 20 | B30: Mario G. Bañez Jr. | C30: 1300 | P30: =C30+D30+E30+F30+G30+H30+I30+J30+K30+L30+M30+N30+O30 -> 1300 | Q30: =P30/12 -> 108.33333
A31: 21 | B31: Marissa B. Ligutan | C31: 750 | P31: =C31+D31+E31+F31+G31+H31+I31+J31+K31+L31+M31+N31+O31 -> 750 | Q31: =P31/12 -> 62.5
A32: 22 | B32: Maristela A. Mandras | C32: 1200 | P32: =C32+D32+E32+F32+G32+H32+I32+J32+K32+L32+M32+N32+O32 -> 1200 | Q32: =P32/12 -> 100
A33: 23 | B33: Mark Gil M. Catingub | C33: 100 | P33: =C33+D33+E33+F33+G33+H33+I33+J33+K33+L33+M33+N33+O33 -> 100 | Q33: =P33/12 -> 8.3333333
A34: 24 | B34: Mary Grace C. Perol | C34: =2009+11.96 -> 2020.96 | P34: =C34+D34+E34+F34+G34+H34+I34+J34+K34+L34+M34+N34+O34 -> 2020.96 | Q34: =P34/12 -> 168.41333
A35: 25 | B35: Maricris Montemor | C35: 600 | P35: =C35+D35+E35+F35+G35+H35+I35+J35+K35+L35+M35+N35+O35 -> 600 | Q35: =P35/12 -> 50
A36: 26 | B36: Analyn Cabahug | C36: =2885+17.17 -> 2902.17 | P36: =C36+D36+E36+F36+G36+H36+I36+J36+K36+L36+M36+N36+O36 -> 2902.17 | Q36: =P36/12 -> 241.8475
A37: 27 | B37: Nenita S. Fay | C37: =2120+12.62 -> 2132.62 | P37: =C37+D37+E37+F37+G37+H37+I37+J37+K37+L37+M37+N37+O37 -> 2132.62 | Q37: =P37/12 -> 177.71833
A38: 28 | B38: Paul C. Espinosa | C38: =2581.27+102.65 -> 2683.92 | P38: =C38+D38+E38+F38+G38+H38+I38+J38+K38+L38+M38+N38+O38 -> 2683.92 | Q38: =P38/12 -> 223.66
P40: =SUM(P11:P39) -> #REF! | U40: Page 1 of 4
A42: SIDLAK CHRISTIAN CHILDREN FUND SAVINGS AND CREDIT COOPERATIVE
A43: CDA Registration No. 9520-1080000000036399 Dated: November 16, 2016
A44: P-2, Brgy. Linao, Ormoc City
A46: COMPUTATION OF SHARES AND PATRONAGE REFUND
A47: As of FY 2022
A49: Members | C49: From 2021 | D49: Jan | E49: Feb | F49: Mar | G49: Apr | H49: May | I49: Jun | J49: Jul | K49: Aug | L49: Sep | M49: Oct | N49: Nov | O49: Dec | P49: TSM | Q49: ASM | R49: IOSC | S49: Int. on Loans | T49: Patronage Refund | U49: Total (IOSC+PR) | V49: Signature
A52: 29 | B52: Raffy C. Banghet | C52: =2021.27+12.03 -> 2033.3 | P52: =C52+D52+E52+F52+G52+H52+I52+J52+K52+L52+M52+N52+O52 -> 2033.3 | Q52: =P52/12 -> 169.44167 | R52: =SCPR2020!AD52 -> 20.742147
A53: 30 | B53: Rexie N. Costan | C53: =2100+12.5 -> 2112.5 | P53: =C53+D53+E53+F53+G53+H53+I53+J53+K53+L53+M53+N53+O53 -> 2112.5 | Q53: =P53/12 -> 176.04167 | R53: =SCPR2020!AD53 -> 21.55007
A54: 31 | B54: Ricardo G. Amarille | C54: =2534+15.08 -> 2549.08 | P54: =C54+D54+E54+F54+G54+H54+I54+J54+K54+L54+M54+N54+O54 -> 2549.08 | Q54: =P54/12 -> 212.42333 | R54: =SCPR2020!AD54 -> 26.906802
A55: 32 | B55: Rodina A. Alvarado | C55: =2554+37.02 -> 2591.02 | P55: =C55+D55+E55+F55+G55+H55+I55+J55+K55+L55+M55+N55+O55 -> 2591.02 | Q55: =P55/12 -> 215.91833 | R55: =SCPR2020!AD55 -> 28.363997
A56: 33 | B56: Rolando C. Miaga | C56: 1100 | P56: =C56+D56+E56+F56+G56+H56+I56+J56+K56+L56+M56+N56+O56 -> 1100 | Q56: =P56/12 -> 91.666667 | R56: =SCPR2020!AD56 -> 11.288132
A57: 34 | B57: Ronald P. Arcillas | C57: 1000 | P57: =C57+D57+E57+F57+G57+H57+I57+J57+K57+L57+M57+N57+O57 -> 1000 | Q57: =P57/12 -> 83.333333 | R57: =SCPR2020!AD57 -> 10.261938
A58: 35 | B58: Victoriana A. Entero | C58: 935.84 | P58: =C58+D58+E58+F58+G58+H58+I58+J58+K58+L58+M58+N58+O58 -> 935.84 | Q58: =P58/12 -> 77.986667 | R58: =SCPR2020!AD58 -> 10.465535
A59: 36 | B59: Jaime A. Cayetano Jr. | C59: 300 | P59: =C59+D59+E59+F59+G59+H59+I59+J59+K59+L59+M59+N59+O59 -> 300 | Q59: =P59/12 -> 25 | R59: =SCPR2020!AD59 -> 3.0785814
A60: 37 | B60: Archie G. Bañez | C60: 650 | P60: =C60+D60+E60+F60+G60+H60+I60+J60+K60+L60+M60+N60+O60 -> 650 | Q60: =P60/12 -> 54.166667 | R60: =SCPR2020!AD60 -> 6.6702597
A61: 38 | B61: Ronan O. Sacay | C61: 350 | P61: =C61+D61+E61+F61+G61+H61+I61+J61+K61+L61+M61+N61+O61 -> 350 | Q61: =P61/12 -> 29.166667 | R61: =SCPR2020!AD61 -> 3.5916783
A62: 39 | B62: Edwin P. Caliwan | C62: 150 | P62: =C62+D62+E62+F62+G62+H62+I62+J62+K62+L62+M62+N62+O62 -> 150 | Q62: =P62/12 -> 12.5 | R62: =SCPR2020!AD62 -> 1.5392907
A63: 40 | B63: Analyn A. Punay | C63: =2540+36.94 -> 2576.94 | P63: =C63+D63+E63+F63+G63+H63+I63+J63+K63+L63+M63+N63+O63 -> 2576.94 | Q63: =P63/12 -> 214.745 | R63: =SCPR2020!AD63 -> 26.927325
A64: 41 | B64: Susana I. Punay | C64: 7000 | P64: =C64+D64+E64+F64+G64+H64+I64+J64+K64+L64+M64+N64+O64 -> 7000 | Q64: =P64/12 -> 583.33333 | R64: =SCPR2020!AD64 -> 71.833566
A65: 42 | B65: Marina S. Caparoso | C65: 7000 | P65: =C65+D65+E65+F65+G65+H65+I65+J65+K65+L65+M65+N65+O65 -> 7000 | Q65: =P65/12 -> 583.33333 | R65: =SCPR2020!AD65 -> 71.833566
A66: 43 | B66: Merian C. Jumao-as | C66: 7000 | P66: =C66+D66+E66+F66+G66+H66+I66+J66+K66+L66+M66+N66+O66 -> 7000 | Q66: =P66/12 -> 583.33333 | R66: =SCPR2020!AD66 -> 71.833566
A67: 44 | B67: Christopher D. Bioco | C67: =2021.27+12.03 -> 2033.3 | P67: =C67+D67+E67+F67+G67+H67+I67+J67+K67+L67+M67+N67+O67 -> 2033.3 | Q67: =P67/12 -> 169.44167 | R67: =SCPR2020!AD67 -> 20.523876
A68: 45 | B68: Rahbie B. Jumao-as | C68: =3218+62.79 -> 3280.79 | P68: =C68+D68+E68+F68+G68+H68+I68+J68+K68+L68+M68+N68+O68 -> 3280.79 | Q68: =P68/12 -> 273.39917 | R68: =SCPR2020!AD68 -> 32.899773
A69: 46 | B69: Shalou J. Balao | C69: 7000 | P69: =C69+D69+E69+F69+G69+H69+I69+J69+K69+L69+M69+N69+O69 -> 7000 | Q69: =P69/12 -> 583.33333 | R69: =SCPR2020!AD69 -> 53.567317
A70: 47 | B70: Brice Vincent M. Jumao-as | C70: 550 | P70: =C70+D70+E70+F70+G70+H70+I70+J70+K70+L70+M70+N70+O70 -> 550 | Q70: =P70/12 -> 45.833333 | R70: =SCPR2020!AD70 -> 5.6440659
A71: 48 | B71: Agustin D. Bioco Jr. | C71: 800 | P71: =C71+D71+E71+F71+G71+H71+I71+J71+K71+L71+M71+N71+O71 -> 800 | Q71: =P71/12 -> 66.666667 | R71: =SCPR2020!AD71 -> 8.2095504
A72: 49 | B72: Jenelyn F. Jimenea | C72: =5520+32.85 -> 5552.85 | P72: =C72+D72+E72+F72+G72+H72+I72+J72+K72+L72+M72+N72+O72 -> 5552.85 | Q72: =P72/12 -> 462.7375 | R72: =SCPR2020!AD72 -> 58.903524
A73: 50 | B73: Elvin P. Manriquez | C73: 200 | P73: =C73+D73+E73+F73+G73+H73+I73+J73+K73+L73+M73+N73+O73 -> 200 | Q73: =P73/12 -> 16.666667 | R73: =SCPR2020!AD73 -> 2.0523876
A74: 51 | B74: Adelaida C. Manriquez | C74: 200 | P74: =C74+D74+E74+F74+G74+H74+I74+J74+K74+L74+M74+N74+O74 -> 200 | Q74: =P74/12 -> 16.666667 | R74: =SCPR2020!AD74 -> 2.0523876
A75: 52 | B75: Everth O. Acaso Jr. | C75: 1550 | P75: =C75+D75+E75+F75+G75+H75+I75+J75+K75+L75+M75+N75+O75 -> 1550 | Q75: =P75/12 -> 129.16667 | R75: =SCPR2020!AD75 -> 15.906004
A76: 53 | B76: Isidro C. Lusanta Jr. | C76: =2000+11.9 -> 2011.9 | P76: =C76+D76+E76+F76+G76+H76+I76+J76+K76+L76+M76+N76+O76 -> 2011.9 | Q76: =P76/12 -> 167.65833 | R76: =SCPR2020!AD76 -> 20.523876
A77: 54 | B77: Joselito L. Edullantes | C77: =1460+43.64 -> 1503.64 | P77: =C77+D77+E77+F77+G77+H77+I77+J77+K77+L77+M77+N77+O77 -> 1503.64 | Q77: =P77/12 -> 125.30333 | R77: =SCPR2020!AD77 -> 16.213862
A78: 55 | B78: Agusto S. Jimenea | C78: =1760+43.64 -> 1803.64 | P78: =C78+D78+E78+F78+G78+H78+I78+J78+K78+L78+M78+N78+O78 -> 1803.64 | Q78: =P78/12 -> 150.30333 | R78: =SCPR2020!AD78 -> 17.835248
P80: =SUM(P52:P79) -> 63834.8 | U80: Page 2 of 4
A83: SIDLAK CHRISTIAN CHILDREN FUND SAVINGS AND CREDIT COOPERATIVE
A84: CDA Registration No. 9520-1080000000036399 Dated: November 16, 2016
A85: P-2, Brgy. Linao, Ormoc City
A87: COMPUTATION OF SHARES AND PATRONAGE REFUND
A88: As of FY 2022
A90: Members | C90: From 2021 | D90: Jan | E90: Feb | F90: Mar | G90: Apr | H90: May | I90: Jun | J90: Jul | K90: Aug | L90: Sep | M90: Oct | N90: Nov | O90: Dec | P90: TSM | Q90: ASM | R90: IOSC | S90: Int. on Loans | T90: Patronage Refund | U90: Total (IOSC+PR) | V90: Signature
A93: 56 | B93: Hazel Q. Bulacan | C93: =2200.1+34.91 -> 2235.01 | P93: =C93+D93+E93+F93+G93+H93+I93+J93+K93+L93+M93+N93+O93 -> 2235.01 | Q93: =P93/12 -> 186.25083 | R93: =SCPR2020!AD93 -> 23.398245
A94: 57 | B94: Lloyd B. Bulacan | C94: =2122.33+12.63 -> 2134.96 | P94: =C94+D94+E94+F94+G94+H94+I94+J94+K94+L94+M94+N94+O94 -> 2134.96 | Q94: =P94/12 -> 177.91333 | R94: =SCPR2020!AD94 -> 21.779219
A95: 58 | B95: Junlyn J. Aquino | C95: =2465+14.67 -> 2479.67 | P95: =C95+D95+E95+F95+G95+H95+I95+J95+K95+L95+M95+N95+O95 -> 2479.67 | Q95: =P95/12 -> 206.63917 | R95: =SCPR2020!AD95 -> 26.814444
A96: 59 | B96: =[1]Membership!$B$71 -> Concepcion B. Cruz | C96: 7000 | P96: =C96+D96+E96+F96+G96+H96+I96+J96+K96+L96+M96+N96+O96 -> 7000 | Q96: =P96/12 -> 583.33333 | R96: =SCPR2020!AD96 -> 71.833566
A97: 60 | B97: =[1]Membership!$B$72 -> Leonardo B. Cruz | C97: =2435+14.49 -> 2449.49 | P97: =C97+D97+E97+F97+G97+H97+I97+J97+K97+L97+M97+N97+O97 -> 2449.49 | Q97: =P97/12 -> 204.12417 | R97: =SCPR2020!AD97 -> 25.89087
A98: 61 | B98: =[1]Membership!$B$73 -> Annalyn B. Cruz | C98: =2450.8+14.58 -> 2465.38 | P98: =C98+D98+E98+F98+G98+H98+I98+J98+K98+L98+M98+N98+O98 -> 2465.38 | Q98: =P98/12 -> 205.44833 | R98: =SCPR2020!AD98 -> 26.011961
A99: 62 | R99: =SCPR2020!AD99 -> 1.0261938
A100: 63 | B100: =[1]Membership!$B$75 -> Milben Rex P. Balao | C100: =3590+108.65 -> 3698.65 | P100: =C100+D100+E100+F100+G100+H100+I100+J100+K100+L100+M100+N100+O100 -> 3698.65 | Q100: =P100/12 -> 308.22083 | R100: =SCPR2020!AD100 -> 36.840358
A101: 64 | B101: Ramil Mirafuentes | C101: 100 | P101: =C101+D101+E101+F101+G101+H101+I101+J101+K101+L101+M101+N101+O101 -> 100 | Q101: =P101/12 -> 8.3333333 | R101: =SCPR2020!AD101 -> 0
A102: 65 | B102: Diosita J. Aquino | C102: =2715+16.16 -> 2731.16 | P102: =C102+D102+E102+F102+G102+H102+I102+J102+K102+L102+M102+N102+O102 -> 2731.16 | Q102: =P102/12 -> 227.59667 | R102: =SCPR2020!AD102 -> 25.295677
A103: 66 | B103: Perpetuo O. Gaelo | C103: 7000 | P103: =C103 -> 7000 | Q103: =P103/12 -> 583.33333 | R103: =SCPR2020!AD103 -> 71.833566
A104: 67 | B104: Marcial Raul S. Almacin | C104: =2261.81+13.46 -> 2275.27 | P104: =C104+D104+E104+F104+G104+H104+I104+J104+K104+L104+M104+N104+O104 -> 2275.27 | Q104: =P104/12 -> 189.60583 | R104: =SCPR2020!AD104 -> 23.210554
A105: 68 | B105: Alma P. Bola | C105: 220 | P105: =C105+D105+E105+F105+G105+H105+I105+J105+K105+L105+M105+N105+O105 -> 220 | Q105: =P105/12 -> 18.333333 | R105: =SCPR2020!AD105 -> 2.2576264
A106: 69 | B106: Joventino C. Larrosa | C106: 100 | P106: =C106+D106+E106+F106+G106+H106+I106+J106+K106+L106+M106+N106+O106 -> 100 | Q106: =P106/12 -> 8.3333333 | R106: =SCPR2020!AD106 -> 1.0261938
A107: 70 | B107: Kristine Joy Lusanta | C107: 100 | P107: =C107+D107+E107+F107+G107+H107+I107+J107+K107+L107+M107+N107+O107 -> 100 | Q107: =P107/12 -> 8.3333333 | R107: =SCPR2020!AD107 -> 1.0261938
A108: 71 | B108: Milagros M. Villamor | C108: 420 | P108: =C108+D108+E108+F108+G108+H108+I108+J108+K108+L108+M108+N108+O108 -> 420 | Q108: =P108/12 -> 35 | R108: =SCPR2020!AD108 -> 5.8287808
A109: 72 | B109: Salvador B. Villamor | C109: 340 | P109: =C109+D109+E109+F109+G109+H109+I109+J109+K109+L109+M109+N109+O109 -> 340 | Q109: =P109/12 -> 28.333333 | R109: =SCPR2020!AD109 -> 11.082893
A110: 73 | B110: Ranilfa L. Amarille | C110: 440 | P110: =C110+D110+E110+F110+G110+H110+I110+J110+K110+L110+M110+N110+O110 -> 440 | Q110: =P110/12 -> 36.666667 | R110: =SCPR2020!AD110 -> 7.6964535
A111: 74 | B111: Rustom Montes | C111: 520 | P111: =C111+D111+E111+F111+G111+H111+I111+J111+K111+L111+M111+N111+O111 -> 520 | Q111: =P111/12 -> 43.333333 | R111: =SCPR2020!AD111 -> 7.285976
A112: 75 | B112: Patricio Loyd Tellidua | C112: 7000 | P112: =C112+D112+E112+F112+G112+H112+I112+J112+K112+L112+M112+N112+O112 -> 7000 | Q112: =P112/12 -> 583.33333
A113: 76 | B113: Ariel Romero | C113: 200 | P113: =C113+D113+E113+F113+G113+H113+I113+J113+K113+L113+M113+N113+O113 -> 200 | Q113: =P113/12 -> 16.666667 | R113: =SCPR2020!AD113 -> 2.0523876
A114: 77 | B114: Edmundo Abrenillo | C114: 340 | P114: =C114+D114+E114+F114+G114+H114+I114+J114+K114+L114+M114+N114+O114 -> 340 | Q114: =P114/12 -> 28.333333 | R114: =SCPR2020!AD114 -> 3.4890589
A115: 78 | B115: Richard S. Arar | C115: 100 | P115: =C115+D115+E115+F115+G115+H115+I115+J115+K115+L115+M115+N115+O115 -> 100 | Q115: =P115/12 -> 8.3333333 | R115: =SCPR2020!AD115 -> 1.0261938
A116: 79 | B116: Tirso L. Cayanong | C116: =400+21.82 -> 421.82 | P116: =C116+D116+E116+F116+G116+H116+I116+J116+K116+L116+M116+N116+O116 -> 421.82 | Q116: =P116/12 -> 35.151667 | R116: =SCPR2020!AD116 -> 1.0261938
B117: Marie Angelie C. Mabag | C117: 100 | P117: =C117+D117+E117+F117+G117+H117+I117+J117+K117+L117+M117+N117+O117 -> 100 | Q117: =P117/12 -> 8.3333333 | R117: =SCPR2020!AD117 -> 1.0261938
...

Sheet SCPR2023
A2: SIDLAK CHRISTIAN CHILDREN FUND SAVINGS AND CREDIT COOPERATIVE
A3: CDA Registration No. 9520-1080000000036399 Dated: November 16, 2016
A4: P-2, Brgy. Linao, Ormoc City
A6: COMPUTATION OF SHARES AND PATRONAGE REFUND
A7: As of FY 2022
A9: Members | C9: From 2021 | D9: Jan | E9: Feb | G9: Mar | H9: Apr | I9: May | J9: Jun | K9: Jul | M9: Aug | N9: Sep | O9: Oct | P9: Nov | Q9: Dec | R9: TSM | S9: ASM | T9: IOSC | U9: Int. on Loans | V9: Patronage Refund | W9: Total (IOSC+PR) | X9: Signature
F10: withdrawal
A11: 1 | B11: Allen L. Gubalane | C11: =2154.73+13.01 -> 2167.74 | R11: =C11+D11+E11+G11+H11+I11+J11+K11+M11+N11+O11+P11+Q11 -> 2167.74 | S11: =R11/12 -> 180.645
A12: 2 | B12: April A. Hubahib | C12: 1300 | R12: =C12+D12+E12+G12+H12+I12+J12+K12+M12+N12+O12+P12+Q12 -> 1300 | S12: =R12/12 -> 108.33333
A13: 3 | B13: Arnold C. Gonzales | C13: =2238.34+13.51 -> 2251.85 | R13: =C13+D13+E13+G13+H13+I13+J13+K13+M13+N13+O13+P13+Q13 -> 2251.85 | S13: =R13/12 -> 187.65417
A14: 4 | B14: Elina Empimo | C14: 750 | R14: =C14+D14+E14+G14+H14+I14+J14+K14+M14+N14+O14+P14+Q14 -> 750 | S14: =R14/12 -> 62.5
A15: 5 | B15: Crisencia R. Ruiz | C15: 7000 | R15: =C15+D15+E15+G15+H15+I15+J15+K15+M15+N15+O15+P15+Q15 -> 7000 | S15: =R15/12 -> 583.33333
A16: 6 | B16: Dennis M. Tolibao | C16: 150 | R16: =C16+D16+E16+G16+H16+I16+J16+K16+M16+N16+O16+P16+Q16 -> 150 | S16: =R16/12 -> 12.5
A17: 7 | B17: Dexter B. Jumao-as | C17: 7000 | R17: =C17+D17+E17+G17+H17+I17+J17+K17+M17+N17+O17+P17+Q17 -> 7000 | S17: =R17/12 -> 583.33333
A18: 8 | B18: Dorotea Jumao-as | C18: 7000 | R18: =C18+D18+E18+G18+H18+I18+J18+K18+M18+N18+O18+P18+Q18 -> 7000 | S18: =R18/12 -> 583.33333
A19: 9 | B19: Edgardo P. Nodalo | C19: =2033.3+12.27 -> 2045.57 | R19: =C19+D19+E19+G19+H19+I19+J19+K19+M19+N19+O19+P19+Q19 -> 2045.57 | S19: =R19/12 -> 170.46417
A20: 10 | B20: Eloisa E. Williams | C20: =2744.95+16.57 -> 2761.52 | R20: =C20+D20+E20+G20+H20+I20+J20+K20+M20+N20+O20+P20+Q20 -> 2761.52 | S20: =R20/12 -> 230.12667
A21: 11 | B21: Emmanuel C. Orellano | C21: 700 | R21: =C21+D21+E21+G21+H21+I21+J21+K21+M21+N21+O21+P21+Q21 -> 700 | S21: =R21/12 -> 58.333333
A22: 12 | B22: Emmanuel S. Quilantang | C22: =2093.66+12.64 -> 2106.3 | R22: =C22+D22+E22+G22+H22+I22+J22+K22+M22+N22+O22+P22+Q22 -> 2106.3 | S22: =R22/12 -> 175.525
A23: 13 | B23: Erlinda E. Quilantang | C23: =2134.96+12.89 -> 2147.85 | R23: =C23+D23+E23+G23+H23+I23+J23+K23+M23+N23+O23+P23+Q23 -> 2147.85 | S23: =R23/12 -> 178.9875
A24: 14 | B24: Eunicelle S. Samson | C24: =5593.09+33.76 -> 5626.85 | R24: =C24+D24+E24+G24+H24+I24+J24+K24+M24+N24+O24+P24+Q24 -> 5626.85 | S24: =R24/12 -> 468.90417
A25: 15 | B25: Genelyn N. Ymas | C25: 150 | R25: =C25+D25+E25+G25+H25+I25+J25+K25+M25+N25+O25+P25+Q25 -> 150 | S25: =R25/12 -> 12.5
A26: 16 | B26: Junel A. Pagay | C26: 1200 | R26: =C26+D26+E26+G26+H26+I26+J26+K26+M26+N26+O26+P26+Q26 -> 1200 | S26: =R26/12 -> 100
A27: 17 | B27: Limuel P. Omega | C27: 200 | R27: =C27+D27+E27+G27+H27+I27+J27+K27+M27+N27+O27+P27+Q27 -> 200 | S27: =R27/12 -> 16.666667
A28: 18 | B28: Ma. Ella P. Solano | C28: =2420+14.4+14.7 -> 2449.1 | R28: =C28+D28+E28+G28+H28+I28+J28+K28+M28+N28+O28+P28+Q28 -> 2449.1 | S28: =R28/12 -> 204.09167
A29: 19 | B29: Maria Genia C. Seguido | C29: 7000 | R29: =C29+D29+E29+G29+H29+I29+J29+K29+M29+N29+O29+P29+Q29 -> 7000 | S29: =R29/12 -> 583.33333
A30: 20 | B30: Mario G. Bañez Jr. | C30: 1300 | R30: =C30+D30+E30+G30+H30+I30+J30+K30+M30+N30+O30+P30+Q30 -> 1300 | S30: =R30/12 -> 108.33333
A31: 21 | B31: Marissa B. Ligutan | C31: 750 | R31: =C31+D31+E31+G31+H31+I31+J31+K31+M31+N31+O31+P31+Q31 -> 750 | S31: =R31/12 -> 62.5
A32: 22 | B32: Maristela A. Mandras | C32: 1200 | R32: =C32+D32+E32+G32+H32+I32+J32+K32+M32+N32+O32+P32+Q32 -> 1200 | S32: =R32/12 -> 100
A33: 23 | B33: Mark Gil M. Catingub | C33: 100 | R33: =C33+D33+E33+G33+H33+I33+J33+K33+M33+N33+O33+P33+Q33 -> 100 | S33: =R33/12 -> 8.3333333
A34: 24 | B34: Mary Grace C. Perol | C34: =2020.96+12.2 -> 2033.16 | R34: =C34+D34+E34+G34+H34+I34+J34+K34+M34+N34+O34+P34+Q34 -> 2033.16 | S34: =R34/12 -> 169.43
A35: 25 | B35: Maricris Montemor | C35: 600 | R35: =C35+D35+E35+G35+H35+I35+J35+K35+M35+N35+O35+P35+Q35 -> 600 | S35: =R35/12 -> 50
A36: 26 | B36: Analyn Cabahug | C36: =2902.17+17.52 -> 2919.69 | R36: =C36+D36+E36+G36+H36+I36+J36+K36+M36+N36+O36+P36+Q36 -> 2919.69 | S36: =R36/12 -> 243.3075
A37: 27 | B37: Nenita S. Fay | C37: =2132.62+12.87 -> 2145.49 | R37: =C37+D37+E37+G37+H37+I37+J37+K37+M37+N37+O37+P37+Q37 -> 2145.49 | S37: =R37/12 -> 178.79083
A38: 28 | B38: Paul C. Espinosa | C38: =2683.92+16.2 -> 2700.12 | R38: =C38+D38+E38+G38+H38+I38+J38+K38+M38+N38+O38+P38+Q38 -> 2700.12 | S38: =R38/12 -> 225.01
R40: =SUM(R11:R39) -> 67755.24 | W40: Page 1 of 4
A42: SIDLAK CHRISTIAN CHILDREN FUND SAVINGS AND CREDIT COOPERATIVE
A43: CDA Registration No. 9520-1080000000036399 Dated: November 16, 2016
A44: P-2, Brgy. Linao, Ormoc City
A46: COMPUTATION OF SHARES AND PATRONAGE REFUND
A47: As of FY 2022
A49: Members | C49: From 2021 | D49: Jan | E49: Feb | G49: Mar | H49: Apr | I49: May | J49: Jun | K49: Jul | M49: Aug | N49: Sep | O49: Oct | P49: Nov | Q49: Dec | R49: TSM | S49: ASM | T49: IOSC | U49: Int. on Loans | V49: Patronage Refund | W49: Total (IOSC+PR) | X49: Signature
A52: 29 | B52: Raffy C. Banghet | C52: =2033.3+12.27 -> 2045.57 | R52: =C52+D52+E52+G52+H52+I52+J52+K52+M52+N52+O52+P52+Q52 -> 2045.57 | S52: =R52/12 -> 170.46417 | T52: =SCPR2020!AD52 -> 20.742147
A53: 30 | B53: Rexie N. Costan | C53: =2112.5+12.75 -> 2125.25 | R53: =C53+D53+E53+G53+H53+I53+J53+K53+M53+N53+O53+P53+Q53 -> 2125.25 | S53: =R53/12 -> 177.10417 | T53: =SCPR2020!AD53 -> 21.55007
A54: 31 | B54: Ricardo G. Amarille | C54: =2549.08+15.39 -> 2564.47 | N54: 200 | R54: =C54+D54+E54+G54+H54+I54+J54+K54+M54+N54+O54+P54+Q54 -> 2764.47 | S54: =R54/12 -> 230.3725 | T54: =SCPR2020!AD54 -> 26.906802
A55: 32 | B55: Rodina A. Alvarado | C55: =2591.02+15.64 -> 2606.66 | R55: =C55+D55+E55+G55+H55+I55+J55+K55+M55+N55+O55+P55+Q55 -> 2606.66 | S55: =R55/12 -> 217.22167 | T55: =SCPR2020!AD55 -> 28.363997
A56: 33 | B56: Rolando C. Miaga | C56: 1100 | R56: =C56+D56+E56+G56+H56+I56+J56+K56+M56+N56+O56+P56+Q56 -> 1100 | S56: =R56/12 -> 91.666667 | T56: =SCPR2020!AD56 -> 11.288132
A57: 34 | B57: Ronald P. Arcillas | C57: 1000 | R57: =C57+D57+E57+G57+H57+I57+J57+K57+M57+N57+O57+P57+Q57 -> 1000 | S57: =R57/12 -> 83.333333 | T57: =SCPR2020!AD57 -> 10.261938
A58: 35 | B58: Victoriana A. Entero | C58: 935.84 | R58: =C58+D58+E58+G58+H58+I58+J58+K58+M58+N58+O58+P58+Q58 -> 935.84 | S58: =R58/12 -> 77.986667 | T58: =SCPR2020!AD58 -> 10.465535
A59: 36 | B59: Jaime A. Cayetano Jr. | C59: 300 | R59: =C59+D59+E59+G59+H59+I59+J59+K59+M59+N59+O59+P59+Q59 -> 300 | S59: =R59/12 -> 25 | T59: =SCPR2020!AD59 -> 3.0785814
A60: 37 | B60: Archie G. Bañez | C60: 650 | R60: =C60+D60+E60+G60+H60+I60+J60+K60+M60+N60+O60+P60+Q60 -> 650 | S60: =R60/12 -> 54.166667 | T60: =SCPR2020!AD60 -> 6.6702597
A61: 38 | B61: Ronan O. Sacay | C61: 350 | R61: =C61+D61+E61+G61+H61+I61+J61+K61+M61+N61+O61+P61+Q61 -> 350 | S61: =R61/12 -> 29.166667 | T61: =SCPR2020!AD61 -> 3.5916783
A62: 39 | B62: Edwin P. Caliwan | C62: 150 | R62: =C62+D62+E62+G62+H62+I62+J62+K62+M62+N62+O62+P62+Q62 -> 150 | S62: =R62/12 -> 12.5 | T62: =SCPR2020!AD62 -> 1.5392907
A63: 40 | B63: Analyn A. Punay | C63: =2733.39+16.5 -> 2749.89 | R63: =C63+D63+E63+G63+H63+I63+J63+K63+M63+N63+O63+P63+Q63 -> 2749.89 | S63: =R63/12 -> 229.1575 | T63: =SCPR2020!AD63 -> 26.927325
A64: 41 | B64: Susana I. Punay | C64: 7000 | F64: 8821.14 | R64: =C64+D64+E64+G64+H64+I64+J64+K64+M64+N64+O64+P64+Q64 -> 7000 | S64: =R64/12 -> 583.33333 | T64: =SCPR2020!AD64 -> 71.833566
A65: 42 | B65: Marina S. Caparoso | C65: 7000 | R65: =C65+D65+E65+G65+H65+I65+J65+K65+M65+N65+O65+P65+Q65 -> 7000 | S65: =R65/12 -> 583.33333 | T65: =SCPR2020!AD65 -> 71.833566
A66: 43 | B66: Merian C. Jumao-as | C66: 7000 | R66: =C66+D66+E66+G66+H66+I66+J66+K66+M66+N66+O66+P66+Q66 -> 7000 | S66: =R66/12 -> 583.33333 | T66: =SCPR2020!AD66 -> 71.833566
A67: 44 | B67: Christopher D. Bioco | C67: =2033.3+12.27 -> 2045.57 | R67: =C67+D67+E67+G67+H67+I67+J67+K67+M67+N67+O67+P67+Q67 -> 2045.57 | S67: =R67/12 -> 170.46417 | T67: =SCPR2020!AD67 -> 20.523876
A68: 45 | B68: Rahbie B. Jumao-as | C68: =3340.79+135.71 -> 3476.5 | R68: =C68+D68+E68+G68+H68+I68+J68+K68+M68+N68+O68+P68+Q68 -> 3476.5 | S68: =R68/12 -> 289.70833 | T68: =SCPR2020!AD68 -> 32.899773
A69: 46 | B69: Shalou J. Balao | C69: 7000 | R69: =C69+D69+E69+G69+H69+I69+J69+K69+M69+N69+O69+P69+Q69 -> 7000 | S69: =R69/12 -> 583.33333 | T69: =SCPR2020!AD69 -> 53.567317
A70: 47 | B70: Brice Vincent M. Jumao-as | C70: 550 | R70: =C70+D70+E70+G70+H70+I70+J70+K70+M70+N70+O70+P70+Q70 -> 550 | S70: =R70/12 -> 45.833333 | T70: =SCPR2020!AD70 -> 5.6440659
A71: 48 | B71: Agustin D. Bioco Jr. | C71: 800 | R71: =C71+D71+E71+G71+H71+I71+J71+K71+M71+N71+O71+P71+Q71 -> 800 | S71: =R71/12 -> 66.666667 | T71: =SCPR2020!AD71 -> 8.2095504
A72: 49 | B72: Jenelyn F. Jimenea | C72: =5552.85+33.52 -> 5586.37 | R72: =C72+D72+E72+G72+H72+I72+J72+K72+M72+N72+O72+P72+Q72 -> 5586.37 | S72: =R72/12 -> 465.53083 | T72: =SCPR2020!AD72 -> 58.903524
A73: 50 | B73: Elvin P. Manriquez | C73: 200 | R73: =C73+D73+E73+G73+H73+I73+J73+K73+M73+N73+O73+P73+Q73 -> 200 | S73: =R73/12 -> 16.666667 | T73: =SCPR2020!AD73 -> 2.0523876
A74: 51 | B74: Adelaida C. Manriquez | C74: 200 | R74: =C74+D74+E74+G74+H74+I74+J74+K74+M74+N74+O74+P74+Q74 -> 200 | S74: =R74/12 -> 16.666667 | T74: =SCPR2020!AD74 -> 2.0523876
A75: 52 | B75: Everth O. Acaso Jr. | C75: 1550 | R75: =C75+D75+E75+G75+H75+I75+J75+K75+M75+N75+O75+P75+Q75 -> 1550 | S75: =R75/12 -> 129.16667 | T75: =SCPR2020!AD75 -> 15.906004
A76: 53 | B76: Isidro C. Lusanta Jr. | C76: =2011.9+12.14 -> 2024.04 | R76: =C76+D76+E76+G76+H76+I76+J76+K76+M76+N76+O76+P76+Q76 -> 2024.04 | S76: =R76/12 -> 168.67 | T76: =SCPR2020!AD76 -> 20.523876
A77: 54 | B77: Joselito L. Edullantes | C77: =1460+43.64 -> 1503.64 | R77: =C77+D77+E77+G77+H77+I77+J77+K77+M77+N77+O77+P77+Q77 -> 1503.64 | S77: =R77/12 -> 125.30333 | T77: =SCPR2020!AD77 -> 16.213862
A78: 55 | B78: Agusto S. Jimenea | C78: =1760+43.64 -> 1803.64 | R78: =C78+D78+E78+G78+H78+I78+J78+K78+M78+N78+O78+P78+Q78 -> 1803.64 | S78: =R78/12 -> 150.30333 | T78: =SCPR2020!AD78 -> 17.835248
R80: =SUM(R52:R79) -> 64517.44 | W80: Page 2 of 4
A83: SIDLAK CHRISTIAN CHILDREN FUND SAVINGS AND CREDIT COOPERATIVE
A84: CDA Registration No. 9520-1080000000036399 Dated: November 16, 2016
A85: P-2, Brgy. Linao, Ormoc City
A87: COMPUTATION OF SHARES AND PATRONAGE REFUND
A88: As of FY 2022
A90: Members | C90: From 2021 | D90: Jan | E90: Feb | G90: Mar | H90: Apr | I90: May | J90: Jun | K90: Jul | M90: Aug | N90: Sep | O90: Oct | P90: Nov | Q90: Dec | R90: TSM | S90: ASM | T90: IOSC | U90: Int. on Loans | V90: Patronage Refund | W90: Total (IOSC+PR) | X90: Signature
A93: 56 | B93: Hazel Q. Bulacan | C93: =2235.01+34.49 -> 2269.5 | R93: =C93+D93+E93+G93+H93+I93+J93+K93+M93+N93+O93+P93+Q93 -> 2269.5 | S93: =R93/12 -> 189.125 | T93: =SCPR2020!AD93 -> 23.398245
A94: 57 | B94: Lloyd B. Bulacan | C94: =2134.96+12.89 -> 2147.85 | R94: =C94+D94+E94+G94+H94+I94+J94+K94+M94+N94+O94+P94+Q94 -> 2147.85 | S94: =R94/12 -> 178.9875 | T94: =SCPR2020!AD94 -> 21.779219
A95: 58 | B95: Junlyn J. Aquino | C95: =2479.67+14.97 -> 2494.64 | R95: =C95+D95+E95+G95+H95+I95+J95+K95+M95+N95+O95+P95+Q95 -> 2494.64 | S95: =R95/12 -> 207.88667 | T95: =SCPR2020!AD95 -> 26.814444
A96: 59 | B96: =[1]Membership!$B$71 -> Concepcion B. Cruz | C96: 7000 | R96: =C96+D96+E96+G96+H96+I96+J96+K96+M96+N96+O96+P96+Q96 -> 7000 | S96: =R96/12 -> 583.33333 | T96: =SCPR2020!AD96 -> 71.833566
A97: 60 | B97: =[1]Membership!$B$72 -> Leonardo B. Cruz | C97: =2509.49+72.92 -> 2582.41 | R97: =C97+D97+E97+G97+H97+I97+J97+K97+M97+N97+O97+P97+Q97 -> 2582.41 | S97: =R97/12 -> 215.20083 | T97: =SCPR2020!AD97 -> 25.89087
A98: 61 | B98: =[1]Membership!$B$73 -> Annalyn B. Cruz | C98: =2465.38+14.88 -> 2480.26 | R98: =C98+D98+E98+G98+H98+I98+J98+K98+M98+N98+O98+P98+Q98 -> 2480.26 | S98: =R98/12 -> 206.68833 | T98: =SCPR2020!AD98 -> 26.011961
A99: 62 | B99: Rowena Tellidua | C99: 100 | J99: =500+500 -> 1000 | K99: 500 | O99: 1500 | R99: =C99+D99+E99+G99+H99+I99+J99+K99+M99+N99+O99+P99+Q99 -> 3100 | T99: =SCPR2020!AD99 -> 1.0261938
A100: 63 | B100: =[1]Membership!$B$75 -> Milben Rex P. Balao | C100: =3698.65+22.33 -> 3720.98 | K100: 1000 | R100: =C100+D100+E100+G100+H100+I100+J100+K100+M100+N100+O100+P100+Q100 -> 4720.98 | S100: =R100/12 -> 393.415 | T100: =SCPR2020!AD100 -> 36.840358
A101: 64 | B101: Ramil Mirafuentes | C101: 100 | R101: =C101+D101+E101+G101+H101+I101+J101+K101+M101+N101+O101+P101+Q101 -> 100 | S101: =R101/12 -> 8.3333333 | T101: =SCPR2020!AD101 -> 0
A102: 65 | B102: Diosita J. Aquino | C102: =2731.16+16.49 -> 2747.65 | R102: =C102+D102+E102+G102+H102+I102+J102+K102+M102+N102+O102+P102+Q102 -> 2747.65 | S102: =R102/12 -> 228.97083 | T102: =SCPR2020!AD102 -> 25.295677
A103: 66 | B103: Perpetuo O. Gaelo | C103: 7000 | R103: =C103 -> 7000 | S103: =R103/12 -> 583.33333 | T103: =SCPR2020!AD103 -> 71.833566
A104: 67 | B104: Marcial Raul S. Almacin | C104: =2275.27+13.73 -> 2289 | R104: =C104+D104+E104+G104+H104+I104+J104+K104+M104+N104+O104+P104+Q104 -> 2289 | S104: =R104/12 -> 190.75 | T104: =SCPR2020!AD104 -> 23.210554
A105: 68 | B105: Alma P. Bola | C105: 220 | R105: =C105+D105+E105+G105+H105+I105+J105+K105+M105+N105+O105+P105+Q105 -> 220 | S105: =R105/12 -> 18.333333 | T105: =SCPR2020!AD105 -> 2.2576264
A106: 69 | B106: Joventino C. Larrosa | C106: 100 | R106: =C106+D106+E106+G106+H106+I106+J106+K106+M106+N106+O106+P106+Q106 -> 100 | S106: =R106/12 -> 8.3333333 | T106: =SCPR2020!AD106 -> 1.0261938
A107: 70 | B107: Kristine Joy Lusanta | C107: 100 | R107: =C107+D107+E107+G107+H107+I107+J107+K107+M107+N107+O107+P107+Q107 -> 100 | S107: =R107/12 -> 8.3333333 | T107: =SCPR2020!AD107 -> 1.0261938
A108: 71 | B108: Milagros M. Villamor | C108: 420 | R108: =C108+D108+E108+G108+H108+I108+J108+K108+M108+N108+O108+P108+Q108 -> 420 | S108: =R108/12 -> 35 | T108: =SCPR2020!AD108 -> 5.8287808
A109: 72 | B109: Salvador B. Villamor | C109: 340 | R109: =C109+D109+E109+G109+H109+I109+J109+K109+M109+N109+O109+P109+Q109 -> 340 | S109: =R109/12 -> 28.333333 | T109: =SCPR2020!AD109 -> 11.082893
A110: 73 | B110: Ranilfa L. Amarille | C110: 440 | R110: =C110+D110+E110+G110+H110+I110+J110+K110+M110+N110+O110+P110+Q110 -> 440 | S110: =R110/12 -> 36.666667 | T110: =SCPR2020!AD110 -> 7.6964535
A111: 74 | B111: Rustom Montes | C111: 520 | R111: =C111+D111+E111+G111+H111+I111+J111+K111+M111+N111+O111+P111+Q111 -> 520 | S111: =R111/12 -> 43.333333 | T111: =SCPR2020!AD111 -> 7.285976
A112: 75 | B112: Patricio Loyd Tellidua | C112: 7000 | R112: =C112+D112+E112+G112+H112+I112+J112+K112+M112+N112+O112+P112+Q112 -> 7000 | S112: =R112/12 -> 583.33333
A113: 76 | B113: Ariel Romero | C113: 200 | R113: =C113+D113+E113+G113+H113+I113+J113+K113+M113+N113+O113+P113+Q113 -> 200 | S113: =R113/12 -> 16.666667 | T113: =SCPR2020!AD113 -> 2.0523876
A114: 77 | B114: Edmundo Abrenillo | C114: 340 | R114: =C114+D114+E114+G114+H114+I114+J114+K114+M114+N114+O114+P114+Q114 -> 340 | S114: =R114/12 -> 28.333333 | T114: =SCPR2020!AD114 -> 3.4890589
A115: 78 | B115: Richard S. Arar | C115: 100 | R115: =C115+D115+E115+G115+H115+I115+J115+K115+M115+N115+O115+P115+Q115 -> 100 | S115: =R115/12 -> 8.3333333 | T115: =SCPR2020!AD115 -> 1.0261938
A116: 79 | B116: Tirso L. Cayanong | C116: =541.82+184.87 -> 726.69 | R116: =C116+D116+E116+G116+H116+I116+J116+K116+M116+N116+O116+P116+Q116 -> 726.69 | S116: =R116/12 -> 60.5575 | T116: =SCPR2020!AD116 -> 1.0261938
...

Sheet SCPR2025
B2: SIDLAK CHRISTIAN CHILDREN FUND SAVINGS AND CREDIT COOPERATIVE
B3: CDA Registration No. 9520-1080000000036399 Dated: November 16, 2016
B4: P-2, Brgy. Linao, Ormoc City
B6: COMPUTATION OF SHARES AND PATRONAGE REFUND
B7: As of FY 2025
B9: Members | D9: Account No. | E9: From 2024 | F9: Jan | G9: Feb | H9: Mar | I9: Apr | J9: May | K9: Jun | L9: Jul | M9: Aug | N9: Sept | O9: Oct | P9: Nov | Q9: Dec | R9: TSM | S9: ASM | T9: IOSC | U9: Int. on Loans | V9: Patronage Refund | W9: Total (IOSC+PR) | X9: Signature
B12: 1 | C12: Allen L. Gubalane | D12: ='[2]2025'!$D$5 -> AN-16-0001 | E12: =2163.78+16.47+2.4 -> 2182.65 | R12: =E12+F12+G12+H12+I12+J12+K12+L12+M12+N12+O12+P12+Q12 -> 2182.65 | S12: =R12/12 -> 181.8875 | W12: =T12+V12 -> 0
B13: 2 | C13: April A. Hubahib | D13: ='[2]2025'!$D$6 -> AN-16-0002 | E13: 1300 | R13: =E13+F13+G13+H13+I13+J13+K13+L13+M13+N13+O13+P13+Q13 -> 1300 | S13: =R13/12 -> 108.33333 | W13: =T13+V13 -> 0
B14: 3 | C14: Arnold C. Gonzales | D14: ='[2]2025'!$D$7 -> AN-16-0003 | E14: =2247.74+17.11+2.49 -> 2267.34 | R14: =E14+F14+G14+H14+I14+J14+K14+L14+M14+N14+O14+P14+Q14 -> 2267.34 | S14: =R14/12 -> 188.945 | W14: =T14+V14 -> 0
B15: 4 | C15: Elina Empimo | D15: ='[2]2025'!$D$8 -> AN-16-0004 | E15: 750 | R15: =E15+F15+G15+H15+I15+J15+K15+L15+M15+N15+O15+P15+Q15 -> 750 | S15: =R15/12 -> 62.5 | W15: =T15+V15 -> 0
B16: 5 | C16: Crisencia R. Ruiz | D16: ='[2]2025'!$D$9 -> AN-16-0005 | E16: =7.75+7053.28 -> 7061.03 | R16: =E16+F16+G16+H16+I16+J16+K16+L16+M16+N16+O16+P16+Q16 -> 7061.03 | S16: =R16/12 -> 588.41917 | W16: =T16+V16 -> 0
B17: 6 | C17: Dennis M. Tolibao | D17: ='[2]2025'!$D$10 -> AN-16-0006 | E17: 150 | R17: =E17+F17+G17+H17+I17+J17+K17+L17+M17+N17+O17+P17+Q17 -> 150 | S17: =R17/12 -> 12.5 | W17: =T17+V17 -> 0
B18: 7 | C18: Dexter B. Jumao-as | D18: ='[2]2025'!$D$11 -> AN-16-0007 | E18: =7455.7+45.01 -> 7500.71 | R18: =E18+F18+G18+H18+I18+J18+K18+L18+M18+N18+O18+P18+Q18 -> 7500.71 | S18: =R18/12 -> 625.05917 | W18: =T18+V18 -> 0
B19: 8 | C19: Dorotea Jumao-as | D19: ='[2]2025'!$D$12 -> AN-16-0008 | E19: =8133.18+31.95 -> 8165.13 | F19: 0 | R19: =E19+F19+G19+H19+I19+J19+K19+L19+M19+N19+O19+P19+Q19 -> 8165.13 | S19: =R19/12 -> 680.4275 | W19: =T19+V19 -> 0
B20: 9 | C20: Edgardo P. Nodalo | D20: ='[2]2025'!$D$13 -> AN-16-0009 | E20: =15.54+2041.84+2.26 -> 2059.64 | R20: =E20+F20+G20+H20+I20+J20+K20+L20+M20+N20+O20+P20+Q20 -> 2059.64 | S20: =R20/12 -> 171.63667 | W20: =T20+V20 -> 0
B21: 10 | C21: Eloisa E. Williams | D21: ='[2]2025'!$D$14 -> AN-16-0010 | E21: =128.45+2756.48+3.17 -> 2888.1 | R21: =E21+F21+G21+H21+I21+J21+K21+L21+M21+N21+O21+P21+Q21 -> 2888.1 | S21: =R21/12 -> 240.675 | W21: =T21+V21 -> 0
B22: 11 | C22: Emmanuel C. Orellano | D22: ='[2]2025'!$D$15 -> AN-16-0011 | E22: 700 | R22: =E22+F22+G22+H22+I22+J22+K22+L22+M22+N22+O22+P22+Q22 -> 700 | S22: =R22/12 -> 58.333333 | W22: =T22+V22 -> 0
B23: 12 | C23: Emmanuel S. Quilantang | D23: ='[2]2025'!$D$16 -> AN-16-0012 | E23: =16+2102.46+2.33 -> 2120.79 | R23: =E23+F23+G23+H23+I23+J23+K23+L23+M23+N23+O23+P23+Q23 -> 2120.79 | S23: =R23/12 -> 176.7325 | W23: =T23+V23 -> 0
B24: 13 | C24: Erlinda E. Quilantang | D24: ='[2]2025'!$D$17 -> AN-16-0013 | E24: =16.32+2143.93+2.37 -> 2162.62 | R24: =E24+F24+G24+H24+I24+J24+K24+L24+M24+N24+O24+P24+Q24 -> 2162.62 | S24: =R24/12 -> 180.21833 | W24: =T24+V24 -> 0
B25: 14 | C25: Eunicelle S. Samson | D25: ='[2]2025'!$D$18 -> AN-16-0014 | E25: =42.75+5616.59+6.22 -> 5665.56 | R25: =E25+F25+G25+H25+I25+J25+K25+L25+M25+N25+O25+P25+Q25 -> 5665.56 | S25: =R25/12 -> 472.13 | W25: =T25+V25 -> 0
B26: 15 | C26: Genelyn N. Ymas | D26: ='[2]2025'!$D$19 -> AN-16-0015 | E26: 150 | R26: =E26+F26+G26+H26+I26+J26+K26+L26+M26+N26+O26+P26+Q26 -> 150 | S26: =R26/12 -> 12.5 | W26: =T26+V26 -> 0
B27: 16 | C27: Junel A. Pagay | D27: ='[2]2025'!$D$20 -> AN-16-0016 | E27: 1200 | R27: =E27+F27+G27+H27+I27+J27+K27+L27+M27+N27+O27+P27+Q27 -> 1200 | S27: =R27/12 -> 100 | W27: =T27+V27 -> 0
B28: 17 | C28: Limuel P. Omega | D28: ='[2]2025'!$D$21 -> AN-16-0017 | E28: 200 | R28: =E28+F28+G28+H28+I28+J28+K28+L28+M28+N28+O28+P28+Q28 -> 200 | S28: =R28/12 -> 16.666667 | W28: =T28+V28 -> 0
B29: 18 | C29: Ma. Ella P. Solano | D29: ='[2]2025'!$D$22 -> AN-16-0018 | E29: =18.61+2444.63+2.71 -> 2465.95 | R29: =E29+F29+G29+H29+I29+J29+K29+L29+M29+N29+O29+P29+Q29 -> 2465.95 | S29: =R29/12 -> 205.49583 | W29: =T29+V29 -> 0
B30: 19 | C30: Maria Genia C. Seguido | D30: ='[2]2025'!$D$23 -> AN-16-0019 | E30: =160.76+7000+12.51 -> 7173.27 | R30: =E30+F30+G30+H30+I30+J30+K30+L30+M30+N30+O30+P30+Q30 -> 7173.27 | S30: =R30/12 -> 597.7725 | W30: =T30+V30 -> 0
B31: 20 | C31: Mario G. Bañez Jr. | D31: ='[2]2025'!$D$24 -> AN-16-0020 | E31: 1300 | R31: =E31+F31+G31+H31+I31+J31+K31+L31+M31+N31+O31+P31+Q31 -> 1300 | S31: =R31/12 -> 108.33333 | W31: =T31+V31 -> 0
B32: 21 | C32: Marissa B. Ligutan | D32: ='[2]2025'!$D$25 -> AN-16-0021 | E32: 750 | R32: =E32+F32+G32+H32+I32+J32+K32+L32+M32+N32+O32+P32+Q32 -> 750 | S32: =R32/12 -> 62.5 | W32: =T32+V32 -> 0
B33: 22 | C33: Maristela A. Mandras | D33: ='[2]2025'!$D$26 -> AN-16-0022 | E33: 1200 | R33: =E33+F33+G33+H33+I33+J33+K33+L33+M33+N33+O33+P33+Q33 -> 1200 | S33: =R33/12 -> 100 | W33: =T33+V33 -> 0
B34: 23 | C34: Mark Gil M. Catingub | D34: ='[2]2025'!$D$27 -> AN-16-0023 | E34: 100 | R34: =E34+F34+G34+H34+I34+J34+K34+L34+M34+N34+O34+P34+Q34 -> 100 | S34: =R34/12 -> 8.3333333 | W34: =T34+V34 -> 0
B35: 24 | C35: Mary Grace C. Perol | D35: ='[2]2025'!$D$28 -> AN-16-0024 | E35: =15.45+2029.45+2.25 -> 2047.15 | R35: =E35+F35+G35+H35+I35+J35+K35+L35+M35+N35+O35+P35+Q35 -> 2047.15 | S35: =R35/12 -> 170.59583 | W35: =T35+V35 -> 0
B36: 25 | C36: Maricris Montemor | D36: ='[2]2025'!$D$29 -> AN-16-0025 | E36: 600 | R36: =E36+F36+G36+H36+I36+J36+K36+L36+M36+N36+O36+P36+Q36 -> 600 | S36: =R36/12 -> 50 | W36: =T36+V36 -> 0
B37: 26 | C37: Analyn Cabahug | D37: ='[2]2025'!$D$30 -> AN-16-0026 | E37: =22.18+2914.36+3.23 -> 2939.77 | R37: =E37+F37+G37+H37+I37+J37+K37+L37+M37+N37+O37+P37+Q37 -> 2939.77 | S37: =R37/12 -> 244.98083 | W37: =T37+V37 -> 0
B38: 27 | C38: Nenita S. Fay | D38: ='[2]2025'!$D$31 -> AN-16-0027 | E38: =16.3+2141.58+2.37 -> 2160.25 | R38: =E38+F38+G38+H38+I38+J38+K38+L38+M38+N38+O38+P38+Q38 -> 2160.25 | S38: =R38/12 -> 180.02083 | W38: =T38+V38 -> 0
B39: 28 | C39: Paul C. Espinosa | D39: ='[2]2025'!$D$32 -> AN-16-0028 | E39: =20.52+2695.2+2.98 -> 2718.7 | R39: =E39+F39+G39+H39+I39+J39+K39+L39+M39+N39+O39+P39+Q39 -> 2718.7 | S39: =R39/12 -> 226.55833 | W39: =T39+V39 -> 0
R41: =SUM(R12:R40) -> 69978.66
X42: Page 1 of 4
B44: SIDLAK CHRISTIAN CHILDREN FUND SAVINGS AND CREDIT COOPERATIVE
B45: CDA Registration No. 9520-1080000000036399 Dated: November 16, 2016
B46: P-2, Brgy. Linao, Ormoc City
B48: COMPUTATION OF SHARES AND PATRONAGE REFUND
B49: As of FY 2025
B51: Members | D51: Account No. | E51: From 2024 | F51: Jan | G51: Feb | H51: Mar | I51: Apr | J51: May | K51: Jun | L51: Jul | M51: Aug | N51: Sep | O51: Oct | P51: Nov | Q51: Dec | R51: TSM | S51: ASM | T51: IOSC | U51: Int. on Loans | V51: Patronage Refund | W51: Total (IOSC+PR) | X51: Signature
B54: 29 | C54: Raffy C. Banghet | D54: ='[2]2025'!$D$33 -> AN-16-0029 | E54: =15.54+2041.84+2.26 -> 2059.64 | R54: =E54+F54+G54+H54+I54+J54+K54+L54+M54+N54+O54+P54+Q54 -> 2059.64 | S54: =R54/12 -> 171.63667 | T54: 0 | W54: =T54+V54 -> 0
B55: 30 | C55: Rexie N. Costan | D55: ='[2]2025'!$D$34 -> AN-16-0030 | E55: =16.15+2121.38+2.35 -> 2139.88 | R55: =E55+F55+G55+H55+I55+J55+K55+L55+M55+N55+O55+P55+Q55 -> 2139.88 | S55: =R55/12 -> 178.32333 | T55: 0 | W55: =T55+V55 -> 0
B56: 31 | C56: Ricardo G. Amarille | D56: ='[2]2025'!$D$35 -> AN-16-0031 | E56: =126.96+2559.79+2.95 -> 2689.7 | R56: =E56+F56+G56+H56+I56+J56+K56+L56+M56+N56+O56+P56+Q56 -> 2689.7 | S56: =R56/12 -> 224.14167 | T56: 0 | W56: =T56+V56 -> 0
B57: 32 | C57: Rodina A. Alvarado | D57: ='[2]2025'!$D$36 -> AN-16-0032 | E57: =19.81+2601.91+2.88 -> 2624.6 | R57: =E57+F57+G57+H57+I57+J57+K57+L57+M57+N57+O57+P57+Q57 -> 2624.6 | S57: =R57/12 -> 218.71667 | T57: 0 | W57: =T57+V57 -> 0
B58: 33 | C58: Rolando C. Miaga | D58: ='[2]2025'!$D$37 -> AN-16-0033 | E58: 1100 | R58: =E58+F58+G58+H58+I58+J58+K58+L58+M58+N58+O58+P58+Q58 -> 1100 | S58: =R58/12 -> 91.666667 | T58: 0 | W58: =T58+V58 -> 0
B59: 34 | C59: Ronald P. Arcillas | D59: ='[2]2025'!$D$38 -> AN-16-0034 | E59: 1000 | R59: =E59+F59+G59+H59+I59+J59+K59+L59+M59+N59+O59+P59+Q59 -> 1000 | S59: =R59/12 -> 83.333333 | T59: 0 | W59: =T59+V59 -> 0
B60: 35 | C60: Victoriana A. Entero | D60: ='[2]2025'!$D$39 -> AN-16-0035 | E60: 935.84 | R60: =E60+F60+G60+H60+I60+J60+K60+L60+M60+N60+O60+P60+Q60 -> 935.84 | S60: =R60/12 -> 77.986667 | T60: 0 | W60: =T60+V60 -> 0
B61: 36 | C61: Jaime A. Cayetano Jr. | D61: ='[2]2025'!$D$40 -> AN-17-0036 | E61: 300 | R61: =E61+F61+G61+H61+I61+J61+K61+L61+M61+N61+O61+P61+Q61 -> 300 | S61: =R61/12 -> 25 | T61: 0 | W61: =T61+V61 -> 0
B62: 37 | C62: Archie G. Bañez | D62: ='[2]2025'!$D$41 -> AN-17-0037 | E62: 650 | R62: =E62+F62+G62+H62+I62+J62+K62+L62+M62+N62+O62+P62+Q62 -> 650 | S62: =R62/12 -> 54.166667 | T62: 0 | W62: =T62+V62 -> 0
B63: 38 | C63: Ronan O. Sacay | D63: ='[2]2025'!$D$42 -> AN-17-0038 | E63: 350 | R63: =E63+F63+G63+H63+I63+J63+K63+L63+M63+N63+O63+P63+Q63 -> 350 | S63: =R63/12 -> 29.166667 | T63: 0 | W63: =T63+V63 -> 0
B64: 39 | C64: Edwin P. Caliwan | D64: ='[2]2025'!$D$43 -> AN-17-0039 | E64: 150 | R64: =E64+F64+G64+H64+I64+J64+K64+L64+M64+N64+O64+P64+Q64 -> 150 | S64: =R64/12 -> 12.5 | T64: 0 | W64: =T64+V64 -> 0
B65: 40 | C65: ='[2]2025'!$X$44 -> Cort Wensley J. Balao | D65: ='[2]2025'!$D$44 -> AN-17-0040 | E65: =KIDDY2024!S10 -> 2844.9657 | R65: =E65+F65+G65+H65+I65+J65+K65+L65+M65+N65+O65+P65+Q65 -> 2844.9657 | S65: =R65/12 -> 237.08048 | T65: 0 | W65: =T65+V65 -> 0
B66: 41 | C66: =[3]CShare!$J$28 -> PURISIMO C. ABRENILLO | D66: ='[2]2025'!$D$45 -> AN-17-0041 | E66: =1439.75+10.79 -> 1450.54 | R66: =E66+F66+G66+H66+I66+J66+K66+L66+M66+N66+O66+P66+Q66 -> 1450.54 | S66: =R66/12 -> 120.87833 | T66: 0 | W66: =T66+V66 -> 0
B67: 42 | C67: Marina S. Caparoso | D67: ='[2]2025'!$D$46 -> AN-17-0042 | E67: =53.28+7000+7.75 -> 7061.03 | R67: =E67+F67+G67+H67+I67+J67+K67+L67+M67+N67+O67+P67+Q67 -> 7061.03 | S67: =R67/12 -> 588.41917 | T67: 0 | W67: =T67+V67 -> 0
B68: 43 | C68: Merian C. Jumao-as | D68: ='[2]2025'!$D$47 -> AN-17-0043 | E68: =53.28+7000+40.05 -> 7093.33 | R68: =E68+F68+G68+H68+I68+J68+K68+L68+M68+N68+O68+P68+Q68 -> 7093.33 | S68: =R68/12 -> 591.11083 | T68: 0 | W68: =T68+V68 -> 0
B69: 44 | C69: Christopher D. Bioco | D69: ='[2]2025'!$D$48 -> AN-17-0044 | E69: =15.54+2041.84+2.26 -> 2059.64 | R69: =E69+F69+G69+H69+I69+J69+K69+L69+M69+N69+O69+P69+Q69 -> 2059.64 | S69: =R69/12 -> 171.63667 | T69: 0 | W69: =T69+V69 -> 0
B70: 45 | C70: Rahbie B. Jumao-as | D70: ='[2]2025'!$D$49 -> AN-17-0045 | E70: =26.15+3435.28+3.8 -> 3465.23 | R70: =E70+F70+G70+H70+I70+J70+K70+L70+M70+N70+O70+P70+Q70 -> 3465.23 | S70: =R70/12 -> 288.76917 | T70: 0 | W70: =T70+V70 -> 0
B71: 46 | C71: Shalou J. Balao | D71: ='[2]2025'!$D$50 -> AN-17-0046 | E71: =160.76+7000+12.51 -> 7173.27 | R71: =E71+F71+G71+H71+I71+J71+K71+L71+M71+N71+O71+P71+Q71 -> 7173.27 | S71: =R71/12 -> 597.7725 | T71: 0 | W71: =T71+V71 -> 0
B72: 47 | C72: Brice Vincent M. Jumao-as | D72: ='[2]2025'!$D$51 -> AN-17-0047 | E72: 550 | R72: =E72+F72+G72+H72+I72+J72+K72+L72+M72+N72+O72+P72+Q72 -> 550 | S72: =R72/12 -> 45.833333 | T72: 0 | W72: =T72+V72 -> 0
B73: 48 | C73: Agustin D. Bioco Jr. | D73: ='[2]2025'!$D$52 -> AN-17-0048 | E73: 800 | R73: =E73+F73+G73+H73+I73+J73+K73+L73+M73+N73+O73+P73+Q73 -> 800 | S73: =R73/12 -> 66.666667 | T73: 0 | W73: =T73+V73 -> 0
B74: 49 | C74: Jenelyn F. Jimenea | D74: ='[2]2025'!$D$53 -> AN-17-0049 | E74: =42.44+5576.18+6.17 -> 5624.79 | R74: =E74+F74+G74+H74+I74+J74+K74+L74+M74+N74+O74+P74+Q74 -> 5624.79 | S74: =R74/12 -> 468.7325 | T74: 0 | W74: =T74+V74 -> 0
B75: 50 | C75: Elvin P. Manriquez | D75: ='[2]2025'!$D$54 -> AN-18-0050 | E75: 200 | R75: =E75+F75+G75+H75+I75+J75+K75+L75+M75+N75+O75+P75+Q75 -> 200 | S75: =R75/12 -> 16.666667 | T75: 0 | W75: =T75+V75 -> 0
B76: 51 | C76: Adelaida C. Manriquez | D76: ='[2]2025'!$D$55 -> AN-18-0051 | E76: 200 | R76: =E76+F76+G76+H76+I76+J76+K76+L76+M76+N76+O76+P76+Q76 -> 200 | S76: =R76/12 -> 16.666667 | T76: 0 | W76: =T76+V76 -> 0
B77: 52 | C77: Everth O. Acaso Jr. | D77: ='[2]2025'!$D$56 -> AN-18-0052 | E77: 1550 | R77: =E77+F77+G77+H77+I77+J77+K77+L77+M77+N77+O77+P77+Q77 -> 1550 | S77: =R77/12 -> 129.16667 | T77: 0 | W77: =T77+V77 -> 0
B78: 53 | C78: Isidro C. Lusanta Jr. | D78: ='[2]2025'!$D$57 -> AN-18-0053 | E78: =15.38+2020.35+2.24 -> 2037.97 | R78: =E78+F78+G78+H78+I78+J78+K78+L78+M78+N78+O78+P78+Q78 -> 2037.97 | S78: =R78/12 -> 169.83083 | T78: 0 | W78: =T78+V78 -> 0
B79: 54 | C79: CHECKY P. PEREZ | D79: ='[2]2025'!$D$58 -> AN-18-0054 | E79: 100 | H79: =200 -> 200 | J79: =1700+20 -> 1720 | R79: =E79+F79+G79+H79+I79+J79+K79+L79+M79+N79+O79+P79+Q79 -> 2020 | S79: =R79/12 -> 168.33333 | T79: 0 | U79: ='[4]2025loaners'!$H$6 -> 3000 | W79: =T79+V79 -> 0
B80: 55 | C80: ='[2]2025'!$X$59 -> Brett Colin J. Balao | D80: ='[2]2025'!$D$59 -> AN-18-0055 | E80: =KIDDY2024!S12 -> 2812.1906 | R80: =E80+F80+G80+H80+I80+J80+K80+L80+M80+N80+O80+P80+Q80 -> 2812.1906 | S80: =R80/12 -> 234.34922 | T80: 0 | W80: =T80+V80 -> 0
R82: =SUM(R54:R81) -> 60942.616
X83: Page 2 of 4
B85: SIDLAK CHRISTIAN CHILDREN FUND SAVINGS AND CREDIT COOPERATIVE
B86: CDA Registration No. 9520-1080000000036399 Dated: November 16, 2016
B87: P-2, Brgy. Linao, Ormoc City
B89: COMPUTATION OF SHARES AND PATRONAGE REFUND
B90: As of FY 2025
B92: Members | D92: Account No. | E92: From 2024 | F92: Jan | G92: Feb | H92: Mar | I92: Apr | J92: May | K92: Jun | L92: Jul | M92: Aug | N92: Sep | O92: Oct | P92: Nov | Q92: Dec | R92: TSM | S92: ASM | T92: IOSC | U92: Int. on Loans | V92: Patronage Refund | W92: Total (IOSC+PR) | X92: Signature
B95: 56 | C95: Hazel Q. Bulacan | D95: ='[2]2025'!$D$60 -> AN-18-0056 | E95: =17.08+2244.4+2.48 -> 2263.96 | R95: =E95+F95+G95+H95+I95+J95+K95+L95+M95+N95+O95+P95+Q95 -> 2263.96 | S95: =R95/12 -> 188.66333 | T95: 0 | W95: =T95+V95 -> 0
B96: 57 | C96: Lloyd B. Bulacan | D96: ='[2]2025'!$D$61 -> AN-18-0057 | E96: =16.32+2143.93+2.37 -> 2162.62 | R96: =E96+F96+G96+H96+I96+J96+K96+L96+M96+N96+O96+P96+Q96 -> 2162.62 | S96: =R96/12 -> 180.21833 | T96: 0 | W96: =T96+V96 -> 0
B97: 58 | C97: Junlyn J. Aquino | D97: ='[2]2025'!$D$62 -> AN-18-0058 | E97: =18.95+2490.09+2.76 -> 2511.8 | R97: =E97+F97+G97+H97+I97+J97+K97+L97+M97+N97+O97+P97+Q97 -> 2511.8 | S97: =R97/12 -> 209.31667 | T97: 0 | W97: =T97+V97 -> 0
B98: 59 | C98: =[1]Membership!$B$71 -> Concepcion B. Cruz | D98: ='[2]2025'!$D$63 -> AN-18-0059 | E98: =53.28+7000+7.75 -> 7061.03 | R98: =E98+F98+G98+H98+I98+J98+K98+L98+M98+N98+O98+P98+Q98 -> 7061.03 | S98: =R98/12 -> 588.41917 | T98: 0 | W98: =T98+V98 -> 0
B99: 60 | C99: =[1]Membership!$B$72 -> Leonardo B. Cruz | D99: ='[2]2025'!$D$64 -> AN-18-0060 | E99: =19.49+2560.26+2.83 -> 2582.58 | R99: =E99+F99+G99+H99+I99+J99+K99+L99+M99+N99+O99+P99+Q99 -> 2582.58 | S99: =R99/12 -> 215.215 | T99: 0 | W99: =T99+V99 -> 0
B100: 61 | C100: =[1]Membership!$B$73 -> Annalyn B. Cruz | D100: ='[2]2025'!$D$65 -> AN-18-0061 | E100: =18.84+2475.74+2.74 -> 2497.32 | R100: =E100+F100+G100+H100+I100+J100+K100+L100+M100+N100+O100+P100+Q100 -> 2497.32 | S100: =R100/12 -> 208.11 | T100: 0 | W100: =T100+V100 -> 0
B101: 62 | C101: ='[2]2025'!$X$66 -> ROWENA B. TELLIDUA | D101: ='[2]2025'!$D$66 -> AN-18-0062 | E101: 4100 | H101: 0 | L101: 500 | R101: =E101+F101+G101+H101+I101+J101+K101+L101+M101+N101+O101+P101+Q101 -> 4600 | S101: =R101/12 -> 383.33333 | T101: 0 | W101: =T101+V101 -> 0
B102: 63 | C102: =[1]Membership!$B$75 -> Milben Rex P. Balao | D102: ='[2]2025'!$D$67 -> AN-18-0063 | E102: =4790.07+10.79 -> 4800.86 | R102: =E102+F102+G102+H102+I102+J102+K102+L102+M102+N102+O102+P102+Q102 -> 4800.86 | S102: =R102/12 -> 400.07167 | T102: 0 | W102: =T102+V102 -> 0
B103: 64 | C103: Ramil Mirafuentes | D103: ='[2]2025'!$D$68 -> AN-18-0064 | E103: 100 | R103: =E103+F103+G103+H103+I103+J103+K103+L103+M103+N103+O103+P103+Q103 -> 100 | S103: =R103/12 -> 8.3333333 | T103: 0 | W103: =T103+V103 -> 0
B104: 65 | C104: Diosita J. Aquino | D104: ='[2]2025'!$D$69 -> AN-18-0065 | E104: =20.88+2742.63+3.04 -> 2766.55 | R104: =E104+F104+G104+H104+I104+J104+K104+L104+M104+N104+O104+P104+Q104 -> 2766.55 | S104: =R104/12 -> 230.54583 | T104: 0 | W104: =T104+V104 -> 0
B105: 66 | C105: Perpetuo O. Gaelo | D105: ='[2]2025'!$D$70 -> AN-18-0066 | E105: =7294.49+17.22 -> 7311.71 | Q105: =20 -> 20 | R105: =E105+F105+G105+H105+I105+J105+K105+L105+M105+N105+O105+P105+Q105 -> 7331.71 | S105: =R105/12 -> 610.97583 | T105: 0 | U105: ='[4]2025loaners'!$H$4 -> 900 | W105: =T105+V105 -> 0
B106: 67 | C106: Marcial Raul S. Almacin | D106: ='[2]2025'!$D$71 -> AN-18-0067 | E106: =17.39+2284.83+2.53 -> 2304.75 | R106: =E106+F106+G106+H106+I106+J106+K106+L106+M106+N106+O106+P106+Q106 -> 2304.75 | S106: =R106/12 -> 192.0625 | T106: 0 | W106: =T106+V106 -> 0
B107: 68 | C107: Alma P. Bola | D107: ='[2]2025'!$D$72 -> AN-18-0068 | E107: 220 | R107: =E107+F107+G107+H107+I107+J107+K107+L107+M107+N107+O107+P107+Q107 -> 220 | S107: =R107/12 -> 18.333333 | T107: 0 | W107: =T107+V107 -> 0
B108: 69 | C108: Joventino C. Larrosa | D108: ='[2]2025'!$D$73 -> AN-18-0069 | E108: 100 | R108: =E108+F108+G108+H108+I108+J108+K108+L108+M108+N108+O108+P108+Q108 -> 100 | S108: =R108/12 -> 8.3333333 | T108: 0 | W108: =T108+V108 -> 0
B109: 70 | C109: Kristine Joy Lusanta | D109: ='[2]2025'!$D$74 -> AN-19-0070 | E109: 100 | R109: =E109+F109+G109+H109+I109+J109+K109+L109+M109+N109+O109+P109+Q109 -> 100 | S109: =R109/12 -> 8.3333333 | T109: 0 | W109: =T109+V109 -> 0
B110: 71 | C110: Milagros M. Villamor | D110: ='[2]2025'!$D$75 -> AN-19-0071 | E110: 420 | R110: =E110+F110+G110+H110+I110+J110+K110+L110+M110+N110+O110+P110+Q110 -> 420 | S110: =R110/12 -> 35 | T110: 0 | W110: =T110+V110 -> 0
B111: 72 | C111: Salvador B. Villamor | D111: ='[2]2025'!$D$76 -> AN-19-0072 | E111: 340 | R111: =E111+F111+G111+H111+I111+J111+K111+L111+M111+N111+O111+P111+Q111 -> 340 | S111: =R111/12 -> 28.333333 | T111: 0 | W111: =T111+V111 -> 0
B112: 73 | C112: Ranilfa L. Amarille | D112: ='[2]2025'!$D$77 -> AN-19-0073 | E112: 440 | F112: 20 | K112: 20 | R112: =E112+F112+G112+H112+I112+J112+K112+L112+M112+N112+O112+P112+Q112 -> 480 | S112: =R112/12 -> 40 | T112: 0 | U112: ='[4]2025loaners'!$H$3+'[4]2025loaners'!$H$8 -> 800 | W112: =T112+V112 -> 0
B113: 74 | C113: Rustom Montes | D113: ='[2]2025'!$D$78 -> AN-19-0074 | E113: 520 | R113: =E113+F113+G113+H113+I113+J113+K113+L113+M113+N113+O113+P113+Q113 -> 520 | S113: =R113/12 -> 43.333333 | T113: 0 | W113: =T113+V113 -> 0
B114: 75 | C114: Patricio Loyd Tellidua | D114: ='[2]2025'!$D$79 -> AN-19-0075 | E114: =53.28+7000+7.75+500 -> 7561.03 | R114: =E114+F114+G114+H114+I114+J114+K114+L114+M114+N114+O114+P114+Q114 -> 7561.03 | S114: =R114/12 -> 630.08583 | T114: 0 | W114: =T114+V114 -> 0
B115: 76 | C115: Ariel Romero | D115: ='[2]2025'!$D$80 -> AN-20-0076 | E115: 200 | R115: =E115+F115+G115+H115+I115+J115+K115+L115+M115+N115+O115+P115+Q115 -> 200 | S115: =R115/12 -> 16.666667 | T115: 0 | W115: =T115+V115 -> 0
B116: 77 | C116: Edmundo Abrenillo | D116: ='[2]2025'!$D$81 -> AN-20-0077 | E116: 340 | R116: =E116+F116+G116+H116+I116+J116+K116+L116+M116+N116+O116+P116+Q116 -> 340 | S116: =R116/12 -> 28.333333 | T116: 0 | W116: =T116+V116 -> 0
B117: 78 | C117: Richard S. Arar | D117: ='[2]2025'!$D$82 -> AN-20-0078 | E117: 100 | R117: =E117+F117+G117+H117+I117+J117+K117+L117+M117+N117+O117+P117+Q117 -> 100 | S117: =R117/12 -> 8.3333333 | T117: 0 | W117: =T117+V117 -> 0
...

Sheet kiddy2020
A2: SIDLAK CHRISTIAN CHILDREN FUND SAVINGS AND CREDIT COOPERATIVE
A3: CDA Registration No. 9520-1080000000036399 Dated: November 16, 2016
A4: P-2, Brgy. Linao, Ormoc City
A6: COMPUTATION OF SAVINGS DEPOSITS
A7: As of FY 2020
A9: Members | C9: 2019 Savings | D9: Jan | E9: Feb | F9: Mar | G9: Apr | H9: May | I9: Jun | J9: Jul | K9: Aug | L9: Sep | M9: Oct | N9: Nov | O9: Dec | P9: TSAD | Q9: ASAD | R9: Int. on TSAD | S9: Total (SAD + Interest)
A10: 1 | B10: Cort Wensley J. Balao | C10: =1075+64.5 -> 1139.5 | D10: 160 | O10: 300 | P10: =C10+D10+E10+F10+G10+H10+I10+J10+K10+L10+M10+N10+O10 -> 1599.5 | Q10: =P10/12 -> 133.29167 | R10: =D11+E11+F11+G11+H11+I11+J11+K11+L11+M11+N11+O11 -> 79.47 | S10: =P10+R10 -> 1678.97
C11: Interest per mo. | D11: =(C10+D10)*0.005 -> 6.4975 | E11: =(C10+D10+E10)*0.005 -> 6.4975 | F11: =(+C10+D10+E10+F10)*0.005 -> 6.4975 | G11: =(C10+D10+E10+F10+G10)*0.005 -> 6.4975 | H11: =(C10+D10+E10+F10+G10+H10)*0.005 -> 6.4975 | I11: =(C10+D10+E10+F10+G10+H10+I10)*0.005 -> 6.4975 | J11: =(C10+D10+E10+F10+G10+H10+I10+J10)*0.005 -> 6.4975 | K11: =(C10+D10+E10+F10+G10+H10+I10+J10+K10)*0.005 -> 6.4975 | L11: =(C10+D10+E10+F10+G10+H10+I10+J10+K10+L10)*0.005 -> 6.4975 | M11: =(C10+D10+E10+F10+G10+H10+I10+J10+K10+L10+M10)*0.005 -> 6.4975 | N11: =(C10+D10+E10+F10+G10+H10+I10+J10+K10+L10+M10+N10)*0.005 -> 6.4975 | O11: =(C10+D10+E10+F10+G10+H10+I10+J10+K10+L10+M10+N10+O10)*0.005 -> 7.9975
A12: 2 | B12: Brett Colin J. Balao | C12: =1100+66 -> 1166 | D12: 70 | N12: 545 | O12: 300 | P12: =C12+D12+E12+F12+G12+H12+I12+J12+K12+L12+M12+N12+O12 -> 2081 | Q12: =P12/12 -> 173.41667 | R12: =D13+E13+F13+G13+H13+I13+J13+K13+L13+M13+N13+O13 -> 81.11 | S12: =P12+R12 -> 2162.11
C13: Interest per mo. | D13: =(C12+D12)*0.005 -> 6.18 | E13: =(C12+D12+E12)*0.005 -> 6.18 | F13: =(+C12+D12+E12+F12)*0.005 -> 6.18 | G13: =(C12+D12+E12+F12+G12)*0.005 -> 6.18 | H13: =(C12+D12+E12+F12+G12+H12)*0.005 -> 6.18 | I13: =(C12+D12+E12+F12+G12+H12+I12)*0.005 -> 6.18 | J13: =(C12+D12+E12+F12+G12+H12+I12+J12)*0.005 -> 6.18 | K13: =(C12+D12+E12+F12+G12+H12+I12+J12+K12)*0.005 -> 6.18 | L13: =(C12+D12+E12+F12+G12+H12+I12+J12+K12+L12)*0.005 -> 6.18 | M13: =(C12+D12+E12+F12+G12+H12+I12+J12+K12+L12+M12)*0.005 -> 6.18 | N13: =(C12+D12+E12+F12+G12+H12+I12+J12+K12+L12+M12+N12)*0.005 -> 8.905 | O13: =(C12+D12+E12+F12+G12+H12+I12+J12+K12+L12+M12+N12+O12)*0.005 -> 10.405
A14: 3 | B14: Demian Sabin C. Jumao-as | C14: =2400+144 -> 2544 | D14: 200 | E14: 340 | I14: 1000 | N14: 700 | P14: =C14+D14+E14+F14+G14+H14+I14+J14+K14+L14+M14+N14+O14 -> 4784 | Q14: =P14/12 -> 398.66667 | R14: =D15+E15+F15+G15+H15+I15+J15+K15+L15+M15+N15+O15 -> 225.34 | S14: =P14+R14 -> 5009.34
C15: Interest per mo. | D15: =(C14+D14)*0.005 -> 13.72 | E15: =(C14+D14+E14)*0.005 -> 15.42 | F15: =(+C14+D14+E14+F14)*0.005 -> 15.42 | G15: =(C14+D14+E14+F14+G14)*0.005 -> 15.42 | H15: =(C14+D14+E14+F14+G14+H14)*0.005 -> 15.42 | I15: =(C14+D14+E14+F14+G14+H14+I14)*0.005 -> 20.42 | J15: =(C14+D14+E14+F14+G14+H14+I14+J14)*0.005 -> 20.42 | K15: =(C14+D14+E14+F14+G14+H14+I14+J14+K14)*0.005 -> 20.42 | L15: =(C14+D14+E14+F14+G14+H14+I14+J14+K14+L14)*0.005 -> 20.42 | M15: =(C14+D14+E14+F14+G14+H14+I14+J14+K14+L14+M14)*0.005 -> 20.42 | N15: =(C14+D14+E14+F14+G14+H14+I14+J14+K14+L14+M14+N14)*0.005 -> 23.92 | O15: =(C14+D14+E14+F14+G14+H14+I14+J14+K14+L14+M14+N14+O14)*0.005 -> 23.92
A16: 4 | B16: Izy Kaizer J. Balao | C16: =1688+101.28 -> 1789.28 | D16: 280 | E16: 0 | F16: 0 | G16: 0 | H16: 0 | J16: 0 | K16: 0 | L16: 0 | M16: 0 | N16: 0 | O16: 600 | P16: =C16+D16+E16+F16+G16+H16+I16+J16+K16+L16+M16+N16+O16 -> 2669.28 | Q16: =P16/12 -> 222.44 | R16: =D17+E17+F17+G17+H17+I17+J17+K17+L17+M17+N17+O17 -> 127.1568 | S16: =P16+R16 -> 2796.4368
C17: Interest per mo. | D17: =(C16+D16)*0.005 -> 10.3464 | E17: =(C16+D16+E16)*0.005 -> 10.3464 | F17: =(+C16+D16+E16+F16)*0.005 -> 10.3464 | G17: =(C16+D16+E16+F16+G16)*0.005 -> 10.3464 | H17: =(C16+D16+E16+F16+G16+H16)*0.005 -> 10.3464 | I17: =(C16+D16+E16+F16+G16+H16+I16)*0.005 -> 10.3464 | J17: =(C16+D16+E16+F16+G16+H16+I16+J16)*0.005 -> 10.3464 | K17: =(C16+D16+E16+F16+G16+H16+I16+J16+K16)*0.005 -> 10.3464 | L17: =(C16+D16+E16+F16+G16+H16+I16+J16+K16+L16)*0.005 -> 10.3464 | M17: =(C16+D16+E16+F16+G16+H16+I16+J16+K16+L16+M16)*0.005 -> 10.3464 | N17: =(C16+D16+E16+F16+G16+H16+I16+J16+K16+L16+M16+N16)*0.005 -> 10.3464 | O17: =(C16+D16+E16+F16+G16+H16+I16+J16+K16+L16+M16+N16+O16)*0.005 -> 13.3464
A18: 5 | B18: Alerc Finlay J. Balao | C18: =1583+94.98 -> 1677.98 | D18: 238 | E18: 60 | F18: 0 | G18: 0 | I18: 0 | J18: 0 | K18: 0 | N18: 0 | P18: =C18+D18+E18+F18+G18+H18+I18+J18+K18+L18+M18+N18+O18 -> 1975.98 | Q18: =P18/12 -> 164.665 | R18: =D19+E19+F19+G19+H19+I19+J19+K19+L19+M19+N19+O19 -> 118.2588 | S18: =P18+R18 -> 2094.2388
C19: Interest per mo. | D19: =(C18+D18)*0.005 -> 9.5799 | E19: =(C18+D18+E18)*0.005 -> 9.8799 | F19: =(+C18+D18+E18+F18)*0.005 -> 9.8799 | G19: =(C18+D18+E18+F18+G18)*0.005 -> 9.8799 | H19: =(C18+D18+E18+F18+G18+H18)*0.005 -> 9.8799 | I19: =(C18+D18+E18+F18+G18+H18+I18)*0.005 -> 9.8799 | J19: =(C18+D18+E18+F18+G18+H18+I18+J18)*0.005 -> 9.8799 | K19: =(C18+D18+E18+F18+G18+H18+I18+J18+K18)*0.005 -> 9.8799 | L19: =(C18+D18+E18+F18+G18+H18+I18+J18+K18+L18)*0.005 -> 9.8799 | M19: =(C18+D18+E18+F18+G18+H18+I18+J18+K18+L18+M18)*0.005 -> 9.8799 | N19: =(C18+D18+E18+F18+G18+H18+I18+J18+K18+L18+M18+N18)*0.005 -> 9.8799 | O19: =(C18+D18+E18+F18+G18+H18+I18+J18+K18+L18+M18+N18+O18)*0.005 -> 9.8799
A20: 6 | B20: Georgette Ann Cabahug | C20: 50 | P20: 50 | Q20: =P20/12 -> 4.1666667 | S20: =P20+R20 -> 50
C21: Interest per mo. | D21: =(C20+D20)*0.005 -> 0.25 | E21: =(C20+D20+E20)*0.005 -> 0.25 | F21: =(+C20+D20+E20+F20)*0.005 -> 0.25 | G21: =(C20+D20+E20+F20+G20)*0.005 -> 0.25 | H21: =(C20+D20+E20+F20+G20+H20)*0.005 -> 0.25 | I21: =(C20+D20+E20+F20+G20+H20+I20)*0.005 -> 0.25 | J21: =(C20+D20+E20+F20+G20+H20+I20+J20)*0.005 -> 0.25 | K21: =(C20+D20+E20+F20+G20+H20+I20+J20+K20)*0.005 -> 0.25 | L21: =(C20+D20+E20+F20+G20+H20+I20+J20+K20+L20)*0.005 -> 0.25 | M21: =(C20+D20+E20+F20+G20+H20+I20+J20+K20+L20+M20)*0.005 -> 0.25 | N21: =(C20+D20+E20+F20+G20+H20+I20+J20+K20+L20+M20+N20)*0.005 -> 0.25 | O21: =(C20+D20+E20+F20+G20+H20+I20+J20+K20+L20+M20+N20+O20)*0.005 -> 0.25
A22: 7 | B22: Luna Mikaela C. Apay | C22: 50 | P22: =C22+D22+E22+F22+G22+H22+I22+J22+K22+L22+M22+N22+O22 -> 50 | Q22: =P22/12 -> 4.1666667 | S22: =P22+R22 -> 50
C23: Interest per mo. | D23: =(C22+D22)*0.005 -> 0.25 | E23: =(C22+D22+E22)*0.005 -> 0.25 | F23: =(+C22+D22+E22+F22)*0.005 -> 0.25 | G23: =(C22+D22+E22+F22+G22)*0.005 -> 0.25 | H23: =(C22+D22+E22+F22+G22+H22)*0.005 -> 0.25 | I23: =(C22+D22+E22+F22+G22+H22+I22)*0.005 -> 0.25 | J23: =(C22+D22+E22+F22+G22+H22+I22+J22)*0.005 -> 0.25 | K23: =(C22+D22+E22+F22+G22+H22+I22+J22+K22)*0.005 -> 0.25 | L23: =(C22+D22+E22+F22+G22+H22+I22+J22+K22+L22)*0.005 -> 0.25 | M23: =(C22+D22+E22+F22+G22+H22+I22+J22+K22+L22+M22)*0.005 -> 0.25 | N23: =(C22+D22+E22+F22+G22+H22+I22+J22+K22+L22+M22+N22)*0.005 -> 0.25 | O23: =(C22+D22+E22+F22+G22+H22+I22+J22+K22+L22+M22+N22+O22)*0.005 -> 0.25
A24: 8 | B24: Mikko Angelo C. Apay | C24: 50 | P24: =C24+D24+E24+F24+G24+H24+I24+J24+K24+L24+M24+N24+O24 -> 50 | Q24: =P24/12 -> 4.1666667 | S24: =P24+R24 -> 50
C25: Interest per mo. | D25: =(C24+D24)*0.005 -> 0.25 | E25: =(C24+D24+E24)*0.005 -> 0.25 | F25: =(+C24+D24+E24+F24)*0.005 -> 0.25 | G25: =(C24+D24+E24+F24+G24)*0.005 -> 0.25 | H25: =(C24+D24+E24+F24+G24+H24)*0.005 -> 0.25 | I25: =(C24+D24+E24+F24+G24+H24+I24)*0.005 -> 0.25 | J25: =(C24+D24+E24+F24+G24+H24+I24+J24)*0.005 -> 0.25 | K25: =(C24+D24+E24+F24+G24+H24+I24+J24+K24)*0.005 -> 0.25 | L25: =(C24+D24+E24+F24+G24+H24+I24+J24+K24+L24)*0.005 -> 0.25 | M25: =(C24+D24+E24+F24+G24+H24+I24+J24+K24+L24+M24)*0.005 -> 0.25 | N25: =(C24+D24+E24+F24+G24+H24+I24+J24+K24+L24+M24+N24)*0.005 -> 0.25 | O25: =(C24+D24+E24+F24+G24+H24+I24+J24+K24+L24+M24+N24+O24)*0.005 -> 0.25
A26: 9 | B26: Casy Marie D. Cruz | C26: 250 | I26: 0 | K26: =100+150 -> 250 | N26: 50 | P26: =C26+D26+E26+F26+G26+H26+I26+J26+K26+L26+M26+N26+O26 -> 550 | Q26: =P26/12 -> 45.833333 | R26: =D27+E27+F27+G27+H27+I27+J27+K27+L27+M27+N27+O27 -> 13 | S26: =P26+R26 -> 563
C27: Interest per mo. | K27: =(C26+D26+E26+F26+G26+H26+I26+J26+K26)*0.005 -> 2.5 | L27: =(C26+D26+E26+F26+G26+H26+I26+J26+K26+L26)*0.005 -> 2.5 | M27: =(C26+D26+E26+F26+G26+H26+I26+J26+K26+L26+M26)*0.005 -> 2.5 | N27: =(C26+D26+E26+F26+G26+H26+I26+J26+K26+L26+M26+N26)*0.005 -> 2.75 | O27: =(C26+D26+E26+F26+G26+H26+I26+J26+K26+L26+M26+N26+O26)*0.005 -> 2.75
A28: 10 | B28: Marissa alvarado | C28: 50 | J28: 0 | M28: 0 | P28: =C28+D28+E28+F28+G28+H28+I28+J28+K28+L28+M28+N28+O28 -> 50 | Q28: =P28/12 -> 4.1666667 | S28: =P28+R28 -> 50
C29: Interest per mo. | D29: =(C28+D28)*0.005 -> 0.25 | E29: =(C28+D28+E28)*0.005 -> 0.25 | F29: =(+C28+D28+E28+F28)*0.005 -> 0.25 | G29: =(C28+D28+E28+F28+G28)*0.005 -> 0.25 | H29: =(C28+D28+E28+F28+G28+H28)*0.005 -> 0.25 | I29: =(C28+D28+E28+F28+G28+H28+I28)*0.005 -> 0.25 | J29: =(C28+D28+E28+F28+G28+H28+I28+J28)*0.005 -> 0.25 | K29: =(C28+D28+E28+F28+G28+H28+I28+J28+K28)*0.005 -> 0.25 | L29: =(C28+D28+E28+F28+G28+H28+I28+J28+K28+L28)*0.005 -> 0.25 | M29: =(C28+D28+E28+F28+G28+H28+I28+J28+K28+L28+M28)*0.005 -> 0.25 | N29: =(C28+D28+E28+F28+G28+H28+I28+J28+K28+L28+M28+N28)*0.005 -> 0.25 | O29: =(C28+D28+E28+F28+G28+H28+I28+J28+K28+L28+M28+N28+O28)*0.005 -> 0.25
A30: 11 | B30: Krissel Alvarado | C30: 50 | D30: 0 | P30: =C30+D30+E30+F30+G30+H30+I30+J30+K30+L30+M30+N30+O30 -> 50 | Q30: =P30/12 -> 4.1666667 | S30: =P30+R30 -> 50
C31: Interest per mo. | D31: =(C30+D30)*0.005 -> 0.25 | E31: =(C30+D30+E30)*0.005 -> 0.25 | F31: =(+C30+D30+E30+F30)*0.005 -> 0.25 | G31: =(C30+D30+E30+F30+G30)*0.005 -> 0.25 | H31: =(C30+D30+E30+F30+G30+H30)*0.005 -> 0.25 | I31: =(C30+D30+E30+F30+G30+H30+I30)*0.005 -> 0.25 | J31: =(C30+D30+E30+F30+G30+H30+I30+J30)*0.005 -> 0.25 | K31: =(C30+D30+E30+F30+G30+H30+I30+J30+K30)*0.005 -> 0.25 | L31: =(C30+D30+E30+F30+G30+H30+I30+J30+K30+L30)*0.005 -> 0.25 | M31: =(C30+D30+E30+F30+G30+H30+I30+J30+K30+L30+M30)*0.005 -> 0.25 | N31: =(C30+D30+E30+F30+G30+H30+I30+J30+K30+L30+M30+N30)*0.005 -> 0.25 | O31: =(C30+D30+E30+F30+G30+H30+I30+J30+K30+L30+M30+N30+O30)*0.005 -> 0.25
A32: 12 | B32: Serg Mateo M. Villamor | C32: 450 | D32: 0 | E32: 500 | F32: 500 | J32: 300 | K32: 300 | L32: 0 | M32: 347 | N32: 300 | P32: =C32+D32+E32+F32+G32+H32+I32+J32+K32+L32+M32+N32+O32 -> 2697 | Q32: =P32/12 -> 224.75 | R32: =D33+E33+F33+G33+H33+I33+J33+K33+L33+M33+N33+O33 -> 101.955 | S32: =P32+R32 -> 2798.955
C33: Interest per mo. | E33: =(C32+D32+E32)*0.005 -> 4.75 | F33: =(+C32+D32+E32+F32)*0.005 -> 7.25 | G33: =(C32+D32+E32+F32+G32)*0.005 -> 7.25 | H33: =(C32+D32+E32+F32+G32+H32)*0.005 -> 7.25 | I33: =(C32+D32+E32+F32+G32+H32+I32)*0.005 -> 7.25 | J33: =(C32+D32+E32+F32+G32+H32+I32+J32)*0.005 -> 8.75 | K33: =(C32+D32+E32+F32+G32+H32+I32+J32+K32)*0.005 -> 10.25 | L33: =(C32+D32+E32+F32+G32+H32+I32+J32+K32+L32)*0.005 -> 10.25 | M33: =(C32+D32+E32+F32+G32+H32+I32+J32+K32+L32+M32)*0.005 -> 11.985 | N33: =(C32+D32+E32+F32+G32+H32+I32+J32+K32+L32+M32+N32)*0.005 -> 13.485 | O33: =(C32+D32+E32+F32+G32+H32+I32+J32+K32+L32+M32+N32+O32)*0.005 -> 13.485
A34: 13 | B34: Rica M. Cruz | C34: 200 | D34: 0 | E34: 0 | F34: 0 | L34: 0 | P34: =C34+D34+E34+F34+G34+H34+I34+J34+K34+L34+M34+N34+O34 -> 200 | Q34: =P34/12 -> 16.666667 | S34: =P34+R34 -> 200
C35: Interest per mo. | D35: =(C34+D34)*0.005 -> 1 | E35: =(C34+D34+E34)*0.005 -> 1 | F35: =(+C34+D34+E34+F34)*0.005 -> 1 | G35: =(C34+D34+E34+F34+G34)*0.005 -> 1 | H35: =(C34+D34+E34+F34+G34+H34)*0.005 -> 1 | I35: =(C34+D34+E34+F34+G34+H34+I34)*0.005 -> 1 | J35: =(C34+D34+E34+F34+G34+H34+I34+J34)*0.005 -> 1 | K35: =(C34+D34+E34+F34+G34+H34+I34+J34+K34)*0.005 -> 1 | L35: =(C34+D34+E34+F34+G34+H34+I34+J34+K34+L34)*0.005 -> 1 | M35: =(C34+D34+E34+F34+G34+H34+I34+J34+K34+L34+M34)*0.005 -> 1 | N35: =(C34+D34+E34+F34+G34+H34+I34+J34+K34+L34+M34+N34)*0.005 -> 1 | O35: =(C34+D34+E34+F34+G34+H34+I34+J34+K34+L34+M34+N34+O34)*0.005 -> 1
A36: 14 | B36: Yvo Rafiel Samson | C36: 200 | D36: =600+100 -> 700 | E36: 280 | F36: 0 | G36: 0 | L36: 0 | P36: =C36+D36+E36+F36+G36+H36+I36+J36+K36+L36+M36+N36+O36 -> 1180 | Q36: =P36/12 -> 98.333333 | R36: =D37+E37+F37+G37+H37+I37+J37+K37+L37+M37+N37+O37 -> 69.4 | S36: =P36+R36 -> 1249.4
C37: Interest per mo. | D37: =(C36+D36)*0.005 -> 4.5 | E37: =(C36+D36+E36)*0.005 -> 5.9 | F37: =(+C36+D36+E36+F36)*0.005 -> 5.9 | G37: =(C36+D36+E36+F36+G36)*0.005 -> 5.9 | H37: =(C36+D36+E36+F36+G36+H36)*0.005 -> 5.9 | I37: =(C36+D36+E36+F36+G36+H36+I36)*0.005 -> 5.9 | J37: =(C36+D36+E36+F36+G36+H36+I36+J36)*0.005 -> 5.9 | K37: =(C36+D36+E36+F36+G36+H36+I36+J36+K36)*0.005 -> 5.9 | L37: =(C36+D36+E36+F36+G36+H36+I36+J36+K36+L36)*0.005 -> 5.9 | M37: =(C36+D36+E36+F36+G36+H36+I36+J36+K36+L36+M36)*0.005 -> 5.9 | N37: =(C36+D36+E36+F36+G36+H36+I36+J36+K36+L36+M36+N36)*0.005 -> 5.9 | O37: =(C36+D36+E36+F36+G36+H36+I36+J36+K36+L36+M36+N36+O36)*0.005 -> 5.9
S38: Page 1 of 2
B42: TOTAL | C42: =SUM(C10:C41) -> 9666.76 | D42: =SUM(D10:D41) -> 1701.0738 | E42: =SUM(E10:E41) -> 1241.2238 | F42: =SUM(F10:F41) -> 563.7238 | G42: =SUM(G10:G41) -> 63.7238 | H42: =SUM(H10:H41) -> 63.7238 | I42: =SUM(I10:I41) -> 1068.7238 | J42: =SUM(J10:J41) -> 370.2238 | ... S42: =SUM(S10:S41) -> 18802.451
A44: Prepared by: | E44: Checked by: | K44: Noted by: | P44: Approved by:
B47: SHALOU J. BALAO | F47: MARIA GENIA C. SEGUIDO | L47: ARNOLD C. GONZALES | Q47: DEXTER B. JUMAO-AS
B48: SCSCC Secretary | F48: SCSCC Treasurer | L48: General Manager, SCSCC | Q48: Chairman, SCSCC BOD
S51: Page 2 of 2
P55: Regular | Q55: =18 -> 18 | R55: =S10+S14+S16+S18+S20+S22+S24+S26+S28+S30+S32+S34+#REF!+#REF!+#REF!+#REF!+#REF!+S36 -> #REF!
P56: Associates | Q56: 11 | R56: =S12+#REF!+#REF!+#REF!+#REF!+#REF!+#REF!+#REF!+#REF!+#REF!+#REF! -> #REF!
Q57: =Q55+Q56 -> 29 | R57: =R55+R56 -> #REF!

Sheet kiddy2021
A2: SIDLAK CHRISTIAN CHILDREN FUND SAVINGS AND CREDIT COOPERATIVE
A3: CDA Registration No. 9520-1080000000036399 Dated: November 16, 2016
A4: P-2, Brgy. Linao, Ormoc City
A6: COMPUTATION OF SAVINGS DEPOSITS
A7: As of FY 2021
C9: 2020 Savings | D9: Jan | E9: Feb | F9: Mar | G9: Apr | H9: May | I9: Jun | J9: Jul | K9: Aug | L9: Sep | M9: Oct | N9: Nov | O9: Dec | P9: TSAD | Q9: ASAD | R9: Int. on TSAD | S9: Total (SAD + Interest)
A10: 1 | B10: Cort Wensley J. Balao | C10: 1678.97 | D10: 200 | E10: 0 | F10: 0 | G10: 0 | H10: 0 | I10: 0 | J10: 0 | K10: 0 | L10: 0 | M10: 0 | N10: 0 | O10: 400 | P10: =C10+D10+E10+F10+G10+H10+I10+J10+K10+L10+M10+N10+O10 -> 2278.97 | Q10: =P10/12 -> 189.91417 | R10: =D11+E11+F11+G11+H11+I11+J11+K11+L11+M11+N11+O11 -> 113.73335 | S10: =P10+R10 -> 2392.7033
C11: Interest per mo. | D11: 8.39 | E11: =(C10+D10+E10)*0.005 -> 9.39485 | F11: =(+C10+D10+E10+F10)*0.005 -> 9.39485 | G11: =(C10+D10+E10+F10+G10)*0.005 -> 9.39485 | H11: =(C10+D10+E10+F10+G10+H10)*0.005 -> 9.39485 | I11: =(C10+D10+E10+F10+G10+H10+I10)*0.005 -> 9.39485 | J11: =(C10+D10+E10+F10+G10+H10+I10+J10)*0.005 -> 9.39485 | K11: =(C10+D10+E10+F10+G10+H10+I10+J10+K10)*0.005 -> 9.39485 | L11: =(C10+D10+E10+F10+G10+H10+I10+J10+K10+L10)*0.005 -> 9.39485 | M11: =(C10+D10+E10+F10+G10+H10+I10+J10+K10+L10+M10)*0.005 -> 9.39485 | N11: =(C10+D10+E10+F10+G10+H10+I10+J10+K10+L10+M10+N10)*0.005 -> 9.39485 | O11: =(C10+D10+E10+F10+G10+H10+I10+J10+K10+L10+M10+N10+O10)*0.005 -> 11.39485
A12: 2 | B12: Brett Colin J. Balao | C12: 2162.11 | D12: 200 | N12: 0 | O12: 0 | P12: =C12+D12+E12+F12+G12+H12+I12+J12+K12+L12+M12+N12+O12 -> 2362.11 | Q12: =P12/12 -> 196.8425 | R12: =D13+E13+F13+G13+H13+I13+J13+K13+L13+M13+N13+O13 -> 140.72605 | S12: =P12+R12 -> 2502.836
C13: Interest per mo. | D13: 10.81 | E13: =(C12+D12+E12)*0.005 -> 11.81055 | F13: =(+C12+D12+E12+F12)*0.005 -> 11.81055 | G13: =(C12+D12+E12+F12+G12)*0.005 -> 11.81055 | H13: =(C12+D12+E12+F12+G12+H12)*0.005 -> 11.81055 | I13: =(C12+D12+E12+F12+G12+H12+I12)*0.005 -> 11.81055 | J13: =(C12+D12+E12+F12+G12+H12+I12+J12)*0.005 -> 11.81055 | K13: =(C12+D12+E12+F12+G12+H12+I12+J12+K12)*0.005 -> 11.81055 | L13: =(C12+D12+E12+F12+G12+H12+I12+J12+K12+L12)*0.005 -> 11.81055 | M13: =(C12+D12+E12+F12+G12+H12+I12+J12+K12+L12+M12)*0.005 -> 11.81055 | N13: =(C12+D12+E12+F12+G12+H12+I12+J12+K12+L12+M12+N12)*0.005 -> 11.81055 | O13: =(C12+D12+E12+F12+G12+H12+I12+J12+K12+L12+M12+N12+O12)*0.005 -> 11.81055
A14: 3 | B14: Demian Sabin C. Jumao-as | C14: 5009.34 | D14: 0 | E14: 0 | F14: 0 | G14: 0 | H14: 0 | I14: 0 | J14: 0 | K14: 0 | L14: 0 | M14: 0 | N14: 0 | O14: 1600 | P14: =C14+D14+E14+F14+G14+H14+I14+J14+K14+L14+M14+N14+O14 -> 6609.34 | Q14: =P14/12 -> 550.77833 | R14: =D15+E15+F15+G15+H15+I15+J15+K15+L15+M15+N15+O15 -> 308.5637 | S14: =P14+R14 -> 6917.9037
C15: Interest per mo. | D15: 25.05 | E15: =(C14+D14+E14)*0.005 -> 25.0467 | F15: =(+C14+D14+E14+F14)*0.005 -> 25.0467 | G15: =(C14+D14+E14+F14+G14)*0.005 -> 25.0467 | H15: =(C14+D14+E14+F14+G14+H14)*0.005 -> 25.0467 | I15: =(C14+D14+E14+F14+G14+H14+I14)*0.005 -> 25.0467 | J15: =(C14+D14+E14+F14+G14+H14+I14+J14)*0.005 -> 25.0467 | K15: =(C14+D14+E14+F14+G14+H14+I14+J14+K14)*0.005 -> 25.0467 | L15: =(C14+D14+E14+F14+G14+H14+I14+J14+K14+L14)*0.005 -> 25.0467 | M15: =(C14+D14+E14+F14+G14+H14+I14+J14+K14+L14+M14)*0.005 -> 25.0467 | N15: =(C14+D14+E14+F14+G14+H14+I14+J14+K14+L14+M14+N14)*0.005 -> 25.0467 | O15: =(C14+D14+E14+F14+G14+H14+I14+J14+K14+L14+M14+N14+O14)*0.005 -> 33.0467
A16: 4 | B16: Izy Kaizer J. Balao | C16: 2796.44 | D16: 600 | E16: 0 | F16: 0 | G16: 0 | H16: 0 | I16: 0 | J16: 0 | K16: 0 | L16: 0 | M16: 0 | N16: 0 | O16: 0 | P16: =C16+D16+E16+F16+G16+H16+I16+J16+K16+L16+M16+N16+O16 -> 3396.44 | Q16: =P16/12 -> 283.03667 | R16: =D17+E17+F17+G17+H17+I17+J17+K17+L17+M17+N17+O17 -> 200.1542 | S16: =P16+R16 -> 3596.5942
C17: Interest per mo. | D17: 13.35 | E17: =(C16+D16+E16)*0.005 -> 16.9822 | F17: =(+C16+D16+E16+F16)*0.005 -> 16.9822 | G17: =(C16+D16+E16+F16+G16)*0.005 -> 16.9822 | H17: =(C16+D16+E16+F16+G16+H16)*0.005 -> 16.9822 | I17: =(C16+D16+E16+F16+G16+H16+I16)*0.005 -> 16.9822 | J17: =(C16+D16+E16+F16+G16+H16+I16+J16)*0.005 -> 16.9822 | K17: =(C16+D16+E16+F16+G16+H16+I16+J16+K16)*0.005 -> 16.9822 | L17: =(C16+D16+E16+F16+G16+H16+I16+J16+K16+L16)*0.005 -> 16.9822 | M17: =(C16+D16+E16+F16+G16+H16+I16+J16+K16+L16+M16)*0.005 -> 16.9822 | N17: =(C16+D16+E16+F16+G16+H16+I16+J16+K16+L16+M16+N16)*0.005 -> 16.9822 | O17: =(C16+D16+E16+F16+G16+H16+I16+J16+K16+L16+M16+N16+O16)*0.005 -> 16.9822
A18: 5 | B18: Alerc Finlay J. Balao | C18: 2094.24 | D18: 200 | E18: 0 | F18: 0 | G18: 0 | H18: 0 | I18: 0 | J18: 0 | K18: 0 | L18: 0 | M18: 0 | N18: 0 | O18: 0 | P18: =C18+D18+E18+F18+G18+H18+I18+J18+K18+L18+M18+N18+O18 -> 2294.24 | Q18: =P18/12 -> 191.18667 | R18: =D19+E19+F19+G19+H19+I19+J19+K19+L19+M19+N19+O19 -> 126.1832 | S18: =P18+R18 -> 2420.4232
C19: Interest per mo. | E19: =(C18+D18+E18)*0.005 -> 11.4712 | F19: =(+C18+D18+E18+F18)*0.005 -> 11.4712 | G19: =(C18+D18+E18+F18+G18)*0.005 -> 11.4712 | H19: =(C18+D18+E18+F18+G18+H18)*0.005 -> 11.4712 | I19: =(C18+D18+E18+F18+G18+H18+I18)*0.005 -> 11.4712 | J19: =(C18+D18+E18+F18+G18+H18+I18+J18)*0.005 -> 11.4712 | K19: =(C18+D18+E18+F18+G18+H18+I18+J18+K18)*0.005 -> 11.4712 | L19: =(C18+D18+E18+F18+G18+H18+I18+J18+K18+L18)*0.005 -> 11.4712 | M19: =(C18+D18+E18+F18+G18+H18+I18+J18+K18+L18+M18)*0.005 -> 11.4712 | N19: =(C18+D18+E18+F18+G18+H18+I18+J18+K18+L18+M18+N18)*0.005 -> 11.4712 | O19: =(C18+D18+E18+F18+G18+H18+I18+J18+K18+L18+M18+N18+O18)*0.005 -> 11.4712
A20: 6 | B20: Georgette Ann Cabahug | C20: 50 | D20: 0 | P20: 50 | Q20: =P20/12 -> 4.1666667 | S20: =P20+R20 -> 50
C21: Interest per mo. | D21: =(C20+D20)*0.005 -> 0.25 | E21: =(C20+D20+E20)*0.005 -> 0.25 | F21: =(+C20+D20+E20+F20)*0.005 -> 0.25 | G21: =(C20+D20+E20+F20+G20)*0.005 -> 0.25 | H21: =(C20+D20+E20+F20+G20+H20)*0.005 -> 0.25 | I21: =(C20+D20+E20+F20+G20+H20+I20)*0.005 -> 0.25 | J21: =(C20+D20+E20+F20+G20+H20+I20+J20)*0.005 -> 0.25 | K21: =(C20+D20+E20+F20+G20+H20+I20+J20+K20)*0.005 -> 0.25 | L21: =(C20+D20+E20+F20+G20+H20+I20+J20+K20+L20)*0.005 -> 0.25 | M21: =(C20+D20+E20+F20+G20+H20+I20+J20+K20+L20+M20)*0.005 -> 0.25 | N21: =(C20+D20+E20+F20+G20+H20+I20+J20+K20+L20+M20+N20)*0.005 -> 0.25 | O21: =(C20+D20+E20+F20+G20+H20+I20+J20+K20+L20+M20+N20+O20)*0.005 -> 0.25
A22: 7 | B22: Luna Mikaela C. Apay | C22: 50 | D22: 0 | P22: =C22+D22+E22+F22+G22+H22+I22+J22+K22+L22+M22+N22+O22 -> 50 | Q22: =P22/12 -> 4.1666667 | S22: =P22+R22 -> 50
C23: Interest per mo. | D23: =(C22+D22)*0.005 -> 0.25 | E23: =(C22+D22+E22)*0.005 -> 0.25 | F23: =(+C22+D22+E22+F22)*0.005 -> 0.25 | G23: =(C22+D22+E22+F22+G22)*0.005 -> 0.25 | H23: =(C22+D22+E22+F22+G22+H22)*0.005 -> 0.25 | I23: =(C22+D22+E22+F22+G22+H22+I22)*0.005 -> 0.25 | J23: =(C22+D22+E22+F22+G22+H22+I22+J22)*0.005 -> 0.25 | K23: =(C22+D22+E22+F22+G22+H22+I22+J22+K22)*0.005 -> 0.25 | L23: =(C22+D22+E22+F22+G22+H22+I22+J22+K22+L22)*0.005 -> 0.25 | M23: =(C22+D22+E22+F22+G22+H22+I22+J22+K22+L22+M22)*0.005 -> 0.25 | N23: =(C22+D22+E22+F22+G22+H22+I22+J22+K22+L22+M22+N22)*0.005 -> 0.25 | O23: =(C22+D22+E22+F22+G22+H22+I22+J22+K22+L22+M22+N22+O22)*0.005 -> 0.25
A24: 8 | B24: Mikko Angelo C. Apay | C24: 50 | D24: 0 | P24: =C24+D24+E24+F24+G24+H24+I24+J24+K24+L24+M24+N24+O24 -> 50 | Q24: =P24/12 -> 4.1666667 | S24: =P24+R24 -> 50
C25: Interest per mo. | D25: =(C24+D24)*0.005 -> 0.25 | E25: =(C24+D24+E24)*0.005 -> 0.25 | F25: =(+C24+D24+E24+F24)*0.005 -> 0.25 | G25: =(C24+D24+E24+F24+G24)*0.005 -> 0.25 | H25: =(C24+D24+E24+F24+G24+H24)*0.005 -> 0.25 | I25: =(C24+D24+E24+F24+G24+H24+I24)*0.005 -> 0.25 | J25: =(C24+D24+E24+F24+G24+H24+I24+J24)*0.005 -> 0.25 | K25: =(C24+D24+E24+F24+G24+H24+I24+J24+K24)*0.005 -> 0.25 | L25: =(C24+D24+E24+F24+G24+H24+I24+J24+K24+L24)*0.005 -> 0.25 | M25: =(C24+D24+E24+F24+G24+H24+I24+J24+K24+L24+M24)*0.005 -> 0.25 | N25: =(C24+D24+E24+F24+G24+H24+I24+J24+K24+L24+M24+N24)*0.005 -> 0.25 | O25: =(C24+D24+E24+F24+G24+H24+I24+J24+K24+L24+M24+N24+O24)*0.005 -> 0.25
A26: 9 | B26: Casy Marie D. Cruz | C26: 563 | D26: 50 | I26: 0 | K26: 100 | N26: 0 | P26: =C26+D26+E26+F26+G26+H26+I26+J26+K26+L26+M26+N26+O26 -> 713 | Q26: =P26/12 -> 59.416667 | R26: =D27+E27+F27+G27+H27+I27+J27+K27+L27+M27+N27+O27 -> 17.825 | S26: =P26+R26 -> 730.825
C27: Interest per mo. | K27: =(C26+D26+E26+F26+G26+H26+I26+J26+K26)*0.005 -> 3.565 | L27: =(C26+D26+E26+F26+G26+H26+I26+J26+K26+L26)*0.005 -> 3.565 | M27: =(C26+D26+E26+F26+G26+H26+I26+J26+K26+L26+M26)*0.005 -> 3.565 | N27: =(C26+D26+E26+F26+G26+H26+I26+J26+K26+L26+M26+N26)*0.005 -> 3.565 | O27: =(C26+D26+E26+F26+G26+H26+I26+J26+K26+L26+M26+N26+O26)*0.005 -> 3.565
A28: 10 | B28: Marissa alvarado | C28: 50 | D28: 0 | J28: 0 | M28: 0 | P28: =C28+D28+E28+F28+G28+H28+I28+J28+K28+L28+M28+N28+O28 -> 50 | Q28: =P28/12 -> 4.1666667 | S28: =P28+R28 -> 50
C29: Interest per mo. | D29: =(C28+D28)*0.005 -> 0.25 | E29: =(C28+D28+E28)*0.005 -> 0.25 | F29: =(+C28+D28+E28+F28)*0.005 -> 0.25 | G29: =(C28+D28+E28+F28+G28)*0.005 -> 0.25 | H29: =(C28+D28+E28+F28+G28+H28)*0.005 -> 0.25 | I29: =(C28+D28+E28+F28+G28+H28+I28)*0.005 -> 0.25 | J29: =(C28+D28+E28+F28+G28+H28+I28+J28)*0.005 -> 0.25 | K29: =(C28+D28+E28+F28+G28+H28+I28+J28+K28)*0.005 -> 0.25 | L29: =(C28+D28+E28+F28+G28+H28+I28+J28+K28+L28)*0.005 -> 0.25 | M29: =(C28+D28+E28+F28+G28+H28+I28+J28+K28+L28+M28)*0.005 -> 0.25 | N29: =(C28+D28+E28+F28+G28+H28+I28+J28+K28+L28+M28+N28)*0.005 -> 0.25 | O29: =(C28+D28+E28+F28+G28+H28+I28+J28+K28+L28+M28+N28+O28)*0.005 -> 0.25
A30: 11 | B30: Krissel Alvarado | C30: 50 | D30: 0 | P30: =C30+D30+E30+F30+G30+H30+I30+J30+K30+L30+M30+N30+O30 -> 50 | Q30: =P30/12 -> 4.1666667 | S30: =P30+R30 -> 50
C31: Interest per mo. | D31: =(C30+D30)*0.005 -> 0.25 | E31: =(C30+D30+E30)*0.005 -> 0.25 | F31: =(+C30+D30+E30+F30)*0.005 -> 0.25 | G31: =(C30+D30+E30+F30+G30)*0.005 -> 0.25 | H31: =(C30+D30+E30+F30+G30+H30)*0.005 -> 0.25 | I31: =(C30+D30+E30+F30+G30+H30+I30)*0.005 -> 0.25 | J31: =(C30+D30+E30+F30+G30+H30+I30+J30)*0.005 -> 0.25 | K31: =(C30+D30+E30+F30+G30+H30+I30+J30+K30)*0.005 -> 0.25 | L31: =(C30+D30+E30+F30+G30+H30+I30+J30+K30+L30)*0.005 -> 0.25 | M31: =(C30+D30+E30+F30+G30+H30+I30+J30+K30+L30+M30)*0.005 -> 0.25 | N31: =(C30+D30+E30+F30+G30+H30+I30+J30+K30+L30+M30+N30)*0.005 -> 0.25 | O31: =(C30+D30+E30+F30+G30+H30+I30+J30+K30+L30+M30+N30+O30)*0.005 -> 0.25
A32: 12 | B32: Serg Mateo M. Villamor | C32: 2798.96 | D32: 0 | E32: 0 | F32: 0 | J32: 0 | K32: 0 | L32: 0 | M32: 0 | N32: 0 | O32: 0 | P32: =C32+D32+E32+F32+G32+H32+I32+J32+K32+L32+M32+N32+O32 -> 2798.96 | Q32: =P32/12 -> 233.24667 | R32: =D33+E33+F33+G33+H33+I33+J33+K33+L33+M33+N33+O33 -> 153.9428 | S32: =P32+R32 -> 2952.9028
C33: Interest per mo. | E33: =(C32+D32+E32)*0.005 -> 13.9948 | F33: =(+C32+D32+E32+F32)*0.005 -> 13.9948 | G33: =(C32+D32+E32+F32+G32)*0.005 -> 13.9948 | H33: =(C32+D32+E32+F32+G32+H32)*0.005 -> 13.9948 | I33: =(C32+D32+E32+F32+G32+H32+I32)*0.005 -> 13.9948 | J33: =(C32+D32+E32+F32+G32+H32+I32+J32)*0.005 -> 13.9948 | K33: =(C32+D32+E32+F32+G32+H32+I32+J32+K32)*0.005 -> 13.9948 | L33: =(C32+D32+E32+F32+G32+H32+I32+J32+K32+L32)*0.005 -> 13.9948 | M33: =(C32+D32+E32+F32+G32+H32+I32+J32+K32+L32+M32)*0.005 -> 13.9948 | N33: =(C32+D32+E32+F32+G32+H32+I32+J32+K32+L32+M32+N32)*0.005 -> 13.9948 | O33: =(C32+D32+E32+F32+G32+H32+I32+J32+K32+L32+M32+N32+O32)*0.005 -> 13.9948
A34: 13 | B34: Rica M. Cruz | C34: 200 | D34: 0 | E34: 0 | F34: 0 | L34: 0 | P34: =C34+D34+E34+F34+G34+H34+I34+J34+K34+L34+M34+N34+O34 -> 200 | Q34: =P34/12 -> 16.666667 | S34: =P34+R34 -> 200
C35: Interest per mo. | D35: =(C34+D34)*0.005 -> 1 | E35: =(C34+D34+E34)*0.005 -> 1 | F35: =(+C34+D34+E34+F34)*0.005 -> 1 | G35: =(C34+D34+E34+F34+G34)*0.005 -> 1 | H35: =(C34+D34+E34+F34+G34+H34)*0.005 -> 1 | I35: =(C34+D34+E34+F34+G34+H34+I34)*0.005 -> 1 | J35: =(C34+D34+E34+F34+G34+H34+I34+J34)*0.005 -> 1 | K35: =(C34+D34+E34+F34+G34+H34+I34+J34+K34)*0.005 -> 1 | L35: =(C34+D34+E34+F34+G34+H34+I34+J34+K34+L34)*0.005 -> 1 | M35: =(C34+D34+E34+F34+G34+H34+I34+J34+K34+L34+M34)*0.005 -> 1 | N35: =(C34+D34+E34+F34+G34+H34+I34+J34+K34+L34+M34+N34)*0.005 -> 1 | O35: =(C34+D34+E34+F34+G34+H34+I34+J34+K34+L34+M34+N34+O34)*0.005 -> 1
A36: 14 | B36: Yvo Rafiel Samson | C36: 1249.4 | D36: 300 | E36: 0 | F36: 0 | G36: 0 | H36: 0 | I36: 0 | J36: 0 | K36: 0 | L36: 0 | M36: 0 | N36: 0 | O36: 0 | P36: =C36+D36+E36+F36+G36+H36+I36+J36+K36+L36+M36+N36+O36 -> 1549.4 | Q36: =P36/12 -> 129.11667 | R36: =D37+E37+F37+G37+H37+I37+J37+K37+L37+M37+N37+O37 -> 92.964 | S36: =P36+R36 -> 1642.364
C37: Interest per mo. | D37: =(C36+D36)*0.005 -> 7.747 | E37: =(C36+D36+E36)*0.005 -> 7.747 | F37: =(+C36+D36+E36+F36)*0.005 -> 7.747 | G37: =(C36+D36+E36+F36+G36)*0.005 -> 7.747 | H37: =(C36+D36+E36+F36+G36+H36)*0.005 -> 7.747 | I37: =(C36+D36+E36+F36+G36+H36+I36)*0.005 -> 7.747 | J37: =(C36+D36+E36+F36+G36+H36+I36+J36)*0.005 -> 7.747 | K37: =(C36+D36+E36+F36+G36+H36+I36+J36+K36)*0.005 -> 7.747 | L37: =(C36+D36+E36+F36+G36+H36+I36+J36+K36+L36)*0.005 -> 7.747 | M37: =(C36+D36+E36+F36+G36+H36+I36+J36+K36+L36+M36)*0.005 -> 7.747 | N37: =(C36+D36+E36+F36+G36+H36+I36+J36+K36+L36+M36+N36)*0.005 -> 7.747 | O37: =(C36+D36+E36+F36+G36+H36+I36+J36+K36+L36+M36+N36+O36)*0.005 -> 7.747
S38: Page 1 of 2
B42: TOTAL | C42: =SUM(C10:C41) -> 18802.46 | D42: =SUM(D10:D41) -> 1617.597 | E42: =SUM(E10:E41) -> 98.6973 | F42: =SUM(F10:F41) -> 98.6973 | G42: =SUM(G10:G41) -> 98.6973 | H42: =SUM(H10:H41) -> 98.6973 | I42: =SUM(I10:I41) -> 98.6973 | J42: =SUM(J10:J41) -> 98.6973 | ... S42: =SUM(S10:S41) -> 23606.552
A44: Prepared by: | E44: Checked by: | K44: Noted by: | P44: Approved by:
B47: SHALOU J. BALAO | F47: MARIA GENIA C. SEGUIDO | L47: ARNOLD C. GONZALES | Q47: DEXTER B. JUMAO-AS
B48: SCSCC Secretary | F48: SCSCC Treasurer | L48: General Manager, SCSCC | Q48: Chairman, SCSCC BOD
S51: Page 2 of 2
P55: Regular | Q55: =18 -> 18 | R55: =S10+S14+S16+S18+S20+S22+S24+S26+S28+S30+S32+S34+#REF!+#REF!+#REF!+#REF!+#REF!+S36 -> #REF!
P56: Associates | Q56: 11 | R56: =S12+#REF!+#REF!+#REF!+#REF!+#REF!+#REF!+#REF!+#REF!+#REF!+#REF! -> #REF!
Q57: =Q55+Q56 -> 29 | R57: =R55+R56 -> #REF!

Sheet kiddy2022
A2: SIDLAK CHRISTIAN CHILDREN FUND SAVINGS AND CREDIT COOPERATIVE
A3: CDA Registration No. 9520-1080000000036399 Dated: November 16, 2016
A4: P-2, Brgy. Linao, Ormoc City
A6: COMPUTATION OF SAVINGS DEPOSITS
A7: As of FY 2021
C9: 2021 Savings | D9: Jan | E9: Feb | F9: Mar | G9: Apr | H9: May | I9: Jun | J9: Jul | K9: Aug | L9: Sep | M9: Oct | N9: Nov | O9: Dec | P9: TSAD | Q9: ASAD | R9: Int. on TSAD | S9: Total (SAD + Interest)
A10: 1 | B10: Cort Wensley J. Balao | C10: 2392.7 | E10: 0 | F10: 0 | G10: 0 | H10: 0 | I10: 0 | J10: 0 | K10: 0 | L10: 0 | M10: 0 | N10: 0 | P10: =C10+D10+E10+F10+G10+H10+I10+J10+K10+L10+M10+N10+O10 -> 2392.7 | Q10: =P10/12 -> 199.39167 | R10: =D11+E11+F11+G11+H11+I11+J11+K11+L11+M11+N11+O11 -> 139.9885 | S10: =P10+R10 -> 2532.6885
C11: Interest per mo. | D11: 8.39 | E11: =(C10+D10+E10)*0.005 -> 11.9635 | F11: =(+C10+D10+E10+F10)*0.005 -> 11.9635 | G11: =(C10+D10+E10+F10+G10)*0.005 -> 11.9635 | H11: =(C10+D10+E10+F10+G10+H10)*0.005 -> 11.9635 | I11: =(C10+D10+E10+F10+G10+H10+I10)*0.005 -> 11.9635 | J11: =(C10+D10+E10+F10+G10+H10+I10+J10)*0.005 -> 11.9635 | K11: =(C10+D10+E10+F10+G10+H10+I10+J10+K10)*0.005 -> 11.9635 | L11: =(C10+D10+E10+F10+G10+H10+I10+J10+K10+L10)*0.005 -> 11.9635 | M11: =(C10+D10+E10+F10+G10+H10+I10+J10+K10+L10+M10)*0.005 -> 11.9635 | N11: =(C10+D10+E10+F10+G10+H10+I10+J10+K10+L10+M10+N10)*0.005 -> 11.9635 | O11: =(C10+D10+E10+F10+G10+H10+I10+J10+K10+L10+M10+N10+O10)*0.005 -> 11.9635
C12: `` | D12: 10.81 | E12: =(#REF!+#REF!+#REF!)*0.005 -> #REF! | F12: =(+#REF!+#REF!+#REF!+#REF!)*0.005 -> #REF! | G12: =(#REF!+#REF!+#REF!+#REF!+#REF!)*0.005 -> #REF! | H12: =(#REF!+#REF!+#REF!+#REF!+#REF!+#REF!)*0.005 -> #REF! | I12: =(#REF!+#REF!+#REF!+#REF!+#REF!+#REF!+#REF!)*0.005 -> #REF! | J12: =(#REF!+#REF!+#REF!+#REF!+#REF!+#REF!+#REF!+#REF!)*0.005 -> #REF! | K12: =(#REF!+#REF!+#REF!+#REF!+#REF!+#REF!+#REF!+#REF!+#REF!)*0.005 -> #REF! | L12: =(#REF!+#REF!+#REF!+#REF!+#REF!+#REF!+#REF!+#REF!+#REF!+#REF!)*0.005 -> #REF! | M12: =(#REF!+#REF!+#REF!+#REF!+#REF!+#REF!+#REF!+#REF!+#REF!+#REF!+#REF!)*0.005 -> #REF! | N12: =(#REF!+#REF!+#REF!+#REF!+#REF!+#REF!+#REF!+#REF!+#REF!+#REF!+#REF!+#REF!)*0.005 -> #REF! | O12: =(#REF!+#REF!+#REF!+#REF!+#REF!+#REF!+#REF!+#REF!+#REF!+#REF!+#REF!+#REF!+#REF!)*0.005 -> #REF!
A13: 3 | B13: Demian Sabin C. Jumao-as | C13: 6917.9 | D13: 0 | E13: 0 | F13: 0 | G13: 0 | H13: 0 | I13: 0 | J13: 0 | K13: 0 | L13: 0 | M13: 0 | N13: 0 | P13: =C13+D13+E13+F13+G13+H13+I13+J13+K13+L13+M13+N13+O13 -> 6917.9 | Q13: =P13/12 -> 576.49167 | R13: =D14+E14+F14+G14+H14+I14+J14+K14+L14+M14+N14+O14 -> 405.5345 | S13: =P13+R13 -> 7323.4345
C14: Interest per mo. | D14: 25.05 | E14: =(C13+D13+E13)*0.005 -> 34.5895 | F14: =(+C13+D13+E13+F13)*0.005 -> 34.5895 | G14: =(C13+D13+E13+F13+G13)*0.005 -> 34.5895 | H14: =(C13+D13+E13+F13+G13+H13)*0.005 -> 34.5895 | I14: =(C13+D13+E13+F13+G13+H13+I13)*0.005 -> 34.5895 | J14: =(C13+D13+E13+F13+G13+H13+I13+J13)*0.005 -> 34.5895 | K14: =(C13+D13+E13+F13+G13+H13+I13+J13+K13)*0.005 -> 34.5895 | L14: =(C13+D13+E13+F13+G13+H13+I13+J13+K13+L13)*0.005 -> 34.5895 | M14: =(C13+D13+E13+F13+G13+H13+I13+J13+K13+L13+M13)*0.005 -> 34.5895 | N14: =(C13+D13+E13+F13+G13+H13+I13+J13+K13+L13+M13+N13)*0.005 -> 34.5895 | O14: =(C13+D13+E13+F13+G13+H13+I13+J13+K13+L13+M13+N13+O13)*0.005 -> 34.5895
A15: 4 | B15: Izy Kaizer J. Balao | C15: 3596.59 | E15: 0 | F15: 0 | G15: 0 | H15: 0 | I15: 0 | J15: 0 | K15: 0 | L15: 0 | M15: 0 | N15: 0 | O15: 0 | P15: =C15+D15+E15+F15+G15+H15+I15+J15+K15+L15+M15+N15+O15 -> 3596.59 | Q15: =P15/12 -> 299.71583 | R15: =D16+E16+F16+G16+H16+I16+J16+K16+L16+M16+N16+O16 -> 211.16245 | S15: =P15+R15 -> 3807.7524
C16: Interest per mo. | D16: 13.35 | E16: =(C15+D15+E15)*0.005 -> 17.98295 | F16: =(+C15+D15+E15+F15)*0.005 -> 17.98295 | G16: =(C15+D15+E15+F15+G15)*0.005 -> 17.98295 | H16: =(C15+D15+E15+F15+G15+H15)*0.005 -> 17.98295 | I16: =(C15+D15+E15+F15+G15+H15+I15)*0.005 -> 17.98295 | J16: =(C15+D15+E15+F15+G15+H15+I15+J15)*0.005 -> 17.98295 | K16: =(C15+D15+E15+F15+G15+H15+I15+J15+K15)*0.005 -> 17.98295 | L16: =(C15+D15+E15+F15+G15+H15+I15+J15+K15+L15)*0.005 -> 17.98295 | M16: =(C15+D15+E15+F15+G15+H15+I15+J15+K15+L15+M15)*0.005 -> 17.98295 | N16: =(C15+D15+E15+F15+G15+H15+I15+J15+K15+L15+M15+N15)*0.005 -> 17.98295 | O16: =(C15+D15+E15+F15+G15+H15+I15+J15+K15+L15+M15+N15+O15)*0.005 -> 17.98295
A17: 5 | B17: Alerc Finlay J. Balao | C17: 2420.42 | E17: 0 | F17: 500 | G17: 0 | H17: 0 | I17: 0 | J17: 0 | K17: 0 | L17: 0 | M17: 0 | N17: 0 | O17: 0 | P17: =C17+D17+E17+F17+G17+H17+I17+J17+K17+L17+M17+N17+O17 -> 2920.42 | Q17: =P17/12 -> 243.36833 | R17: =D18+E18+F18+G18+H18+I18+J18+K18+L18+M18+N18+O18 -> 158.1231 | S17: =P17+R17 -> 3078.5431
C18: Interest per mo. | E18: =(C17+D17+E17)*0.005 -> 12.1021 | F18: =(+C17+D17+E17+F17)*0.005 -> 14.6021 | G18: =(C17+D17+E17+F17+G17)*0.005 -> 14.6021 | H18: =(C17+D17+E17+F17+G17+H17)*0.005 -> 14.6021 | I18: =(C17+D17+E17+F17+G17+H17+I17)*0.005 -> 14.6021 | J18: =(C17+D17+E17+F17+G17+H17+I17+J17)*0.005 -> 14.6021 | K18: =(C17+D17+E17+F17+G17+H17+I17+J17+K17)*0.005 -> 14.6021 | L18: =(C17+D17+E17+F17+G17+H17+I17+J17+K17+L17)*0.005 -> 14.6021 | M18: =(C17+D17+E17+F17+G17+H17+I17+J17+K17+L17+M17)*0.005 -> 14.6021 | N18: =(C17+D17+E17+F17+G17+H17+I17+J17+K17+L17+M17+N17)*0.005 -> 14.6021 | O18: =(C17+D17+E17+F17+G17+H17+I17+J17+K17+L17+M17+N17+O17)*0.005 -> 14.6021
A19: 6 | B19: Georgette Ann Cabahug | C19: 50 | D19: 0 | P19: 50 | Q19: =P19/12 -> 4.1666667 | S19: =P19+R19 -> 50
C20: Interest per mo. | D20: =(C19+D19)*0.005 -> 0.25 | E20: =(C19+D19+E19)*0.005 -> 0.25 | F20: =(+C19+D19+E19+F19)*0.005 -> 0.25 | G20: =(C19+D19+E19+F19+G19)*0.005 -> 0.25 | H20: =(C19+D19+E19+F19+G19+H19)*0.005 -> 0.25 | I20: =(C19+D19+E19+F19+G19+H19+I19)*0.005 -> 0.25 | J20: =(C19+D19+E19+F19+G19+H19+I19+J19)*0.005 -> 0.25 | K20: =(C19+D19+E19+F19+G19+H19+I19+J19+K19)*0.005 -> 0.25 | L20: =(C19+D19+E19+F19+G19+H19+I19+J19+K19+L19)*0.005 -> 0.25 | M20: =(C19+D19+E19+F19+G19+H19+I19+J19+K19+L19+M19)*0.005 -> 0.25 | N20: =(C19+D19+E19+F19+G19+H19+I19+J19+K19+L19+M19+N19)*0.005 -> 0.25 | O20: =(C19+D19+E19+F19+G19+H19+I19+J19+K19+L19+M19+N19+O19)*0.005 -> 0.25
A21: 7 | B21: Luna Mikaela C. Apay | C21: 50 | D21: 0 | P21: =C21+D21+E21+F21+G21+H21+I21+J21+K21+L21+M21+N21+O21 -> 50 | Q21: =P21/12 -> 4.1666667 | S21: =P21+R21 -> 50
C22: Interest per mo. | D22: =(C21+D21)*0.005 -> 0.25 | E22: =(C21+D21+E21)*0.005 -> 0.25 | F22: =(+C21+D21+E21+F21)*0.005 -> 0.25 | G22: =(C21+D21+E21+F21+G21)*0.005 -> 0.25 | H22: =(C21+D21+E21+F21+G21+H21)*0.005 -> 0.25 | I22: =(C21+D21+E21+F21+G21+H21+I21)*0.005 -> 0.25 | J22: =(C21+D21+E21+F21+G21+H21+I21+J21)*0.005 -> 0.25 | K22: =(C21+D21+E21+F21+G21+H21+I21+J21+K21)*0.005 -> 0.25 | L22: =(C21+D21+E21+F21+G21+H21+I21+J21+K21+L21)*0.005 -> 0.25 | M22: =(C21+D21+E21+F21+G21+H21+I21+J21+K21+L21+M21)*0.005 -> 0.25 | N22: =(C21+D21+E21+F21+G21+H21+I21+J21+K21+L21+M21+N21)*0.005 -> 0.25 | O22: =(C21+D21+E21+F21+G21+H21+I21+J21+K21+L21+M21+N21+O21)*0.005 -> 0.25
A23: 8 | B23: Mikko Angelo C. Apay | C23: 50 | D23: 0 | P23: =C23+D23+E23+F23+G23+H23+I23+J23+K23+L23+M23+N23+O23 -> 50 | Q23: =P23/12 -> 4.1666667 | S23: =P23+R23 -> 50
C24: Interest per mo. | D24: =(C23+D23)*0.005 -> 0.25 | E24: =(C23+D23+E23)*0.005 -> 0.25 | F24: =(+C23+D23+E23+F23)*0.005 -> 0.25 | G24: =(C23+D23+E23+F23+G23)*0.005 -> 0.25 | H24: =(C23+D23+E23+F23+G23+H23)*0.005 -> 0.25 | I24: =(C23+D23+E23+F23+G23+H23+I23)*0.005 -> 0.25 | J24: =(C23+D23+E23+F23+G23+H23+I23+J23)*0.005 -> 0.25 | K24: =(C23+D23+E23+F23+G23+H23+I23+J23+K23)*0.005 -> 0.25 | L24: =(C23+D23+E23+F23+G23+H23+I23+J23+K23+L23)*0.005 -> 0.25 | M24: =(C23+D23+E23+F23+G23+H23+I23+J23+K23+L23+M23)*0.005 -> 0.25 | N24: =(C23+D23+E23+F23+G23+H23+I23+J23+K23+L23+M23+N23)*0.005 -> 0.25 | O24: =(C23+D23+E23+F23+G23+H23+I23+J23+K23+L23+M23+N23+O23)*0.005 -> 0.25
A25: 9 | B25: Casy Marie D. Cruz | C25: 730.83 | I25: 0 | N25: 0 | P25: =C25+D25+E25+F25+G25+H25+I25+J25+K25+L25+M25+N25+O25 -> 730.83 | Q25: =P25/12 -> 60.9025 | R25: =D26+E26+F26+G26+H26+I26+J26+K26+L26+M26+N26+O26 -> 18.27075 | S25: =P25+R25 -> 749.10075
C26: Interest per mo. | K26: =(C25+D25+E25+F25+G25+H25+I25+J25+K25)*0.005 -> 3.65415 | L26: =(C25+D25+E25+F25+G25+H25+I25+J25+K25+L25)*0.005 -> 3.65415 | M26: =(C25+D25+E25+F25+G25+H25+I25+J25+K25+L25+M25)*0.005 -> 3.65415 | N26: =(C25+D25+E25+F25+G25+H25+I25+J25+K25+L25+M25+N25)*0.005 -> 3.65415 | O26: =(C25+D25+E25+F25+G25+H25+I25+J25+K25+L25+M25+N25+O25)*0.005 -> 3.65415
A27: 10 | B27: Marissa alvarado | C27: 50 | D27: 0 | J27: 0 | M27: 0 | P27: =C27+D27+E27+F27+G27+H27+I27+J27+K27+L27+M27+N27+O27 -> 50 | Q27: =P27/12 -> 4.1666667 | S27: =P27+R27 -> 50
C28: Interest per mo. | D28: =(C27+D27)*0.005 -> 0.25 | E28: =(C27+D27+E27)*0.005 -> 0.25 | F28: =(+C27+D27+E27+F27)*0.005 -> 0.25 | G28: =(C27+D27+E27+F27+G27)*0.005 -> 0.25 | H28: =(C27+D27+E27+F27+G27+H27)*0.005 -> 0.25 | I28: =(C27+D27+E27+F27+G27+H27+I27)*0.005 -> 0.25 | J28: =(C27+D27+E27+F27+G27+H27+I27+J27)*0.005 -> 0.25 | K28: =(C27+D27+E27+F27+G27+H27+I27+J27+K27)*0.005 -> 0.25 | L28: =(C27+D27+E27+F27+G27+H27+I27+J27+K27+L27)*0.005 -> 0.25 | M28: =(C27+D27+E27+F27+G27+H27+I27+J27+K27+L27+M27)*0.005 -> 0.25 | N28: =(C27+D27+E27+F27+G27+H27+I27+J27+K27+L27+M27+N27)*0.005 -> 0.25 | O28: =(C27+D27+E27+F27+G27+H27+I27+J27+K27+L27+M27+N27+O27)*0.005 -> 0.25
A29: 11 | B29: Krissel Alvarado | C29: 50 | D29: 0 | P29: =C29+D29+E29+F29+G29+H29+I29+J29+K29+L29+M29+N29+O29 -> 50 | Q29: =P29/12 -> 4.1666667 | S29: =P29+R29 -> 50
C30: Interest per mo. | D30: =(C29+D29)*0.005 -> 0.25 | E30: =(C29+D29+E29)*0.005 -> 0.25 | F30: =(+C29+D29+E29+F29)*0.005 -> 0.25 | G30: =(C29+D29+E29+F29+G29)*0.005 -> 0.25 | H30: =(C29+D29+E29+F29+G29+H29)*0.005 -> 0.25 | I30: =(C29+D29+E29+F29+G29+H29+I29)*0.005 -> 0.25 | J30: =(C29+D29+E29+F29+G29+H29+I29+J29)*0.005 -> 0.25 | K30: =(C29+D29+E29+F29+G29+H29+I29+J29+K29)*0.005 -> 0.25 | L30: =(C29+D29+E29+F29+G29+H29+I29+J29+K29+L29)*0.005 -> 0.25 | M30: =(C29+D29+E29+F29+G29+H29+I29+J29+K29+L29+M29)*0.005 -> 0.25 | N30: =(C29+D29+E29+F29+G29+H29+I29+J29+K29+L29+M29+N29)*0.005 -> 0.25 | O30: =(C29+D29+E29+F29+G29+H29+I29+J29+K29+L29+M29+N29+O29)*0.005 -> 0.25
A31: 12 | B31: Serg Mateo M. Villamor | C31: 2952.9 | D31: 0 | E31: 0 | F31: 0 | J31: 0 | K31: 0 | L31: 0 | M31: 0 | N31: 0 | O31: 0 | P31: =C31+D31+E31+F31+G31+H31+I31+J31+K31+L31+M31+N31+O31 -> 2952.9 | Q31: =P31/12 -> 246.075 | R31: =D32+E32+F32+G32+H32+I32+J32+K32+L32+M32+N32+O32 -> 162.4095 | S31: =P31+R31 -> 3115.3095
C32: Interest per mo. | E32: =(C31+D31+E31)*0.005 -> 14.7645 | F32: =(+C31+D31+E31+F31)*0.005 -> 14.7645 | G32: =(C31+D31+E31+F31+G31)*0.005 -> 14.7645 | H32: =(C31+D31+E31+F31+G31+H31)*0.005 -> 14.7645 | I32: =(C31+D31+E31+F31+G31+H31+I31)*0.005 -> 14.7645 | J32: =(C31+D31+E31+F31+G31+H31+I31+J31)*0.005 -> 14.7645 | K32: =(C31+D31+E31+F31+G31+H31+I31+J31+K31)*0.005 -> 14.7645 | L32: =(C31+D31+E31+F31+G31+H31+I31+J31+K31+L31)*0.005 -> 14.7645 | M32: =(C31+D31+E31+F31+G31+H31+I31+J31+K31+L31+M31)*0.005 -> 14.7645 | N32: =(C31+D31+E31+F31+G31+H31+I31+J31+K31+L31+M31+N31)*0.005 -> 14.7645 | O32: =(C31+D31+E31+F31+G31+H31+I31+J31+K31+L31+M31+N31+O31)*0.005 -> 14.7645
A33: 13 | B33: Rica M. Cruz | C33: 200 | D33: 0 | E33: 0 | F33: 0 | L33: 0 | P33: =C33+D33+E33+F33+G33+H33+I33+J33+K33+L33+M33+N33+O33 -> 200 | Q33: =P33/12 -> 16.666667 | S33: =P33+R33 -> 200
C34: Interest per mo. | D34: =(C33+D33)*0.005 -> 1 | E34: =(C33+D33+E33)*0.005 -> 1 | F34: =(+C33+D33+E33+F33)*0.005 -> 1 | G34: =(C33+D33+E33+F33+G33)*0.005 -> 1 | H34: =(C33+D33+E33+F33+G33+H33)*0.005 -> 1 | I34: =(C33+D33+E33+F33+G33+H33+I33)*0.005 -> 1 | J34: =(C33+D33+E33+F33+G33+H33+I33+J33)*0.005 -> 1 | K34: =(C33+D33+E33+F33+G33+H33+I33+J33+K33)*0.005 -> 1 | L34: =(C33+D33+E33+F33+G33+H33+I33+J33+K33+L33)*0.005 -> 1 | M34: =(C33+D33+E33+F33+G33+H33+I33+J33+K33+L33+M33)*0.005 -> 1 | N34: =(C33+D33+E33+F33+G33+H33+I33+J33+K33+L33+M33+N33)*0.005 -> 1 | O34: =(C33+D33+E33+F33+G33+H33+I33+J33+K33+L33+M33+N33+O33)*0.005 -> 1
A35: 14 | B35: Yvo Rafiel Samson | C35: 1642.36 | E35: 0 | F35: 255 | G35: 250 | H35: 0 | I35: 0 | J35: 0 | K35: 0 | L35: 0 | M35: 0 | N35: 0 | O35: 0 | P35: =C35+D35+E35+F35+G35+H35+I35+J35+K35+L35+M35+N35+O35 -> 2147.36 | Q35: =P35/12 -> 178.94667 | R35: =D36+E36+F36+G36+H36+I36+J36+K36+L36+M36+N36+O36 -> 122.5416 | S35: =P35+R35 -> 2269.9016
C36: Interest per mo. | D36: =(C35+D35)*0.005 -> 8.2118 | E36: =(C35+D35+E35)*0.005 -> 8.2118 | F36: =(+C35+D35+E35+F35)*0.005 -> 9.4868 | G36: =(C35+D35+E35+F35+G35)*0.005 -> 10.7368 | H36: =(C35+D35+E35+F35+G35+H35)*0.005 -> 10.7368 | I36: =(C35+D35+E35+F35+G35+H35+I35)*0.005 -> 10.7368 | J36: =(C35+D35+E35+F35+G35+H35+I35+J35)*0.005 -> 10.7368 | K36: =(C35+D35+E35+F35+G35+H35+I35+J35+K35)*0.005 -> 10.7368 | L36: =(C35+D35+E35+F35+G35+H35+I35+J35+K35+L35)*0.005 -> 10.7368 | M36: =(C35+D35+E35+F35+G35+H35+I35+J35+K35+L35+M35)*0.005 -> 10.7368 | N36: =(C35+D35+E35+F35+G35+H35+I35+J35+K35+L35+M35+N35)*0.005 -> 10.7368 | O36: =(C35+D35+E35+F35+G35+H35+I35+J35+K35+L35+M35+N35+O35)*0.005 -> 10.7368
S37: Page 1 of 2
B41: TOTAL | C41: =SUM(C10:C40) -> 21103.7 | D41: =SUM(D10:D40) -> 68.0618 | E41: =SUM(E10:E40) -> #REF! | F41: =SUM(F10:F40) -> #REF! | G41: =SUM(G10:G40) -> #REF! | H41: =SUM(H10:H40) -> #REF! | I41: =SUM(I10:I40) -> #REF! | J41: =SUM(J10:J40) -> #REF! | ... S41: =SUM(S10:S40) -> 23326.73
A43: Prepared by: | E43: Checked by: | K43: Noted by: | P43: Approved by:
B46: SHALOU J. BALAO | F46: MARIA GENIA C. SEGUIDO | L46: ARNOLD C. GONZALES | Q46: DEXTER B. JUMAO-AS
B47: SCSCC Secretary | F47: SCSCC Treasurer | L47: General Manager, SCSCC | Q47: Chairman, SCSCC BOD
S50: Page 2 of 2
P54: Regular | Q54: =18 -> 18 | R54: =S10+S13+S15+S17+S19+S21+S23+S25+S27+S29+S31+S33+#REF!+#REF!+#REF!+#REF!+#REF!+S35 -> #REF!
P55: Associates | Q55: 11 | R55: =#REF!+#REF!+#REF!+#REF!+#REF!+#REF!+#REF!+#REF!+#REF!+#REF!+#REF! -> #REF!
Q56: =Q54+Q55 -> 29 | R56: =R54+R55 -> #REF!

Sheet KIDDY2023
A2: SIDLAK CHRISTIAN CHILDREN FUND SAVINGS AND CREDIT COOPERATIVE
A3: CDA Registration No. 9520-1080000000036399 Dated: November 16, 2016
A4: P-2, Brgy. Linao, Ormoc City
A6: COMPUTATION OF SAVINGS DEPOSITS
A7: As of FY 2021
C9: 2022 Savings | D9: Jan | E9: Feb | F9: Mar | G9: Apr | H9: May | I9: Jun | J9: withdrawal | K9: Jul | L9: Aug | M9: Sep | N9: Oct | O9: Nov | P9: Dec | Q9: TSAD | R9: ASAD | S9: Int. on TSAD | T9: Total (SAD + Interest)
A10: 1 | B10: Cort Wensley J. Balao | C10: =2392.7+139.99 -> 2532.69 | E10: 0 | F10: 0 | G10: 0 | H10: 0 | I10: 0 | K10: 0 | L10: 0 | M10: 0 | N10: 0 | O10: 0 | Q10: =C10+D10+E10+F10+G10+H10+I10+K10+L10+M10+N10+O10+P10 -> 2532.69 | R10: =Q10/12 -> 211.0575 | S10: =D11+E11+F11+G11+H11+I11+K11+L11+M11+N11+O11+P11 -> 147.68795 | T10: =Q10+S10 -> 2680.378
C11: Interest per mo. | D11: 8.39 | E11: =(C10+D10+E10)*0.005 -> 12.66345 | F11: =(+C10+D10+E10+F10)*0.005 -> 12.66345 | G11: =(C10+D10+E10+F10+G10)*0.005 -> 12.66345 | H11: =(C10+D10+E10+F10+G10+H10)*0.005 -> 12.66345 | I11: =(C10+D10+E10+F10+G10+H10+I10)*0.005 -> 12.66345 | K11: =(C10+D10+E10+F10+G10+H10+I10+K10)*0.005 -> 12.66345 | L11: =(C10+D10+E10+F10+G10+H10+I10+K10+L10)*0.005 -> 12.66345 | M11: =(C10+D10+E10+F10+G10+H10+I10+K10+L10+M10)*0.005 -> 12.66345 | N11: =(C10+D10+E10+F10+G10+H10+I10+K10+L10+M10+N10)*0.005 -> 12.66345 | O11: =(C10+D10+E10+F10+G10+H10+I10+K10+L10+M10+N10+O10)*0.005 -> 12.66345 | P11: =(C10+D10+E10+F10+G10+H10+I10+K10+L10+M10+N10+O10+P10)*0.005 -> 12.66345
A12: 2 | B12: Brett Colin J. Balao | C12: 2502.84
C13: Interest per mo.
A14: 3 | B14: Demian Sabin C. Jumao-as | C14: =6917.9+405.53 -> 7323.43 | D14: 0 | E14: 0 | F14: 500 | G14: 0 | H14: 0 | I14: 0 | K14: 0 | L14: 0 | M14: 0 | N14: 0 | O14: 0 | Q14: =C14+D14+E14+F14+G14+H14+I14+K14+L14+M14+N14+O14+P14 -> 7823.43 | R14: =Q14/12 -> 651.9525 | S14: =D15+E15+F15+G15+H15+I15+K15+L15+M15+N15+O15+P15 -> 452.83865 | T14: =Q14+S14 -> 8276.2686
C15: Interest per mo. | D15: 25.05 | E15: =(C14+D14+E14)*0.005 -> 36.61715 | F15: =(+C14+D14+E14+F14)*0.005 -> 39.11715 | G15: =(C14+D14+E14+F14+G14)*0.005 -> 39.11715 | H15: =(C14+D14+E14+F14+G14+H14)*0.005 -> 39.11715 | I15: =(C14+D14+E14+F14+G14+H14+I14)*0.005 -> 39.11715 | K15: =(C14+D14+E14+F14+G14+H14+I14+K14)*0.005 -> 39.11715 | L15: =(C14+D14+E14+F14+G14+H14+I14+K14+L14)*0.005 -> 39.11715 | M15: =(C14+D14+E14+F14+G14+H14+I14+K14+L14+M14)*0.005 -> 39.11715 | N15: =(C14+D14+E14+F14+G14+H14+I14+K14+L14+M14+N14)*0.005 -> 39.11715 | O15: =(C14+D14+E14+F14+G14+H14+I14+K14+L14+M14+N14+O14)*0.005 -> 39.11715 | P15: =(C14+D14+E14+F14+G14+H14+I14+K14+L14+M14+N14+O14+P14)*0.005 -> 39.11715
A16: 4 | B16: Izy Kaizer J. Balao | C16: =3596.59+211.16 -> 3807.75 | E16: =420+200 -> 620 | F16: 0 | G16: 0 | H16: 0 | I16: 0 | K16: 0 | L16: 0 | M16: 0 | N16: 0 | O16: 0 | P16: 0 | Q16: =C16+D16+E16+F16+G16+H16+I16+K16+L16+M16+N16+O16+P16 -> 4427.75 | R16: =Q16/12 -> 368.97917 | S16: =D17+E17+F17+G17+H17+I17+K17+L17+M17+N17+O17+P17 -> 256.87625 | T16: =Q16+S16 -> 4684.6263
C17: Interest per mo. | D17: 13.35 | E17: =(C16+D16+E16)*0.005 -> 22.13875 | F17: =(+C16+D16+E16+F16)*0.005 -> 22.13875 | G17: =(C16+D16+E16+F16+G16)*0.005 -> 22.13875 | H17: =(C16+D16+E16+F16+G16+H16)*0.005 -> 22.13875 | I17: =(C16+D16+E16+F16+G16+H16+I16)*0.005 -> 22.13875 | K17: =(C16+D16+E16+F16+G16+H16+I16+K16)*0.005 -> 22.13875 | L17: =(C16+D16+E16+F16+G16+H16+I16+K16+L16)*0.005 -> 22.13875 | M17: =(C16+D16+E16+F16+G16+H16+I16+K16+L16+M16)*0.005 -> 22.13875 | N17: =(C16+D16+E16+F16+G16+H16+I16+K16+L16+M16+N16)*0.005 -> 22.13875 | O17: =(C16+D16+E16+F16+G16+H16+I16+K16+L16+M16+N16+O16)*0.005 -> 22.13875 | P17: =(C16+D16+E16+F16+G16+H16+I16+K16+L16+M16+N16+O16+P16)*0.005 -> 22.13875
A18: 5 | B18: Alerc Finlay J. Balao | C18: =2920.42+158.12 -> 3078.54 | E18: 900 | G18: 0 | H18: 0 | I18: 0 | K18: 1000 | L18: 0 | M18: 0 | N18: 0 | O18: 0 | P18: 0 | Q18: =C18+D18+E18+F18+G18+H18+I18+K18+L18+M18+N18+O18+P18 -> 4978.54 | R18: =Q18/12 -> 414.87833 | S18: =D19+E19+F19+G19+H19+I19+K19+L19+M19+N19+O19+P19 -> 248.8197 | T18: =Q18+S18 -> 5227.3597
C19: Interest per mo. | E19: =(C18+D18+E18)*0.005 -> 19.8927 | F19: =(+C18+D18+E18+F18)*0.005 -> 19.8927 | G19: =(C18+D18+E18+F18+G18)*0.005 -> 19.8927 | H19: =(C18+D18+E18+F18+G18+H18)*0.005 -> 19.8927 | I19: =(C18+D18+E18+F18+G18+H18+I18)*0.005 -> 19.8927 | K19: =(C18+D18+E18+F18+G18+H18+I18+K18)*0.005 -> 24.8927 | L19: =(C18+D18+E18+F18+G18+H18+I18+K18+L18)*0.005 -> 24.8927 | M19: =(C18+D18+E18+F18+G18+H18+I18+K18+L18+M18)*0.005 -> 24.8927 | N19: =(C18+D18+E18+F18+G18+H18+I18+K18+L18+M18+N18)*0.005 -> 24.8927 | O19: =(C18+D18+E18+F18+G18+H18+I18+K18+L18+M18+N18+O18)*0.005 -> 24.8927 | P19: =(C18+D18+E18+F18+G18+H18+I18+K18+L18+M18+N18+O18+P18)*0.005 -> 24.8927
A20: 6 | B20: Georgette Ann Cabahug | C20: 50 | D20: 0 | Q20: 50 | R20: =Q20/12 -> 4.1666667 | T20: =Q20+S20 -> 50
C21: Interest per mo. | D21: =(C20+D20)*0.005 -> 0.25 | E21: =(C20+D20+E20)*0.005 -> 0.25 | F21: =(+C20+D20+E20+F20)*0.005 -> 0.25 | G21: =(C20+D20+E20+F20+G20)*0.005 -> 0.25 | H21: =(C20+D20+E20+F20+G20+H20)*0.005 -> 0.25 | I21: =(C20+D20+E20+F20+G20+H20+I20)*0.005 -> 0.25 | K21: =(C20+D20+E20+F20+G20+H20+I20+K20)*0.005 -> 0.25 | L21: =(C20+D20+E20+F20+G20+H20+I20+K20+L20)*0.005 -> 0.25 | M21: =(C20+D20+E20+F20+G20+H20+I20+K20+L20+M20)*0.005 -> 0.25 | N21: =(C20+D20+E20+F20+G20+H20+I20+K20+L20+M20+N20)*0.005 -> 0.25 | O21: =(C20+D20+E20+F20+G20+H20+I20+K20+L20+M20+N20+O20)*0.005 -> 0.25 | P21: =(C20+D20+E20+F20+G20+H20+I20+K20+L20+M20+N20+O20+P20)*0.005 -> 0.25
A22: 7 | B22: Luna Mikaela C. Apay | C22: 50 | D22: 0 | Q22: =C22+D22+E22+F22+G22+H22+I22+K22+L22+M22+N22+O22+P22 -> 50 | R22: =Q22/12 -> 4.1666667 | T22: =Q22+S22 -> 50
C23: Interest per mo. | D23: =(C22+D22)*0.005 -> 0.25 | E23: =(C22+D22+E22)*0.005 -> 0.25 | F23: =(+C22+D22+E22+F22)*0.005 -> 0.25 | G23: =(C22+D22+E22+F22+G22)*0.005 -> 0.25 | H23: =(C22+D22+E22+F22+G22+H22)*0.005 -> 0.25 | I23: =(C22+D22+E22+F22+G22+H22+I22)*0.005 -> 0.25 | K23: =(C22+D22+E22+F22+G22+H22+I22+K22)*0.005 -> 0.25 | L23: =(C22+D22+E22+F22+G22+H22+I22+K22+L22)*0.005 -> 0.25 | M23: =(C22+D22+E22+F22+G22+H22+I22+K22+L22+M22)*0.005 -> 0.25 | N23: =(C22+D22+E22+F22+G22+H22+I22+K22+L22+M22+N22)*0.005 -> 0.25 | O23: =(C22+D22+E22+F22+G22+H22+I22+K22+L22+M22+N22+O22)*0.005 -> 0.25 | P23: =(C22+D22+E22+F22+G22+H22+I22+K22+L22+M22+N22+O22+P22)*0.005 -> 0.25
A24: 8 | B24: Mikko Angelo C. Apay | C24: 50 | D24: 0 | Q24: =C24+D24+E24+F24+G24+H24+I24+K24+L24+M24+N24+O24+P24 -> 50 | R24: =Q24/12 -> 4.1666667 | T24: =Q24+S24 -> 50
C25: Interest per mo. | D25: =(C24+D24)*0.005 -> 0.25 | E25: =(C24+D24+E24)*0.005 -> 0.25 | F25: =(+C24+D24+E24+F24)*0.005 -> 0.25 | G25: =(C24+D24+E24+F24+G24)*0.005 -> 0.25 | H25: =(C24+D24+E24+F24+G24+H24)*0.005 -> 0.25 | I25: =(C24+D24+E24+F24+G24+H24+I24)*0.005 -> 0.25 | K25: =(C24+D24+E24+F24+G24+H24+I24+K24)*0.005 -> 0.25 | L25: =(C24+D24+E24+F24+G24+H24+I24+K24+L24)*0.005 -> 0.25 | M25: =(C24+D24+E24+F24+G24+H24+I24+K24+L24+M24)*0.005 -> 0.25 | N25: =(C24+D24+E24+F24+G24+H24+I24+K24+L24+M24+N24)*0.005 -> 0.25 | O25: =(C24+D24+E24+F24+G24+H24+I24+K24+L24+M24+N24+O24)*0.005 -> 0.25 | P25: =(C24+D24+E24+F24+G24+H24+I24+K24+L24+M24+N24+O24+P24)*0.005 -> 0.25
A26: 9 | B26: Casy Marie D. Cruz | C26: =730.83+18.27 -> 749.1 | I26: 0 | O26: 0 | Q26: =C26+D26+E26+F26+G26+H26+I26+K26+L26+M26+N26+O26+P26 -> 749.1 | R26: =Q26/12 -> 62.425 | S26: =D27+E27+F27+G27+H27+I27+K27+L27+M27+N27+O27+P27 -> 18.7275 | T26: =Q26+S26 -> 767.8275
C27: Interest per mo. | L27: =(C26+D26+E26+F26+G26+H26+I26+K26+L26)*0.005 -> 3.7455 | M27: =(C26+D26+E26+F26+G26+H26+I26+K26+L26+M26)*0.005 -> 3.7455 | N27: =(C26+D26+E26+F26+G26+H26+I26+K26+L26+M26+N26)*0.005 -> 3.7455 | O27: =(C26+D26+E26+F26+G26+H26+I26+K26+L26+M26+N26+O26)*0.005 -> 3.7455 | P27: =(C26+D26+E26+F26+G26+H26+I26+K26+L26+M26+N26+O26+P26)*0.005 -> 3.7455
A28: 10 | B28: Marissa alvarado | C28: 50 | D28: 0 | K28: 0 | N28: 0 | Q28: =C28+D28+E28+F28+G28+H28+I28+K28+L28+M28+N28+O28+P28 -> 50 | R28: =Q28/12 -> 4.1666667 | T28: =Q28+S28 -> 50
C29: Interest per mo. | D29: =(C28+D28)*0.005 -> 0.25 | E29: =(C28+D28+E28)*0.005 -> 0.25 | F29: =(+C28+D28+E28+F28)*0.005 -> 0.25 | G29: =(C28+D28+E28+F28+G28)*0.005 -> 0.25 | H29: =(C28+D28+E28+F28+G28+H28)*0.005 -> 0.25 | I29: =(C28+D28+E28+F28+G28+H28+I28)*0.005 -> 0.25 | K29: =(C28+D28+E28+F28+G28+H28+I28+K28)*0.005 -> 0.25 | L29: =(C28+D28+E28+F28+G28+H28+I28+K28+L28)*0.005 -> 0.25 | M29: =(C28+D28+E28+F28+G28+H28+I28+K28+L28+M28)*0.005 -> 0.25 | N29: =(C28+D28+E28+F28+G28+H28+I28+K28+L28+M28+N28)*0.005 -> 0.25 | O29: =(C28+D28+E28+F28+G28+H28+I28+K28+L28+M28+N28+O28)*0.005 -> 0.25 | P29: =(C28+D28+E28+F28+G28+H28+I28+K28+L28+M28+N28+O28+P28)*0.005 -> 0.25
A30: 11 | B30: Krissel Alvarado | C30: 50 | D30: 0 | Q30: =C30+D30+E30+F30+G30+H30+I30+K30+L30+M30+N30+O30+P30 -> 50 | R30: =Q30/12 -> 4.1666667 | T30: =Q30+S30 -> 50
C31: Interest per mo. | D31: =(C30+D30)*0.005 -> 0.25 | E31: =(C30+D30+E30)*0.005 -> 0.25 | F31: =(+C30+D30+E30+F30)*0.005 -> 0.25 | G31: =(C30+D30+E30+F30+G30)*0.005 -> 0.25 | H31: =(C30+D30+E30+F30+G30+H30)*0.005 -> 0.25 | I31: =(C30+D30+E30+F30+G30+H30+I30)*0.005 -> 0.25 | K31: =(C30+D30+E30+F30+G30+H30+I30+K30)*0.005 -> 0.25 | L31: =(C30+D30+E30+F30+G30+H30+I30+K30+L30)*0.005 -> 0.25 | M31: =(C30+D30+E30+F30+G30+H30+I30+K30+L30+M30)*0.005 -> 0.25 | N31: =(C30+D30+E30+F30+G30+H30+I30+K30+L30+M30+N30)*0.005 -> 0.25 | O31: =(C30+D30+E30+F30+G30+H30+I30+K30+L30+M30+N30+O30)*0.005 -> 0.25 | P31: =(C30+D30+E30+F30+G30+H30+I30+K30+L30+M30+N30+O30+P30)*0.005 -> 0.25
A32: 12 | B32: Serg Mateo M. Villamor | C32: =2952.9+162.41 -> 3115.31 | D32: 0 | E32: 0 | F32: 0 | J32: 2000 | K32: 0 | L32: 0 | M32: 0 | N32: 0 | O32: 0 | P32: 0 | Q32: =C32+D32+E32+F32+G32+H32+I32+K32+L32+M32+N32+O32+P32-J32 -> 1115.31 | R32: =Q32/12 -> 92.9425 | S32: =D33+E33+F33+G33+H33+I33+K33+L33+M33+N33+O33+P33 -> 171.34205 | T32: =Q32+S32 -> 1286.652
C33: Interest per mo. | E33: =(C32+D32+E32)*0.005 -> 15.57655 | F33: =(+C32+D32+E32+F32)*0.005 -> 15.57655 | G33: =(C32+D32+E32+F32+G32)*0.005 -> 15.57655 | H33: =(C32+D32+E32+F32+G32+H32)*0.005 -> 15.57655 | I33: =(C32+D32+E32+F32+G32+H32+I32)*0.005 -> 15.57655 | K33: =(C32+D32+E32+F32+G32+H32+I32+K32)*0.005 -> 15.57655 | L33: =(C32+D32+E32+F32+G32+H32+I32+K32+L32)*0.005 -> 15.57655 | M33: =(C32+D32+E32+F32+G32+H32+I32+K32+L32+M32)*0.005 -> 15.57655 | N33: =(C32+D32+E32+F32+G32+H32+I32+K32+L32+M32+N32)*0.005 -> 15.57655 | O33: =(C32+D32+E32+F32+G32+H32+I32+K32+L32+M32+N32+O32)*0.005 -> 15.57655 | P33: =(C32+D32+E32+F32+G32+H32+I32+K32+L32+M32+N32+O32+P32)*0.005 -> 15.57655
A34: 13 | B34: Rica M. Cruz | C34: 200 | D34: 0 | E34: 0 | F34: 0 | M34: 0 | Q34: =C34+D34+E34+F34+G34+H34+I34+K34+L34+M34+N34+O34+P34 -> 200 | R34: =Q34/12 -> 16.666667 | T34: =Q34+S34 -> 200
C35: Interest per mo. | D35: =(C34+D34)*0.005 -> 1 | E35: =(C34+D34+E34)*0.005 -> 1 | F35: =(+C34+D34+E34+F34)*0.005 -> 1 | G35: =(C34+D34+E34+F34+G34)*0.005 -> 1 | H35: =(C34+D34+E34+F34+G34+H34)*0.005 -> 1 | I35: =(C34+D34+E34+F34+G34+H34+I34)*0.005 -> 1 | K35: =(C34+D34+E34+F34+G34+H34+I34+K34)*0.005 -> 1 | L35: =(C34+D34+E34+F34+G34+H34+I34+K34+L34)*0.005 -> 1 | M35: =(C34+D34+E34+F34+G34+H34+I34+K34+L34+M34)*0.005 -> 1 | N35: =(C34+D34+E34+F34+G34+H34+I34+K34+L34+M34+N34)*0.005 -> 1 | O35: =(C34+D34+E34+F34+G34+H34+I34+K34+L34+M34+N34+O34)*0.005 -> 1 | P35: =(C34+D34+E34+F34+G34+H34+I34+K34+L34+M34+N34+O34+P34)*0.005 -> 1
A36: 14 | B36: Yvo Rafiel Samson | C36: =2147.36+122.54 -> 2269.9 | E36: 0 | H36: 0 | I36: 0 | K36: 0 | L36: 0 | M36: 0 | N36: 0 | O36: 0 | P36: 0 | Q36: =C36+D36+E36+F36+G36+H36+I36+K36+L36+M36+N36+O36+P36 -> 2269.9 | R36: =Q36/12 -> 189.15833 | S36: =D37+E37+F37+G37+H37+I37+K37+L37+M37+N37+O37+P37 -> 136.194 | T36: =Q36+S36 -> 2406.094
C37: Interest per mo. | D37: =(C36+D36)*0.005 -> 11.3495 | E37: =(C36+D36+E36)*0.005 -> 11.3495 | F37: =(+C36+D36+E36+F36)*0.005 -> 11.3495 | G37: =(C36+D36+E36+F36+G36)*0.005 -> 11.3495 | H37: =(C36+D36+E36+F36+G36+H36)*0.005 -> 11.3495 | I37: =(C36+D36+E36+F36+G36+H36+I36)*0.005 -> 11.3495 | K37: =(C36+D36+E36+F36+G36+H36+I36+K36)*0.005 -> 11.3495 | L37: =(C36+D36+E36+F36+G36+H36+I36+K36+L36)*0.005 -> 11.3495 | M37: =(C36+D36+E36+F36+G36+H36+I36+K36+L36+M36)*0.005 -> 11.3495 | N37: =(C36+D36+E36+F36+G36+H36+I36+K36+L36+M36+N36)*0.005 -> 11.3495 | O37: =(C36+D36+E36+F36+G36+H36+I36+K36+L36+M36+N36+O36)*0.005 -> 11.3495 | P37: =(C36+D36+E36+F36+G36+H36+I36+K36+L36+M36+N36+O36+P36)*0.005 -> 11.3495
T38: Page 1 of 2
B42: TOTAL | C42: =SUM(C10:C41) -> 25829.56 | D42: =SUM(D10:D41) -> 60.3895 | E42: =SUM(E10:E41) -> 1640.4881 | F42: =SUM(F10:F41) -> 622.9881 | G42: =SUM(G10:G41) -> 122.9881 | H42: =SUM(H10:H41) -> 122.9881 | I42: =SUM(I10:I41) -> 122.9881 | K42: =SUM(K10:K41) -> 1127.9881 | L42: =SUM(L10:L41) -> 131.7336 | M42: =SUM(M10:M41) -> 131.7336 | N42: =SUM(N10:N41) -> 131.7336 | O42: =SUM(O10:O41) -> 131.7336 | P42: =SUM(P10:P41) -> 131.7336 | Q42: =SUM(Q10:Q41) -> 24346.72 | R42: =SUM(R10:R41) -> 2028.8933 | ... T42: =SUM(T10:T41) -> 25779.206
A44: Prepared by: | E44: Checked by: | L44: Noted by: | Q44: Approved by:
B47: SHALOU J. BALAO | F47: MARIA GENIA C. SEGUIDO | M47: ARNOLD C. GONZALES | R47: DEXTER B. JUMAO-AS
B48: SCSCC Secretary | F48: SCSCC Treasurer | M48: General Manager, SCSCC | R48: Chairman, SCSCC BOD
T51: Page 2 of 2
Q55: Regular | R55: =18 -> 18 | S55: =T10+T14+T16+T18+T20+T22+T24+T26+T28+T30+T32+T34+#REF!+#REF!+#REF!+#REF!+#REF!+T36 -> #REF!
Q56: Associates | R56: 11 | S56: =#REF!+#REF!+#REF!+#REF!+#REF!+#REF!+#REF!+#REF!+#REF!+#REF!+#REF! -> #REF!
R57: =R55+R56 -> 29 | S57: =S55+S56 -> #REF!

Sheet KIDDY2024
A2: SIDLAK CHRISTIAN CHILDREN FUND SAVINGS AND CREDIT COOPERATIVE
A3: CDA Registration No. 9520-1080000000036399 Dated: November 16, 2016
A4: P-2, Brgy. Linao, Ormoc City
A6: COMPUTATION OF SAVINGS DEPOSITS
A7: As of FY 2024
C9: 2023Savings | D9: Jan | E9: Feb | F9: Mar | G9: Apr | H9: May | I9: Jun | J9: Jul | K9: Aug | L9: Sep | M9: Oct | N9: Nov | O9: Dec | P9: TSAD | Q9: ASAD | R9: Int. on TSAD | S9: Total (SAD + Interest)
A10: 1 | B10: Cort Wensley J. Balao | C10: 2684.65 | D10: 0 | E10: 0 | F10: 0 | G10: 0 | H10: 0 | I10: 0 | J10: 0 | K10: 0 | L10: 0 | M10: 0 | N10: 0 | P10: =C10+D10+E10+F10+G10+H10+I10+J10+K10+L10+M10+N10+O10 -> 2684.65 | Q10: =P10/12 -> 223.72083 | R10: =D11+E11+F11+G11+H11+I11+J11+K11+L11+M11+N11+O11 -> 160.31575 | S10: =P10+R10 -> 2844.9657
C11: Interest per mo. | D11: 12.66 | E11: =(C10+D10+E10)*0.005 -> 13.42325 | F11: =(+C10+D10+E10+F10)*0.005 -> 13.42325 | G11: =(C10+D10+E10+F10+G10)*0.005 -> 13.42325 | H11: =(C10+D10+E10+F10+G10+H10)*0.005 -> 13.42325 | I11: =(C10+D10+E10+F10+G10+H10+I10)*0.005 -> 13.42325 | J11: =(C10+D10+E10+F10+G10+H10+I10+J10)*0.005 -> 13.42325 | K11: =(C10+D10+E10+F10+G10+H10+I10+J10+K10)*0.005 -> 13.42325 | L11: =(C10+D10+E10+F10+G10+H10+I10+J10+K10+L10)*0.005 -> 13.42325 | M11: =(C10+D10+E10+F10+G10+H10+I10+J10+K10+L10+M10)*0.005 -> 13.42325 | N11: =(C10+D10+E10+F10+G10+H10+I10+J10+K10+L10+M10+N10)*0.005 -> 13.42325 | O11: =(C10+D10+E10+F10+G10+H10+I10+J10+K10+L10+M10+N10+O10)*0.005 -> 13.42325
A12: 2 | B12: Brett Colin J. Balao | C12: 2653.01 | P12: =C12+D12+E12+F12+G12+H12+I12+J12+K12+L12+M12+N12+O12 -> 2653.01 | Q12: =P12/12 -> 221.08417 | R12: =D13+E13+F13+G13+H13+I13+J13+K13+L13+M13+N13+O13 -> 159.1806 | S12: =P12+R12 -> 2812.1906
C13: Interest per mo. | D13: =(C12+D12)*0.005 -> 13.26505 | E13: =(C12+D12+E12)*0.005 -> 13.26505 | F13: =(+C12+D12+E12+F12)*0.005 -> 13.26505 | G13: =(C12+D12+E12+F12+G12)*0.005 -> 13.26505 | H13: =(C12+D12+E12+F12+G12+H12)*0.005 -> 13.26505 | I13: =(C12+D12+E12+F12+G12+H12+I12)*0.005 -> 13.26505 | J13: =(C12+D12+E12+F12+G12+H12+I12+J12)*0.005 -> 13.26505 | K13: =(C12+D12+E12+F12+G12+H12+I12+J12+K12)*0.005 -> 13.26505 | L13: =(C12+D12+E12+F12+G12+H12+I12+J12+K12+L12)*0.005 -> 13.26505 | M13: =(C12+D12+E12+F12+G12+H12+I12+J12+K12+L12+M12)*0.005 -> 13.26505 | N13: =(C12+D12+E12+F12+G12+H12+I12+J12+K12+L12+M12+N12)*0.005 -> 13.26505 | O13: =(C12+D12+E12+F12+G12+H12+I12+J12+K12+L12+M12+N12+O12)*0.005 -> 13.26505
A14: 3 | B14: Demian Sabin C. Jumao-as | C14: 8287.84 | D14: 0 | E14: 0 | G14: 0 | H14: 0 | I14: 0 | J14: 0 | K14: 0 | L14: 0 | M14: 0 | N14: 0 | P14: =C14+D14+E14+F14+G14+H14+I14+J14+K14+L14+M14+N14+O14 -> 8287.84 | Q14: =P14/12 -> 690.65333 | R14: =D15+E15+F15+G15+H15+I15+J15+K15+L15+M15+N15+O15 -> 497.2704 | S14: =P14+R14 -> 8785.1104
C15: Interest per mo. | D15: =(C14+D14)*0.005 -> 41.4392 | E15: =(C14+D14+E14)*0.005 -> 41.4392 | F15: =(+C14+D14+E14+F14)*0.005 -> 41.4392 | G15: =(C14+D14+E14+F14+G14)*0.005 -> 41.4392 | H15: =(C14+D14+E14+F14+G14+H14)*0.005 -> 41.4392 | I15: =(C14+D14+E14+F14+G14+H14+I14)*0.005 -> 41.4392 | J15: =(C14+D14+E14+F14+G14+H14+I14+J14)*0.005 -> 41.4392 | K15: =(C14+D14+E14+F14+G14+H14+I14+J14+K14)*0.005 -> 41.4392 | L15: =(C14+D14+E14+F14+G14+H14+I14+J14+K14+L14)*0.005 -> 41.4392 | M15: =(C14+D14+E14+F14+G14+H14+I14+J14+K14+L14+M14)*0.005 -> 41.4392 | N15: =(C14+D14+E14+F14+G14+H14+I14+J14+K14+L14+M14+N14)*0.005 -> 41.4392 | O15: =(C14+D14+E14+F14+G14+H14+I14+J14+K14+L14+M14+N14+O14)*0.005 -> 41.4392
A16: 4 | B16: Izy Kaizer J. Balao | C16: 4690.32 | F16: 0 | G16: 0 | H16: 0 | I16: 0 | J16: 0 | K16: 0 | L16: 0 | M16: 0 | N16: 0 | O16: 1000 | P16: =C16+D16+E16+F16+G16+H16+I16+J16+K16+L16+M16+N16+O16 -> 5690.32 | Q16: =P16/12 -> 474.19333 | R16: =D17+E17+F17+G17+H17+I17+J17+K17+L17+M17+N17+O17 -> 286.4192 | S16: =P16+R16 -> 5976.7392
C17: Interest per mo. | D17: =(C16+D16)*0.005 -> 23.4516 | E17: =(C16+D16+E16)*0.005 -> 23.4516 | F17: =(+C16+D16+E16+F16)*0.005 -> 23.4516 | G17: =(C16+D16+E16+F16+G16)*0.005 -> 23.4516 | H17: =(C16+D16+E16+F16+G16+H16)*0.005 -> 23.4516 | I17: =(C16+D16+E16+F16+G16+H16+I16)*0.005 -> 23.4516 | J17: =(C16+D16+E16+F16+G16+H16+I16+J16)*0.005 -> 23.4516 | K17: =(C16+D16+E16+F16+G16+H16+I16+J16+K16)*0.005 -> 23.4516 | L17: =(C16+D16+E16+F16+G16+H16+I16+J16+K16+L16)*0.005 -> 23.4516 | M17: =(C16+D16+E16+F16+G16+H16+I16+J16+K16+L16+M16)*0.005 -> 23.4516 | N17: =(C16+D16+E16+F16+G16+H16+I16+J16+K16+L16+M16+N16)*0.005 -> 23.4516 | O17: =(C16+D16+E16+F16+G16+H16+I16+J16+K16+L16+M16+N16+O16)*0.005 -> 28.4516
A18: 5 | B18: Alec Finlay J. Balao | C18: 4212.76 | E18: 600 | G18: 0 | H18: 0 | I18: 0 | K18: 0 | L18: 0 | M18: 0 | N18: 0 | O18: 600 | P18: =C18+D18+E18+F18+G18+H18+I18+J18+K18+L18+M18+N18+O18 -> 5412.76 | Q18: =P18/12 -> 451.06333 | R18: =D19+E19+F19+G19+H19+I19+J19+K19+L19+M19+N19+O19 -> 288.7656 | S18: =P18+R18 -> 5701.5256
C19: Interest per mo. | D19: =(C18+D18)*0.005 -> 21.0638 | E19: =(C18+D18+E18)*0.005 -> 24.0638 | F19: =(+C18+D18+E18+F18)*0.005 -> 24.0638 | G19: =(C18+D18+E18+F18+G18)*0.005 -> 24.0638 | H19: =(C18+D18+E18+F18+G18+H18)*0.005 -> 24.0638 | I19: =(C18+D18+E18+F18+G18+H18+I18)*0.005 -> 24.0638 | J19: =(C18+D18+E18+F18+G18+H18+I18+J18)*0.005 -> 24.0638 | K19: =(C18+D18+E18+F18+G18+H18+I18+J18+K18)*0.005 -> 24.0638 | L19: =(C18+D18+E18+F18+G18+H18+I18+J18+K18+L18)*0.005 -> 24.0638 | M19: =(C18+D18+E18+F18+G18+H18+I18+J18+K18+L18+M18)*0.005 -> 24.0638 | N19: =(C18+D18+E18+F18+G18+H18+I18+J18+K18+L18+M18+N18)*0.005 -> 24.0638 | O19: =(C18+D18+E18+F18+G18+H18+I18+J18+K18+L18+M18+N18+O18)*0.005 -> 27.0638
A20: 6 | B20: Georgette Ann Cabahug | C20: 50 | D20: 0 | P20: 50 | Q20: =P20/12 -> 4.1666667 | S20: =P20+R20 -> 50
C21: Interest per mo. | D21: =(C20+D20)*0.005 -> 0.25 | E21: =(C20+D20+E20)*0.005 -> 0.25 | F21: =(+C20+D20+E20+F20)*0.005 -> 0.25 | G21: =(C20+D20+E20+F20+G20)*0.005 -> 0.25 | H21: =(C20+D20+E20+F20+G20+H20)*0.005 -> 0.25 | I21: =(C20+D20+E20+F20+G20+H20+I20)*0.005 -> 0.25 | J21: =(C20+D20+E20+F20+G20+H20+I20+J20)*0.005 -> 0.25 | K21: =(C20+D20+E20+F20+G20+H20+I20+J20+K20)*0.005 -> 0.25 | L21: =(C20+D20+E20+F20+G20+H20+I20+J20+K20+L20)*0.005 -> 0.25 | M21: =(C20+D20+E20+F20+G20+H20+I20+J20+K20+L20+M20)*0.005 -> 0.25 | N21: =(C20+D20+E20+F20+G20+H20+I20+J20+K20+L20+M20+N20)*0.005 -> 0.25 | O21: =(C20+D20+E20+F20+G20+H20+I20+J20+K20+L20+M20+N20+O20)*0.005 -> 0.25
A22: 7 | B22: Luna Mikaela C. Apay | C22: 50 | D22: 0 | P22: =C22+D22+E22+F22+G22+H22+I22+J22+K22+L22+M22+N22+O22 -> 50 | Q22: =P22/12 -> 4.1666667 | S22: =P22+R22 -> 50
C23: Interest per mo. | D23: =(C22+D22)*0.005 -> 0.25 | E23: =(C22+D22+E22)*0.005 -> 0.25 | F23: =(+C22+D22+E22+F22)*0.005 -> 0.25 | G23: =(C22+D22+E22+F22+G22)*0.005 -> 0.25 | H23: =(C22+D22+E22+F22+G22+H22)*0.005 -> 0.25 | I23: =(C22+D22+E22+F22+G22+H22+I22)*0.005 -> 0.25 | J23: =(C22+D22+E22+F22+G22+H22+I22+J22)*0.005 -> 0.25 | K23: =(C22+D22+E22+F22+G22+H22+I22+J22+K22)*0.005 -> 0.25 | L23: =(C22+D22+E22+F22+G22+H22+I22+J22+K22+L22)*0.005 -> 0.25 | M23: =(C22+D22+E22+F22+G22+H22+I22+J22+K22+L22+M22)*0.005 -> 0.25 | N23: =(C22+D22+E22+F22+G22+H22+I22+J22+K22+L22+M22+N22)*0.005 -> 0.25 | O23: =(C22+D22+E22+F22+G22+H22+I22+J22+K22+L22+M22+N22+O22)*0.005 -> 0.25
A24: 8 | B24: Mikko Angelo C. Apay | C24: 50 | D24: 0 | P24: =C24+D24+E24+F24+G24+H24+I24+J24+K24+L24+M24+N24+O24 -> 50 | Q24: =P24/12 -> 4.1666667 | S24: =P24+R24 -> 50
C25: Interest per mo. | D25: =(C24+D24)*0.005 -> 0.25 | E25: =(C24+D24+E24)*0.005 -> 0.25 | F25: =(+C24+D24+E24+F24)*0.005 -> 0.25 | G25: =(C24+D24+E24+F24+G24)*0.005 -> 0.25 | H25: =(C24+D24+E24+F24+G24+H24)*0.005 -> 0.25 | I25: =(C24+D24+E24+F24+G24+H24+I24)*0.005 -> 0.25 | J25: =(C24+D24+E24+F24+G24+H24+I24+J24)*0.005 -> 0.25 | K25: =(C24+D24+E24+F24+G24+H24+I24+J24+K24)*0.005 -> 0.25 | L25: =(C24+D24+E24+F24+G24+H24+I24+J24+K24+L24)*0.005 -> 0.25 | M25: =(C24+D24+E24+F24+G24+H24+I24+J24+K24+L24+M24)*0.005 -> 0.25 | N25: =(C24+D24+E24+F24+G24+H24+I24+J24+K24+L24+M24+N24)*0.005 -> 0.25 | O25: =(C24+D24+E24+F24+G24+H24+I24+J24+K24+L24+M24+N24+O24)*0.005 -> 0.25
A26: 9 | B26: Casy Marie D. Cruz | C26: 794.05 | I26: 0 | N26: 0 | P26: =C26+D26+E26+F26+G26+H26+I26+J26+K26+L26+M26+N26+O26 -> 794.05 | Q26: =P26/12 -> 66.170833 | R26: =D27+E27+F27+G27+H27+I27+J27+K27+L27+M27+N27+O27 -> 47.643 | S26: =P26+R26 -> 841.693
C27: Interest per mo. | D27: =(C26+D26)*0.005 -> 3.97025 | E27: =(C26+D26+E26)*0.005 -> 3.97025 | F27: =(+C26+D26+E26+F26)*0.005 -> 3.97025 | G27: =(C26+D26+E26+F26+G26)*0.005 -> 3.97025 | H27: =(C26+D26+E26+F26+G26+H26)*0.005 -> 3.97025 | I27: =(C26+D26+E26+F26+G26+H26+I26)*0.005 -> 3.97025 | J27: =(C26+D26+E26+F26+G26+H26+I26+J26)*0.005 -> 3.97025 | K27: =(C26+D26+E26+F26+G26+H26+I26+J26+K26)*0.005 -> 3.97025 | L27: =(C26+D26+E26+F26+G26+H26+I26+J26+K26+L26)*0.005 -> 3.97025 | M27: =(C26+D26+E26+F26+G26+H26+I26+J26+K26+L26+M26)*0.005 -> 3.97025 | N27: =(C26+D26+E26+F26+G26+H26+I26+J26+K26+L26+M26+N26)*0.005 -> 3.97025 | O27: =(C26+D26+E26+F26+G26+H26+I26+J26+K26+L26+M26+N26+O26)*0.005 -> 3.97025
A28: 10 | B28: Marissa alvarado | C28: 50 | D28: 0 | J28: 0 | M28: 0 | P28: =C28+D28+E28+F28+G28+H28+I28+J28+K28+L28+M28+N28+O28 -> 50 | Q28: =P28/12 -> 4.1666667 | S28: =P28+R28 -> 50
C29: Interest per mo. | D29: =(C28+D28)*0.005 -> 0.25 | E29: =(C28+D28+E28)*0.005 -> 0.25 | F29: =(+C28+D28+E28+F28)*0.005 -> 0.25 | G29: =(C28+D28+E28+F28+G28)*0.005 -> 0.25 | H29: =(C28+D28+E28+F28+G28+H28)*0.005 -> 0.25 | I29: =(C28+D28+E28+F28+G28+H28+I28)*0.005 -> 0.25 | J29: =(C28+D28+E28+F28+G28+H28+I28+J28)*0.005 -> 0.25 | K29: =(C28+D28+E28+F28+G28+H28+I28+J28+K28)*0.005 -> 0.25 | L29: =(C28+D28+E28+F28+G28+H28+I28+J28+K28+L28)*0.005 -> 0.25 | M29: =(C28+D28+E28+F28+G28+H28+I28+J28+K28+L28+M28)*0.005 -> 0.25 | N29: =(C28+D28+E28+F28+G28+H28+I28+J28+K28+L28+M28+N28)*0.005 -> 0.25 | O29: =(C28+D28+E28+F28+G28+H28+I28+J28+K28+L28+M28+N28+O28)*0.005 -> 0.25
A30: 11 | B30: Krissel Alvarado | C30: 50 | D30: 0 | P30: =C30+D30+E30+F30+G30+H30+I30+J30+K30+L30+M30+N30+O30 -> 50 | Q30: =P30/12 -> 4.1666667 | S30: =P30+R30 -> 50
C31: Interest per mo. | D31: =(C30+D30)*0.005 -> 0.25 | E31: =(C30+D30+E30)*0.005 -> 0.25 | F31: =(+C30+D30+E30+F30)*0.005 -> 0.25 | G31: =(C30+D30+E30+F30+G30)*0.005 -> 0.25 | H31: =(C30+D30+E30+F30+G30+H30)*0.005 -> 0.25 | I31: =(C30+D30+E30+F30+G30+H30+I30)*0.005 -> 0.25 | J31: =(C30+D30+E30+F30+G30+H30+I30+J30)*0.005 -> 0.25 | K31: =(C30+D30+E30+F30+G30+H30+I30+J30+K30)*0.005 -> 0.25 | L31: =(C30+D30+E30+F30+G30+H30+I30+J30+K30+L30)*0.005 -> 0.25 | M31: =(C30+D30+E30+F30+G30+H30+I30+J30+K30+L30+M30)*0.005 -> 0.25 | N31: =(C30+D30+E30+F30+G30+H30+I30+J30+K30+L30+M30+N30)*0.005 -> 0.25 | O31: =(C30+D30+E30+F30+G30+H30+I30+J30+K30+L30+M30+N30+O30)*0.005 -> 0.25
A32: 12 | B32: Serg Mateo M. Villamor | C32: 1292.23 | D32: 0 | E32: 0 | F32: 0 | J32: 0 | K32: 0 | L32: 0 | M32: 0 | N32: 0 | O32: 0 | P32: =C32+D32+E32+F32+G32+H32+I32+J32+K32+L32+M32+N32+O32 -> 1292.23 | Q32: =P32/12 -> 107.68583 | R32: =D33+E33+F33+G33+H33+I33+J33+K33+L33+M33+N33+O33 -> 71.07265 | S32: =P32+R32 -> 1363.3027
C33: Interest per mo. | E33: =(C32+D32+E32)*0.005 -> 6.46115 | F33: =(+C32+D32+E32+F32)*0.005 -> 6.46115 | G33: =(C32+D32+E32+F32+G32)*0.005 -> 6.46115 | H33: =(C32+D32+E32+F32+G32+H32)*0.005 -> 6.46115 | I33: =(C32+D32+E32+F32+G32+H32+I32)*0.005 -> 6.46115 | J33: =(C32+D32+E32+F32+G32+H32+I32+J32)*0.005 -> 6.46115 | K33: =(C32+D32+E32+F32+G32+H32+I32+J32+K32)*0.005 -> 6.46115 | L33: =(C32+D32+E32+F32+G32+H32+I32+J32+K32+L32)*0.005 -> 6.46115 | M33: =(C32+D32+E32+F32+G32+H32+I32+J32+K32+L32+M32)*0.005 -> 6.46115 | N33: =(C32+D32+E32+F32+G32+H32+I32+J32+K32+L32+M32+N32)*0.005 -> 6.46115 | O33: =(C32+D32+E32+F32+G32+H32+I32+J32+K32+L32+M32+N32+O32)*0.005 -> 6.46115
A34: 13 | B34: Rica M. Cruz | C34: 200 | D34: 0 | E34: 0 | F34: 0 | L34: 0 | P34: =C34+D34+E34+F34+G34+H34+I34+J34+K34+L34+M34+N34+O34 -> 200 | Q34: =P34/12 -> 16.666667 | S34: =P34+R34 -> 200
C35: Interest per mo. | D35: =(C34+D34)*0.005 -> 1 | E35: =(C34+D34+E34)*0.005 -> 1 | F35: =(+C34+D34+E34+F34)*0.005 -> 1 | G35: =(C34+D34+E34+F34+G34)*0.005 -> 1 | H35: =(C34+D34+E34+F34+G34+H34)*0.005 -> 1 | I35: =(C34+D34+E34+F34+G34+H34+I34)*0.005 -> 1 | J35: =(C34+D34+E34+F34+G34+H34+I34+J34)*0.005 -> 1 | K35: =(C34+D34+E34+F34+G34+H34+I34+J34+K34)*0.005 -> 1 | L35: =(C34+D34+E34+F34+G34+H34+I34+J34+K34+L34)*0.005 -> 1 | M35: =(C34+D34+E34+F34+G34+H34+I34+J34+K34+L34+M34)*0.005 -> 1 | N35: =(C34+D34+E34+F34+G34+H34+I34+J34+K34+L34+M34+N34)*0.005 -> 1 | O35: =(C34+D34+E34+F34+G34+H34+I34+J34+K34+L34+M34+N34+O34)*0.005 -> 1
A36: 14 | B36: Yvo Rafiel Samson | C36: 2406.1 | E36: 0 | H36: 0 | I36: 0 | J36: 0 | K36: 0 | L36: 0 | M36: 0 | N36: 0 | O36: 0 | P36: =C36+D36+E36+F36+G36+H36+I36+J36+K36+L36+M36+N36+O36 -> 2406.1 | Q36: =P36/12 -> 200.50833 | R36: =D37+E37+F37+G37+H37+I37+J37+K37+L37+M37+N37+O37 -> 144.366 | S36: =P36+R36 -> 2550.466
C37: Interest per mo. | D37: =(C36+D36)*0.005 -> 12.0305 | E37: =(C36+D36+E36)*0.005 -> 12.0305 | F37: =(+C36+D36+E36+F36)*0.005 -> 12.0305 | G37: =(C36+D36+E36+F36+G36)*0.005 -> 12.0305 | H37: =(C36+D36+E36+F36+G36+H36)*0.005 -> 12.0305 | I37: =(C36+D36+E36+F36+G36+H36+I36)*0.005 -> 12.0305 | J37: =(C36+D36+E36+F36+G36+H36+I36+J36)*0.005 -> 12.0305 | K37: =(C36+D36+E36+F36+G36+H36+I36+J36+K36)*0.005 -> 12.0305 | L37: =(C36+D36+E36+F36+G36+H36+I36+J36+K36+L36)*0.005 -> 12.0305 | M37: =(C36+D36+E36+F36+G36+H36+I36+J36+K36+L36+M36)*0.005 -> 12.0305 | N37: =(C36+D36+E36+F36+G36+H36+I36+J36+K36+L36+M36+N36)*0.005 -> 12.0305 | O37: =(C36+D36+E36+F36+G36+H36+I36+J36+K36+L36+M36+N36+O36)*0.005 -> 12.0305
S38: Page 1 of 2
B42: TOTAL | C42: =SUM(C10:C41) -> 27470.96 | D42: =SUM(D10:D41) -> 130.1304 | E42: =SUM(E10:E41) -> 740.3548 | F42: =SUM(F10:F41) -> 140.3548 | G42: =SUM(G10:G41) -> 140.3548 | H42: =SUM(H10:H41) -> 140.3548 | I42: =SUM(I10:I41) -> 140.3548 | J42: =SUM(J10:J41) -> 140.3548 | ... S42: =SUM(S10:S41) -> 31325.993
A44: Prepared by: | E44: Checked by: | K44: Noted by: | P44: Approved by:
B47: ARNOLD C. GONZALES | F47: TIRSO L. CAYANONG | L47: DEXTER B. JUMAO-AS | Q47: PERPETUO O. GAELO
B48: SCSCC Secretary | F48: Treasurer, SCSCC BOD | L48: General Manager, SCSCC | Q48: Chairman, SCSCC BOD
S51: Page 2 of 2
P55: Regular | Q55: =18 -> 18 | R55: =S10+S14+S16+S18+S20+S22+S24+S26+S28+S30+S32+S34+#REF!+#REF!+#REF!+#REF!+#REF!+S36 -> #REF!
P56: Associates | Q56: 11 | R56: =#REF!+#REF!+#REF!+#REF!+#REF!+#REF!+#REF!+#REF!+#REF!+#REF!+#REF! -> #REF!
Q57: =Q55+Q56 -> 29 | R57: =R55+R56 -> #REF!

Sheet Savings2020
A2: SIDLAK CHRISTIAN CHILDREN FUND SAVINGS AND CREDIT COOPERATIVE
A3: CDA Registration No. 9520-1080000000036399 Dated: November 16, 2016
A4: P-2, Brgy. Linao, Ormoc City
A6: COMPUTATION OF SAVINGS DEPOSITS
A7: As of FY 2020
A9: Members | C9: 2019 Savings | D9: Jan | E9: Feb | F9: Mar | G9: Apr | H9: withdrawal | I9: May | J9: Jun | K9: Jul | L9: Aug | M9: Sep | N9: Oct | O9: Nov | P9: Dec | Q9: withdrawal | R9: TSAD | S9: ASAD | T9: Int. on TSAD | U9: Total (SAD + Interest)
A10: 1 | B10: Allen L. Gubalane | C10: =[5]Savings2019!$U$10 -> 350.5632 | R10: =C10+D10+E10+F10+G10+I10+J10+K10+L10+M10+N10+O10+P10 -> 350.5632 | S10: =R10/12 -> 29.2136 | T10: =D11+E11+F11+G11+I11+J11+K11+L11+M11+N11+O11+P11 -> 21.033792 | U10: =R10+T10 -> 371.59699
C11: Interest per mo. | D11: =(C10+D10)*0.005 -> 1.752816 | E11: =(C10+D10+E10)*0.005 -> 1.752816 | F11: =(+C10+D10+E10+F10)*0.005 -> 1.752816 | G11: =(C10+D10+E10+F10+G10)*0.005 -> 1.752816 | I11: =(C10+D10+E10+F10+G10+I10)*0.005 -> 1.752816 | J11: =(C10+D10+E10+F10+G10+I10+J10)*0.005 -> 1.752816 | K11: =(C10+D10+E10+F10+G10+I10+J10+K10)*0.005 -> 1.752816 | L11: =(C10+D10+E10+F10+G10+I10+J10+K10+L10)*0.005 -> 1.752816 | M11: =(C10+D10+E10+F10+G10+I10+J10+K10+L10+M10)*0.005 -> 1.752816 | N11: =(C10+D10+E10+F10+G10+I10+J10+K10+L10+M10+N10)*0.005 -> 1.752816 | O11: =(C10+D10+E10+F10+G10+I10+J10+K10+L10+M10+N10+O10)*0.005 -> 1.752816 | P11: =(C10+D10+E10+F10+G10+I10+J10+K10+L10+M10+N10+O10+P10)*0.005 -> 1.752816
A12: 2 | B12: April A. Hubahib | C12: =[5]Savings2019!$U$11 -> 1067.42 | R12: =C12+D12+E12+F12+G12+I12+J12+K12+L12+M12+N12+O12+P12 -> 1067.42 | S12: =R12/12 -> 88.951667 | T12: =D13+E13+F13+G13+I13+J13+K13+L13+M13+N13+O13+P13 -> 64.0452 | U12: =R12+T12 -> 1131.4652
C13: Interest per mo. | D13: =(C12+D12)*0.005 -> 5.3371 | E13: =(C12+D12+E12)*0.005 -> 5.3371 | F13: =(+C12+D12+E12+F12)*0.005 -> 5.3371 | G13: =(C12+D12+E12+F12+G12)*0.005 -> 5.3371 | I13: =(C12+D12+E12+F12+G12+I12)*0.005 -> 5.3371 | J13: =(C12+D12+E12+F12+G12+I12+J12)*0.005 -> 5.3371 | K13: =(C12+D12+E12+F12+G12+I12+J12+K12)*0.005 -> 5.3371 | L13: =(C12+D12+E12+F12+G12+I12+J12+K12+L12)*0.005 -> 5.3371 | M13: =(C12+D12+E12+F12+G12+I12+J12+K12+L12+M12)*0.005 -> 5.3371 | N13: =(C12+D12+E12+F12+G12+I12+J12+K12+L12+M12+N12)*0.005 -> 5.3371 | O13: =(C12+D12+E12+F12+G12+I12+J12+K12+L12+M12+N12+O12)*0.005 -> 5.3371 | P13: =(C12+D12+E12+F12+G12+I12+J12+K12+L12+M12+N12+O12+P12)*0.005 -> 5.3371
A14: 3 | B14: Crisencia R. Ruiz | C14: =[5]Savings2019!$U$12 -> 535.5544 | R14: =C14+D14+E14+F14+G14+I14+J14+K14+L14+M14+N14+O14+P14 -> 535.5544 | S14: =R14/12 -> 44.629533 | T14: =D15+E15+F15+G15+I15+J15+K15+L15+M15+N15+O15+P15 -> 32.133264 | U14: =R14+T14 -> 567.68766
C15: Interest per mo. | D15: =(C14+D14)*0.005 -> 2.677772 | E15: =(C14+D14+E14)*0.005 -> 2.677772 | F15: =(+C14+D14+E14+F14)*0.005 -> 2.677772 | G15: =(C14+D14+E14+F14+G14)*0.005 -> 2.677772 | I15: =(C14+D14+E14+F14+G14+I14)*0.005 -> 2.677772 | J15: =(C14+D14+E14+F14+G14+I14+J14)*0.005 -> 2.677772 | K15: =(C14+D14+E14+F14+G14+I14+J14+K14)*0.005 -> 2.677772 | L15: =(C14+D14+E14+F14+G14+I14+J14+K14+L14)*0.005 -> 2.677772 | M15: =(C14+D14+E14+F14+G14+I14+J14+K14+L14+M14)*0.005 -> 2.677772 | N15: =(C14+D14+E14+F14+G14+I14+J14+K14+L14+M14+N14)*0.005 -> 2.677772 | O15: =(C14+D14+E14+F14+G14+I14+J14+K14+L14+M14+N14+O14)*0.005 -> 2.677772 | P15: =(C14+D14+E14+F14+G14+I14+J14+K14+L14+M14+N14+O14+P14)*0.005 -> 2.677772
A16: 4 | B16: Dexter B. Jumao-as | C16: =[5]Savings2019!$U$13 -> 21454.93 | D16: 0 | E16: 0 | F16: 0 | G16: 0 | I16: 0 | J16: 7000 | K16: 0 | L16: 0 | M16: 1000 | N16: 0 | O16: 0 | P16: 0 | Q16: 20000 | R16: =C16+D16+E16+F16+G16+I16+J16+K16+L16+M16+N16+O16+P16-Q16 -> 9454.93 | S16: =R16/12 -> 787.91083 | T16: =D17+E17+F17+G17+I17+J17+K17+L17+M17+N17+O17+P17 -> 1552.2958 | U16: =R16+T16 -> 11007.226
C17: Interest per mo. | D17: =(C16+D16)*0.005 -> 107.27465 | E17: =(C16+D16+E16)*0.005 -> 107.27465 | F17: =(+C16+D16+E16+F16)*0.005 -> 107.27465 | G17: =(C16+D16+E16+F16+G16)*0.005 -> 107.27465 | I17: =(C16+D16+E16+F16+G16+I16)*0.005 -> 107.27465 | J17: =(C16+D16+E16+F16+G16+I16+J16)*0.005 -> 142.27465 | K17: =(C16+D16+E16+F16+G16+I16+J16+K16)*0.005 -> 142.27465 | L17: =(C16+D16+E16+F16+G16+I16+J16+K16+L16)*0.005 -> 142.27465 | M17: =(C16+D16+E16+F16+G16+I16+J16+K16+L16+M16)*0.005 -> 147.27465 | N17: =(C16+D16+E16+F16+G16+I16+J16+K16+L16+M16+N16)*0.005 -> 147.27465 | O17: =(C16+D16+E16+F16+G16+I16+J16+K16+L16+M16+N16+O16)*0.005 -> 147.27465 | P17: =(C16+D16+E16+F16+G16+I16+J16+K16+L16+M16+N16+O16+P16)*0.005 -> 147.27465
A18: 5 | B18: Dorotea B. Jumao-as | C18: =[5]Savings2019!$U$14 -> 6406.1948 | D18: 0 | F18: 0 | G18: 0 | J18: 0 | K18: 0 | L18: 0 | O18: 0 | R18: =C18+D18+E18+F18+G18+I18+J18+K18+L18+M18+N18+O18+P18 -> 6406.1948 | S18: =R18/12 -> 533.84957 | T18: =D19+E19+F19+G19+I19+J19+K19+L19+M19+N19+O19+P19 -> 384.37169 | U18: =R18+T18 -> 6790.5665
C19: Interest per mo. | D19: =(C18+D18)*0.005 -> 32.030974 | E19: =(C18+D18+E18)*0.005 -> 32.030974 | F19: =(+C18+D18+E18+F18)*0.005 -> 32.030974 | G19: =(C18+D18+E18+F18+G18)*0.005 -> 32.030974 | I19: =(C18+D18+E18+F18+G18+I18)*0.005 -> 32.030974 | J19: =(C18+D18+E18+F18+G18+I18+J18)*0.005 -> 32.030974 | K19: =(C18+D18+E18+F18+G18+I18+J18+K18)*0.005 -> 32.030974 | L19: =(C18+D18+E18+F18+G18+I18+J18+K18+L18)*0.005 -> 32.030974 | M19: =(C18+D18+E18+F18+G18+I18+J18+K18+L18+M18)*0.005 -> 32.030974 | N19: =(C18+D18+E18+F18+G18+I18+J18+K18+L18+M18+N18)*0.005 -> 32.030974 | O19: =(C18+D18+E18+F18+G18+I18+J18+K18+L18+M18+N18+O18)*0.005 -> 32.030974 | P19: =(C18+D18+E18+F18+G18+I18+J18+K18+L18+M18+N18+O18+P18)*0.005 -> 32.030974
A20: 6 | B20: Edgardo P. Nodalo | C20: 0 | S20: =R20/12 -> 0 | T20: =D21+E21+F21+G21+I21+J21+K21+L21+M21+N21+O21+P21 -> 0 | U20: =R20+T20 -> 0
C21: Interest per mo. | D21: =(C20+D20)*0.005 -> 0 | E21: =(C20+D20+E20)*0.005 -> 0 | F21: =(+C20+D20+E20+F20)*0.005 -> 0 | G21: =(C20+D20+E20+F20+G20)*0.005 -> 0 | I21: =(C20+D20+E20+F20+G20+I20)*0.005 -> 0 | J21: =(C20+D20+E20+F20+G20+I20+J20)*0.005 -> 0 | K21: =(C20+D20+E20+F20+G20+I20+J20+K20)*0.005 -> 0 | L21: =(C20+D20+E20+F20+G20+I20+J20+K20+L20)*0.005 -> 0 | M21: =(C20+D20+E20+F20+G20+I20+J20+K20+L20+M20)*0.005 -> 0 | N21: =(C20+D20+E20+F20+G20+I20+J20+K20+L20+M20+N20)*0.005 -> 0 | O21: =(C20+D20+E20+F20+G20+I20+J20+K20+L20+M20+N20+O20)*0.005 -> 0 | P21: =(C20+D20+E20+F20+G20+I20+J20+K20+L20+M20+N20+O20+P20)*0.005 -> 0
A22: 7 | B22: Edgardo P. Nodalo | C22: 0 | S22: =R22/12 -> 0 | T22: =D23+E23+F23+G23+I23+J23+K23+L23+M23+N23+O23+P23 -> 0 | U22: =R22+T22 -> 0
C23: Interest per mo. | D23: =(C22+D22)*0.005 -> 0 | E23: =(C22+D22+E22)*0.005 -> 0 | F23: =(+C22+D22+E22+F22)*0.005 -> 0 | G23: =(C22+D22+E22+F22+G22)*0.005 -> 0 | I23: =(C22+D22+E22+F22+G22+I22)*0.005 -> 0 | J23: =(C22+D22+E22+F22+G22+I22+J22)*0.005 -> 0 | K23: =(C22+D22+E22+F22+G22+I22+J22+K22)*0.005 -> 0 | L23: =(C22+D22+E22+F22+G22+I22+J22+K22+L22)*0.005 -> 0 | M23: =(C22+D22+E22+F22+G22+I22+J22+K22+L22+M22)*0.005 -> 0 | N23: =(C22+D22+E22+F22+G22+I22+J22+K22+L22+M22+N22)*0.005 -> 0 | O23: =(C22+D22+E22+F22+G22+I22+J22+K22+L22+M22+N22+O22)*0.005 -> 0 | P23: =(C22+D22+E22+F22+G22+I22+J22+K22+L22+M22+N22+O22+P22)*0.005 -> 0
A24: 8 | B24: Emmanuel S. Quilantang | C24: 922.77 | R24: =C24+D24+E24+F24+G24+I24+J24+K24+L24+M24+N24+O24+P24 -> 922.77 | S24: =R24/12 -> 76.8975 | T24: =D25+E25+F25+G25+I25+J25+K25+L25+M25+N25+O25+P25 -> 55.3662 | U24: =R24+T24 -> 978.1362
C25: Interest per mo. | D25: =(C24+D24)*0.005 -> 4.61385 | E25: =(C24+D24+E24)*0.005 -> 4.61385 | F25: =(+C24+D24+E24+F24)*0.005 -> 4.61385 | G25: =(C24+D24+E24+F24+G24)*0.005 -> 4.61385 | I25: =(C24+D24+E24+F24+G24+I24)*0.005 -> 4.61385 | J25: =(C24+D24+E24+F24+G24+I24+J24)*0.005 -> 4.61385 | K25: =(C24+D24+E24+F24+G24+I24+J24+K24)*0.005 -> 4.61385 | L25: =(C24+D24+E24+F24+G24+I24+J24+K24+L24)*0.005 -> 4.61385 | M25: =(C24+D24+E24+F24+G24+I24+J24+K24+L24+M24)*0.005 -> 4.61385 | N25: =(C24+D24+E24+F24+G24+I24+J24+K24+L24+M24+N24)*0.005 -> 4.61385 | O25: =(C24+D24+E24+F24+G24+I24+J24+K24+L24+M24+N24+O24)*0.005 -> 4.61385 | P25: =(C24+D24+E24+F24+G24+I24+J24+K24+L24+M24+N24+O24+P24)*0.005 -> 4.61385
A26: 9 | B26: Erlinda E. Quilantang | C26: 984.71 | R26: =C26+D26+E26+F26+G26+I26+J26+K26+L26+M26+N26+O26+P26 -> 984.71 | S26: =R26/12 -> 82.059167 | T26: =D27+E27+F27+G27+I27+J27+K27+L27+M27+N27+O27+P27 -> 59.0826 | U26: =R26+T26 -> 1043.7926
C27: Interest per mo. | D27: =(C26+D26)*0.005 -> 4.92355 | E27: =(C26+D26+E26)*0.005 -> 4.92355 | F27: =(+C26+D26+E26+F26)*0.005 -> 4.92355 | G27: =(C26+D26+E26+F26+G26)*0.005 -> 4.92355 | I27: =(C26+D26+E26+F26+G26+I26)*0.005 -> 4.92355 | J27: =(C26+D26+E26+F26+G26+I26+J26)*0.005 -> 4.92355 | K27: =(C26+D26+E26+F26+G26+I26+J26+K26)*0.005 -> 4.92355 | L27: =(C26+D26+E26+F26+G26+I26+J26+K26+L26)*0.005 -> 4.92355 | M27: =(C26+D26+E26+F26+G26+I26+J26+K26+L26+M26)*0.005 -> 4.92355 | N27: =(C26+D26+E26+F26+G26+I26+J26+K26+L26+M26+N26)*0.005 -> 4.92355 | O27: =(C26+D26+E26+F26+G26+I26+J26+K26+L26+M26+N26+O26)*0.005 -> 4.92355 | P27: =(C26+D26+E26+F26+G26+I26+J26+K26+L26+M26+N26+O26+P26)*0.005 -> 4.92355
A28: 10 | B28: Maria Genia C. Seguido | C28: 706 | D28: 500 | F28: 1000 | J28: 0 | R28: =C28+D28+E28+F28+G28+I28+J28+K28+L28+M28+N28+O28+P28 -> 2206 | S28: =R28/12 -> 183.83333 | T28: =D29+E29+F29+G29+I29+J29+K29+L29+M29+N29+O29+P29 -> 122.36 | U28: =R28+T28 -> 2328.36
C29: Interest per mo. | D29: =(C28+D28)*0.005 -> 6.03 | E29: =(C28+D28+E28)*0.005 -> 6.03 | F29: =(+C28+D28+E28+F28)*0.005 -> 11.03 | G29: =(C28+D28+E28+F28+G28)*0.005 -> 11.03 | I29: =(C28+D28+E28+F28+G28+I28)*0.005 -> 11.03 | J29: =(C28+D28+E28+F28+G28+I28+J28)*0.005 -> 11.03 | K29: =(C28+D28+E28+F28+G28+I28+J28+K28)*0.005 -> 11.03 | L29: =(C28+D28+E28+F28+G28+I28+J28+K28+L28)*0.005 -> 11.03 | M29: =(C28+D28+E28+F28+G28+I28+J28+K28+L28+M28)*0.005 -> 11.03 | N29: =(C28+D28+E28+F28+G28+I28+J28+K28+L28+M28+N28)*0.005 -> 11.03 | O29: =(C28+D28+E28+F28+G28+I28+J28+K28+L28+M28+N28+O28)*0.005 -> 11.03 | P29: =(C28+D28+E28+F28+G28+I28+J28+K28+L28+M28+N28+O28+P28)*0.005 -> 11.03
A30: 11 | B30: Nenita S. Fay | C30: 492.64 | K30: 0 | N30: 0 | R30: =C30+D30+E30+F30+G30+I30+J30+K30+L30+M30+N30+O30+P30 -> 492.64 | S30: =R30/12 -> 41.053333 | T30: =D31+E31+F31+G31+I31+J31+K31+L31+M31+N31+O31+P31 -> 29.5584 | U30: =R30+T30 -> 522.1984
C31: Interest per mo. | D31: =(C30+D30)*0.005 -> 2.4632 | E31: =(C30+D30+E30)*0.005 -> 2.4632 | F31: =(+C30+D30+E30+F30)*0.005 -> 2.4632 | G31: =(C30+D30+E30+F30+G30)*0.005 -> 2.4632 | I31: =(C30+D30+E30+F30+G30+I30)*0.005 -> 2.4632 | J31: =(C30+D30+E30+F30+G30+I30+J30)*0.005 -> 2.4632 | K31: =(C30+D30+E30+F30+G30+I30+J30+K30)*0.005 -> 2.4632 | L31: =(C30+D30+E30+F30+G30+I30+J30+K30+L30)*0.005 -> 2.4632 | M31: =(C30+D30+E30+F30+G30+I30+J30+K30+L30+M30)*0.005 -> 2.4632 | N31: =(C30+D30+E30+F30+G30+I30+J30+K30+L30+M30+N30)*0.005 -> 2.4632 | O31: =(C30+D30+E30+F30+G30+I30+J30+K30+L30+M30+N30+O30)*0.005 -> 2.4632 | P31: =(C30+D30+E30+F30+G30+I30+J30+K30+L30+M30+N30+O30+P30)*0.005 -> 2.4632
A32: 12 | B32: Raffy C. Banghet | C32: 318 | D32: 0 | R32: =C32+D32+E32+F32+G32+I32+J32+K32+L32+M32+N32+O32+P32 -> 318 | S32: =R32/12 -> 26.5 | T32: =D33+E33+F33+G33+I33+J33+K33+L33+M33+N33+O33+P33 -> 19.08 | U32: =R32+T32 -> 337.08
C33: Interest per mo. | D33: =(C32+D32)*0.005 -> 1.59 | E33: =(C32+D32+E32)*0.005 -> 1.59 | F33: =(+C32+D32+E32+F32)*0.005 -> 1.59 | G33: =(C32+D32+E32+F32+G32)*0.005 -> 1.59 | I33: =(C32+D32+E32+F32+G32+I32)*0.005 -> 1.59 | J33: =(C32+D32+E32+F32+G32+I32+J32)*0.005 -> 1.59 | K33: =(C32+D32+E32+F32+G32+I32+J32+K32)*0.005 -> 1.59 | L33: =(C32+D32+E32+F32+G32+I32+J32+K32+L32)*0.005 -> 1.59 | M33: =(C32+D32+E32+F32+G32+I32+J32+K32+L32+M32)*0.005 -> 1.59 | N33: =(C32+D32+E32+F32+G32+I32+J32+K32+L32+M32+N32)*0.005 -> 1.59 | O33: =(C32+D32+E32+F32+G32+I32+J32+K32+L32+M32+N32+O32)*0.005 -> 1.59 | P33: =(C32+D32+E32+F32+G32+I32+J32+K32+L32+M32+N32+O32+P32)*0.005 -> 1.59
A34: 13 | B34: Analyn A. Punay | C34: 456.26 | D34: 0 | E34: 0 | F34: 0 | M34: 0 | R34: =C34+D34+E34+F34+G34+I34+J34+K34+L34+M34+N34+O34+P34 -> 456.26 | S34: =R34/12 -> 38.021667 | T34: =D35+E35+F35+G35+I35+J35+K35+L35+M35+N35+O35+P35 -> 27.3756 | U34: =R34+T34 -> 483.6356
C35: Interest per mo. | D35: =(C34+D34)*0.005 -> 2.2813 | E35: =(C34+D34+E34)*0.005 -> 2.2813 | F35: =(+C34+D34+E34+F34)*0.005 -> 2.2813 | G35: =(C34+D34+E34+F34+G34)*0.005 -> 2.2813 | I35: =(C34+D34+E34+F34+G34+I34)*0.005 -> 2.2813 | J35: =(C34+D34+E34+F34+G34+I34+J34)*0.005 -> 2.2813 | K35: =(C34+D34+E34+F34+G34+I34+J34+K34)*0.005 -> 2.2813 | L35: =(C34+D34+E34+F34+G34+I34+J34+K34+L34)*0.005 -> 2.2813 | M35: =(C34+D34+E34+F34+G34+I34+J34+K34+L34+M34)*0.005 -> 2.2813 | N35: =(C34+D34+E34+F34+G34+I34+J34+K34+L34+M34+N34)*0.005 -> 2.2813 | O35: =(C34+D34+E34+F34+G34+I34+J34+K34+L34+M34+N34+O34)*0.005 -> 2.2813 | P35: =(C34+D34+E34+F34+G34+I34+J34+K34+L34+M34+N34+O34+P34)*0.005 -> 2.2813
A36: 14 | B36: Susana I. Punay | C36: 500.99 | D36: 0 | E36: 0 | F36: 0 | M36: 0 | P36: 400 | R36: =C36+D36+E36+F36+G36+I36+J36+K36+L36+M36+N36+O36+P36 -> 900.99 | S36: =R36/12 -> 75.0825 | T36: =D37+E37+F37+G37+I37+J37+K37+L37+M37+N37+O37+P37 -> 32.0594 | U36: =R36+T36 -> 933.0494
C37: Interest per mo. | D37: =(C36+D36)*0.005 -> 2.50495 | E37: =(C36+D36+E36)*0.005 -> 2.50495 | F37: =(+C36+D36+E36+F36)*0.005 -> 2.50495 | G37: =(C36+D36+E36+F36+G36)*0.005 -> 2.50495 | I37: =(C36+D36+E36+F36+G36+I36)*0.005 -> 2.50495 | J37: =(C36+D36+E36+F36+G36+I36+J36)*0.005 -> 2.50495 | K37: =(C36+D36+E36+F36+G36+I36+J36+K36)*0.005 -> 2.50495 | L37: =(C36+D36+E36+F36+G36+I36+J36+K36+L36)*0.005 -> 2.50495 | M37: =(C36+D36+E36+F36+G36+I36+J36+K36+L36+M36)*0.005 -> 2.50495 | N37: =(C36+D36+E36+F36+G36+I36+J36+K36+L36+M36+N36)*0.005 -> 2.50495 | O37: =(C36+D36+E36+F36+G36+I36+J36+K36+L36+M36+N36+O36)*0.005 -> 2.50495 | P37: =(C36+D36+E36+F36+G36+I36+J36+K36+L36+M36+N36+O36+P36)*0.005 -> 4.50495
A38: 15 | B38: Marina S. Caparoso | C38: 534.24 | D38: 0 | E38: 0 | F38: 0 | G38: 0 | M38: 0 | R38: =C38+D38+E38+F38+G38+I38+J38+K38+L38+M38+N38+O38+P38 -> 534.24 | S38: =R38/12 -> 44.52 | T38: =D39+E39+F39+G39+I39+J39+K39+L39+M39+N39+O39+P39 -> 32.0544 | U38: =R38+T38 -> 566.2944
C39: Interest per mo. | D39: =(C38+D38)*0.005 -> 2.6712 | E39: =(C38+D38+E38)*0.005 -> 2.6712 | F39: =(+C38+D38+E38+F38)*0.005 -> 2.6712 | G39: =(C38+D38+E38+F38+G38)*0.005 -> 2.6712 | I39: =(C38+D38+E38+F38+G38+I38)*0.005 -> 2.6712 | J39: =(C38+D38+E38+F38+G38+I38+J38)*0.005 -> 2.6712 | K39: =(C38+D38+E38+F38+G38+I38+J38+K38)*0.005 -> 2.6712 | L39: =(C38+D38+E38+F38+G38+I38+J38+K38+L38)*0.005 -> 2.6712 | M39: =(C38+D38+E38+F38+G38+I38+J38+K38+L38+M38)*0.005 -> 2.6712 | N39: =(C38+D38+E38+F38+G38+I38+J38+K38+L38+M38+N38)*0.005 -> 2.6712 | O39: =(C38+D38+E38+F38+G38+I38+J38+K38+L38+M38+N38+O38)*0.005 -> 2.6712 | P39: =(C38+D38+E38+F38+G38+I38+J38+K38+L38+M38+N38+O38+P38)*0.005 -> 2.6712
A40: 16 | B40: Merian C. Jumao-as | C40: 859.23 | D40: 0 | E40: 0 | F40: 0 | G40: 0 | I40: 0 | M40: 0 | R40: =C40+D40+E40+F40+G40+I40+J40+K40+L40+M40+N40+O40+P40 -> 859.23 | S40: =R40/12 -> 71.6025 | T40: =D41+E41+F41+G41+I41+J41+K41+L41+M41+N41+O41+P41 -> 51.5538 | U40: =R40+T40 -> 910.7838
C41: Interest per mo. | D41: =(C40+D40)*0.005 -> 4.29615 | E41: =(C40+D40+E40)*0.005 -> 4.29615 | F41: =(+C40+D40+E40+F40)*0.005 -> 4.29615 | G41: =(C40+D40+E40+F40+G40)*0.005 -> 4.29615 | I41: =(C40+D40+E40+F40+G40+I40)*0.005 -> 4.29615 | J41: =(C40+D40+E40+F40+G40+I40+J40)*0.005 -> 4.29615 | K41: =(C40+D40+E40+F40+G40+I40+J40+K40)*0.005 -> 4.29615 | L41: =(C40+D40+E40+F40+G40+I40+J40+K40+L40)*0.005 -> 4.29615 | M41: =(C40+D40+E40+F40+G40+I40+J40+K40+L40+M40)*0.005 -> 4.29615 | N41: =(C40+D40+E40+F40+G40+I40+J40+K40+L40+M40+N40)*0.005 -> 4.29615 | O41: =(C40+D40+E40+F40+G40+I40+J40+K40+L40+M40+N40+O40)*0.005 -> 4.29615 | P41: =(C40+D40+E40+F40+G40+I40+J40+K40+L40+M40+N40+O40+P40)*0.005 -> 4.29615
U42: Page 1 of 2
A45: 17 | B45: Rahbie B. Jumao-as | C45: 252.75 | J45: 0 | O45: 0 | R45: =C45+D45+E45+F45+G45+I45+J45+K45+L45+M45+N45+O45+P45 -> 252.75 | S45: =R45/12 -> 21.0625 | T45: =D46+E46+F46+G46+I46+J46+K46+L46+M46+N46+O46+P46 -> 15.165 | U45: =R45+T45 -> 267.915
C46: Interest per mo. | D46: =(C45+D45)*0.005 -> 1.26375 | E46: =(C45+D45+E45)*0.005 -> 1.26375 | F46: =(+C45+D45+E45+F45)*0.005 -> 1.26375 | G46: =(C45+D45+E45+F45+G45)*0.005 -> 1.26375 | I46: =(C45+D45+E45+F45+G45+I45)*0.005 -> 1.26375 | J46: =(C45+D45+E45+F45+G45+I45+J45)*0.005 -> 1.26375 | K46: =(C45+D45+E45+F45+G45+I45+J45+K45)*0.005 -> 1.26375 | L46: =(C45+D45+E45+F45+G45+I45+J45+K45+L45)*0.005 -> 1.26375 | M46: =(C45+D45+E45+F45+G45+I45+J45+K45+L45+M45)*0.005 -> 1.26375 | N46: =(C45+D45+E45+F45+G45+I45+J45+K45+L45+M45+N45)*0.005 -> 1.26375 | O46: =(C45+D45+E45+F45+G45+I45+J45+K45+L45+M45+N45+O45)*0.005 -> 1.26375 | P46: =(C45+D45+E45+F45+G45+I45+J45+K45+L45+M45+N45+O45+P45)*0.005 -> 1.26375
A47: 18 | B47: Shalou J. Balao | C47: 991.75 | E47: 0 | F47: 0 | G47: 0 | I47: 0 | J47: 0 | K47: 415 | R47: =C47+D47+E47+F47+G47+I47+J47+K47+L47+M47+N47+O47+P47 -> 1406.75 | S47: =R47/12 -> 117.22917 | T47: =D48+E48+F48+G48+I48+J48+K48+L48+M48+N48+O48+P48 -> 71.955 | U47: =R47+T47 -> 1478.705
C48: Interest per mo. | D48: =(C47+D47)*0.005 -> 4.95875 | E48: =(C47+D47+E47)*0.005 -> 4.95875 | F48: =(+C47+D47+E47+F47)*0.005 -> 4.95875 | G48: =(C47+D47+E47+F47+G47)*0.005 -> 4.95875 | I48: =(C47+D47+E47+F47+G47+I47)*0.005 -> 4.95875 | J48: =(C47+D47+E47+F47+G47+I47+J47)*0.005 -> 4.95875 | K48: =(C47+D47+E47+F47+G47+I47+J47+K47)*0.005 -> 7.03375 | L48: =(C47+D47+E47+F47+G47+I47+J47+K47+L47)*0.005 -> 7.03375 | M48: =(C47+D47+E47+F47+G47+I47+J47+K47+L47+M47)*0.005 -> 7.03375 | N48: =(C47+D47+E47+F47+G47+I47+J47+K47+L47+M47+N47)*0.005 -> 7.03375 | O48: =(C47+D47+E47+F47+G47+I47+J47+K47+L47+M47+N47+O47)*0.005 -> 7.03375 | P48: =(C47+D47+E47+F47+G47+I47+J47+K47+L47+M47+N47+O47+P47)*0.005 -> 7.03375
A49: 19 | B49: Everth O. Acaso Jr. | C49: 52.25 | G49: 0 | R49: =C49+D49+E49+F49+G49+I49+J49+K49+L49+M49+N49+O49+P49 -> 52.25 | S49: =R49/12 -> 4.3541667 | T49: =D50+E50+F50+G50+I50+J50+K50+L50+M50+N50+O50+P50 -> 3.135 | U49: =R49+T49 -> 55.385
C50: Interest per mo. | D50: =(C49+D49)*0.005 -> 0.26125 | E50: =(C49+D49+E49)*0.005 -> 0.26125 | F50: =(+C49+D49+E49+F49)*0.005 -> 0.26125 | G50: =(C49+D49+E49+F49+G49)*0.005 -> 0.26125 | I50: =(C49+D49+E49+F49+G49+I49)*0.005 -> 0.26125 | J50: =(C49+D49+E49+F49+G49+I49+J49)*0.005 -> 0.26125 | K50: =(C49+D49+E49+F49+G49+I49+J49+K49)*0.005 -> 0.26125 | L50: =(C49+D49+E49+F49+G49+I49+J49+K49+L49)*0.005 -> 0.26125 | M50: =(C49+D49+E49+F49+G49+I49+J49+K49+L49+M49)*0.005 -> 0.26125 | N50: =(C49+D49+E49+F49+G49+I49+J49+K49+L49+M49+N49)*0.005 -> 0.26125 | O50: =(C49+D49+E49+F49+G49+I49+J49+K49+L49+M49+N49+O49)*0.005 -> 0.26125 | P50: =(C49+D49+E49+F49+G49+I49+J49+K49+L49+M49+N49+O49+P49)*0.005 -> 0.26125
A51: 20 | B51: Joselito L. Edullantes | C51: 1517.25 | F51: 0 | G51: 0 | I51: 0 | J51: 0 | K51: 0 | R51: =C51+D51+E51+F51+G51+I51+J51+K51+L51+M51+N51+O51+P51 -> 1517.25 | S51: =R51/12 -> 126.4375 | T51: =D52+E52+F52+G52+I52+J52+K52+L52+M52+N52+O52+P52 -> 91.035 | U51: =R51+T51 -> 1608.285
C52: Interest per mo. | D52: =(C51+D51)*0.005 -> 7.58625 | E52: =(C51+D51+E51)*0.005 -> 7.58625 | F52: =(+C51+D51+E51+F51)*0.005 -> 7.58625 | G52: =(C51+D51+E51+F51+G51)*0.005 -> 7.58625 | I52: =(C51+D51+E51+F51+G51+I51)*0.005 -> 7.58625 | J52: =(C51+D51+E51+F51+G51+I51+J51)*0.005 -> 7.58625 | K52: =(C51+D51+E51+F51+G51+I51+J51+K51)*0.005 -> 7.58625 | L52: =(C51+D51+E51+F51+G51+I51+J51+K51+L51)*0.005 -> 7.58625 | M52: =(C51+D51+E51+F51+G51+I51+J51+K51+L51+M51)*0.005 -> 7.58625 | N52: =(C51+D51+E51+F51+G51+I51+J51+K51+L51+M51+N51)*0.005 -> 7.58625 | O52: =(C51+D51+E51+F51+G51+I51+J51+K51+L51+M51+N51+O51)*0.005 -> 7.58625 | P52: =(C51+D51+E51+F51+G51+I51+J51+K51+L51+M51+N51+O51+P51)*0.005 -> 7.58625
A53: 21 | B53: Agusto S. Jimenea | C53: 207.75 | F53: 0 | G53: 0 | I53: 0 | J53: 0 | K53: 0 | R53: =C53+D53+E53+F53+G53+I53+J53+K53+L53+M53+N53+O53+P53 -> 207.75 | S53: =R53/12 -> 17.3125 | T53: =D54+E54+F54+G54+I54+J54+K54+L54+M54+N54+O54+P54 -> 12.465 | U53: =R53+T53 -> 220.215
C54: Interest per mo. | D54: =(C53+D53)*0.005 -> 1.03875 | E54: =(C53+D53+E53)*0.005 -> 1.03875 | F54: =(+C53+D53+E53+F53)*0.005 -> 1.03875 | G54: =(C53+D53+E53+F53+G53)*0.005 -> 1.03875 | I54: =(C53+D53+E53+F53+G53+I53)*0.005 -> 1.03875 | J54: =(C53+D53+E53+F53+G53+I53+J53)*0.005 -> 1.03875 | K54: =(C53+D53+E53+F53+G53+I53+J53+K53)*0.005 -> 1.03875 | L54: =(C53+D53+E53+F53+G53+I53+J53+K53+L53)*0.005 -> 1.03875 | M54: =(C53+D53+E53+F53+G53+I53+J53+K53+L53+M53)*0.005 -> 1.03875 | N54: =(C53+D53+E53+F53+G53+I53+J53+K53+L53+M53+N53)*0.005 -> 1.03875 | O54: =(C53+D53+E53+F53+G53+I53+J53+K53+L53+M53+N53+O53)*0.005 -> 1.03875 | P54: =(C53+D53+E53+F53+G53+I53+J53+K53+L53+M53+N53+O53+P53)*0.005 -> 1.03875
A55: 22 | B55: Hazel Q. Bulacan | C55: 309.5 | J55: 0 | K55: 0 | R55: =C55+D55+E55+F55+G55+I55+J55+K55+L55+M55+N55+O55+P55 -> 309.5 | S55: =R55/12 -> 25.791667 | T55: =D56+E56+F56+G56+I56+J56+K56+L56+M56+N56+O56+P56 -> 18.57 | U55: =R55+T55 -> 328.07
C56: Interest per mo. | D56: =(C55+D55)*0.005 -> 1.5475 | E56: =(C55+D55+E55)*0.005 -> 1.5475 | F56: =(+C55+D55+E55+F55)*0.005 -> 1.5475 | G56: =(C55+D55+E55+F55+G55)*0.005 -> 1.5475 | I56: =(C55+D55+E55+F55+G55+I55)*0.005 -> 1.5475 | J56: =(C55+D55+E55+F55+G55+I55+J55)*0.005 -> 1.5475 | K56: =(C55+D55+E55+F55+G55+I55+J55+K55)*0.005 -> 1.5475 | L56: =(C55+D55+E55+F55+G55+I55+J55+K55+L55)*0.005 -> 1.5475 | M56: =(C55+D55+E55+F55+G55+I55+J55+K55+L55+M55)*0.005 -> 1.5475 | N56: =(C55+D55+E55+F55+G55+I55+J55+K55+L55+M55+N55)*0.005 -> 1.5475 | O56: =(C55+D55+E55+F55+G55+I55+J55+K55+L55+M55+N55+O55)*0.005 -> 1.5475 | P56: =(C55+D55+E55+F55+G55+I55+J55+K55+L55+M55+N55+O55+P55)*0.005 -> 1.5475
A57: 23 | B57: ='[1]Subscribed&Paid-up (2)'!$B$72 -> Concepcion B. Cruz | C57: 3275 | F57: 120 | H57: 1000 | I57: 5000 | J57: 0 | K57: 0 | R57: =C57+D57+E57+F57+G57+I57+J57+K57+L57+M57+N57+O57+P57-H57 -> 7395 | S57: =R57/12 -> 616.25 | T57: =D58+E58+F58+G58+I58+J58+K58+L58+M58+N58+O58+P58 -> 402.5 | U57: =R57+T57 -> 7797.5
C58: Interest per mo. | D58: =(C57+D57)*0.005 -> 16.375 | E58: =(C57+D57+E57)*0.005 -> 16.375 | F58: =(+C57+D57+E57+F57)*0.005 -> 16.975 | G58: =(C57+D57+E57+F57+G57)*0.005 -> 16.975 | I58: =(C57+D57+E57+F57+G57+I57)*0.005 -> 41.975 | J58: =(C57+D57+E57+F57+G57+I57+J57)*0.005 -> 41.975 | K58: =(C57+D57+E57+F57+G57+I57+J57+K57)*0.005 -> 41.975 | L58: =(C57+D57+E57+F57+G57+I57+J57+K57+L57)*0.005 -> 41.975 | M58: =(C57+D57+E57+F57+G57+I57+J57+K57+L57+M57)*0.005 -> 41.975 | N58: =(C57+D57+E57+F57+G57+I57+J57+K57+L57+M57+N57)*0.005 -> 41.975 | O58: =(C57+D57+E57+F57+G57+I57+J57+K57+L57+M57+N57+O57)*0.005 -> 41.975 | P58: =(C57+D57+E57+F57+G57+I57+J57+K57+L57+M57+N57+O57+P57)*0.005 -> 41.975
A59: 24 | B59: ='[1]Subscribed&Paid-up (2)'!$B$73 -> Leonardo B. Cruz | C59: 1375.45 | J59: 0 | R59: =C59+D59+E59+F59+G59+I59+J59+K59+L59+M59+N59+O59+P59 -> 1375.45 | S59: =R59/12 -> 114.62083 | T59: =D60+E60+F60+G60+I60+J60+K60+L60+M60+N60+O60+P60 -> 82.527 | U59: =R59+T59 -> 1457.977
C60: Interest per mo. | D60: =(C59+D59)*0.005 -> 6.87725 | E60: =(C59+D59+E59)*0.005 -> 6.87725 | F60: =(+C59+D59+E59+F59)*0.005 -> 6.87725 | G60: =(C59+D59+E59+F59+G59)*0.005 -> 6.87725 | I60: =(C59+D59+E59+F59+G59+I59)*0.005 -> 6.87725 | J60: =(C59+D59+E59+F59+G59+I59+J59)*0.005 -> 6.87725 | K60: =(C59+D59+E59+F59+G59+I59+J59+K59)*0.005 -> 6.87725 | L60: =(C59+D59+E59+F59+G59+I59+J59+K59+L59)*0.005 -> 6.87725 | M60: =(C59+D59+E59+F59+G59+I59+J59+K59+L59+M59)*0.005 -> 6.87725 | N60: =(C59+D59+E59+F59+G59+I59+J59+K59+L59+M59+N59)*0.005 -> 6.87725 | O60: =(C59+D59+E59+F59+G59+I59+J59+K59+L59+M59+N59+O59)*0.005 -> 6.87725 | P60: =(C59+D59+E59+F59+G59+I59+J59+K59+L59+M59+N59+O59+P59)*0.005 -> 6.87725
A61: 25 | B61: ='[1]Subscribed&Paid-up (2)'!$B$74 -> Annalyn B. Cruz | C61: 463.36 | O61: 0 | R61: =C61+D61+E61+F61+G61+I61+J61+K61+L61+M61+N61+O61+P61 -> 463.36 | S61: =R61/12 -> 38.613333 | T61: =D62+E62+F62+G62+I62+J62+K62+L62+M62+N62+O62+P62 -> 27.8016 | U61: =R61+T61 -> 491.1616
C62: Interest per mo. | D62: =(C61+D61)*0.005 -> 2.3168 | E62: =(C61+D61+E61)*0.005 -> 2.3168 | F62: =(+C61+D61+E61+F61)*0.005 -> 2.3168 | G62: =(C61+D61+E61+F61+G61)*0.005 -> 2.3168 | I62: =(C61+D61+E61+F61+G61+I61)*0.005 -> 2.3168 | J62: =(C61+D61+E61+F61+G61+I61+J61)*0.005 -> 2.3168 | K62: =(C61+D61+E61+F61+G61+I61+J61+K61)*0.005 -> 2.3168 | L62: =(C61+D61+E61+F61+G61+I61+J61+K61+L61)*0.005 -> 2.3168 | M62: =(C61+D61+E61+F61+G61+I61+J61+K61+L61+M61)*0.005 -> 2.3168 | N62: =(C61+D61+E61+F61+G61+I61+J61+K61+L61+M61+N61)*0.005 -> 2.3168 | O62: =(C61+D61+E61+F61+G61+I61+J61+K61+L61+M61+N61+O61)*0.005 -> 2.3168 | P62: =(C61+D61+E61+F61+G61+I61+J61+K61+L61+M61+N61+O61+P61)*0.005 -> 2.3168
A63: 26 | B63: ='[1]Subscribed&Paid-up (2)'!$B$76 -> Milben Rex P. Balao | C63: 719 | K63: 0 | O63: 0 | R63: =C63+D63+E63+F63+G63+I63+J63+K63+L63+M63+N63+O63+P63 -> 719 | S63: =R63/12 -> 59.916667 | T63: =D64+E64+F64+G64+I64+J64+K64+L64+M64+N64+O64+P64 -> 43.14 | U63: =R63+T63 -> 762.14
C64: Interest per mo. | D64: =(C63+D63)*0.005 -> 3.595 | E64: =(C63+D63+E63)*0.005 -> 3.595 | F64: =(+C63+D63+E63+F63)*0.005 -> 3.595 | G64: =(C63+D63+E63+F63+G63)*0.005 -> 3.595 | I64: =(C63+D63+E63+F63+G63+I63)*0.005 -> 3.595 | J64: =(C63+D63+E63+F63+G63+I63+J63)*0.005 -> 3.595 | K64: =(C63+D63+E63+F63+G63+I63+J63+K63)*0.005 -> 3.595 | L64: =(C63+D63+E63+F63+G63+I63+J63+K63+L63)*0.005 -> 3.595 | M64: =(C63+D63+E63+F63+G63+I63+J63+K63+L63+M63)*0.005 -> 3.595 | N64: =(C63+D63+E63+F63+G63+I63+J63+K63+L63+M63+N63)*0.005 -> 3.595 | O64: =(C63+D63+E63+F63+G63+I63+J63+K63+L63+M63+N63+O63)*0.005 -> 3.595 | P64: =(C63+D63+E63+F63+G63+I63+J63+K63+L63+M63+N63+O63+P63)*0.005 -> 3.595
A65: 27 | B65: Victoriana Entero | C65: 6456.6 | M65: 0 | P65: 0 | R65: =C65+D65+E65+F65+G65+I65+J65+K65+L65+M65+N65+O65+P65 -> 6456.6 | S65: =R65/12 -> 538.05 | T65: =D66+E66+F66+G66+I66+J66+K66+L66+M66+N66+O66+P66 -> 387.396 | U65: =R65+T65 -> 6843.996
C66: Interest per mo. | D66: =(C65+D65)*0.005 -> 32.283 | E66: =(C65+D65+E65)*0.005 -> 32.283 | F66: =(+C65+D65+E65+F65)*0.005 -> 32.283 | G66: =(C65+D65+E65+F65+G65)*0.005 -> 32.283 | I66: =(C65+D65+E65+F65+G65+I65)*0.005 -> 32.283 | J66: =(C65+D65+E65+F65+G65+I65+J65)*0.005 -> 32.283 | K66: =(C65+D65+E65+F65+G65+I65+J65+K65)*0.005 -> 32.283 | L66: =(C65+D65+E65+F65+G65+I65+J65+K65+L65)*0.005 -> 32.283 | M66: =(C65+D65+E65+F65+G65+I65+J65+K65+L65+M65)*0.005 -> 32.283 | N66: =(C65+D65+E65+F65+G65+I65+J65+K65+L65+M65+N65)*0.005 -> 32.283 | O66: =(C65+D65+E65+F65+G65+I65+J65+K65+L65+M65+N65+O65)*0.005 -> 32.283 | P66: =(C65+D65+E65+F65+G65+I65+J65+K65+L65+M65+N65+O65+P65)*0.005 -> 32.283
A67: 28 | B67: Diosita J. Aquino | C67: 101.5 | N67: 0 | R67: =C67+D67+E67+F67+G67+I67+J67+K67+L67+M67+N67+O67+P67 -> 101.5 | S67: =R67/12 -> 8.4583333 | T67: =D68+E68+F68+G68+I68+J68+K68+L68+M68+N68+O68+P68 -> 6.09 | U67: =R67+T67 -> 107.59
C68: Interest per mo. | D68: =(C67+D67)*0.005 -> 0.5075 | E68: =(C67+D67+E67)*0.005 -> 0.5075 | F68: =(+C67+D67+E67+F67)*0.005 -> 0.5075 | G68: =(C67+D67+E67+F67+G67)*0.005 -> 0.5075 | I68: =(C67+D67+E67+F67+G67+I67)*0.005 -> 0.5075 | J68: =(C67+D67+E67+F67+G67+I67+J67)*0.005 -> 0.5075 | K68: =(C67+D67+E67+F67+G67+I67+J67+K67)*0.005 -> 0.5075 | L68: =(C67+D67+E67+F67+G67+I67+J67+K67+L67)*0.005 -> 0.5075 | M68: =(C67+D67+E67+F67+G67+I67+J67+K67+L67+M67)*0.005 -> 0.5075 | N68: =(C67+D67+E67+F67+G67+I67+J67+K67+L67+M67+N67)*0.005 -> 0.5075 | O68: =(C67+D67+E67+F67+G67+I67+J67+K67+L67+M67+N67+O67)*0.005 -> 0.5075 | P68: =(C67+D67+E67+F67+G67+I67+J67+K67+L67+M67+N67+O67+P67)*0.005 -> 0.5075
A69: 29 | B69: Perpetuo O. Gaelo | C69: =#REF! -> #REF! | I69: 15000 | N69: 0 | Q69: 1220 | R69: =C69+D69+E69+F69+G69+I69+J69+K69+L69+M69+N69+O69+P69-Q69 -> #REF! | S69: =R69/12 -> #REF! | T69: =D70+E70+F70+G70+I70+J70+K70+L70+M70+N70+O70+P70 -> #REF! | U69: =R69+T69 -> #REF!
C70: Interest per mo. | D70: =(C69+D69)*0.005 -> #REF! | E70: =(C69+D69+E69)*0.005 -> #REF! | F70: =(+C69+D69+E69+F69)*0.005 -> #REF! | G70: =(C69+D69+E69+F69+G69)*0.005 -> #REF! | I70: =(C69+D69+E69+F69+G69+I69)*0.005 -> #REF! | J70: =(C69+D69+E69+F69+G69+I69+J69)*0.005 -> #REF! | K70: =(C69+D69+E69+F69+G69+I69+J69+K69)*0.005 -> #REF! | L70: =(C69+D69+E69+F69+G69+I69+J69+K69+L69)*0.005 -> #REF! | M70: =(C69+D69+E69+F69+G69+I69+J69+K69+L69+M69)*0.005 -> #REF! | N70: =(C69+D69+E69+F69+G69+I69+J69+K69+L69+M69+N69)*0.005 -> #REF! | O70: =(C69+D69+E69+F69+G69+I69+J69+K69+L69+M69+N69+O69)*0.005 -> #REF! | P70: =(C69+D69+E69+F69+G69+I69+J69+K69+L69+M69+N69+O69+P69)*0.005 -> #REF!
A71: 30 | B71: Eloisa Williams | C71: 366 | N71: 0 | R71: =C71+D71+E71+F71+G71+I71+J71+K71+L71+M71+N71+O71+P71 -> 366 | S71: =R71/12 -> 30.5 | T71: =D72+E72+F72+G72+I72+J72+K72+L72+M72+N72+O72+P72 -> 21.96 | U71: =R71+T71 -> 387.96
C72: Interest per mo. | D72: =(C71+D71)*0.005 -> 1.83 | E72: =(C71+D71+E71)*0.005 -> 1.83 | F72: =(+C71+D71+E71+F71)*0.005 -> 1.83 | G72: =(C71+D71+E71+F71+G71)*0.005 -> 1.83 | I72: =(C71+D71+E71+F71+G71+I71)*0.005 -> 1.83 | J72: =(C71+D71+E71+F71+G71+I71+J71)*0.005 -> 1.83 | K72: =(C71+D71+E71+F71+G71+I71+J71+K71)*0.005 -> 1.83 | L72: =(C71+D71+E71+F71+G71+I71+J71+K71+L71)*0.005 -> 1.83 | M72: =(C71+D71+E71+F71+G71+I71+J71+K71+L71+M71)*0.005 -> 1.83 | N72: =(C71+D71+E71+F71+G71+I71+J71+K71+L71+M71+N71)*0.005 -> 1.83 | O72: =(C71+D71+E71+F71+G71+I71+J71+K71+L71+M71+N71+O71)*0.005 -> 1.83 | P72: =(C71+D71+E71+F71+G71+I71+J71+K71+L71+M71+N71+O71+P71)*0.005 -> 1.83
A73: 31 | B73: Paul Espinosa | C73: 94.47 | N73: 0 | R73: =C73+D73+E73+F73+G73+I73+J73+K73+L73+M73+N73+O73+P73 -> 94.47 | S73: =R73/12 -> 7.8725 | T73: =D74+E74+F74+G74+I74+J74+K74+L74+M74+N74+O74+P74 -> 5.6682 | U73: =R73+T73 -> 100.1382
C74: Interest per mo. | D74: =(C73+D73)*0.005 -> 0.47235 | E74: =(C73+D73+E73)*0.005 -> 0.47235 | F74: =(+C73+D73+E73+F73)*0.005 -> 0.47235 | G74: =(C73+D73+E73+F73+G73)*0.005 -> 0.47235 | I74: =(C73+D73+E73+F73+G73+I73)*0.005 -> 0.47235 | J74: =(C73+D73+E73+F73+G73+I73+J73)*0.005 -> 0.47235 | K74: =(C73+D73+E73+F73+G73+I73+J73+K73)*0.005 -> 0.47235 | L74: =(C73+D73+E73+F73+G73+I73+J73+K73+L73)*0.005 -> 0.47235 | M74: =(C73+D73+E73+F73+G73+I73+J73+K73+L73+M73)*0.005 -> 0.47235 | N74: =(C73+D73+E73+F73+G73+I73+J73+K73+L73+M73+N73)*0.005 -> 0.47235 | O74: =(C73+D73+E73+F73+G73+I73+J73+K73+L73+M73+N73+O73)*0.005 -> 0.47235 | P74: =(C73+D73+E73+F73+G73+I73+J73+K73+L73+M73+N73+O73+P73)*0.005 -> 0.47235
A75: 32 | B75: Joventino Larrosa | C75: 2350 | N75: 0 | R75: =C75+D75+E75+F75+G75+I75+J75+K75+L75+M75+N75+O75+P75 -> 2350 | S75: =R75/12 -> 195.83333 | T75: =D76+E76+F76+G76+I76+J76+K76+L76+M76+N76+O76+P76 -> 141 | U75: =R75+T75 -> 2491
C76: Interest per mo. | D76: =(C75+D75)*0.005 -> 11.75 | E76: =(C75+D75+E75)*0.005 -> 11.75 | F76: =(+C75+D75+E75+F75)*0.005 -> 11.75 | G76: =(C75+D75+E75+F75+G75)*0.005 -> 11.75 | I76: =(C75+D75+E75+F75+G75+I75)*0.005 -> 11.75 | J76: =(C75+D75+E75+F75+G75+I75+J75)*0.005 -> 11.75 | K76: =(C75+D75+E75+F75+G75+I75+J75+K75)*0.005 -> 11.75 | L76: =(C75+D75+E75+F75+G75+I75+J75+K75+L75)*0.005 -> 11.75 | M76: =(C75+D75+E75+F75+G75+I75+J75+K75+L75+M75)*0.005 -> 11.75 | N76: =(C75+D75+E75+F75+G75+I75+J75+K75+L75+M75+N75)*0.005 -> 11.75 | O76: =(C75+D75+E75+F75+G75+I75+J75+K75+L75+M75+N75+O75)*0.005 -> 11.75 | P76: =(C75+D75+E75+F75+G75+I75+J75+K75+L75+M75+N75+O75+P75)*0.005 -> 11.75
A77: 33 | B77: Jociel Esmero | K77: =200+200 -> 400 | L77: 300 | N77: 100 | R77: =C77+D77+E77+F77+G77+I77+J77+K77+L77+M77+N77+O77+P77 -> 800 | S77: =R77/12 -> 66.666667 | T77: =D78+E78+F78+G78+I78+J78+K78+L78+M78+N78+O78+P78 -> 21 | U77: =R77+T77 -> 821
C78: Interest per mo. | D78: =(C77+D77)*0.005 -> 0 | E78: =(C77+D77+E77)*0.005 -> 0 | F78: =(+C77+D77+E77+F77)*0.005 -> 0 | G78: =(C77+D77+E77+F77+G77)*0.005 -> 0 | I78: =(C77+D77+E77+F77+G77+I77)*0.005 -> 0 | J78: =(C77+D77+E77+F77+G77+I77+J77)*0.005 -> 0 | K78: =(C77+D77+E77+F77+G77+I77+J77+K77)*0.005 -> 2 | L78: =(C77+D77+E77+F77+G77+I77+J77+K77+L77)*0.005 -> 3.5 | M78: =(C77+D77+E77+F77+G77+I77+J77+K77+L77+M77)*0.005 -> 3.5 | N78: =(C77+D77+E77+F77+G77+I77+J77+K77+L77+M77+N77)*0.005 -> 4 | O78: =(C77+D77+E77+F77+G77+I77+J77+K77+L77+M77+N77+O77)*0.005 -> 4 | P78: =(C77+D77+E77+F77+G77+I77+J77+K77+L77+M77+N77+O77+P77)*0.005 -> 4
A79: 34 | B79: Alma Bola | L79: 500 | N79: 0 | R79: =C79+D79+E79+F79+G79+I79+J79+K79+L79+M79+N79+O79+P79 -> 500 | S79: =R79/12 -> 41.666667 | T79: =D80+E80+F80+G80+I80+J80+K80+L80+M80+N80+O80+P80 -> 12.5 | U79: =R79+T79 -> 512.5
C80: Interest per mo. | D80: =(C79+D79)*0.005 -> 0 | E80: =(C79+D79+E79)*0.005 -> 0 | F80: =(+C79+D79+E79+F79)*0.005 -> 0 | G80: =(C79+D79+E79+F79+G79)*0.005 -> 0 | I80: =(C79+D79+E79+F79+G79+I79)*0.005 -> 0 | J80: =(C79+D79+E79+F79+G79+I79+J79)*0.005 -> 0 | K80: =(C79+D79+E79+F79+G79+I79+J79+K79)*0.005 -> 0 | L80: =(C79+D79+E79+F79+G79+I79+J79+K79+L79)*0.005 -> 2.5 | M80: =(C79+D79+E79+F79+G79+I79+J79+K79+L79+M79)*0.005 -> 2.5 | N80: =(C79+D79+E79+F79+G79+I79+J79+K79+L79+M79+N79)*0.005 -> 2.5 | O80: =(C79+D79+E79+F79+G79+I79+J79+K79+L79+M79+N79+O79)*0.005 -> 2.5 | P80: =(C79+D79+E79+F79+G79+I79+J79+K79+L79+M79+N79+O79+P79)*0.005 -> 2.5
A81: 35 | B81: Sabiniano Caparoso | N81: 0 | O81: =2750+250 -> 3000 | R81: =C81+D81+E81+F81+G81+I81+J81+K81+L81+M81+N81+O81+P81 -> 3000 | S81: =R81/12 -> 250 | T81: =D82+E82+F82+G82+I82+J82+K82+L82+M82+N82+O82+P82 -> 30 | U81: =R81+T81 -> 3030
C82: Interest per mo. | D82: =(C81+D81)*0.005 -> 0 | E82: =(C81+D81+E81)*0.005 -> 0 | F82: =(+C81+D81+E81+F81)*0.005 -> 0 | G82: =(C81+D81+E81+F81+G81)*0.005 -> 0 | I82: =(C81+D81+E81+F81+G81+I81)*0.005 -> 0 | J82: =(C81+D81+E81+F81+G81+I81+J81)*0.005 -> 0 | K82: =(C81+D81+E81+F81+G81+I81+J81+K81)*0.005 -> 0 | L82: =(C81+D81+E81+F81+G81+I81+J81+K81+L81)*0.005 -> 0 | M82: =(C81+D81+E81+F81+G81+I81+J81+K81+L81+M81)*0.005 -> 0 | N82: =(C81+D81+E81+F81+G81+I81+J81+K81+L81+M81+N81)*0.005 -> 0 | O82: =(C81+D81+E81+F81+G81+I81+J81+K81+L81+M81+N81+O81)*0.005 -> 15 | P82: =(C81+D81+E81+F81+G81+I81+J81+K81+L81+M81+N81+O81+P81)*0.005 -> 15
B83: TOTAL | C83: =SUM(C10:C81) -> #REF! | R83: =SUM(R10:R81) -> #REF! | S83: =SUM(S10:S81) -> #REF! | T83: =SUM(T10:T81) -> #REF! | U83: =SUM(U10:U81) -> #REF!
A85: Prepared by: | E85: Checked by: | L85: Noted by: | R85: Approved by:
B88: SHALOU J. BALAO | F88: MARIA GENIA C. SEGUIDO | M88: ARNOLD C. GONZALES | S88: DEXTER B. JUMAO-AS
B89: SCSCC Secretary | F89: SCSCC Treasurer | M89: General Manager, SCSCC | S89: Chairman, SCSCC BOD
U92: Page 2 of 2
R96: Regular | S96: =18 -> 18 | T96: =U10+U14+U16+U18+U20+U24+U26+U28+U30+U32+U34+U36+U40+U45+U47+U55+U67+U38+U57+U59+U61+U63 -> 39531.466
R97: Associates | S97: 11 | T97: =U12+U49+U51+U53+U57+U59+U61+U63+U65+U69 -> #REF!
S98: =S96+S97 -> 29 | T98: =T96+T97 -> #REF!

Sheet Savings2022
A2: SIDLAK CHRISTIAN CHILDREN FUND SAVINGS AND CREDIT COOPERATIVE
A3: CDA Registration No. 9520-1080000000036399 Dated: November 16, 2016
A4: P-2, Brgy. Linao, Ormoc City
A6: COMPUTATION OF SAVINGS DEPOSITS
A7: As of FY 2022
A9: Members | C9: 2021 Savings | D9: Jan | E9: Feb | F9: withdrawal | G9: Mar | H9: withdrawal | I9: Apr | J9: withdrawal | K9: May | L9: Jun | M9: Jul | N9: Aug | O9: Sep | P9: Oct | Q9: Withdrawal | R9: Nov | S9: Dec | T9: withdrawal | U9: TSAD | V9: ASAD | W9: Int. on TSAD | X9: Total (SAD + Interest)
A10: 1 | B10: Allen L. Gubalane | C10: 393.9 | U10: =C10+D10+E10+G10+I10+K10+L10+M10+N10+O10+P10+R10+S10 -> 393.9 | V10: =U10/12 -> 32.825 | W10: =D11+E11+G11+I11+K11+L11+M11+N11+O11+P11+R11+S11 -> 23.634 | X10: =U10+W10 -> 417.534
C11: Interest per mo. | D11: =(C10+D10)*0.005 -> 1.9695 | E11: =(C10+D10+E10)*0.005 -> 1.9695 | G11: =(+C10+D10+E10+G10)*0.005 -> 1.9695 | I11: =(C10+D10+E10+G10+I10)*0.005 -> 1.9695 | K11: =(C10+D10+E10+G10+I10+K10)*0.005 -> 1.9695 | L11: =(C10+D10+E10+G10+I10+K10+L10)*0.005 -> 1.9695 | M11: =(C10+D10+E10+G10+I10+K10+L10+M10)*0.005 -> 1.9695 | N11: =(C10+D10+E10+G10+I10+K10+L10+M10+N10)*0.005 -> 1.9695 | O11: =(C10+D10+E10+G10+I10+K10+L10+M10+N10+O10)*0.005 -> 1.9695 | P11: =(C10+D10+E10+G10+I10+K10+L10+M10+N10+O10+P10)*0.005 -> 1.9695 | R11: =(C10+D10+E10+G10+I10+K10+L10+M10+N10+O10+P10+R10)*0.005 -> 1.9695 | S11: =(C10+D10+E10+G10+I10+K10+L10+M10+N10+O10+P10+R10+S10)*0.005 -> 1.9695
A12: 2 | B12: April A. Hubahib | C12: 1199.36 | U12: =C12+D12+E12+G12+I12+K12+L12+M12+N12+O12+P12+R12+S12 -> 1199.36 | V12: =U12/12 -> 99.946667 | W12: =D13+E13+G13+I13+K13+L13+M13+N13+O13+P13+R13+S13 -> 71.9616 | X12: =U12+W12 -> 1271.3216
C13: Interest per mo. | D13: =(C12+D12)*0.005 -> 5.9968 | E13: =(C12+D12+E12)*0.005 -> 5.9968 | G13: =(+C12+D12+E12+G12)*0.005 -> 5.9968 | I13: =(C12+D12+E12+G12+I12)*0.005 -> 5.9968 | K13: =(C12+D12+E12+G12+I12+K12)*0.005 -> 5.9968 | L13: =(C12+D12+E12+G12+I12+K12+L12)*0.005 -> 5.9968 | M13: =(C12+D12+E12+G12+I12+K12+L12+M12)*0.005 -> 5.9968 | N13: =(C12+D12+E12+G12+I12+K12+L12+M12+N12)*0.005 -> 5.9968 | O13: =(C12+D12+E12+G12+I12+K12+L12+M12+N12+O12)*0.005 -> 5.9968 | P13: =(C12+D12+E12+G12+I12+K12+L12+M12+N12+O12+P12)*0.005 -> 5.9968 | R13: =(C12+D12+E12+G12+I12+K12+L12+M12+N12+O12+P12+R12)*0.005 -> 5.9968 | S13: =(C12+D12+E12+G12+I12+K12+L12+M12+N12+O12+P12+R12+S12)*0.005 -> 5.9968
A14: 3 | B14: Crisencia R. Ruiz | C14: =3635.79+37.6 -> 3673.39 | U14: =C14+D14+E14+G14+I14+K14+L14+M14+N14+O14+P14+R14+S14 -> 3673.39 | V14: =U14/12 -> 306.11583 | W14: =D15+E15+G15+I15+K15+L15+M15+N15+O15+P15+R15+S15 -> 220.4034 | X14: =U14+W14 -> 3893.7934
C15: Interest per mo. | D15: =(C14+D14)*0.005 -> 18.36695 | E15: =(C14+D14+E14)*0.005 -> 18.36695 | G15: =(+C14+D14+E14+G14)*0.005 -> 18.36695 | I15: =(C14+D14+E14+G14+I14)*0.005 -> 18.36695 | K15: =(C14+D14+E14+G14+I14+K14)*0.005 -> 18.36695 | L15: =(C14+D14+E14+G14+I14+K14+L14)*0.005 -> 18.36695 | M15: =(C14+D14+E14+G14+I14+K14+L14+M14)*0.005 -> 18.36695 | N15: =(C14+D14+E14+G14+I14+K14+L14+M14+N14)*0.005 -> 18.36695 | O15: =(C14+D14+E14+G14+I14+K14+L14+M14+N14+O14)*0.005 -> 18.36695 | P15: =(C14+D14+E14+G14+I14+K14+L14+M14+N14+O14+P14)*0.005 -> 18.36695 | R15: =(C14+D14+E14+G14+I14+K14+L14+M14+N14+O14+P14+R14)*0.005 -> 18.36695 | S15: =(C14+D14+E14+G14+I14+K14+L14+M14+N14+O14+P14+R14+S14)*0.005 -> 18.36695
A16: 4 | B16: Dexter B. Jumao-as | C16: =11667.66+355.89 -> 12023.55 | D16: 500 | E16: 500 | G16: 675 | I16: 0 | K16: 0 | L16: 0 | M16: 0 | N16: 0 | O16: 0 | P16: 0 | R16: 0 | S16: 0 | U16: =C16+D16+E16+G16+I16+K16+L16+M16+N16+O16+P16+R16+S16-T16 -> 13698.55 | V16: =U16/12 -> 1141.5458 | W16: =D17+E17+G17+I17+K17+L17+M17+N17+O17+P17+R17+S17 -> 812.663 | X16: =U16+W16 -> 14511.213
C17: Interest per mo. | D17: =(C16+D16)*0.005 -> 62.61775 | E17: =(C16+D16+E16)*0.005 -> 65.11775 | G17: =(+C16+D16+E16+G16)*0.005 -> 68.49275 | I17: =(C16+D16+E16+G16+I16)*0.005 -> 68.49275 | K17: =(C16+D16+E16+G16+I16+K16)*0.005 -> 68.49275 | L17: =(C16+D16+E16+G16+I16+K16+L16)*0.005 -> 68.49275 | M17: =(C16+D16+E16+G16+I16+K16+L16+M16)*0.005 -> 68.49275 | N17: =(C16+D16+E16+G16+I16+K16+L16+M16+N16)*0.005 -> 68.49275 | O17: =(C16+D16+E16+G16+I16+K16+L16+M16+N16+O16)*0.005 -> 68.49275 | P17: =(C16+D16+E16+G16+I16+K16+L16+M16+N16+O16+P16)*0.005 -> 68.49275 | R17: =(C16+D16+E16+G16+I16+K16+L16+M16+N16+O16+P16+R16)*0.005 -> 68.49275 | S17: =(C16+D16+E16+G16+I16+K16+L16+M16+N16+O16+P16+R16+S16)*0.005 -> 68.49275
A18: 5 | B18: Dorotea B. Jumao-as | C18: =7404+107.12 -> 7511.12 | D18: 0 | G18: 0 | I18: 0 | L18: 0 | N18: 0 | R18: 0 | U18: =C18+D18+E18+G18+I18+K18+L18+M18+N18+O18+P18+R18+S18 -> 7511.12 | V18: =U18/12 -> 625.92667 | W18: =D19+E19+G19+I19+K19+L19+M19+N19+O19+P19+R19+S19 -> 450.6672 | X18: =U18+W18 -> 7961.7872
C19: Interest per mo. | D19: =(C18+D18)*0.005 -> 37.5556 | E19: =(C18+D18+E18)*0.005 -> 37.5556 | G19: =(+C18+D18+E18+G18)*0.005 -> 37.5556 | I19: =(C18+D18+E18+G18+I18)*0.005 -> 37.5556 | K19: =(C18+D18+E18+G18+I18+K18)*0.005 -> 37.5556 | L19: =(C18+D18+E18+G18+I18+K18+L18)*0.005 -> 37.5556 | M19: =(C18+D18+E18+G18+I18+K18+L18+M18)*0.005 -> 37.5556 | N19: =(C18+D18+E18+G18+I18+K18+L18+M18+N18)*0.005 -> 37.5556 | O19: =(C18+D18+E18+G18+I18+K18+L18+M18+N18+O18)*0.005 -> 37.5556 | P19: =(C18+D18+E18+G18+I18+K18+L18+M18+N18+O18+P18)*0.005 -> 37.5556 | R19: =(C18+D18+E18+G18+I18+K18+L18+M18+N18+O18+P18+R18)*0.005 -> 37.5556 | S19: =(C18+D18+E18+G18+I18+K18+L18+M18+N18+O18+P18+R18+S18)*0.005 -> 37.5556
A20: 6 | B20: Edgardo P. Nodalo | C20: 0 | V20: =U20/12 -> 0 | W20: =D21+E21+G21+I21+K21+L21+M21+N21+O21+P21+R21+S21 -> 0 | X20: =U20+W20 -> 0
C21: Interest per mo. | D21: =(C20+D20)*0.005 -> 0 | E21: =(C20+D20+E20)*0.005 -> 0 | G21: =(+C20+D20+E20+G20)*0.005 -> 0 | I21: =(C20+D20+E20+G20+I20)*0.005 -> 0 | K21: =(C20+D20+E20+G20+I20+K20)*0.005 -> 0 | L21: =(C20+D20+E20+G20+I20+K20+L20)*0.005 -> 0 | M21: =(C20+D20+E20+G20+I20+K20+L20+M20)*0.005 -> 0 | N21: =(C20+D20+E20+G20+I20+K20+L20+M20+N20)*0.005 -> 0 | O21: =(C20+D20+E20+G20+I20+K20+L20+M20+N20+O20)*0.005 -> 0 | P21: =(C20+D20+E20+G20+I20+K20+L20+M20+N20+O20+P20)*0.005 -> 0 | R21: =(C20+D20+E20+G20+I20+K20+L20+M20+N20+O20+P20+R20)*0.005 -> 0 | S21: =(C20+D20+E20+G20+I20+K20+L20+M20+N20+O20+P20+R20+S20)*0.005 -> 0
A22: 8 | B22: Emmanuel S. Quilantang | C22: 1036.83 | U22: =C22+D22+E22+G22+I22+K22+L22+M22+N22+O22+P22+R22+S22 -> 1036.83 | V22: =U22/12 -> 86.4025 | W22: =D23+E23+G23+I23+K23+L23+M23+N23+O23+P23+R23+S23 -> 62.2098 | X22: =U22+W22 -> 1099.0398
C23: Interest per mo. | D23: =(C22+D22)*0.005 -> 5.18415 | E23: =(C22+D22+E22)*0.005 -> 5.18415 | G23: =(+C22+D22+E22+G22)*0.005 -> 5.18415 | I23: =(C22+D22+E22+G22+I22)*0.005 -> 5.18415 | K23: =(C22+D22+E22+G22+I22+K22)*0.005 -> 5.18415 | L23: =(C22+D22+E22+G22+I22+K22+L22)*0.005 -> 5.18415 | M23: =(C22+D22+E22+G22+I22+K22+L22+M22)*0.005 -> 5.18415 | N23: =(C22+D22+E22+G22+I22+K22+L22+M22+N22)*0.005 -> 5.18415 | O23: =(C22+D22+E22+G22+I22+K22+L22+M22+N22+O22)*0.005 -> 5.18415 | P23: =(C22+D22+E22+G22+I22+K22+L22+M22+N22+O22+P22)*0.005 -> 5.18415 | R23: =(C22+D22+E22+G22+I22+K22+L22+M22+N22+O22+P22+R22)*0.005 -> 5.18415 | S23: =(C22+D22+E22+G22+I22+K22+L22+M22+N22+O22+P22+R22+S22)*0.005 -> 5.18415
A24: 9 | B24: Erlinda E. Quilantang | C24: 1106.42 | U24: =C24+D24+E24+G24+I24+K24+L24+M24+N24+O24+P24+R24+S24 -> 1106.42 | V24: =U24/12 -> 92.201667 | W24: =D25+E25+G25+I25+K25+L25+M25+N25+O25+P25+R25+S25 -> 66.3852 | X24: =U24+W24 -> 1172.8052
C25: Interest per mo. | D25: =(C24+D24)*0.005 -> 5.5321 | E25: =(C24+D24+E24)*0.005 -> 5.5321 | G25: =(+C24+D24+E24+G24)*0.005 -> 5.5321 | I25: =(C24+D24+E24+G24+I24)*0.005 -> 5.5321 | K25: =(C24+D24+E24+G24+I24+K24)*0.005 -> 5.5321 | L25: =(C24+D24+E24+G24+I24+K24+L24)*0.005 -> 5.5321 | M25: =(C24+D24+E24+G24+I24+K24+L24+M24)*0.005 -> 5.5321 | N25: =(C24+D24+E24+G24+I24+K24+L24+M24+N24)*0.005 -> 5.5321 | O25: =(C24+D24+E24+G24+I24+K24+L24+M24+N24+O24)*0.005 -> 5.5321 | P25: =(C24+D24+E24+G24+I24+K24+L24+M24+N24+O24+P24)*0.005 -> 5.5321 | R25: =(C24+D24+E24+G24+I24+K24+L24+M24+N24+O24+P24+R24)*0.005 -> 5.5321 | S25: =(C24+D24+E24+G24+I24+K24+L24+M24+N24+O24+P24+R24+S24)*0.005 -> 5.5321
A26: 10 | B26: Maria Genia C. Seguido | C26: 2880.06 | D26: 0 | G26: 0 | L26: 0 | U26: =C26+D26+E26+G26+I26+K26+L26+M26+N26+O26+P26+R26+S26 -> 2880.06 | V26: =U26/12 -> 240.005 | W26: =D27+E27+G27+I27+K27+L27+M27+N27+O27+P27+R27+S27 -> 172.8036 | X26: =U26+W26 -> 3052.8636
C27: Interest per mo. | D27: =(C26+D26)*0.005 -> 14.4003 | E27: =(C26+D26+E26)*0.005 -> 14.4003 | G27: =(+C26+D26+E26+G26)*0.005 -> 14.4003 | I27: =(C26+D26+E26+G26+I26)*0.005 -> 14.4003 | K27: =(C26+D26+E26+G26+I26+K26)*0.005 -> 14.4003 | L27: =(C26+D26+E26+G26+I26+K26+L26)*0.005 -> 14.4003 | M27: =(C26+D26+E26+G26+I26+K26+L26+M26)*0.005 -> 14.4003 | N27: =(C26+D26+E26+G26+I26+K26+L26+M26+N26)*0.005 -> 14.4003 | O27: =(C26+D26+E26+G26+I26+K26+L26+M26+N26+O26)*0.005 -> 14.4003 | P27: =(C26+D26+E26+G26+I26+K26+L26+M26+N26+O26+P26)*0.005 -> 14.4003 | R27: =(C26+D26+E26+G26+I26+K26+L26+M26+N26+O26+P26+R26)*0.005 -> 14.4003 | S27: =(C26+D26+E26+G26+I26+K26+L26+M26+N26+O26+P26+R26+S26)*0.005 -> 14.4003
A28: 11 | B28: Nenita S. Fay | C28: 553.53 | M28: 0 | P28: 0 | U28: =C28+D28+E28+G28+I28+K28+L28+M28+N28+O28+P28+R28+S28 -> 553.53 | V28: =U28/12 -> 46.1275 | W28: =D29+E29+G29+I29+K29+L29+M29+N29+O29+P29+R29+S29 -> 33.2118 | X28: =U28+W28 -> 586.7418
C29: Interest per mo. | D29: =(C28+D28)*0.005 -> 2.76765 | E29: =(C28+D28+E28)*0.005 -> 2.76765 | G29: =(+C28+D28+E28+G28)*0.005 -> 2.76765 | I29: =(C28+D28+E28+G28+I28)*0.005 -> 2.76765 | K29: =(C28+D28+E28+G28+I28+K28)*0.005 -> 2.76765 | L29: =(C28+D28+E28+G28+I28+K28+L28)*0.005 -> 2.76765 | M29: =(C28+D28+E28+G28+I28+K28+L28+M28)*0.005 -> 2.76765 | N29: =(C28+D28+E28+G28+I28+K28+L28+M28+N28)*0.005 -> 2.76765 | O29: =(C28+D28+E28+G28+I28+K28+L28+M28+N28+O28)*0.005 -> 2.76765 | P29: =(C28+D28+E28+G28+I28+K28+L28+M28+N28+O28+P28)*0.005 -> 2.76765 | R29: =(C28+D28+E28+G28+I28+K28+L28+M28+N28+O28+P28+R28)*0.005 -> 2.76765 | S29: =(C28+D28+E28+G28+I28+K28+L28+M28+N28+O28+P28+R28+S28)*0.005 -> 2.76765
A30: 12 | B30: Raffy C. Banghet | C30: 357.3 | D30: 0 | U30: =C30+D30+E30+G30+I30+K30+L30+M30+N30+O30+P30+R30+S30 -> 357.3 | V30: =U30/12 -> 29.775 | W30: =D31+E31+G31+I31+K31+L31+M31+N31+O31+P31+R31+S31 -> 21.438 | X30: =U30+W30 -> 378.738
C31: Interest per mo. | D31: =(C30+D30)*0.005 -> 1.7865 | E31: =(C30+D30+E30)*0.005 -> 1.7865 | G31: =(+C30+D30+E30+G30)*0.005 -> 1.7865 | I31: =(C30+D30+E30+G30+I30)*0.005 -> 1.7865 | K31: =(C30+D30+E30+G30+I30+K30)*0.005 -> 1.7865 | L31: =(C30+D30+E30+G30+I30+K30+L30)*0.005 -> 1.7865 | M31: =(C30+D30+E30+G30+I30+K30+L30+M30)*0.005 -> 1.7865 | N31: =(C30+D30+E30+G30+I30+K30+L30+M30+N30)*0.005 -> 1.7865 | O31: =(C30+D30+E30+G30+I30+K30+L30+M30+N30+O30)*0.005 -> 1.7865 | P31: =(C30+D30+E30+G30+I30+K30+L30+M30+N30+O30+P30)*0.005 -> 1.7865 | R31: =(C30+D30+E30+G30+I30+K30+L30+M30+N30+O30+P30+R30)*0.005 -> 1.7865 | S31: =(C30+D30+E30+G30+I30+K30+L30+M30+N30+O30+P30+R30+S30)*0.005 -> 1.7865
A32: 13 | B32: Analyn A. Punay | C32: 512.66 | D32: 0 | E32: 0 | G32: 0 | O32: 0 | U32: =C32+D32+E32+G32+I32+K32+L32+M32+N32+O32+P32+R32+S32 -> 512.66 | V32: =U32/12 -> 42.721667 | W32: =D33+E33+G33+I33+K33+L33+M33+N33+O33+P33+R33+S33 -> 30.7596 | X32: =U32+W32 -> 543.4196
C33: Interest per mo. | D33: =(C32+D32)*0.005 -> 2.5633 | E33: =(C32+D32+E32)*0.005 -> 2.5633 | G33: =(+C32+D32+E32+G32)*0.005 -> 2.5633 | I33: =(C32+D32+E32+G32+I32)*0.005 -> 2.5633 | K33: =(C32+D32+E32+G32+I32+K32)*0.005 -> 2.5633 | L33: =(C32+D32+E32+G32+I32+K32+L32)*0.005 -> 2.5633 | M33: =(C32+D32+E32+G32+I32+K32+L32+M32)*0.005 -> 2.5633 | N33: =(C32+D32+E32+G32+I32+K32+L32+M32+N32)*0.005 -> 2.5633 | O33: =(C32+D32+E32+G32+I32+K32+L32+M32+N32+O32)*0.005 -> 2.5633 | P33: =(C32+D32+E32+G32+I32+K32+L32+M32+N32+O32+P32)*0.005 -> 2.5633 | R33: =(C32+D32+E32+G32+I32+K32+L32+M32+N32+O32+P32+R32)*0.005 -> 2.5633 | S33: =(C32+D32+E32+G32+I32+K32+L32+M32+N32+O32+P32+R32+S32)*0.005 -> 2.5633
A34: 14 | B34: Susana I. Punay | C34: =989.03+128.94 -> 1117.97 | D34: 0 | E34: 0 | G34: 0 | O34: 0 | U34: =C34+D34+E34+G34+I34+K34+L34+M34+N34+O34+P34+R34+S34 -> 1117.97 | V34: =U34/12 -> 93.164167 | W34: =D35+E35+G35+I35+K35+L35+M35+N35+O35+P35+R35+S35 -> 67.0782 | X34: =U34+W34 -> 1185.0482
C35: Interest per mo. | D35: =(C34+D34)*0.005 -> 5.58985 | E35: =(C34+D34+E34)*0.005 -> 5.58985 | G35: =(+C34+D34+E34+G34)*0.005 -> 5.58985 | I35: =(C34+D34+E34+G34+I34)*0.005 -> 5.58985 | K35: =(C34+D34+E34+G34+I34+K34)*0.005 -> 5.58985 | L35: =(C34+D34+E34+G34+I34+K34+L34)*0.005 -> 5.58985 | M35: =(C34+D34+E34+G34+I34+K34+L34+M34)*0.005 -> 5.58985 | N35: =(C34+D34+E34+G34+I34+K34+L34+M34+N34)*0.005 -> 5.58985 | O35: =(C34+D34+E34+G34+I34+K34+L34+M34+N34+O34)*0.005 -> 5.58985 | P35: =(C34+D34+E34+G34+I34+K34+L34+M34+N34+O34+P34)*0.005 -> 5.58985 | R35: =(C34+D34+E34+G34+I34+K34+L34+M34+N34+O34+P34+R34)*0.005 -> 5.58985 | S35: =(C34+D34+E34+G34+I34+K34+L34+M34+N34+O34+P34+R34+S34)*0.005 -> 5.58985
A36: 15 | B36: Marina S. Caparoso | C36: =600.27+63.4+94.03 -> 757.7 | D36: 0 | E36: 0 | G36: 0 | I36: 0 | O36: 0 | U36: =C36+D36+E36+G36+I36+K36+L36+M36+N36+O36+P36+R36+S36 -> 757.7 | V36: =U36/12 -> 63.141667 | W36: =D37+E37+G37+I37+K37+L37+M37+N37+O37+P37+R37+S37 -> 45.462 | X36: =U36+W36 -> 803.162
C37: Interest per mo. | D37: =(C36+D36)*0.005 -> 3.7885 | E37: =(C36+D36+E36)*0.005 -> 3.7885 | G37: =(+C36+D36+E36+G36)*0.005 -> 3.7885 | I37: =(C36+D36+E36+G36+I36)*0.005 -> 3.7885 | K37: =(C36+D36+E36+G36+I36+K36)*0.005 -> 3.7885 | L37: =(C36+D36+E36+G36+I36+K36+L36)*0.005 -> 3.7885 | M37: =(C36+D36+E36+G36+I36+K36+L36+M36)*0.005 -> 3.7885 | N37: =(C36+D36+E36+G36+I36+K36+L36+M36+N36)*0.005 -> 3.7885 | O37: =(C36+D36+E36+G36+I36+K36+L36+M36+N36+O36)*0.005 -> 3.7885 | P37: =(C36+D36+E36+G36+I36+K36+L36+M36+N36+O36+P36)*0.005 -> 3.7885 | R37: =(C36+D36+E36+G36+I36+K36+L36+M36+N36+O36+P36+R36)*0.005 -> 3.7885 | S37: =(C36+D36+E36+G36+I36+K36+L36+M36+N36+O36+P36+R36+S36)*0.005 -> 3.7885
A38: 16 | B38: Merian C. Jumao-as | C38: =1482.93+115.85 -> 1598.78 | D38: 0 | E38: 0 | G38: 0 | I38: 0 | K38: 0 | O38: 0 | U38: =C38+D38+E38+G38+I38+K38+L38+M38+N38+O38+P38+R38+S38 -> 1598.78 | V38: =U38/12 -> 133.23167 | W38: =D39+E39+G39+I39+K39+L39+M39+N39+O39+P39+R39+S39 -> 95.9268 | X38: =U38+W38 -> 1694.7068
C39: Interest per mo. | D39: =(C38+D38)*0.005 -> 7.9939 | E39: =(C38+D38+E38)*0.005 -> 7.9939 | G39: =(+C38+D38+E38+G38)*0.005 -> 7.9939 | I39: =(C38+D38+E38+G38+I38)*0.005 -> 7.9939 | K39: =(C38+D38+E38+G38+I38+K38)*0.005 -> 7.9939 | L39: =(C38+D38+E38+G38+I38+K38+L38)*0.005 -> 7.9939 | M39: =(C38+D38+E38+G38+I38+K38+L38+M38)*0.005 -> 7.9939 | N39: =(C38+D38+E38+G38+I38+K38+L38+M38+N38)*0.005 -> 7.9939 | O39: =(C38+D38+E38+G38+I38+K38+L38+M38+N38+O38)*0.005 -> 7.9939 | P39: =(C38+D38+E38+G38+I38+K38+L38+M38+N38+O38+P38)*0.005 -> 7.9939 | R39: =(C38+D38+E38+G38+I38+K38+L38+M38+N38+O38+P38+R38)*0.005 -> 7.9939 | S39: =(C38+D38+E38+G38+I38+K38+L38+M38+N38+O38+P38+R38+S38)*0.005 -> 7.9939
X40: Page 1 of 2
A43: 17 | B43: Rahbie B. Jumao-as | C43: 284 | L43: 0 | R43: 0 | U43: =C43+D43+E43+G43+I43+K43+L43+M43+N43+O43+P43+R43+S43 -> 284 | V43: =U43/12 -> 23.666667 | W43: =D44+E44+G44+I44+K44+L44+M44+N44+O44+P44+R44+S44 -> 17.04 | X43: =U43+W43 -> 301.04
C44: Interest per mo. | D44: =(C43+D43)*0.005 -> 1.42 | E44: =(C43+D43+E43)*0.005 -> 1.42 | G44: =(+C43+D43+E43+G43)*0.005 -> 1.42 | I44: =(C43+D43+E43+G43+I43)*0.005 -> 1.42 | K44: =(C43+D43+E43+G43+I43+K43)*0.005 -> 1.42 | L44: =(C43+D43+E43+G43+I43+K43+L43)*0.005 -> 1.42 | M44: =(C43+D43+E43+G43+I43+K43+L43+M43)*0.005 -> 1.42 | N44: =(C43+D43+E43+G43+I43+K43+L43+M43+N43)*0.005 -> 1.42 | O44: =(C43+D43+E43+G43+I43+K43+L43+M43+N43+O43)*0.005 -> 1.42 | P44: =(C43+D43+E43+G43+I43+K43+L43+M43+N43+O43+P43)*0.005 -> 1.42 | R44: =(C43+D43+E43+G43+I43+K43+L43+M43+N43+O43+P43+R43)*0.005 -> 1.42 | S44: =(C43+D43+E43+G43+I43+K43+L43+M43+N43+O43+P43+R43+S43)*0.005 -> 1.42
A45: 18 | B45: Shalou J. Balao | C45: =1979.43+198.77 -> 2178.2 | E45: 0 | G45: 0 | I45: 0 | K45: 0 | L45: 0 | U45: =C45+D45+E45+G45+I45+K45+L45+M45+N45+O45+P45+R45+S45 -> 2178.2 | V45: =U45/12 -> 181.51667 | W45: =D46+E46+G46+I46+K46+L46+M46+N46+O46+P46+R46+S46 -> 130.692 | X45: =U45+W45 -> 2308.892
C46: Interest per mo. | D46: =(C45+D45)*0.005 -> 10.891 | E46: =(C45+D45+E45)*0.005 -> 10.891 | G46: =(+C45+D45+E45+G45)*0.005 -> 10.891 | I46: =(C45+D45+E45+G45+I45)*0.005 -> 10.891 | K46: =(C45+D45+E45+G45+I45+K45)*0.005 -> 10.891 | L46: =(C45+D45+E45+G45+I45+K45+L45)*0.005 -> 10.891 | M46: =(C45+D45+E45+G45+I45+K45+L45+M45)*0.005 -> 10.891 | N46: =(C45+D45+E45+G45+I45+K45+L45+M45+N45)*0.005 -> 10.891 | O46: =(C45+D45+E45+G45+I45+K45+L45+M45+N45+O45)*0.005 -> 10.891 | P46: =(C45+D45+E45+G45+I45+K45+L45+M45+N45+O45+P45)*0.005 -> 10.891 | R46: =(C45+D45+E45+G45+I45+K45+L45+M45+N45+O45+P45+R45)*0.005 -> 10.891 | S46: =(C45+D45+E45+G45+I45+K45+L45+M45+N45+O45+P45+R45+S45)*0.005 -> 10.891
A47: 19 | B47: Everth O. Acaso Jr. | C47: 58.71 | I47: 0 | U47: =C47+D47+E47+G47+I47+K47+L47+M47+N47+O47+P47+R47+S47 -> 58.71 | V47: =U47/12 -> 4.8925 | W47: =D48+E48+G48+I48+K48+L48+M48+N48+O48+P48+R48+S48 -> 3.5226 | X47: =U47+W47 -> 62.2326
C48: Interest per mo. | D48: =(C47+D47)*0.005 -> 0.29355 | E48: =(C47+D47+E47)*0.005 -> 0.29355 | G48: =(+C47+D47+E47+G47)*0.005 -> 0.29355 | I48: =(C47+D47+E47+G47+I47)*0.005 -> 0.29355 | K48: =(C47+D47+E47+G47+I47+K47)*0.005 -> 0.29355 | L48: =(C47+D47+E47+G47+I47+K47+L47)*0.005 -> 0.29355 | M48: =(C47+D47+E47+G47+I47+K47+L47+M47)*0.005 -> 0.29355 | N48: =(C47+D47+E47+G47+I47+K47+L47+M47+N47)*0.005 -> 0.29355 | O48: =(C47+D47+E47+G47+I47+K47+L47+M47+N47+O47)*0.005 -> 0.29355 | P48: =(C47+D47+E47+G47+I47+K47+L47+M47+N47+O47+P47)*0.005 -> 0.29355 | R48: =(C47+D47+E47+G47+I47+K47+L47+M47+N47+O47+P47+R47)*0.005 -> 0.29355 | S48: =(C47+D47+E47+G47+I47+K47+L47+M47+N47+O47+P47+R47+S47)*0.005 -> 0.29355
A49: 20 | B49: Joselito L. Edullantes | C49: 1704.79 | G49: 0 | I49: 0 | K49: 0 | L49: 0 | M49: 0 | U49: =C49+D49+E49+G49+I49+K49+L49+M49+N49+O49+P49+R49+S49 -> 1704.79 | V49: =U49/12 -> 142.06583 | W49: =D50+E50+G50+I50+K50+L50+M50+N50+O50+P50+R50+S50 -> 102.2874 | X49: =U49+W49 -> 1807.0774
C50: Interest per mo. | D50: =(C49+D49)*0.005 -> 8.52395 | E50: =(C49+D49+E49)*0.005 -> 8.52395 | G50: =(+C49+D49+E49+G49)*0.005 -> 8.52395 | I50: =(C49+D49+E49+G49+I49)*0.005 -> 8.52395 | K50: =(C49+D49+E49+G49+I49+K49)*0.005 -> 8.52395 | L50: =(C49+D49+E49+G49+I49+K49+L49)*0.005 -> 8.52395 | M50: =(C49+D49+E49+G49+I49+K49+L49+M49)*0.005 -> 8.52395 | N50: =(C49+D49+E49+G49+I49+K49+L49+M49+N49)*0.005 -> 8.52395 | O50: =(C49+D49+E49+G49+I49+K49+L49+M49+N49+O49)*0.005 -> 8.52395 | P50: =(C49+D49+E49+G49+I49+K49+L49+M49+N49+O49+P49)*0.005 -> 8.52395 | R50: =(C49+D49+E49+G49+I49+K49+L49+M49+N49+O49+P49+R49)*0.005 -> 8.52395 | S50: =(C49+D49+E49+G49+I49+K49+L49+M49+N49+O49+P49+R49+S49)*0.005 -> 8.52395
A51: 21 | B51: Agusto S. Jimenea | C51: 233.43 | G51: 0 | I51: 0 | K51: 0 | L51: 0 | M51: 0 | U51: =C51+D51+E51+G51+I51+K51+L51+M51+N51+O51+P51+R51+S51 -> 233.43 | V51: =U51/12 -> 19.4525 | W51: =D52+E52+G52+I52+K52+L52+M52+N52+O52+P52+R52+S52 -> 14.0058 | X51: =U51+W51 -> 247.4358
C52: Interest per mo. | D52: =(C51+D51)*0.005 -> 1.16715 | E52: =(C51+D51+E51)*0.005 -> 1.16715 | G52: =(+C51+D51+E51+G51)*0.005 -> 1.16715 | I52: =(C51+D51+E51+G51+I51)*0.005 -> 1.16715 | K52: =(C51+D51+E51+G51+I51+K51)*0.005 -> 1.16715 | L52: =(C51+D51+E51+G51+I51+K51+L51)*0.005 -> 1.16715 | M52: =(C51+D51+E51+G51+I51+K51+L51+M51)*0.005 -> 1.16715 | N52: =(C51+D51+E51+G51+I51+K51+L51+M51+N51)*0.005 -> 1.16715 | O52: =(C51+D51+E51+G51+I51+K51+L51+M51+N51+O51)*0.005 -> 1.16715 | P52: =(C51+D51+E51+G51+I51+K51+L51+M51+N51+O51+P51)*0.005 -> 1.16715 | R52: =(C51+D51+E51+G51+I51+K51+L51+M51+N51+O51+P51+R51)*0.005 -> 1.16715 | S52: =(C51+D51+E51+G51+I51+K51+L51+M51+N51+O51+P51+R51+S51)*0.005 -> 1.16715
A53: 22 | B53: Hazel Q. Bulacan | C53: 347.75 | L53: 0 | M53: 0 | U53: =C53+D53+E53+G53+I53+K53+L53+M53+N53+O53+P53+R53+S53 -> 347.75 | V53: =U53/12 -> 28.979167 | W53: =D54+E54+G54+I54+K54+L54+M54+N54+O54+P54+R54+S54 -> 20.865 | X53: =U53+W53 -> 368.615
C54: Interest per mo. | D54: =(C53+D53)*0.005 -> 1.73875 | E54: =(C53+D53+E53)*0.005 -> 1.73875 | G54: =(+C53+D53+E53+G53)*0.005 -> 1.73875 | I54: =(C53+D53+E53+G53+I53)*0.005 -> 1.73875 | K54: =(C53+D53+E53+G53+I53+K53)*0.005 -> 1.73875 | L54: =(C53+D53+E53+G53+I53+K53+L53)*0.005 -> 1.73875 | M54: =(C53+D53+E53+G53+I53+K53+L53+M53)*0.005 -> 1.73875 | N54: =(C53+D53+E53+G53+I53+K53+L53+M53+N53)*0.005 -> 1.73875 | O54: =(C53+D53+E53+G53+I53+K53+L53+M53+N53+O53)*0.005 -> 1.73875 | P54: =(C53+D53+E53+G53+I53+K53+L53+M53+N53+O53+P53)*0.005 -> 1.73875 | R54: =(C53+D53+E53+G53+I53+K53+L53+M53+N53+O53+P53+R53)*0.005 -> 1.73875 | S54: =(C53+D53+E53+G53+I53+K53+L53+M53+N53+O53+P53+R53+S53)*0.005 -> 1.73875
A55: 23 | B55: ='[1]Subscribed&Paid-up (2)'!$B$72 -> Concepcion B. Cruz | C55: 9270.35 | F55: 1500 | G55: 2500 | I55: 1000 | J55: 0 | K55: 0 | L55: 0 | M55: 0 | Q55: 8000 | U55: =C55+D55+E55-F55+G55+H55+I55+J55+K55+L55+M55+N55+O55+P55-Q55+R55+S55+D56+E56+F56+G56+H56+I56+J56+K56+L56+M56+N56+O56+P56+R56+S56 -> 3996.571 | V55: =U55/12 -> 333.04758 | W55: =D56+E56+G56+I56+K56+L56+M56+N56+O56+P56+R56+S56 -> 726.221 | X55: =U55+W55 -> 4722.792
C56: Interest per mo. | D56: =(C55+D55)*0.005 -> 46.35175 | E56: =(C55+D55+E55)*0.005 -> 46.35175 | G56: =(+C55+D55+E55+G55)*0.005 -> 58.85175 | I56: =(C55+D55+E55+G55+I55)*0.005 -> 63.85175 | K56: =(C55+D55+E55+G55+I55+K55)*0.005 -> 63.85175 | L56: =(C55+D55+E55+G55+I55+K55+L55)*0.005 -> 63.85175 | M56: =(C55+D55+E55+G55+I55+K55+L55+M55)*0.005 -> 63.85175 | N56: =(C55+D55+E55+G55+I55+K55+L55+M55+N55)*0.005 -> 63.85175 | O56: =(C55+D55+E55+G55+I55+K55+L55+M55+N55+O55)*0.005 -> 63.85175 | P56: =(C55+D55+E55+G55+I55+K55+L55+M55+N55+O55+P55)*0.005 -> 63.85175 | R56: =(C55+D55+E55+G55+I55+K55+L55+M55+N55+O55+P55+R55)*0.005 -> 63.85175 | S56: =(C55+D55+E55+G55+I55+K55+L55+M55+N55+O55+P55+R55+S55)*0.005 -> 63.85175
A57: 24 | B57: ='[1]Subscribed&Paid-up (2)'!$B$73 -> Leonardo B. Cruz | C57: 1545.46 | L57: 0 | U57: =C57+D57+E57+G57+I57+K57+L57+M57+N57+O57+P57+R57+S57 -> 1545.46 | V57: =U57/12 -> 128.78833 | W57: =D58+E58+G58+I58+K58+L58+M58+N58+O58+P58+R58+S58 -> 92.7276 | X57: =U57+W57 -> 1638.1876
C58: Interest per mo. | D58: =(C57+D57)*0.005 -> 7.7273 | E58: =(C57+D57+E57)*0.005 -> 7.7273 | G58: =(+C57+D57+E57+G57)*0.005 -> 7.7273 | I58: =(C57+D57+E57+G57+I57)*0.005 -> 7.7273 | K58: =(C57+D57+E57+G57+I57+K57)*0.005 -> 7.7273 | L58: =(C57+D57+E57+G57+I57+K57+L57)*0.005 -> 7.7273 | M58: =(C57+D57+E57+G57+I57+K57+L57+M57)*0.005 -> 7.7273 | N58: =(C57+D57+E57+G57+I57+K57+L57+M57+N57)*0.005 -> 7.7273 | O58: =(C57+D57+E57+G57+I57+K57+L57+M57+N57+O57)*0.005 -> 7.7273 | P58: =(C57+D57+E57+G57+I57+K57+L57+M57+N57+O57+P57)*0.005 -> 7.7273 | R58: =(C57+D57+E57+G57+I57+K57+L57+M57+N57+O57+P57+R57)*0.005 -> 7.7273 | S58: =(C57+D57+E57+G57+I57+K57+L57+M57+N57+O57+P57+R57+S57)*0.005 -> 7.7273
A59: 25 | B59: ='[1]Subscribed&Paid-up (2)'!$B$74 -> Annalyn B. Cruz | C59: 520.63 | R59: 0 | U59: =C59+D59+E59+G59+I59+K59+L59+M59+N59+O59+P59+R59+S59 -> 520.63 | V59: =U59/12 -> 43.385833 | W59: =D60+E60+G60+I60+K60+L60+M60+N60+O60+P60+R60+S60 -> 31.2378 | X59: =U59+W59 -> 551.8678
C60: Interest per mo. | D60: =(C59+D59)*0.005 -> 2.60315 | E60: =(C59+D59+E59)*0.005 -> 2.60315 | G60: =(+C59+D59+E59+G59)*0.005 -> 2.60315 | I60: =(C59+D59+E59+G59+I59)*0.005 -> 2.60315 | K60: =(C59+D59+E59+G59+I59+K59)*0.005 -> 2.60315 | L60: =(C59+D59+E59+G59+I59+K59+L59)*0.005 -> 2.60315 | M60: =(C59+D59+E59+G59+I59+K59+L59+M59)*0.005 -> 2.60315 | N60: =(C59+D59+E59+G59+I59+K59+L59+M59+N59)*0.005 -> 2.60315 | O60: =(C59+D59+E59+G59+I59+K59+L59+M59+N59+O59)*0.005 -> 2.60315 | P60: =(C59+D59+E59+G59+I59+K59+L59+M59+N59+O59+P59)*0.005 -> 2.60315 | R60: =(C59+D59+E59+G59+I59+K59+L59+M59+N59+O59+P59+R59)*0.005 -> 2.60315 | S60: =(C59+D59+E59+G59+I59+K59+L59+M59+N59+O59+P59+R59+S59)*0.005 -> 2.60315
A61: 26 | B61: ='[1]Subscribed&Paid-up (2)'!$B$76 -> Milben Rex P. Balao | C61: 807.87 | M61: 0 | R61: 0 | U61: =C61+D61+E61+G61+I61+K61+L61+M61+N61+O61+P61+R61+S61 -> 807.87 | V61: =U61/12 -> 67.3225 | W61: =D62+E62+G62+I62+K62+L62+M62+N62+O62+P62+R62+S62 -> 48.4722 | X61: =U61+W61 -> 856.3422
C62: Interest per mo. | D62: =(C61+D61)*0.005 -> 4.03935 | E62: =(C61+D61+E61)*0.005 -> 4.03935 | G62: =(+C61+D61+E61+G61)*0.005 -> 4.03935 | I62: =(C61+D61+E61+G61+I61)*0.005 -> 4.03935 | K62: =(C61+D61+E61+G61+I61+K61)*0.005 -> 4.03935 | L62: =(C61+D61+E61+G61+I61+K61+L61)*0.005 -> 4.03935 | M62: =(C61+D61+E61+G61+I61+K61+L61+M61)*0.005 -> 4.03935 | N62: =(C61+D61+E61+G61+I61+K61+L61+M61+N61)*0.005 -> 4.03935 | O62: =(C61+D61+E61+G61+I61+K61+L61+M61+N61+O61)*0.005 -> 4.03935 | P62: =(C61+D61+E61+G61+I61+K61+L61+M61+N61+O61+P61)*0.005 -> 4.03935 | R62: =(C61+D61+E61+G61+I61+K61+L61+M61+N61+O61+P61+R61)*0.005 -> 4.03935 | S62: =(C61+D61+E61+G61+I61+K61+L61+M61+N61+O61+P61+R61+S61)*0.005 -> 4.03935
A63: 27 | B63: Victoriana Entero | C63: 7254.64 | O63: 0 | S63: 0 | U63: =C63+D63+E63+G63+I63+K63+L63+M63+N63+O63+P63+R63+S63 -> 7254.64 | V63: =U63/12 -> 604.55333 | W63: =D64+E64+G64+I64+K64+L64+M64+N64+O64+P64+R64+S64 -> 435.2784 | X63: =U63+W63 -> 7689.9184
C64: Interest per mo. | D64: =(C63+D63)*0.005 -> 36.2732 | E64: =(C63+D63+E63)*0.005 -> 36.2732 | G64: =(+C63+D63+E63+G63)*0.005 -> 36.2732 | I64: =(C63+D63+E63+G63+I63)*0.005 -> 36.2732 | K64: =(C63+D63+E63+G63+I63+K63)*0.005 -> 36.2732 | L64: =(C63+D63+E63+G63+I63+K63+L63)*0.005 -> 36.2732 | M64: =(C63+D63+E63+G63+I63+K63+L63+M63)*0.005 -> 36.2732 | N64: =(C63+D63+E63+G63+I63+K63+L63+M63+N63)*0.005 -> 36.2732 | O64: =(C63+D63+E63+G63+I63+K63+L63+M63+N63+O63)*0.005 -> 36.2732 | P64: =(C63+D63+E63+G63+I63+K63+L63+M63+N63+O63+P63)*0.005 -> 36.2732 | R64: =(C63+D63+E63+G63+I63+K63+L63+M63+N63+O63+P63+R63)*0.005 -> 36.2732 | S64: =(C63+D63+E63+G63+I63+K63+L63+M63+N63+O63+P63+R63+S63)*0.005 -> 36.2732
A65: 28 | B65: Diosita J. Aquino | C65: 114.05 | P65: 0 | U65: =C65+D65+E65+G65+I65+K65+L65+M65+N65+O65+P65+R65+S65 -> 114.05 | V65: =U65/12 -> 9.5041667 | W65: =D66+E66+G66+I66+K66+L66+M66+N66+O66+P66+R66+S66 -> 6.843 | X65: =U65+W65 -> 120.893
C66: Interest per mo. | D66: =(C65+D65)*0.005 -> 0.57025 | E66: =(C65+D65+E65)*0.005 -> 0.57025 | G66: =(+C65+D65+E65+G65)*0.005 -> 0.57025 | I66: =(C65+D65+E65+G65+I65)*0.005 -> 0.57025 | K66: =(C65+D65+E65+G65+I65+K65)*0.005 -> 0.57025 | L66: =(C65+D65+E65+G65+I65+K65+L65)*0.005 -> 0.57025 | M66: =(C65+D65+E65+G65+I65+K65+L65+M65)*0.005 -> 0.57025 | N66: =(C65+D65+E65+G65+I65+K65+L65+M65+N65)*0.005 -> 0.57025 | O66: =(C65+D65+E65+G65+I65+K65+L65+M65+N65+O65)*0.005 -> 0.57025 | P66: =(C65+D65+E65+G65+I65+K65+L65+M65+N65+O65+P65)*0.005 -> 0.57025 | R66: =(C65+D65+E65+G65+I65+K65+L65+M65+N65+O65+P65+R65)*0.005 -> 0.57025 | S66: =(C65+D65+E65+G65+I65+K65+L65+M65+N65+O65+P65+R65+S65)*0.005 -> 0.57025
A67: 29 | B67: Perpetuo O. Gaelo | C67: =9218.04+41.66 -> 9259.7 | P67: 0 | U67: =C67+D67+E67-F67+G67+I67-H67+K67+L67+M67+N67+O67+P67+R67+S67 -> 9259.7 | V67: =U67/12 -> 771.64167 | W67: =D68+E68+G68+I68+K68+L68+M68+N68+O68+P68+R68+S68 -> 555.582 | X67: =U67+W67 -> 9815.282
C68: Interest per mo. | D68: =(C67+D67)*0.005 -> 46.2985 | E68: =(C67+D67+E67)*0.005 -> 46.2985 | G68: =(+C67+D67+E67+G67)*0.005 -> 46.2985 | I68: =(C67+D67+E67+G67+I67)*0.005 -> 46.2985 | K68: =(C67+D67+E67+G67+I67+K67)*0.005 -> 46.2985 | L68: =(C67+D67+E67+G67+I67+K67+L67)*0.005 -> 46.2985 | M68: =(C67+D67+E67+G67+I67+K67+L67+M67)*0.005 -> 46.2985 | N68: =(C67+D67+E67+G67+I67+K67+L67+M67+N67)*0.005 -> 46.2985 | O68: =(C67+D67+E67+G67+I67+K67+L67+M67+N67+O67)*0.005 -> 46.2985 | P68: =(C67+D67+E67+G67+I67+K67+L67+M67+N67+O67+P67)*0.005 -> 46.2985 | R68: =(C67+D67+E67+G67+I67+K67+L67+M67+N67+O67+P67+R67)*0.005 -> 46.2985 | S68: =(C67+D67+E67+G67+I67+K67+L67+M67+N67+O67+P67+R67+S67)*0.005 -> 46.2985
A69: 30 | B69: Eloisa Williams | C69: 411.24 | P69: 0 | U69: =C69+D69+E69+G69+I69+K69+L69+M69+N69+O69+P69+R69+S69 -> 411.24 | V69: =U69/12 -> 34.27 | W69: =D70+E70+G70+I70+K70+L70+M70+N70+O70+P70+R70+S70 -> 24.6744 | X69: =U69+W69 -> 435.9144
C70: Interest per mo. | D70: =(C69+D69)*0.005 -> 2.0562 | E70: =(C69+D69+E69)*0.005 -> 2.0562 | G70: =(+C69+D69+E69+G69)*0.005 -> 2.0562 | I70: =(C69+D69+E69+G69+I69)*0.005 -> 2.0562 | K70: =(C69+D69+E69+G69+I69+K69)*0.005 -> 2.0562 | L70: =(C69+D69+E69+G69+I69+K69+L69)*0.005 -> 2.0562 | M70: =(C69+D69+E69+G69+I69+K69+L69+M69)*0.005 -> 2.0562 | N70: =(C69+D69+E69+G69+I69+K69+L69+M69+N69)*0.005 -> 2.0562 | O70: =(C69+D69+E69+G69+I69+K69+L69+M69+N69+O69)*0.005 -> 2.0562 | P70: =(C69+D69+E69+G69+I69+K69+L69+M69+N69+O69+P69)*0.005 -> 2.0562 | R70: =(C69+D69+E69+G69+I69+K69+L69+M69+N69+O69+P69+R69)*0.005 -> 2.0562 | S70: =(C69+D69+E69+G69+I69+K69+L69+M69+N69+O69+P69+R69+S69)*0.005 -> 2.0562
A71: 31 | B71: Paul Espinosa | C71: 106.15 | P71: 0 | U71: =C71+D71+E71+G71+I71+K71+L71+M71+N71+O71+P71+R71+S71 -> 106.15 | V71: =U71/12 -> 8.8458333 | W71: =D72+E72+G72+I72+K72+L72+M72+N72+O72+P72+R72+S72 -> 6.369 | X71: =U71+W71 -> 112.519
C72: Interest per mo. | D72: =(C71+D71)*0.005 -> 0.53075 | E72: =(C71+D71+E71)*0.005 -> 0.53075 | G72: =(+C71+D71+E71+G71)*0.005 -> 0.53075 | I72: =(C71+D71+E71+G71+I71)*0.005 -> 0.53075 | K72: =(C71+D71+E71+G71+I71+K71)*0.005 -> 0.53075 | L72: =(C71+D71+E71+G71+I71+K71+L71)*0.005 -> 0.53075 | M72: =(C71+D71+E71+G71+I71+K71+L71+M71)*0.005 -> 0.53075 | N72: =(C71+D71+E71+G71+I71+K71+L71+M71+N71)*0.005 -> 0.53075 | O72: =(C71+D71+E71+G71+I71+K71+L71+M71+N71+O71)*0.005 -> 0.53075 | P72: =(C71+D71+E71+G71+I71+K71+L71+M71+N71+O71+P71)*0.005 -> 0.53075 | R72: =(C71+D71+E71+G71+I71+K71+L71+M71+N71+O71+P71+R71)*0.005 -> 0.53075 | S72: =(C71+D71+E71+G71+I71+K71+L71+M71+N71+O71+P71+R71+S71)*0.005 -> 0.53075
A73: 32 | B73: Joventino Larrosa | C73: 2640.46 | P73: 0 | U73: =C73+D73+E73+G73+I73+K73+L73+M73+N73+O73+P73+R73+S73 -> 2640.46 | V73: =U73/12 -> 220.03833 | W73: =D74+E74+G74+I74+K74+L74+M74+N74+O74+P74+R74+S74 -> 158.4276 | X73: =U73+W73 -> 2798.8876
C74: Interest per mo. | D74: =(C73+D73)*0.005 -> 13.2023 | E74: =(C73+D73+E73)*0.005 -> 13.2023 | G74: =(+C73+D73+E73+G73)*0.005 -> 13.2023 | I74: =(C73+D73+E73+G73+I73)*0.005 -> 13.2023 | K74: =(C73+D73+E73+G73+I73+K73)*0.005 -> 13.2023 | L74: =(C73+D73+E73+G73+I73+K73+L73)*0.005 -> 13.2023 | M74: =(C73+D73+E73+G73+I73+K73+L73+M73)*0.005 -> 13.2023 | N74: =(C73+D73+E73+G73+I73+K73+L73+M73+N73)*0.005 -> 13.2023 | O74: =(C73+D73+E73+G73+I73+K73+L73+M73+N73+O73)*0.005 -> 13.2023 | P74: =(C73+D73+E73+G73+I73+K73+L73+M73+N73+O73+P73)*0.005 -> 13.2023 | R74: =(C73+D73+E73+G73+I73+K73+L73+M73+N73+O73+P73+R73)*0.005 -> 13.2023 | S74: =(C73+D73+E73+G73+I73+K73+L73+M73+N73+O73+P73+R73+S73)*0.005 -> 13.2023
A75: 33 | B75: Jociel Esmero | C75: 870.26 | M75: 0 | N75: 0 | P75: 0 | U75: =C75+D75+E75+G75+I75+K75+L75+M75+N75+O75+P75+R75+S75 -> 870.26 | V75: =U75/12 -> 72.521667 | W75: =D76+E76+G76+I76+K76+L76+M76+N76+O76+P76+R76+S76 -> 52.2156 | X75: =U75+W75 -> 922.4756
C76: Interest per mo. | D76: =(C75+D75)*0.005 -> 4.3513 | E76: =(C75+D75+E75)*0.005 -> 4.3513 | G76: =(+C75+D75+E75+G75)*0.005 -> 4.3513 | I76: =(C75+D75+E75+G75+I75)*0.005 -> 4.3513 | K76: =(C75+D75+E75+G75+I75+K75)*0.005 -> 4.3513 | L76: =(C75+D75+E75+G75+I75+K75+L75)*0.005 -> 4.3513 | M76: =(C75+D75+E75+G75+I75+K75+L75+M75)*0.005 -> 4.3513 | N76: =(C75+D75+E75+G75+I75+K75+L75+M75+N75)*0.005 -> 4.3513 | O76: =(C75+D75+E75+G75+I75+K75+L75+M75+N75+O75)*0.005 -> 4.3513 | P76: =(C75+D75+E75+G75+I75+K75+L75+M75+N75+O75+P75)*0.005 -> 4.3513 | R76: =(C75+D75+E75+G75+I75+K75+L75+M75+N75+O75+P75+R75)*0.005 -> 4.3513 | S76: =(C75+D75+E75+G75+I75+K75+L75+M75+N75+O75+P75+R75+S75)*0.005 -> 4.3513
A77: 34 | B77: Alma Bola | C77: 1055.75 | N77: 500 | P77: 0 | U77: =C77+D77+E77+G77+I77+K77+L77+M77+N77+O77+P77+R77+S77 -> 1555.75 | V77: =U77/12 -> 129.64583 | W77: =D78+E78+G78+I78+K78+L78+M78+N78+O78+P78+R78+S78 -> 75.845 | X77: =U77+W77 -> 1631.595
C78: Interest per mo. | D78: =(C77+D77)*0.005 -> 5.27875 | E78: =(C77+D77+E77)*0.005 -> 5.27875 | G78: =(+C77+D77+E77+G77)*0.005 -> 5.27875 | I78: =(C77+D77+E77+G77+I77)*0.005 -> 5.27875 | K78: =(C77+D77+E77+G77+I77+K77)*0.005 -> 5.27875 | L78: =(C77+D77+E77+G77+I77+K77+L77)*0.005 -> 5.27875 | M78: =(C77+D77+E77+G77+I77+K77+L77+M77)*0.005 -> 5.27875 | N78: =(C77+D77+E77+G77+I77+K77+L77+M77+N77)*0.005 -> 7.77875 | O78: =(C77+D77+E77+G77+I77+K77+L77+M77+N77+O77)*0.005 -> 7.77875 | P78: =(C77+D77+E77+G77+I77+K77+L77+M77+N77+O77+P77)*0.005 -> 7.77875 | R78: =(C77+D77+E77+G77+I77+K77+L77+M77+N77+O77+P77+R77)*0.005 -> 7.77875 | S78: =(C77+D77+E77+G77+I77+K77+L77+M77+N77+O77+P77+R77+S77)*0.005 -> 7.77875
A79: 35 | B79: Sabiniano Caparoso | C79: =7251.8+41.66 -> 7293.46 | P79: 0 | U79: =C79+D79+E79+G79+I79+K79+L79+M79+N79+O79+P79+R79+S79 -> 7293.46 | V79: =U79/12 -> 607.78833 | W79: =D80+E80+G80+I80+K80+L80+M80+N80+O80+P80+R80+S80 -> 437.6076 | X79: =U79+W79 -> 7731.0676
C80: Interest per mo. | D80: =(C79+D79)*0.005 -> 36.4673 | E80: =(C79+D79+E79)*0.005 -> 36.4673 | G80: =(+C79+D79+E79+G79)*0.005 -> 36.4673 | I80: =(C79+D79+E79+G79+I79)*0.005 -> 36.4673 | K80: =(C79+D79+E79+G79+I79+K79)*0.005 -> 36.4673 | L80: =(C79+D79+E79+G79+I79+K79+L79)*0.005 -> 36.4673 | M80: =(C79+D79+E79+G79+I79+K79+L79+M79)*0.005 -> 36.4673 | N80: =(C79+D79+E79+G79+I79+K79+L79+M79+N79)*0.005 -> 36.4673 | O80: =(C79+D79+E79+G79+I79+K79+L79+M79+N79+O79)*0.005 -> 36.4673 | P80: =(C79+D79+E79+G79+I79+K79+L79+M79+N79+O79+P79)*0.005 -> 36.4673 | R80: =(C79+D79+E79+G79+I79+K79+L79+M79+N79+O79+P79+R79)*0.005 -> 36.4673 | S80: =(C79+D79+E79+G79+I79+K79+L79+M79+N79+O79+P79+R79+S79)*0.005 -> 36.4673
A81: 35 | B81: EUNIECELLE SAMSON | C81: 1045 | P81: 0 | R81: 0 | U81: =C81+D81+E81+G81+I81+K81+L81+M81+N81+O81+P81+R81+S81 -> 1045 | V81: =U81/12 -> 87.083333 | W81: =D82+E82+G82+I82+K82+L82+M82+N82+O82+P82+R82+S82 -> 62.7 | X81: =U81+W81 -> 1107.7
C82: Interest per mo. | D82: =(C81+D81)*0.005 -> 5.225 | E82: =(C81+D81+E81)*0.005 -> 5.225 | G82: =(+C81+D81+E81+G81)*0.005 -> 5.225 | I82: =(C81+D81+E81+G81+I81)*0.005 -> 5.225 | K82: =(C81+D81+E81+G81+I81+K81)*0.005 -> 5.225 | L82: =(C81+D81+E81+G81+I81+K81+L81)*0.005 -> 5.225 | M82: =(C81+D81+E81+G81+I81+K81+L81+M81)*0.005 -> 5.225 | N82: =(C81+D81+E81+G81+I81+K81+L81+M81+N81)*0.005 -> 5.225 | O82: =(C81+D81+E81+G81+I81+K81+L81+M81+N81+O81)*0.005 -> 5.225 | P82: =(C81+D81+E81+G81+I81+K81+L81+M81+N81+O81+P81)*0.005 -> 5.225 | R82: =(C81+D81+E81+G81+I81+K81+L81+M81+N81+O81+P81+R81)*0.005 -> 5.225 | S82: =(C81+D81+E81+G81+I81+K81+L81+M81+N81+O81+P81+R81+S81)*0.005 -> 5.225
A83: 36 | B83: Patricio Lloyd Tellidua | C83: =502.5+44.63 -> 547.13 | D83: 500 | E83: 500 | P83: 0 | R83: 0 | U83: =C83+D83+E83+G83+I83+K83+L83+M83+N83+O83+P83+R83+S83 -> 1547.13 | V83: =U83/12 -> 128.9275 | W83: =D84+E84+G84+I84+K84+L84+M84+N84+O84+P84+R84+S84 -> 90.3278 | X83: =U83+W83 -> 1637.4578
C84: Interest per mo. | D84: =(C83+D83)*0.005 -> 5.23565 | E84: =(C83+D83+E83)*0.005 -> 7.73565 | G84: =(+C83+D83+E83+G83)*0.005 -> 7.73565 | I84: =(C83+D83+E83+G83+I83)*0.005 -> 7.73565 | K84: =(C83+D83+E83+G83+I83+K83)*0.005 -> 7.73565 | L84: =(C83+D83+E83+G83+I83+K83+L83)*0.005 -> 7.73565 | M84: =(C83+D83+E83+G83+I83+K83+L83+M83)*0.005 -> 7.73565 | N84: =(C83+D83+E83+G83+I83+K83+L83+M83+N83)*0.005 -> 7.73565 | O84: =(C83+D83+E83+G83+I83+K83+L83+M83+N83+O83)*0.005 -> 7.73565 | P84: =(C83+D83+E83+G83+I83+K83+L83+M83+N83+O83+P83)*0.005 -> 7.73565 | R84: =(C83+D83+E83+G83+I83+K83+L83+M83+N83+O83+P83+R83)*0.005 -> 7.73565 | S84: =(C83+D83+E83+G83+I83+K83+L83+M83+N83+O83+P83+R83+S83)*0.005 -> 7.73565
B86: TOTAL | C86: =SUM(C10:C79) -> 80679.47 | U86: =SUM(U10:U79) -> 77580.691 | V86: =SUM(V10:V79) -> 6465.0576 | W86: =SUM(W10:W79) -> 5114.5182 | X86: =SUM(X10:X79) -> 82695.209
A88: Prepared by: | E88: Checked by: | N88: Noted by: | U88: Approved by:
B91: SHALOU J. BALAO | G91: MARIA GENIA C. SEGUIDO | O91: ARNOLD C. GONZALES | V91: DEXTER B. JUMAO-AS
B92: SCSCC Secretary | G92: SCSCC Treasurer | O92: General Manager, SCSCC | V92: Chairman, SCSCC BOD
X95: Page 2 of 2
U99: Regular | V99: =18 -> 18 | W99: =X10+X14+X16+X18+X20+X22+X24+X26+X28+X30+X32+X34+X38+X43+X45+X53+X65+X36+X55+X57+X59+X61 -> 48169.482
U100: Associates | V100: 11 | W100: =X12+X47+X49+X51+X55+X57+X59+X61+X63+X67 -> 28662.457
V101: =V99+V100 -> 29 | W101: =W99+W100 -> 76831.94

Sheet Savings2023
A2: SIDLAK CHRISTIAN CHILDREN FUND SAVINGS AND CREDIT COOPERATIVE
A3: CDA Registration No. 9520-1080000000036399 Dated: November 16, 2016
A4: P-2, Brgy. Linao, Ormoc City
A6: COMPUTATION OF SAVINGS DEPOSITS
A7: As of FY 2023
A9: Members | C9: 2022 Savings | D9: Jan | E9: Feb | F9: withdrawal | G9: Mar | H9: withdrawal | I9: Apr | J9: withdrawal | K9: May | L9: Jun | M9: Jul | N9: Aug | O9: Sep | P9: Oct | Q9: Withdrawal | R9: Nov | S9: Dec | T9: withdrawal | U9: TSAD | V9: ASAD | W9: Int. on TSAD | X9: Total (SAD + Interest)
A10: 1 | B10: Allen L. Gubalane | C10: =393.9+23.63 -> 417.53 | U10: =C10+D10+E10+G10+I10+K10+L10+M10+N10+O10+P10+R10+S10 -> 417.53 | V10: =U10/12 -> 34.794167 | W10: =D11+E11+G11+I11+K11+L11+M11+N11+O11+P11+R11+S11 -> 25.0518 | X10: =U10+W10 -> 442.5818
C11: Interest per mo. | D11: =(C10+D10)*0.005 -> 2.08765 | E11: =(C10+D10+E10)*0.005 -> 2.08765 | G11: =(+C10+D10+E10+G10)*0.005 -> 2.08765 | I11: =(C10+D10+E10+G10+I10)*0.005 -> 2.08765 | K11: =(C10+D10+E10+G10+I10+K10)*0.005 -> 2.08765 | L11: =(C10+D10+E10+G10+I10+K10+L10)*0.005 -> 2.08765 | M11: =(C10+D10+E10+G10+I10+K10+L10+M10)*0.005 -> 2.08765 | N11: =(C10+D10+E10+G10+I10+K10+L10+M10+N10)*0.005 -> 2.08765 | O11: =(C10+D10+E10+G10+I10+K10+L10+M10+N10+O10)*0.005 -> 2.08765 | P11: =(C10+D10+E10+G10+I10+K10+L10+M10+N10+O10+P10)*0.005 -> 2.08765 | R11: =(C10+D10+E10+G10+I10+K10+L10+M10+N10+O10+P10+R10)*0.005 -> 2.08765 | S11: =(C10+D10+E10+G10+I10+K10+L10+M10+N10+O10+P10+R10+S10)*0.005 -> 2.08765
A12: 2 | B12: April A. Hubahib | C12: =1199.36+71.96 -> 1271.32 | U12: =C12+D12+E12+G12+I12+K12+L12+M12+N12+O12+P12+R12+S12 -> 1271.32 | V12: =U12/12 -> 105.94333 | W12: =D13+E13+G13+I13+K13+L13+M13+N13+O13+P13+R13+S13 -> 76.2792 | X12: =U12+W12 -> 1347.5992
C13: Interest per mo. | D13: =(C12+D12)*0.005 -> 6.3566 | E13: =(C12+D12+E12)*0.005 -> 6.3566 | G13: =(+C12+D12+E12+G12)*0.005 -> 6.3566 | I13: =(C12+D12+E12+G12+I12)*0.005 -> 6.3566 | K13: =(C12+D12+E12+G12+I12+K12)*0.005 -> 6.3566 | L13: =(C12+D12+E12+G12+I12+K12+L12)*0.005 -> 6.3566 | M13: =(C12+D12+E12+G12+I12+K12+L12+M12)*0.005 -> 6.3566 | N13: =(C12+D12+E12+G12+I12+K12+L12+M12+N12)*0.005 -> 6.3566 | O13: =(C12+D12+E12+G12+I12+K12+L12+M12+N12+O12)*0.005 -> 6.3566 | P13: =(C12+D12+E12+G12+I12+K12+L12+M12+N12+O12+P12)*0.005 -> 6.3566 | R13: =(C12+D12+E12+G12+I12+K12+L12+M12+N12+O12+P12+R12)*0.005 -> 6.3566 | S13: =(C12+D12+E12+G12+I12+K12+L12+M12+N12+O12+P12+R12+S12)*0.005 -> 6.3566
A14: 3 | B14: Crisencia R. Ruiz | C14: =3776.1+226.57 -> 4002.67 | U14: =C14+D14+E14+G14+I14+K14+L14+M14+N14+O14+P14+R14+S14 -> 4002.67 | V14: =U14/12 -> 333.55583 | W14: =D15+E15+G15+I15+K15+L15+M15+N15+O15+P15+R15+S15 -> 240.1602 | X14: =U14+W14 -> 4242.8302
C15: Interest per mo. | D15: =(C14+D14)*0.005 -> 20.01335 | E15: =(C14+D14+E14)*0.005 -> 20.01335 | G15: =(+C14+D14+E14+G14)*0.005 -> 20.01335 | I15: =(C14+D14+E14+G14+I14)*0.005 -> 20.01335 | K15: =(C14+D14+E14+G14+I14+K14)*0.005 -> 20.01335 | L15: =(C14+D14+E14+G14+I14+K14+L14)*0.005 -> 20.01335 | M15: =(C14+D14+E14+G14+I14+K14+L14+M14)*0.005 -> 20.01335 | N15: =(C14+D14+E14+G14+I14+K14+L14+M14+N14)*0.005 -> 20.01335 | O15: =(C14+D14+E14+G14+I14+K14+L14+M14+N14+O14)*0.005 -> 20.01335 | P15: =(C14+D14+E14+G14+I14+K14+L14+M14+N14+O14+P14)*0.005 -> 20.01335 | R15: =(C14+D14+E14+G14+I14+K14+L14+M14+N14+O14+P14+R14)*0.005 -> 20.01335 | S15: =(C14+D14+E14+G14+I14+K14+L14+M14+N14+O14+P14+R14+S14)*0.005 -> 20.01335
A16: 4 | B16: Dexter B. Jumao-as | C16: =13738.55+813.06 -> 14551.61 | D16: 1000 | E16: 500 | G16: 500 | I16: 0 | K16: 0 | L16: 500 | M16: 0 | N16: 0 | O16: 0 | P16: 0 | R16: 0 | S16: 0 | U16: =C16+D16+E16+G16+I16+K16+L16+M16+N16+O16+P16+R16+S16-T16 -> 17051.61 | V16: =U16/12 -> 1420.9675 | W16: =D17+E17+G17+I17+K17+L17+M17+N17+O17+P17+R17+S17 -> 1003.0966 | X16: =U16+W16 -> 18054.707
C17: Interest per mo. | D17: =(C16+D16)*0.005 -> 77.75805 | E17: =(C16+D16+E16)*0.005 -> 80.25805 | G17: =(+C16+D16+E16+G16)*0.005 -> 82.75805 | I17: =(C16+D16+E16+G16+I16)*0.005 -> 82.75805 | K17: =(C16+D16+E16+G16+I16+K16)*0.005 -> 82.75805 | L17: =(C16+D16+E16+G16+I16+K16+L16)*0.005 -> 85.25805 | M17: =(C16+D16+E16+G16+I16+K16+L16+M16)*0.005 -> 85.25805 | N17: =(C16+D16+E16+G16+I16+K16+L16+M16+N16)*0.005 -> 85.25805 | O17: =(C16+D16+E16+G16+I16+K16+L16+M16+N16+O16)*0.005 -> 85.25805 | P17: =(C16+D16+E16+G16+I16+K16+L16+M16+N16+O16+P16)*0.005 -> 85.25805 | R17: =(C16+D16+E16+G16+I16+K16+L16+M16+N16+O16+P16+R16)*0.005 -> 85.25805 | S17: =(C16+D16+E16+G16+I16+K16+L16+M16+N16+O16+P16+R16+S16)*0.005 -> 85.25805
A18: 5 | B18: Dorotea B. Jumao-as | C18: =7511.12+450.67 -> 7961.79 | D18: 0 | G18: 0 | I18: 0 | L18: 0 | N18: 0 | R18: 0 | U18: =C18+D18+E18+G18+I18+K18+L18+M18+N18+O18+P18+R18+S18 -> 7961.79 | V18: =U18/12 -> 663.4825 | W18: =D19+E19+G19+I19+K19+L19+M19+N19+O19+P19+R19+S19 -> 477.7074 | X18: =U18+W18 -> 8439.4974
C19: Interest per mo. | D19: =(C18+D18)*0.005 -> 39.80895 | E19: =(C18+D18+E18)*0.005 -> 39.80895 | G19: =(+C18+D18+E18+G18)*0.005 -> 39.80895 | I19: =(C18+D18+E18+G18+I18)*0.005 -> 39.80895 | K19: =(C18+D18+E18+G18+I18+K18)*0.005 -> 39.80895 | L19: =(C18+D18+E18+G18+I18+K18+L18)*0.005 -> 39.80895 | M19: =(C18+D18+E18+G18+I18+K18+L18+M18)*0.005 -> 39.80895 | N19: =(C18+D18+E18+G18+I18+K18+L18+M18+N18)*0.005 -> 39.80895 | O19: =(C18+D18+E18+G18+I18+K18+L18+M18+N18+O18)*0.005 -> 39.80895 | P19: =(C18+D18+E18+G18+I18+K18+L18+M18+N18+O18+P18)*0.005 -> 39.80895 | R19: =(C18+D18+E18+G18+I18+K18+L18+M18+N18+O18+P18+R18)*0.005 -> 39.80895 | S19: =(C18+D18+E18+G18+I18+K18+L18+M18+N18+O18+P18+R18+S18)*0.005 -> 39.80895
A20: 6 | B20: Edgardo P. Nodalo | C20: 0 | V20: =U20/12 -> 0 | W20: =D21+E21+G21+I21+K21+L21+M21+N21+O21+P21+R21+S21 -> 0 | X20: =U20+W20 -> 0
C21: Interest per mo. | D21: =(C20+D20)*0.005 -> 0 | E21: =(C20+D20+E20)*0.005 -> 0 | G21: =(+C20+D20+E20+G20)*0.005 -> 0 | I21: =(C20+D20+E20+G20+I20)*0.005 -> 0 | K21: =(C20+D20+E20+G20+I20+K20)*0.005 -> 0 | L21: =(C20+D20+E20+G20+I20+K20+L20)*0.005 -> 0 | M21: =(C20+D20+E20+G20+I20+K20+L20+M20)*0.005 -> 0 | N21: =(C20+D20+E20+G20+I20+K20+L20+M20+N20)*0.005 -> 0 | O21: =(C20+D20+E20+G20+I20+K20+L20+M20+N20+O20)*0.005 -> 0 | P21: =(C20+D20+E20+G20+I20+K20+L20+M20+N20+O20+P20)*0.005 -> 0 | R21: =(C20+D20+E20+G20+I20+K20+L20+M20+N20+O20+P20+R20)*0.005 -> 0 | S21: =(C20+D20+E20+G20+I20+K20+L20+M20+N20+O20+P20+R20+S20)*0.005 -> 0
A22: 8 | B22: Emmanuel S. Quilantang | C22: =1036.83+62.21 -> 1099.04 | U22: =C22+D22+E22+G22+I22+K22+L22+M22+N22+O22+P22+R22+S22 -> 1099.04 | V22: =U22/12 -> 91.586667 | W22: =D23+E23+G23+I23+K23+L23+M23+N23+O23+P23+R23+S23 -> 65.9424 | X22: =U22+W22 -> 1164.9824
C23: Interest per mo. | D23: =(C22+D22)*0.005 -> 5.4952 | E23: =(C22+D22+E22)*0.005 -> 5.4952 | G23: =(+C22+D22+E22+G22)*0.005 -> 5.4952 | I23: =(C22+D22+E22+G22+I22)*0.005 -> 5.4952 | K23: =(C22+D22+E22+G22+I22+K22)*0.005 -> 5.4952 | L23: =(C22+D22+E22+G22+I22+K22+L22)*0.005 -> 5.4952 | M23: =(C22+D22+E22+G22+I22+K22+L22+M22)*0.005 -> 5.4952 | N23: =(C22+D22+E22+G22+I22+K22+L22+M22+N22)*0.005 -> 5.4952 | O23: =(C22+D22+E22+G22+I22+K22+L22+M22+N22+O22)*0.005 -> 5.4952 | P23: =(C22+D22+E22+G22+I22+K22+L22+M22+N22+O22+P22)*0.005 -> 5.4952 | R23: =(C22+D22+E22+G22+I22+K22+L22+M22+N22+O22+P22+R22)*0.005 -> 5.4952 | S23: =(C22+D22+E22+G22+I22+K22+L22+M22+N22+O22+P22+R22+S22)*0.005 -> 5.4952
A24: 9 | B24: Erlinda E. Quilantang | C24: =1106.42+66.39 -> 1172.81 | U24: =C24+D24+E24+G24+I24+K24+L24+M24+N24+O24+P24+R24+S24 -> 1172.81 | V24: =U24/12 -> 97.734167 | W24: =D25+E25+G25+I25+K25+L25+M25+N25+O25+P25+R25+S25 -> 70.3686 | X24: =U24+W24 -> 1243.1786
