Workbook

Sheet SUMMARY
A2: BRANCH NAME:
A3: FOR THE MONTH OF: JULY
A5: GROSS SALES | D5: COGS | G5: DELIVERIES | J5: B.O | M5: ENDING INVENTORY
A6: CATEGORIES | B6: TOTAL | D6: CATEGORIES | E6: TOTAL | G6: CATEGORIES | H6: TOTAL | J6: CATEGORIES | K6: TOTAL | M6: CATEGORIES | N6: TOTAL
B7: AMOUNT | E7: AMOUNT | H7: AMOUNT | K7: AMOUNT | N7: AMOUNT
A8: DAILY | B8: =GROSS!CA55 -> 512383 | D8: DAILY | E8: ='DAILY COGS'!CA55 -> 332893.88 | G8: DAILY | H8: =DELIVERIES!CA55 -> 335172.5 | J8: DAILY | K8: =B.O!CA55 -> 0 | M8: DAILY | N8: ='MONTHLY INV.'!K30 -> 18206.5
A9: WEEKLY | B9: ='WEEKLY INV.'!T121 -> 512383 | D9: WEEKLY | E9: ='WEEKLY INV.'!P121 -> 332893.88 | G9: WEEKLY | H9: ='WEEKLY INV.'!F121 -> 335172.5 | J9: WEEKLY | K9: ='WEEKLY INV.'!H121 -> 0 | M9: WEEKLY | N9: ='WEEKLY INV.'!K119 -> 18206.5
A10: MONTHLY | B10: ='MONTHLY INV.'!T30 -> 512383 | D10: MONTHLY | E10: ='MONTHLY INV.'!P30 -> 332893.88 | G10: MONTHLY | H10: ='MONTHLY INV.'!F30 -> 335172.5 | J10: MONTHLY | K10: ='MONTHLY INV.'!H30 -> 0 | M10: MONTHLY | N10: ='MONTHLY INV.'!K30 -> 18206.5
B11: =B10-'income statement'!C19 -> 0 | E11: =E9-E8 -> 0

Sheet DAILY SUMMARY
A1: CRISPY KING FOOD STATION
A2: DAILY SALES SUMMARY — JULY 2026
A3: DAY | B3: DATE | C3: GROSS SALES | D3: LESS EXPENSES | E3: NET SALES | F3: CASH DEPOSIT | G3: OVER/SHORT | H3: TOTAL OPEX | I3: TOTAL CAPEX | J3: TOTAL PURCHASES | K3: TOTAL DELIVERIES | L3: REMARKS
A4: 1 | B4: ='1'!T3 -> 46204 | C4: ='1'!B33 -> 14797 | D4: ='1'!B34 -> 5970 | E4: ='1'!B35 -> 8827 | F4: ='1'!B36 -> 8827 | G4: ='1'!B37 -> 0 | H4: ='1'!T30 -> 4270 | I4: ='1'!W30 -> 0 | J4: ='1'!W22 -> 1700 | K4: ='1'!AB18 -> 9220
A5: 2 | B5: ='2'!T3 -> 46205 | C5: ='2'!B33 -> 17889 | D5: ='2'!B34 -> 3439 | E5: ='2'!B35 -> 14450 | F5: ='2'!B36 -> 14450 | G5: ='2'!B37 -> 0 | H5: ='2'!T30 -> 1284 | I5: ='2'!W30 -> 60 | J5: ='2'!W22 -> 2095 | K5: ='2'!AB18 -> 6430
A6: 3 | B6: ='3'!T3 -> 46206 | C6: ='3'!B33 -> 16664 | D6: ='3'!B34 -> 5491 | E6: ='3'!B35 -> 11173 | F6: ='3'!B36 -> 11181.5 | G6: ='3'!B37 -> 8.5 | H6: ='3'!T30 -> 1091 | I6: ='3'!W30 -> 0 | J6: ='3'!W22 -> 4400 | K6: ='3'!AB18 -> 11134
A7: 4 | B7: ='4'!T3 -> 46207 | C7: ='4'!B33 -> 12936 | D7: ='4'!B34 -> 10512.5 | E7: ='4'!B35 -> 2423.5 | F7: ='4'!B36 -> 2424 | G7: ='4'!B37 -> 0.5 | H7: ='4'!T30 -> 0 | I7: ='4'!W30 -> 90 | J7: ='4'!W22 -> 1360 | K7: ='4'!AB18 -> 22005
A8: 5 | B8: ='5'!T3 -> 46208 | C8: ='5'!B33 -> 19041 | D8: ='5'!B34 -> 6767.5 | E8: ='5'!B35 -> 12273.5 | F8: ='5'!B36 -> 12279 | G8: ='5'!B37 -> 5.5 | H8: ='5'!T30 -> 4270 | I8: ='5'!W30 -> 500 | J8: ='5'!W22 -> 1997.5 | K8: ='5'!AB18 -> 0
A9: 6 | B9: ='6'!T3 -> 46209 | C9: ='6'!B33 -> 16561 | D9: ='6'!B34 -> 7360 | E9: ='6'!B35 -> 9201 | F9: ='6'!B36 -> 9207.5 | G9: ='6'!B37 -> 6.5 | H9: ='6'!T30 -> 5185 | I9: ='6'!W30 -> 60 | J9: ='6'!W22 -> 2115 | K9: ='6'!AB18 -> 5030
A10: 7 | B10: ='7'!T3 -> 46210 | C10: ='7'!B33 -> 14102 | D10: ='7'!B34 -> 7694 | E10: ='7'!B35 -> 6408 | F10: ='7'!B36 -> 6410 | G10: ='7'!B37 -> 2 | H10: ='7'!T30 -> 3660 | I10: ='7'!W30 -> 530 | J10: ='7'!W22 -> 3504 | K10: ='7'!AB18 -> 8160
A11: 8 | B11: ='8'!T3 -> 46211 | C11: ='8'!B33 -> 18444 | D11: ='8'!B34 -> 8305.29 | E11: ='8'!B35 -> 10138.71 | F11: ='8'!B36 -> 10141 | G11: ='8'!B37 -> 2.29 | H11: ='8'!T30 -> 6775.29 | I11: ='8'!W30 -> 0 | J11: ='8'!W22 -> 1530 | K11: ='8'!AB18 -> 7611
A12: 9 | B12: ='9'!T3 -> 46212 | C12: ='9'!B33 -> 18214 | D12: ='9'!B34 -> 9968.25 | E12: ='9'!B35 -> 8245.75 | F12: ='9'!B36 -> 8250 | G12: ='9'!B37 -> 4.25 | H12: ='9'!T30 -> 8378.25 | I12: ='9'!W30 -> 60 | J12: ='9'!W22 -> 1530 | K12: ='9'!AB18 -> 9254
A13: 10 | B13: ='10'!T3 -> 46213 | C13: ='10'!B33 -> 15286 | D13: ='10'!B34 -> 8505 | E13: ='10'!B35 -> 6781 | F13: ='10'!B36 -> 6781 | G13: ='10'!B37 -> 0 | H13: ='10'!T30 -> 5000 | I13: ='10'!W30 -> 0 | J13: ='10'!W22 -> 3505 | K13: ='10'!AB18 -> 9520
A14: 11 | B14: ='11'!T3 -> 46214 | C14: ='11'!B33 -> 17440 | D14: ='11'!B34 -> 15145.5 | E14: ='11'!B35 -> 2294.5 | F14: ='11'!B36 -> 2295 | G14: ='11'!B37 -> 0.5 | H14: ='11'!T30 -> 4200 | I14: ='11'!W30 -> 60 | J14: ='11'!W22 -> 1823 | K14: ='11'!AB18 -> 21764
A15: 12 | B15: ='12'!T3 -> 46215 | C15: ='12'!B33 -> 20150 | D15: ='12'!B34 -> 2552.14 | E15: ='12'!B35 -> 17597.86 | F15: ='12'!B36 -> 17603 | G15: ='12'!B37 -> 5.14 | H15: ='12'!T30 -> 1022.14 | I15: ='12'!W30 -> 0 | J15: ='12'!W22 -> 1530 | K15: ='12'!AB18 -> 0
A16: 13 | B16: ='13'!T3 -> 46216 | C16: ='13'!B33 -> 15248 | D16: ='13'!B34 -> 3090 | E16: ='13'!B35 -> 12158 | F16: ='13'!B36 -> 12159 | G16: ='13'!B37 -> 1 | H16: ='13'!T30 -> 275 | I16: ='13'!W30 -> 90 | J16: ='13'!W22 -> 2725 | K16: ='13'!AB18 -> 10531
A17: 14 | B17: ='14'!T3 -> 46217 | C17: ='14'!B33 -> 15740 | D17: ='14'!B34 -> 10380.5 | E17: ='14'!B35 -> 5359.5 | F17: ='14'!B36 -> 5359.5 | G17: ='14'!B37 -> 0 | H17: ='14'!T30 -> 6909.5 | I17: ='14'!W30 -> 0 | J17: ='14'!W22 -> 3471 | K17: ='14'!AB18 -> 7160
A18: 15 | B18: ='15'!T3 -> 46218 | C18: ='15'!B33 -> 18654 | D18: ='15'!B34 -> 4627.87 | E18: ='15'!B35 -> 14026.13 | F18: ='15'!B36 -> 14026 | G18: ='15'!B37 -> -0.13 | H18: ='15'!T30 -> 3007.87 | I18: ='15'!W30 -> 90 | J18: ='15'!W22 -> 1530 | K18: ='15'!AB18 -> 8614
A19: 16 | B19: ='16'!T3 -> 46219 | C19: ='16'!B33 -> 17527 | D19: ='16'!B34 -> 5675 | E19: ='16'!B35 -> 11852 | F19: ='16'!B36 -> 11853 | G19: ='16'!B37 -> 1 | H19: ='16'!T30 -> 4060 | I19: ='16'!W30 -> 0 | J19: ='16'!W22 -> 1615 | K19: ='16'!AB18 -> 8120
A20: 17 | B20: ='17'!T3 -> 46220 | C20: ='17'!B33 -> 17898 | D20: ='17'!B34 -> 7460.69 | E20: ='17'!B35 -> 10437.31 | F20: ='17'!B36 -> 10438 | G20: ='17'!B37 -> 0.69 | H20: ='17'!T30 -> 4200.69 | I20: ='17'!W30 -> 90 | J20: ='17'!W22 -> 3170 | K20: ='17'!AB18 -> 12270
A21: 18 | B21: ='18'!T3 -> 38916 | C21: ='18'!B33 -> 16732 | D21: ='18'!B34 -> 14353.57 | E21: ='18'!B35 -> 2378.43 | F21: ='18'!B36 -> 2379 | G21: ='18'!B37 -> 0.57 | H21: ='18'!T30 -> 11.07 | I21: ='18'!W30 -> 30 | J21: ='18'!W22 -> 1700 | K21: ='18'!AB18 -> 22701
A22: 19 | B22: ='19'!T3 -> 46222 | C22: ='19'!B33 -> 20302 | D22: ='19'!B34 -> 2210.87 | E22: ='19'!B35 -> 18091.13 | F22: ='19'!B36 -> 18092 | G22: ='19'!B37 -> 0.87 | H22: ='19'!T30 -> 85.87 | I22: ='19'!W30 -> 0 | J22: ='19'!W22 -> 2125 | K22: ='19'!AB18 -> 0
A23: 20 | B23: ='20'!T3 -> 46223 | C23: ='20'!B33 -> 15110 | D23: ='20'!B34 -> 2175.95 | E23: ='20'!B35 -> 12934.05 | F23: ='20'!B36 -> 12936 | G23: ='20'!B37 -> 1.95 | H23: ='20'!T30 -> 555.95 | I23: ='20'!W30 -> 90 | J23: ='20'!W22 -> 1530 | K23: ='20'!AB18 -> 8704
A24: 21 | B24: ='21'!T3 -> 46224 | C24: ='21'!B33 -> 15951 | D24: ='21'!B34 -> 7877.82 | E24: ='21'!B35 -> 8073.18 | F24: ='21'!B36 -> 8075 | G24: ='21'!B37 -> 1.82 | H24: ='21'!T30 -> 1564.82 | I24: ='21'!W30 -> 135 | J24: ='21'!W22 -> 6178 | K24: ='21'!AB18 -> 12380
A25: 22 | B25: ='22'!T3 -> 46225 | C25: ='22'!B33 -> 15625 | D25: ='22'!B34 -> 3679 | E25: ='22'!B35 -> 11946 | F25: ='22'!B36 -> 11947 | G25: ='22'!B37 -> 1 | H25: ='22'!T30 -> 1444 | I25: ='22'!W30 -> 0 | J25: ='22'!W22 -> 2235 | K25: ='22'!AB18 -> 8004
A26: 23 | B26: ='23'!T3 -> 46226 | C26: ='23'!B33 -> 16503 | D26: ='23'!B34 -> 8999.07 | E26: ='23'!B35 -> 7503.93 | F26: ='23'!B36 -> 7505 | G26: ='23'!B37 -> 1.07 | H26: ='23'!T30 -> 7239.07 | I26: ='23'!W30 -> 60 | J26: ='23'!W22 -> 1700 | K26: ='23'!AB18 -> 7740
A27: 24 | B27: ='24'!T3 -> 45862 | C27: ='24'!B33 -> 17337 | D27: ='24'!B34 -> 6551.75 | E27: ='24'!B35 -> 10785.25 | F27: ='24'!B36 -> 10785.25 | G27: ='24'!B37 -> 0 | H27: ='24'!T30 -> 2961.75 | I27: ='24'!W30 -> 0 | J27: ='24'!W22 -> 3590 | K27: ='24'!AB18 -> 7311
A28: 25 | B28: ='25'!T3 -> 46228 | C28: ='25'!B33 -> 14880 | D28: ='25'!B34 -> 11383.57 | E28: ='25'!B35 -> 3496.43 | F28: ='25'!B36 -> 3482 | G28: ='25'!B37 -> -14.43 | H28: ='25'!T30 -> 11.07 | I28: ='25'!W30 -> 60 | J28: ='25'!W22 -> 1700 | K28: ='25'!AB18 -> 21094
A29: 26 | B29: ='26'!T3 -> 46229 | C29: ='26'!B33 -> 18894 | D29: ='26'!B34 -> 6632.99 | E29: ='26'!B35 -> 12261.01 | F29: ='26'!B36 -> 12263.25 | G29: ='26'!B37 -> 2.24 | H29: ='26'!T30 -> 4932.99 | I29: ='26'!W30 -> 0 | J29: ='26'!W22 -> 1700 | K29: ='26'!AB18 -> 0
A30: 27 | B30: ='27'!T3 -> 46230 | C30: ='27'!B33 -> 15393 | D30: ='27'!B34 -> 2110 | E30: ='27'!B35 -> 13283 | F30: ='27'!B36 -> 13293 | G30: ='27'!B37 -> 10 | H30: ='27'!T30 -> 0 | I30: ='27'!W30 -> 90 | J30: ='27'!W22 -> 2020 | K30: ='27'!AB18 -> 9780
A31: 28 | B31: ='28'!T3 -> 46231 | C31: ='28'!B33 -> 15154 | D31: ='28'!B34 -> 6109.75 | E31: ='28'!B35 -> 9044.25 | F31: ='28'!B36 -> 9050 | G31: ='28'!B37 -> 5.75 | H31: ='28'!T30 -> 1639.75 | I31: ='28'!W30 -> 0 | J31: ='28'!W22 -> 4470 | K31: ='28'!AB18 -> 9335
A32: 29 | B32: ='29'!T3 -> 46232 | C32: ='29'!B33 -> 12776 | D32: ='29'!B34 -> 1873 | E32: ='29'!B35 -> 10903 | F32: ='29'!B36 -> 10903 | G32: ='29'!B37 -> 0 | H32: ='29'!T30 -> 198 | I32: ='29'!W30 -> 60 | J32: ='29'!W22 -> 1615 | K32: ='29'!AB18 -> 7820
A33: 30 | B33: ='30'!T3 -> 46233 | C33: ='30'!B33 -> 15386 | D33: ='30'!B34 -> 2015 | E33: ='30'!B35 -> 13371 | F33: ='30'!B36 -> 13372 | G33: ='30'!B37 -> 1 | H33: ='30'!T30 -> 15 | I33: ='30'!W30 -> 0 | J33: ='30'!W22 -> 2000 | K33: ='30'!AB18 -> 6750
A34: 31 | B34: ='31'!T3 -> 46234 | C34: ='31'!B33 -> 15749 | D34: ='31'!B34 -> 3009 | E34: ='31'!B35 -> 12740 | F34: ='31'!B36 -> 12746 | G34: ='31'!B37 -> 6 | H34: ='31'!T30 -> 0 | I34: ='31'!W30 -> 0 | J34: ='31'!W22 -> 3009 | K34: ='31'!AB18 -> 8084
A35: MONTHLY TOTAL | C35: =SUM(C4:C34) -> 512383 | D35: =SUM(D4:D34) -> 201925.58 | E35: =SUM(E4:E34) -> 310457.42 | F35: =SUM(F4:F34) -> 310513 | G35: =SUM(G4:G34) -> 55.58 | H35: =SUM(H4:H34) -> 84248.08 | I35: =SUM(I4:I34) -> 2155 | J35: =SUM(J4:J34) -> 75172.5 | K35: =SUM(K4:K34) -> 286526
A37: 📋 HOW TO USE: Enter data directly in each Day tab (sheets 1–31). Branch name & Date entered there will auto-appear in the Date column above. Gross Sales, Expenses, Net Sales & Over/Short pull automatically.

Sheet income statement
B3: BRANCH
B4: INCOME STATEMENT
B5: MONTH
A7: PARTICULARS:
B8: SPECIAL CUT | C8: =GROSS!G55 -> 300600
B9: PREMIUM CUT | C9: =GROSS!D55 -> 0
B10: Neck | C10: =GROSS!P55 -> 33384
B11: Rice | C11: =GROSS!V55 -> 88110
B12: Softdrinks | C12: =GROSS!BY55 -> 50689
B13: Ngohiong | C13: =GROSS!J55 -> 4056
B14: Atsara | C14: =GROSS!AE55 -> 2570
B15: Siomai | C15: =GROSS!S55 -> 0
B16: Bola-Bola | C16: =GROSS!Y55 -> 11800
B17: Lumpia | C17: =GROSS!AB55 -> 9224
B18: c-fillet | C18: =GROSS!M55 -> 11950
A19: GROSS SALES: | C19: =SUM(C8:C18) -> 512383
A21: LESS: | B21: Cost of Good Sold | C21: ='DAILY COGS'!CA55 -> 332893.88 | E21: =C21/C19 -> 0.64969735
A23: GROSS PROFIT | C23: =C19-C21 -> 179489.12
A24: LESS: OPERATING EXPENSES
B25: =OPEX!B50 -> LPG | C25: =OPEX!D50 -> 16996 | D25: =C25/C19 -> 0.033170499
B26: =OPEX!B51 -> BREADING | C26: =OPEX!D51 -> 9546 | D26: =C26/C19 -> 0.018630595
B27: =OPEX!B52 -> OIL | C27: =OPEX!D52 -> 15114 | D27: =C27/C19 -> 0.029497466
B28: =OPEX!B53 -> GRAVY | C28: =OPEX!D53 -> 3240 | D28: =C28/C19 -> 0.0063233948
B29: =OPEX!B54 -> SALARY | C29: =OPEX!D54 -> 43550 | D29: =C29/C19 -> 0.084995013
B30: =OPEX!B55 -> HOLIDAY | C30: =OPEX!D55 -> 0 | D30: =C30/C19 -> 0
B31: =OPEX!B56 -> OVERTIME | C31: =OPEX!D56 -> 0 | D31: =C31/C19 -> 0
B32: =OPEX!B57 -> TL ALLOWANCE | C32: =OPEX!D57 -> 1300 | D32: =C32/C19 -> 0.0025371646
B33: =OPEX!B58 -> Admin / Office Supplies | C33: =OPEX!D58 -> 1646.72 | D33: =C33/C19 -> 0.0032138459
B34: =OPEX!B59 -> 13th month | C34: =OPEX!D59 -> 4792.74 | D34: =C34/C19 -> 0.0093538232
B35: =OPEX!B60 -> pag ibig | C35: =OPEX!D60 -> 275 | D35: =C35/C19 -> 0.00053670789
B36: =OPEX!B61 -> SSS | C36: =OPEX!D61 -> 1428.86 | D36: =C36/C19 -> 0.0027886561
B37: =OPEX!B62 -> PHIL HEALTH | C37: =OPEX!D62 -> 346.43 | D37: =C37/C19 -> 0.00067611533
B38: =OPEX!B63 -> SIOMAI SAUCE | C38: =OPEX!D63 -> 0 | D38: =C38/C19 -> 0
B39: =OPEX!B64 -> TRANSPO. | C39: =OPEX!D64 -> 0 | D39: =C39/C19 -> 0
B40: =OPEX!B65 -> CHARGE DEPOSIT | C40: =OPEX!D65 -> 0 | D40: =C40/C19 -> 0
B41: =OPEX!B66 -> RENTAL | C41: =OPEX!D66 -> 28000 | D41: =C41/C19 -> 0.054646622
B42: =OPEX!B67 -> LIGHT | C42: =OPEX!D67 -> 9007.87 | D42: =C42/C19 -> 0.017580345
B43: =OPEX!B68 -> WATER | C43: =OPEX!D68 -> 2160 | D43: =C43/C19 -> 0.0042155965
B44: =OPEX!B69 -> BIR/TAXES | C44: =OPEX!D69 -> 4732.69 | D44: =C44/C19 -> 0.0092366257
B45: =OPEX!B70 -> supot/roll bag/T-bag | C45: =OPEX!D70 -> 2166.75 | D45: =C45/C19 -> 0.0042287703
B46: =OPEX!B71 -> COMMUNICATION | C46: =OPEX!D71 -> 200 | D46: =C46/C19 -> 0.00039033301
B47: =OPEX!B72 -> SENIOR DISC. | C47: =OPEX!D72 -> 64.27 | D47: =C47/C19 -> 0.00012543351
B48: =OPEX!B73 -> Detergent | C48: =OPEX!D73 -> 629.75 | D48: =C48/C19 -> 0.0012290611
B49: =OPEX!B74 -> SERVICE WATER | C49: =OPEX!D74 -> 0 | D49: =C49/C19 -> 0
B50: =OPEX!B75 -> KITCHEN WARES | C50: =OPEX!D75 -> 0 | D50: =C50/C19 -> 0
B51: =OPEX!B76 -> (Patis / suka) | C51: =OPEX!D76 -> 651 | D51: =C51/C19 -> 0.001270534
B52: =OPEX!B77 -> Maintenance & Labor | C52: =OPEX!D77 -> 6650 | D52: =C52/C19 -> 0.012978573
B53: =OPEX!B78 -> OTHERS | C53: =OPEX!D78 -> 0 | D53: =C53/C19 -> 0
B54: =OPEX!B79 -> ADMIN COST | C54: =OPEX!D79 -> 6787.62 | D54: =C54/C19 -> 0.013247161
B55: =OPEX!B80 -> TRANSPO (SUPERVISORS REPLENISHMENT) | C55: =OPEX!D80 -> 1160.52 | D55: =C55/C19 -> 0.0022649463
B56: =OPEX!B81 -> B.O. | C56: =OPEX!D81 -> 0 | D56: =C56/C19 -> 0
A57: TOTAL OPERATING EXPENSES | C57: =SUM(C25:C56) -> 160446.22 | D57: =C57-B.O!CA55-OPEX!AS47 -> 0 | E57: =C57/C19 -> 0.31313728
B59: NET INCOME | C59: =C23-C57 -> 19042.905 | E59: =C59/C19 -> 0.037165372
B61: 10% ROYALTY | C61: =C59*10% -> 1904.2905
B62: 90% ROYALTY | C62: =C59*90% -> 17138.615
A63: 80% LESS CAPEX | F63: COST OF GOOD SOLD (COGS)
B64: =CAPEX!B4 -> Birthday cake | C64: =CAPEX!B47 -> 0 | F64: INVENTORY BEG. | G64: ='MONTHLY INV.'!D30 -> 15858.939
B65: =CAPEX!C4 -> staff bunos / incentives | C65: =CAPEX!C47 -> 500 | F65: Add: PURCHASES | G65: ='MONTHLY INV.'!F30 -> 335172.5
B66: =CAPEX!D4 -> owners pull-out | C66: =CAPEX!D47 -> 0 | F66: Less: COST OF GOOD SOLD (COGS) | G66: =C21 -> 332893.88
B67: =CAPEX!E4 -> Other Capex | C67: =CAPEX!E47 -> 575 | F67: INVENTORY ENDING BALANCE | G67: =G64+G65-G66 -> 18137.564
B68: =CAPEX!F4 -> SERVICE WATER | C68: =CAPEX!F47 -> 1080 | F68: ACTUAL ENDING BALANCE | G68: ='MONTHLY INV.'!K30 -> 18206.5
B69: TOTAL CAPEX | C69: =SUM(C64:C68) -> 2155 | F69: Discripancy | G69: =G67-G68 -> -68.935606
A71: 80% NET | C71: =C62-C69 -> 14983.615

Sheet DAILY COGS
A1: CRISPY KING FOOD STATION : | E1: =GROSS!E1 -> BRANCH | BN1: DRINKS
A2: Daily Monitoring of COGS
A3: For the Month of: | C3: 45473
A5: WEEK- 1 | B5: PREMIUM - CUT | E5: ='1'!A7 -> SPECIAL CUT | H5: ='1'!A8 -> NGOHIONG | K5: ='1'!A15 -> Chicken Fillet | N5: NECK | Q5: SIOMAI | T5: RICE | W5: BOLA-BOLA | Z5: LUMPIA | AC5: ATSARA | AI5: SUBTOTAL | AM5: ='1'!A17 -> 8 oz | AP5: 12 OZ | AS5: WATER 350 ML | AV5: WATER 500 ML | AY5: PANALO | BB5: swakto | BE5: Calamansi Juice | BH5: ='1'!A23 -> GATORADE | BK5: TROPICANA | BN5: STING | BQ5: ='1'!A19 -> 1 LITER | BT5: ='1'!A20 -> 1.5 L | BW5: SUBTOTAL FOR DRINKS | CA5: TOTAL | CC5: AUDIT GROSS | CD5: DIFFERENCE
A6: DATE | B6: QTY | C6: UP | D6: AMOUNT | E6: QTY | F6: UP | G6: AMOUNT | H6: QTY | I6: UP | J6: AMOUNT | K6: QTY | L6: UP | M6: AMOUNT | N6: QTY | O6: UP | P6: AMOUNT | Q6: QTY | R6: UP | S6: AMOUNT | T6: QTY | U6: UP | V6: AMOUNT | W6: QTY | X6: UP | Y6: AMOUNT | Z6: QTY | AA6: UP | AB6: AMOUNT | AC6: QTY | AD6: UP | AE6: AMOUNT | AF6: QTY | AG6: UP | AH6: AMOUNT | AK6: AMOUNT | AM6: QTY | AN6: UP | AO6: AMOUNT | AP6: QTY | AQ6: UP | AR6: AMOUNT | AS6: QTY | AT6: UP | AU6: AMOUNT | AV6: QTY | AW6: UP | AX6: AMOUNT | AY6: QTY | AZ6: UP | BA6: AMOUNT | BB6: QTY | BC6: UP | BD6: AMOUNT | BE6: QTY | BF6: UP | BG6: AMOUNT | BH6: QTY | BI6: UP | BJ6: AMOUNT | BK6: QTY | BL6: UP | BM6: AMOUNT | BN6: QTY | BO6: UP | BP6: AMOUNT | BQ6: QTY | BR6: UP | BS6: AMOUNT | BT6: QTY | BU6: UP | BV6: AMOUNT | BY6: AMOUNT | CA6: AMOUNT
A7: 1 | B7: =GROSS!B7 -> 0 | C7: =DELIVERIES!C7 -> 30 | D7: =B7*C7 -> 0 | E7: ='1'!F7 -> 169 | F7: =DELIVERIES!F7 -> 35 | G7: =E7*F7 -> 5915 | H7: ='1'!F8 -> 15 | I7: =DELIVERIES!I7 -> 8.5 | J7: =H7*I7 -> 127.5 | K7: ='1'!F15 -> 18 | L7: =DELIVERIES!L7 -> 18 | M7: =K7*L7 -> 324 | N7: ='1'!F9 -> 16 | O7: =DELIVERIES!O7 -> 7 | P7: =N7*O7 -> 112 | Q7: ='1'!F10 -> 0 | R7: =DELIVERIES!R7 -> 5.5 | S7: =Q7*R7 -> 0 | T7: ='1'!F11 -> 192 | U7: =DELIVERIES!U7 -> 8.5 | V7: =T7*U7 -> 1632 | W7: ='1'!F12 -> 43 | X7: =DELIVERIES!X7 -> 6 | Y7: =W7*X7 -> 258 | Z7: ='1'!F13 -> 32 | AA7: =DELIVERIES!AA7 -> 6 | AB7: =Z7*AA7 -> 192 | AC7: ='1'!F14 -> 18 | AD7: =DELIVERIES!AD7 -> 8 | AE7: =AC7*AD7 -> 144 | AH7: =AF7*AG7 -> 0 | AK7: =D7+G7+J7+M7+P7+S7+V7+Y7+AB7+AE7+AH7 -> 8704.5 | AM7: ='1'!F17 -> 16 | AN7: =DELIVERIES!AQ7 -> 8.75 | AO7: =AM7*AN7 -> 140 | AP7: ='1'!F18 -> 43 | AQ7: =DELIVERIES!AT7 -> 12.25 | AR7: =AP7*AQ7 -> 526.75 | AS7: ='1'!F21 -> 0 | AT7: =DELIVERIES!AW7 -> 7.9166667 | AU7: =AS7*AT7 -> 0 | AV7: ='1'!F22 -> 7 | AW7: =DELIVERIES!AZ7 -> 9.7916667 | AX7: =AV7*AW7 -> 68.541667 | AY7: ='1'!F26 -> 0 | AZ7: =DELIVERIES!BC7 -> 16.333333 | BA7: =AY7*AZ7 -> 0 | BB7: ='1'!F27 -> 7 | BC7: =DELIVERIES!BF7 -> 11.5 | BD7: =BB7*BC7 -> 80.5 | BE7: ='1'!F28 -> 3 | BF7: =DELIVERIES!BI31 -> 20 | BG7: =BE7*BF7 -> 60 | BH7: ='1'!F23 -> 0 | BI7: =DELIVERIES!BL7 -> 23 | BJ7: =BH7*BI7 -> 0 | BK7: ='1'!F25 -> 0 | BL7: =DELIVERIES!BO7 -> 12.5 | BM7: =BK7*BL7 -> 0 | BN7: ='1'!F24 -> 2 | BO7: =DELIVERIES!BR7 -> 12.75 | BP7: =BN7*BO7 -> 25.5 | BQ7: ='1'!F19 -> 0 | BR7: =DELIVERIES!BU7 -> 30.25 | BS7: =BQ7*BR7 -> 0 | BT7: ='1'!F20 -> 0 | BU7: =DELIVERIES!BX7 -> 15.916667 | BV7: =BT7*BU7 -> 0 | BY7: =AO7+AR7+AU7+AX7+BA7+BD7+BG7+BJ7+BM7+BP7+BS7+BV7 -> 901.29167 | CA7: =BY7+AK7 -> 9605.7917 | CD7: =CA7-CC7 -> 9605.7917
A8: 2 | B8: =GROSS!B8 -> 0 | C8: =DELIVERIES!C8 -> 30 | D8: =B8*C8 -> 0 | E8: ='2'!F7 -> 214 | F8: =DELIVERIES!F8 -> 35 | G8: =E8*F8 -> 7490 | H8: ='2'!F8 -> 12 | I8: =DELIVERIES!I8 -> 8.5 | J8: =H8*I8 -> 102 | K8: ='2'!F15 -> 18 | L8: =DELIVERIES!L8 -> 18 | M8: =K8*L8 -> 324 | N8: ='2'!F9 -> 62 | O8: =DELIVERIES!O8 -> 7 | P8: =N8*O8 -> 434 | Q8: ='2'!F10 -> 0 | R8: =DELIVERIES!R8 -> 5.5 | S8: =Q8*R8 -> 0 | T8: ='2'!F11 -> 176 | U8: =DELIVERIES!U8 -> 8.5 | V8: =T8*U8 -> 1496 | W8: ='2'!F12 -> 74 | X8: =DELIVERIES!X8 -> 6 | Y8: =W8*X8 -> 444 | Z8: ='2'!F13 -> 33 | AA8: =DELIVERIES!AA8 -> 6 | AB8: =Z8*AA8 -> 198 | AC8: ='2'!F14 -> 9 | AD8: =DELIVERIES!AD8 -> 8 | AE8: =AC8*AD8 -> 72 | AG8: =AG7 -> 0 | AH8: =AF8*AG8 -> 0 | AK8: =D8+G8+J8+M8+P8+S8+V8+Y8+AB8+AE8+AH8 -> 10560 | AM8: ='2'!F17 -> 16 | AN8: =DELIVERIES!AQ8 -> 8.75 | AO8: =AM8*AN8 -> 140 | AP8: ='2'!F18 -> 51 | AQ8: =DELIVERIES!AT8 -> 12.25 | AR8: =AP8*AQ8 -> 624.75 | AS8: ='2'!F21 -> 0 | AT8: =DELIVERIES!AW8 -> 7.9166667 | AU8: =AS8*AT8 -> 0 | AV8: ='2'!F22 -> 6 | AW8: =DELIVERIES!AZ8 -> 9.7916667 | AX8: =AV8*AW8 -> 58.75 | AY8: ='2'!F26 -> 0 | AZ8: =DELIVERIES!BC8 -> 16.333333 | BA8: =AY8*AZ8 -> 0 | BB8: ='2'!F27 -> 6 | BC8: =DELIVERIES!BF8 -> 11.5 | BD8: =BB8*BC8 -> 69 | BE8: ='2'!F28 -> 6 | BF8: =DELIVERIES!BI32 -> 20 | BG8: =BE8*BF8 -> 120 | BH8: ='2'!F23 -> 0 | BI8: =DELIVERIES!BL8 -> 23 | BJ8: =BH8*BI8 -> 0 | BK8: ='2'!F25 -> 0 | BL8: =DELIVERIES!BO8 -> 12.5 | BM8: =BK8*BL8 -> 0 | BN8: ='2'!F24 -> 6 | BO8: =DELIVERIES!BR8 -> 12.75 | BP8: =BN8*BO8 -> 76.5 | BQ8: ='2'!F19 -> 0 | BR8: =DELIVERIES!BU8 -> 30.25 | BS8: =BQ8*BR8 -> 0 | BT8: ='2'!F20 -> 0 | BU8: =DELIVERIES!BX8 -> 15.916667 | BV8: =BT8*BU8 -> 0 | BY8: =AO8+AR8+AU8+AX8+BA8+BD8+BG8+BJ8+BM8+BP8+BS8+BV8 -> 1089 | CA8: =BY8+AK8 -> 11649 | CD8: =CA8-CC8 -> 11649
A9: 3 | B9: =GROSS!B9 -> 0 | C9: =DELIVERIES!C9 -> 30 | D9: =B9*C9 -> 0 | E9: ='3'!F7 -> 185 | F9: =DELIVERIES!F9 -> 35 | G9: =E9*F9 -> 6475 | H9: ='3'!F8 -> 11 | I9: =DELIVERIES!I9 -> 8.5 | J9: =H9*I9 -> 93.5 | K9: ='3'!F15 -> 20 | L9: =DELIVERIES!L9 -> 18 | M9: =K9*L9 -> 360 | N9: ='3'!F9 -> 118 | O9: =DELIVERIES!O9 -> 7 | P9: =N9*O9 -> 826 | Q9: ='3'!F10 -> 0 | R9: =DELIVERIES!R9 -> 5.5 | S9: =Q9*R9 -> 0 | T9: ='3'!F11 -> 191 | U9: =DELIVERIES!U9 -> 8.5 | V9: =T9*U9 -> 1623.5 | W9: ='3'!F12 -> 33 | X9: =DELIVERIES!X9 -> 6 | Y9: =W9*X9 -> 198 | Z9: ='3'!F13 -> 44 | AA9: =DELIVERIES!AA9 -> 6 | AB9: =Z9*AA9 -> 264 | AC9: ='3'!F14 -> 12 | AD9: =DELIVERIES!AD9 -> 8 | AE9: =AC9*AD9 -> 96 | AG9: =AG7 -> 0 | AH9: =AF9*AG9 -> 0 | AK9: =D9+G9+J9+M9+P9+S9+V9+Y9+AB9+AE9+AH9 -> 9936 | AM9: ='3'!F17 -> 15 | AN9: =DELIVERIES!AQ9 -> 8.75 | AO9: =AM9*AN9 -> 131.25 | AP9: ='3'!F18 -> 38 | AQ9: =DELIVERIES!AT9 -> 12.25 | AR9: =AP9*AQ9 -> 465.5 | AS9: ='3'!F21 -> 0 | AT9: =DELIVERIES!AW9 -> 7.9166667 | AU9: =AS9*AT9 -> 0 | AV9: ='3'!F22 -> 4 | AW9: =DELIVERIES!AZ9 -> 9.7916667 | AX9: =AV9*AW9 -> 39.166667 | AY9: ='3'!F26 -> 0 | AZ9: =DELIVERIES!BC9 -> 16.333333 | BA9: =AY9*AZ9 -> 0 | BB9: ='3'!F27 -> 7 | BC9: =DELIVERIES!BF9 -> 11.5 | BD9: =BB9*BC9 -> 80.5 | BE9: ='3'!F28 -> 4 | BF9: =DELIVERIES!BI33 -> 20 | BG9: =BE9*BF9 -> 80 | BH9: ='3'!F23 -> 0 | BI9: =DELIVERIES!BL9 -> 23 | BJ9: =BH9*BI9 -> 0 | BK9: ='3'!F25 -> 0 | BL9: =DELIVERIES!BO9 -> 12.5 | BM9: =BK9*BL9 -> 0 | BN9: ='3'!F24 -> 6 | BO9: =DELIVERIES!BR9 -> 12.75 | BP9: =BN9*BO9 -> 76.5 | BQ9: ='3'!F19 -> 0 | BR9: =DELIVERIES!BU9 -> 30.25 | BS9: =BQ9*BR9 -> 0 | BT9: ='3'!F20 -> 0 | BU9: =DELIVERIES!BX9 -> 15.916667 | BV9: =BT9*BU9 -> 0 | BY9: =AO9+AR9+AU9+AX9+BA9+BD9+BG9+BJ9+BM9+BP9+BS9+BV9 -> 872.91667 | CA9: =BY9+AK9 -> 10808.917 | CD9: =CA9-CC9 -> 10808.917
A10: 4 | B10: =GROSS!B10 -> 0 | C10: =DELIVERIES!C10 -> 30 | D10: =B10*C10 -> 0 | E10: ='4'!F7 -> 142 | F10: =DELIVERIES!F10 -> 35 | G10: =E10*F10 -> 4970 | H10: ='4'!F8 -> 12 | I10: =DELIVERIES!I10 -> 8.5 | J10: =H10*I10 -> 102 | K10: ='4'!F15 -> 7 | L10: =DELIVERIES!L10 -> 18 | M10: =K10*L10 -> 126 | N10: ='4'!F9 -> 99 | O10: =DELIVERIES!O10 -> 7 | P10: =N10*O10 -> 693 | Q10: ='4'!F10 -> 0 | R10: =DELIVERIES!R10 -> 5.5 | S10: =Q10*R10 -> 0 | T10: ='4'!F11 -> 160 | U10: =DELIVERIES!U10 -> 8.5 | V10: =T10*U10 -> 1360 | W10: ='4'!F12 -> 24 | X10: =DELIVERIES!X10 -> 6 | Y10: =W10*X10 -> 144 | Z10: ='4'!F13 -> 34 | AA10: =DELIVERIES!AA10 -> 6 | AB10: =Z10*AA10 -> 204 | AC10: ='4'!F14 -> 10 | AD10: =DELIVERIES!AD10 -> 8 | AE10: =AC10*AD10 -> 80 | AG10: =AG7 -> 0 | AH10: =AF10*AG10 -> 0 | AK10: =D10+G10+J10+M10+P10+S10+V10+Y10+AB10+AE10+AH10 -> 7679 | AM10: ='4'!F17 -> 4 | AN10: =DELIVERIES!AQ10 -> 8.75 | AO10: =AM10*AN10 -> 35 | AP10: ='4'!F18 -> 27 | AQ10: =DELIVERIES!AT10 -> 12.25 | AR10: =AP10*AQ10 -> 330.75 | AS10: ='4'!F21 -> 0 | AT10: =DELIVERIES!AW10 -> 7.9166667 | AU10: =AS10*AT10 -> 0 | AV10: ='4'!F22 -> 3 | AW10: =DELIVERIES!AZ10 -> 9.7916667 | AX10: =AV10*AW10 -> 29.375 | AY10: ='4'!F26 -> 0 | AZ10: =DELIVERIES!BC10 -> 16.333333 | BA10: =AY10*AZ10 -> 0 | BB10: ='4'!F27 -> 6 | BC10: =DELIVERIES!BF10 -> 11.5 | BD10: =BB10*BC10 -> 69 | BE10: ='4'!F28 -> 10 | BF10: =DELIVERIES!BI34 -> 20 | BG10: =BE10*BF10 -> 200 | BH10: ='4'!F23 -> 0 | BI10: =DELIVERIES!BL10 -> 23 | BJ10: =BH10*BI10 -> 0 | BK10: ='4'!F25 -> 0 | BL10: =DELIVERIES!BO10 -> 12.5 | BM10: =BK10*BL10 -> 0 | BN10: ='4'!F24 -> 6 | BO10: =DELIVERIES!BR10 -> 12.75 | BP10: =BN10*BO10 -> 76.5 | BQ10: ='4'!F19 -> 0 | BR10: =DELIVERIES!BU10 -> 30.25 | BS10: =BQ10*BR10 -> 0 | BT10: ='4'!F20 -> 0 | BU10: =DELIVERIES!BX10 -> 15.916667 | BV10: =BT10*BU10 -> 0 | BY10: =AO10+AR10+AU10+AX10+BA10+BD10+BG10+BJ10+BM10+BP10+BS10+BV10 -> 740.625 | CA10: =BY10+AK10 -> 8419.625 | CD10: =CA10-CC10 -> 8419.625
A11: 5 | B11: =GROSS!B11 -> 0 | C11: =DELIVERIES!C11 -> 30 | D11: =B11*C11 -> 0 | E11: ='5'!F7 -> 207 | F11: =DELIVERIES!F11 -> 35 | G11: =E11*F11 -> 7245 | H11: ='5'!F8 -> 19 | I11: =DELIVERIES!I11 -> 8.5 | J11: =H11*I11 -> 161.5 | K11: ='5'!F15 -> 22 | L11: =DELIVERIES!L11 -> 18 | M11: =K11*L11 -> 396 | N11: ='5'!F9 -> 21 | O11: =DELIVERIES!O11 -> 7 | P11: =N11*O11 -> 147 | Q11: ='5'!F10 -> 0 | R11: =DELIVERIES!R11 -> 5.5 | S11: =Q11*R11 -> 0 | T11: ='5'!F11 -> 273 | U11: =DELIVERIES!U11 -> 8.5 | V11: =T11*U11 -> 2320.5 | W11: ='5'!F12 -> 59 | X11: =DELIVERIES!X11 -> 6 | Y11: =W11*X11 -> 354 | Z11: ='5'!F13 -> 59 | AA11: =DELIVERIES!AA11 -> 6 | AB11: =Z11*AA11 -> 354 | AC11: ='5'!F14 -> 15 | AD11: =DELIVERIES!AD11 -> 8 | AE11: =AC11*AD11 -> 120 | AG11: =AG7 -> 0 | AH11: =AF11*AG11 -> 0 | AK11: =D11+G11+J11+M11+P11+S11+V11+Y11+AB11+AE11+AH11 -> 11098 | AM11: ='5'!F17 -> 17 | AN11: =DELIVERIES!AQ11 -> 8.75 | AO11: =AM11*AN11 -> 148.75 | AP11: ='5'!F18 -> 50 | AQ11: =DELIVERIES!AT11 -> 12.25 | AR11: =AP11*AQ11 -> 612.5 | AS11: ='5'!F21 -> 0 | AT11: =DELIVERIES!AW11 -> 7.9166667 | AU11: =AS11*AT11 -> 0 | AV11: ='5'!F22 -> 10 | AW11: =DELIVERIES!AZ11 -> 9.7916667 | AX11: =AV11*AW11 -> 97.916667 | AY11: ='5'!F26 -> 0 | AZ11: =DELIVERIES!BC11 -> 16.333333 | BA11: =AY11*AZ11 -> 0 | BB11: ='5'!F27 -> 17 | BC11: =DELIVERIES!BF11 -> 11.5 | BD11: =BB11*BC11 -> 195.5 | BE11: ='5'!F28 -> 8 | BF11: =DELIVERIES!BI35 -> 20 | BG11: =BE11*BF11 -> 160 | BH11: ='5'!F23 -> 0 | BI11: =DELIVERIES!BL11 -> 23 | BJ11: =BH11*BI11 -> 0 | BK11: ='5'!F25 -> 0 | BL11: =DELIVERIES!BO11 -> 12.5 | BM11: =BK11*BL11 -> 0 | BN11: ='5'!F24 -> 3 | BO11: =DELIVERIES!BR11 -> 12.75 | BP11: =BN11*BO11 -> 38.25 | BQ11: ='5'!F19 -> 0 | BR11: =DELIVERIES!BU11 -> 30.25 | BS11: =BQ11*BR11 -> 0 | BT11: ='5'!F20 -> 0 | BU11: =DELIVERIES!BX11 -> 15.916667 | BV11: =BT11*BU11 -> 0 | BY11: =AO11+AR11+AU11+AX11+BA11+BD11+BG11+BJ11+BM11+BP11+BS11+BV11 -> 1252.9167 | CA11: =BY11+AK11 -> 12350.917 | CD11: =CA11-CC11 -> 12350.917
A12: 6 | B12: =GROSS!B12 -> 0 | C12: =DELIVERIES!C12 -> 30 | D12: =B12*C12 -> 0 | E12: ='6'!F7 -> 203 | F12: =DELIVERIES!F12 -> 35 | G12: =E12*F12 -> 7105 | H12: ='6'!F8 -> 6 | I12: =DELIVERIES!I12 -> 8.5 | J12: =H12*I12 -> 51 | K12: ='6'!F15 -> 7 | L12: =DELIVERIES!L12 -> 18 | M12: =K12*L12 -> 126 | N12: ='6'!F9 -> 50 | O12: =DELIVERIES!O12 -> 7 | P12: =N12*O12 -> 350 | Q12: ='6'!F10 -> 0 | R12: =DELIVERIES!R12 -> 5.5 | S12: =Q12*R12 -> 0 | T12: ='6'!F11 -> 220 | U12: =DELIVERIES!U12 -> 8.5 | V12: =T12*U12 -> 1870 | W12: ='6'!F12 -> 35 | X12: =DELIVERIES!X12 -> 6 | Y12: =W12*X12 -> 210 | Z12: ='6'!F13 -> 36 | AA12: =DELIVERIES!AA12 -> 6 | AB12: =Z12*AA12 -> 216 | AC12: ='6'!F14 -> 6 | AD12: =DELIVERIES!AD12 -> 8 | AE12: =AC12*AD12 -> 48 | AG12: =AG7 -> 0 | AH12: =AF12*AG12 -> 0 | AK12: =D12+G12+J12+M12+P12+S12+V12+Y12+AB12+AE12+AH12 -> 9976 | AM12: ='6'!F17 -> 7 | AN12: =DELIVERIES!AQ12 -> 8.75 | AO12: =AM12*AN12 -> 61.25 | AP12: ='6'!F18 -> 41 | AQ12: =DELIVERIES!AT12 -> 12.25 | AR12: =AP12*AQ12 -> 502.25 | AS12: ='6'!F21 -> 0 | AT12: =DELIVERIES!AW12 -> 7.9166667 | AU12: =AS12*AT12 -> 0 | AV12: ='6'!F22 -> 7 | AW12: =DELIVERIES!AZ12 -> 9.7916667 | AX12: =AV12*AW12 -> 68.541667 | AY12: ='6'!F26 -> 0 | AZ12: =DELIVERIES!BC12 -> 16.333333 | BA12: =AY12*AZ12 -> 0 | BB12: ='6'!F27 -> 8 | BC12: =DELIVERIES!BF12 -> 11.5 | BD12: =BB12*BC12 -> 92 | BE12: ='6'!F28 -> 3 | BF12: =DELIVERIES!BI36 -> 20 | BG12: =BE12*BF12 -> 60 | BH12: ='6'!F23 -> 0 | BI12: =DELIVERIES!BL12 -> 23 | BJ12: =BH12*BI12 -> 0 | BK12: ='6'!F25 -> 0 | BL12: =DELIVERIES!BO12 -> 12.5 | BM12: =BK12*BL12 -> 0 | BN12: ='6'!F24 -> 2 | BO12: =DELIVERIES!BR12 -> 12.75 | BP12: =BN12*BO12 -> 25.5 | BQ12: ='6'!F19 -> 0 | BR12: =DELIVERIES!BU12 -> 30.25 | BS12: =BQ12*BR12 -> 0 | BT12: ='6'!F20 -> 0 | BU12: =DELIVERIES!BX12 -> 15.916667 | BV12: =BT12*BU12 -> 0 | BY12: =AO12+AR12+AU12+AX12+BA12+BD12+BG12+BJ12+BM12+BP12+BS12+BV12 -> 809.54167 | CA12: =BY12+AK12 -> 10785.542 | CD12: =CA12-CC12 -> 10785.542
A13: 7 | B13: =GROSS!B13 -> 0 | C13: =DELIVERIES!C13 -> 30 | D13: =B13*C13 -> 0 | E13: ='7'!F7 -> 158 | F13: =DELIVERIES!F13 -> 35 | G13: =E13*F13 -> 5530 | H13: ='7'!F8 -> 17 | I13: =DELIVERIES!I13 -> 8.5 | J13: =H13*I13 -> 144.5 | K13: ='7'!F15 -> 11 | L13: =DELIVERIES!L13 -> 18 | M13: =K13*L13 -> 198 | N13: ='7'!F9 -> 86 | O13: =DELIVERIES!O13 -> 7 | P13: =N13*O13 -> 602 | Q13: ='7'!F10 -> 0 | R13: =DELIVERIES!R13 -> 5.5 | S13: =Q13*R13 -> 0 | T13: ='7'!F11 -> 169 | U13: =DELIVERIES!U13 -> 8.5 | V13: =T13*U13 -> 1436.5 | W13: ='7'!F12 -> 34 | X13: =DELIVERIES!X13 -> 6 | Y13: =W13*X13 -> 204 | Z13: ='7'!F13 -> 33 | AA13: =DELIVERIES!AA13 -> 6 | AB13: =Z13*AA13 -> 198 | AC13: ='7'!F14 -> 11 | AD13: =DELIVERIES!AD13 -> 8 | AE13: =AC13*AD13 -> 88 | AG13: =AG7 -> 0 | AH13: =AF13*AG13 -> 0 | AK13: =D13+G13+J13+M13+P13+S13+V13+Y13+AB13+AE13+AH13 -> 8401 | AM13: ='7'!F17 -> 8 | AN13: =DELIVERIES!AQ13 -> 8.75 | AO13: =AM13*AN13 -> 70 | AP13: ='7'!F18 -> 31 | AQ13: =DELIVERIES!AT13 -> 12.25 | AR13: =AP13*AQ13 -> 379.75 | AS13: ='7'!F21 -> 0 | AT13: =DELIVERIES!AW13 -> 7.9166667 | AU13: =AS13*AT13 -> 0 | AV13: ='7'!F22 -> 9 | AW13: =DELIVERIES!AZ13 -> 9.7916667 | AX13: =AV13*AW13 -> 88.125 | AY13: ='7'!F26 -> 0 | AZ13: =DELIVERIES!BC13 -> 16.333333 | BA13: =AY13*AZ13 -> 0 | BB13: ='7'!F27 -> 6 | BC13: =DELIVERIES!BF13 -> 11.5 | BD13: =BB13*BC13 -> 69 | BE13: ='7'!F28 -> 2 | BF13: =DELIVERIES!BI37 -> 20 | BG13: =BE13*BF13 -> 40 | BH13: ='7'!F23 -> 0 | BI13: =DELIVERIES!BL13 -> 23 | BJ13: =BH13*BI13 -> 0 | BK13: ='7'!F25 -> 0 | BL13: =DELIVERIES!BO13 -> 12.5 | BM13: =BK13*BL13 -> 0 | BN13: ='7'!F24 -> 7 | BO13: =DELIVERIES!BR13 -> 12.75 | BP13: =BN13*BO13 -> 89.25 | BQ13: ='7'!F19 -> 0 | BR13: =DELIVERIES!BU13 -> 30.25 | BS13: =BQ13*BR13 -> 0 | BT13: ='7'!F20 -> 0 | BU13: =DELIVERIES!BX13 -> 15.916667 | BV13: =BT13*BU13 -> 0 | BY13: =AO13+AR13+AU13+AX13+BA13+BD13+BG13+BJ13+BM13+BP13+BS13+BV13 -> 736.125 | CA13: =BY13+AK13 -> 9137.125 | CD13: =CA13-CC13 -> 9137.125
A14: TOTAL | B14: =SUM(B7:B13) -> 0 | D14: =SUM(D7:D13) -> 0 | E14: =SUM(E7:E13) -> 1278 | G14: =SUM(G7:G13) -> 44730 | H14: =SUM(H7:H13) -> 92 | J14: =SUM(J7:J13) -> 782 | K14: =SUM(K7:K13) -> 103 | M14: =SUM(M7:M13) -> 1854 | N14: =SUM(N7:N13) -> 452 | P14: =SUM(P7:P13) -> 3164 | Q14: =SUM(Q7:Q13) -> 0 | S14: =SUM(S7:S13) -> 0 | T14: =SUM(T7:T13) -> 1381 | V14: =SUM(V7:V13) -> 11738.5 | W14: =SUM(W7:W13) -> 302 | Y14: =SUM(Y7:Y13) -> 1812 | Z14: =SUM(Z7:Z13) -> 271 | AB14: =SUM(AB7:AB13) -> 1626 | AC14: =SUM(AC7:AC13) -> 81 | AE14: =SUM(AE7:AE13) -> 648 | AF14: =SUM(AF7:AF13) -> 0 | AH14: =SUM(AH7:AH13) -> 0 | AK14: =SUM(AK7:AK13) -> 66354.5 | AM14: =SUM(AM7:AM13) -> 83 | AO14: =SUM(AO7:AO13) -> 726.25 | AP14: =SUM(AP7:AP13) -> 281 | AR14: =SUM(AR7:AR13) -> 3442.25 | AS14: =SUM(AS7:AS13) -> 0 | AU14: =SUM(AU7:AU13) -> 0 | AV14: =SUM(AV7:AV13) -> 46 | AX14: =SUM(AX7:AX13) -> 450.41667 | AY14: =SUM(AY7:AY13) -> 0 | BA14: =SUM(BA7:BA13) -> 0 | BB14: =SUM(BB7:BB13) -> 57 | BD14: =SUM(BD7:BD13) -> 655.5 | BE14: =SUM(BE7:BE13) -> 36 | BG14: =SUM(BG7:BG13) -> 720 | BH14: =SUM(BH7:BH13) -> 0 | BJ14: =SUM(BJ7:BJ13) -> 0 | BK14: =SUM(BK7:BK13) -> 0 | BM14: =SUM(BM7:BM13) -> 0 | BN14: =SUM(BN7:BN13) -> 32 | BP14: =SUM(BP7:BP13) -> 408 | BQ14: =SUM(BQ7:BQ13) -> 0 | BS14: =SUM(BS7:BS13) -> 0 | BT14: =SUM(BT7:BT13) -> 0 | BV14: =SUM(BV7:BV13) -> 0 | BY14: =SUM(BY7:BY13) -> 6402.4167 | CA14: =SUM(CA7:CA13) -> 72756.917 | CD14: =SUM(CD7:CD13) -> 72756.917
A17: WEEK- 2 | B17: =B5 -> PREMIUM - CUT | E17: SPECIAL CUT | H17: NGOHIONG | K17: =K5 -> Chicken Fillet | N17: NECK | Q17: SIOMAI | T17: RICE | W17: BOLA-BOLA | Z17: LUMPIA | AC17: ATSARA | AF17: =AF5 -> 0 | AI17: =AI5 -> SUBTOTAL | AM17: 8OZ | AP17: 12 OZ | AS17: WATER 350 ML | AV17: WATER 500 ML | AY17: PANALO | BB17: =BB5 -> swakto | BE17: =BE5 -> Calamansi Juice | BH17: =BH5 -> GATORADE | BK17: TROPICANA | BN17: STING | BQ17: =BQ5 -> 1 LITER | BT17: =BT5 -> 1.5 L | BW17: SUBTOTAL FOR DRINKS | CA17: TOTAL
A18: DATE | B18: QTY | C18: UP | D18: AMOUNT | E18: QTY | F18: UP | G18: AMOUNT | H18: QTY | I18: UP | J18: AMOUNT | K18: QTY | L18: UP | M18: AMOUNT | N18: QTY | O18: UP | P18: AMOUNT | Q18: QTY | R18: UP | S18: AMOUNT | T18: QTY | U18: UP | V18: AMOUNT | W18: QTY | X18: UP | Y18: AMOUNT | Z18: QTY | AA18: UP | AB18: AMOUNT | AC18: QTY | AD18: UP | AE18: AMOUNT | AF18: QTY | AG18: UP | AH18: AMOUNT | AK18: AMOUNT | AM18: QTY | AN18: UP | AO18: AMOUNT | AP18: QTY | AQ18: UP | AR18: AMOUNT | AS18: QTY | AT18: UP | AU18: AMOUNT | AV18: QTY | AW18: UP | AX18: AMOUNT | AY18: QTY | AZ18: UP | BA18: AMOUNT | BB18: QTY | BC18: UP | BD18: AMOUNT | BE18: QTY | BF18: UP | BG18: AMOUNT | BH18: QTY | BI18: UP | BJ18: AMOUNT | BK18: QTY | BL18: UP | BM18: AMOUNT | BN18: QTY | BO18: UP | BP18: AMOUNT | BQ18: QTY | BR18: UP | BS18: AMOUNT | BT18: QTY | BU18: UP | BV18: AMOUNT | BY18: AMOUNT | CA18: AMOUNT
A19: 8 | B19: =GROSS!B19 -> 0 | C19: =DELIVERIES!C19 -> 30 | D19: =B19*C19 -> 0 | E19: ='8'!F7 -> 243 | F19: =DELIVERIES!F19 -> 35 | G19: =E19*F19 -> 8505 | H19: ='8'!F8 -> 8 | I19: =DELIVERIES!I19 -> 8.5 | J19: =H19*I19 -> 68 | K19: ='8'!F15 -> 12 | L19: =DELIVERIES!L19 -> 18 | M19: =K19*L19 -> 216 | N19: ='8'!F9 -> 64 | O19: =DELIVERIES!O19 -> 7 | P19: =N19*O19 -> 448 | Q19: ='8'!F10 -> 0 | R19: =DELIVERIES!R19 -> 5.5 | S19: =Q19*R19 -> 0 | T19: ='8'!F11 -> 180 | U19: =DELIVERIES!U19 -> 8.5 | V19: =T19*U19 -> 1530 | W19: ='8'!F12 -> 44 | X19: =DELIVERIES!X19 -> 6 | Y19: =W19*X19 -> 264 | Z19: ='8'!F13 -> 41 | AA19: =DELIVERIES!AA19 -> 6 | AB19: =Z19*AA19 -> 246 | AC19: ='8'!F14 -> 4 | AD19: =DELIVERIES!AD19 -> 8 | AE19: =AC19*AD19 -> 32 | AG19: =AG7 -> 0 | AH19: =AF19*AG19 -> 0 | AK19: =D19+G19+J19+M19+P19+S19+V19+Y19+AB19+AE19+AH19 -> 11309 | AM19: ='8'!F17 -> 13 | AN19: =DELIVERIES!AQ19 -> 8.75 | AO19: =AM19*AN19 -> 113.75 | AP19: ='8'!F18 -> 32 | AQ19: =DELIVERIES!AT19 -> 12.25 | AR19: =AP19*AQ19 -> 392 | AS19: ='8'!F21 -> 0 | AT19: =DELIVERIES!AZ19 -> 9.7916667 | AU19: =AS19*AT19 -> 0 | AV19: ='8'!F22 -> 10 | AW19: =DELIVERIES!AZ19 -> 9.7916667 | AX19: =AV19*AW19 -> 97.916667 | AY19: ='8'!F26 -> 0 | AZ19: =DELIVERIES!BC19 -> 16.333333 | BA19: =AY19*AZ19 -> 0 | BB19: ='8'!F27 -> 11 | BC19: =DELIVERIES!BF19 -> 11.5 | BD19: =BB19*BC19 -> 126.5 | BE19: ='8'!F28 -> 3 | BF19: =DELIVERIES!BI43 -> 20 | BG19: =BE19*BF19 -> 60 | BH19: ='8'!F23 -> 0 | BI19: =DELIVERIES!BL19 -> 23 | BJ19: =BH19*BI19 -> 0 | BK19: ='8'!F25 -> 0 | BL19: =DELIVERIES!BO19 -> 12.5 | BM19: =BK19*BL19 -> 0 | BN19: ='8'!F24 -> 4 | BO19: =DELIVERIES!BR19 -> 12.75 | BP19: =BN19*BO19 -> 51 | BQ19: ='8'!F19 -> 0 | BR19: =DELIVERIES!BU19 -> 30.25 | BS19: =BQ19*BR19 -> 0 | BT19: ='8'!F20 -> 0 | BU19: =DELIVERIES!BX19 -> 15.916667 | BV19: =BT19*BU19 -> 0 | BY19: =AO19+AR19+AU19+AX19+BA19+BD19+BG19+BJ19+BM19+BP19+BS19+BV19 -> 841.16667 | CA19: =AK19+BY19 -> 12150.167 | CD19: =CA19-CC19 -> 12150.167
A20: 9 | B20: =GROSS!B20 -> 0 | C20: =DELIVERIES!C20 -> 30 | D20: =B20*C20 -> 0 | E20: ='9'!F7 -> 226 | F20: =DELIVERIES!F20 -> 35 | G20: =E20*F20 -> 7910 | H20: ='9'!F8 -> 8 | I20: =DELIVERIES!I20 -> 8.5 | J20: =H20*I20 -> 68 | K20: ='9'!F15 -> 16 | L20: =DELIVERIES!L20 -> 18 | M20: =K20*L20 -> 288 | N20: ='9'!F9 -> 100 | O20: =DELIVERIES!O20 -> 7 | P20: =N20*O20 -> 700 | Q20: ='9'!F10 -> 0 | R20: =DELIVERIES!R20 -> 5.5 | S20: =Q20*R20 -> 0 | T20: ='9'!F11 -> 203 | U20: =DELIVERIES!U20 -> 8.5 | V20: =T20*U20 -> 1725.5 | W20: ='9'!F12 -> 39 | X20: =DELIVERIES!X20 -> 6 | Y20: =W20*X20 -> 234 | Z20: ='9'!F13 -> 35 | AA20: =DELIVERIES!AA20 -> 6 | AB20: =Z20*AA20 -> 210 | AC20: ='9'!F14 -> 7 | AD20: =DELIVERIES!AD20 -> 8 | AE20: =AC20*AD20 -> 56 | AG20: =AG7 -> 0 | AH20: =AF20*AG20 -> 0 | AK20: =D20+G20+J20+M20+P20+S20+V20+Y20+AB20+AE20+AH20 -> 11191.5 | AM20: ='9'!F17 -> 10 | AN20: =DELIVERIES!AQ20 -> 8.75 | AO20: =AM20*AN20 -> 87.5 | AP20: ='9'!F18 -> 38 | AQ20: =DELIVERIES!AT20 -> 12.25 | AR20: =AP20*AQ20 -> 465.5 | AS20: ='9'!F21 -> 0 | AT20: =DELIVERIES!AZ20 -> 9.7916667 | AU20: =AS20*AT20 -> 0 | AV20: ='9'!F22 -> 1 | AW20: =DELIVERIES!AZ20 -> 9.7916667 | AX20: =AV20*AW20 -> 9.7916667 | AY20: ='9'!F26 -> 0 | AZ20: =DELIVERIES!BC20 -> 16.333333 | BA20: =AY20*AZ20 -> 0 | BB20: ='9'!F27 -> 14 | BC20: =DELIVERIES!BF20 -> 11.5 | BD20: =BB20*BC20 -> 161 | BE20: ='9'!F28 -> 0 | BF20: =DELIVERIES!BI44 -> 20 | BG20: =BE20*BF20 -> 0 | BH20: ='9'!F23 -> 0 | BI20: =DELIVERIES!BL20 -> 23 | BJ20: =BH20*BI20 -> 0 | BK20: ='9'!F25 -> 0 | BL20: =DELIVERIES!BO20 -> 12.5 | BM20: =BK20*BL20 -> 0 | BN20: ='9'!F24 -> 1 | BO20: =DELIVERIES!BR20 -> 12.75 | BP20: =BN20*BO20 -> 12.75 | BQ20: ='9'!F19 -> 0 | BR20: =DELIVERIES!BU20 -> 30.25 | BS20: =BQ20*BR20 -> 0 | BT20: ='9'!F20 -> 0 | BU20: =DELIVERIES!BX20 -> 15.916667 | BV20: =BT20*BU20 -> 0 | BY20: =AO20+AR20+AU20+AX20+BA20+BD20+BG20+BJ20+BM20+BP20+BS20+BV20 -> 736.54167 | CA20: =AK20+BY20 -> 11928.042 | CD20: =CA20-CC20 -> 11928.042
A21: 10 | B21: =GROSS!B21 -> 0 | C21: =DELIVERIES!C21 -> 30 | D21: =B21*C21 -> 0 | E21: ='10'!F7 -> 190 | F21: =DELIVERIES!F21 -> 35 | G21: =E21*F21 -> 6650 | H21: ='10'!F8 -> 4 | I21: =DELIVERIES!I21 -> 8.5 | J21: =H21*I21 -> 34 | K21: ='10'!F15 -> 7 | L21: =DELIVERIES!L21 -> 18 | M21: =K21*L21 -> 126 | N21: ='10'!F9 -> 100 | O21: =DELIVERIES!O21 -> 7 | P21: =N21*O21 -> 700 | Q21: ='10'!F10 -> 0 | R21: =DELIVERIES!R21 -> 5.5 | S21: =Q21*R21 -> 0 | T21: ='10'!F11 -> 167 | U21: =DELIVERIES!U21 -> 8.5 | V21: =T21*U21 -> 1419.5 | W21: ='10'!F12 -> 36 | X21: =DELIVERIES!X21 -> 6 | Y21: =W21*X21 -> 216 | Z21: ='10'!F13 -> 35 | AA21: =DELIVERIES!AA21 -> 6 | AB21: =Z21*AA21 -> 210 | AC21: ='10'!F14 -> 5 | AD21: =DELIVERIES!AD21 -> 8 | AE21: =AC21*AD21 -> 40 | AG21: =AG7 -> 0 | AH21: =AF21*AG21 -> 0 | AK21: =D21+G21+J21+M21+P21+S21+V21+Y21+AB21+AE21+AH21 -> 9395.5 | AM21: ='10'!F17 -> 8 | AN21: =DELIVERIES!AQ21 -> 8.75 | AO21: =AM21*AN21 -> 70 | AP21: ='10'!F18 -> 30 | AQ21: =DELIVERIES!AT21 -> 12.25 | AR21: =AP21*AQ21 -> 367.5 | AS21: ='10'!F21 -> 0 | AT21: =DELIVERIES!AZ21 -> 9.7916667 | AU21: =AS21*AT21 -> 0 | AV21: ='10'!F22 -> 2 | AW21: =DELIVERIES!AZ21 -> 9.7916667 | AX21: =AV21*AW21 -> 19.583333 | AY21: ='10'!F26 -> 0 | AZ21: =DELIVERIES!BC21 -> 16.333333 | BA21: =AY21*AZ21 -> 0 | BB21: ='10'!F27 -> 4 | BC21: =DELIVERIES!BF21 -> 11.5 | BD21: =BB21*BC21 -> 46 | BE21: ='10'!F28 -> 5 | BF21: =DELIVERIES!BI45 -> 20 | BG21: =BE21*BF21 -> 100 | BH21: ='10'!F23 -> 0 | BI21: =DELIVERIES!BL21 -> 23 | BJ21: =BH21*BI21 -> 0 | BK21: ='10'!F25 -> 0 | BL21: =DELIVERIES!BO21 -> 12.5 | BM21: =BK21*BL21 -> 0 | BN21: ='10'!F24 -> 1 | BO21: =DELIVERIES!BR21 -> 12.75 | BP21: =BN21*BO21 -> 12.75 | BQ21: ='10'!F19 -> 0 | BR21: =DELIVERIES!BU21 -> 30.25 | BS21: =BQ21*BR21 -> 0 | BT21: ='10'!F20 -> 0 | BU21: =DELIVERIES!BX21 -> 15.916667 | BV21: =BT21*BU21 -> 0 | BY21: =AO21+AR21+AU21+AX21+BA21+BD21+BG21+BJ21+BM21+BP21+BS21+BV21 -> 615.83333 | CA21: =AK21+BY21 -> 10011.333 | CD21: =CA21-CC21 -> 10011.333
A22: 11 | B22: =GROSS!B22 -> 0 | C22: =DELIVERIES!C22 -> 30 | D22: =B22*C22 -> 0 | E22: ='11'!F7 -> 213 | F22: =DELIVERIES!F22 -> 35 | G22: =E22*F22 -> 7455 | H22: ='11'!F8 -> 7 | I22: =DELIVERIES!I22 -> 8.5 | J22: =H22*I22 -> 59.5 | K22: ='11'!F15 -> 16 | L22: =DELIVERIES!L22 -> 18 | M22: =K22*L22 -> 288 | N22: ='11'!F9 -> 110 | O22: =DELIVERIES!O22 -> 7 | P22: =N22*O22 -> 770 | Q22: ='11'!F10 -> 0 | R22: =DELIVERIES!R22 -> 5.5 | S22: =Q22*R22 -> 0 | T22: ='11'!F11 -> 190 | U22: =DELIVERIES!U22 -> 8.5 | V22: =T22*U22 -> 1615 | W22: ='11'!F12 -> 41 | X22: =DELIVERIES!X22 -> 6 | Y22: =W22*X22 -> 246 | Z22: ='11'!F13 -> 37 | AA22: =DELIVERIES!AA22 -> 6 | AB22: =Z22*AA22 -> 222 | AC22: ='11'!F14 -> 12 | AD22: =DELIVERIES!AD22 -> 8 | AE22: =AC22*AD22 -> 96 | AG22: =AG7 -> 0 | AH22: =AF22*AG22 -> 0 | AK22: =D22+G22+J22+M22+P22+S22+V22+Y22+AB22+AE22+AH22 -> 10751.5 | AM22: ='11'!F17 -> 16 | AN22: =DELIVERIES!AQ22 -> 8.75 | AO22: =AM22*AN22 -> 140 | AP22: ='11'!F18 -> 27 | AQ22: =DELIVERIES!AT22 -> 12.25 | AR22: =AP22*AQ22 -> 330.75 | AS22: ='11'!F21 -> 0 | AT22: =DELIVERIES!AZ22 -> 9.7916667 | AU22: =AS22*AT22 -> 0 | AV22: ='11'!F22 -> 1 | AW22: =DELIVERIES!AZ22 -> 9.7916667 | AX22: =AV22*AW22 -> 9.7916667 | AY22: ='11'!F26 -> 0 | AZ22: =DELIVERIES!BC22 -> 16.333333 | BA22: =AY22*AZ22 -> 0 | BB22: ='11'!F27 -> 10 | BC22: =DELIVERIES!BF22 -> 11.5 | BD22: =BB22*BC22 -> 115 | BE22: ='11'!F28 -> 0 | BF22: =DELIVERIES!BI46 -> 20 | BG22: =BE22*BF22 -> 0 | BH22: ='11'!F23 -> 0 | BI22: =DELIVERIES!BL22 -> 23 | BJ22: =BH22*BI22 -> 0 | BK22: ='11'!F25 -> 0 | BL22: =DELIVERIES!BO22 -> 12.5 | BM22: =BK22*BL22 -> 0 | BN22: ='11'!F24 -> 5 | BO22: =DELIVERIES!BR22 -> 12.75 | BP22: =BN22*BO22 -> 63.75 | BQ22: ='11'!F19 -> 0 | BR22: =DELIVERIES!BU22 -> 30.25 | BS22: =BQ22*BR22 -> 0 | BT22: ='11'!F20 -> 0 | BU22: =DELIVERIES!BX22 -> 15.916667 | BV22: =BT22*BU22 -> 0 | BY22: =AO22+AR22+AU22+AX22+BA22+BD22+BG22+BJ22+BM22+BP22+BS22+BV22 -> 659.29167 | CA22: =AK22+BY22 -> 11410.792 | CD22: =CA22-CC22 -> 11410.792
A23: 12 | B23: =GROSS!B23 -> 0 | C23: =DELIVERIES!C23 -> 30 | D23: =B23*C23 -> 0 | E23: ='12'!F7 -> 258 | F23: =DELIVERIES!F23 -> 35 | G23: =E23*F23 -> 9030 | H23: ='12'!F8 -> 12 | I23: =DELIVERIES!I23 -> 8.5 | J23: =H23*I23 -> 102 | K23: ='12'!F15 -> 25 | L23: =DELIVERIES!L23 -> 18 | M23: =K23*L23 -> 450 | N23: ='12'!F9 -> 40 | O23: =DELIVERIES!O23 -> 7 | P23: =N23*O23 -> 280 | Q23: ='12'!F10 -> 0 | R23: =DELIVERIES!R23 -> 5.5 | S23: =Q23*R23 -> 0 | T23: ='12'!F11 -> 183 | U23: =DELIVERIES!U23 -> 8.5 | V23: =T23*U23 -> 1555.5 | W23: ='12'!F12 -> 65 | X23: =DELIVERIES!X23 -> 6 | Y23: =W23*X23 -> 390 | Z23: ='12'!F13 -> 48 | AA23: =DELIVERIES!AA23 -> 6 | AB23: =Z23*AA23 -> 288 | AC23: ='12'!F14 -> 21 | AD23: =DELIVERIES!AD23 -> 8 | AE23: =AC23*AD23 -> 168 | AG23: =AG7 -> 0 | AH23: =AF23*AG23 -> 0 | AK23: =D23+G23+J23+M23+P23+S23+V23+Y23+AB23+AE23+AH23 -> 12263.5 | AM23: ='12'!F17 -> 16 | AN23: =DELIVERIES!AQ23 -> 8.75 | AO23: =AM23*AN23 -> 140 | AP23: ='12'!F18 -> 44 | AQ23: =DELIVERIES!AT23 -> 12.25 | AR23: =AP23*AQ23 -> 539 | AS23: ='12'!F21 -> 0 | AT23: =DELIVERIES!AZ23 -> 9.7916667 | AU23: =AS23*AT23 -> 0 | AV23: ='12'!F22 -> 9 | AW23: =DELIVERIES!AZ23 -> 9.7916667 | AX23: =AV23*AW23 -> 88.125 | AY23: ='12'!F26 -> 0 | AZ23: =DELIVERIES!BC23 -> 16.333333 | BA23: =AY23*AZ23 -> 0 | BB23: ='12'!F27 -> 11 | BC23: =DELIVERIES!BF23 -> 11.666667 | BD23: =BB23*BC23 -> 128.33333 | BE23: ='12'!F28 -> 7 | BF23: =DELIVERIES!BI47 -> 20 | BG23: =BE23*BF23 -> 140 | BH23: ='12'!F23 -> 0 | BI23: =DELIVERIES!BL23 -> 23 | BJ23: =BH23*BI23 -> 0 | BK23: ='12'!F25 -> 0 | BL23: =DELIVERIES!BO23 -> 12.5 | BM23: =BK23*BL23 -> 0 | BN23: ='12'!F24 -> 2 | BO23: =DELIVERIES!BR23 -> 12.75 | BP23: =BN23*BO23 -> 25.5 | BQ23: ='12'!F19 -> 0 | BR23: =DELIVERIES!BU23 -> 30.25 | BS23: =BQ23*BR23 -> 0 | BT23: ='12'!F20 -> 0 | BU23: =DELIVERIES!BX23 -> 15.916667 | BV23: =BT23*BU23 -> 0 | BY23: =AO23+AR23+AU23+AX23+BA23+BD23+BG23+BJ23+BM23+BP23+BS23+BV23 -> 1060.9583 | CA23: =AK23+BY23 -> 13324.458 | CD23: =CA23-CC23 -> 13324.458
A24: 13 | B24: =GROSS!B24 -> 0 | C24: =DELIVERIES!C24 -> 30 | D24: =B24*C24 -> 0 | E24: ='13'!F7 -> 183 | F24: =DELIVERIES!F24 -> 35 | G24: =E24*F24 -> 6405 | H24: ='13'!F8 -> 6 | I24: =DELIVERIES!I24 -> 8.5 | J24: =H24*I24 -> 51 | K24: ='13'!F15 -> 11 | L24: =DELIVERIES!L24 -> 18 | M24: =K24*L24 -> 198 | N24: ='13'!F9 -> 89 | O24: =DELIVERIES!O24 -> 7 | P24: =N24*O24 -> 623 | Q24: ='13'!F10 -> 0 | R24: =DELIVERIES!R24 -> 5.5 | S24: =Q24*R24 -> 0 | T24: ='13'!F11 -> 169 | U24: =DELIVERIES!U24 -> 8.5 | V24: =T24*U24 -> 1436.5 | W24: ='13'!F12 -> 39 | X24: =DELIVERIES!X24 -> 6 | Y24: =W24*X24 -> 234 | Z24: ='13'!F13 -> 36 | AA24: =DELIVERIES!AA24 -> 6 | AB24: =Z24*AA24 -> 216 | AC24: ='13'!F14 -> 11 | AD24: =DELIVERIES!AD24 -> 8 | AE24: =AC24*AD24 -> 88 | AG24: =AG7 -> 0 | AH24: =AF24*AG24 -> 0 | AK24: =D24+G24+J24+M24+P24+S24+V24+Y24+AB24+AE24+AH24 -> 9251.5 | AM24: ='13'!F17 -> 17 | AN24: =DELIVERIES!AQ24 -> 8.75 | AO24: =AM24*AN24 -> 148.75 | AP24: ='13'!F18 -> 32 | AQ24: =DELIVERIES!AT24 -> 12.25 | AR24: =AP24*AQ24 -> 392 | AS24: ='13'!F21 -> 0 | AT24: =DELIVERIES!AZ24 -> 9.7916667 | AU24: =AS24*AT24 -> 0 | AV24: ='13'!F22 -> 6 | AW24: =DELIVERIES!AZ24 -> 9.7916667 | AX24: =AV24*AW24 -> 58.75 | AY24: ='13'!F26 -> 0 | AZ24: =DELIVERIES!BC24 -> 16.333333 | BA24: =AY24*AZ24 -> 0 | BB24: ='13'!F27 -> 0 | BC24: =DELIVERIES!BF24 -> 11.666667 | BD24: =BB24*BC24 -> 0 | BE24: ='13'!F28 -> 2 | BF24: =DELIVERIES!BI48 -> 20 | BG24: =BE24*BF24 -> 40 | BH24: ='13'!F23 -> 0 | BI24: =DELIVERIES!BL24 -> 23 | BJ24: =BH24*BI24 -> 0 | BK24: ='13'!F25 -> 0 | BL24: =DELIVERIES!BO24 -> 12.5 | BM24: =BK24*BL24 -> 0 | BN24: ='13'!F24 -> 2 | BO24: =DELIVERIES!BR24 -> 12.75 | BP24: =BN24*BO24 -> 25.5 | BQ24: ='13'!F19 -> 0 | BR24: =DELIVERIES!BU24 -> 30.25 | BS24: =BQ24*BR24 -> 0 | BT24: ='13'!F20 -> 0 | BU24: =DELIVERIES!BX24 -> 15.916667 | BV24: =BT24*BU24 -> 0 | BY24: =AO24+AR24+AU24+AX24+BA24+BD24+BG24+BJ24+BM24+BP24+BS24+BV24 -> 665 | CA24: =AK24+BY24 -> 9916.5 | CD24: =CA24-CC24 -> 9916.5
A25: 14 | B25: =GROSS!B25 -> 0 | C25: =DELIVERIES!C25 -> 30 | D25: =B25*C25 -> 0 | E25: ='14'!F7 -> 183 | F25: =DELIVERIES!F25 -> 35 | G25: =E25*F25 -> 6405 | H25: ='14'!F8 -> 3 | I25: =DELIVERIES!I25 -> 8.5 | J25: =H25*I25 -> 25.5 | K25: ='14'!F15 -> 10 | L25: =DELIVERIES!L25 -> 18 | M25: =K25*L25 -> 180 | N25: ='14'!F9 -> 111 | O25: =DELIVERIES!O25 -> 7 | P25: =N25*O25 -> 777 | Q25: ='14'!F10 -> 0 | R25: =DELIVERIES!R25 -> 5.5 | S25: =Q25*R25 -> 0 | T25: ='14'!F11 -> 167 | U25: =DELIVERIES!U25 -> 8.5 | V25: =T25*U25 -> 1419.5 | W25: ='14'!F12 -> 26 | X25: =DELIVERIES!X25 -> 6 | Y25: =W25*X25 -> 156 | Z25: ='14'!F13 -> 34 | AA25: =DELIVERIES!AA25 -> 6 | AB25: =Z25*AA25 -> 204 | AC25: ='14'!F14 -> 20 | AD25: =DELIVERIES!AD25 -> 8 | AE25: =AC25*AD25 -> 160 | AG25: =AG7 -> 0 | AH25: =AF25*AG25 -> 0 | AK25: =D25+G25+J25+M25+P25+S25+V25+Y25+AB25+AE25+AH25 -> 9327 | AM25: ='14'!F17 -> 13 | AN25: =DELIVERIES!AQ25 -> 8.75 | AO25: =AM25*AN25 -> 113.75 | AP25: ='14'!F18 -> 39 | AQ25: =DELIVERIES!AT25 -> 12.25 | AR25: =AP25*AQ25 -> 477.75 | AS25: ='14'!F21 -> 0 | AT25: =DELIVERIES!AZ25 -> 9.7916667 | AU25: =AS25*AT25 -> 0 | AV25: ='14'!F22 -> 10 | AW25: =DELIVERIES!AZ25 -> 9.7916667 | AX25: =AV25*AW25 -> 97.916667 | AY25: ='14'!F26 -> 0 | AZ25: =DELIVERIES!BC25 -> 16.333333 | BA25: =AY25*AZ25 -> 0 | BB25: ='14'!F27 -> 0 | BC25: =DELIVERIES!BF25 -> 11.666667 | BD25: =BB25*BC25 -> 0 | BE25: ='14'!F28 -> 8 | BF25: =DELIVERIES!BI49 -> 20 | BG25: =BE25*BF25 -> 160 | BH25: ='14'!F23 -> 0 | BI25: =DELIVERIES!BL25 -> 23 | BJ25: =BH25*BI25 -> 0 | BK25: ='14'!F25 -> 0 | BL25: =DELIVERIES!BO25 -> 12.5 | BM25: =BK25*BL25 -> 0 | BN25: ='14'!F24 -> 4 | BO25: =DELIVERIES!BR25 -> 12.75 | BP25: =BN25*BO25 -> 51 | BQ25: ='14'!F19 -> 0 | BR25: =DELIVERIES!BU25 -> 30.25 | BS25: =BQ25*BR25 -> 0 | BT25: ='14'!F20 -> 0 | BU25: =DELIVERIES!BX25 -> 15.916667 | BV25: =BT25*BU25 -> 0 | BY25: =AO25+AR25+AU25+AX25+BA25+BD25+BG25+BJ25+BM25+BP25+BS25+BV25 -> 900.41667 | CA25: =AK25+BY25 -> 10227.417 | CD25: =CA25-CC25 -> 10227.417
A26: TOTAL | B26: =SUM(B19:B25) -> 0 | D26: =SUM(D19:D25) -> 0 | E26: =SUM(E19:E25) -> 1496 | G26: =SUM(G19:G25) -> 52360 | H26: =SUM(H19:H25) -> 48 | J26: =SUM(J19:J25) -> 408 | K26: =SUM(K19:K25) -> 97 | M26: =SUM(M19:M25) -> 1746 | N26: =SUM(N19:N25) -> 614 | P26: =SUM(P19:P25) -> 4298 | Q26: =SUM(Q19:Q25) -> 0 | S26: =SUM(S19:S25) -> 0 | T26: =SUM(T19:T25) -> 1259 | V26: =SUM(V19:V25) -> 10701.5 | W26: =SUM(W19:W25) -> 290 | Y26: =SUM(Y19:Y25) -> 1740 | Z26: =SUM(Z19:Z25) -> 266 | AB26: =SUM(AB19:AB25) -> 1596 | AC26: =SUM(AC19:AC25) -> 80 | AE26: =SUM(AE19:AE25) -> 640 | AF26: =SUM(AF19:AF25) -> 0 | AH26: =SUM(AH19:AH25) -> 0 | AK26: =SUM(AK19:AK25) -> 73489.5 | AM26: =SUM(AM19:AM25) -> 93 | AO26: =SUM(AO19:AO25) -> 813.75 | AP26: =SUM(AP19:AP25) -> 242 | AR26: =SUM(AR19:AR25) -> 2964.5 | AS26: =SUM(AS19:AS25) -> 0 | AU26: =SUM(AU19:AU25) -> 0 | AV26: =SUM(AV19:AV25) -> 39 | AX26: =SUM(AX19:AX25) -> 381.875 | AY26: =SUM(AY19:AY25) -> 0 | BA26: =SUM(BA19:BA25) -> 0 | BB26: =SUM(BB19:BB25) -> 50 | BD26: =SUM(BD19:BD25) -> 576.83333 | BE26: =SUM(BE19:BE25) -> 25 | BG26: =SUM(BG19:BG25) -> 500 | BH26: =SUM(BH19:BH25) -> 0 | BJ26: =SUM(BJ19:BJ25) -> 0 | BK26: =SUM(BK19:BK25) -> 0 | BM26: =SUM(BM19:BM25) -> 0 | BN26: =SUM(BN19:BN25) -> 19 | BP26: =SUM(BP19:BP25) -> 242.25 | BQ26: =SUM(BQ19:BQ25) -> 0 | BS26: =SUM(BS19:BS25) -> 0 | BT26: =SUM(BT19:BT25) -> 0 | BV26: =SUM(BV19:BV25) -> 0 | BY26: =SUM(BY19:BY25) -> 5479.2083 | CA26: =SUM(CA19:CA25) -> 78968.708 | CD26: =SUM(CD19:CD25) -> 78968.708
A29: WEEK- 3 | B29: =B5 -> PREMIUM - CUT | E29: SPECIAL CUT | H29: NGOHIONG | K29: =K17 -> Chicken Fillet | N29: NECK | Q29: SIOMAI | T29: RICE | W29: BOLA-BOLA | Z29: LUMPIA | AC29: ATSARA | AF29: =AF5 -> 0 | AI29: =AI5 -> SUBTOTAL | AM29: 8OZ | AP29: 12 OZ | AS29: WATER 350 ML | AV29: WATER 500 ML | AY29: PANALO | BB29: =BB17 -> swakto | BE29: Calamansi Juice | BH29: =BH17 -> GATORADE | BK29: TROPICANA | BN29: STING | BQ29: =BQ17 -> 1 LITER | BT29: =BT17 -> 1.5 L | BW29: SUBTOTAL FOR DRINKS | CA29: TOTAL
A30: DATE | B30: QTY | C30: UP | D30: AMOUNT | E30: QTY | F30: UP | G30: AMOUNT | H30: QTY | I30: UP | J30: AMOUNT | K30: QTY | L30: UP | M30: AMOUNT | N30: QTY | O30: UP | P30: AMOUNT | Q30: QTY | R30: UP | S30: AMOUNT | T30: QTY | U30: UP | V30: AMOUNT | W30: QTY | X30: UP | Y30: AMOUNT | Z30: QTY | AA30: UP | AB30: AMOUNT | AC30: QTY | AD30: UP | AE30: AMOUNT | AF30: QTY | AG30: UP | AH30: AMOUNT | AK30: AMOUNT | AM30: QTY | AN30: UP | AO30: AMOUNT | AP30: QTY | AQ30: UP | AR30: AMOUNT | AS30: QTY | AT30: UP | AU30: AMOUNT | AV30: QTY | AW30: UP | AX30: AMOUNT | AY30: QTY | AZ30: UP | BA30: AMOUNT | BB30: QTY | BC30: UP | BD30: AMOUNT | BE30: QTY | BF30: UP | BG30: AMOUNT | BH30: QTY | BI30: UP | BJ30: AMOUNT | BK30: QTY | BL30: UP | BM30: AMOUNT | BN30: QTY | BO30: UP | BP30: AMOUNT | BQ30: QTY | BR30: UP | BS30: AMOUNT | BT30: QTY | BU30: UP | BV30: AMOUNT | BY30: AMOUNT | CA30: AMOUNT
A31: 15 | B31: =GROSS!B31 -> 0 | C31: =DELIVERIES!C31 -> 30 | D31: =B31*C31 -> 0 | E31: ='15'!F7 -> 238 | F31: =DELIVERIES!F31 -> 35 | G31: =E31*F31 -> 8330 | H31: ='15'!F8 -> 14 | I31: =DELIVERIES!I31 -> 8.5 | J31: =H31*I31 -> 119 | K31: ='15'!F15 -> 10 | L31: =DELIVERIES!L31 -> 18 | M31: =K31*L31 -> 180 | N31: ='15'!F9 -> 50 | O31: =DELIVERIES!O31 -> 7 | P31: =N31*O31 -> 350 | Q31: ='15'!F10 -> 0 | R31: =DELIVERIES!R31 -> 5.5 | S31: =Q31*R31 -> 0 | T31: ='15'!F11 -> 195 | U31: =DELIVERIES!U31 -> 8.5 | V31: =T31*U31 -> 1657.5 | W31: ='15'!F12 -> 36 | X31: =DELIVERIES!X31 -> 6 | Y31: =W31*X31 -> 216 | Z31: ='15'!F13 -> 42 | AA31: =DELIVERIES!AA31 -> 6 | AB31: =Z31*AA31 -> 252 | AC31: ='15'!F14 -> 12 | AD31: =DELIVERIES!AD31 -> 8 | AE31: =AC31*AD31 -> 96 | AG31: =AG7 -> 0 | AH31: =AF31*AG31 -> 0 | AK31: =D31+G31+J31+M31+P31+S31+V31+Y31+AB31+AE31+AH31 -> 11200.5 | AM31: ='15'!F17 -> 20 | AN31: =DELIVERIES!AQ31 -> 8.75 | AO31: =AM31*AN31 -> 175 | AP31: ='15'!F18 -> 54 | AQ31: =DELIVERIES!AT31 -> 12.25 | AR31: =AP31*AQ31 -> 661.5 | AS31: ='15'!F21 -> 0 | AT31: =DELIVERIES!AW31 -> 7.9166667 | AU31: =AS31*AT31 -> 0 | AV31: ='15'!F22 -> 6 | AW31: =DELIVERIES!AZ31 -> 9.7916667 | AX31: =AV31*AW31 -> 58.75 | AY31: ='15'!F26 -> 0 | AZ31: =DELIVERIES!BC31 -> 16.333333 | BA31: =AY31*AZ31 -> 0 | BB31: ='15'!F27 -> 0 | BC31: =DELIVERIES!BF31 -> 11.666667 | BD31: =BB31*BC31 -> 0 | BE31: ='15'!F28 -> 2 | BF31: =DELIVERIES!BI31 -> 20 | BG31: =BE31*BF31 -> 40 | BH31: ='15'!F23 -> 0 | BI31: =DELIVERIES!BL31 -> 23 | BJ31: =BH31*BI31 -> 0 | BK31: ='15'!F25 -> 0 | BL31: =DELIVERIES!BO31 -> 12.5 | BM31: =BK31*BL31 -> 0 | BN31: ='15'!F24 -> 3 | BO31: =DELIVERIES!BR31 -> 12.75 | BP31: =BN31*BO31 -> 38.25 | BQ31: ='15'!F19 -> 0 | BR31: =DELIVERIES!BU31 -> 30.25 | BS31: =BQ31*BR31 -> 0 | BT31: ='15'!F20 -> 0 | BU31: =DELIVERIES!BX31 -> 15.916667 | BV31: =BT31*BU31 -> 0 | BY31: =AO31+AR31+AU31+AX31+BA31+BD31+BG31+BJ31+BM31+BP31+BS31+BV31 -> 973.5 | CA31: =AK31+BY31 -> 12174 | CD31: =CA31-CC31 -> 12174
A32: 16 | B32: =GROSS!B32 -> 0 | C32: =DELIVERIES!C32 -> 30 | D32: =B32*C32 -> 0 | E32: ='16'!F7 -> 214 | F32: =DELIVERIES!F32 -> 35 | G32: =E32*F32 -> 7490 | H32: ='16'!F8 -> 6 | I32: =DELIVERIES!I32 -> 8.5 | J32: =H32*I32 -> 51 | K32: ='16'!F15 -> 20 | L32: =DELIVERIES!L32 -> 18 | M32: =K32*L32 -> 360 | N32: ='16'!F9 -> 80 | O32: =DELIVERIES!O32 -> 7 | P32: =N32*O32 -> 560 | Q32: ='16'!F10 -> 0 | R32: =DELIVERIES!R32 -> 5.5 | S32: =Q32*R32 -> 0 | T32: ='16'!F11 -> 204 | U32: =DELIVERIES!U32 -> 8.5 | V32: =T32*U32 -> 1734 | W32: ='16'!F12 -> 24 | X32: =DELIVERIES!X32 -> 6 | Y32: =W32*X32 -> 144 | Z32: ='16'!F13 -> 25 | AA32: =DELIVERIES!AA32 -> 6 | AB32: =Z32*AA32 -> 150 | AC32: ='16'!F14 -> 7 | AD32: =DELIVERIES!AD32 -> 8 | AE32: =AC32*AD32 -> 56 | AG32: =AG7 -> 0 | AH32: =AF32*AG32 -> 0 | AK32: =D32+G32+J32+M32+P32+S32+V32+Y32+AB32+AE32+AH32 -> 10545 | AM32: ='16'!F17 -> 9 | AN32: =DELIVERIES!AQ32 -> 8.75 | AO32: =AM32*AN32 -> 78.75 | AP32: ='16'!F18 -> 47 | AQ32: =DELIVERIES!AT32 -> 12.25 | AR32: =AP32*AQ32 -> 575.75 | AS32: ='16'!F21 -> 0 | AT32: =DELIVERIES!AW32 -> 7.9166667 | AU32: =AS32*AT32 -> 0 | AV32: ='16'!F22 -> 6 | AW32: =DELIVERIES!AZ32 -> 9.7916667 | AX32: =AV32*AW32 -> 58.75 | AY32: ='16'!F26 -> 0 | AZ32: =DELIVERIES!BC32 -> 16.333333 | BA32: =AY32*AZ32 -> 0 | BB32: ='16'!F27 -> 0 | BC32: =DELIVERIES!BF32 -> 11.666667 | BD32: =BB32*BC32 -> 0 | BE32: ='16'!F28 -> 6 | BF32: =DELIVERIES!BI32 -> 20 | BG32: =BE32*BF32 -> 120 | BH32: ='16'!F23 -> 0 | BI32: =DELIVERIES!BL32 -> 23 | BJ32: =BH32*BI32 -> 0 | BK32: ='16'!F25 -> 0 | BL32: =DELIVERIES!BO32 -> 12.5 | BM32: =BK32*BL32 -> 0 | BN32: ='16'!F24 -> 4 | BO32: =DELIVERIES!BR32 -> 12.75 | BP32: =BN32*BO32 -> 51 | BQ32: ='16'!F19 -> 0 | BR32: =DELIVERIES!BU32 -> 30.25 | BS32: =BQ32*BR32 -> 0 | BT32: ='16'!F20 -> 0 | BU32: =DELIVERIES!BX32 -> 15.916667 | BV32: =BT32*BU32 -> 0 | BY32: =AO32+AR32+AU32+AX32+BA32+BD32+BG32+BJ32+BM32+BP32+BS32+BV32 -> 884.25 | CA32: =AK32+BY32 -> 11429.25 | CD32: =CA32-CC32 -> 11429.25
A33: 17 | B33: =GROSS!B33 -> 0 | C33: =DELIVERIES!C33 -> 30 | D33: =B33*C33 -> 0 | E33: ='17'!F7 -> 217 | F33: =DELIVERIES!F33 -> 35 | G33: =E33*F33 -> 7595 | H33: ='17'!F8 -> 15 | I33: =DELIVERIES!I33 -> 8.5 | J33: =H33*I33 -> 127.5 | K33: ='17'!F15 -> 10 | L33: =DELIVERIES!L33 -> 18 | M33: =K33*L33 -> 180 | N33: ='17'!F9 -> 110 | O33: =DELIVERIES!O33 -> 7 | P33: =N33*O33 -> 770 | Q33: ='17'!F10 -> 0 | R33: =DELIVERIES!R33 -> 5.5 | S33: =Q33*R33 -> 0 | T33: ='17'!F11 -> 200 | U33: =DELIVERIES!U33 -> 8.5 | V33: =T33*U33 -> 1700 | W33: ='17'!F12 -> 34 | X33: =DELIVERIES!X33 -> 6 | Y33: =W33*X33 -> 204 | Z33: ='17'!F13 -> 31 | AA33: =DELIVERIES!AA33 -> 6 | AB33: =Z33*AA33 -> 186 | AC33: ='17'!F14 -> 0 | AD33: =DELIVERIES!AD33 -> 8 | AE33: =AC33*AD33 -> 0 | AG33: =AG7 -> 0 | AH33: =AF33*AG33 -> 0 | AK33: =D33+G33+J33+M33+P33+S33+V33+Y33+AB33+AE33+AH33 -> 10762.5 | AM33: ='17'!F17 -> 14 | AN33: =DELIVERIES!AQ33 -> 8.75 | AO33: =AM33*AN33 -> 122.5 | AP33: ='17'!F18 -> 45 | AQ33: =DELIVERIES!AT33 -> 12.25 | AR33: =AP33*AQ33 -> 551.25 | AS33: ='17'!F21 -> 0 | AT33: =DELIVERIES!AW33 -> 7.9166667 | AU33: =AS33*AT33 -> 0 | AV33: ='17'!F22 -> 9 | AW33: =DELIVERIES!AZ33 -> 9.7916667 | AX33: =AV33*AW33 -> 88.125 | AY33: ='17'!F26 -> 0 | AZ33: =DELIVERIES!BC33 -> 16.333333 | BA33: =AY33*AZ33 -> 0 | BB33: ='17'!F27 -> 0 | BC33: =DELIVERIES!BF33 -> 11.666667 | BD33: =BB33*BC33 -> 0 | BE33: ='17'!F28 -> 4 | BF33: =DELIVERIES!BI33 -> 20 | BG33: =BE33*BF33 -> 80 | BH33: ='17'!F23 -> 0 | BI33: =DELIVERIES!BL33 -> 23 | BJ33: =BH33*BI33 -> 0 | BK33: ='17'!F25 -> 0 | BL33: =DELIVERIES!BO33 -> 12.5 | BM33: =BK33*BL33 -> 0 | BN33: ='17'!F24 -> 1 | BO33: =DELIVERIES!BR33 -> 12.75 | BP33: =BN33*BO33 -> 12.75 | BQ33: ='17'!F19 -> 0 | BR33: =DELIVERIES!BU33 -> 30.25 | BS33: =BQ33*BR33 -> 0 | BT33: ='17'!F20 -> 0 | BU33: =DELIVERIES!BX33 -> 15.916667 | BV33: =BT33*BU33 -> 0 | BY33: =AO33+AR33+AU33+AX33+BA33+BD33+BG33+BJ33+BM33+BP33+BS33+BV33 -> 854.625 | CA33: =AK33+BY33 -> 11617.125 | CD33: =CA33-CC33 -> 11617.125
A34: 18 | B34: =GROSS!B34 -> 0 | C34: =DELIVERIES!C34 -> 30 | D34: =B34*C34 -> 0 | E34: ='18'!F7 -> 195 | F34: =DELIVERIES!F34 -> 35 | G34: =E34*F34 -> 6825 | H34: ='18'!F8 -> 23 | I34: =DELIVERIES!I34 -> 8.5 | J34: =H34*I34 -> 195.5 | K34: ='18'!F15 -> 20 | L34: =DELIVERIES!L34 -> 18 | M34: =K34*L34 -> 360 | N34: ='18'!F9 -> 100 | O34: =DELIVERIES!O34 -> 7 | P34: =N34*O34 -> 700 | Q34: ='18'!F10 -> 0 | R34: =DELIVERIES!R34 -> 5.5 | S34: =Q34*R34 -> 0 | T34: ='18'!F11 -> 197 | U34: =DELIVERIES!U34 -> 8.5 | V34: =T34*U34 -> 1674.5 | W34: ='18'!F12 -> 50 | X34: =DELIVERIES!X34 -> 6 | Y34: =W34*X34 -> 300 | Z34: ='18'!F13 -> 47 | AA34: =DELIVERIES!AA34 -> 6 | AB34: =Z34*AA34 -> 282 | AC34: ='18'!F14 -> 0 | AD34: =DELIVERIES!AD34 -> 8 | AE34: =AC34*AD34 -> 0 | AG34: =AG7 -> 0 | AH34: =AF34*AG34 -> 0 | AK34: =D34+G34+J34+M34+P34+S34+V34+Y34+AB34+AE34+AH34 -> 10337 | AM34: ='18'!F17 -> 13 | AN34: =DELIVERIES!AQ34 -> 8.75 | AO34: =AM34*AN34 -> 113.75 | AP34: ='18'!F18 -> 28 | AQ34: =DELIVERIES!AT34 -> 12.25 | AR34: =AP34*AQ34 -> 343 | AS34: ='18'!F21 -> 0 | AT34: =DELIVERIES!AW34 -> 7.9166667 | AU34: =AS34*AT34 -> 0 | AV34: ='18'!F22 -> 7 | AW34: =DELIVERIES!AZ34 -> 9.7916667 | AX34: =AV34*AW34 -> 68.541667 | AY34: ='18'!F26 -> 0 | AZ34: =DELIVERIES!BC34 -> 16.333333 | BA34: =AY34*AZ34 -> 0 | BB34: ='18'!F27 -> 0 | BC34: =DELIVERIES!BF34 -> 11.666667 | BD34: =BB34*BC34 -> 0 | BE34: ='18'!F28 -> 2 | BF34: =DELIVERIES!BI34 -> 20 | BG34: =BE34*BF34 -> 40 | BH34: ='18'!F23 -> 0 | BI34: =DELIVERIES!BL34 -> 23 | BJ34: =BH34*BI34 -> 0 | BK34: ='18'!F25 -> 0 | BL34: =DELIVERIES!BO34 -> 12.5 | BM34: =BK34*BL34 -> 0 | BN34: ='18'!F24 -> 1 | BO34: =DELIVERIES!BR34 -> 12.75 | BP34: =BN34*BO34 -> 12.75 | BQ34: ='18'!F19 -> 0 | BR34: =DELIVERIES!BU34 -> 30.416667 | BS34: =BQ34*BR34 -> 0 | BT34: ='18'!F20 -> 0 | BU34: =DELIVERIES!BX34 -> 15.916667 | BV34: =BT34*BU34 -> 0 | BY34: =AO34+AR34+AU34+AX34+BA34+BD34+BG34+BJ34+BM34+BP34+BS34+BV34 -> 578.04167 | CA34: =AK34+BY34 -> 10915.042 | CD34: =CA34-CC34 -> 10915.042
A35: 19 | B35: =GROSS!B35 -> 0 | C35: =DELIVERIES!C35 -> 30 | D35: =B35*C35 -> 0 | E35: ='19'!F7 -> 236 | F35: =DELIVERIES!F35 -> 35 | G35: =E35*F35 -> 8260 | H35: ='19'!F8 -> 5 | I35: =DELIVERIES!I35 -> 8.5 | J35: =H35*I35 -> 42.5 | K35: ='19'!F15 -> 25 | L35: =DELIVERIES!L35 -> 18 | M35: =K35*L35 -> 450 | N35: ='19'!F9 -> 120 | O35: =DELIVERIES!O35 -> 7 | P35: =N35*O35 -> 840 | Q35: ='19'!F10 -> 0 | R35: =DELIVERIES!R35 -> 5.5 | S35: =Q35*R35 -> 0 | T35: ='19'!F11 -> 229 | U35: =DELIVERIES!U35 -> 8.5 | V35: =T35*U35 -> 1946.5 | W35: ='19'!F12 -> 34 | X35: =DELIVERIES!X35 -> 6 | Y35: =W35*X35 -> 204 | Z35: ='19'!F13 -> 44 | AA35: =DELIVERIES!AA35 -> 6 | AB35: =Z35*AA35 -> 264 | AC35: ='19'!F14 -> 0 | AD35: =DELIVERIES!AD35 -> 8 | AE35: =AC35*AD35 -> 0 | AG35: =AG7 -> 0 | AH35: =AF35*AG35 -> 0 | AK35: =D35+G35+J35+M35+P35+S35+V35+Y35+AB35+AE35+AH35 -> 12007 | AM35: ='19'!F17 -> 21 | AN35: =DELIVERIES!AQ35 -> 8.75 | AO35: =AM35*AN35 -> 183.75 | AP35: ='19'!F18 -> 61 | AQ35: =DELIVERIES!AT35 -> 12.25 | AR35: =AP35*AQ35 -> 747.25 | AS35: ='19'!F21 -> 0 | AT35: =DELIVERIES!AW35 -> 7.9166667 | AU35: =AS35*AT35 -> 0 | AV35: ='19'!F22 -> 9 | AW35: =DELIVERIES!AZ35 -> 9.7916667 | AX35: =AV35*AW35 -> 88.125 | AY35: ='19'!F26 -> 0 | AZ35: =DELIVERIES!BC35 -> 16.333333 | BA35: =AY35*AZ35 -> 0 | BB35: ='19'!F27 -> 0 | BC35: =DELIVERIES!BF35 -> 11.666667 | BD35: =BB35*BC35 -> 0 | BE35: ='19'!F28 -> 1 | BF35: =DELIVERIES!BI35 -> 20 | BG35: =BE35*BF35 -> 20 | BH35: ='19'!F23 -> 0 | BI35: =DELIVERIES!BL35 -> 23 | BJ35: =BH35*BI35 -> 0 | BK35: ='19'!F25 -> 0 | BL35: =DELIVERIES!BO35 -> 12.5 | BM35: =BK35*BL35 -> 0 | BN35: ='19'!F24 -> 4 | BO35: =DELIVERIES!BR35 -> 12.75 | BP35: =BN35*BO35 -> 51 | BQ35: ='19'!F19 -> 0 | BR35: =DELIVERIES!BU35 -> 30.416667 | BS35: =BQ35*BR35 -> 0 | BT35: ='19'!F20 -> 0 | BU35: =DELIVERIES!BX35 -> 15.916667 | BV35: =BT35*BU35 -> 0 | BY35: =AO35+AR35+AU35+AX35+BA35+BD35+BG35+BJ35+BM35+BP35+BS35+BV35 -> 1090.125 | CA35: =AK35+BY35 -> 13097.125 | CD35: =CA35-CC35 -> 13097.125
A36: 20 | B36: =GROSS!B36 -> 0 | C36: =DELIVERIES!C36 -> 30 | D36: =B36*C36 -> 0 | E36: ='20'!F7 -> 176 | F36: =DELIVERIES!F36 -> 35 | G36: =E36*F36 -> 6160 | H36: ='20'!F8 -> 5 | I36: =DELIVERIES!I36 -> 8.5 | J36: =H36*I36 -> 42.5 | K36: ='20'!F15 -> 13 | L36: =DELIVERIES!L36 -> 18 | M36: =K36*L36 -> 234 | N36: ='20'!F9 -> 90 | O36: =DELIVERIES!O36 -> 7 | P36: =N36*O36 -> 630 | Q36: ='20'!F10 -> 0 | R36: =DELIVERIES!R36 -> 5.5 | S36: =Q36*R36 -> 0 | T36: ='20'!F11 -> 185 | U36: =DELIVERIES!U36 -> 8.5 | V36: =T36*U36 -> 1572.5 | W36: ='20'!F12 -> 25 | X36: =DELIVERIES!X36 -> 6 | Y36: =W36*X36 -> 150 | Z36: ='20'!F13 -> 25 | AA36: =DELIVERIES!AA36 -> 6 | AB36: =Z36*AA36 -> 150 | AC36: ='20'!F14 -> 0 | AD36: =DELIVERIES!AD36 -> 8 | AE36: =AC36*AD36 -> 0 | AG36: =AG7 -> 0 | AH36: =AF36*AG36 -> 0 | AK36: =D36+G36+J36+M36+P36+S36+V36+Y36+AB36+AE36+AH36 -> 8939 | AM36: ='20'!F17 -> 9 | AN36: =DELIVERIES!AQ36 -> 8.75 | AO36: =AM36*AN36 -> 78.75 | AP36: ='20'!F18 -> 44 | AQ36: =DELIVERIES!AT36 -> 12.25 | AR36: =AP36*AQ36 -> 539 | AS36: ='20'!F21 -> 0 | AT36: =DELIVERIES!AW36 -> 7.9166667 | AU36: =AS36*AT36 -> 0 | AV36: ='20'!F22 -> 12 | AW36: =DELIVERIES!AZ36 -> 9.7916667 | AX36: =AV36*AW36 -> 117.5 | AY36: ='20'!F26 -> 0 | AZ36: =DELIVERIES!BC36 -> 16.333333 | BA36: =AY36*AZ36 -> 0 | BB36: ='20'!F27 -> 0 | BC36: =DELIVERIES!BF36 -> 11.666667 | BD36: =BB36*BC36 -> 0 | BE36: ='20'!F28 -> 2 | BF36: =DELIVERIES!BI36 -> 20 | BG36: =BE36*BF36 -> 40 | BH36: ='20'!F23 -> 0 | BI36: =DELIVERIES!BL36 -> 23 | BJ36: =BH36*BI36 -> 0 | BK36: ='20'!F25 -> 0 | BL36: =DELIVERIES!BO36 -> 12.5 | BM36: =BK36*BL36 -> 0 | BN36: ='20'!F24 -> 2 | BO36: =DELIVERIES!BR36 -> 12.75 | BP36: =BN36*BO36 -> 25.5 | BQ36: ='20'!F19 -> 0 | BR36: =DELIVERIES!BU36 -> 30.416667 | BS36: =BQ36*BR36 -> 0 | BT36: ='20'!F20 -> 0 | BU36: =DELIVERIES!BX36 -> 15.916667 | BV36: =BT36*BU36 -> 0 | BY36: =AO36+AR36+AU36+AX36+BA36+BD36+BG36+BJ36+BM36+BP36+BS36+BV36 -> 800.75 | CA36: =AK36+BY36 -> 9739.75 | CD36: =CA36-CC36 -> 9739.75
A37: 21 | B37: =GROSS!B37 -> 0 | C37: =DELIVERIES!C37 -> 30 | D37: =B37*C37 -> 0 | E37: ='21'!F7 -> 182 | F37: =DELIVERIES!F37 -> 35 | G37: =E37*F37 -> 6370 | H37: ='21'!F8 -> 15 | I37: =DELIVERIES!I37 -> 8.5 | J37: =H37*I37 -> 127.5 | K37: ='21'!F15 -> 22 | L37: =DELIVERIES!L37 -> 18 | M37: =K37*L37 -> 396 | N37: ='21'!F9 -> 120 | O37: =DELIVERIES!O37 -> 7 | P37: =N37*O37 -> 840 | Q37: ='21'!F10 -> 0 | R37: =DELIVERIES!R37 -> 5.5 | S37: =Q37*R37 -> 0 | T37: ='21'!F11 -> 169 | U37: =DELIVERIES!U37 -> 8.5 | V37: =T37*U37 -> 1436.5 | W37: ='21'!F12 -> 33 | X37: =DELIVERIES!X37 -> 6 | Y37: =W37*X37 -> 198 | Z37: ='21'!F13 -> 42 | AA37: =DELIVERIES!AA37 -> 6 | AB37: =Z37*AA37 -> 252 | AC37: ='21'!F14 -> 10 | AD37: =DELIVERIES!AD37 -> 8 | AE37: =AC37*AD37 -> 80 | AG37: =AG7 -> 0 | AH37: =AF37*AG37 -> 0 | AK37: =D37+G37+J37+M37+P37+S37+V37+Y37+AB37+AE37+AH37 -> 9700 | AM37: ='21'!F17 -> 6 | AN37: =DELIVERIES!AQ37 -> 8.75 | AO37: =AM37*AN37 -> 52.5 | AP37: ='21'!F18 -> 38 | AQ37: =DELIVERIES!AT37 -> 12.25 | AR37: =AP37*AQ37 -> 465.5 | AS37: ='21'!F21 -> 0 | AT37: =DELIVERIES!AW37 -> 7.9166667 | AU37: =AS37*AT37 -> 0 | AV37: ='21'!F22 -> 8 | AW37: =DELIVERIES!AZ37 -> 9.7916667 | AX37: =AV37*AW37 -> 78.333333 | AY37: ='21'!F26 -> 0 | AZ37: =DELIVERIES!BC37 -> 16.333333 | BA37: =AY37*AZ37 -> 0 | BB37: ='21'!F27 -> 0 | BC37: =DELIVERIES!BF37 -> 11.666667 | BD37: =BB37*BC37 -> 0 | BE37: ='21'!F28 -> 3 | BF37: =DELIVERIES!BI37 -> 20 | BG37: =BE37*BF37 -> 60 | BH37: ='21'!F23 -> 0 | BI37: =DELIVERIES!BL37 -> 23 | BJ37: =BH37*BI37 -> 0 | BK37: ='21'!F25 -> 0 | BL37: =DELIVERIES!BO37 -> 12.5 | BM37: =BK37*BL37 -> 0 | BN37: ='21'!F24 -> 3 | BO37: =DELIVERIES!BR37 -> 12.75 | BP37: =BN37*BO37 -> 38.25 | BQ37: ='21'!F19 -> 0 | BR37: =DELIVERIES!BU37 -> 30.416667 | BS37: =BQ37*BR37 -> 0 | BT37: ='21'!F20 -> 0 | BU37: =DELIVERIES!BX37 -> 15.916667 | BV37: =BT37*BU37 -> 0 | BY37: =AO37+AR37+AU37+AX37+BA37+BD37+BG37+BJ37+BM37+BP37+BS37+BV37 -> 694.58333 | CA37: =AK37+BY37 -> 10394.583 | CD37: =CA37-CC37 -> 10394.583
A38: TOTAL | B38: =SUM(B31:B37) -> 0 | D38: =SUM(D31:D37) -> 0 | E38: =SUM(E31:E37) -> 1458 | G38: =SUM(G31:G37) -> 51030 | H38: =SUM(H31:H37) -> 83 | J38: =SUM(J31:J37) -> 705.5 | K38: =SUM(K31:K37) -> 120 | M38: =SUM(M31:M37) -> 2160 | N38: =SUM(N31:N37) -> 670 | P38: =SUM(P31:P37) -> 4690 | Q38: =SUM(Q31:Q37) -> 0 | S38: =SUM(S31:S37) -> 0 | T38: =SUM(T31:T37) -> 1379 | V38: =SUM(V31:V37) -> 11721.5 | W38: =SUM(W31:W37) -> 236 | Y38: =SUM(Y31:Y37) -> 1416 | Z38: =SUM(Z31:Z37) -> 256 | AB38: =SUM(AB31:AB37) -> 1536 | AC38: =SUM(AC31:AC37) -> 29 | AE38: =SUM(AE31:AE37) -> 232 | AF38: =SUM(AF31:AF37) -> 0 | AH38: =SUM(AH31:AH37) -> 0 | AK38: =SUM(AK31:AK37) -> 73491 | AM38: =SUM(AM31:AM37) -> 92 | AO38: =SUM(AO31:AO37) -> 805 | AP38: =SUM(AP31:AP37) -> 317 | AR38: =SUM(AR31:AR37) -> 3883.25 | AS38: =SUM(AS31:AS37) -> 0 | AU38: =SUM(AU31:AU37) -> 0 | AV38: =SUM(AV31:AV37) -> 57 | AX38: =SUM(AX31:AX37) -> 558.125 | AY38: =SUM(AY31:AY37) -> 0 | BA38: =SUM(BA31:BA37) -> 0 | BB38: =SUM(BB31:BB37) -> 0 | BD38: =SUM(BD31:BD37) -> 0 | BE38: =SUM(BE31:BE37) -> 20 | BG38: =SUM(BG31:BG37) -> 400 | BH38: =SUM(BH31:BH37) -> 0 | BJ38: =SUM(BJ31:BJ37) -> 0 | BK38: =SUM(BK31:BK37) -> 0 | BM38: =SUM(BM31:BM37) -> 0 | BN38: =SUM(BN31:BN37) -> 18 | BP38: =SUM(BP31:BP37) -> 229.5 | BQ38: =SUM(BQ31:BQ37) -> 0 | BS38: =SUM(BS31:BS37) -> 0 | BT38: =SUM(BT31:BT37) -> 0 | BV38: =SUM(BV31:BV37) -> 0 | BY38: =SUM(BY31:BY37) -> 5875.875 | CA38: =SUM(CA31:CA37) -> 79366.875 | CD38: =SUM(CD31:CD37) -> 79366.875
A41: WEEK- 4 | B41: =B5 -> PREMIUM - CUT | E41: SPECIAL CUT | H41: NGOHIONG | K41: =K29 -> Chicken Fillet | N41: NECK | Q41: SIOMAI | T41: RICE | W41: BOLA-BOLA | Z41: LUMPIA | AC41: ATSARA | AF41: =AF5 -> 0 | AI41: =AI5 -> SUBTOTAL | AM41: 8OZ | AP41: 12 OZ | AS41: WATER 350 ML | AV41: WATER 500 ML | AY41: PANALO | BB41: =BB29 -> swakto | BE41: Calamansi Juice | BH41: =BH29 -> GATORADE | BK41: TROPICANA | BN41: STING | BQ41: =BQ29 -> 1 LITER | BT41: =BT29 -> 1.5 L | BW41: SUBTOTAL FOR DRINKS | CA41: TOTAL
A42: DATE | B42: QTY | C42: UP | D42: AMOUNT | E42: QTY | F42: UP | G42: AMOUNT | H42: QTY | I42: UP | J42: AMOUNT | K42: QTY | L42: UP | M42: AMOUNT | N42: QTY | O42: UP | P42: AMOUNT | Q42: QTY | R42: UP | S42: AMOUNT | T42: QTY | U42: UP | V42: AMOUNT | W42: QTY | X42: UP | Y42: AMOUNT | Z42: QTY | AA42: UP | AB42: AMOUNT | AC42: QTY | AD42: UP | AE42: AMOUNT | AF42: QTY | AG42: UP | AH42: AMOUNT | AK42: AMOUNT | AM42: QTY | AN42: UP | AO42: AMOUNT | AP42: QTY | AQ42: UP | AR42: AMOUNT | AS42: QTY | AT42: UP | AU42: AMOUNT | AV42: QTY | AW42: UP | AX42: AMOUNT | AY42: QTY | AZ42: UP | BA42: AMOUNT | BB42: QTY | BC42: UP | BD42: AMOUNT | BE42: QTY | BF42: UP | BG42: AMOUNT | BH42: QTY | BI42: UP | BJ42: AMOUNT | BK42: QTY | BL42: UP | BM42: AMOUNT | BN42: QTY | BO42: UP | BP42: AMOUNT | BQ42: QTY | BR42: UP | BS42: AMOUNT | BT42: QTY | BU42: UP | BV42: AMOUNT | BY42: AMOUNT | CA42: AMOUNT
A43: 22 | B43: =GROSS!B43 -> 0 | C43: =DELIVERIES!C43 -> 30 | D43: =B43*C43 -> 0 | E43: ='22'!F7 -> 172 | F43: =DELIVERIES!F43 -> 35 | G43: =E43*F43 -> 6020 | H43: ='22'!F8 -> 7 | I43: =DELIVERIES!I43 -> 8.5 | J43: =H43*I43 -> 59.5 | K43: ='22'!F15 -> 15 | L43: =DELIVERIES!L43 -> 18 | M43: =K43*L43 -> 270 | N43: ='22'!F9 -> 100 | O43: =DELIVERIES!O43 -> 7 | P43: =N43*O43 -> 700 | Q43: ='22'!F10 -> 0 | R43: =DELIVERIES!R43 -> 5.5 | S43: =Q43*R43 -> 0 | T43: ='22'!F11 -> 192 | U43: =DELIVERIES!U43 -> 8.5 | V43: =T43*U43 -> 1632 | W43: ='22'!F12 -> 34 | X43: =DELIVERIES!X43 -> 6 | Y43: =W43*X43 -> 204 | Z43: ='22'!F13 -> 47 | AA43: =DELIVERIES!AA43 -> 6 | AB43: =Z43*AA43 -> 282 | AC43: ='22'!F14 -> 13 | AD43: =DELIVERIES!AD43 -> 8 | AE43: =AC43*AD43 -> 104 | AG43: =AG7 -> 0 | AH43: =AF43*AG43 -> 0 | AK43: =D43+G43+J43+M43+P43+S43+V43+Y43+AB43+AE43+AH43 -> 9271.5 | AM43: ='22'!F17 -> 10 | AN43: =DELIVERIES!AQ43 -> 8.75 | AO43: =AM43*AN43 -> 87.5 | AP43: ='22'!F18 -> 44 | AQ43: =DELIVERIES!AT43 -> 12.25 | AR43: =AP43*AQ43 -> 539 | AS43: ='22'!F21 -> 0 | AT43: =DELIVERIES!AW43 -> 7.7916667 | AU43: =AS43*AT43 -> 0 | AV43: ='22'!F22 -> 7 | AW43: =DELIVERIES!AZ43 -> 9.7916667 | AX43: =AV43*AW43 -> 68.541667 | AY43: ='22'!F26 -> 0 | AZ43: =DELIVERIES!BC43 -> 16.333333 | BA43: =AY43*AZ43 -> 0 | BB43: ='22'!F27 -> 0 | BC43: =DELIVERIES!BF43 -> 11.833333 | BD43: =BB43*BC43 -> 0 | BE43: ='22'!F28 -> 4 | BF43: =DELIVERIES!BI43 -> 20 | BG43: =BE43*BF43 -> 80 | BH43: ='22'!F23 -> 0 | BI43: =DELIVERIES!BL43 -> 23 | BJ43: =BH43*BI43 -> 0 | BK43: ='22'!F25 -> 0 | BL43: =DELIVERIES!BO43 -> 12.5 | BM43: =BK43*BL43 -> 0 | BN43: ='22'!F24 -> 4 | BO43: =DELIVERIES!BR43 -> 12.75 | BP43: =BN43*BO43 -> 51 | BQ43: ='22'!F19 -> 0 | BR43: =DELIVERIES!BU43 -> 30.416667 | BS43: =BQ43*BR43 -> 0 | BT43: ='22'!F20 -> 0 | BU43: =DELIVERIES!BX43 -> 15.916667 | BV43: =BT43*BU43 -> 0 | BY43: =AO43+AR43+AU43+AX43+BA43+BD43+BG43+BJ43+BM43+BP43+BS43+BV43 -> 826.04167 | CA43: =AK43+BY43 -> 10097.542 | CD43: =CA43-CC43 -> 10097.542
A44: 23 | B44: =GROSS!B44 -> 0 | C44: =DELIVERIES!C44 -> 30 | D44: =B44*C44 -> 0 | E44: ='23'!F7 -> 194 | F44: =DELIVERIES!F44 -> 35 | G44: =E44*F44 -> 6790 | H44: ='23'!F8 -> 14 | I44: =DELIVERIES!I44 -> 8.5 | J44: =H44*I44 -> 119 | K44: ='23'!F15 -> 11 | L44: =DELIVERIES!L44 -> 18 | M44: =K44*L44 -> 198 | N44: ='23'!F9 -> 109 | O44: =DELIVERIES!O44 -> 7 | P44: =N44*O44 -> 763 | Q44: ='23'!F10 -> 0 | R44: =DELIVERIES!R44 -> 5.5 | S44: =Q44*R44 -> 0 | T44: ='23'!F11 -> 190 | U44: =DELIVERIES!U44 -> 8.5 | V44: =T44*U44 -> 1615 | W44: ='23'!F12 -> 24 | X44: =DELIVERIES!X44 -> 6 | Y44: =W44*X44 -> 144 | Z44: ='23'!F13 -> 54 | AA44: =DELIVERIES!AA44 -> 6 | AB44: =Z44*AA44 -> 324 | AC44: ='23'!F14 -> 10 | AD44: =DELIVERIES!AD44 -> 8 | AE44: =AC44*AD44 -> 80 | AG44: =AG7 -> 0 | AH44: =AF44*AG44 -> 0 | AK44: =D44+G44+J44+M44+P44+S44+V44+Y44+AB44+AE44+AH44 -> 10033 | AM44: ='23'!F17 -> 12 | AN44: =DELIVERIES!AQ44 -> 8.75 | AO44: =AM44*AN44 -> 105 | AP44: ='23'!F18 -> 37 | AQ44: =DELIVERIES!AT44 -> 12.25 | AR44: =AP44*AQ44 -> 453.25 | AS44: ='23'!F21 -> 0 | AT44: =DELIVERIES!AW44 -> 7.7916667 | AU44: =AS44*AT44 -> 0 | AV44: ='23'!F22 -> 7 | AW44: =DELIVERIES!AZ44 -> 9.7916667 | AX44: =AV44*AW44 -> 68.541667 | AY44: ='23'!F26 -> 0 | AZ44: =DELIVERIES!BC44 -> 16.333333 | BA44: =AY44*AZ44 -> 0 | BB44: ='23'!F27 -> 0 | BC44: =DELIVERIES!BF44 -> 11.833333 | BD44: =BB44*BC44 -> 0 | BE44: ='23'!F28 -> 3 | BF44: =DELIVERIES!BI44 -> 20 | BG44: =BE44*BF44 -> 60 | BH44: ='23'!F23 -> 0 | BI44: =DELIVERIES!BL44 -> 23 | BJ44: =BH44*BI44 -> 0 | BK44: ='23'!F25 -> 0 | BL44: =DELIVERIES!BO44 -> 12.5 | BM44: =BK44*BL44 -> 0 | BN44: ='23'!F24 -> 2 | BO44: =DELIVERIES!BR44 -> 12.75 | BP44: =BN44*BO44 -> 25.5 | BQ44: ='23'!F19 -> 0 | BR44: =DELIVERIES!BU44 -> 30.416667 | BS44: =BQ44*BR44 -> 0 | BT44: ='23'!F20 -> 0 | BU44: =DELIVERIES!BX44 -> 15.916667 | BV44: =BT44*BU44 -> 0 | BY44: =AO44+AR44+AU44+AX44+BA44+BD44+BG44+BJ44+BM44+BP44+BS44+BV44 -> 712.29167 | CA44: =AK44+BY44 -> 10745.292 | CD44: =CA44-CC44 -> 10745.292
A45: 24 | B45: =GROSS!B45 -> 0 | C45: =DELIVERIES!C45 -> 30 | D45: =B45*C45 -> 0 | E45: ='24'!F7 -> 203 | F45: =DELIVERIES!F45 -> 35 | G45: =E45*F45 -> 7105 | H45: ='24'!F8 -> 6 | I45: =DELIVERIES!I45 -> 8.5 | J45: =H45*I45 -> 51 | K45: ='24'!F15 -> 30 | L45: =DELIVERIES!L45 -> 18 | M45: =K45*L45 -> 540 | N45: ='24'!F9 -> 111 | O45: =DELIVERIES!O45 -> 7 | P45: =N45*O45 -> 777 | Q45: ='24'!F10 -> 0 | R45: =DELIVERIES!R45 -> 5.5 | S45: =Q45*R45 -> 0 | T45: ='24'!F11 -> 202 | U45: =DELIVERIES!U45 -> 8.5 | V45: =T45*U45 -> 1717 | W45: ='24'!F12 -> 33 | X45: =DELIVERIES!X45 -> 6 | Y45: =W45*X45 -> 198 | Z45: ='24'!F13 -> 51 | AA45: =DELIVERIES!AA45 -> 6 | AB45: =Z45*AA45 -> 306 | AC45: ='24'!F14 -> 7 | AD45: =DELIVERIES!AD45 -> 8 | AE45: =AC45*AD45 -> 56 | AG45: =AG7 -> 0 | AH45: =AF45*AG45 -> 0 | AK45: =D45+G45+J45+M45+P45+S45+V45+Y45+AB45+AE45+AH45 -> 10750 | AM45: ='24'!F17 -> 16 | AN45: =DELIVERIES!AQ45 -> 8.75 | AO45: =AM45*AN45 -> 140 | AP45: ='24'!F18 -> 25 | AQ45: =DELIVERIES!AT45 -> 12.25 | AR45: =AP45*AQ45 -> 306.25 | AS45: ='24'!F21 -> 0 | AT45: =DELIVERIES!AW45 -> 7.7916667 | AU45: =AS45*AT45 -> 0 | AV45: ='24'!F22 -> 5 | AW45: =DELIVERIES!AZ45 -> 9.7916667 | AX45: =AV45*AW45 -> 48.958333 | AY45: ='24'!F26 -> 0 | AZ45: =DELIVERIES!BC45 -> 16.333333 | BA45: =AY45*AZ45 -> 0 | BB45: ='24'!F27 -> 0 | BC45: =DELIVERIES!BF45 -> 11.833333 | BD45: =BB45*BC45 -> 0 | BE45: ='24'!F28 -> 5 | BF45: =DELIVERIES!BI45 -> 20 | BG45: =BE45*BF45 -> 100 | BH45: ='24'!F23 -> 0 | BI45: =DELIVERIES!BL45 -> 23 | BJ45: =BH45*BI45 -> 0 | BK45: ='24'!F25 -> 0 | BL45: =DELIVERIES!BO45 -> 12.5 | BM45: =BK45*BL45 -> 0 | BN45: ='24'!F24 -> 1 | BO45: =DELIVERIES!BR45 -> 12.75 | BP45: =BN45*BO45 -> 12.75 | BQ45: ='24'!F19 -> 0 | BR45: =DELIVERIES!BU45 -> 30.416667 | BS45: =BQ45*BR45 -> 0 | BT45: ='24'!F20 -> 0 | BU45: =DELIVERIES!BX45 -> 15.916667 | BV45: =BT45*BU45 -> 0 | BY45: =AO45+AR45+AU45+AX45+BA45+BD45+BG45+BJ45+BM45+BP45+BS45+BV45 -> 607.95833 | CA45: =AK45+BY45 -> 11357.958 | CD45: =CA45-CC45 -> 11357.958
A46: 25 | B46: =GROSS!B46 -> 0 | C46: =DELIVERIES!C46 -> 30 | D46: =B46*C46 -> 0 | E46: ='25'!F7 -> 169 | F46: =DELIVERIES!F46 -> 35 | G46: =E46*F46 -> 5915 | H46: ='25'!F8 -> 10 | I46: =DELIVERIES!I46 -> 8.5 | J46: =H46*I46 -> 85 | K46: ='25'!F15 -> 13 | L46: =DELIVERIES!L46 -> 18 | M46: =K46*L46 -> 234 | N46: ='25'!F9 -> 110 | O46: =DELIVERIES!O46 -> 7 | P46: =N46*O46 -> 770 | Q46: ='25'!F10 -> 0 | R46: =DELIVERIES!R46 -> 5.5 | S46: =Q46*R46 -> 0 | T46: ='25'!F11 -> 186 | U46: =DELIVERIES!U46 -> 8.5 | V46: =T46*U46 -> 1581 | W46: ='25'!F12 -> 30 | X46: =DELIVERIES!X46 -> 6 | Y46: =W46*X46 -> 180 | Z46: ='25'!F13 -> 25 | AA46: =DELIVERIES!AA46 -> 6 | AB46: =Z46*AA46 -> 150 | AC46: ='25'!F14 -> 0 | AD46: =DELIVERIES!AD46 -> 8 | AE46: =AC46*AD46 -> 0 | AG46: =AG7 -> 0 | AH46: =AF46*AG46 -> 0 | AK46: =D46+G46+J46+M46+P46+S46+V46+Y46+AB46+AE46+AH46 -> 8915 | AM46: ='25'!F17 -> 17 | AN46: =DELIVERIES!AQ46 -> 8.75 | AO46: =AM46*AN46 -> 148.75 | AP46: ='25'!F18 -> 33 | AQ46: =DELIVERIES!AT46 -> 12.25 | AR46: =AP46*AQ46 -> 404.25 | AS46: ='25'!F21 -> 0 | AT46: =DELIVERIES!AW46 -> 7.7916667 | AU46: =AS46*AT46 -> 0 | AV46: ='25'!F22 -> 3 | AW46: =DELIVERIES!AZ46 -> 9.7916667 | AX46: =AV46*AW46 -> 29.375 | AY46: ='25'!F26 -> 0 | AZ46: =DELIVERIES!BC46 -> 16.333333 | BA46: =AY46*AZ46 -> 0 | BB46: ='25'!F27 -> 0 | BC46: =DELIVERIES!BF46 -> 11.833333 | BD46: =BB46*BC46 -> 0 | BE46: ='25'!F28 -> 3 | BF46: =DELIVERIES!BI46 -> 20 | BG46: =BE46*BF46 -> 60 | BH46: ='25'!F23 -> 0 | BI46: =DELIVERIES!BL46 -> 23 | BJ46: =BH46*BI46 -> 0 | BK46: ='25'!F25 -> 0 | BL46: =DELIVERIES!BO46 -> 12.5 | BM46: =BK46*BL46 -> 0 | BN46: ='25'!F24 -> 3 | BO46: =DELIVERIES!BR46 -> 12.75 | BP46: =BN46*BO46 -> 38.25 | BQ46: ='25'!F19 -> 0 | BR46: =DELIVERIES!BU46 -> 30.25 | BS46: =BQ46*BR46 -> 0 | BT46: ='25'!F20 -> 0 | BU46: =DELIVERIES!BX46 -> 15.916667 | BV46: =BT46*BU46 -> 0 | BY46: =AO46+AR46+AU46+AX46+BA46+BD46+BG46+BJ46+BM46+BP46+BS46+BV46 -> 680.625 | CA46: =AK46+BY46 -> 9595.625 | CD46: =CA46-CC46 -> 9595.625
A47: 26 | B47: =GROSS!B47 -> 0 | C47: =DELIVERIES!C47 -> 30 | D47: =B47*C47 -> 0 | E47: ='26'!F7 -> 211 | F47: =DELIVERIES!F47 -> 35 | G47: =E47*F47 -> 7385 | H47: ='26'!F8 -> 18 | I47: =DELIVERIES!I47 -> 8.5 | J47: =H47*I47 -> 153 | K47: ='26'!F15 -> 30 | L47: =DELIVERIES!L47 -> 18 | M47: =K47*L47 -> 540 | N47: ='26'!F9 -> 90 | O47: =DELIVERIES!O47 -> 7 | P47: =N47*O47 -> 630 | Q47: ='26'!F10 -> 0 | R47: =DELIVERIES!R47 -> 5.5 | S47: =Q47*R47 -> 0 | T47: ='26'!F11 -> 220 | U47: =DELIVERIES!U47 -> 8.5 | V47: =T47*U47 -> 1870 | W47: ='26'!F12 -> 58 | X47: =DELIVERIES!X47 -> 6 | Y47: =W47*X47 -> 348 | Z47: ='26'!F13 -> 36 | AA47: =DELIVERIES!AA47 -> 6 | AB47: =Z47*AA47 -> 216 | AC47: ='26'!F14 -> 0 | AD47: =DELIVERIES!AD47 -> 8 | AE47: =AC47*AD47 -> 0 | AG47: =AG7 -> 0 | AH47: =AF47*AG47 -> 0 | AK47: =D47+G47+J47+M47+P47+S47+V47+Y47+AB47+AE47+AH47 -> 11142 | AM47: ='26'!F17 -> 13 | AN47: =DELIVERIES!AQ47 -> 8.75 | AO47: =AM47*AN47 -> 113.75 | AP47: ='26'!F18 -> 64 | AQ47: =DELIVERIES!AT47 -> 12.25 | AR47: =AP47*AQ47 -> 784 | AS47: ='26'!F21 -> 0 | AT47: =DELIVERIES!AW47 -> 7.7916667 | AU47: =AS47*AT47 -> 0 | AV47: ='26'!F22 -> 6 | AW47: =DELIVERIES!AZ47 -> 9.7916667 | AX47: =AV47*AW47 -> 58.75 | AY47: ='26'!F26 -> 0 | AZ47: =DELIVERIES!BC47 -> 16.333333 | BA47: =AY47*AZ47 -> 0 | BB47: ='26'!F27 -> 0 | BC47: =DELIVERIES!BF47 -> 11.833333 | BD47: =BB47*BC47 -> 0 | BE47: ='26'!F28 -> 0 | BF47: =DELIVERIES!BI47 -> 20 | BG47: =BE47*BF47 -> 0 | BH47: ='26'!F23 -> 0 | BI47: =DELIVERIES!BL47 -> 23 | BJ47: =BH47*BI47 -> 0 | BK47: ='26'!F25 -> 0 | BL47: =DELIVERIES!BO47 -> 12.5 | BM47: =BK47*BL47 -> 0 | BN47: ='26'!F24 -> 6 | BO47: =DELIVERIES!BR47 -> 12.75 | BP47: =BN47*BO47 -> 76.5 | BQ47: ='26'!F19 -> 0 | BR47: =DELIVERIES!BU47 -> 30.25 | BS47: =BQ47*BR47 -> 0 | BT47: ='26'!F20 -> 0 | BU47: =DELIVERIES!BX47 -> 15.916667 | BV47: =BT47*BU47 -> 0 | BY47: =AO47+AR47+AU47+AX47+BA47+BD47+BG47+BJ47+BM47+BP47+BS47+BV47 -> 1033 | CA47: =AK47+BY47 -> 12175 | CD47: =CA47-CC47 -> 12175
A48: 27 | B48: =GROSS!B48 -> 0 | C48: =DELIVERIES!C48 -> 30 | D48: =B48*C48 -> 0 | E48: ='27'!F7 -> 184 | F48: =DELIVERIES!F48 -> 35 | G48: =E48*F48 -> 6440 | H48: ='27'!F8 -> 10 | I48: =DELIVERIES!I48 -> 8.5 | J48: =H48*I48 -> 85 | K48: ='27'!F15 -> 9 | L48: =DELIVERIES!L48 -> 18 | M48: =K48*L48 -> 162 | N48: ='27'!F9 -> 90 | O48: =DELIVERIES!O48 -> 7 | P48: =N48*O48 -> 630 | Q48: ='27'!F10 -> 0 | R48: =DELIVERIES!R48 -> 5.5 | S48: =Q48*R48 -> 0 | T48: ='27'!F11 -> 176 | U48: =DELIVERIES!U48 -> 8.5 | V48: =T48*U48 -> 1496 | W48: ='27'!F12 -> 22 | X48: =DELIVERIES!X48 -> 6 | Y48: =W48*X48 -> 132 | Z48: ='27'!F13 -> 31 | AA48: =DELIVERIES!AA48 -> 6 | AB48: =Z48*AA48 -> 186 | AC48: ='27'!F14 -> 9 | AD48: =DELIVERIES!AD48 -> 8 | AE48: =AC48*AD48 -> 72 | AG48: =AG7 -> 0 | AH48: =AF48*AG48 -> 0 | AK48: =D48+G48+J48+M48+P48+S48+V48+Y48+AB48+AE48+AH48 -> 9203 | AM48: ='27'!F17 -> 14 | AN48: =DELIVERIES!AQ48 -> 8.75 | AO48: =AM48*AN48 -> 122.5 | AP48: ='27'!F18 -> 42 | AQ48: =DELIVERIES!AT48 -> 12.25 | AR48: =AP48*AQ48 -> 514.5 | AS48: ='27'!F21 -> 0 | AT48: =DELIVERIES!AW48 -> 7.7916667 | AU48: =AS48*AT48 -> 0 | AV48: ='27'!F22 -> 12 | AW48: =DELIVERIES!AZ48 -> 9.7916667 | AX48: =AV48*AW48 -> 117.5 | AY48: ='27'!F26 -> 0 | AZ48: =DELIVERIES!BC48 -> 16.333333 | BA48: =AY48*AZ48 -> 0 | BB48: ='27'!F27 -> 0 | BC48: =DELIVERIES!BF48 -> 11.833333 | BD48: =BB48*BC48 -> 0 | BE48: ='27'!F28 -> 0 | BF48: =DELIVERIES!BI48 -> 20 | BG48: =BE48*BF48 -> 0 | BH48: ='27'!F23 -> 0 | BI48: =DELIVERIES!BL48 -> 23 | BJ48: =BH48*BI48 -> 0 | BK48: ='27'!F25 -> 0 | BL48: =DELIVERIES!BO48 -> 12.5 | BM48: =BK48*BL48 -> 0 | BN48: ='27'!F24 -> 0 | BO48: =DELIVERIES!BR48 -> 12.75 | BP48: =BN48*BO48 -> 0 | BQ48: ='27'!F19 -> 0 | BR48: =DELIVERIES!BU48 -> 30.25 | BS48: =BQ48*BR48 -> 0 | BT48: ='27'!F20 -> 0 | BU48: =DELIVERIES!BX48 -> 15.916667 | BV48: =BT48*BU48 -> 0 | BY48: =AO48+AR48+AU48+AX48+BA48+BD48+BG48+BJ48+BM48+BP48+BS48+BV48 -> 754.5 | CA48: =AK48+BY48 -> 9957.5 | CD48: =CA48-CC48 -> 9957.5
A49: 28 | B49: =GROSS!B49 -> 0 | C49: =DELIVERIES!C49 -> 30 | D49: =B49*C49 -> 0 | E49: ='28'!F7 -> 167 | F49: =DELIVERIES!F49 -> 35 | G49: =E49*F49 -> 5845 | H49: ='28'!F8 -> 15 | I49: =DELIVERIES!I49 -> 8.5 | J49: =H49*I49 -> 127.5 | K49: ='28'!F15 -> 9 | L49: =DELIVERIES!L49 -> 18 | M49: =K49*L49 -> 162 | N49: ='28'!F9 -> 110 | O49: =DELIVERIES!O49 -> 7 | P49: =N49*O49 -> 770 | Q49: ='28'!F10 -> 0 | R49: =DELIVERIES!R49 -> 5.5 | S49: =Q49*R49 -> 0 | T49: ='28'!F11 -> 176 | U49: =DELIVERIES!U49 -> 8.5 | V49: =T49*U49 -> 1496 | W49: ='28'!F12 -> 38 | X49: =DELIVERIES!X49 -> 6 | Y49: =W49*X49 -> 228 | Z49: ='28'!F13 -> 28 | AA49: =DELIVERIES!AA49 -> 6 | AB49: =Z49*AA49 -> 168 | AC49: ='28'!F14 -> 11 | AD49: =DELIVERIES!AD49 -> 8 | AE49: =AC49*AD49 -> 88 | AG49: =AG7 -> 0 | AH49: =AF49*AG49 -> 0 | AK49: =D49+G49+J49+M49+P49+S49+V49+Y49+AB49+AE49+AH49 -> 8884.5 | AM49: ='28'!F17 -> 13 | AN49: =DELIVERIES!AQ49 -> 8.75 | AO49: =AM49*AN49 -> 113.75 | AP49: ='28'!F18 -> 52 | AQ49: =DELIVERIES!AT49 -> 12.25 | AR49: =AP49*AQ49 -> 637 | AS49: ='28'!F21 -> 0 | AT49: =DELIVERIES!AW49 -> 7.7916667 | AU49: =AS49*AT49 -> 0 | AV49: ='28'!F22 -> 7 | AW49: =DELIVERIES!AZ49 -> 9.7916667 | AX49: =AV49*AW49 -> 68.541667 | AY49: ='28'!F26 -> 0 | AZ49: =DELIVERIES!BC49 -> 16.333333 | BA49: =AY49*AZ49 -> 0 | BB49: ='28'!F27 -> 0 | BC49: =DELIVERIES!BF49 -> 11.833333 | BD49: =BB49*BC49 -> 0 | BE49: ='28'!F28 -> 0 | BF49: =DELIVERIES!BI49 -> 20 | BG49: =BE49*BF49 -> 0 | BH49: ='28'!F23 -> 0 | BI49: =DELIVERIES!BL49 -> 23 | BJ49: =BH49*BI49 -> 0 | BK49: ='28'!F25 -> 0 | BL49: =DELIVERIES!BO49 -> 12.5 | BM49: =BK49*BL49 -> 0 | BN49: ='28'!F24 -> 1 | BO49: =DELIVERIES!BR49 -> 12.75 | BP49: =BN49*BO49 -> 12.75 | BQ49: ='28'!F19 -> 0 | BR49: =DELIVERIES!BU49 -> 30.25 | BS49: =BQ49*BR49 -> 0 | BT49: ='28'!F20 -> 0 | BU49: =DELIVERIES!BX49 -> 15.916667 | BV49: =BT49*BU49 -> 0 | BY49: =AO49+AR49+AU49+AX49+BA49+BD49+BG49+BJ49+BM49+BP49+BS49+BV49 -> 832.04167 | CA49: =AK49+BY49 -> 9716.5417 | CD49: =CA49-CC49 -> 9716.5417
A50: 29 | B50: =GROSS!B50 -> 0 | C50: =DELIVERIES!C50 -> 30 | D50: =B50*C50 -> 0 | E50: ='29'!F7 -> 118 | F50: =DELIVERIES!F50 -> 35 | G50: =E50*F50 -> 4130 | H50: ='29'!F8 -> 18 | I50: =DELIVERIES!I50 -> 8.5 | J50: =H50*I50 -> 153 | K50: ='29'!F15 -> 13 | L50: =DELIVERIES!L50 -> 18 | M50: =K50*L50 -> 234 | N50: ='29'!F9 -> 106 | O50: =DELIVERIES!O50 -> 7 | P50: =N50*O50 -> 742 | Q50: ='29'!F10 -> 0 | R50: =DELIVERIES!R50 -> 5.5 | S50: =Q50*R50 -> 0 | T50: ='29'!F11 -> 182 | U50: =DELIVERIES!U50 -> 8.5 | V50: =T50*U50 -> 1547 | W50: ='29'!F12 -> 46 | X50: =DELIVERIES!X50 -> 6 | Y50: =W50*X50 -> 276 | Z50: ='29'!F13 -> 26 | AA50: =DELIVERIES!AA50 -> 6 | AB50: =Z50*AA50 -> 156 | AC50: ='29'!F14 -> 3 | AD50: =DELIVERIES!AD50 -> 8 | AE50: =AC50*AD50 -> 24 | AG50: =AG7 -> 0 | AH50: =AF50*AG50 -> 0 | AK50: =D50+G50+J50+M50+P50+S50+V50+Y50+AB50+AE50+AH50 -> 7262 | AM50: ='29'!F17 -> 13 | AN50: =DELIVERIES!AQ50 -> 8.75 | AO50: =AM50*AN50 -> 113.75 | AP50: ='29'!F18 -> 41 | AQ50: =DELIVERIES!AT50 -> 12.25 | AR50: =AP50*AQ50 -> 502.25 | AS50: ='29'!F21 -> 0 | AT50: =DELIVERIES!AW50 -> 7.7916667 | AU50: =AS50*AT50 -> 0 | AV50: ='29'!F22 -> 15 | AW50: =DELIVERIES!AZ50 -> 9.7916667 | AX50: =AV50*AW50 -> 146.875 | AY50: ='29'!F26 -> 0 | AZ50: =DELIVERIES!BC50 -> 16.333333 | BA50: =AY50*AZ50 -> 0 | BB50: ='29'!F27 -> 0 | BC50: =DELIVERIES!BF50 -> 11.833333 | BD50: =BB50*BC50 -> 0 | BE50: ='29'!F28 -> 0 | BF50: =DELIVERIES!BI50 -> 20 | BG50: =BE50*BF50 -> 0 | BH50: ='29'!F23 -> 0 | BI50: =DELIVERIES!BL50 -> 23 | BJ50: =BH50*BI50 -> 0 | BK50: ='29'!F25 -> 0 | BL50: =DELIVERIES!BO50 -> 12.5 | BM50: =BK50*BL50 -> 0 | BN50: ='29'!F24 -> 2 | BO50: =DELIVERIES!BR50 -> 12.75 | BP50: =BN50*BO50 -> 25.5 | BQ50: ='29'!F19 -> 0 | BR50: =DELIVERIES!BU50 -> 30.25 | BS50: =BQ50*BR50 -> 0 | BT50: ='29'!F20 -> 0 | BU50: =DELIVERIES!BX50 -> 15.916667 | BV50: =BT50*BU50 -> 0 | BY50: =AO50+AR50+AU50+AX50+BA50+BD50+BG50+BJ50+BM50+BP50+BS50+BV50 -> 788.375 | CA50: =AK50+BY50 -> 8050.375 | CD50: =CA50-CC50 -> 8050.375
A51: 30 | B51: =GROSS!B51 -> 0 | C51: =DELIVERIES!C51 -> 30 | D51: =B51*C51 -> 0 | E51: ='30'!F7 -> 182 | F51: =DELIVERIES!F51 -> 35 | G51: =E51*F51 -> 6370 | H51: ='30'!F8 -> 10 | I51: =DELIVERIES!I51 -> 8.5 | J51: =H51*I51 -> 85 | K51: ='30'!F15 -> 19 | L51: =DELIVERIES!L51 -> 18 | M51: =K51*L51 -> 342 | N51: ='30'!F9 -> 94 | O51: =DELIVERIES!O51 -> 7 | P51: =N51*O51 -> 658 | Q51: ='30'!F10 -> 0 | R51: =DELIVERIES!R51 -> 5.5 | S51: =Q51*R51 -> 0 | T51: ='30'!F11 -> 158 | U51: =DELIVERIES!U51 -> 8.5 | V51: =T51*U51 -> 1343 | W51: ='30'!F12 -> 29 | X51: =DELIVERIES!X51 -> 6 | Y51: =W51*X51 -> 174 | Z51: ='30'!F13 -> 36 | AA51: =DELIVERIES!AA51 -> 6 | AB51: =Z51*AA51 -> 216 | AC51: ='30'!F14 -> 3 | AD51: =DELIVERIES!AD51 -> 8 | AE51: =AC51*AD51 -> 24 | AG51: =AG7 -> 0 | AH51: =AF51*AG51 -> 0 | AK51: =D51+G51+J51+M51+P51+S51+V51+Y51+AB51+AE51+AH51 -> 9212 | AM51: ='30'!F17 -> 17 | AN51: =DELIVERIES!AQ51 -> 8.75 | AO51: =AM51*AN51 -> 148.75 | AP51: ='30'!F18 -> 34 | AQ51: =DELIVERIES!AT51 -> 12.25 | AR51: =AP51*AQ51 -> 416.5 | AS51: ='30'!F21 -> 0 | AT51: =DELIVERIES!AW51 -> 7.7916667 | AU51: =AS51*AT51 -> 0 | AV51: ='30'!F22 -> 16 | AW51: =DELIVERIES!AZ51 -> 9.7916667 | AX51: =AV51*AW51 -> 156.66667 | AY51: ='30'!F26 -> 0 | AZ51: =DELIVERIES!BC51 -> 16.333333 | BA51: =AY51*AZ51 -> 0 | BB51: ='30'!F27 -> 0 | BC51: =DELIVERIES!BF51 -> 11.833333 | BD51: =BB51*BC51 -> 0 | BE51: ='30'!F28 -> 0 | BF51: =DELIVERIES!BI51 -> 20 | BG51: =BE51*BF51 -> 0 | BH51: ='30'!F23 -> 0 | BI51: =DELIVERIES!BL51 -> 23 | BJ51: =BH51*BI51 -> 0 | BK51: ='30'!F25 -> 0 | BL51: =DELIVERIES!BO51 -> 12.5 | BM51: =BK51*BL51 -> 0 | BN51: ='30'!F24 -> 3 | BO51: =DELIVERIES!BR51 -> 12.75 | BP51: =BN51*BO51 -> 38.25 | BQ51: ='30'!F19 -> 0 | BR51: =DELIVERIES!BU51 -> 30.25 | BS51: =BQ51*BR51 -> 0 | BT51: ='30'!F20 -> 0 | BU51: =DELIVERIES!BX51 -> 15.916667 | BV51: =BT51*BU51 -> 0 | BY51: =AO51+AR51+AU51+AX51+BA51+BD51+BG51+BJ51+BM51+BP51+BS51+BV51 -> 760.16667 | CA51: =AK51+BY51 -> 9972.1667 | CD51: =CA51-CC51 -> 9972.1667
A52: 31 | B52: =GROSS!B52 -> 0 | C52: =DELIVERIES!C52 -> 30 | D52: =B52*C52 -> 0 | E52: ='31'!F7 -> 180 | F52: =DELIVERIES!F52 -> 35 | G52: =E52*F52 -> 6300 | H52: ='31'!F8 -> 7 | I52: =DELIVERIES!I52 -> 8.5 | J52: =H52*I52 -> 59.5 | K52: ='31'!F15 -> 9 | L52: =DELIVERIES!L52 -> 18 | M52: =K52*L52 -> 162 | N52: ='31'!F9 -> 126 | O52: =DELIVERIES!O52 -> 7 | P52: =N52*O52 -> 882 | Q52: ='31'!F10 -> 0 | R52: =DELIVERIES!R52 -> 5.5 | S52: =Q52*R52 -> 0 | T52: ='31'!F11 -> 173 | U52: =DELIVERIES!U52 -> 8.5 | V52: =T52*U52 -> 1470.5 | W52: ='31'!F12 -> 38 | X52: =DELIVERIES!X52 -> 6 | Y52: =W52*X52 -> 228 | Z52: ='31'!F13 -> 26 | AA52: =DELIVERIES!AA52 -> 6 | AB52: =Z52*AA52 -> 156 | AC52: ='31'!F14 -> 11 | AD52: =DELIVERIES!AD52 -> 8 | AE52: =AC52*AD52 -> 88 | AG52: =AG7 -> 0 | AH52: =AF52*AG52 -> 0 | AK52: =D52+G52+J52+M52+P52+S52+V52+Y52+AB52+AE52+AH52 -> 9346 | AM52: ='31'!F17 -> 14 | AN52: =DELIVERIES!AQ52 -> 8.75 | AO52: =AM52*AN52 -> 122.5 | AP52: ='31'!F18 -> 45 | AQ52: =DELIVERIES!AT52 -> 12.25 | AR52: =AP52*AQ52 -> 551.25 | AS52: ='31'!F21 -> 0 | AT52: =DELIVERIES!AW52 -> 7.7916667 | AU52: =AS52*AT52 -> 0 | AV52: ='31'!F22 -> 9 | AW52: =DELIVERIES!AZ52 -> 9.7916667 | AX52: =AV52*AW52 -> 88.125 | AY52: ='31'!F26 -> 0 | AZ52: =DELIVERIES!BC52 -> 16.333333 | BA52: =AY52*AZ52 -> 0 | BB52: ='31'!F27 -> 0 | BC52: =DELIVERIES!BF52 -> 11.833333 | BD52: =BB52*BC52 -> 0 | BE52: ='31'!F28 -> 0 | BF52: =DELIVERIES!BI52 -> 20 | BG52: =BE52*BF52 -> 0 | BH52: ='31'!F23 -> 0 | BI52: =DELIVERIES!BL52 -> 23 | BJ52: =BH52*BI52 -> 0 | BK52: ='31'!F25 -> 0 | BL52: =DELIVERIES!BO52 -> 12.5 | BM52: =BK52*BL52 -> 0 | BN52: ='31'!F24 -> 2 | BO52: =DELIVERIES!BR52 -> 12.75 | BP52: =BN52*BO52 -> 25.5 | BQ52: ='31'!F19 -> 0 | BR52: =DELIVERIES!BU52 -> 30.25 | BS52: =BQ52*BR52 -> 0 | BT52: ='31'!F20 -> 0 | BU52: =DELIVERIES!BX52 -> 15.916667 | BV52: =BT52*BU52 -> 0 | BY52: =AO52+AR52+AU52+AX52+BA52+BD52+BG52+BJ52+BM52+BP52+BS52+BV52 -> 787.375 | CA52: =AK52+BY52 -> 10133.375 | CD52: =CA52-CC52 -> 10133.375
A53: TOTAL | B53: =SUM(B43:B52) -> 0 | D53: =SUM(D43:D52) -> 0 | E53: =SUM(E43:E52) -> 1780 | G53: =SUM(G43:G52) -> 62300 | H53: =SUM(H43:H52) -> 115 | J53: =SUM(J43:J52) -> 977.5 | K53: =SUM(K43:K52) -> 158 | M53: =SUM(M43:M52) -> 2844 | N53: =SUM(N43:N52) -> 1046 | P53: =SUM(P43:P52) -> 7322 | Q53: =SUM(Q43:Q52) -> 0 | S53: =SUM(S43:S52) -> 0 | T53: =SUM(T43:T52) -> 1855 | V53: =SUM(V43:V52) -> 15767.5 | W53: =SUM(W43:W52) -> 352 | Y53: =SUM(Y43:Y52) -> 2112 | Z53: =SUM(Z43:Z52) -> 360 | AB53: =SUM(AB43:AB52) -> 2160 | AC53: =SUM(AC43:AC52) -> 67 | AE53: =SUM(AE43:AE52) -> 536 | AF53: =SUM(AF43:AF52) -> 0 | AH53: =SUM(AH43:AH52) -> 0 | AK53: =SUM(AK43:AK52) -> 94019 | AM53: =SUM(AM43:AM52) -> 139 | AO53: =SUM(AO43:AO52) -> 1216.25 | AP53: =SUM(AP43:AP52) -> 417 | AR53: =SUM(AR43:AR52) -> 5108.25 | AS53: =SUM(AS43:AS52) -> 0 | AU53: =SUM(AU43:AU52) -> 0 | AV53: =SUM(AV43:AV52) -> 87 | AX53: =SUM(AX43:AX52) -> 851.875 | AY53: =SUM(AY43:AY52) -> 0 | BA53: =SUM(BA43:BA52) -> 0 | BB53: =SUM(BB43:BB52) -> 0 | BD53: =SUM(BD43:BD52) -> 0 | BE53: =SUM(BE43:BE52) -> 15 | BG53: =SUM(BG43:BG52) -> 300 | BH53: =SUM(BH43:BH52) -> 0 | BJ53: =SUM(BJ43:BJ52) -> 0 | BK53: =SUM(BK43:BK52) -> 0 | BM53: =SUM(BM43:BM52) -> 0 | BN53: =SUM(BN43:BN52) -> 24 | BP53: =SUM(BP43:BP52) -> 306 | BQ53: =SUM(BQ43:BQ52) -> 0 | BS53: =SUM(BS43:BS52) -> 0 | BT53: =SUM(BT43:BT52) -> 0 | BV53: =SUM(BV43:BV52) -> 0 | BY53: =SUM(BY43:BY52) -> 7782.375 | CA53: =SUM(CA43:CA52) -> 101801.38 | CD53: =SUM(CD43:CD52) -> 101801.38
A55: TOTAL | B55: =B14+B26+B38+B53 -> 0 | D55: =D14+D26+D38+D53 -> 0 | E55: =E14+E26+E38+E53 -> 6012 | G55: =G14+G26+G38+G53 -> 210420 | H55: =H14+H26+H38+H53 -> 338 | J55: =J14+J26+J38+J53 -> 2873 | K55: =K14+K26+K38+K53 -> 478 | M55: =M14+M26+M38+M53 -> 8604 | N55: =N14+N26+N38+N53 -> 2782 | P55: =P14+P26+P38+P53 -> 19474 | Q55: =Q14+Q26+Q38+Q53 -> 0 | S55: =S14+S26+S38+S53 -> 0 | T55: =T14+T26+T38+T53 -> 5874 | V55: =V14+V26+V38+V53 -> 49929 | W55: =W14+W26+W38+W53 -> 1180 | Y55: =Y14+Y26+Y38+Y53 -> 7080 | Z55: =Z14+Z26+Z38+Z53 -> 1153 | AB55: =AB14+AB26+AB38+AB53 -> 6918 | AC55: =AC14+AC26+AC38+AC53 -> 257 | AE55: =AE14+AE26+AE38+AE53 -> 2056 | AF55: =AF14+AF26+AF38+AF53 -> 0 | AH55: =AH14+AH26+AH38+AH53 -> 0 | AK55: =AK14+AK26+AK38+AK53 -> 307354 | AM55: =AM14+AM26+AM38+AM53 -> 407 | AO55: =AO14+AO26+AO38+AO53 -> 3561.25 | AP55: =AP14+AP26+AP38+AP53 -> 1257 | AR55: =AR14+AR26+AR38+AR53 -> 15398.25 | AS55: =AS14+AS26+AS38+AS53 -> 0 | AU55: =AU14+AU26+AU38+AU53 -> 0 | AV55: =AV14+AV26+AV38+AV53 -> 229 | AX55: =AX14+AX26+AX38+AX53 -> 2242.2917 | AY55: =AY14+AY26+AY38+AY53 -> 0 | BA55: =BA14+BA26+BA38+BA53 -> 0 | BB55: =BB14+BB26+BB38+BB53 -> 107 | BD55: =BD14+BD26+BD38+BD53 -> 1232.3333 | BE55: =BE14+BE26+BE38+BE53 -> 96 | BG55: =BG14+BG26+BG38+BG53 -> 1920 | BH55: =BH14+BH26+BH38+BH53 -> 0 | BJ55: =BJ14+BJ26+BJ38+BJ53 -> 0 | BK55: =BK14+BK26+BK38+BK53 -> 0 | BM55: =BM14+BM26+BM38+BM53 -> 0 | BN55: =BN14+BN26+BN38+BN53 -> 93 | BP55: =BP14+BP26+BP38+BP53 -> 1185.75 | BQ55: =BQ14+BQ26+BQ38+BQ53 -> 0 | BS55: =BS14+BS26+BS38+BS53 -> 0 | BT55: =BT14+BT26+BT38+BT53 -> 0 | BV55: =BV14+BV26+BV38+BV53 -> 0 | BY55: =BY14+BY26+BY38+BY53 -> 25539.875 | CA55: =CA14+CA26+CA38+CA53 -> 332893.88 | CB55: =CA55/30 -> 11096.462 | CE55: =BY14+BY26+BY38+BY53 -> 25539.875

Sheet B.O
A1: CRISPY KING FOOD STATION : | E1: =GROSS!E1 -> BRANCH | BN1: DRINKS
A2: Daily Monitoring of COGS
A3: For the Month of:
A5: WEEK- 1 | B5: PREMIUM - CUT | E5: ='1'!A7 -> SPECIAL CUT | H5: ='1'!A8 -> NGOHIONG | K5: ='1'!A15 -> Chicken Fillet | N5: NECK | Q5: SIOMAI | T5: RICE | W5: BOLA-BOLA | Z5: LUMPIA | AC5: ATSARA | AI5: SUBTOTAL | AM5: ='1'!A17 -> 8 oz | AP5: 12 OZ | AS5: WATER 350 ML | AV5: WATER 500 ML | AY5: PANALO | BB5: swakto | BE5: Calamansi Juice | BH5: ='1'!A23 -> GATORADE | BK5: TROPICANA | BN5: STING | BQ5: ='1'!A19 -> 1 LITER | BT5: ='1'!A20 -> 1.5 L | BW5: SUBTOTAL FOR DRINKS | CA5: TOTAL | CC5: AUDIT GROSS | CD5: DIFFERENCE
A6: DATE | B6: QTY | C6: UP | D6: AMOUNT | E6: QTY | F6: UP | G6: AMOUNT | H6: QTY | I6: UP | J6: AMOUNT | K6: QTY | L6: UP | M6: AMOUNT | N6: QTY | O6: UP | P6: AMOUNT | Q6: QTY | R6: UP | S6: AMOUNT | T6: QTY | U6: UP | V6: AMOUNT | W6: QTY | X6: UP | Y6: AMOUNT | Z6: QTY | AA6: UP | AB6: AMOUNT | AC6: QTY | AD6: UP | AE6: AMOUNT | AF6: QTY | AG6: UP | AH6: AMOUNT | AK6: AMOUNT | AM6: QTY | AN6: UP | AO6: AMOUNT | AP6: QTY | AQ6: UP | AR6: AMOUNT | AS6: QTY | AT6: UP | AU6: AMOUNT | AV6: QTY | AW6: UP | AX6: AMOUNT | AY6: QTY | AZ6: UP | BA6: AMOUNT | BB6: QTY | BC6: UP | BD6: AMOUNT | BE6: QTY | BF6: UP | BG6: AMOUNT | BH6: QTY | BI6: UP | BJ6: AMOUNT | BK6: QTY | BL6: UP | BM6: AMOUNT | BN6: QTY | BO6: UP | BP6: AMOUNT | BQ6: QTY | BR6: UP | BS6: AMOUNT | BT6: QTY | BU6: UP | BV6: AMOUNT | BY6: AMOUNT | CA6: AMOUNT
A7: 1 | B7: ='1'!D29 -> 0 | C7: =DELIVERIES!C7 -> 30 | D7: =B7*C7 -> 0 | E7: ='1'!D7 -> 0 | F7: =DELIVERIES!F7 -> 35 | G7: =E7*F7 -> 0 | H7: ='1'!D8 -> 0 | I7: =DELIVERIES!I7 -> 8.5 | J7: =H7*I7 -> 0 | K7: ='1'!D15 -> 0 | L7: =DELIVERIES!L7 -> 18 | M7: =K7*L7 -> 0 | N7: ='1'!D9 -> 0 | O7: =DELIVERIES!O7 -> 7 | P7: =N7*O7 -> 0 | Q7: ='1'!D10 -> 0 | R7: =DELIVERIES!R7 -> 5.5 | S7: =Q7*R7 -> 0 | T7: ='1'!D11 -> 0 | U7: =DELIVERIES!U7 -> 8.5 | V7: =T7*U7 -> 0 | W7: ='1'!D12 -> 0 | X7: =DELIVERIES!X7 -> 6 | Y7: =W7*X7 -> 0 | Z7: ='1'!D13 -> 0 | AA7: =DELIVERIES!AA7 -> 6 | AB7: =Z7*AA7 -> 0 | AC7: ='1'!D14 -> 0 | AD7: =DELIVERIES!AD7 -> 8 | AE7: =AC7*AD7 -> 0 | AH7: =AF7*AG7 -> 0 | AK7: =D7+G7+J7+M7+P7+S7+V7+Y7+AB7+AE7+AH7 -> 0 | AM7: ='1'!D17 -> 0 | AN7: =DELIVERIES!AQ7 -> 8.75 | AO7: =AM7*AN7 -> 0 | AP7: ='1'!D18 -> 0 | AQ7: =DELIVERIES!AT7 -> 12.25 | AR7: =AP7*AQ7 -> 0 | AS7: ='1'!D21 -> 0 | AT7: =DELIVERIES!AW7 -> 7.9166667 | AU7: =AS7*AT7 -> 0 | AV7: ='1'!D22 -> 0 | AW7: =DELIVERIES!AZ7 -> 9.7916667 | AX7: =AV7*AW7 -> 0 | AY7: ='1'!D26 -> 0 | AZ7: =DELIVERIES!BC7 -> 16.333333 | BA7: =AY7*AZ7 -> 0 | BB7: ='1'!D27 -> 0 | BC7: =DELIVERIES!BF7 -> 11.5 | BD7: =BB7*BC7 -> 0 | BE7: ='1'!D28 -> 0 | BF7: =DELIVERIES!BI31 -> 20 | BG7: =BE7*BF7 -> 0 | BH7: ='1'!D23 -> 0 | BI7: =DELIVERIES!BL7 -> 23 | BJ7: =BH7*BI7 -> 0 | BK7: ='1'!D25 -> 0 | BL7: =DELIVERIES!BO7 -> 12.5 | BM7: =BK7*BL7 -> 0 | BN7: ='1'!D24 -> 0 | BO7: =DELIVERIES!BR7 -> 12.75 | BP7: =BN7*BO7 -> 0 | BQ7: ='1'!D19 -> 0 | BR7: =DELIVERIES!BU7 -> 30.25 | BS7: =BQ7*BR7 -> 0 | BT7: ='1'!D20 -> 0 | BU7: =DELIVERIES!BX7 -> 15.916667 | BV7: =BT7*BU7 -> 0 | BY7: =AO7+AR7+AU7+AX7+BA7+BD7+BG7+BJ7+BM7+BP7+BS7+BV7 -> 0 | CA7: =BY7+AK7 -> 0 | CD7: =CA7-CC7 -> 0
A8: 2 | B8: ='2'!D29 -> 0 | C8: =DELIVERIES!C8 -> 30 | D8: =B8*C8 -> 0 | E8: ='2'!D7 -> 0 | F8: =DELIVERIES!F8 -> 35 | G8: =E8*F8 -> 0 | H8: ='2'!D8 -> 0 | I8: =DELIVERIES!I8 -> 8.5 | J8: =H8*I8 -> 0 | K8: ='2'!D15 -> 0 | L8: =DELIVERIES!L8 -> 18 | M8: =K8*L8 -> 0 | N8: ='2'!D9 -> 0 | O8: =DELIVERIES!O8 -> 7 | P8: =N8*O8 -> 0 | Q8: ='2'!D10 -> 0 | R8: =DELIVERIES!R8 -> 5.5 | S8: =Q8*R8 -> 0 | T8: ='2'!D11 -> 0 | U8: =DELIVERIES!U8 -> 8.5 | V8: =T8*U8 -> 0 | W8: ='2'!D12 -> 0 | X8: =DELIVERIES!X8 -> 6 | Y8: =W8*X8 -> 0 | Z8: ='2'!D13 -> 0 | AA8: =DELIVERIES!AA8 -> 6 | AB8: =Z8*AA8 -> 0 | AC8: ='2'!D14 -> 0 | AD8: =DELIVERIES!AD8 -> 8 | AE8: =AC8*AD8 -> 0 | AG8: =AG7 -> 0 | AH8: =AF8*AG8 -> 0 | AK8: =D8+G8+J8+M8+P8+S8+V8+Y8+AB8+AE8+AH8 -> 0 | AM8: ='2'!D17 -> 0 | AN8: =DELIVERIES!AQ8 -> 8.75 | AO8: =AM8*AN8 -> 0 | AP8: ='2'!D18 -> 0 | AQ8: =DELIVERIES!AT8 -> 12.25 | AR8: =AP8*AQ8 -> 0 | AS8: ='2'!D21 -> 0 | AT8: =DELIVERIES!AW8 -> 7.9166667 | AU8: =AS8*AT8 -> 0 | AV8: ='2'!D22 -> 0 | AW8: =DELIVERIES!AZ8 -> 9.7916667 | AX8: =AV8*AW8 -> 0 | AY8: ='2'!D26 -> 0 | AZ8: =DELIVERIES!BC8 -> 16.333333 | BA8: =AY8*AZ8 -> 0 | BB8: ='2'!D27 -> 0 | BC8: =DELIVERIES!BF8 -> 11.5 | BD8: =BB8*BC8 -> 0 | BE8: ='2'!D28 -> 0 | BF8: =DELIVERIES!BI32 -> 20 | BG8: =BE8*BF8 -> 0 | BH8: ='2'!D23 -> 0 | BI8: =DELIVERIES!BL8 -> 23 | BJ8: =BH8*BI8 -> 0 | BK8: ='2'!D25 -> 0 | BL8: =DELIVERIES!BO8 -> 12.5 | BM8: =BK8*BL8 -> 0 | BN8: ='2'!D24 -> 0 | BO8: =DELIVERIES!BR8 -> 12.75 | BP8: =BN8*BO8 -> 0 | BQ8: ='2'!D19 -> 0 | BR8: =DELIVERIES!BU8 -> 30.25 | BS8: =BQ8*BR8 -> 0 | BT8: ='2'!D20 -> 0 | BU8: =DELIVERIES!BX8 -> 15.916667 | BV8: =BT8*BU8 -> 0 | BY8: =AO8+AR8+AU8+AX8+BA8+BD8+BG8+BJ8+BM8+BP8+BS8+BV8 -> 0 | CA8: =BY8+AK8 -> 0 | CD8: =CA8-CC8 -> 0
A9: 3 | B9: ='3'!D29 -> 0 | C9: =DELIVERIES!C9 -> 30 | D9: =B9*C9 -> 0 | E9: ='3'!D7 -> 0 | F9: =DELIVERIES!F9 -> 35 | G9: =E9*F9 -> 0 | H9: ='3'!D8 -> 0 | I9: =DELIVERIES!I9 -> 8.5 | J9: =H9*I9 -> 0 | K9: ='3'!D15 -> 0 | L9: =DELIVERIES!L9 -> 18 | M9: =K9*L9 -> 0 | N9: ='3'!D9 -> 0 | O9: =DELIVERIES!O9 -> 7 | P9: =N9*O9 -> 0 | Q9: ='3'!D10 -> 0 | R9: =DELIVERIES!R9 -> 5.5 | S9: =Q9*R9 -> 0 | T9: ='3'!D11 -> 0 | U9: =DELIVERIES!U9 -> 8.5 | V9: =T9*U9 -> 0 | W9: ='3'!D12 -> 0 | X9: =DELIVERIES!X9 -> 6 | Y9: =W9*X9 -> 0 | Z9: ='3'!D13 -> 0 | AA9: =DELIVERIES!AA9 -> 6 | AB9: =Z9*AA9 -> 0 | AC9: ='3'!D14 -> 0 | AD9: =DELIVERIES!AD9 -> 8 | AE9: =AC9*AD9 -> 0 | AG9: =AG7 -> 0 | AH9: =AF9*AG9 -> 0 | AK9: =D9+G9+J9+M9+P9+S9+V9+Y9+AB9+AE9+AH9 -> 0 | AM9: ='3'!D17 -> 0 | AN9: =DELIVERIES!AQ9 -> 8.75 | AO9: =AM9*AN9 -> 0 | AP9: ='3'!D18 -> 0 | AQ9: =DELIVERIES!AT9 -> 12.25 | AR9: =AP9*AQ9 -> 0 | AS9: ='3'!D21 -> 0 | AT9: =DELIVERIES!AW9 -> 7.9166667 | AU9: =AS9*AT9 -> 0 | AV9: ='3'!D22 -> 0 | AW9: =DELIVERIES!AZ9 -> 9.7916667 | AX9: =AV9*AW9 -> 0 | AY9: ='3'!D26 -> 0 | AZ9: =DELIVERIES!BC9 -> 16.333333 | BA9: =AY9*AZ9 -> 0 | BB9: ='3'!D27 -> 0 | BC9: =DELIVERIES!BF9 -> 11.5 | BD9: =BB9*BC9 -> 0 | BE9: ='3'!D28 -> 0 | BF9: =DELIVERIES!BI33 -> 20 | BG9: =BE9*BF9 -> 0 | BH9: ='3'!D23 -> 0 | BI9: =DELIVERIES!BL9 -> 23 | BJ9: =BH9*BI9 -> 0 | BK9: ='3'!D25 -> 0 | BL9: =DELIVERIES!BO9 -> 12.5 | BM9: =BK9*BL9 -> 0 | BN9: ='3'!D24 -> 0 | BO9: =DELIVERIES!BR9 -> 12.75 | BP9: =BN9*BO9 -> 0 | BQ9: ='3'!D19 -> 0 | BR9: =DELIVERIES!BU9 -> 30.25 | BS9: =BQ9*BR9 -> 0 | BT9: ='3'!D20 -> 0 | BU9: =DELIVERIES!BX9 -> 15.916667 | BV9: =BT9*BU9 -> 0 | BY9: =AO9+AR9+AU9+AX9+BA9+BD9+BG9+BJ9+BM9+BP9+BS9+BV9 -> 0 | CA9: =BY9+AK9 -> 0 | CD9: =CA9-CC9 -> 0
A10: 4 | B10: ='4'!D29 -> 0 | C10: =DELIVERIES!C10 -> 30 | D10: =B10*C10 -> 0 | E10: ='4'!D7 -> 0 | F10: =DELIVERIES!F10 -> 35 | G10: =E10*F10 -> 0 | H10: ='4'!D8 -> 0 | I10: =DELIVERIES!I10 -> 8.5 | J10: =H10*I10 -> 0 | K10: ='4'!D15 -> 0 | L10: =DELIVERIES!L10 -> 18 | M10: =K10*L10 -> 0 | N10: ='4'!D9 -> 0 | O10: =DELIVERIES!O10 -> 7 | P10: =N10*O10 -> 0 | Q10: ='4'!D10 -> 0 | R10: =DELIVERIES!R10 -> 5.5 | S10: =Q10*R10 -> 0 | T10: ='4'!D11 -> 0 | U10: =DELIVERIES!U10 -> 8.5 | V10: =T10*U10 -> 0 | W10: ='4'!D12 -> 0 | X10: =DELIVERIES!X10 -> 6 | Y10: =W10*X10 -> 0 | Z10: ='4'!D13 -> 0 | AA10: =DELIVERIES!AA10 -> 6 | AB10: =Z10*AA10 -> 0 | AC10: ='4'!D14 -> 0 | AD10: =DELIVERIES!AD10 -> 8 | AE10: =AC10*AD10 -> 0 | AG10: =AG7 -> 0 | AH10: =AF10*AG10 -> 0 | AK10: =D10+G10+J10+M10+P10+S10+V10+Y10+AB10+AE10+AH10 -> 0 | AM10: ='4'!D17 -> 0 | AN10: =DELIVERIES!AQ10 -> 8.75 | AO10: =AM10*AN10 -> 0 | AP10: ='4'!D18 -> 0 | AQ10: =DELIVERIES!AT10 -> 12.25 | AR10: =AP10*AQ10 -> 0 | AS10: ='4'!D21 -> 0 | AT10: =DELIVERIES!AW10 -> 7.9166667 | AU10: =AS10*AT10 -> 0 | AV10: ='4'!D22 -> 0 | AW10: =DELIVERIES!AZ10 -> 9.7916667 | AX10: =AV10*AW10 -> 0 | AY10: ='4'!D26 -> 0 | AZ10: =DELIVERIES!BC10 -> 16.333333 | BA10: =AY10*AZ10 -> 0 | BB10: ='4'!D27 -> 0 | BC10: =DELIVERIES!BF10 -> 11.5 | BD10: =BB10*BC10 -> 0 | BE10: ='4'!D28 -> 0 | BF10: =DELIVERIES!BI34 -> 20 | BG10: =BE10*BF10 -> 0 | BH10: ='4'!D23 -> 0 | BI10: =DELIVERIES!BL10 -> 23 | BJ10: =BH10*BI10 -> 0 | BK10: ='4'!D25 -> 0 | BL10: =DELIVERIES!BO10 -> 12.5 | BM10: =BK10*BL10 -> 0 | BN10: ='4'!D24 -> 0 | BO10: =DELIVERIES!BR10 -> 12.75 | BP10: =BN10*BO10 -> 0 | BQ10: ='4'!D19 -> 0 | BR10: =DELIVERIES!BU10 -> 30.25 | BS10: =BQ10*BR10 -> 0 | BT10: ='4'!D20 -> 0 | BU10: =DELIVERIES!BX10 -> 15.916667 | BV10: =BT10*BU10 -> 0 | BY10: =AO10+AR10+AU10+AX10+BA10+BD10+BG10+BJ10+BM10+BP10+BS10+BV10 -> 0 | CA10: =BY10+AK10 -> 0 | CD10: =CA10-CC10 -> 0
A11: 5 | B11: ='5'!D29 -> 0 | C11: =DELIVERIES!C11 -> 30 | D11: =B11*C11 -> 0 | E11: ='5'!D7 -> 0 | F11: =DELIVERIES!F11 -> 35 | G11: =E11*F11 -> 0 | H11: ='5'!D8 -> 0 | I11: =DELIVERIES!I11 -> 8.5 | J11: =H11*I11 -> 0 | K11: ='5'!D15 -> 0 | L11: =DELIVERIES!L11 -> 18 | M11: =K11*L11 -> 0 | N11: ='5'!D9 -> 0 | O11: =DELIVERIES!O11 -> 7 | P11: =N11*O11 -> 0 | Q11: ='5'!D10 -> 0 | R11: =DELIVERIES!R11 -> 5.5 | S11: =Q11*R11 -> 0 | T11: ='5'!D11 -> 0 | U11: =DELIVERIES!U11 -> 8.5 | V11: =T11*U11 -> 0 | W11: ='5'!D12 -> 0 | X11: =DELIVERIES!X11 -> 6 | Y11: =W11*X11 -> 0 | Z11: ='5'!D13 -> 0 | AA11: =DELIVERIES!AA11 -> 6 | AB11: =Z11*AA11 -> 0 | AC11: ='5'!D14 -> 0 | AD11: =DELIVERIES!AD11 -> 8 | AE11: =AC11*AD11 -> 0 | AG11: =AG7 -> 0 | AH11: =AF11*AG11 -> 0 | AK11: =D11+G11+J11+M11+P11+S11+V11+Y11+AB11+AE11+AH11 -> 0 | AM11: ='5'!D17 -> 0 | AN11: =DELIVERIES!AQ11 -> 8.75 | AO11: =AM11*AN11 -> 0 | AP11: ='5'!D18 -> 0 | AQ11: =DELIVERIES!AT11 -> 12.25 | AR11: =AP11*AQ11 -> 0 | AS11: ='5'!D21 -> 0 | AT11: =DELIVERIES!AW11 -> 7.9166667 | AU11: =AS11*AT11 -> 0 | AV11: ='5'!D22 -> 0 | AW11: =DELIVERIES!AZ11 -> 9.7916667 | AX11: =AV11*AW11 -> 0 | AY11: ='5'!D26 -> 0 | AZ11: =DELIVERIES!BC11 -> 16.333333 | BA11: =AY11*AZ11 -> 0 | BB11: ='5'!D27 -> 0 | BC11: =DELIVERIES!BF11 -> 11.5 | BD11: =BB11*BC11 -> 0 | BE11: ='5'!D28 -> 0 | BF11: =DELIVERIES!BI35 -> 20 | BG11: =BE11*BF11 -> 0 | BH11: ='5'!D23 -> 0 | BI11: =DELIVERIES!BL11 -> 23 | BJ11: =BH11*BI11 -> 0 | BK11: ='5'!D25 -> 0 | BL11: =DELIVERIES!BO11 -> 12.5 | BM11: =BK11*BL11 -> 0 | BN11: ='5'!D24 -> 0 | BO11: =DELIVERIES!BR11 -> 12.75 | BP11: =BN11*BO11 -> 0 | BQ11: ='5'!D19 -> 0 | BR11: =DELIVERIES!BU11 -> 30.25 | BS11: =BQ11*BR11 -> 0 | BT11: ='5'!D20 -> 0 | BU11: =DELIVERIES!BX11 -> 15.916667 | BV11: =BT11*BU11 -> 0 | BY11: =AO11+AR11+AU11+AX11+BA11+BD11+BG11+BJ11+BM11+BP11+BS11+BV11 -> 0 | CA11: =BY11+AK11 -> 0 | CD11: =CA11-CC11 -> 0
A12: 6 | B12: ='6'!D29 -> 0 | C12: =DELIVERIES!C12 -> 30 | D12: =B12*C12 -> 0 | E12: ='6'!D7 -> 0 | F12: =DELIVERIES!F12 -> 35 | G12: =E12*F12 -> 0 | H12: ='6'!D8 -> 0 | I12: =DELIVERIES!I12 -> 8.5 | J12: =H12*I12 -> 0 | K12: ='6'!D15 -> 0 | L12: =DELIVERIES!L12 -> 18 | M12: =K12*L12 -> 0 | N12: ='6'!D9 -> 0 | O12: =DELIVERIES!O12 -> 7 | P12: =N12*O12 -> 0 | Q12: ='6'!D10 -> 0 | R12: =DELIVERIES!R12 -> 5.5 | S12: =Q12*R12 -> 0 | T12: ='6'!D11 -> 0 | U12: =DELIVERIES!U12 -> 8.5 | V12: =T12*U12 -> 0 | W12: ='6'!D12 -> 0 | X12: =DELIVERIES!X12 -> 6 | Y12: =W12*X12 -> 0 | Z12: ='6'!D13 -> 0 | AA12: =DELIVERIES!AA12 -> 6 | AB12: =Z12*AA12 -> 0 | AC12: ='6'!D14 -> 0 | AD12: =DELIVERIES!AD12 -> 8 | AE12: =AC12*AD12 -> 0 | AG12: =AG7 -> 0 | AH12: =AF12*AG12 -> 0 | AK12: =D12+G12+J12+M12+P12+S12+V12+Y12+AB12+AE12+AH12 -> 0 | AM12: ='6'!D17 -> 0 | AN12: =DELIVERIES!AQ12 -> 8.75 | AO12: =AM12*AN12 -> 0 | AP12: ='6'!D18 -> 0 | AQ12: =DELIVERIES!AT12 -> 12.25 | AR12: =AP12*AQ12 -> 0 | AS12: ='6'!D21 -> 0 | AT12: =DELIVERIES!AW12 -> 7.9166667 | AU12: =AS12*AT12 -> 0 | AV12: ='6'!D22 -> 0 | AW12: =DELIVERIES!AZ12 -> 9.7916667 | AX12: =AV12*AW12 -> 0 | AY12: ='6'!D26 -> 0 | AZ12: =DELIVERIES!BC12 -> 16.333333 | BA12: =AY12*AZ12 -> 0 | BB12: ='6'!D27 -> 0 | BC12: =DELIVERIES!BF12 -> 11.5 | BD12: =BB12*BC12 -> 0 | BE12: ='6'!D28 -> 0 | BF12: =DELIVERIES!BI36 -> 20 | BG12: =BE12*BF12 -> 0 | BH12: ='6'!D23 -> 0 | BI12: =DELIVERIES!BL12 -> 23 | BJ12: =BH12*BI12 -> 0 | BK12: ='6'!D25 -> 0 | BL12: =DELIVERIES!BO12 -> 12.5 | BM12: =BK12*BL12 -> 0 | BN12: ='6'!D24 -> 0 | BO12: =DELIVERIES!BR12 -> 12.75 | BP12: =BN12*BO12 -> 0 | BQ12: ='6'!D19 -> 0 | BR12: =DELIVERIES!BU12 -> 30.25 | BS12: =BQ12*BR12 -> 0 | BT12: ='6'!D20 -> 0 | BU12: =DELIVERIES!BX12 -> 15.916667 | BV12: =BT12*BU12 -> 0 | BY12: =AO12+AR12+AU12+AX12+BA12+BD12+BG12+BJ12+BM12+BP12+BS12+BV12 -> 0 | CA12: =BY12+AK12 -> 0 | CD12: =CA12-CC12 -> 0
A13: 7 | B13: ='7'!D29 -> 0 | C13: =DELIVERIES!C13 -> 30 | D13: =B13*C13 -> 0 | E13: ='7'!D7 -> 0 | F13: =DELIVERIES!F13 -> 35 | G13: =E13*F13 -> 0 | H13: ='7'!D8 -> 0 | I13: =DELIVERIES!I13 -> 8.5 | J13: =H13*I13 -> 0 | K13: ='7'!D15 -> 0 | L13: =DELIVERIES!L13 -> 18 | M13: =K13*L13 -> 0 | N13: ='7'!D9 -> 0 | O13: =DELIVERIES!O13 -> 7 | P13: =N13*O13 -> 0 | Q13: ='7'!D10 -> 0 | R13: =DELIVERIES!R13 -> 5.5 | S13: =Q13*R13 -> 0 | T13: ='7'!D11 -> 0 | U13: =DELIVERIES!U13 -> 8.5 | V13: =T13*U13 -> 0 | W13: ='7'!D12 -> 0 | X13: =DELIVERIES!X13 -> 6 | Y13: =W13*X13 -> 0 | Z13: ='7'!D13 -> 0 | AA13: =DELIVERIES!AA13 -> 6 | AB13: =Z13*AA13 -> 0 | AC13: ='7'!D14 -> 0 | AD13: =DELIVERIES!AD13 -> 8 | AE13: =AC13*AD13 -> 0 | AG13: =AG7 -> 0 | AH13: =AF13*AG13 -> 0 | AK13: =D13+G13+J13+M13+P13+S13+V13+Y13+AB13+AE13+AH13 -> 0 | AM13: ='7'!D17 -> 0 | AN13: =DELIVERIES!AQ13 -> 8.75 | AO13: =AM13*AN13 -> 0 | AP13: ='7'!D18 -> 0 | AQ13: =DELIVERIES!AT13 -> 12.25 | AR13: =AP13*AQ13 -> 0 | AS13: ='7'!D21 -> 0 | AT13: =DELIVERIES!AW13 -> 7.9166667 | AU13: =AS13*AT13 -> 0 | AV13: ='7'!D22 -> 0 | AW13: =DELIVERIES!AZ13 -> 9.7916667 | AX13: =AV13*AW13 -> 0 | AY13: ='7'!D26 -> 0 | AZ13: =DELIVERIES!BC13 -> 16.333333 | BA13: =AY13*AZ13 -> 0 | BB13: ='7'!D27 -> 0 | BC13: =DELIVERIES!BF13 -> 11.5 | BD13: =BB13*BC13 -> 0 | BE13: ='7'!D28 -> 0 | BF13: =DELIVERIES!BI37 -> 20 | BG13: =BE13*BF13 -> 0 | BH13: ='7'!D23 -> 0 | BI13: =DELIVERIES!BL13 -> 23 | BJ13: =BH13*BI13 -> 0 | BK13: ='7'!D25 -> 0 | BL13: =DELIVERIES!BO13 -> 12.5 | BM13: =BK13*BL13 -> 0 | BN13: ='7'!D24 -> 0 | BO13: =DELIVERIES!BR13 -> 12.75 | BP13: =BN13*BO13 -> 0 | BQ13: ='7'!D19 -> 0 | BR13: =DELIVERIES!BU13 -> 30.25 | BS13: =BQ13*BR13 -> 0 | BT13: ='7'!D20 -> 0 | BU13: =DELIVERIES!BX13 -> 15.916667 | BV13: =BT13*BU13 -> 0 | BY13: =AO13+AR13+AU13+AX13+BA13+BD13+BG13+BJ13+BM13+BP13+BS13+BV13 -> 0 | CA13: =BY13+AK13 -> 0 | CD13: =CA13-CC13 -> 0
A14: TOTAL | B14: =SUM(B7:B13) -> 0 | D14: =SUM(D7:D13) -> 0 | E14: =SUM(E7:E13) -> 0 | G14: =SUM(G7:G13) -> 0 | H14: =SUM(H7:H13) -> 0 | J14: =SUM(J7:J13) -> 0 | K14: =SUM(K7:K13) -> 0 | M14: =SUM(M7:M13) -> 0 | N14: =SUM(N7:N13) -> 0 | P14: =SUM(P7:P13) -> 0 | Q14: =SUM(Q7:Q13) -> 0 | S14: =SUM(S7:S13) -> 0 | T14: =SUM(T7:T13) -> 0 | V14: =SUM(V7:V13) -> 0 | W14: =SUM(W7:W13) -> 0 | Y14: =SUM(Y7:Y13) -> 0 | Z14: =SUM(Z7:Z13) -> 0 | AB14: =SUM(AB7:AB13) -> 0 | AC14: =SUM(AC7:AC13) -> 0 | AE14: =SUM(AE7:AE13) -> 0 | AF14: =SUM(AF7:AF13) -> 0 | AH14: =SUM(AH7:AH13) -> 0 | AK14: =SUM(AK7:AK13) -> 0 | AM14: =SUM(AM7:AM13) -> 0 | AO14: =SUM(AO7:AO13) -> 0 | AP14: =SUM(AP7:AP13) -> 0 | AR14: =SUM(AR7:AR13) -> 0 | AS14: =SUM(AS7:AS13) -> 0 | AU14: =SUM(AU7:AU13) -> 0 | AV14: =SUM(AV7:AV13) -> 0 | AX14: =SUM(AX7:AX13) -> 0 | AY14: =SUM(AY7:AY13) -> 0 | BA14: =SUM(BA7:BA13) -> 0 | BB14: =SUM(BB7:BB13) -> 0 | BD14: =SUM(BD7:BD13) -> 0 | BE14: =SUM(BE7:BE13) -> 0 | BG14: =SUM(BG7:BG13) -> 0 | BH14: =SUM(BH7:BH13) -> 0 | BJ14: =SUM(BJ7:BJ13) -> 0 | BK14: =SUM(BK7:BK13) -> 0 | BM14: =SUM(BM7:BM13) -> 0 | BN14: =SUM(BN7:BN13) -> 0 | BP14: =SUM(BP7:BP13) -> 0 | BQ14: =SUM(BQ7:BQ13) -> 0 | BS14: =SUM(BS7:BS13) -> 0 | BT14: =SUM(BT7:BT13) -> 0 | BV14: =SUM(BV7:BV13) -> 0 | BY14: =SUM(BY7:BY13) -> 0 | CA14: =SUM(CA7:CA13) -> 0 | CD14: =SUM(CD7:CD13) -> 0
A17: WEEK- 2 | B17: =B5 -> PREMIUM - CUT | E17: SPECIAL CUT | H17: NGOHIONG | K17: =K5 -> Chicken Fillet | N17: NECK | Q17: SIOMAI | T17: RICE | W17: BOLA-BOLA | Z17: LUMPIA | AC17: ATSARA | AF17: =AF5 -> 0 | AI17: =AI5 -> SUBTOTAL | AM17: 8OZ | AP17: 12 OZ | AS17: WATER 350 ML | AV17: WATER 500 ML | AY17: PANALO | BB17: =BB5 -> swakto | BE17: =BE5 -> Calamansi Juice | BH17: =BH5 -> GATORADE | BK17: TROPICANA | BN17: STING | BQ17: =BQ5 -> 1 LITER | BT17: =BT5 -> 1.5 L | BW17: SUBTOTAL FOR DRINKS | CA17: TOTAL
A18: DATE | B18: QTY | C18: UP | D18: AMOUNT | E18: QTY | F18: UP | G18: AMOUNT | H18: QTY | I18: UP | J18: AMOUNT | K18: QTY | L18: UP | M18: AMOUNT | N18: QTY | O18: UP | P18: AMOUNT | Q18: QTY | R18: UP | S18: AMOUNT | T18: QTY | U18: UP | V18: AMOUNT | W18: QTY | X18: UP | Y18: AMOUNT | Z18: QTY | AA18: UP | AB18: AMOUNT | AC18: QTY | AD18: UP | AE18: AMOUNT | AF18: QTY | AG18: UP | AH18: AMOUNT | AK18: AMOUNT | AM18: QTY | AN18: UP | AO18: AMOUNT | AP18: QTY | AQ18: UP | AR18: AMOUNT | AS18: QTY | AT18: UP | AU18: AMOUNT | AV18: QTY | AW18: UP | AX18: AMOUNT | AY18: QTY | AZ18: UP | BA18: AMOUNT | BB18: QTY | BC18: UP | BD18: AMOUNT | BE18: QTY | BF18: UP | BG18: AMOUNT | BH18: QTY | BI18: UP | BJ18: AMOUNT | BK18: QTY | BL18: UP | BM18: AMOUNT | BN18: QTY | BO18: UP | BP18: AMOUNT | BQ18: QTY | BR18: UP | BS18: AMOUNT | BT18: QTY | BU18: UP | BV18: AMOUNT | BY18: AMOUNT | CA18: AMOUNT
A19: 8 | B19: ='8'!D29 -> 0 | C19: =DELIVERIES!C19 -> 30 | D19: =B19*C19 -> 0 | E19: ='8'!D7 -> 0 | F19: =DELIVERIES!F19 -> 35 | G19: =E19*F19 -> 0 | H19: ='8'!D8 -> 0 | I19: =DELIVERIES!I19 -> 8.5 | J19: =H19*I19 -> 0 | K19: ='8'!D15 -> 0 | L19: =DELIVERIES!L19 -> 18 | M19: =K19*L19 -> 0 | N19: ='8'!D9 -> 0 | O19: =DELIVERIES!O19 -> 7 | P19: =N19*O19 -> 0 | Q19: ='8'!D10 -> 0 | R19: =DELIVERIES!R19 -> 5.5 | S19: =Q19*R19 -> 0 | T19: ='8'!D11 -> 0 | U19: =DELIVERIES!U19 -> 8.5 | V19: =T19*U19 -> 0 | W19: ='8'!D12 -> 0 | X19: =DELIVERIES!X19 -> 6 | Y19: =W19*X19 -> 0 | Z19: ='8'!D13 -> 0 | AA19: =DELIVERIES!AA19 -> 6 | AB19: =Z19*AA19 -> 0 | AC19: ='8'!D14 -> 0 | AD19: =DELIVERIES!AD19 -> 8 | AE19: =AC19*AD19 -> 0 | AG19: =AG7 -> 0 | AH19: =AF19*AG19 -> 0 | AK19: =AE19+AB19+Y19+V19+S19+P19+J19+G19 -> 0 | AM19: ='8'!D17 -> 0 | AN19: =DELIVERIES!AQ19 -> 8.75 | AO19: =AM19*AN19 -> 0 | AP19: ='8'!D18 -> 0 | AQ19: =DELIVERIES!AT19 -> 12.25 | AR19: =AP19*AQ19 -> 0 | AS19: ='8'!D21 -> 0 | AT19: =DELIVERIES!AZ19 -> 9.7916667 | AU19: =AS19*AT19 -> 0 | AV19: ='8'!D22 -> 0 | AW19: =DELIVERIES!AZ19 -> 9.7916667 | AX19: =AV19*AW19 -> 0 | AY19: ='8'!D26 -> 0 | AZ19: =DELIVERIES!BC19 -> 16.333333 | BA19: =AY19*AZ19 -> 0 | BB19: ='8'!D27 -> 0 | BC19: =DELIVERIES!BF19 -> 11.5 | BD19: =BB19*BC19 -> 0 | BE19: ='8'!D28 -> 0 | BF19: =DELIVERIES!BI43 -> 20 | BG19: =BE19*BF19 -> 0 | BH19: ='8'!D23 -> 0 | BI19: =DELIVERIES!BL19 -> 23 | BJ19: =BH19*BI19 -> 0 | BK19: ='8'!D25 -> 0 | BL19: =DELIVERIES!BO19 -> 12.5 | BM19: =BK19*BL19 -> 0 | BN19: ='8'!D24 -> 0 | BO19: =DELIVERIES!BR19 -> 12.75 | BP19: =BN19*BO19 -> 0 | BQ19: ='8'!D19 -> 0 | BR19: =DELIVERIES!BU19 -> 30.25 | BS19: =BQ19*BR19 -> 0 | BT19: ='8'!D20 -> 0 | BU19: =DELIVERIES!BX19 -> 15.916667 | BV19: =BT19*BU19 -> 0 | BY19: =AO19+AR19+AU19+AX19+BA19+BD19+BG19+BJ19+BM19+BP19+BS19+BV19 -> 0 | CA19: =AK19+BY19 -> 0 | CD19: =CA19-CC19 -> 0
A20: 9 | B20: ='9'!D29 -> 0 | C20: =DELIVERIES!C20 -> 30 | D20: =B20*C20 -> 0 | E20: ='9'!D7 -> 0 | F20: =DELIVERIES!F20 -> 35 | G20: =E20*F20 -> 0 | H20: ='9'!D8 -> 0 | I20: =DELIVERIES!I20 -> 8.5 | J20: =H20*I20 -> 0 | K20: ='9'!D15 -> 0 | L20: =DELIVERIES!L20 -> 18 | M20: =K20*L20 -> 0 | N20: ='9'!D9 -> 0 | O20: =DELIVERIES!O20 -> 7 | P20: =N20*O20 -> 0 | Q20: ='9'!D10 -> 0 | R20: =DELIVERIES!R20 -> 5.5 | S20: =Q20*R20 -> 0 | T20: ='9'!D11 -> 0 | U20: =DELIVERIES!U20 -> 8.5 | V20: =T20*U20 -> 0 | W20: ='9'!D12 -> 0 | X20: =DELIVERIES!X20 -> 6 | Y20: =W20*X20 -> 0 | Z20: ='9'!D13 -> 0 | AA20: =DELIVERIES!AA20 -> 6 | AB20: =Z20*AA20 -> 0 | AC20: ='9'!D14 -> 0 | AD20: =DELIVERIES!AD20 -> 8 | AE20: =AC20*AD20 -> 0 | AG20: =AG7 -> 0 | AH20: =AF20*AG20 -> 0 | AK20: =D20+G20+J20+M20+P20+S20+V20+Y20+AB20+AE20+AH20 -> 0 | AM20: ='9'!D17 -> 0 | AN20: =DELIVERIES!AQ20 -> 8.75 | AO20: =AM20*AN20 -> 0 | AP20: ='9'!D18 -> 0 | AQ20: =DELIVERIES!AT20 -> 12.25 | AR20: =AP20*AQ20 -> 0 | AS20: ='9'!D21 -> 0 | AT20: =DELIVERIES!AZ20 -> 9.7916667 | AU20: =AS20*AT20 -> 0 | AV20: ='9'!D22 -> 0 | AW20: =DELIVERIES!AZ20 -> 9.7916667 | AX20: =AV20*AW20 -> 0 | AY20: ='9'!D26 -> 0 | AZ20: =DELIVERIES!BC20 -> 16.333333 | BA20: =AY20*AZ20 -> 0 | BB20: ='9'!D27 -> 0 | BC20: =DELIVERIES!BF20 -> 11.5 | BD20: =BB20*BC20 -> 0 | BE20: ='9'!D28 -> 0 | BF20: =DELIVERIES!BI44 -> 20 | BG20: =BE20*BF20 -> 0 | BH20: ='9'!D23 -> 0 | BI20: =DELIVERIES!BL20 -> 23 | BJ20: =BH20*BI20 -> 0 | BK20: ='9'!D25 -> 0 | BL20: =DELIVERIES!BO20 -> 12.5 | BM20: =BK20*BL20 -> 0 | BN20: ='9'!D24 -> 0 | BO20: =DELIVERIES!BR20 -> 12.75 | BP20: =BN20*BO20 -> 0 | BQ20: ='9'!D19 -> 0 | BR20: =DELIVERIES!BU20 -> 30.25 | BS20: =BQ20*BR20 -> 0 | BT20: ='9'!D20 -> 0 | BU20: =DELIVERIES!BX20 -> 15.916667 | BV20: =BT20*BU20 -> 0 | BY20: =AO20+AR20+AU20+AX20+BA20+BD20+BG20+BJ20+BM20+BP20+BS20+BV20 -> 0 | CA20: =AK20+BY20 -> 0 | CD20: =CA20-CC20 -> 0
A21: 10 | B21: ='10'!D29 -> 0 | C21: =DELIVERIES!C21 -> 30 | D21: =B21*C21 -> 0 | E21: ='10'!D7 -> 0 | F21: =DELIVERIES!F21 -> 35 | G21: =E21*F21 -> 0 | H21: ='10'!D8 -> 0 | I21: =DELIVERIES!I21 -> 8.5 | J21: =H21*I21 -> 0 | K21: ='10'!D15 -> 0 | L21: =DELIVERIES!L21 -> 18 | M21: =K21*L21 -> 0 | N21: ='10'!D9 -> 0 | O21: =DELIVERIES!O21 -> 7 | P21: =N21*O21 -> 0 | Q21: ='10'!D10 -> 0 | R21: =DELIVERIES!R21 -> 5.5 | S21: =Q21*R21 -> 0 | T21: ='10'!D11 -> 0 | U21: =DELIVERIES!U21 -> 8.5 | V21: =T21*U21 -> 0 | W21: ='10'!D12 -> 0 | X21: =DELIVERIES!X21 -> 6 | Y21: =W21*X21 -> 0 | Z21: ='10'!D13 -> 0 | AA21: =DELIVERIES!AA21 -> 6 | AB21: =Z21*AA21 -> 0 | AC21: ='10'!D14 -> 0 | AD21: =DELIVERIES!AD21 -> 8 | AE21: =AC21*AD21 -> 0 | AG21: =AG7 -> 0 | AH21: =AF21*AG21 -> 0 | AK21: =D21+G21+J21+M21+P21+S21+V21+Y21+AB21+AE21+AH21 -> 0 | AM21: ='10'!D17 -> 0 | AN21: =DELIVERIES!AQ21 -> 8.75 | AO21: =AM21*AN21 -> 0 | AP21: ='10'!D18 -> 0 | AQ21: =DELIVERIES!AT21 -> 12.25 | AR21: =AP21*AQ21 -> 0 | AS21: ='10'!D21 -> 0 | AT21: =DELIVERIES!AZ21 -> 9.7916667 | AU21: =AS21*AT21 -> 0 | AV21: ='10'!D22 -> 0 | AW21: =DELIVERIES!AZ21 -> 9.7916667 | AX21: =AV21*AW21 -> 0 | AY21: ='10'!D26 -> 0 | AZ21: =DELIVERIES!BC21 -> 16.333333 | BA21: =AY21*AZ21 -> 0 | BB21: ='10'!D27 -> 0 | BC21: =DELIVERIES!BF21 -> 11.5 | BD21: =BB21*BC21 -> 0 | BE21: ='10'!D28 -> 0 | BF21: =DELIVERIES!BI45 -> 20 | BG21: =BE21*BF21 -> 0 | BH21: ='10'!D23 -> 0 | BI21: =DELIVERIES!BL21 -> 23 | BJ21: =BH21*BI21 -> 0 | BK21: ='10'!D25 -> 0 | BL21: =DELIVERIES!BO21 -> 12.5 | BM21: =BK21*BL21 -> 0 | BN21: ='10'!D24 -> 0 | BO21: =DELIVERIES!BR21 -> 12.75 | BP21: =BN21*BO21 -> 0 | BQ21: ='10'!D19 -> 0 | BR21: =DELIVERIES!BU21 -> 30.25 | BS21: =BQ21*BR21 -> 0 | BT21: ='10'!D20 -> 0 | BU21: =DELIVERIES!BX21 -> 15.916667 | BV21: =BT21*BU21 -> 0 | BY21: =AO21+AR21+AU21+AX21+BA21+BD21+BG21+BJ21+BM21+BP21+BS21+BV21 -> 0 | CA21: =AK21+BY21 -> 0 | CD21: =CA21-CC21 -> 0
A22: 11 | B22: ='11'!D29 -> 0 | C22: =DELIVERIES!C22 -> 30 | D22: =B22*C22 -> 0 | E22: ='11'!D7 -> 0 | F22: =DELIVERIES!F22 -> 35 | G22: =E22*F22 -> 0 | H22: ='11'!D8 -> 0 | I22: =DELIVERIES!I22 -> 8.5 | J22: =H22*I22 -> 0 | K22: ='11'!D15 -> 0 | L22: =DELIVERIES!L22 -> 18 | M22: =K22*L22 -> 0 | N22: ='11'!D9 -> 0 | O22: =DELIVERIES!O22 -> 7 | P22: =N22*O22 -> 0 | Q22: ='11'!D10 -> 0 | R22: =DELIVERIES!R22 -> 5.5 | S22: =Q22*R22 -> 0 | T22: ='11'!D11 -> 0 | U22: =DELIVERIES!U22 -> 8.5 | V22: =T22*U22 -> 0 | W22: ='11'!D12 -> 0 | X22: =DELIVERIES!X22 -> 6 | Y22: =W22*X22 -> 0 | Z22: ='11'!D13 -> 0 | AA22: =DELIVERIES!AA22 -> 6 | AB22: =Z22*AA22 -> 0 | AC22: ='11'!D14 -> 0 | AD22: =DELIVERIES!AD22 -> 8 | AE22: =AC22*AD22 -> 0 | AG22: =AG7 -> 0 | AH22: =AF22*AG22 -> 0 | AK22: =D22+G22+J22+M22+P22+S22+V22+Y22+AB22+AE22+AH22 -> 0 | AM22: ='11'!D17 -> 0 | AN22: =DELIVERIES!AQ22 -> 8.75 | AO22: =AM22*AN22 -> 0 | AP22: ='11'!D18 -> 0 | AQ22: =DELIVERIES!AT22 -> 12.25 | AR22: =AP22*AQ22 -> 0 | AS22: ='11'!D21 -> 0 | AT22: =DELIVERIES!AZ22 -> 9.7916667 | AU22: =AS22*AT22 -> 0 | AV22: ='11'!D22 -> 0 | AW22: =DELIVERIES!AZ22 -> 9.7916667 | AX22: =AV22*AW22 -> 0 | AY22: ='11'!D26 -> 0 | AZ22: =DELIVERIES!BC22 -> 16.333333 | BA22: =AY22*AZ22 -> 0 | BB22: ='11'!D27 -> 0 | BC22: =DELIVERIES!BF22 -> 11.5 | BD22: =BB22*BC22 -> 0 | BE22: ='11'!D28 -> 0 | BF22: =DELIVERIES!BI46 -> 20 | BG22: =BE22*BF22 -> 0 | BH22: ='11'!D23 -> 0 | BI22: =DELIVERIES!BL22 -> 23 | BJ22: =BH22*BI22 -> 0 | BK22: ='11'!D25 -> 0 | BL22: =DELIVERIES!BO22 -> 12.5 | BM22: =BK22*BL22 -> 0 | BN22: ='11'!D24 -> 0 | BO22: =DELIVERIES!BR22 -> 12.75 | BP22: =BN22*BO22 -> 0 | BQ22: ='11'!D19 -> 0 | BR22: =DELIVERIES!BU22 -> 30.25 | BS22: =BQ22*BR22 -> 0 | BT22: ='11'!D20 -> 0 | BU22: =DELIVERIES!BX22 -> 15.916667 | BV22: =BT22*BU22 -> 0 | BY22: =AO22+AR22+AU22+AX22+BA22+BD22+BG22+BJ22+BM22+BP22+BS22+BV22 -> 0 | CA22: =AK22+BY22 -> 0 | CD22: =CA22-CC22 -> 0
A23: 12 | B23: ='12'!D29 -> 0 | C23: =DELIVERIES!C23 -> 30 | D23: =B23*C23 -> 0 | E23: ='12'!D7 -> 0 | F23: =DELIVERIES!F23 -> 35 | G23: =E23*F23 -> 0 | H23: ='12'!D8 -> 0 | I23: =DELIVERIES!I23 -> 8.5 | J23: =H23*I23 -> 0 | K23: ='12'!D15 -> 0 | L23: =DELIVERIES!L23 -> 18 | M23: =K23*L23 -> 0 | N23: ='12'!D9 -> 0 | O23: =DELIVERIES!O23 -> 7 | P23: =N23*O23 -> 0 | Q23: ='12'!D10 -> 0 | R23: =DELIVERIES!R23 -> 5.5 | S23: =Q23*R23 -> 0 | T23: ='12'!D11 -> 0 | U23: =DELIVERIES!U23 -> 8.5 | V23: =T23*U23 -> 0 | W23: ='12'!D12 -> 0 | X23: =DELIVERIES!X23 -> 6 | Y23: =W23*X23 -> 0 | Z23: ='12'!D13 -> 0 | AA23: =DELIVERIES!AA23 -> 6 | AB23: =Z23*AA23 -> 0 | AC23: ='12'!D14 -> 0 | AD23: =DELIVERIES!AD23 -> 8 | AE23: =AC23*AD23 -> 0 | AG23: =AG7 -> 0 | AH23: =AF23*AG23 -> 0 | AK23: =D23+G23+J23+M23+P23+S23+V23+Y23+AB23+AE23+AH23 -> 0 | AM23: ='12'!D17 -> 0 | AN23: =DELIVERIES!AQ23 -> 8.75 | AO23: =AM23*AN23 -> 0 | AP23: ='12'!D18 -> 0 | AQ23: =DELIVERIES!AT23 -> 12.25 | AR23: =AP23*AQ23 -> 0 | AS23: ='12'!D21 -> 0 | AT23: =DELIVERIES!AZ23 -> 9.7916667 | AU23: =AS23*AT23 -> 0 | AV23: ='12'!D22 -> 0 | AW23: =DELIVERIES!AZ23 -> 9.7916667 | AX23: =AV23*AW23 -> 0 | AY23: ='12'!D26 -> 0 | AZ23: =DELIVERIES!BC23 -> 16.333333 | BA23: =AY23*AZ23 -> 0 | BB23: ='12'!D27 -> 0 | BC23: =DELIVERIES!BF23 -> 11.666667 | BD23: =BB23*BC23 -> 0 | BE23: ='12'!D28 -> 0 | BF23: =DELIVERIES!BI47 -> 20 | BG23: =BE23*BF23 -> 0 | BH23: ='12'!D23 -> 0 | BI23: =DELIVERIES!BL23 -> 23 | BJ23: =BH23*BI23 -> 0 | BK23: ='12'!D25 -> 0 | BL23: =DELIVERIES!BO23 -> 12.5 | BM23: =BK23*BL23 -> 0 | BN23: ='12'!D24 -> 0 | BO23: =DELIVERIES!BR23 -> 12.75 | BP23: =BN23*BO23 -> 0 | BQ23: ='12'!D19 -> 0 | BR23: =DELIVERIES!BU23 -> 30.25 | BS23: =BQ23*BR23 -> 0 | BT23: ='12'!D20 -> 0 | BU23: =DELIVERIES!BX23 -> 15.916667 | BV23: =BT23*BU23 -> 0 | BY23: =AO23+AR23+AU23+AX23+BA23+BD23+BG23+BJ23+BM23+BP23+BS23+BV23 -> 0 | CA23: =AK23+BY23 -> 0 | CD23: =CA23-CC23 -> 0
A24: 13 | B24: ='13'!D29 -> 0 | C24: =DELIVERIES!C24 -> 30 | D24: =B24*C24 -> 0 | E24: ='13'!D7 -> 0 | F24: =DELIVERIES!F24 -> 35 | G24: =E24*F24 -> 0 | H24: ='13'!D8 -> 0 | I24: =DELIVERIES!I24 -> 8.5 | J24: =H24*I24 -> 0 | K24: ='13'!D15 -> 0 | L24: =DELIVERIES!L24 -> 18 | M24: =K24*L24 -> 0 | N24: ='13'!D9 -> 0 | O24: =DELIVERIES!O24 -> 7 | P24: =N24*O24 -> 0 | Q24: ='13'!D10 -> 0 | R24: =DELIVERIES!R24 -> 5.5 | S24: =Q24*R24 -> 0 | T24: ='13'!D11 -> 0 | U24: =DELIVERIES!U24 -> 8.5 | V24: =T24*U24 -> 0 | W24: ='13'!D12 -> 0 | X24: =DELIVERIES!X24 -> 6 | Y24: =W24*X24 -> 0 | Z24: ='13'!D13 -> 0 | AA24: =DELIVERIES!AA24 -> 6 | AB24: =Z24*AA24 -> 0 | AC24: ='13'!D14 -> 0 | AD24: =DELIVERIES!AD24 -> 8 | AE24: =AC24*AD24 -> 0 | AG24: =AG7 -> 0 | AH24: =AF24*AG24 -> 0 | AK24: =D24+G24+J24+M24+P24+S24+V24+Y24+AB24+AE24+AH24 -> 0 | AM24: ='13'!D17 -> 0 | AN24: =DELIVERIES!AQ24 -> 8.75 | AO24: =AM24*AN24 -> 0 | AP24: ='13'!D18 -> 0 | AQ24: =DELIVERIES!AT24 -> 12.25 | AR24: =AP24*AQ24 -> 0 | AS24: ='13'!D21 -> 0 | AT24: =DELIVERIES!AZ24 -> 9.7916667 | AU24: =AS24*AT24 -> 0 | AV24: ='13'!D22 -> 0 | AW24: =DELIVERIES!AZ24 -> 9.7916667 | AX24: =AV24*AW24 -> 0 | AY24: ='13'!D26 -> 0 | AZ24: =DELIVERIES!BC24 -> 16.333333 | BA24: =AY24*AZ24 -> 0 | BB24: ='13'!D27 -> 0 | BC24: =DELIVERIES!BF24 -> 11.666667 | BD24: =BB24*BC24 -> 0 | BE24: ='13'!D28 -> 0 | BF24: =DELIVERIES!BI48 -> 20 | BG24: =BE24*BF24 -> 0 | BH24: ='13'!D23 -> 0 | BI24: =DELIVERIES!BL24 -> 23 | BJ24: =BH24*BI24 -> 0 | BK24: ='13'!D25 -> 0 | BL24: =DELIVERIES!BO24 -> 12.5 | BM24: =BK24*BL24 -> 0 | BN24: ='13'!D24 -> 0 | BO24: =DELIVERIES!BR24 -> 12.75 | BP24: =BN24*BO24 -> 0 | BQ24: ='13'!D19 -> 0 | BR24: =DELIVERIES!BU24 -> 30.25 | BS24: =BQ24*BR24 -> 0 | BT24: ='13'!D20 -> 0 | BU24: =DELIVERIES!BX24 -> 15.916667 | BV24: =BT24*BU24 -> 0 | BY24: =AO24+AR24+AU24+AX24+BA24+BD24+BG24+BJ24+BM24+BP24+BS24+BV24 -> 0 | CA24: =AK24+BY24 -> 0 | CD24: =CA24-CC24 -> 0
A25: 14 | B25: ='14'!D29 -> 0 | C25: =DELIVERIES!C25 -> 30 | D25: =B25*C25 -> 0 | E25: ='14'!D7 -> 0 | F25: =DELIVERIES!F25 -> 35 | G25: =E25*F25 -> 0 | H25: ='14'!D8 -> 0 | I25: =DELIVERIES!I25 -> 8.5 | J25: =H25*I25 -> 0 | K25: ='14'!D15 -> 0 | L25: =DELIVERIES!L25 -> 18 | M25: =K25*L25 -> 0 | N25: ='14'!D9 -> 0 | O25: =DELIVERIES!O25 -> 7 | P25: =N25*O25 -> 0 | Q25: ='14'!D10 -> 0 | R25: =DELIVERIES!R25 -> 5.5 | S25: =Q25*R25 -> 0 | T25: ='14'!D11 -> 0 | U25: =DELIVERIES!U25 -> 8.5 | V25: =T25*U25 -> 0 | W25: ='14'!D12 -> 0 | X25: =DELIVERIES!X25 -> 6 | Y25: =W25*X25 -> 0 | Z25: ='14'!D13 -> 0 | AA25: =DELIVERIES!AA25 -> 6 | AB25: =Z25*AA25 -> 0 | AC25: ='14'!D14 -> 0 | AD25: =DELIVERIES!AD25 -> 8 | AE25: =AC25*AD25 -> 0 | AG25: =AG7 -> 0 | AH25: =AF25*AG25 -> 0 | AK25: =D25+G25+J25+M25+P25+S25+V25+Y25+AB25+AE25+AH25 -> 0 | AM25: ='14'!D17 -> 0 | AN25: =DELIVERIES!AQ25 -> 8.75 | AO25: =AM25*AN25 -> 0 | AP25: ='14'!D18 -> 0 | AQ25: =DELIVERIES!AT25 -> 12.25 | AR25: =AP25*AQ25 -> 0 | AS25: ='14'!D21 -> 0 | AT25: =DELIVERIES!AZ25 -> 9.7916667 | AU25: =AS25*AT25 -> 0 | AV25: ='14'!D22 -> 0 | AW25: =DELIVERIES!AZ25 -> 9.7916667 | AX25: =AV25*AW25 -> 0 | AY25: ='14'!D26 -> 0 | AZ25: =DELIVERIES!BC25 -> 16.333333 | BA25: =AY25*AZ25 -> 0 | BB25: ='14'!D27 -> 0 | BC25: =DELIVERIES!BF25 -> 11.666667 | BD25: =BB25*BC25 -> 0 | BE25: ='14'!D28 -> 0 | BF25: =DELIVERIES!BI49 -> 20 | BG25: =BE25*BF25 -> 0 | BH25: ='14'!D23 -> 0 | BI25: =DELIVERIES!BL25 -> 23 | BJ25: =BH25*BI25 -> 0 | BK25: ='14'!D25 -> 0 | BL25: =DELIVERIES!BO25 -> 12.5 | BM25: =BK25*BL25 -> 0 | BN25: ='14'!D24 -> 0 | BO25: =DELIVERIES!BR25 -> 12.75 | BP25: =BN25*BO25 -> 0 | BQ25: ='14'!D19 -> 0 | BR25: =DELIVERIES!BU25 -> 30.25 | BS25: =BQ25*BR25 -> 0 | BT25: ='14'!D20 -> 0 | BU25: =DELIVERIES!BX25 -> 15.916667 | BV25: =BT25*BU25 -> 0 | BY25: =AO25+AR25+AU25+AX25+BA25+BD25+BG25+BJ25+BM25+BP25+BS25+BV25 -> 0 | CA25: =AK25+BY25 -> 0 | CD25: =CA25-CC25 -> 0
A26: TOTAL | B26: =SUM(B19:B25) -> 0 | D26: =SUM(D19:D25) -> 0 | E26: =SUM(E19:E25) -> 0 | G26: =SUM(G19:G25) -> 0 | H26: =SUM(H19:H25) -> 0 | J26: =SUM(J19:J25) -> 0 | K26: =SUM(K19:K25) -> 0 | M26: =SUM(M19:M25) -> 0 | N26: =SUM(N19:N25) -> 0 | P26: =SUM(P19:P25) -> 0 | Q26: =SUM(Q19:Q25) -> 0 | S26: =SUM(S19:S25) -> 0 | T26: =SUM(T19:T25) -> 0 | V26: =SUM(V19:V25) -> 0 | W26: =SUM(W19:W25) -> 0 | Y26: =SUM(Y19:Y25) -> 0 | Z26: =SUM(Z19:Z25) -> 0 | AB26: =SUM(AB19:AB25) -> 0 | AC26: =SUM(AC19:AC25) -> 0 | AE26: =SUM(AE19:AE25) -> 0 | AF26: =SUM(AF19:AF25) -> 0 | AH26: =SUM(AH19:AH25) -> 0 | AK26: =SUM(AK19:AK25) -> 0 | AM26: =SUM(AM19:AM25) -> 0 | AO26: =SUM(AO19:AO25) -> 0 | AP26: =SUM(AP19:AP25) -> 0 | AR26: =SUM(AR19:AR25) -> 0 | AS26: =SUM(AS19:AS25) -> 0 | AU26: =SUM(AU19:AU25) -> 0 | AV26: =SUM(AV19:AV25) -> 0 | AX26: =SUM(AX19:AX25) -> 0 | AY26: =SUM(AY19:AY25) -> 0 | BA26: =SUM(BA19:BA25) -> 0 | BB26: =SUM(BB19:BB25) -> 0 | BD26: =SUM(BD19:BD25) -> 0 | BE26: =SUM(BE19:BE25) -> 0 | BG26: =SUM(BG19:BG25) -> 0 | BH26: =SUM(BH19:BH25) -> 0 | BJ26: =SUM(BJ19:BJ25) -> 0 | BK26: =SUM(BK19:BK25) -> 0 | BM26: =SUM(BM19:BM25) -> 0 | BN26: =SUM(BN19:BN25) -> 0 | BP26: =SUM(BP19:BP25) -> 0 | BQ26: =SUM(BQ19:BQ25) -> 0 | BS26: =SUM(BS19:BS25) -> 0 | BT26: =SUM(BT19:BT25) -> 0 | BV26: =SUM(BV19:BV25) -> 0 | BY26: =SUM(BY19:BY25) -> 0 | CA26: =SUM(CA19:CA25) -> 0 | CD26: =SUM(CD19:CD25) -> 0
A29: WEEK- 3 | B29: =B5 -> PREMIUM - CUT | E29: SPECIAL CUT | H29: NGOHIONG | K29: =K17 -> Chicken Fillet | N29: NECK | Q29: SIOMAI | T29: RICE | W29: BOLA-BOLA | Z29: LUMPIA | AC29: ATSARA | AF29: =AF5 -> 0 | AI29: =AI5 -> SUBTOTAL | AM29: 8OZ | AP29: 12 OZ | AS29: WATER 350 ML | AV29: WATER 500 ML | AY29: PANALO | BB29: =BB17 -> swakto | BE29: Calamansi Juice | BH29: =BH17 -> GATORADE | BK29: TROPICANA | BN29: STING | BQ29: =BQ17 -> 1 LITER | BT29: =BT17 -> 1.5 L | BW29: SUBTOTAL FOR DRINKS | CA29: TOTAL
A30: DATE | B30: QTY | C30: UP | D30: AMOUNT | E30: QTY | F30: UP | G30: AMOUNT | H30: QTY | I30: UP | J30: AMOUNT | K30: QTY | L30: UP | M30: AMOUNT | N30: QTY | O30: UP | P30: AMOUNT | Q30: QTY | R30: UP | S30: AMOUNT | T30: QTY | U30: UP | V30: AMOUNT | W30: QTY | X30: UP | Y30: AMOUNT | Z30: QTY | AA30: UP | AB30: AMOUNT | AC30: QTY | AD30: UP | AE30: AMOUNT | AF30: QTY | AG30: UP | AH30: AMOUNT | AK30: AMOUNT | AM30: QTY | AN30: UP | AO30: AMOUNT | AP30: QTY | AQ30: UP | AR30: AMOUNT | AS30: QTY | AT30: UP | AU30: AMOUNT | AV30: QTY | AW30: UP | AX30: AMOUNT | AY30: QTY | AZ30: UP | BA30: AMOUNT | BB30: QTY | BC30: UP | BD30: AMOUNT | BE30: QTY | BF30: UP | BG30: AMOUNT | BH30: QTY | BI30: UP | BJ30: AMOUNT | BK30: QTY | BL30: UP | BM30: AMOUNT | BN30: QTY | BO30: UP | BP30: AMOUNT | BQ30: QTY | BR30: UP | BS30: AMOUNT | BT30: QTY | BU30: UP | BV30: AMOUNT | BY30: AMOUNT | CA30: AMOUNT
A31: 15 | B31: ='15'!D29 -> 0 | C31: =DELIVERIES!C31 -> 30 | D31: =B31*C31 -> 0 | E31: ='15'!D7 -> 0 | F31: =DELIVERIES!F31 -> 35 | G31: =E31*F31 -> 0 | H31: ='15'!D8 -> 0 | I31: =DELIVERIES!I31 -> 8.5 | J31: =H31*I31 -> 0 | K31: ='15'!D15 -> 0 | L31: =DELIVERIES!L31 -> 18 | M31: =K31*L31 -> 0 | N31: ='15'!D9 -> 0 | O31: =DELIVERIES!O31 -> 7 | P31: =N31*O31 -> 0 | Q31: ='15'!D10 -> 0 | R31: =DELIVERIES!R31 -> 5.5 | S31: =Q31*R31 -> 0 | T31: ='15'!D11 -> 0 | U31: =DELIVERIES!U31 -> 8.5 | V31: =T31*U31 -> 0 | W31: ='15'!D12 -> 0 | X31: =DELIVERIES!X31 -> 6 | Y31: =W31*X31 -> 0 | Z31: ='15'!D13 -> 0 | AA31: =DELIVERIES!AA31 -> 6 | AB31: =Z31*AA31 -> 0 | AC31: ='15'!D14 -> 0 | AD31: =DELIVERIES!AD31 -> 8 | AE31: =AC31*AD31 -> 0 | AG31: =AG7 -> 0 | AH31: =AF31*AG31 -> 0 | AK31: =D31+G31+J31+M31+P31+S31+V31+Y31+AB31+AE31+AH31 -> 0 | AM31: ='15'!D17 -> 0 | AN31: =DELIVERIES!AQ31 -> 8.75 | AO31: =AM31*AN31 -> 0 | AP31: ='15'!D18 -> 0 | AQ31: =DELIVERIES!AT31 -> 12.25 | AR31: =AP31*AQ31 -> 0 | AS31: ='15'!D21 -> 0 | AT31: =DELIVERIES!AW31 -> 7.9166667 | AU31: =AS31*AT31 -> 0 | AV31: ='15'!D22 -> 0 | AW31: =DELIVERIES!AZ31 -> 9.7916667 | AX31: =AV31*AW31 -> 0 | AY31: ='15'!D26 -> 0 | AZ31: =DELIVERIES!BC31 -> 16.333333 | BA31: =AY31*AZ31 -> 0 | BB31: ='15'!D27 -> 0 | BC31: =DELIVERIES!BF31 -> 11.666667 | BD31: =BB31*BC31 -> 0 | BE31: ='15'!D28 -> 0 | BF31: =DELIVERIES!BI31 -> 20 | BG31: =BE31*BF31 -> 0 | BH31: ='15'!D23 -> 0 | BI31: =DELIVERIES!BL31 -> 23 | BJ31: =BH31*BI31 -> 0 | BK31: ='15'!D25 -> 0 | BL31: =DELIVERIES!BO31 -> 12.5 | BM31: =BK31*BL31 -> 0 | BN31: ='15'!D24 -> 0 | BO31: =DELIVERIES!BR31 -> 12.75 | BP31: =BN31*BO31 -> 0 | BQ31: ='15'!D19 -> 0 | BR31: =DELIVERIES!BU31 -> 30.25 | BS31: =BQ31*BR31 -> 0 | BT31: ='15'!D20 -> 0 | BU31: =DELIVERIES!BX31 -> 15.916667 | BV31: =BT31*BU31 -> 0 | BY31: =AO31+AR31+AU31+AX31+BA31+BD31+BG31+BJ31+BM31+BP31+BS31+BV31 -> 0 | CA31: =AK31+BY31 -> 0 | CD31: =CA31-CC31 -> 0
A32: 16 | B32: ='16'!D29 -> 0 | C32: =DELIVERIES!C32 -> 30 | D32: =B32*C32 -> 0 | E32: ='16'!D7 -> 0 | F32: =DELIVERIES!F32 -> 35 | G32: =E32*F32 -> 0 | H32: ='16'!D8 -> 0 | I32: =DELIVERIES!I32 -> 8.5 | J32: =H32*I32 -> 0 | K32: ='16'!D15 -> 0 | L32: =DELIVERIES!L32 -> 18 | M32: =K32*L32 -> 0 | N32: ='16'!D9 -> 0 | O32: =DELIVERIES!O32 -> 7 | P32: =N32*O32 -> 0 | Q32: ='16'!D10 -> 0 | R32: =DELIVERIES!R32 -> 5.5 | S32: =Q32*R32 -> 0 | T32: ='16'!D11 -> 0 | U32: =DELIVERIES!U32 -> 8.5 | V32: =T32*U32 -> 0 | W32: ='16'!D12 -> 0 | X32: =DELIVERIES!X32 -> 6 | Y32: =W32*X32 -> 0 | Z32: ='16'!D13 -> 0 | AA32: =DELIVERIES!AA32 -> 6 | AB32: =Z32*AA32 -> 0 | AC32: ='16'!D14 -> 0 | AD32: =DELIVERIES!AD32 -> 8 | AE32: =AC32*AD32 -> 0 | AG32: =AG7 -> 0 | AH32: =AF32*AG32 -> 0 | AK32: =D32+G32+J32+M32+P32+S32+V32+Y32+AB32+AE32+AH32 -> 0 | AM32: ='16'!D17 -> 0 | AN32: =DELIVERIES!AQ32 -> 8.75 | AO32: =AM32*AN32 -> 0 | AP32: ='16'!D18 -> 0 | AQ32: =DELIVERIES!AT32 -> 12.25 | AR32: =AP32*AQ32 -> 0 | AS32: ='16'!D21 -> 0 | AT32: =DELIVERIES!AW32 -> 7.9166667 | AU32: =AS32*AT32 -> 0 | AV32: ='16'!D22 -> 0 | AW32: =DELIVERIES!AZ32 -> 9.7916667 | AX32: =AV32*AW32 -> 0 | AY32: ='16'!D26 -> 0 | AZ32: =DELIVERIES!BC32 -> 16.333333 | BA32: =AY32*AZ32 -> 0 | BB32: ='16'!D27 -> 0 | BC32: =DELIVERIES!BF32 -> 11.666667 | BD32: =BB32*BC32 -> 0 | BE32: ='16'!D28 -> 0 | BF32: =DELIVERIES!BI32 -> 20 | BG32: =BE32*BF32 -> 0 | BH32: ='16'!D23 -> 0 | BI32: =DELIVERIES!BL32 -> 23 | BJ32: =BH32*BI32 -> 0 | BK32: ='16'!D25 -> 0 | BL32: =DELIVERIES!BO32 -> 12.5 | BM32: =BK32*BL32 -> 0 | BN32: ='16'!D24 -> 0 | BO32: =DELIVERIES!BR32 -> 12.75 | BP32: =BN32*BO32 -> 0 | BQ32: ='16'!D19 -> 0 | BR32: =DELIVERIES!BU32 -> 30.25 | BS32: =BQ32*BR32 -> 0 | BT32: ='16'!D20 -> 0 | BU32: =DELIVERIES!BX32 -> 15.916667 | BV32: =BT32*BU32 -> 0 | BY32: =AO32+AR32+AU32+AX32+BA32+BD32+BG32+BJ32+BM32+BP32+BS32+BV32 -> 0 | CA32: =AK32+BY32 -> 0 | CD32: =CA32-CC32 -> 0
A33: 17 | B33: ='17'!D29 -> 0 | C33: =DELIVERIES!C33 -> 30 | D33: =B33*C33 -> 0 | E33: ='17'!D7 -> 0 | F33: =DELIVERIES!F33 -> 35 | G33: =E33*F33 -> 0 | H33: ='17'!D8 -> 0 | I33: =DELIVERIES!I33 -> 8.5 | J33: =H33*I33 -> 0 | K33: ='17'!D15 -> 0 | L33: =DELIVERIES!L33 -> 18 | M33: =K33*L33 -> 0 | N33: ='17'!D9 -> 0 | O33: =DELIVERIES!O33 -> 7 | P33: =N33*O33 -> 0 | Q33: ='17'!D10 -> 0 | R33: =DELIVERIES!R33 -> 5.5 | S33: =Q33*R33 -> 0 | T33: ='17'!D11 -> 0 | U33: =DELIVERIES!U33 -> 8.5 | V33: =T33*U33 -> 0 | W33: ='17'!D12 -> 0 | X33: =DELIVERIES!X33 -> 6 | Y33: =W33*X33 -> 0 | Z33: ='17'!D13 -> 0 | AA33: =DELIVERIES!AA33 -> 6 | AB33: =Z33*AA33 -> 0 | AC33: ='17'!D14 -> 0 | AD33: =DELIVERIES!AD33 -> 8 | AE33: =AC33*AD33 -> 0 | AG33: =AG7 -> 0 | AH33: =AF33*AG33 -> 0 | AK33: =D33+G33+J33+M33+P33+S33+V33+Y33+AB33+AE33+AH33 -> 0 | AM33: ='17'!D17 -> 0 | AN33: =DELIVERIES!AQ33 -> 8.75 | AO33: =AM33*AN33 -> 0 | AP33: ='17'!D18 -> 0 | AQ33: =DELIVERIES!AT33 -> 12.25 | AR33: =AP33*AQ33 -> 0 | AS33: ='17'!D21 -> 0 | AT33: =DELIVERIES!AW33 -> 7.9166667 | AU33: =AS33*AT33 -> 0 | AV33: ='17'!D22 -> 0 | AW33: =DELIVERIES!AZ33 -> 9.7916667 | AX33: =AV33*AW33 -> 0 | AY33: ='17'!D26 -> 0 | AZ33: =DELIVERIES!BC33 -> 16.333333 | BA33: =AY33*AZ33 -> 0 | BB33: ='17'!D27 -> 0 | BC33: =DELIVERIES!BF33 -> 11.666667 | BD33: =BB33*BC33 -> 0 | BE33: ='17'!D28 -> 0 | BF33: =DELIVERIES!BI33 -> 20 | BG33: =BE33*BF33 -> 0 | BH33: ='17'!D23 -> 0 | BI33: =DELIVERIES!BL33 -> 23 | BJ33: =BH33*BI33 -> 0 | BK33: ='17'!D25 -> 0 | BL33: =DELIVERIES!BO33 -> 12.5 | BM33: =BK33*BL33 -> 0 | BN33: ='17'!D24 -> 0 | BO33: =DELIVERIES!BR33 -> 12.75 | BP33: =BN33*BO33 -> 0 | BQ33: ='17'!D19 -> 0 | BR33: =DELIVERIES!BU33 -> 30.25 | BS33: =BQ33*BR33 -> 0 | BT33: ='17'!D20 -> 0 | BU33: =DELIVERIES!BX33 -> 15.916667 | BV33: =BT33*BU33 -> 0 | BY33: =AO33+AR33+AU33+AX33+BA33+BD33+BG33+BJ33+BM33+BP33+BS33+BV33 -> 0 | CA33: =AK33+BY33 -> 0 | CD33: =CA33-CC33 -> 0
A34: 18 | B34: ='18'!D29 -> 0 | C34: =DELIVERIES!C34 -> 30 | D34: =B34*C34 -> 0 | E34: ='18'!D7 -> 0 | F34: =DELIVERIES!F34 -> 35 | G34: =E34*F34 -> 0 | H34: ='18'!D8 -> 0 | I34: =DELIVERIES!I34 -> 8.5 | J34: =H34*I34 -> 0 | K34: ='18'!D15 -> 0 | L34: =DELIVERIES!L34 -> 18 | M34: =K34*L34 -> 0 | N34: ='18'!D9 -> 0 | O34: =DELIVERIES!O34 -> 7 | P34: =N34*O34 -> 0 | Q34: ='18'!D10 -> 0 | R34: =DELIVERIES!R34 -> 5.5 | S34: =Q34*R34 -> 0 | T34: ='18'!D11 -> 0 | U34: =DELIVERIES!U34 -> 8.5 | V34: =T34*U34 -> 0 | W34: ='18'!D12 -> 0 | X34: =DELIVERIES!X34 -> 6 | Y34: =W34*X34 -> 0 | Z34: ='18'!D13 -> 0 | AA34: =DELIVERIES!AA34 -> 6 | AB34: =Z34*AA34 -> 0 | AC34: ='18'!D14 -> 0 | AD34: =DELIVERIES!AD34 -> 8 | AE34: =AC34*AD34 -> 0 | AG34: =AG7 -> 0 | AH34: =AF34*AG34 -> 0 | AK34: =D34+G34+J34+M34+P34+S34+V34+Y34+AB34+AE34+AH34 -> 0 | AM34: ='18'!D17 -> 0 | AN34: =DELIVERIES!AQ34 -> 8.75 | AO34: =AM34*AN34 -> 0 | AP34: ='18'!D18 -> 0 | AQ34: =DELIVERIES!AT34 -> 12.25 | AR34: =AP34*AQ34 -> 0 | AS34: ='18'!D21 -> 0 | AT34: =DELIVERIES!AW34 -> 7.9166667 | AU34: =AS34*AT34 -> 0 | AV34: ='18'!D22 -> 0 | AW34: =DELIVERIES!AZ34 -> 9.7916667 | AX34: =AV34*AW34 -> 0 | AY34: ='18'!D26 -> 0 | AZ34: =DELIVERIES!BC34 -> 16.333333 | BA34: =AY34*AZ34 -> 0 | BB34: ='18'!D27 -> 0 | BC34: =DELIVERIES!BF34 -> 11.666667 | BD34: =BB34*BC34 -> 0 | BE34: ='18'!D28 -> 0 | BF34: =DELIVERIES!BI34 -> 20 | BG34: =BE34*BF34 -> 0 | BH34: ='18'!D23 -> 0 | BI34: =DELIVERIES!BL34 -> 23 | BJ34: =BH34*BI34 -> 0 | BK34: ='18'!D25 -> 0 | BL34: =DELIVERIES!BO34 -> 12.5 | BM34: =BK34*BL34 -> 0 | BN34: ='18'!D24 -> 0 | BO34: =DELIVERIES!BR34 -> 12.75 | BP34: =BN34*BO34 -> 0 | BQ34: ='18'!D19 -> 0 | BR34: =DELIVERIES!BU34 -> 30.416667 | BS34: =BQ34*BR34 -> 0 | BT34: ='18'!D20 -> 0 | BU34: =DELIVERIES!BX34 -> 15.916667 | BV34: =BT34*BU34 -> 0 | BY34: =AO34+AR34+AU34+AX34+BA34+BD34+BG34+BJ34+BM34+BP34+BS34+BV34 -> 0 | CA34: =AK34+BY34 -> 0 | CD34: =CA34-CC34 -> 0
A35: 19 | B35: ='19'!D29 -> 0 | C35: =DELIVERIES!C35 -> 30 | D35: =B35*C35 -> 0 | E35: ='19'!D7 -> 0 | F35: =DELIVERIES!F35 -> 35 | G35: =E35*F35 -> 0 | H35: ='19'!D8 -> 0 | I35: =DELIVERIES!I35 -> 8.5 | J35: =H35*I35 -> 0 | K35: ='19'!D15 -> 0 | L35: =DELIVERIES!L35 -> 18 | M35: =K35*L35 -> 0 | N35: ='19'!D9 -> 0 | O35: =DELIVERIES!O35 -> 7 | P35: =N35*O35 -> 0 | Q35: ='19'!D10 -> 0 | R35: =DELIVERIES!R35 -> 5.5 | S35: =Q35*R35 -> 0 | T35: ='19'!D11 -> 0 | U35: =DELIVERIES!U35 -> 8.5 | V35: =T35*U35 -> 0 | W35: ='19'!D12 -> 0 | X35: =DELIVERIES!X35 -> 6 | Y35: =W35*X35 -> 0 | Z35: ='19'!D13 -> 0 | AA35: =DELIVERIES!AA35 -> 6 | AB35: =Z35*AA35 -> 0 | AC35: ='19'!D14 -> 0 | AD35: =DELIVERIES!AD35 -> 8 | AE35: =AC35*AD35 -> 0 | AG35: =AG7 -> 0 | AH35: =AF35*AG35 -> 0 | AK35: =D35+G35+J35+M35+P35+S35+V35+Y35+AB35+AE35+AH35 -> 0 | AM35: ='19'!D17 -> 0 | AN35: =DELIVERIES!AQ35 -> 8.75 | AO35: =AM35*AN35 -> 0 | AP35: ='19'!D18 -> 0 | AQ35: =DELIVERIES!AT35 -> 12.25 | AR35: =AP35*AQ35 -> 0 | AS35: ='19'!D21 -> 0 | AT35: =DELIVERIES!AW35 -> 7.9166667 | AU35: =AS35*AT35 -> 0 | AV35: ='19'!D22 -> 0 | AW35: =DELIVERIES!AZ35 -> 9.7916667 | AX35: =AV35*AW35 -> 0 | AY35: ='19'!D26 -> 0 | AZ35: =DELIVERIES!BC35 -> 16.333333 | BA35: =AY35*AZ35 -> 0 | BB35: ='19'!D27 -> 0 | BC35: =DELIVERIES!BF35 -> 11.666667 | BD35: =BB35*BC35 -> 0 | BE35: ='19'!D28 -> 0 | BF35: =DELIVERIES!BI35 -> 20 | BG35: =BE35*BF35 -> 0 | BH35: ='19'!D23 -> 0 | BI35: =DELIVERIES!BL35 -> 23 | BJ35: =BH35*BI35 -> 0 | BK35: ='19'!D25 -> 0 | BL35: =DELIVERIES!BO35 -> 12.5 | BM35: =BK35*BL35 -> 0 | BN35: ='19'!D24 -> 0 | BO35: =DELIVERIES!BR35 -> 12.75 | BP35: =BN35*BO35 -> 0 | BQ35: ='19'!D19 -> 0 | BR35: =DELIVERIES!BU35 -> 30.416667 | BS35: =BQ35*BR35 -> 0 | BT35: ='19'!D20 -> 0 | BU35: =DELIVERIES!BX35 -> 15.916667 | BV35: =BT35*BU35 -> 0 | BY35: =AO35+AR35+AU35+AX35+BA35+BD35+BG35+BJ35+BM35+BP35+BS35+BV35 -> 0 | CA35: =AK35+BY35 -> 0 | CD35: =CA35-CC35 -> 0
A36: 20 | B36: ='20'!D29 -> 0 | C36: =DELIVERIES!C36 -> 30 | D36: =B36*C36 -> 0 | E36: ='20'!D7 -> 0 | F36: =DELIVERIES!F36 -> 35 | G36: =E36*F36 -> 0 | H36: ='20'!D8 -> 0 | I36: =DELIVERIES!I36 -> 8.5 | J36: =H36*I36 -> 0 | K36: ='20'!D15 -> 0 | L36: =DELIVERIES!L36 -> 18 | M36: =K36*L36 -> 0 | N36: ='20'!D9 -> 0 | O36: =DELIVERIES!O36 -> 7 | P36: =N36*O36 -> 0 | Q36: ='20'!D10 -> 0 | R36: =DELIVERIES!R36 -> 5.5 | S36: =Q36*R36 -> 0 | T36: ='20'!D11 -> 0 | U36: =DELIVERIES!U36 -> 8.5 | V36: =T36*U36 -> 0 | W36: ='20'!D12 -> 0 | X36: =DELIVERIES!X36 -> 6 | Y36: =W36*X36 -> 0 | Z36: ='20'!D13 -> 0 | AA36: =DELIVERIES!AA36 -> 6 | AB36: =Z36*AA36 -> 0 | AC36: ='20'!D14 -> 0 | AD36: =DELIVERIES!AD36 -> 8 | AE36: =AC36*AD36 -> 0 | AG36: =AG7 -> 0 | AH36: =AF36*AG36 -> 0 | AK36: =D36+G36+J36+M36+P36+S36+V36+Y36+AB36+AE36+AH36 -> 0 | AM36: ='20'!D17 -> 0 | AN36: =DELIVERIES!AQ36 -> 8.75 | AO36: =AM36*AN36 -> 0 | AP36: ='20'!D18 -> 0 | AQ36: =DELIVERIES!AT36 -> 12.25 | AR36: =AP36*AQ36 -> 0 | AS36: ='20'!D21 -> 0 | AT36: =DELIVERIES!AW36 -> 7.9166667 | AU36: =AS36*AT36 -> 0 | AV36: ='20'!D22 -> 0 | AW36: =DELIVERIES!AZ36 -> 9.7916667 | AX36: =AV36*AW36 -> 0 | AY36: ='20'!D26 -> 0 | AZ36: =DELIVERIES!BC36 -> 16.333333 | BA36: =AY36*AZ36 -> 0 | BB36: ='20'!D27 -> 0 | BC36: =DELIVERIES!BF36 -> 11.666667 | BD36: =BB36*BC36 -> 0 | BE36: ='20'!D28 -> 0 | BF36: =DELIVERIES!BI36 -> 20 | BG36: =BE36*BF36 -> 0 | BH36: ='20'!D23 -> 0 | BI36: =DELIVERIES!BL36 -> 23 | BJ36: =BH36*BI36 -> 0 | BK36: ='20'!D25 -> 0 | BL36: =DELIVERIES!BO36 -> 12.5 | BM36: =BK36*BL36 -> 0 | BN36: ='20'!D24 -> 0 | BO36: =DELIVERIES!BR36 -> 12.75 | BP36: =BN36*BO36 -> 0 | BQ36: ='20'!D19 -> 0 | BR36: =DELIVERIES!BU36 -> 30.416667 | BS36: =BQ36*BR36 -> 0 | BT36: ='20'!D20 -> 0 | BU36: =DELIVERIES!BX36 -> 15.916667 | BV36: =BT36*BU36 -> 0 | BY36: =AO36+AR36+AU36+AX36+BA36+BD36+BG36+BJ36+BM36+BP36+BS36+BV36 -> 0 | CA36: =AK36+BY36 -> 0 | CD36: =CA36-CC36 -> 0
A37: 21 | B37: ='21'!D29 -> 0 | C37: =DELIVERIES!C37 -> 30 | D37: =B37*C37 -> 0 | E37: ='21'!D7 -> 0 | F37: =DELIVERIES!F37 -> 35 | G37: =E37*F37 -> 0 | H37: ='21'!D8 -> 0 | I37: =DELIVERIES!I37 -> 8.5 | J37: =H37*I37 -> 0 | K37: ='21'!D15 -> 0 | L37: =DELIVERIES!L37 -> 18 | M37: =K37*L37 -> 0 | N37: ='21'!D9 -> 0 | O37: =DELIVERIES!O37 -> 7 | P37: =N37*O37 -> 0 | Q37: ='21'!D10 -> 0 | R37: =DELIVERIES!R37 -> 5.5 | S37: =Q37*R37 -> 0 | T37: ='21'!D11 -> 0 | U37: =DELIVERIES!U37 -> 8.5 | V37: =T37*U37 -> 0 | W37: ='21'!D12 -> 0 | X37: =DELIVERIES!X37 -> 6 | Y37: =W37*X37 -> 0 | Z37: ='21'!D13 -> 0 | AA37: =DELIVERIES!AA37 -> 6 | AB37: =Z37*AA37 -> 0 | AC37: ='21'!D14 -> 0 | AD37: =DELIVERIES!AD37 -> 8 | AE37: =AC37*AD37 -> 0 | AG37: =AG7 -> 0 | AH37: =AF37*AG37 -> 0 | AK37: =D37+G37+J37+M37+P37+S37+V37+Y37+AB37+AE37+AH37 -> 0 | AM37: ='21'!D17 -> 0 | AN37: =DELIVERIES!AQ37 -> 8.75 | AO37: =AM37*AN37 -> 0 | AP37: ='21'!D18 -> 0 | AQ37: =DELIVERIES!AT37 -> 12.25 | AR37: =AP37*AQ37 -> 0 | AS37: ='21'!D21 -> 0 | AT37: =DELIVERIES!AW37 -> 7.9166667 | AU37: =AS37*AT37 -> 0 | AV37: ='21'!D22 -> 0 | AW37: =DELIVERIES!AZ37 -> 9.7916667 | AX37: =AV37*AW37 -> 0 | AY37: ='21'!D26 -> 0 | AZ37: =DELIVERIES!BC37 -> 16.333333 | BA37: =AY37*AZ37 -> 0 | BB37: ='21'!D27 -> 0 | BC37: =DELIVERIES!BF37 -> 11.666667 | BD37: =BB37*BC37 -> 0 | BE37: ='21'!D28 -> 0 | BF37: =DELIVERIES!BI37 -> 20 | BG37: =BE37*BF37 -> 0 | BH37: ='21'!D23 -> 0 | BI37: =DELIVERIES!BL37 -> 23 | BJ37: =BH37*BI37 -> 0 | BK37: ='21'!D25 -> 0 | BL37: =DELIVERIES!BO37 -> 12.5 | BM37: =BK37*BL37 -> 0 | BN37: ='21'!D24 -> 0 | BO37: =DELIVERIES!BR37 -> 12.75 | BP37: =BN37*BO37 -> 0 | BQ37: ='21'!D19 -> 0 | BR37: =DELIVERIES!BU37 -> 30.416667 | BS37: =BQ37*BR37 -> 0 | BT37: ='21'!D20 -> 0 | BU37: =DELIVERIES!BX37 -> 15.916667 | BV37: =BT37*BU37 -> 0 | BY37: =AO37+AR37+AU37+AX37+BA37+BD37+BG37+BJ37+BM37+BP37+BS37+BV37 -> 0 | CA37: =AK37+BY37 -> 0 | CD37: =CA37-CC37 -> 0
A38: TOTAL | B38: =SUM(B31:B37) -> 0 | D38: =SUM(D31:D37) -> 0 | E38: =SUM(E31:E37) -> 0 | G38: =SUM(G31:G37) -> 0 | H38: =SUM(H31:H37) -> 0 | J38: =SUM(J31:J37) -> 0 | K38: =SUM(K31:K37) -> 0 | M38: =SUM(M31:M37) -> 0 | N38: =SUM(N31:N37) -> 0 | P38: =SUM(P31:P37) -> 0 | Q38: =SUM(Q31:Q37) -> 0 | S38: =SUM(S31:S37) -> 0 | T38: =SUM(T31:T37) -> 0 | V38: =SUM(V31:V37) -> 0 | W38: =SUM(W31:W37) -> 0 | Y38: =SUM(Y31:Y37) -> 0 | Z38: =SUM(Z31:Z37) -> 0 | AB38: =SUM(AB31:AB37) -> 0 | AC38: =SUM(AC31:AC37) -> 0 | AE38: =SUM(AE31:AE37) -> 0 | AF38: =SUM(AF31:AF37) -> 0 | AH38: =SUM(AH31:AH37) -> 0 | AK38: =SUM(AK31:AK37) -> 0 | AM38: =SUM(AM31:AM37) -> 0 | AO38: =SUM(AO31:AO37) -> 0 | AP38: =SUM(AP31:AP37) -> 0 | AR38: =SUM(AR31:AR37) -> 0 | AS38: =SUM(AS31:AS37) -> 0 | AU38: =SUM(AU31:AU37) -> 0 | AV38: =SUM(AV31:AV37) -> 0 | AX38: =SUM(AX31:AX37) -> 0 | AY38: =SUM(AY31:AY37) -> 0 | BA38: =SUM(BA31:BA37) -> 0 | BB38: =SUM(BB31:BB37) -> 0 | BD38: =SUM(BD31:BD37) -> 0 | BE38: =SUM(BE31:BE37) -> 0 | BG38: =SUM(BG31:BG37) -> 0 | BH38: =SUM(BH31:BH37) -> 0 | BJ38: =SUM(BJ31:BJ37) -> 0 | BK38: =SUM(BK31:BK37) -> 0 | BM38: =SUM(BM31:BM37) -> 0 | BN38: =SUM(BN31:BN37) -> 0 | BP38: =SUM(BP31:BP37) -> 0 | BQ38: =SUM(BQ31:BQ37) -> 0 | BS38: =SUM(BS31:BS37) -> 0 | BT38: =SUM(BT31:BT37) -> 0 | BV38: =SUM(BV31:BV37) -> 0 | BY38: =SUM(BY31:BY37) -> 0 | CA38: =SUM(CA31:CA37) -> 0 | CD38: =SUM(CD31:CD37) -> 0
A41: WEEK- 4 | B41: =B5 -> PREMIUM - CUT | E41: SPECIAL CUT | H41: NGOHIONG | K41: =K29 -> Chicken Fillet | N41: NECK | Q41: SIOMAI | T41: RICE | W41: BOLA-BOLA | Z41: LUMPIA | AC41: ATSARA | AF41: =AF5 -> 0 | AI41: =AI5 -> SUBTOTAL | AM41: 8OZ | AP41: 12 OZ | AS41: WATER 350 ML | AV41: WATER 500 ML | AY41: PANALO | BB41: =BB29 -> swakto | BE41: Calamansi Juice | BH41: =BH29 -> GATORADE | BK41: TROPICANA | BN41: STING | BQ41: =BQ29 -> 1 LITER | BT41: =BT29 -> 1.5 L | BW41: SUBTOTAL FOR DRINKS | CA41: TOTAL
A42: DATE | B42: QTY | C42: UP | D42: AMOUNT | E42: QTY | F42: UP | G42: AMOUNT | H42: QTY | I42: UP | J42: AMOUNT | K42: QTY | L42: UP | M42: AMOUNT | N42: QTY | O42: UP | P42: AMOUNT | Q42: QTY | R42: UP | S42: AMOUNT | T42: QTY | U42: UP | V42: AMOUNT | W42: QTY | X42: UP | Y42: AMOUNT | Z42: QTY | AA42: UP | AB42: AMOUNT | AC42: QTY | AD42: UP | AE42: AMOUNT | AF42: QTY | AG42: UP | AH42: AMOUNT | AK42: AMOUNT | AM42: QTY | AN42: UP | AO42: AMOUNT | AP42: QTY | AQ42: UP | AR42: AMOUNT | AS42: QTY | AT42: UP | AU42: AMOUNT | AV42: QTY | AW42: UP | AX42: AMOUNT | AY42: QTY | AZ42: UP | BA42: AMOUNT | BB42: QTY | BC42: UP | BD42: AMOUNT | BE42: QTY | BF42: UP | BG42: AMOUNT | BH42: QTY | BI42: UP | BJ42: AMOUNT | BK42: QTY | BL42: UP | BM42: AMOUNT | BN42: QTY | BO42: UP | BP42: AMOUNT | BQ42: QTY | BR42: UP | BS42: AMOUNT | BT42: QTY | BU42: UP | BV42: AMOUNT | BY42: AMOUNT | CA42: AMOUNT
A43: 22 | B43: ='22'!D29 -> 0 | C43: =DELIVERIES!C43 -> 30 | D43: =B43*C43 -> 0 | E43: ='22'!D7 -> 0 | F43: =DELIVERIES!F43 -> 35 | G43: =E43*F43 -> 0 | H43: ='22'!D8 -> 0 | I43: =DELIVERIES!I43 -> 8.5 | J43: =H43*I43 -> 0 | K43: ='22'!D15 -> 0 | L43: =DELIVERIES!L43 -> 18 | M43: =K43*L43 -> 0 | N43: ='22'!D9 -> 0 | O43: =DELIVERIES!O43 -> 7 | P43: =N43*O43 -> 0 | Q43: ='22'!D10 -> 0 | R43: =DELIVERIES!R43 -> 5.5 | S43: =Q43*R43 -> 0 | T43: ='22'!D11 -> 0 | U43: =DELIVERIES!U43 -> 8.5 | V43: =T43*U43 -> 0 | W43: ='22'!D12 -> 0 | X43: =DELIVERIES!X43 -> 6 | Y43: =W43*X43 -> 0 | Z43: ='22'!D13 -> 0 | AA43: =DELIVERIES!AA43 -> 6 | AB43: =Z43*AA43 -> 0 | AC43: ='22'!D14 -> 0 | AD43: =DELIVERIES!AD43 -> 8 | AE43: =AC43*AD43 -> 0 | AG43: =AG7 -> 0 | AH43: =AF43*AG43 -> 0 | AK43: =D43+G43+J43+M43+P43+S43+V43+Y43+AB43+AE43+AH43 -> 0 | AM43: ='22'!D17 -> 0 | AN43: =DELIVERIES!AQ43 -> 8.75 | AO43: =AM43*AN43 -> 0 | AP43: ='22'!D18 -> 0 | AQ43: =DELIVERIES!AT43 -> 12.25 | AR43: =AP43*AQ43 -> 0 | AS43: ='22'!D21 -> 0 | AT43: =DELIVERIES!AW43 -> 7.7916667 | AU43: =AS43*AT43 -> 0 | AV43: ='22'!D22 -> 0 | AW43: =DELIVERIES!AZ43 -> 9.7916667 | AX43: =AV43*AW43 -> 0 | AY43: ='22'!D26 -> 0 | AZ43: =DELIVERIES!BC43 -> 16.333333 | BA43: =AY43*AZ43 -> 0 | BB43: ='22'!D27 -> 0 | BC43: =DELIVERIES!BF43 -> 11.833333 | BD43: =BB43*BC43 -> 0 | BE43: ='22'!D28 -> 0 | BF43: =DELIVERIES!BI43 -> 20 | BG43: =BE43*BF43 -> 0 | BH43: ='22'!D23 -> 0 | BI43: =DELIVERIES!BL43 -> 23 | BJ43: =BH43*BI43 -> 0 | BK43: ='22'!D25 -> 0 | BL43: =DELIVERIES!BO43 -> 12.5 | BM43: =BK43*BL43 -> 0 | BN43: ='22'!D24 -> 0 | BO43: =DELIVERIES!BR43 -> 12.75 | BP43: =BN43*BO43 -> 0 | BQ43: ='22'!D19 -> 0 | BR43: =DELIVERIES!BU43 -> 30.416667 | BS43: =BQ43*BR43 -> 0 | BT43: ='22'!D20 -> 0 | BU43: =DELIVERIES!BX43 -> 15.916667 | BV43: =BT43*BU43 -> 0 | BY43: =AO43+AR43+AU43+AX43+BA43+BD43+BG43+BJ43+BM43+BP43+BS43+BV43 -> 0 | CA43: =AK43+BY43 -> 0 | CD43: =CA43-CC43 -> 0
A44: 23 | B44: ='23'!D29 -> 0 | C44: =DELIVERIES!C44 -> 30 | D44: =B44*C44 -> 0 | E44: ='23'!D7 -> 0 | F44: =DELIVERIES!F44 -> 35 | G44: =E44*F44 -> 0 | H44: ='23'!D8 -> 0 | I44: =DELIVERIES!I44 -> 8.5 | J44: =H44*I44 -> 0 | K44: ='23'!D15 -> 0 | L44: =DELIVERIES!L44 -> 18 | M44: =K44*L44 -> 0 | N44: ='23'!D9 -> 0 | O44: =DELIVERIES!O44 -> 7 | P44: =N44*O44 -> 0 | Q44: ='23'!D10 -> 0 | R44: =DELIVERIES!R44 -> 5.5 | S44: =Q44*R44 -> 0 | T44: ='23'!D11 -> 0 | U44: =DELIVERIES!U44 -> 8.5 | V44: =T44*U44 -> 0 | W44: ='23'!D12 -> 0 | X44: =DELIVERIES!X44 -> 6 | Y44: =W44*X44 -> 0 | Z44: ='23'!D13 -> 0 | AA44: =DELIVERIES!AA44 -> 6 | AB44: =Z44*AA44 -> 0 | AC44: ='23'!D14 -> 0 | AD44: =DELIVERIES!AD44 -> 8 | AE44: =AC44*AD44 -> 0 | AG44: =AG7 -> 0 | AH44: =AF44*AG44 -> 0 | AK44: =D44+G44+J44+M44+P44+S44+V44+Y44+AB44+AE44+AH44 -> 0 | AM44: ='23'!D17 -> 0 | AN44: =DELIVERIES!AQ44 -> 8.75 | AO44: =AM44*AN44 -> 0 | AP44: ='23'!D18 -> 0 | AQ44: =DELIVERIES!AT44 -> 12.25 | AR44: =AP44*AQ44 -> 0 | AS44: ='23'!D21 -> 0 | AT44: =DELIVERIES!AW44 -> 7.7916667 | AU44: =AS44*AT44 -> 0 | AV44: ='23'!D22 -> 0 | AW44: =DELIVERIES!AZ44 -> 9.7916667 | AX44: =AV44*AW44 -> 0 | AY44: ='23'!D26 -> 0 | AZ44: =DELIVERIES!BC44 -> 16.333333 | BA44: =AY44*AZ44 -> 0 | BB44: ='23'!D27 -> 0 | BC44: =DELIVERIES!BF44 -> 11.833333 | BD44: =BB44*BC44 -> 0 | BE44: ='23'!D28 -> 0 | BF44: =DELIVERIES!BI44 -> 20 | BG44: =BE44*BF44 -> 0 | BH44: ='23'!D23 -> 0 | BI44: =DELIVERIES!BL44 -> 23 | BJ44: =BH44*BI44 -> 0 | BK44: ='23'!D25 -> 0 | BL44: =DELIVERIES!BO44 -> 12.5 | BM44: =BK44*BL44 -> 0 | BN44: ='23'!D24 -> 0 | BO44: =DELIVERIES!BR44 -> 12.75 | BP44: =BN44*BO44 -> 0 | BQ44: ='23'!D19 -> 0 | BR44: =DELIVERIES!BU44 -> 30.416667 | BS44: =BQ44*BR44 -> 0 | BT44: ='23'!D20 -> 0 | BU44: =DELIVERIES!BX44 -> 15.916667 | BV44: =BT44*BU44 -> 0 | BY44: =AO44+AR44+AU44+AX44+BA44+BD44+BG44+BJ44+BM44+BP44+BS44+BV44 -> 0 | CA44: =AK44+BY44 -> 0 | CD44: =CA44-CC44 -> 0
A45: 24 | B45: ='24'!D29 -> 0 | C45: =DELIVERIES!C45 -> 30 | D45: =B45*C45 -> 0 | E45: ='24'!D7 -> 0 | F45: =DELIVERIES!F45 -> 35 | G45: =E45*F45 -> 0 | H45: ='24'!D8 -> 0 | I45: =DELIVERIES!I45 -> 8.5 | J45: =H45*I45 -> 0 | K45: ='24'!D15 -> 0 | L45: =DELIVERIES!L45 -> 18 | M45: =K45*L45 -> 0 | N45: ='24'!D9 -> 0 | O45: =DELIVERIES!O45 -> 7 | P45: =N45*O45 -> 0 | Q45: ='24'!D10 -> 0 | R45: =DELIVERIES!R45 -> 5.5 | S45: =Q45*R45 -> 0 | T45: ='24'!D11 -> 0 | U45: =DELIVERIES!U45 -> 8.5 | V45: =T45*U45 -> 0 | W45: ='24'!D12 -> 0 | X45: =DELIVERIES!X45 -> 6 | Y45: =W45*X45 -> 0 | Z45: ='24'!D13 -> 0 | AA45: =DELIVERIES!AA45 -> 6 | AB45: =Z45*AA45 -> 0 | AC45: ='24'!D14 -> 0 | AD45: =DELIVERIES!AD45 -> 8 | AE45: =AC45*AD45 -> 0 | AG45: =AG7 -> 0 | AH45: =AF45*AG45 -> 0 | AK45: =D45+G45+J45+M45+P45+S45+V45+Y45+AB45+AE45+AH45 -> 0 | AM45: ='24'!D17 -> 0 | AN45: =DELIVERIES!AQ45 -> 8.75 | AO45: =AM45*AN45 -> 0 | AP45: ='24'!D18 -> 0 | AQ45: =DELIVERIES!AT45 -> 12.25 | AR45: =AP45*AQ45 -> 0 | AS45: ='24'!D21 -> 0 | AT45: =DELIVERIES!AW45 -> 7.7916667 | AU45: =AS45*AT45 -> 0 | AV45: ='24'!D22 -> 0 | AW45: =DELIVERIES!AZ45 -> 9.7916667 | AX45: =AV45*AW45 -> 0 | AY45: ='24'!D26 -> 0 | AZ45: =DELIVERIES!BC45 -> 16.333333 | BA45: =AY45*AZ45 -> 0 | BB45: ='24'!D27 -> 0 | BC45: =DELIVERIES!BF45 -> 11.833333 | BD45: =BB45*BC45 -> 0 | BE45: ='24'!D28 -> 0 | BF45: =DELIVERIES!BI45 -> 20 | BG45: =BE45*BF45 -> 0 | BH45: ='24'!D23 -> 0 | BI45: =DELIVERIES!BL45 -> 23 | BJ45: =BH45*BI45 -> 0 | BK45: ='24'!D25 -> 0 | BL45: =DELIVERIES!BO45 -> 12.5 | BM45: =BK45*BL45 -> 0 | BN45: ='24'!D24 -> 0 | BO45: =DELIVERIES!BR45 -> 12.75 | BP45: =BN45*BO45 -> 0 | BQ45: ='24'!D19 -> 0 | BR45: =DELIVERIES!BU45 -> 30.416667 | BS45: =BQ45*BR45 -> 0 | BT45: ='24'!D20 -> 0 | BU45: =DELIVERIES!BX45 -> 15.916667 | BV45: =BT45*BU45 -> 0 | BY45: =AO45+AR45+AU45+AX45+BA45+BD45+BG45+BJ45+BM45+BP45+BS45+BV45 -> 0 | CA45: =AK45+BY45 -> 0 | CD45: =CA45-CC45 -> 0
A46: 25 | B46: ='25'!D29 -> 0 | C46: =DELIVERIES!C46 -> 30 | D46: =B46*C46 -> 0 | E46: ='25'!D7 -> 0 | F46: =DELIVERIES!F46 -> 35 | G46: =E46*F46 -> 0 | H46: ='25'!D8 -> 0 | I46: =DELIVERIES!I46 -> 8.5 | J46: =H46*I46 -> 0 | K46: ='25'!D15 -> 0 | L46: =DELIVERIES!L46 -> 18 | M46: =K46*L46 -> 0 | N46: ='25'!D9 -> 0 | O46: =DELIVERIES!O46 -> 7 | P46: =N46*O46 -> 0 | Q46: ='25'!D10 -> 0 | R46: =DELIVERIES!R46 -> 5.5 | S46: =Q46*R46 -> 0 | T46: ='25'!D11 -> 0 | U46: =DELIVERIES!U46 -> 8.5 | V46: =T46*U46 -> 0 | W46: ='25'!D12 -> 0 | X46: =DELIVERIES!X46 -> 6 | Y46: =W46*X46 -> 0 | Z46: ='25'!D13 -> 0 | AA46: =DELIVERIES!AA46 -> 6 | AB46: =Z46*AA46 -> 0 | AC46: ='25'!D14 -> 0 | AD46: =DELIVERIES!AD46 -> 8 | AE46: =AC46*AD46 -> 0 | AG46: =AG7 -> 0 | AH46: =AF46*AG46 -> 0 | AK46: =D46+G46+J46+M46+P46+S46+V46+Y46+AB46+AE46+AH46 -> 0 | AM46: ='25'!D17 -> 0 | AN46: =DELIVERIES!AQ46 -> 8.75 | AO46: =AM46*AN46 -> 0 | AP46: ='25'!D18 -> 0 | AQ46: =DELIVERIES!AT46 -> 12.25 | AR46: =AP46*AQ46 -> 0 | AS46: ='25'!D21 -> 0 | AT46: =DELIVERIES!AW46 -> 7.7916667 | AU46: =AS46*AT46 -> 0 | AV46: ='25'!D22 -> 0 | AW46: =DELIVERIES!AZ46 -> 9.7916667 | AX46: =AV46*AW46 -> 0 | AY46: ='25'!D26 -> 0 | AZ46: =DELIVERIES!BC46 -> 16.333333 | BA46: =AY46*AZ46 -> 0 | BB46: ='25'!D27 -> 0 | BC46: =DELIVERIES!BF46 -> 11.833333 | BD46: =BB46*BC46 -> 0 | BE46: ='25'!D28 -> 0 | BF46: =DELIVERIES!BI46 -> 20 | BG46: =BE46*BF46 -> 0 | BH46: ='25'!D23 -> 0 | BI46: =DELIVERIES!BL46 -> 23 | BJ46: =BH46*BI46 -> 0 | BK46: ='25'!D25 -> 0 | BL46: =DELIVERIES!BO46 -> 12.5 | BM46: =BK46*BL46 -> 0 | BN46: ='25'!D24 -> 0 | BO46: =DELIVERIES!BR46 -> 12.75 | BP46: =BN46*BO46 -> 0 | BQ46: ='25'!D19 -> 0 | BR46: =DELIVERIES!BU46 -> 30.25 | BS46: =BQ46*BR46 -> 0 | BT46: ='25'!D20 -> 0 | BU46: =DELIVERIES!BX46 -> 15.916667 | BV46: =BT46*BU46 -> 0 | BY46: =AO46+AR46+AU46+AX46+BA46+BD46+BG46+BJ46+BM46+BP46+BS46+BV46 -> 0 | CA46: =AK46+BY46 -> 0 | CD46: =CA46-CC46 -> 0
A47: 26 | B47: ='26'!D29 -> 0 | C47: =DELIVERIES!C47 -> 30 | D47: =B47*C47 -> 0 | E47: ='26'!D7 -> 0 | F47: =DELIVERIES!F47 -> 35 | G47: =E47*F47 -> 0 | H47: ='26'!D8 -> 0 | I47: =DELIVERIES!I47 -> 8.5 | J47: =H47*I47 -> 0 | K47: ='26'!D15 -> 0 | L47: =DELIVERIES!L47 -> 18 | M47: =K47*L47 -> 0 | N47: ='26'!D9 -> 0 | O47: =DELIVERIES!O47 -> 7 | P47: =N47*O47 -> 0 | Q47: ='26'!D10 -> 0 | R47: =DELIVERIES!R47 -> 5.5 | S47: =Q47*R47 -> 0 | T47: ='26'!D11 -> 0 | U47: =DELIVERIES!U47 -> 8.5 | V47: =T47*U47 -> 0 | W47: ='26'!D12 -> 0 | X47: =DELIVERIES!X47 -> 6 | Y47: =W47*X47 -> 0 | Z47: ='26'!D13 -> 0 | AA47: =DELIVERIES!AA47 -> 6 | AB47: =Z47*AA47 -> 0 | AC47: ='26'!D14 -> 0 | AD47: =DELIVERIES!AD47 -> 8 | AE47: =AC47*AD47 -> 0 | AG47: =AG7 -> 0 | AH47: =AF47*AG47 -> 0 | AK47: =D47+G47+J47+M47+P47+S47+V47+Y47+AB47+AE47+AH47 -> 0 | AM47: ='26'!D17 -> 0 | AN47: =DELIVERIES!AQ47 -> 8.75 | AO47: =AM47*AN47 -> 0 | AP47: ='26'!D18 -> 0 | AQ47: =DELIVERIES!AT47 -> 12.25 | AR47: =AP47*AQ47 -> 0 | AS47: ='26'!D21 -> 0 | AT47: =DELIVERIES!AW47 -> 7.7916667 | AU47: =AS47*AT47 -> 0 | AV47: ='26'!D22 -> 0 | AW47: =DELIVERIES!AZ47 -> 9.7916667 | AX47: =AV47*AW47 -> 0 | AY47: ='26'!D26 -> 0 | AZ47: =DELIVERIES!BC47 -> 16.333333 | BA47: =AY47*AZ47 -> 0 | BB47: ='26'!D27 -> 0 | BC47: =DELIVERIES!BF47 -> 11.833333 | BD47: =BB47*BC47 -> 0 | BE47: ='26'!D28 -> 0 | BF47: =DELIVERIES!BI47 -> 20 | BG47: =BE47*BF47 -> 0 | BH47: ='26'!D23 -> 0 | BI47: =DELIVERIES!BL47 -> 23 | BJ47: =BH47*BI47 -> 0 | BK47: ='26'!D25 -> 0 | BL47: =DELIVERIES!BO47 -> 12.5 | BM47: =BK47*BL47 -> 0 | BN47: ='26'!D24 -> 0 | BO47: =DELIVERIES!BR47 -> 12.75 | BP47: =BN47*BO47 -> 0 | BQ47: ='26'!D19 -> 0 | BR47: =DELIVERIES!BU47 -> 30.25 | BS47: =BQ47*BR47 -> 0 | BT47: ='26'!D20 -> 0 | BU47: =DELIVERIES!BX47 -> 15.916667 | BV47: =BT47*BU47 -> 0 | BY47: =AO47+AR47+AU47+AX47+BA47+BD47+BG47+BJ47+BM47+BP47+BS47+BV47 -> 0 | CA47: =AK47+BY47 -> 0 | CD47: =CA47-CC47 -> 0
A48: 27 | B48: ='27'!D29 -> 0 | C48: =DELIVERIES!C48 -> 30 | D48: =B48*C48 -> 0 | E48: ='27'!D7 -> 0 | F48: =DELIVERIES!F48 -> 35 | G48: =E48*F48 -> 0 | H48: ='27'!D8 -> 0 | I48: =DELIVERIES!I48 -> 8.5 | J48: =H48*I48 -> 0 | K48: ='27'!D15 -> 0 | L48: =DELIVERIES!L48 -> 18 | M48: =K48*L48 -> 0 | N48: ='27'!D9 -> 0 | O48: =DELIVERIES!O48 -> 7 | P48: =N48*O48 -> 0 | Q48: ='27'!D10 -> 0 | R48: =DELIVERIES!R48 -> 5.5 | S48: =Q48*R48 -> 0 | T48: ='27'!D11 -> 0 | U48: =DELIVERIES!U48 -> 8.5 | V48: =T48*U48 -> 0 | W48: ='27'!D12 -> 0 | X48: =DELIVERIES!X48 -> 6 | Y48: =W48*X48 -> 0 | Z48: ='27'!D13 -> 0 | AA48: =DELIVERIES!AA48 -> 6 | AB48: =Z48*AA48 -> 0 | AC48: ='27'!D14 -> 0 | AD48: =DELIVERIES!AD48 -> 8 | AE48: =AC48*AD48 -> 0 | AG48: =AG7 -> 0 | AH48: =AF48*AG48 -> 0 | AK48: =D48+G48+J48+M48+P48+S48+V48+Y48+AB48+AE48+AH48 -> 0 | AM48: ='27'!D17 -> 0 | AN48: =DELIVERIES!AQ48 -> 8.75 | AO48: =AM48*AN48 -> 0 | AP48: ='27'!D18 -> 0 | AQ48: =DELIVERIES!AT48 -> 12.25 | AR48: =AP48*AQ48 -> 0 | AS48: ='27'!D21 -> 0 | AT48: =DELIVERIES!AW48 -> 7.7916667 | AU48: =AS48*AT48 -> 0 | AV48: ='27'!D22 -> 0 | AW48: =DELIVERIES!AZ48 -> 9.7916667 | AX48: =AV48*AW48 -> 0 | AY48: ='27'!D26 -> 0 | AZ48: =DELIVERIES!BC48 -> 16.333333 | BA48: =AY48*AZ48 -> 0 | BB48: ='27'!D27 -> 0 | BC48: =DELIVERIES!BF48 -> 11.833333 | BD48: =BB48*BC48 -> 0 | BE48: ='27'!D28 -> 0 | BF48: =DELIVERIES!BI48 -> 20 | BG48: =BE48*BF48 -> 0 | BH48: ='27'!D23 -> 0 | BI48: =DELIVERIES!BL48 -> 23 | BJ48: =BH48*BI48 -> 0 | BK48: ='27'!D25 -> 0 | BL48: =DELIVERIES!BO48 -> 12.5 | BM48: =BK48*BL48 -> 0 | BN48: ='27'!D24 -> 0 | BO48: =DELIVERIES!BR48 -> 12.75 | BP48: =BN48*BO48 -> 0 | BQ48: ='27'!D19 -> 0 | BR48: =DELIVERIES!BU48 -> 30.25 | BS48: =BQ48*BR48 -> 0 | BT48: ='27'!D20 -> 0 | BU48: =DELIVERIES!BX48 -> 15.916667 | BV48: =BT48*BU48 -> 0 | BY48: =AO48+AR48+AU48+AX48+BA48+BD48+BG48+BJ48+BM48+BP48+BS48+BV48 -> 0 | CA48: =AK48+BY48 -> 0 | CD48: =CA48-CC48 -> 0
A49: 28 | B49: ='28'!D29 -> 0 | C49: =DELIVERIES!C49 -> 30 | D49: =B49*C49 -> 0 | E49: ='28'!D7 -> 0 | F49: =DELIVERIES!F49 -> 35 | G49: =E49*F49 -> 0 | H49: ='28'!D8 -> 0 | I49: =DELIVERIES!I49 -> 8.5 | J49: =H49*I49 -> 0 | K49: ='28'!D15 -> 0 | L49: =DELIVERIES!L49 -> 18 | M49: =K49*L49 -> 0 | N49: ='28'!D9 -> 0 | O49: =DELIVERIES!O49 -> 7 | P49: =N49*O49 -> 0 | Q49: ='28'!D10 -> 0 | R49: =DELIVERIES!R49 -> 5.5 | S49: =Q49*R49 -> 0 | T49: ='28'!D11 -> 0 | U49: =DELIVERIES!U49 -> 8.5 | V49: =T49*U49 -> 0 | W49: ='28'!D12 -> 0 | X49: =DELIVERIES!X49 -> 6 | Y49: =W49*X49 -> 0 | Z49: ='28'!D13 -> 0 | AA49: =DELIVERIES!AA49 -> 6 | AB49: =Z49*AA49 -> 0 | AC49: ='28'!D14 -> 0 | AD49: =DELIVERIES!AD49 -> 8 | AE49: =AC49*AD49 -> 0 | AG49: =AG7 -> 0 | AH49: =AF49*AG49 -> 0 | AK49: =D49+G49+J49+M49+P49+S49+V49+Y49+AB49+AE49+AH49 -> 0 | AM49: ='28'!D17 -> 0 | AN49: =DELIVERIES!AQ49 -> 8.75 | AO49: =AM49*AN49 -> 0 | AP49: ='28'!D18 -> 0 | AQ49: =DELIVERIES!AT49 -> 12.25 | AR49: =AP49*AQ49 -> 0 | AS49: ='28'!D21 -> 0 | AT49: =DELIVERIES!AW49 -> 7.7916667 | AU49: =AS49*AT49 -> 0 | AV49: ='28'!D22 -> 0 | AW49: =DELIVERIES!AZ49 -> 9.7916667 | AX49: =AV49*AW49 -> 0 | AY49: ='28'!D26 -> 0 | AZ49: =DELIVERIES!BC49 -> 16.333333 | BA49: =AY49*AZ49 -> 0 | BB49: ='28'!D27 -> 0 | BC49: =DELIVERIES!BF49 -> 11.833333 | BD49: =BB49*BC49 -> 0 | BE49: ='28'!D28 -> 0 | BF49: =DELIVERIES!BI49 -> 20 | BG49: =BE49*BF49 -> 0 | BH49: ='28'!D23 -> 0 | BI49: =DELIVERIES!BL49 -> 23 | BJ49: =BH49*BI49 -> 0 | BK49: ='28'!D25 -> 0 | BL49: =DELIVERIES!BO49 -> 12.5 | BM49: =BK49*BL49 -> 0 | BN49: ='28'!D24 -> 0 | BO49: =DELIVERIES!BR49 -> 12.75 | BP49: =BN49*BO49 -> 0 | BQ49: ='28'!D19 -> 0 | BR49: =DELIVERIES!BU49 -> 30.25 | BS49: =BQ49*BR49 -> 0 | BT49: ='28'!D20 -> 0 | BU49: =DELIVERIES!BX49 -> 15.916667 | BV49: =BT49*BU49 -> 0 | BY49: =AO49+AR49+AU49+AX49+BA49+BD49+BG49+BJ49+BM49+BP49+BS49+BV49 -> 0 | CA49: =AK49+BY49 -> 0 | CD49: =CA49-CC49 -> 0
A50: 29 | B50: ='29'!D29 -> 0 | C50: =DELIVERIES!C50 -> 30 | D50: =B50*C50 -> 0 | E50: ='29'!D7 -> 0 | F50: =DELIVERIES!F50 -> 35 | G50: =E50*F50 -> 0 | H50: ='29'!D8 -> 0 | I50: =DELIVERIES!I50 -> 8.5 | J50: =H50*I50 -> 0 | K50: ='29'!D15 -> 0 | L50: =DELIVERIES!L50 -> 18 | M50: =K50*L50 -> 0 | N50: ='29'!D9 -> 0 | O50: =DELIVERIES!O50 -> 7 | P50: =N50*O50 -> 0 | Q50: ='29'!D10 -> 0 | R50: =DELIVERIES!R50 -> 5.5 | S50: =Q50*R50 -> 0 | T50: ='29'!D11 -> 0 | U50: =DELIVERIES!U50 -> 8.5 | V50: =T50*U50 -> 0 | W50: ='29'!D12 -> 0 | X50: =DELIVERIES!X50 -> 6 | Y50: =W50*X50 -> 0 | Z50: ='29'!D13 -> 0 | AA50: =DELIVERIES!AA50 -> 6 | AB50: =Z50*AA50 -> 0 | AC50: ='29'!D14 -> 0 | AD50: =DELIVERIES!AD50 -> 8 | AE50: =AC50*AD50 -> 0 | AG50: =AG7 -> 0 | AH50: =AF50*AG50 -> 0 | AK50: =D50+G50+J50+M50+P50+S50+V50+Y50+AB50+AE50+AH50 -> 0 | AM50: ='29'!D17 -> 0 | AN50: =DELIVERIES!AQ50 -> 8.75 | AO50: =AM50*AN50 -> 0 | AP50: ='29'!D18 -> 0 | AQ50: =DELIVERIES!AT50 -> 12.25 | AR50: =AP50*AQ50 -> 0 | AS50: ='29'!D21 -> 0 | AT50: =DELIVERIES!AW50 -> 7.7916667 | AU50: =AS50*AT50 -> 0 | AV50: ='29'!D22 -> 0 | AW50: =DELIVERIES!AZ50 -> 9.7916667 | AX50: =AV50*AW50 -> 0 | AY50: ='29'!D26 -> 0 | AZ50: =DELIVERIES!BC50 -> 16.333333 | BA50: =AY50*AZ50 -> 0 | BB50: ='29'!D27 -> 0 | BC50: =DELIVERIES!BF50 -> 11.833333 | BD50: =BB50*BC50 -> 0 | BE50: ='29'!D28 -> 0 | BF50: =DELIVERIES!BI50 -> 20 | BG50: =BE50*BF50 -> 0 | BH50: ='29'!D23 -> 0 | BI50: =DELIVERIES!BL50 -> 23 | BJ50: =BH50*BI50 -> 0 | BK50: ='29'!D25 -> 0 | BL50: =DELIVERIES!BO50 -> 12.5 | BM50: =BK50*BL50 -> 0 | BN50: ='29'!D24 -> 0 | BO50: =DELIVERIES!BR50 -> 12.75 | BP50: =BN50*BO50 -> 0 | BQ50: ='29'!D19 -> 0 | BR50: =DELIVERIES!BU50 -> 30.25 | BS50: =BQ50*BR50 -> 0 | BT50: ='29'!D20 -> 0 | BU50: =DELIVERIES!BX50 -> 15.916667 | BV50: =BT50*BU50 -> 0 | BY50: =AO50+AR50+AU50+AX50+BA50+BD50+BG50+BJ50+BM50+BP50+BS50+BV50 -> 0 | CA50: =AK50+BY50 -> 0 | CD50: =CA50-CC50 -> 0
A51: 30 | B51: ='30'!D29 -> 0 | C51: =DELIVERIES!C51 -> 30 | D51: =B51*C51 -> 0 | E51: ='30'!D7 -> 0 | F51: =DELIVERIES!F51 -> 35 | G51: =E51*F51 -> 0 | H51: ='30'!D8 -> 0 | I51: =DELIVERIES!I51 -> 8.5 | J51: =H51*I51 -> 0 | K51: ='30'!D15 -> 0 | L51: =DELIVERIES!L51 -> 18 | M51: =K51*L51 -> 0 | N51: ='30'!D9 -> 0 | O51: =DELIVERIES!O51 -> 7 | P51: =N51*O51 -> 0 | Q51: ='30'!D10 -> 0 | R51: =DELIVERIES!R51 -> 5.5 | S51: =Q51*R51 -> 0 | T51: ='30'!D11 -> 0 | U51: =DELIVERIES!U51 -> 8.5 | V51: =T51*U51 -> 0 | W51: ='30'!D12 -> 0 | X51: =DELIVERIES!X51 -> 6 | Y51: =W51*X51 -> 0 | Z51: ='30'!D13 -> 0 | AA51: =DELIVERIES!AA51 -> 6 | AB51: =Z51*AA51 -> 0 | AC51: ='30'!D14 -> 0 | AD51: =DELIVERIES!AD51 -> 8 | AE51: =AC51*AD51 -> 0 | AG51: =AG7 -> 0 | AH51: =AF51*AG51 -> 0 | AK51: =D51+G51+J51+M51+P51+S51+V51+Y51+AB51+AE51+AH51 -> 0 | AM51: ='30'!D17 -> 0 | AN51: =DELIVERIES!AQ51 -> 8.75 | AO51: =AM51*AN51 -> 0 | AP51: ='30'!D18 -> 0 | AQ51: =DELIVERIES!AT51 -> 12.25 | AR51: =AP51*AQ51 -> 0 | AS51: ='30'!D21 -> 0 | AT51: =DELIVERIES!AW51 -> 7.7916667 | AU51: =AS51*AT51 -> 0 | AV51: ='30'!D22 -> 0 | AW51: =DELIVERIES!AZ51 -> 9.7916667 | AX51: =AV51*AW51 -> 0 | AY51: ='30'!D26 -> 0 | AZ51: =DELIVERIES!BC51 -> 16.333333 | BA51: =AY51*AZ51 -> 0 | BB51: ='30'!D27 -> 0 | BC51: =DELIVERIES!BF51 -> 11.833333 | BD51: =BB51*BC51 -> 0 | BE51: ='30'!D28 -> 0 | BF51: =DELIVERIES!BI51 -> 20 | BG51: =BE51*BF51 -> 0 | BH51: ='30'!D23 -> 0 | BI51: =DELIVERIES!BL51 -> 23 | BJ51: =BH51*BI51 -> 0 | BK51: ='30'!D25 -> 0 | BL51: =DELIVERIES!BO51 -> 12.5 | BM51: =BK51*BL51 -> 0 | BN51: ='30'!D24 -> 0 | BO51: =DELIVERIES!BR51 -> 12.75 | BP51: =BN51*BO51 -> 0 | BQ51: ='30'!D19 -> 0 | BR51: =DELIVERIES!BU51 -> 30.25 | BS51: =BQ51*BR51 -> 0 | BT51: ='30'!D20 -> 0 | BU51: =DELIVERIES!BX51 -> 15.916667 | BV51: =BT51*BU51 -> 0 | BY51: =AO51+AR51+AU51+AX51+BA51+BD51+BG51+BJ51+BM51+BP51+BS51+BV51 -> 0 | CA51: =AK51+BY51 -> 0 | CD51: =CA51-CC51 -> 0
A52: 31 | B52: ='31'!D29 -> 0 | C52: =DELIVERIES!C52 -> 30 | D52: =B52*C52 -> 0 | E52: ='31'!D7 -> 0 | F52: =DELIVERIES!F52 -> 35 | G52: =E52*F52 -> 0 | H52: ='31'!D8 -> 0 | I52: =DELIVERIES!I52 -> 8.5 | J52: =H52*I52 -> 0 | K52: ='31'!D15 -> 0 | L52: =DELIVERIES!L52 -> 18 | M52: =K52*L52 -> 0 | N52: ='31'!D9 -> 0 | O52: =DELIVERIES!O52 -> 7 | P52: =N52*O52 -> 0 | Q52: ='31'!D10 -> 0 | R52: =DELIVERIES!R52 -> 5.5 | S52: =Q52*R52 -> 0 | T52: ='31'!D11 -> 0 | U52: =DELIVERIES!U52 -> 8.5 | V52: =T52*U52 -> 0 | W52: ='31'!D12 -> 0 | X52: =DELIVERIES!X52 -> 6 | Y52: =W52*X52 -> 0 | Z52: ='31'!D13 -> 0 | AA52: =DELIVERIES!AA52 -> 6 | AB52: =Z52*AA52 -> 0 | AC52: ='31'!D14 -> 0 | AD52: =DELIVERIES!AD52 -> 8 | AE52: =AC52*AD52 -> 0 | AG52: =AG7 -> 0 | AH52: =AF52*AG52 -> 0 | AK52: =D52+G52+J52+M52+P52+S52+V52+Y52+AB52+AE52+AH52 -> 0 | AM52: ='31'!D17 -> 0 | AN52: =DELIVERIES!AQ52 -> 8.75 | AO52: =AM52*AN52 -> 0 | AP52: ='31'!D18 -> 0 | AQ52: =DELIVERIES!AT52 -> 12.25 | AR52: =AP52*AQ52 -> 0 | AS52: ='31'!D21 -> 0 | AT52: =DELIVERIES!AW52 -> 7.7916667 | AU52: =AS52*AT52 -> 0 | AV52: ='31'!D22 -> 0 | AW52: =DELIVERIES!AZ52 -> 9.7916667 | AX52: =AV52*AW52 -> 0 | AY52: ='31'!D26 -> 0 | AZ52: =DELIVERIES!BC52 -> 16.333333 | BA52: =AY52*AZ52 -> 0 | BB52: ='31'!D27 -> 0 | BC52: =DELIVERIES!BF52 -> 11.833333 | BD52: =BB52*BC52 -> 0 | BE52: ='31'!D28 -> 0 | BF52: =DELIVERIES!BI52 -> 20 | BG52: =BE52*BF52 -> 0 | BH52: ='31'!D23 -> 0 | BI52: =DELIVERIES!BL52 -> 23 | BJ52: =BH52*BI52 -> 0 | BK52: ='31'!D25 -> 0 | BL52: =DELIVERIES!BO52 -> 12.5 | BM52: =BK52*BL52 -> 0 | BN52: ='31'!D24 -> 0 | BO52: =DELIVERIES!BR52 -> 12.75 | BP52: =BN52*BO52 -> 0 | BQ52: ='31'!D19 -> 0 | BR52: =DELIVERIES!BU52 -> 30.25 | BS52: =BQ52*BR52 -> 0 | BT52: ='31'!D20 -> 0 | BU52: =DELIVERIES!BX52 -> 15.916667 | BV52: =BT52*BU52 -> 0 | BY52: =AO52+AR52+AU52+AX52+BA52+BD52+BG52+BJ52+BM52+BP52+BS52+BV52 -> 0 | CA52: =AK52+BY52 -> 0 | CD52: =CA52-CC52 -> 0
A53: TOTAL | B53: =SUM(B43:B52) -> 0 | D53: =SUM(D43:D52) -> 0 | E53: =SUM(E43:E52) -> 0 | G53: =SUM(G43:G52) -> 0 | H53: =SUM(H43:H52) -> 0 | J53: =SUM(J43:J52) -> 0 | K53: =SUM(K43:K52) -> 0 | M53: =SUM(M43:M52) -> 0 | N53: =SUM(N43:N52) -> 0 | P53: =SUM(P43:P52) -> 0 | Q53: =SUM(Q43:Q52) -> 0 | S53: =SUM(S43:S52) -> 0 | T53: =SUM(T43:T52) -> 0 | V53: =SUM(V43:V52) -> 0 | W53: =SUM(W43:W52) -> 0 | Y53: =SUM(Y43:Y52) -> 0 | Z53: =SUM(Z43:Z52) -> 0 | AB53: =SUM(AB43:AB52) -> 0 | AC53: =SUM(AC43:AC52) -> 0 | AE53: =SUM(AE43:AE52) -> 0 | AF53: =SUM(AF43:AF52) -> 0 | AH53: =SUM(AH43:AH52) -> 0 | AK53: =SUM(AK43:AK52) -> 0 | AM53: =SUM(AM43:AM52) -> 0 | AO53: =SUM(AO43:AO52) -> 0 | AP53: =SUM(AP43:AP52) -> 0 | AR53: =SUM(AR43:AR52) -> 0 | AS53: =SUM(AS43:AS52) -> 0 | AU53: =SUM(AU43:AU52) -> 0 | AV53: =SUM(AV43:AV52) -> 0 | AX53: =SUM(AX43:AX52) -> 0 | AY53: =SUM(AY43:AY52) -> 0 | BA53: =SUM(BA43:BA52) -> 0 | BB53: =SUM(BB43:BB52) -> 0 | BD53: =SUM(BD43:BD52) -> 0 | BE53: =SUM(BE43:BE52) -> 0 | BG53: =SUM(BG43:BG52) -> 0 | BH53: =SUM(BH43:BH52) -> 0 | BJ53: =SUM(BJ43:BJ52) -> 0 | BK53: =SUM(BK43:BK52) -> 0 | BM53: =SUM(BM43:BM52) -> 0 | BN53: =SUM(BN43:BN52) -> 0 | BP53: =SUM(BP43:BP52) -> 0 | BQ53: =SUM(BQ43:BQ52) -> 0 | BS53: =SUM(BS43:BS52) -> 0 | BT53: =SUM(BT43:BT52) -> 0 | BV53: =SUM(BV43:BV52) -> 0 | BY53: =SUM(BY43:BY52) -> 0 | CA53: =SUM(CA43:CA52) -> 0 | CD53: =SUM(CD43:CD52) -> 0
A55: TOTAL | B55: =B14+B26+B38+B53 -> 0 | D55: =D14+D26+D38+D53 -> 0 | E55: =E14+E26+E38+E53 -> 0 | G55: =G14+G26+G38+G53 -> 0 | H55: =H14+H26+H38+H53 -> 0 | J55: =J14+J26+J38+J53 -> 0 | K55: =K14+K26+K38+K53 -> 0 | M55: =M14+M26+M38+M53 -> 0 | N55: =N14+N26+N38+N53 -> 0 | P55: =P14+P26+P38+P53 -> 0 | Q55: =Q14+Q26+Q38+Q53 -> 0 | S55: =S14+S26+S38+S53 -> 0 | T55: =T14+T26+T38+T53 -> 0 | V55: =V14+V26+V38+V53 -> 0 | W55: =W14+W26+W38+W53 -> 0 | Y55: =Y14+Y26+Y38+Y53 -> 0 | Z55: =Z14+Z26+Z38+Z53 -> 0 | AB55: =AB14+AB26+AB38+AB53 -> 0 | AC55: =AC14+AC26+AC38+AC53 -> 0 | AE55: =AE14+AE26+AE38+AE53 -> 0 | AF55: =AF14+AF26+AF38+AF53 -> 0 | AH55: =AH14+AH26+AH38+AH53 -> 0 | AK55: =AK14+AK26+AK38+AK53 -> 0 | AM55: =AM14+AM26+AM38+AM53 -> 0 | AO55: =AO14+AO26+AO38+AO53 -> 0 | AP55: =AP14+AP26+AP38+AP53 -> 0 | AR55: =AR14+AR26+AR38+AR53 -> 0 | AS55: =AS14+AS26+AS38+AS53 -> 0 | AU55: =AU14+AU26+AU38+AU53 -> 0 | AV55: =AV14+AV26+AV38+AV53 -> 0 | AX55: =AX14+AX26+AX38+AX53 -> 0 | AY55: =AY14+AY26+AY38+AY53 -> 0 | BA55: =BA14+BA26+BA38+BA53 -> 0 | BB55: =BB14+BB26+BB38+BB53 -> 0 | BD55: =BD14+BD26+BD38+BD53 -> 0 | BE55: =BE14+BE26+BE38+BE53 -> 0 | BG55: =BG14+BG26+BG38+BG53 -> 0 | BH55: =BH14+BH26+BH38+BH53 -> 0 | BJ55: =BJ14+BJ26+BJ38+BJ53 -> 0 | BK55: =BK14+BK26+BK38+BK53 -> 0 | BM55: =BM14+BM26+BM38+BM53 -> 0 | BN55: =BN14+BN26+BN38+BN53 -> 0 | BP55: =BP14+BP26+BP38+BP53 -> 0 | BQ55: =BQ14+BQ26+BQ38+BQ53 -> 0 | BS55: =BS14+BS26+BS38+BS53 -> 0 | BT55: =BT14+BT26+BT38+BT53 -> 0 | BV55: =BV14+BV26+BV38+BV53 -> 0 | BY55: =BY14+BY26+BY38+BY53 -> 0 | CA55: =CA14+CA26+CA38+CA53 -> 0 | CB55: =CA55/30 -> 0

Sheet MONTHLY INV.
A1: Monthly Inventory: | C1: =GROSS!E1 -> BRANCH
A2: For the Month of:
A4: INGREDIENTS | B4: Beginning Inventory | E4: Purchases/Deliveries | G4: B. O. | I4: Ending Inventory | M4: INGREDIENTS | N4: Cost Of Goods Sold | R4: Gross Sales
B5: Qty. | C5: Unit Price | D5: Amount | E5: Qty. | F5: Amount | G5: Qty. | H5: Amount | I5: Qty. | J5: Unit Price | K5: Amount | N5: Qty. | O5: Unit Price | P5: Amount | R5: Qty. | S5: SP | T5: Amount
A6: ='WEEKLY INV.'!A8 -> SPECIAL CUT | B6: ='WEEKLY INV.'!B8 -> 175 | C6: ='WEEKLY INV.'!C8 -> 35 | D6: =B6*C6 -> 6125 | E6: =DELIVERIES!E55 -> 6150 | F6: =DELIVERIES!G55 -> 215250 | G6: =B.O!E55 -> 0 | H6: =B.O!G55 -> 0 | I6: =B6+E6-G6-N6 -> 313 | J6: ='WEEKLY INV.'!J95 -> 35 | K6: =I6*J6 -> 10955 | M6: =A6 -> SPECIAL CUT | N6: =R6 -> 6012 | O6: =C6 -> 35 | P6: ='DAILY COGS'!G55 -> 210420 | R6: =GROSS!E55 -> 6012 | S6: ='WEEKLY INV.'!S8 -> 50 | T6: =GROSS!G55 -> 300600
A7: ='WEEKLY INV.'!A9 -> NGOHIONG | B7: ='WEEKLY INV.'!B9 -> 23 | C7: ='WEEKLY INV.'!C9 -> 8.5 | D7: =B7*C7 -> 195.5 | E7: =DELIVERIES!H55 -> 340 | F7: =DELIVERIES!J55 -> 2890 | G7: =B.O!H55 -> 0 | H7: =B.O!J55 -> 0 | I7: =B7+E7-G7-N7 -> 25 | J7: ='WEEKLY INV.'!J96 -> 8.5 | K7: =I7*J7 -> 212.5 | M7: =A7 -> NGOHIONG | N7: =R7 -> 338 | O7: =C7 -> 8.5 | P7: ='DAILY COGS'!J55 -> 2873 | R7: =GROSS!H55 -> 338 | S7: ='WEEKLY INV.'!S9 -> 12 | T7: =GROSS!J55 -> 4056
A8: ='WEEKLY INV.'!A10 -> NECK | B8: ='WEEKLY INV.'!B10 -> 16 | C8: ='WEEKLY INV.'!C10 -> 7 | D8: =B8*C8 -> 112 | E8: =DELIVERIES!N55 -> 2800 | F8: =DELIVERIES!P55 -> 19600 | G8: =B.O!N55 -> 0 | H8: =B.O!P55 -> 0 | I8: =B8+E8-G8-N8 -> 34 | J8: ='WEEKLY INV.'!J97 -> 7 | K8: =I8*J8 -> 238 | M8: =A8 -> NECK | N8: =R8 -> 2782 | O8: =C8 -> 7 | P8: ='DAILY COGS'!P55 -> 19474 | R8: =GROSS!N55 -> 2782 | S8: ='WEEKLY INV.'!S10 -> 12 | T8: =GROSS!P55 -> 33384
A9: ='WEEKLY INV.'!A11 -> SIOMAI | B9: ='WEEKLY INV.'!B11 -> 39 | C9: ='WEEKLY INV.'!C11 -> 5.5 | D9: =B9*C9 -> 214.5 | E9: =DELIVERIES!Q55 -> 0 | F9: =DELIVERIES!S55 -> 0 | G9: =B.O!Q55 -> 0 | H9: =B.O!S55 -> 0 | I9: =B9+E9-G9-N9 -> 39 | J9: ='WEEKLY INV.'!J98 -> 5.5 | K9: =I9*J9 -> 214.5 | M9: =A9 -> SIOMAI | N9: =R9 -> 0 | O9: =C9 -> 5.5 | P9: ='DAILY COGS'!S55 -> 0 | R9: =GROSS!Q55 -> 0 | S9: ='WEEKLY INV.'!S11 -> 7.5 | T9: =GROSS!S55 -> 0
A10: ='WEEKLY INV.'!A12 -> RICE | B10: ='WEEKLY INV.'!B12 -> 15 | C10: =2500/528 -> 4.7348485 | D10: =B10*C10 -> 71.022727 | E10: =DELIVERIES!T55 -> 5905 | F10: =DELIVERIES!V55 -> 50192.5 | G10: =B.O!T55 -> 0 | H10: =B.O!V55 -> 0 | I10: =B10+E10-G10-N10 -> 46 | J10: ='WEEKLY INV.'!J99 -> 8.5 | K10: =I10*J10 -> 391 | M10: =A10 -> RICE | N10: =R10 -> 5874 | O10: =C10 -> 4.7348485 | P10: ='DAILY COGS'!V55 -> 49929 | R10: =GROSS!T55 -> 5874 | S10: ='WEEKLY INV.'!S12 -> 15 | T10: =GROSS!V55 -> 88110
A11: ='WEEKLY INV.'!A13 -> BOLA BOLA | B11: ='WEEKLY INV.'!B13 -> 70 | C11: ='WEEKLY INV.'!C13 -> 6 | D11: =B11*C11 -> 420 | E11: =DELIVERIES!W55 -> 1180 | F11: =DELIVERIES!Y55 -> 7080 | G11: =B.O!Q55 -> 0 | H11: =B.O!Y55 -> 0 | I11: =B11+E11-G11-N11 -> 70 | J11: ='WEEKLY INV.'!J100 -> 6 | K11: =I11*J11 -> 420 | M11: =A11 -> BOLA BOLA | N11: =R11 -> 1180 | O11: =C11 -> 6 | P11: ='DAILY COGS'!Y55 -> 7080 | R11: =GROSS!W55 -> 1180 | S11: ='WEEKLY INV.'!S13 -> 10 | T11: =GROSS!Y55 -> 11800
A12: ='WEEKLY INV.'!A14 -> LUMPIA | B12: ='WEEKLY INV.'!B14 -> 32 | C12: ='WEEKLY INV.'!C14 -> 6 | D12: =B12*C12 -> 192 | E12: =DELIVERIES!Z55 -> 1180 | F12: =DELIVERIES!AB55 -> 7080 | G12: =B.O!Z55 -> 0 | H12: =B.O!AB55 -> 0 | I12: =B12+E12-G12-N12 -> 59 | J12: ='WEEKLY INV.'!J101 -> 6 | K12: =I12*J12 -> 354 | M12: =A12 -> LUMPIA | N12: =R12 -> 1153 | O12: =C12 -> 6 | P12: ='DAILY COGS'!AB55 -> 6918 | R12: =GROSS!Z55 -> 1153 | S12: ='WEEKLY INV.'!S14 -> 8 | T12: =GROSS!AB55 -> 9224
A13: ='WEEKLY INV.'!A15 -> ATSARA | B13: ='WEEKLY INV.'!B15 -> 34 | C13: ='WEEKLY INV.'!C15 -> 8 | D13: =B13*C13 -> 272 | E13: =DELIVERIES!AC55 -> 226 | F13: =DELIVERIES!AE55 -> 1808 | G13: =B.O!AC55 -> 0 | H13: =B.O!AE55 -> 0 | I13: =B13+E13-G13-N13 -> 3 | J13: ='WEEKLY INV.'!J102 -> 8 | K13: =I13*J13 -> 24 | M13: =A13 -> ATSARA | N13: =R13 -> 257 | O13: =C13 -> 8 | P13: ='DAILY COGS'!AE55 -> 2056 | R13: =GROSS!AC55 -> 257 | S13: ='WEEKLY INV.'!S15 -> 10 | T13: =GROSS!AE55 -> 2570
A14: ='WEEKLY INV.'!A16 -> Chicken Fillet | B14: ='WEEKLY INV.'!B16 -> 40 | C14: ='WEEKLY INV.'!C16 -> 18 | D14: =B14*C14 -> 720 | E14: =DELIVERIES!K55 -> 450 | F14: =DELIVERIES!M55 -> 8100 | G14: =B.O!Z55 -> 0 | H14: =B.O!M55 -> 0 | I14: =B14+E14-G14-N14 -> 12 | J14: ='WEEKLY INV.'!J103 -> 18 | K14: =I14*J14 -> 216 | M14: =A14 -> Chicken Fillet | N14: =R14 -> 478 | O14: =C14 -> 18 | P14: ='DAILY COGS'!M55 -> 8604 | R14: =GROSS!K55 -> 478 | S14: ='WEEKLY INV.'!S16 -> 25 | T14: =GROSS!M55 -> 11950
A15: ='WEEKLY INV.'!A17 -> SUB TOTAL | C15: ='WEEKLY INV.'!C17 -> 0 | D15: =SUM(D6:D14) -> 8322.0227 | F15: =SUM(F6:F14) -> 312000.5 | H15: =SUM(H6:H14) -> 0 | K15: =SUM(K6:K14) -> 13025 | M15: =A15 -> SUB TOTAL | O15: =C15 -> 0 | P15: =SUM(P6:P14) -> 307354 | T15: =SUM(T6:T14) -> 461694
A16: ='WEEKLY INV.'!A18 -> 8 oz | B16: ='WEEKLY INV.'!B18 -> 70 | C16: ='WEEKLY INV.'!C18 -> 8.75 | D16: =B16*C16 -> 612.5 | E16: =DELIVERIES!AP55 -> 432 | F16: =DELIVERIES!AR55 -> 3780 | G16: =B.O!AM55 -> 0 | H16: =B.O!AO55 -> 0 | I16: =B16+E16-G16-N16 -> 95 | J16: ='WEEKLY INV.'!J105 -> 8.75 | K16: =I16*J16 -> 831.25 | M16: =A16 -> 8 oz | N16: =R16 -> 407 | O16: =C16 -> 8.75 | P16: ='DAILY COGS'!AO55 -> 3561.25 | R16: =GROSS!AM55 -> 407 | S16: ='WEEKLY INV.'!S18 -> 20 | T16: =GROSS!AO55 -> 8140
A17: ='WEEKLY INV.'!A19 -> 12 oz | B17: ='WEEKLY INV.'!B19 -> 227 | C17: ='WEEKLY INV.'!C19 -> 12.25 | D17: =B17*C17 -> 2780.75 | E17: =DELIVERIES!AS55 -> 1248 | F17: =DELIVERIES!AU55 -> 15288 | G17: =B.O!AP55 -> 0 | H17: =B.O!AR55 -> 0 | I17: =B17+E17-G17-N17 -> 218 | J17: ='WEEKLY INV.'!J106 -> 12.25 | K17: =I17*J17 -> 2670.5 | M17: =A17 -> 12 oz | N17: =R17 -> 1257 | O17: =C17 -> 12.25 | P17: ='DAILY COGS'!AR55 -> 15398.25 | R17: =GROSS!AP55 -> 1257 | S17: ='WEEKLY INV.'!S19 -> 25 | T17: =GROSS!AR55 -> 31425
A18: ='WEEKLY INV.'!A20 -> 1 LITER | B18: ='WEEKLY INV.'!B20 -> 0 | C18: ='WEEKLY INV.'!C20 -> 30.25 | D18: =B18*C18 -> 0 | E18: =DELIVERIES!BT55 -> 0 | F18: =DELIVERIES!BV55 -> 0 | G18: =B.O!AM55 -> 0 | H18: =B.O!BS55 -> 0 | I18: =B18+E18-G18-N18 -> 0 | J18: ='WEEKLY INV.'!J107 -> 30.25 | K18: =I18*J18 -> 0 | M18: =A18 -> 1 LITER | N18: =R18 -> 0 | O18: =C18 -> 30.25 | P18: ='DAILY COGS'!BS55 -> 0 | R18: =GROSS!BQ55 -> 0 | S18: ='WEEKLY INV.'!S20 -> 40 | T18: =GROSS!BS55 -> 0 | V18: 10905
A19: ='WEEKLY INV.'!A21 -> 1.5 L | B19: ='WEEKLY INV.'!B21 -> 0 | C19: ='WEEKLY INV.'!C21 -> 15.916667 | D19: =B19*C19 -> 0 | E19: =DELIVERIES!BW55 -> 0 | F19: =DELIVERIES!BY55 -> 0 | G19: =B.O!AP55 -> 0 | H19: =B.O!BV55 -> 0 | I19: =B19+E19-G19-N19 -> 0 | J19: ='WEEKLY INV.'!J108 -> 15.916667 | K19: =I19*J19 -> 0 | M19: =A19 -> 1.5 L | N19: =R19 -> 0 | O19: =C19 -> 15.916667 | P19: ='DAILY COGS'!BV55 -> 0 | R19: =GROSS!BT55 -> 0 | S19: ='WEEKLY INV.'!S21 -> 80 | T19: =GROSS!BV55 -> 0 | V19: 11271
A20: ='WEEKLY INV.'!A22 -> Water 350ml | B20: ='WEEKLY INV.'!B22 -> 0 | C20: ='WEEKLY INV.'!C22 -> 7.9166667 | D20: =B20*C20 -> 0 | E20: =DELIVERIES!AV55 -> 0 | F20: =DELIVERIES!AX55 -> 0 | G20: =B.O!AS55 -> 0 | H20: =B.O!AU55 -> 0 | I20: =B20+E20-G20-N20 -> 0 | J20: ='WEEKLY INV.'!J109 -> 7.7916667 | K20: =I20*J20 -> 0 | M20: =A20 -> Water 350ml | N20: =R20 -> 0 | O20: =C20 -> 7.9166667 | P20: ='DAILY COGS'!AU55 -> 0 | R20: =GROSS!AS55 -> 0 | S20: ='WEEKLY INV.'!S22 -> 15 | T20: =GROSS!AU55 -> 0
A21: ='WEEKLY INV.'!A23 -> Water 500ml | B21: ='WEEKLY INV.'!B23 -> 85 | C21: =232/24 -> 9.6666667 | D21: =B21*C21 -> 821.66667 | E21: =DELIVERIES!AY55 -> 192 | F21: =DELIVERIES!BA55 -> 1880 | G21: =B.O!AV55 -> 0 | H21: =B.O!AX55 -> 0 | I21: =B21+E21-G21-N21 -> 48 | J21: ='WEEKLY INV.'!J110 -> 9.7916667 | K21: =I21*J21 -> 470 | M21: =A21 -> Water 500ml | N21: =R21 -> 229 | O21: =C21 -> 9.6666667 | P21: ='DAILY COGS'!AX55 -> 2242.2917 | R21: =GROSS!AV55 -> 229 | S21: ='WEEKLY INV.'!S23 -> 20 | T21: =GROSS!AX55 -> 4580
A22: ='WEEKLY INV.'!A24 -> GATORADE | B22: ='WEEKLY INV.'!B24 -> 0 | C22: ='WEEKLY INV.'!C24 -> 23 | D22: =B22*C22 -> 0 | E22: =DELIVERIES!BK55 -> 0 | F22: =DELIVERIES!BM55 -> 0 | G22: =B.O!AY55 -> 0 | H22: =B.O!BJ55 -> 0 | I22: =B22+E22-G22-N22 -> 0 | J22: ='WEEKLY INV.'!J111 -> 23 | K22: =I22*J22 -> 0 | M22: =A22 -> GATORADE | N22: =R22 -> 0 | O22: =C22 -> 23 | P22: ='DAILY COGS'!BJ55 -> 0 | R22: =GROSS!BH55 -> 0 | S22: ='WEEKLY INV.'!S24 -> 35 | T22: =GROSS!BJ55 -> 0 | V22: 4500
A23: ='WEEKLY INV.'!A25 -> STING | B23: ='WEEKLY INV.'!B25 -> 26 | C23: ='WEEKLY INV.'!C25 -> 12.75 | D23: =B23*C23 -> 331.5 | E23: =DELIVERIES!BQ55 -> 96 | F23: =DELIVERIES!BS55 -> 1224 | G23: =B.O!BB55 -> 0 | H23: =B.O!BP55 -> 0 | I23: =B23+E23-G23-N23 -> 29 | J23: ='WEEKLY INV.'!J112 -> 12.75 | K23: =I23*J23 -> 369.75 | M23: =A23 -> STING | N23: =R23 -> 93 | O23: =C23 -> 12.75 | P23: ='DAILY COGS'!BP55 -> 1185.75 | R23: =GROSS!BN55 -> 93 | S23: ='WEEKLY INV.'!S25 -> 25 | T23: =GROSS!BP55 -> 2325
A24: ='WEEKLY INV.'!A26 -> TROPICANA | B24: ='WEEKLY INV.'!B26 -> 0 | C24: ='WEEKLY INV.'!C26 -> 12.5 | D24: =B24*C24 -> 0 | E24: =DELIVERIES!BN55 -> 0 | F24: =DELIVERIES!BP55 -> 0 | G24: =B.O!BE55 -> 0 | H24: =B.O!BM55 -> 0 | I24: =B24+E24-G24-N24 -> 0 | J24: ='WEEKLY INV.'!J113 -> 12.5 | K24: =I24*J24 -> 0 | M24: =A24 -> TROPICANA | N24: =R24 -> 0 | O24: =C24 -> 12.5 | P24: ='DAILY COGS'!BM55 -> 0 | R24: =GROSS!BK55 -> 0 | S24: ='WEEKLY INV.'!S26 -> 22 | T24: =GROSS!BM55 -> 0
A25: ='WEEKLY INV.'!A27 -> PANALO | B25: ='WEEKLY INV.'!B27 -> 0 | C25: ='WEEKLY INV.'!C27 -> 16.333333 | D25: =B25*C25 -> 0 | E25: =DELIVERIES!BB55 -> 0 | F25: =DELIVERIES!BD55 -> 0 | G25: =B.O!BH55 -> 0 | H25: =B.O!BA55 -> 0 | I25: =B25+E25-G25-N25 -> 0 | J25: ='WEEKLY INV.'!J114 -> 16.333333 | K25: =I25*J25 -> 0 | M25: =A25 -> PANALO | N25: =R25 -> 0 | O25: =C25 -> 16.333333 | P25: ='DAILY COGS'!BA55 -> 0 | R25: =GROSS!AY55 -> 0 | S25: ='WEEKLY INV.'!S27 -> 25 | T25: =GROSS!BA55 -> 0
A26: ='WEEKLY INV.'!A28 -> SWAKTO | B26: ='WEEKLY INV.'!B28 -> 107 | C26: ='WEEKLY INV.'!C28 -> 11.5 | D26: =B26*C26 -> 1230.5 | E26: =DELIVERIES!BE55 -> 0 | F26: =DELIVERIES!BG55 -> 0 | G26: =B.O!BK55 -> 0 | H26: =B.O!BD55 -> 0 | I26: =B26+E26-G26-N26 -> 0 | J26: ='WEEKLY INV.'!J115 -> 11.833333 | K26: =I26*J26 -> 0 | M26: =A26 -> SWAKTO | N26: =R26 -> 107 | O26: =C26 -> 11.5 | P26: ='DAILY COGS'!BD55 -> 1232.3333 | R26: =GROSS!BB55 -> 107 | S26: ='WEEKLY INV.'!S28 -> 17 | T26: =GROSS!BD55 -> 1819
A27: ='WEEKLY INV.'!A29 -> CALAMANSI JUICE | B27: ='WEEKLY INV.'!B29 -> 88 | C27: ='WEEKLY INV.'!C29 -> 20 | D27: =B27*C27 -> 1760 | E27: =DELIVERIES!BH55 -> 50 | F27: =DELIVERIES!BJ55 -> 1000 | G27: =B.O!BN55 -> 0 | H27: =G27*C27 -> 0 | I27: =B27+E27-G27-N27 -> 42 | J27: ='WEEKLY INV.'!J116 -> 20 | K27: =I27*J27 -> 840 | M27: =A27 -> CALAMANSI JUICE | N27: =R27 -> 96 | O27: =C27 -> 20 | P27: ='DAILY COGS'!BG55 -> 1920 | R27: =GROSS!BE55 -> 96 | S27: ='WEEKLY INV.'!S29 -> 25 | T27: =GROSS!BG55 -> 2400 | V27: 620
A28: ='WEEKLY INV.'!A30 -> PREMIUM CUT | B28: ='WEEKLY INV.'!B30 -> 0 | C28: ='WEEKLY INV.'!C30 -> 30 | D28: =B28*C28 -> 0 | E28: =DELIVERIES!B55 -> 0 | F28: =DELIVERIES!D55 -> 0 | G28: =B.O!B55 -> 0 | H28: =G28*C28 -> 0 | I28: =B28+E28-G28-N28 -> 0 | J28: ='WEEKLY INV.'!J117 -> 30 | K28: =I28*J28 -> 0 | M28: =A28 -> PREMIUM CUT | N28: =R28 -> 0 | O28: =C28 -> 30 | P28: ='DAILY COGS'!D55 -> 0 | R28: =GROSS!B55 -> 0 | S28: ='WEEKLY INV.'!S30 -> 40 | T28: =GROSS!D55 -> 0
A29: ='WEEKLY INV.'!A31 -> SUB TOTAL | C29: ='WEEKLY INV.'!C31 -> 0 | D29: =SUM(D16:D28) -> 7536.9167 | F29: =SUM(F16:F28) -> 23172 | H29: =SUM(H16:H28) -> 0 | J29: ='WEEKLY INV.'!J118 -> 0 | K29: =SUM(K16:K28) -> 5181.5 | M29: =A29 -> SUB TOTAL | O29: =C29 -> 0 | P29: =SUM(P16:P28) -> 25539.875 | R29: =GROSS!CC55 -> 0 | S29: ='WEEKLY INV.'!S31 -> 0 | T29: =SUM(T16:T28) -> 50689
A30: TOTAL | D30: =D29+D15 -> 15858.939 | F30: =F29+F15 -> 335172.5 | H30: =H29+H15 -> 0 | K30: =K29+K15 -> 18206.5 | M30: =A30 -> TOTAL | P30: =P29+P15 -> 332893.88 | T30: =T29+T15 -> 512383
E33: =D30+F30-K30 -> 332824.94 | F33: =P30 -> 332893.88
K36: =D30+F30-P30 -> 18137.564

Sheet DELIVERIES
A1: CRISPY KING FOOD STATION : | BN1: DRINKS
A2: Daily Monitoring of Deliveries
A3: For the Month of:
A5: WEEK- 1 | B5: PREMIUM CUT | E5: ='1'!A7 -> SPECIAL CUT | H5: ='1'!A8 -> NGOHIONG | K5: ='1'!A15 -> Chicken Fillet | N5: NECK | Q5: SIOMAI | T5: RICE | W5: BOLA-BOLA | Z5: LUMPIA | AC5: ATSARA | AL5: SUB TOTAL | AP5: 8 OZ | AS5: 12 OZ | AV5: WATER 350 ML | AY5: WATER 500 ML | BB5: PANALO | BE5: swakto | BH5: Calamansi Juice | BK5: ='1'!A23 -> GATORADE | BN5: TROPICANA | BQ5: STING | BT5: ='1'!A19 -> 1 LITER | BW5: ='1'!A20 -> 1.5 L | BZ5: SUBTOTAL FOR DRINKS | CC5: AUDIT GROSS | CD5: DIFFERENCE | CF5: Payment Commissary
A6: DATE | B6: QTY | C6: UP | D6: AMOUNT | E6: QTY | F6: UP | G6: AMOUNT | H6: QTY | I6: UP | J6: AMOUNT | K6: QTY | L6: UP | M6: AMOUNT | N6: QTY | O6: UP | P6: AMOUNT | Q6: QTY | R6: UP | S6: AMOUNT | T6: QTY | U6: UP | V6: AMOUNT | W6: QTY | X6: UP | Y6: AMOUNT | Z6: QTY | AA6: UP | AB6: AMOUNT | AC6: QTY | AD6: UP | AE6: AMOUNT | AF6: QTY | AG6: UP | AH6: AMOUNT | AI6: QTY | AJ6: UP | AK6: AMOUNT | AL6: QTY | AM6: UP | AN6: AMOUNT | AP6: QTY | AQ6: UP | AR6: AMOUNT | AS6: QTY | AT6: UP | AU6: AMOUNT | AV6: QTY | AW6: UP | AX6: AMOUNT | AY6: QTY | AZ6: UP | BA6: AMOUNT | BB6: QTY | BC6: UP | BD6: AMOUNT | BE6: QTY | BF6: UP | BG6: AMOUNT | BH6: QTY | BI6: UP | BJ6: AMOUNT | BK6: QTY | BL6: UP | BM6: AMOUNT | BN6: QTY | BO6: UP | BP6: AMOUNT | BQ6: QTY | BR6: UP | BS6: AMOUNT | BT6: QTY | BU6: UP | BV6: AMOUNT | BW6: QTY | BX6: UP | BY6: AMOUNT | CA6: AMOUNT
A7: 45444 | B7: ='1'!C29 -> 0 | C7: 30 | D7: =B7*C7 -> 0 | E7: ='1'!C7 -> 250 | F7: 35 | G7: =E7*F7 -> 8750 | H7: ='1'!C8 -> 20 | I7: 8.5 | J7: =H7*I7 -> 170 | K7: ='1'!C15 -> 0 | L7: 18 | M7: =K7*L7 -> 0 | N7: ='1'!C9 -> 0 | O7: 7 | P7: =N7*O7 -> 0 | Q7: ='1'!C10 -> 0 | R7: 5.5 | S7: =Q7*R7 -> 0 | T7: ='1'!C11 -> 200 | U7: 8.5 | V7: =T7*U7 -> 1700 | W7: ='1'!C12 -> 0 | X7: 6 | Y7: =W7*X7 -> 0 | Z7: ='1'!C13 -> 50 | AA7: 6 | AB7: =Z7*AA7 -> 300 | AC7: ='1'!C14 -> 0 | AD7: =1280/160 -> 8 | AE7: =AC7*AD7 -> 0 | AG7: 14 | AH7: =AF7*AG7 -> 0 | AJ7: 0 | AK7: =AI7*AJ7 -> 0 | AM7: 0 | AP7: ='1'!C17 -> 0 | AQ7: =2310/264 -> 8.75 | AR7: =AP7*AQ7 -> 0 | AS7: ='1'!C18 -> 0 | AT7: =1764/144 -> 12.25 | AU7: =AS7*AT7 -> 0 | AV7: ='1'!C21 -> 0 | AW7: 7.9166667 | AX7: =AV7*AW7 -> 0 | AY7: ='1'!C22 -> 0 | AZ7: =1175/120 -> 9.7916667 | BA7: =AY7*AZ7 -> 0 | BB7: ='1'!C26 -> 0 | BC7: =1960/120 -> 16.333333 | BD7: =BB7*BC7 -> 0 | BE7: ='1'!C27 -> 0 | BF7: =828/72 -> 11.5 | BG7: =BE7*BF7 -> 0 | BH7: ='1'!C28 -> 0 | BI7: 20 | BJ7: =BH7*BI7 -> 0 | BK7: ='1'!C23 -> 0 | BL7: 23 | BM7: =BK7*BL7 -> 0 | BN7: ='1'!C25 -> 0 | BO7: 12.5 | BP7: =BN7*BO7 -> 0 | BQ7: ='1'!C24 -> 0 | BR7: =306/24 -> 12.75 | BS7: =BQ7*BR7 -> 0 | BT7: ='1'!C19 -> 0 | BU7: =1089/36 -> 30.25 | BV7: =BT7*BU7 -> 0 | BW7: ='1'!C20 -> 0 | BX7: 15.916667 | BY7: =BW7*BX7 -> 0 | CA7: =D7+G7+J7+M7+P7+S7+V7+Y7+AB7+AE7+AH7+AK7+AN7+AR7+AU7+AX7+BA7+BD7+BG7+BJ7+BM7+BP7+BS7+BV7+BY7 -> 10920 | CD7: =CA7-CC7 -> 10920 | CF7: ='1'!W26 -> 0
A8: 45445 | B8: ='2'!C29 -> 0 | C8: =C7 -> 30 | D8: =B8*C8 -> 0 | E8: ='2'!C7 -> 150 | F8: 35 | G8: =E8*F8 -> 5250 | H8: ='2'!C8 -> 0 | I8: =I7 -> 8.5 | J8: =H8*I8 -> 0 | K8: ='2'!C15 -> 0 | L8: =L7 -> 18 | M8: =K8*L8 -> 0 | N8: ='2'!C9 -> 100 | O8: =O7 -> 7 | P8: =N8*O8 -> 700 | Q8: ='2'!C10 -> 0 | R8: =R7 -> 5.5 | S8: =Q8*R8 -> 0 | T8: ='2'!C11 -> 190 | U8: 8.5 | V8: =T8*U8 -> 1615 | W8: ='2'!C12 -> 60 | X8: 6 | Y8: =W8*X8 -> 360 | Z8: ='2'!C13 -> 40 | AA8: =AA7 -> 6 | AB8: =Z8*AA8 -> 240 | AC8: ='2'!C14 -> 60 | AD8: =1280/160 -> 8 | AE8: =AC8*AD8 -> 480 | AG8: =AG7 -> 14 | AH8: =AF8*AG8 -> 0 | AJ8: =AJ7 -> 0 | AK8: =AI8*AJ8 -> 0 | AM8: =AM7 -> 0 | AN8: =AL8*AM8 -> 0 | AP8: ='2'!C17 -> 0 | AQ8: =2310/264 -> 8.75 | AR8: =AP8*AQ8 -> 0 | AS8: ='2'!C18 -> 0 | AT8: =1764/144 -> 12.25 | AU8: =AS8*AT8 -> 0 | AV8: ='2'!C21 -> 0 | AW8: 7.9166667 | AX8: =AV8*AW8 -> 0 | AY8: ='2'!C22 -> 0 | AZ8: =1175/120 -> 9.7916667 | BA8: =AY8*AZ8 -> 0 | BB8: ='2'!C26 -> 0 | BC8: =1960/120 -> 16.333333 | BD8: =BB8*BC8 -> 0 | BE8: ='2'!C27 -> 0 | BF8: =828/72 -> 11.5 | BG8: =BE8*BF8 -> 0 | BH8: ='2'!C28 -> 0 | BI8: 20 | BJ8: =BH8*BI8 -> 0 | BK8: ='2'!C23 -> 0 | BL8: =BL7 -> 23 | BM8: =BK8*BL8 -> 0 | BN8: ='2'!C25 -> 0 | BO8: =BO7 -> 12.5 | BQ8: ='2'!C24 -> 0 | BR8: =306/24 -> 12.75 | BS8: =BQ8*BR8 -> 0 | BT8: ='2'!C19 -> 0 | BU8: =1089/36 -> 30.25 | BV8: =BT8*BU8 -> 0 | BW8: ='2'!C20 -> 0 | BX8: =BX7 -> 15.916667 | BY8: =BW8*BX8 -> 0 | CA8: =D8+G8+J8+M8+P8+S8+V8+Y8+AB8+AE8+AH8+AK8+AN8+AR8+AU8+AX8+BA8+BD8+BG8+BJ8+BM8+BP8+BS8+BV8+BY8 -> 8645 | CD8: =CA8-CC8 -> 8645 | CF8: ='2'!W26 -> 0
A9: 45446 | B9: ='3'!C29 -> 0 | C9: =C7 -> 30 | D9: =B9*C9 -> 0 | E9: ='3'!C7 -> 200 | F9: 35 | G9: =E9*F9 -> 7000 | H9: ='3'!C8 -> 20 | I9: =I7 -> 8.5 | J9: =H9*I9 -> 170 | K9: ='3'!C15 -> 50 | L9: =L7 -> 18 | M9: =K9*L9 -> 900 | N9: ='3'!C9 -> 100 | O9: =O7 -> 7 | P9: =N9*O9 -> 700 | Q9: ='3'!C10 -> 0 | R9: =R7 -> 5.5 | S9: =Q9*R9 -> 0 | T9: ='3'!C11 -> 200 | U9: 8.5 | V9: =T9*U9 -> 1700 | W9: ='3'!C12 -> 60 | X9: 6 | Y9: =W9*X9 -> 360 | Z9: ='3'!C13 -> 40 | AA9: =AA7 -> 6 | AB9: =Z9*AA9 -> 240 | AC9: ='3'!C14 -> 0 | AD9: =1280/160 -> 8 | AE9: =AC9*AD9 -> 0 | AG9: =AG7 -> 14 | AH9: =AF9*AG9 -> 0 | AJ9: =AJ7 -> 0 | AK9: =AI9*AJ9 -> 0 | AM9: =AM7 -> 0 | AN9: =AL9*AM9 -> 0 | AP9: ='3'!C17 -> 72 | AQ9: =2310/264 -> 8.75 | AR9: =AP9*AQ9 -> 630 | AS9: ='3'!C18 -> 144 | AT9: =1764/144 -> 12.25 | AU9: =AS9*AT9 -> 1764 | AV9: ='3'!C21 -> 0 | AW9: 7.9166667 | AX9: =AV9*AW9 -> 0 | AY9: ='3'!C22 -> 0 | AZ9: =1175/120 -> 9.7916667 | BA9: =AY9*AZ9 -> 0 | BB9: ='3'!C26 -> 0 | BC9: =1960/120 -> 16.333333 | BD9: =BB9*BC9 -> 0 | BE9: ='3'!C27 -> 0 | BF9: =828/72 -> 11.5 | BG9: =BE9*BF9 -> 0 | BH9: ='3'!C28 -> 0 | BI9: 20 | BJ9: =BH9*BI9 -> 0 | BK9: ='3'!C23 -> 0 | BL9: =BL7 -> 23 | BM9: =BK9*BL9 -> 0 | BN9: ='3'!C25 -> 0 | BO9: =BO7 -> 12.5 | BP9: =BN9*BO9 -> 0 | BQ9: ='3'!C24 -> 24 | BR9: =306/24 -> 12.75 | BS9: =BQ9*BR9 -> 306 | BT9: ='3'!C19 -> 0 | BU9: =1089/36 -> 30.25 | BV9: =BT9*BU9 -> 0 | BW9: ='3'!C20 -> 0 | BX9: =BX7 -> 15.916667 | BY9: =BW9*BX9 -> 0 | CA9: =D9+G9+J9+M9+P9+S9+V9+Y9+AB9+AE9+AH9+AK9+AN9+AR9+AU9+AX9+BA9+BD9+BG9+BJ9+BM9+BP9+BS9+BV9+BY9 -> 13770 | CD9: =CA9-CC9 -> 13770 | CF9: ='3'!W26 -> 0
A10: 45447 | B10: ='4'!C29 -> 0 | C10: =C7 -> 30 | D10: =B10*C10 -> 0 | E10: ='4'!C7 -> 450 | F10: 35 | G10: =E10*F10 -> 15750 | H10: ='4'!C8 -> 40 | I10: =I7 -> 8.5 | J10: =H10*I10 -> 340 | K10: ='4'!C15 -> 50 | L10: =L7 -> 18 | M10: =K10*L10 -> 900 | N10: ='4'!C9 -> 100 | O10: =O7 -> 7 | P10: =N10*O10 -> 700 | Q10: ='4'!C10 -> 0 | R10: =R7 -> 5.5 | S10: =Q10*R10 -> 0 | T10: ='4'!C11 -> 160 | U10: 8.5 | V10: =T10*U10 -> 1360 | W10: ='4'!C12 -> 100 | X10: 6 | Y10: =W10*X10 -> 600 | Z10: ='4'!C13 -> 80 | AA10: =AA7 -> 6 | AB10: =Z10*AA10 -> 480 | AC10: ='4'!C14 -> 0 | AD10: =1280/160 -> 8 | AE10: =AC10*AD10 -> 0 | AG10: =AG7 -> 14 | AH10: =AF10*AG10 -> 0 | AJ10: =AJ7 -> 0 | AK10: =AI10*AJ10 -> 0 | AM10: =AM7 -> 0 | AN10: =AL10*AM10 -> 0 | AP10: ='4'!C17 -> 0 | AQ10: =2310/264 -> 8.75 | AR10: =AP10*AQ10 -> 0 | AS10: ='4'!C18 -> 0 | AT10: =1764/144 -> 12.25 | AU10: =AS10*AT10 -> 0 | AV10: ='4'!C21 -> 0 | AW10: 7.9166667 | AX10: =AV10*AW10 -> 0 | AY10: ='4'!C22 -> 0 | AZ10: =1175/120 -> 9.7916667 | BA10: =AY10*AZ10 -> 0 | BB10: ='4'!C26 -> 0 | BC10: =1960/120 -> 16.333333 | BD10: =BB10*BC10 -> 0 | BE10: ='4'!C27 -> 0 | BF10: =828/72 -> 11.5 | BG10: =BE10*BF10 -> 0 | BH10: ='4'!C28 -> 0 | BI10: 20 | BJ10: =BH10*BI10 -> 0 | BK10: ='4'!C23 -> 0 | BL10: =BL7 -> 23 | BM10: =BK10*BL10 -> 0 | BN10: ='4'!C25 -> 0 | BO10: =BO7 -> 12.5 | BP10: =BN10*BO10 -> 0 | BQ10: ='4'!C24 -> 0 | BR10: =306/24 -> 12.75 | BS10: =BQ10*BR10 -> 0 | BT10: ='4'!C19 -> 0 | BU10: =1089/36 -> 30.25 | BV10: =BT10*BU10 -> 0 | BW10: ='4'!C20 -> 0 | BX10: =BX7 -> 15.916667 | BY10: =BW10*BX10 -> 0 | CA10: =D10+G10+J10+M10+P10+S10+V10+Y10+AB10+AE10+AH10+AK10+AN10+AR10+AU10+AX10+BA10+BD10+BG10+BJ10+BM10+BP10+BS10+BV10+BY10 -> 20130 | CD10: =CA10-CC10 -> 20130 | CF10: ='4'!W26 -> 0
A11: 45448 | B11: ='5'!C29 -> 0 | C11: =C7 -> 30 | D11: =B11*C11 -> 0 | E11: ='5'!C7 -> 0 | F11: 35 | G11: =E11*F11 -> 0 | H11: ='5'!C8 -> 0 | I11: =I7 -> 8.5 | J11: =H11*I11 -> 0 | K11: ='5'!C15 -> 0 | L11: =L7 -> 18 | M11: =K11*L11 -> 0 | N11: ='5'!C9 -> 0 | O11: =O7 -> 7 | P11: =N11*O11 -> 0 | Q11: ='5'!C10 -> 0 | R11: =R7 -> 5.5 | S11: =Q11*R11 -> 0 | T11: ='5'!C11 -> 235 | U11: 8.5 | V11: =T11*U11 -> 1997.5 | W11: ='5'!C12 -> 0 | X11: 6 | Y11: =W11*X11 -> 0 | Z11: ='5'!C13 -> 0 | AA11: =AA7 -> 6 | AB11: =Z11*AA11 -> 0 | AC11: ='5'!C14 -> 0 | AD11: =1280/160 -> 8 | AE11: =AC11*AD11 -> 0 | AG11: =AG7 -> 14 | AH11: =AF11*AG11 -> 0 | AJ11: =AJ7 -> 0 | AK11: =AI11*AJ11 -> 0 | AM11: =AM7 -> 0 | AN11: =AL11*AM11 -> 0 | AP11: ='5'!C17 -> 0 | AQ11: =2310/264 -> 8.75 | AR11: =AP11*AQ11 -> 0 | AS11: ='5'!C18 -> 0 | AT11: =1764/144 -> 12.25 | AU11: =AS11*AT11 -> 0 | AV11: ='5'!C21 -> 0 | AW11: 7.9166667 | AX11: =AV11*AW11 -> 0 | AY11: ='5'!C22 -> 0 | AZ11: =1175/120 -> 9.7916667 | BA11: =AY11*AZ11 -> 0 | BB11: ='5'!C26 -> 0 | BC11: =1960/120 -> 16.333333 | BD11: =BB11*BC11 -> 0 | BE11: ='5'!C27 -> 0 | BF11: =828/72 -> 11.5 | BG11: =BE11*BF11 -> 0 | BH11: ='5'!C28 -> 0 | BI11: 20 | BJ11: =BH11*BI11 -> 0 | BK11: ='5'!C23 -> 0 | BL11: =BL7 -> 23 | BM11: =BK11*BL11 -> 0 | BN11: ='5'!C25 -> 0 | BO11: =BO7 -> 12.5 | BP11: =BN11*BO11 -> 0 | BQ11: ='5'!C24 -> 0 | BR11: =306/24 -> 12.75 | BS11: =BQ11*BR11 -> 0 | BT11: ='5'!C19 -> 0 | BU11: =1089/36 -> 30.25 | BV11: =BT11*BU11 -> 0 | BW11: ='5'!C20 -> 0 | BX11: =BX7 -> 15.916667 | BY11: =BW11*BX11 -> 0 | CA11: =D11+G11+J11+M11+P11+S11+V11+Y11+AB11+AE11+AH11+AK11+AN11+AR11+AU11+AX11+BA11+BD11+BG11+BJ11+BM11+BP11+BS11+BV11+BY11 -> 1997.5 | CD11: =CA11-CC11 -> 1997.5 | CF11: ='5'!W26 -> 0
A12: 45449 | B12: ='6'!C29 -> 0 | C12: =C7 -> 30 | D12: =B12*C12 -> 0 | E12: ='6'!C7 -> 100 | F12: 35 | G12: =E12*F12 -> 3500 | H12: ='6'!C8 -> 0 | I12: =I7 -> 8.5 | J12: =H12*I12 -> 0 | K12: ='6'!C15 -> 0 | L12: =L7 -> 18 | M12: =K12*L12 -> 0 | N12: ='6'!C9 -> 150 | O12: =O7 -> 7 | P12: =N12*O12 -> 1050 | Q12: ='6'!C10 -> 0 | R12: =R7 -> 5.5 | S12: =Q12*R12 -> 0 | T12: ='6'!C11 -> 230 | U12: 8.5 | V12: =T12*U12 -> 1955 | W12: ='6'!C12 -> 40 | X12: 6 | Y12: =W12*X12 -> 240 | Z12: ='6'!C13 -> 40 | AA12: =AA7 -> 6 | AB12: =Z12*AA12 -> 240 | AC12: ='6'!C14 -> 20 | AD12: =1280/160 -> 8 | AE12: =AC12*AD12 -> 160 | AG12: =AG7 -> 14 | AH12: =AF12*AG12 -> 0 | AJ12: =AJ7 -> 0 | AK12: =AI12*AJ12 -> 0 | AM12: =AM7 -> 0 | AN12: =AL12*AM12 -> 0 | AP12: ='6'!C17 -> 0 | AQ12: =2310/264 -> 8.75 | AR12: =AP12*AQ12 -> 0 | AS12: ='6'!C18 -> 0 | AT12: =1764/144 -> 12.25 | AU12: =AS12*AT12 -> 0 | AV12: ='6'!C21 -> 0 | AW12: 7.9166667 | AX12: =AV12*AW12 -> 0 | AY12: ='6'!C22 -> 0 | AZ12: =1175/120 -> 9.7916667 | BA12: =AY12*AZ12 -> 0 | BB12: ='6'!C26 -> 0 | BC12: =1960/120 -> 16.333333 | BD12: =BB12*BC12 -> 0 | BE12: ='6'!C27 -> 0 | BF12: =828/72 -> 11.5 | BG12: =BE12*BF12 -> 0 | BH12: ='6'!C28 -> 0 | BI12: 20 | BJ12: =BH12*BI12 -> 0 | BK12: ='6'!C23 -> 0 | BL12: =BL7 -> 23 | BM12: =BK12*BL12 -> 0 | BN12: ='6'!C25 -> 0 | BO12: =BO7 -> 12.5 | BP12: =BN12*BO12 -> 0 | BQ12: ='6'!C24 -> 0 | BR12: =306/24 -> 12.75 | BS12: =BQ12*BR12 -> 0 | BT12: ='6'!C19 -> 0 | BU12: =1089/36 -> 30.25 | BV12: =BT12*BU12 -> 0 | BW12: ='6'!C20 -> 0 | BX12: =BX7 -> 15.916667 | BY12: =BW12*BX12 -> 0 | CA12: =D12+G12+J12+M12+P12+S12+V12+Y12+AB12+AE12+AH12+AK12+AN12+AR12+AU12+AX12+BA12+BD12+BG12+BJ12+BM12+BP12+BS12+BV12+BY12 -> 7145 | CD12: =CA12-CC12 -> 7145 | CF12: ='6'!W26 -> 0
A13: 45450 | B13: ='7'!C29 -> 0 | C13: =C7 -> 30 | D13: =B13*C13 -> 0 | E13: ='7'!C7 -> 200 | F13: 35 | G13: =E13*F13 -> 7000 | H13: ='7'!C8 -> 0 | I13: =I7 -> 8.5 | J13: =H13*I13 -> 0 | K13: ='7'!C15 -> 0 | L13: =L7 -> 18 | M13: =K13*L13 -> 0 | N13: ='7'!C9 -> 50 | O13: =O7 -> 7 | P13: =N13*O13 -> 350 | Q13: ='7'!C10 -> 0 | R13: =R7 -> 5.5 | S13: =Q13*R13 -> 0 | T13: ='7'!C11 -> 180 | U13: 8.5 | V13: =T13*U13 -> 1530 | W13: ='7'!C12 -> 40 | X13: 6 | Y13: =W13*X13 -> 240 | Z13: ='7'!C13 -> 50 | AA13: =AA7 -> 6 | AB13: =Z13*AA13 -> 300 | AC13: ='7'!C14 -> 0 | AD13: =1280/160 -> 8 | AE13: =AC13*AD13 -> 0 | AG13: =AG7 -> 14 | AH13: =AF13*AG13 -> 0 | AJ13: =AJ7 -> 0 | AK13: =AI13*AJ13 -> 0 | AM13: =AM7 -> 0 | AN13: =AL13*AM13 -> 0 | AP13: ='7'!C17 -> 24 | AQ13: =2310/264 -> 8.75 | AR13: =AP13*AQ13 -> 210 | AS13: ='7'!C18 -> 144 | AT13: =1764/144 -> 12.25 | AU13: =AS13*AT13 -> 1764 | AV13: ='7'!C21 -> 0 | AW13: 7.9166667 | AX13: =AV13*AW13 -> 0 | AY13: ='7'!C22 -> 0 | AZ13: =1175/120 -> 9.7916667 | BA13: =AY13*AZ13 -> 0 | BB13: ='7'!C26 -> 0 | BC13: =1960/120 -> 16.333333 | BD13: =BB13*BC13 -> 0 | BE13: ='7'!C27 -> 0 | BF13: =828/72 -> 11.5 | BG13: =BE13*BF13 -> 0 | BH13: ='7'!C28 -> 0 | BI13: 20 | BJ13: =BH13*BI13 -> 0 | BK13: ='7'!C23 -> 0 | BL13: =BL7 -> 23 | BM13: =BK13*BL13 -> 0 | BN13: ='7'!C25 -> 0 | BO13: =BO7 -> 12.5 | BP13: =BN13*BO13 -> 0 | BQ13: ='7'!C24 -> 0 | BR13: =306/24 -> 12.75 | BS13: =BQ13*BR13 -> 0 | BT13: ='7'!C19 -> 0 | BU13: =1089/36 -> 30.25 | BV13: =BT13*BU13 -> 0 | BW13: ='7'!C20 -> 0 | BX13: =BX7 -> 15.916667 | BY13: =BW13*BX13 -> 0 | CA13: =D13+G13+J13+M13+P13+S13+V13+Y13+AB13+AE13+AH13+AK13+AN13+AR13+AU13+AX13+BA13+BD13+BG13+BJ13+BM13+BP13+BS13+BV13+BY13 -> 11394 | CD13: =CA13-CC13 -> 11394 | CF13: ='7'!W26 -> 500
A14: TOTAL | B14: =SUM(B7:B13) -> 0 | D14: =SUM(D7:D13) -> 0 | E14: =SUM(E7:E13) -> 1350 | G14: =SUM(G7:G13) -> 47250 | H14: =SUM(H7:H13) -> 80 | J14: =SUM(J7:J13) -> 680 | K14: =SUM(K7:K13) -> 100 | M14: =SUM(M7:M13) -> 1800 | N14: =SUM(N7:N13) -> 500 | P14: =SUM(P7:P13) -> 3500 | Q14: =SUM(Q7:Q13) -> 0 | S14: =SUM(S7:S13) -> 0 | T14: =SUM(T7:T13) -> 1395 | V14: =SUM(V7:V13) -> 11857.5 | W14: =SUM(W7:W13) -> 300 | Y14: =SUM(Y7:Y13) -> 1800 | Z14: =SUM(Z7:Z13) -> 300 | AB14: =SUM(AB7:AB13) -> 1800 | AC14: =SUM(AC7:AC13) -> 80 | AE14: =SUM(AE7:AE13) -> 640 | AF14: =SUM(AF7:AF13) -> 0 | AH14: =SUM(AH7:AH13) -> 0 | AI14: =SUM(AI7:AI13) -> 0 | AK14: =SUM(AK7:AK13) -> 0 | AL14: =SUM(AL7:AL13) -> 0 | AN14: =SUM(AN7:AN13) -> 0 | AP14: =SUM(AP7:AP13) -> 96 | AR14: =SUM(AR7:AR13) -> 840 | AS14: =SUM(AS7:AS13) -> 288 | AU14: =SUM(AU7:AU13) -> 3528 | AV14: =SUM(AV7:AV13) -> 0 | AX14: =SUM(AX7:AX13) -> 0 | AY14: =SUM(AY7:AY13) -> 0 | BA14: =SUM(BA7:BA13) -> 0 | BB14: =SUM(BB7:BB13) -> 0 | BD14: =SUM(BD7:BD13) -> 0 | BE14: =SUM(BE7:BE13) -> 0 | BG14: =SUM(BG7:BG13) -> 0 | BH14: =SUM(BH7:BH13) -> 0 | BJ14: =SUM(BJ7:BJ13) -> 0 | BK14: =SUM(BK7:BK13) -> 0 | BM14: =SUM(BM7:BM13) -> 0 | BN14: =SUM(BN7:BN13) -> 0 | BP14: =SUM(BP7:BP13) -> 0 | BQ14: =SUM(BQ7:BQ13) -> 24 | BS14: =SUM(BS7:BS13) -> 306 | BT14: =SUM(BT7:BT13) -> 0 | BV14: =SUM(BV7:BV13) -> 0 | BW14: =SUM(BW7:BW13) -> 0 | BY14: =SUM(BY7:BY13) -> 0 | CA14: =SUM(CA7:CA13) -> 74001.5 | CB14: =G14+J14+P14+S14+V14+Y14+AB14+AE14+AR14+AU14+AX14+BA14+BD14+BS14 -> 72201.5 | CD14: =SUM(CD7:CD13) -> 74001.5 | CF14: =SUM(CF7:CF13) -> 500
A17: WEEK- 2 | B17: =B5 -> PREMIUM CUT | E17: SPECIAL CUT | H17: NGOHIONG | K17: =K5 -> Chicken Fillet | N17: NECK | Q17: SIOMAI | T17: RICE | W17: BOLA-BOLA | Z17: LUMPIA | AC17: ATSARA | AF17: SIOPAO | AP17: 8OZ | AS17: 12 OZ | AV17: WATER 350 ML | AY17: WATER 500 ML | BB17: PANALO | BE17: =BE5 -> swakto | BH17: =BH5 -> Calamansi Juice | BK17: =BK5 -> GATORADE | BN17: TROPICANA | BQ17: STING | BT17: =BT5 -> 1 LITER | BW17: =BW5 -> 1.5 L | CA17: TOTAL
A18: DATE | B18: QTY | C18: UP | D18: AMOUNT | E18: QTY | F18: UP | G18: AMOUNT | H18: QTY | I18: UP | J18: AMOUNT | K18: QTY | L18: UP | M18: AMOUNT | N18: QTY | O18: UP | P18: AMOUNT | Q18: QTY | R18: UP | S18: AMOUNT | T18: QTY | U18: UP | V18: AMOUNT | W18: QTY | X18: UP | Y18: AMOUNT | Z18: QTY | AA18: UP | AB18: AMOUNT | AC18: QTY | AD18: UP | AE18: AMOUNT | AF18: QTY | AG18: UP | AH18: AMOUNT | AI18: QTY | AJ18: UP | AK18: AMOUNT | AL18: QTY | AM18: UP | AN18: AMOUNT | AP18: QTY | AQ18: UP | AR18: AMOUNT | AS18: QTY | AT18: UP | AU18: AMOUNT | AV18: QTY | AW18: UP | AX18: AMOUNT | AY18: QTY | AZ18: UP | BA18: AMOUNT | BB18: QTY | BC18: UP | BD18: AMOUNT | BE18: QTY | BF18: UP | BG18: AMOUNT | BH18: QTY | BI18: UP | BJ18: AMOUNT | BK18: QTY | BL18: UP | BM18: AMOUNT | BN18: QTY | BO18: UP | BP18: AMOUNT | BQ18: QTY | BR18: UP | BS18: AMOUNT | BT18: QTY | BU18: UP | BV18: AMOUNT | BW18: QTY | BX18: UP | BY18: AMOUNT | CA18: AMOUNT
A19: 45451 | B19: ='8'!C29 -> 0 | C19: =C7 -> 30 | D19: =B19*C19 -> 0 | E19: ='8'!C7 -> 150 | F19: 35 | G19: =E19*F19 -> 5250 | H19: ='8'!C8 -> 0 | I19: =I7 -> 8.5 | J19: =H19*I19 -> 0 | K19: ='8'!C15 -> 0 | L19: =L7 -> 18 | M19: =K19*L19 -> 0 | N19: ='8'!C9 -> 50 | O19: =O7 -> 7 | P19: =N19*O19 -> 350 | Q19: ='8'!C10 -> 0 | R19: =R7 -> 5.5 | S19: =Q19*R19 -> 0 | T19: ='8'!C11 -> 180 | U19: 8.5 | V19: =T19*U19 -> 1530 | W19: ='8'!C12 -> 40 | X19: 6 | Y19: =W19*X19 -> 240 | Z19: ='8'!C13 -> 30 | AA19: =AA7 -> 6 | AB19: =Z19*AA19 -> 180 | AC19: ='8'!C14 -> 0 | AD19: =1280/160 -> 8 | AE19: =AC19*AD19 -> 0 | AG19: =AG7 -> 14 | AH19: =AF19*AG19 -> 0 | AJ19: =AJ7 -> 0 | AK19: =AI19*AJ19 -> 0 | AM19: =AM7 -> 0 | AN19: =AL19*AM19 -> 0 | AP19: ='8'!C17 -> 0 | AQ19: =2310/264 -> 8.75 | AR19: =AP19*AQ19 -> 0 | AS19: ='8'!C18 -> 0 | AT19: =1764/144 -> 12.25 | AU19: =AS19*AT19 -> 0 | AV19: ='8'!C21 -> 0 | AW19: 7.9166667 | AX19: =AV19*AW19 -> 0 | AY19: ='8'!C22 -> 0 | AZ19: =1175/120 -> 9.7916667 | BA19: =AY19*AZ19 -> 0 | BB19: ='8'!C26 -> 0 | BC19: =3920/240 -> 16.333333 | BD19: =BB19*BC19 -> 0 | BE19: ='8'!C27 -> 0 | BF19: =690/60 -> 11.5 | BG19: =BE19*BF19 -> 0 | BH19: ='8'!C28 -> 0 | BI19: 20 | BJ19: =BH19*BI19 -> 0 | BK19: ='8'!C23 -> 0 | BL19: =BL7 -> 23 | BM19: =BK19*BL19 -> 0 | BN19: ='8'!C25 -> 0 | BO19: =BO7 -> 12.5 | BP19: =BN19*BO19 -> 0 | BQ19: ='8'!C24 -> 0 | BR19: =306/24 -> 12.75 | BS19: =BQ19*BR19 -> 0 | BT19: ='8'!C19 -> 0 | BU19: =363/12 -> 30.25 | BV19: =BT19*BU19 -> 0 | BW19: ='8'!C20 -> 0 | BX19: =BX7 -> 15.916667 | BY19: =BW19*BX19 -> 0 | CA19: =D19+G19+J19+M19+P19+S19+V19+Y19+AB19+AE19+AH19+AK19+AN19+AR19+AU19+AX19+BA19+BD19+BG19+BJ19+BM19+BP19+BS19+BV19+BY19 -> 7550 | CD19: =CA19-CC19 -> 7550 | CF19: ='8'!W26 -> 0
A20: 45452 | B20: ='9'!C29 -> 0 | C20: =C7 -> 30 | D20: =B20*C20 -> 0 | E20: ='9'!C7 -> 200 | F20: 35 | G20: =E20*F20 -> 7000 | H20: ='9'!C8 -> 20 | I20: =I7 -> 8.5 | J20: =H20*I20 -> 170 | K20: ='9'!C15 -> 0 | L20: =L7 -> 18 | M20: =K20*L20 -> 0 | N20: ='9'!C9 -> 50 | O20: =O7 -> 7 | P20: =N20*O20 -> 350 | Q20: ='9'!C10 -> 0 | R20: =R7 -> 5.5 | S20: =Q20*R20 -> 0 | T20: ='9'!C11 -> 180 | U20: 8.5 | V20: =T20*U20 -> 1530 | W20: ='9'!C12 -> 40 | X20: 6 | Y20: =W20*X20 -> 240 | Z20: ='9'!C13 -> 20 | AA20: =AA7 -> 6 | AB20: =Z20*AA20 -> 120 | AC20: ='9'!C14 -> 0 | AD20: =1280/160 -> 8 | AE20: =AC20*AD20 -> 0 | AG20: =AG7 -> 14 | AH20: =AF20*AG20 -> 0 | AJ20: =AJ7 -> 0 | AK20: =AI20*AJ20 -> 0 | AM20: =AM7 -> 0 | AN20: =AL20*AM20 -> 0 | AP20: ='9'!C17 -> 0 | AQ20: =2310/264 -> 8.75 | AR20: =AP20*AQ20 -> 0 | AS20: ='9'!C18 -> 0 | AT20: =1764/144 -> 12.25 | AU20: =AS20*AT20 -> 0 | AV20: ='9'!C21 -> 0 | AW20: 7.9166667 | AX20: =AV20*AW20 -> 0 | AY20: ='9'!C22 -> 0 | AZ20: =1175/120 -> 9.7916667 | BA20: =AY20*AZ20 -> 0 | BB20: ='9'!C26 -> 0 | BC20: =3920/240 -> 16.333333 | BD20: =BB20*BC20 -> 0 | BE20: ='9'!C27 -> 0 | BF20: =690/60 -> 11.5 | BG20: =BE20*BF20 -> 0 | BH20: ='9'!C28 -> 0 | BI20: 20 | BJ20: =BH20*BI20 -> 0 | BK20: ='9'!C23 -> 0 | BL20: =BL7 -> 23 | BM20: =BK20*BL20 -> 0 | BN20: ='9'!C25 -> 0 | BO20: =BO7 -> 12.5 | BP20: =BN20*BO20 -> 0 | BQ20: ='9'!C24 -> 0 | BR20: =306/24 -> 12.75 | BS20: =BQ20*BR20 -> 0 | BT20: ='9'!C19 -> 0 | BU20: =363/12 -> 30.25 | BV20: =BT20*BU20 -> 0 | BW20: ='9'!C20 -> 0 | BX20: =BX7 -> 15.916667 | BY20: =BW20*BX20 -> 0 | CA20: =D20+G20+J20+M20+P20+S20+V20+Y20+AB20+AE20+AH20+AK20+AN20+AR20+AU20+AX20+BA20+BD20+BG20+BJ20+BM20+BP20+BS20+BV20+BY20 -> 9410 | CD20: =CA20-CC20 -> 9410 | CF20: ='9'!W26 -> 0
A21: 45453 | B21: ='10'!C29 -> 0 | C21: =C7 -> 30 | D21: =B21*C21 -> 0 | E21: ='10'!C7 -> 200 | F21: 35 | G21: =E21*F21 -> 7000 | H21: ='10'!C8 -> 20 | I21: =I7 -> 8.5 | J21: =H21*I21 -> 170 | K21: ='10'!C15 -> 50 | L21: =L7 -> 18 | M21: =K21*L21 -> 900 | N21: ='10'!C9 -> 100 | O21: =O7 -> 7 | P21: =N21*O21 -> 700 | Q21: ='10'!C10 -> 0 | R21: =R7 -> 5.5 | S21: =Q21*R21 -> 0 | T21: ='10'!C11 -> 190 | U21: 8.5 | V21: =T21*U21 -> 1615 | W21: ='10'!C12 -> 40 | X21: 6 | Y21: =W21*X21 -> 240 | Z21: ='10'!C13 -> 40 | AA21: =AA7 -> 6 | AB21: =Z21*AA21 -> 240 | AC21: ='10'!C14 -> 0 | AD21: =1280/160 -> 8 | AE21: =AC21*AD21 -> 0 | AG21: =AG7 -> 14 | AH21: =AF21*AG21 -> 0 | AJ21: =AJ7 -> 0 | AK21: =AI21*AJ21 -> 0 | AM21: =AM7 -> 0 | AN21: =AL21*AM21 -> 0 | AP21: ='10'!C17 -> 48 | AQ21: =2310/264 -> 8.75 | AR21: =AP21*AQ21 -> 420 | AS21: ='10'!C18 -> 120 | AT21: =1764/144 -> 12.25 | AU21: =AS21*AT21 -> 1470 | AV21: ='10'!C21 -> 0 | AW21: 7.9166667 | AX21: =AV21*AW21 -> 0 | AY21: ='10'!C22 -> 0 | AZ21: =1175/120 -> 9.7916667 | BA21: =AY21*AZ21 -> 0 | BB21: ='10'!C26 -> 0 | BC21: =3920/240 -> 16.333333 | BD21: =BB21*BC21 -> 0 | BE21: ='10'!C27 -> 0 | BF21: =690/60 -> 11.5 | BG21: =BE21*BF21 -> 0 | BH21: ='10'!C28 -> 0 | BI21: 20 | BJ21: =BH21*BI21 -> 0 | BK21: ='10'!C23 -> 0 | BL21: =BL7 -> 23 | BM21: =BK21*BL21 -> 0 | BN21: ='10'!C25 -> 0 | BO21: =BO7 -> 12.5 | BP21: =BN21*BO21 -> 0 | BQ21: ='10'!C24 -> 0 | BR21: =306/24 -> 12.75 | BS21: =BQ21*BR21 -> 0 | BT21: ='10'!C19 -> 0 | BU21: =363/12 -> 30.25 | BV21: =BT21*BU21 -> 0 | BW21: ='10'!C20 -> 0 | BX21: =BX7 -> 15.916667 | BY21: =BW21*BX21 -> 0 | CA21: =D21+G21+J21+M21+P21+S21+V21+Y21+AB21+AE21+AH21+AK21+AN21+AR21+AU21+AX21+BA21+BD21+BG21+BJ21+BM21+BP21+BS21+BV21+BY21 -> 12755 | CD21: =CA21-CC21 -> 12755 | CF21: ='10'!W26 -> 0
A22: 45454 | B22: ='11'!C29 -> 0 | C22: =C7 -> 30 | D22: =B22*C22 -> 0 | E22: ='11'!C7 -> 500 | F22: 35 | G22: =E22*F22 -> 17500 | H22: ='11'!C8 -> 40 | I22: 8.5 | J22: =H22*I22 -> 340 | K22: ='11'!C15 -> 0 | L22: =L7 -> 18 | M22: =K22*L22 -> 0 | N22: ='11'!C9 -> 150 | O22: =O7 -> 7 | P22: =N22*O22 -> 1050 | Q22: ='11'!C10 -> 0 | R22: =R7 -> 5.5 | S22: =Q22*R22 -> 0 | T22: ='11'!C11 -> 190 | U22: 8.5 | V22: =T22*U22 -> 1615 | W22: ='11'!C12 -> 80 | X22: 6 | Y22: =W22*X22 -> 480 | Z22: ='11'!C13 -> 80 | AA22: =AA7 -> 6 | AB22: =Z22*AA22 -> 480 | AC22: ='11'!C14 -> 26 | AD22: =1280/160 -> 8 | AE22: =AC22*AD22 -> 208 | AG22: =AG7 -> 14 | AH22: =AF22*AG22 -> 0 | AJ22: =AJ7 -> 0 | AK22: =AI22*AJ22 -> 0 | AM22: =AM7 -> 0 | AN22: =AL22*AM22 -> 0 | AP22: ='11'!C17 -> 0 | AQ22: =2310/264 -> 8.75 | AR22: =AP22*AQ22 -> 0 | AS22: ='11'!C18 -> 0 | AT22: =1764/144 -> 12.25 | AU22: =AS22*AT22 -> 0 | AV22: ='11'!C21 -> 0 | AW22: 7.9166667 | AX22: =AV22*AW22 -> 0 | AY22: ='11'!C22 -> 0 | AZ22: =1175/120 -> 9.7916667 | BA22: =AY22*AZ22 -> 0 | BB22: ='11'!C26 -> 0 | BC22: =3920/240 -> 16.333333 | BD22: =BB22*BC22 -> 0 | BE22: ='11'!C27 -> 0 | BF22: =690/60 -> 11.5 | BG22: =BE22*BF22 -> 0 | BH22: ='11'!C28 -> 0 | BI22: 20 | BJ22: =BH22*BI22 -> 0 | BK22: ='11'!C23 -> 0 | BL22: =BL7 -> 23 | BM22: =BK22*BL22 -> 0 | BN22: ='11'!C25 -> 0 | BO22: =BO7 -> 12.5 | BP22: =BN22*BO22 -> 0 | BQ22: ='11'!C24 -> 0 | BR22: =306/24 -> 12.75 | BS22: =BQ22*BR22 -> 0 | BT22: ='11'!C19 -> 0 | BU22: =363/12 -> 30.25 | BV22: =BT22*BU22 -> 0 | BW22: ='11'!C20 -> 0 | BX22: =BX7 -> 15.916667 | BY22: =BW22*BX22 -> 0 | CA22: =D22+G22+J22+M22+P22+S22+V22+Y22+AB22+AE22+AH22+AK22+AN22+AR22+AU22+AX22+BA22+BD22+BG22+BJ22+BM22+BP22+BS22+BV22+BY22 -> 21673 | CD22: =CA22-CC22 -> 21673 | CF22: ='11'!W26 -> 0
A23: 45455 | B23: ='12'!C29 -> 0 | C23: =C7 -> 30 | D23: =B23*C23 -> 0 | E23: ='12'!C7 -> 0 | F23: 35 | G23: =E23*F23 -> 0 | H23: ='12'!C8 -> 0 | I23: 8.5 | J23: =H23*I23 -> 0 | K23: ='12'!C15 -> 0 | L23: =L7 -> 18 | M23: =K23*L23 -> 0 | N23: ='12'!C9 -> 0 | O23: =O7 -> 7 | P23: =N23*O23 -> 0 | Q23: ='12'!C10 -> 0 | R23: =R7 -> 5.5 | S23: =Q23*R23 -> 0 | T23: ='12'!C11 -> 180 | U23: 8.5 | V23: =T23*U23 -> 1530 | W23: ='12'!C12 -> 0 | X23: 6 | Y23: =W23*X23 -> 0 | Z23: ='12'!C13 -> 0 | AA23: =AA7 -> 6 | AB23: =Z23*AA23 -> 0 | AC23: ='12'!C14 -> 0 | AD23: =1280/160 -> 8 | AE23: =AC23*AD23 -> 0 | AG23: =AG7 -> 14 | AH23: =AF23*AG23 -> 0 | AJ23: =AJ7 -> 0 | AK23: =AI23*AJ23 -> 0 | AM23: =AM7 -> 0 | AN23: =AL23*AM23 -> 0 | AP23: ='12'!C17 -> 0 | AQ23: =2310/264 -> 8.75 | AR23: =AP23*AQ23 -> 0 | AS23: ='12'!C18 -> 0 | AT23: =1764/144 -> 12.25 | AU23: =AS23*AT23 -> 0 | AV23: ='12'!C21 -> 0 | AW23: 7.9166667 | AX23: =AV23*AW23 -> 0 | AY23: ='12'!C22 -> 0 | AZ23: =1175/120 -> 9.7916667 | BA23: =AY23*AZ23 -> 0 | BB23: ='12'!C26 -> 0 | BC23: =3920/240 -> 16.333333 | BD23: =BB23*BC23 -> 0 | BE23: ='12'!C27 -> 0 | BF23: =840/72 -> 11.666667 | BG23: =BE23*BF23 -> 0 | BH23: ='12'!C28 -> 0 | BI23: 20 | BJ23: =BH23*BI23 -> 0 | BK23: ='12'!C23 -> 0 | BL23: =BL7 -> 23 | BM23: =BK23*BL23 -> 0 | BN23: ='12'!C25 -> 0 | BO23: =BO7 -> 12.5 | BP23: =BN23*BO23 -> 0 | BQ23: ='12'!C24 -> 0 | BR23: =306/24 -> 12.75 | BS23: =BQ23*BR23 -> 0 | BT23: ='12'!C19 -> 0 | BU23: =363/12 -> 30.25 | BV23: =BT23*BU23 -> 0 | BW23: ='12'!C20 -> 0 | BX23: =BX7 -> 15.916667 | BY23: =BW23*BX23 -> 0 | CA23: =D23+G23+J23+M23+P23+S23+V23+Y23+AB23+AE23+AH23+AK23+AN23+AR23+AU23+AX23+BA23+BD23+BG23+BJ23+BM23+BP23+BS23+BV23+BY23 -> 1530 | CD23: =CA23-CC23 -> 1530 | CF23: ='12'!W26 -> 0
