Workbook

Sheet Sheet4
B1: VITERBO FOODS OPC - CRISPY KING
B2: SALES COMPARISON
A4: 1 | B4: AYUNGON 2 | C4: 46023 | D4: 46054 | E4: 46082
B5: GROSS SALES | C5: 575689.5 | D5: 494977.5 | E5: 519613.5
B6: COST OF GOOGS | C6: 385184.17 | D6: 331160.57 | E6: 347500.32
B7: OPEX | C7: 141054.7 | D7: 135657.29 | E7: 126503.24
B8: NET INCOME | C8: =C5-C6-C7 -> 49450.63 | D8: =D5-D6-D7 -> 28159.64 | E8: =E5-E6-E7 -> 45609.94
A11: 2 | B11: AYUNGON 1 | C11: 46023 | D11: 46054 | E11: 46082
B12: GROSS SALES | C12: 824216 | D12: 668379 | E12: 730344
B13: COST OF GOOGS | C13: 552617.61 | D13: 448218.2 | E13: 489400.4
B14: OPEX | C14: 207819 | D14: 203708.17 | E14: 176377.34
B15: NET INCOME | C15: =C12-C13-C14 -> 63779.39 | D15: =D12-D13-D14 -> 16452.63 | E15: =E12-E13-E14 -> 64566.26
A18: 3 | B18: BACONG 1 | C18: 46023 | D18: 46054 | E18: 46082
B19: GROSS SALES | C19: 610111 | D19: 545964.5 | E19: 612575
B20: COST OF GOOGS | C20: 411472.29 | D20: 368801.04 | E20: 412999.13
B21: OPEX | C21: 156442.81 | D21: 167634.74 | E21: 143738.43
B22: NET INCOME | C22: =C19-C20-C21 -> 42195.9 | D22: =D19-D20-D21 -> 9528.72 | E22: =E19-E20-E21 -> 55837.44
A25: 4 | B25: BACONG 2 | C25: 46023 | D25: 46054 | E25: 46082
B26: GROSS SALES | C26: 304710.5 | D26: 288500 | E26: 321537
B27: COST OF GOOGS | C27: 203245.08 | D27: 193568.3 | E27: 214530.92
B28: OPEX | C28: 93880.29 | D28: 99903.41 | E28: 89396.54
B29: NET INCOME | C29: =C26-C27-C28 -> 7585.13 | D29: =D26-D27-D28 -> -4971.71 | E29: =E26-E27-E28 -> 17609.54
A32: 5 | B32: BAGACAY | C32: 46023 | D32: 46054 | E32: 46082
B33: GROSS SALES | C33: 550265 | D33: 505422 | E33: 569205
B34: COST OF GOOGS | C34: 369484.17 | D34: 338901.17 | E34: 382404.08
B35: OPEX | C35: 176413.58 | D35: 161950.04 | E35: 159564.85
B36: NET INCOME | C36: =C33-C34-C35 -> 4367.25 | D36: =D33-D34-D35 -> 4570.79 | E36: =E33-E34-E35 -> 27236.07
A39: 6 | B39: BAYAWAN | C39: 46023 | D39: 46054 | E39: 46082
B40: GROSS SALES | C40: 623237 | D40: 519687.5 | E40: 560768
B41: COST OF GOOGS | C41: 419147.42 | D41: 349199.05 | E41: 376312.23
B42: OPEX | C42: 182544.55 | D42: 136610.83 | E42: 150903.62
B43: NET INCOME | C43: =C40-C41-C42 -> 21545.03 | D43: =D40-D41-D42 -> 33877.62 | E43: =E40-E41-E42 -> 33552.15
A46: 7 | B46: BINDOY 1 | C46: 46023 | D46: 46054 | E46: 46082
B47: GROSS SALES | C47: 1092355 | D47: 949506.5 | E47: 1085109
B48: COST OF GOOGS | C48: 740138.61 | D48: 643565.89 | E48: 734897.52
B49: OPEX | C49: 232540.1 | D49: 209121.08 | E49: 207575.54
B50: NET INCOME | C50: =C47-C48-C49 -> 119676.29 | D50: =D47-D48-D49 -> 96819.53 | E50: =E47-E48-E49 -> 142635.94
A53: 8 | B53: BINDOY 2 | C53: 46023 | D53: 46054 | E53: 46082
B54: GROSS SALES | C54: 468779 | D54: 389125.5 | E54: 443250
B55: COST OF GOOGS | C55: 316349.25 | D55: 263201.5 | E55: 301039.26
B56: OPEX | C56: 128365 | D56: 116265 | E56: 109885.68
B57: NET INCOME | C57: =C54-C55-C56 -> 24064.75 | D57: =D54-D55-D56 -> 9659 | E57: =E54-E55-E56 -> 32325.06
A60: 9 | B60: CADIZ 3 | C60: 46023 | D60: 46054 | E60: 46082
B61: GROSS SALES | C61: 641725 | D61: 417047 | E61: 447154
B62: COST OF GOOGS | C62: 427735.27 | D62: 277927.56 | E62: 298492.17
B63: OPEX | C63: 175930.15 | D63: 135523.47 | E63: 130760
B64: NET INCOME | C64: =C61-C62-C63 -> 38059.58 | D64: =D61-D62-D63 -> 3595.97 | E64: =E61-E62-E63 -> 17901.83
A67: 10 | B67: DARO | C67: 46023 | D67: 46054 | E67: 46082
B68: GROSS SALES | C68: 927633.5 | D68: 857516 | E68: 880472.5
B69: COST OF GOOGS | C69: 633026.54 | D69: 585143.92 | E69: 600584.21
B70: OPEX | C70: 233539.1 | D70: 184402.95 | E70: 196438.25
B71: NET INCOME | C71: =C68-C69-C70 -> 61067.86 | D71: =D68-D69-D70 -> 87969.13 | E71: =E68-E69-E70 -> 83450.04
A74: 11 | B74: GUIHULNGAN | C74: 46023 | D74: 46054 | E74: 46082
B75: GROSS SALES | C75: 635621.5 | D75: 518457 | E75: 611948
B76: COST OF GOOGS | C76: 426238.17 | D76: 348023.98 | E76: 411984.75
B77: OPEX | C77: 199432.38 | D77: 146817.63 | E77: 179091.17
B78: NET INCOME | C78: =C75-C76-C77 -> 9950.95 | D78: =D75-D76-D77 -> 23615.39 | E78: =E75-E76-E77 -> 20872.08
A81: 12 | B81: JIMALALUD | C81: 46023 | D81: 46054 | E81: 46082
B82: GROSS SALES | C82: 655174.5 | D82: 441305 | E82: 471839.5
B83: COST OF GOOGS | C83: 436893.86 | D83: 294338.75 | E83: 312389.29
B84: OPEX | C84: 153013.24 | D84: 127769.13 | E84: 130929.22
B85: NET INCOME | C85: =C82-C83-C84 -> 65267.4 | D85: =D82-D83-D84 -> 19197.12 | E85: =E82-E83-E84 -> 28520.99
A88: 13 | B88: JUNOB | C88: 46023 | D88: 46054 | E88: 46082
B89: GROSS SALES | C89: 510732 | D89: 459714 | E89: 476253.5
B90: COST OF GOOGS | C90: 348854.75 | D90: 313454.75 | E90: 324943.64
B91: OPEX | C91: 160397.11 | D91: 151486.71 | E91: 139775
B92: NET INCOME | C92: =C89-C90-C91 -> 1480.14 | D92: =D89-D90-D91 -> -5227.46 | E92: =E89-E90-E91 -> 11534.86
A95: 14 | B95: LARENA | C95: 46023 | D95: 46054 | E95: 46082
B96: GROSS SALES | C96: 540963 | D96: 478890 | E96: 495109
B97: COST OF GOOGS | C97: 359062.46 | D97: 318786.13 | E97: 329923.08
B98: OPEX | C98: 184185.17 | D98: 154773.91 | E98: 150503.47
B99: NET INCOME | C99: =C96-C97-C98 -> -2284.63 | D99: =D96-D97-D98 -> 5329.96 | E99: =E96-E97-E98 -> 14682.45
A102: 15 | B102: LOCSIN | C102: 46023 | D102: 46054 | E102: 46082
B103: GROSS SALES | C103: 1716607 | D103: 1523258.5 | E103: 1752146.5
B104: COST OF GOOGS | C104: 1158880.2 | D104: 1027295.8 | E104: 1181854.8
B105: OPEX | C105: 439987.32 | D105: 331234.45 | E105: 431592.44
B106: NET INCOME | C106: =C103-C104-C105 -> 117739.5 | D106: =D103-D104-D105 -> 164728.21 | E106: =E103-E104-E105 -> 138699.28
A109: 16 | B109: MABINAY 1 | C109: 46023 | D109: 46054 | E109: 46082
B110: GROSS SALES | C110: 1059917 | D110: 865277.5 | E110: 922653
B111: COST OF GOOGS | C111: 710921.03 | D111: 576217.25 | E111: 614717.25
B112: OPEX | C112: 268538.78 | D112: 227158.19 | E112: 231183.96
B113: NET INCOME | C113: =C110-C111-C112 -> 80457.19 | D113: =D110-D111-D112 -> 61902.06 | E113: =E110-E111-E112 -> 76751.79
A116: 17 | B116: MABINAY 2 | C116: 45931 | D116: 45962 | E116: 45992
B117: GROSS SALES | C117: 448374 | D117: 459157 | E117: 527270
B118: COST OF GOOGS | C118: 299552.6 | D118: 305178.86 | E118: 353757.1
B119: OPEX | C119: 130421.8 | D119: 177032.68 | E119: 136718.27
B120: NET INCOME | C120: =C117-C118-C119 -> 18399.6 | D120: =D117-D118-D119 -> -23054.54 | E120: =E117-E118-E119 -> 36794.63

Sheet JAN
A1: CRISPY KING FRANCHISE PERFORMANCE REPORT
A3: MONTH 2026 - AREA/REGION | BU3: CONSOLIDATED REPORT FOR THE MONTH OF JANUARY 2026
G5: DO NOT EDIT! | J5: DO NOT EDIT! | M5: DO NOT EDIT! | P5: DO NOT EDIT! | S5: DO NOT EDIT! | V5: DO NOT EDIT! | Y5: DO NOT EDIT! | AB5: DO NOT EDIT! | AE5: DO NOT EDIT! | AH5: DO NOT EDIT! | AK5: DO NOT EDIT! | AN5: DO NOT EDIT! | AR5: DO NOT EDIT! | AU5: DO NOT EDIT! | AX5: ! | AZ5: CAUTION! AUTO-FORMULA! DO NOT EDIT! | BI5: CAUTION! AUTO-FORMULA! DO NOT EDIT! | BV5: DO NOT EDIT! | CF5: CAUTION! AUTO-FORMULA! DO NOT EDIT!
A6: GROSS RANK | B6: MAN POWER | C6: BRANCH | D6: OWNER | E6: SALES SUPERVISOR | F6: QUANTITY SOLD | I6: S-CUT | L6: J-CUT | O6: RICE | R6: NECK(PCS) | U6: LUMPIA | X6: NGOHIONG | AA6: BOLA2X | AD6: C-FILLET | AG6: SIOMAI | AJ6: ATSARA (15) | AM6: ATSARA (12) | AP6: TOTAL OTHER PRODUCT | AW6: OTHER DRINKS SOLD | AX6: TOTAL QTY SOLD S.DRINKSPCS) | AZ6: CHICKEN VS RICE (50%) | BA6: CHICKEN VS OTHER PRODUCTS (20%) | BB6: RICE VS DRINKS (40%) | BC6: TOTAL AMOUNT FOR LPG % | BD6: TOTAL AMOUNT FOR BREADING% | BE6: TOTAL AMOUNT FOR OIL % | BF6: TOTAL AMOUNT FOR SAUCE % | BG6: TOTAL GROSS SALES | BH6: COST OF GOODS SOLD | BI6: COGS (%) | BJ6: TOTAL AMOUNT USAGES | BK6: USAGES (%) | BL6: MAN POWER | BM6: SALARY | BN6: SALARY (%) | BO6: OVERTIME | BP6: OVERTIME (%) | BQ6: RENT | BR6: RENT (%) | BS6: OPERATIONAL EXPENSES | BT6: OPERATION (%) | BU6: TOTAL OPEX | BV6: OPEX (%) | BW6: NET INCOME | BX6: NET (%) | BY6: NON - SALES ITEM | CK6: 20% ROYALTY SHARE
F7: CHICKEN 40(PCS) | G7: UNIT PRICE | H7: TOTAL AMOUNT | I7: QNTY | J7: UNIT PRICE | K7: TOTAL AMOUNT | L7: J -CUT 60 (PCS) | M7: UNIT PRICE | N7: TOTAL AMOUNT | O7: RICE(PCS) | P7: UNIT PRICE | Q7: TOTAL AMOUNT | R7: NECK(PCS) | S7: UNIT PRICE | T7: TOTAL AMOUNT | U7: LUMPIA(PCS) | V7: UNIT PRICE | W7: TOTAL AMOUNT | X7: NGOHIONG(PCS) | Y7: UNIT PRICE | Z7: TOTAL AMOUNT | AA7: BOLA2X(PCS) | AB7: UNIT PRICE | AC7: TOTAL AMOUNT | AD7: C. FILLET(PCS) | AE7: UNIT PRICE | AF7: TOTAL AMOUNT | AG7: SIOMAI(PCS) | AH7: UNIT PRICE | AI7: TOTAL AMOUNT | AJ7: ATSARA( 15 ) | AK7: UNIT PRICE | AL7: TOTAL AMOUNT | AM7: ATSARA( 12 ) | AN7: UNIT PRICE | AO7: TOTAL AMOUNT | AQ7: 1 LITER | AR7: PCS *4 | AS7: TOTAL PCS | AT7: 1.5 LITER | AU7: PCS * 6 | AV7: TOTAL PCS | AY7: TOTAL AMOUNT | BY7: LPG | BZ7: BREADING | CA7: OIL | CB7: SAUCE | CC7: SALARY | CD7: OVERTIME | CE7: RENT | CF7: LPG | CG7: BREADING | CH7: OIL | CI7: SAUCE | CJ7: SALARY
A8: 1 | B8: 4 | C8: AYUNGON 2 | G8: 40 | H8: =SUM(F8*G8) -> 0 | I8: 9033 | J8: 50 | K8: =J8*I8 -> 451650 | M8: 60 | N8: =M8*L8 -> 0 | O8: 3130 | P8: 12 | Q8: =O8*P8 -> 37560 | R8: 1608 | S8: 12 | T8: =R8*S8 -> 19296 | U8: 852 | V8: 8 | W8: =U8*V8 -> 6816 | X8: 556 | Y8: 12 | Z8: =X8*Y8 -> 6672 | AA8: 1103 | AB8: 10 | AC8: =AA8*AB8 -> 11030 | AD8: 236 | AE8: 25 | AF8: =AD8*AE8 -> 5900 | AG8: 257 | AH8: 7.5 | AI8: =AG8*AH8 -> 1927.5 | AK8: 15 | AL8: =AJ8*AK8 -> 0 | AM8: 180 | AN8: 10 | AO8: =AM8*AN8 -> 1800 | AP8: =R8+U8+X8+AA8+AD8+AG8+AM8 -> 4792 | AX8: =936+168+346+156+42 -> 1648 | AZ8: =O8/(I8+F8+L8) -> 0.34650725 | BA8: =AP8/(I8+F8+L8) -> 0.53049928 | BB8: =AX8/O8 -> 0.52651757 | BC8: =H8+W8+Z8+AC8+AF8+T8+K8+N8 -> 501364 | BD8: =H8+AF8+T8+K8+N8 -> 476846 | BE8: =H8+W8+Z8+AC8+AF8+T8+K8+N8 -> 501364 | BF8: =H8+W8+Z8+AC8+AF8+AI8+T8+K8+N8 -> 503291.5 | BG8: 575689.5 | BH8: 385184.17 | BI8: =+BH8/BG8% -> 66.90832 | BJ8: =SUM(BY8+BZ8+CA8+CB8) -> 36410 | BK8: =SUM(CF8+CG8+CH8+CI8) -> 0.063245899 | BL8: =B8 -> 4 | BM8: =CC8 -> 56211 | BN8: =+BU8/BM8 -> 2.5093789 | BO8: =CD8 -> 875 | BP8: =+BU8/BO8 -> 161.20537 | BQ8: =CE8 -> 20000 | BR8: =+BU8/BQ8 -> 7.052735 | BS8: =BU8-BM8-BO8-BQ8-BY8-BZ8-CA8-CB8 -> 27558.7 | BT8: =+BU8/BS8 -> 5.1183365 | BU8: 141054.7 | BV8: =+BU8/BG8% -> 24.501871 | BW8: =SUM(BG8-BH8-BU8) -> 49450.63 | BX8: =+BW8/BG8% -> 8.5898093 | BY8: 14719 | BZ8: 7955 | CA8: 10496 | CB8: 3240 | CC8: 56211 | CD8: 875 | CE8: 20000 | CF8: =BY8/BG8 -> 0.025567602 | CG8: =BZ8/BG8 -> 0.013818213 | CH8: =CA8/BG8 -> 0.01823205 | CI8: =CB8/BG8 -> 0.0056280339 | CJ8: =CC8/BG8 -> 0.097641176 | CK8: =+BW8*20% -> 9890.126
A9: =A8+1 -> 2 | B9: 5 | C9: AYUNGON 1 | G9: 40 | H9: =SUM(F9*G9) -> 0 | I9: 13187 | J9: 50 | K9: =J9*I9 -> 659350 | M9: 60 | N9: =M9*L9 -> 0 | O9: 5612 | P9: 12 | Q9: =O9*P9 -> 67344 | R9: 1684 | S9: 12 | T9: =R9*S9 -> 20208 | U9: 726 | V9: 8 | W9: =U9*V9 -> 5808 | X9: 489 | Y9: 12 | Z9: =X9*Y9 -> 5868 | AA9: 989 | AB9: 10 | AC9: =AA9*AB9 -> 9890 | AD9: 274 | AE9: 25 | AF9: =AD9*AE9 -> 6850 | AG9: 144 | AH9: 7.5 | AI9: =AG9*AH9 -> 1080 | AK9: 15 | AL9: =AJ9*AK9 -> 0 | AM9: 180 | AN9: 10 | AO9: =AM9*AN9 -> 1800 | AP9: =R9+U9+X9+AA9+AD9+AG9+AM9 -> 4486 | AX9: =1343+223+360+95+331+83 -> 2435 | AZ9: =O9/(I9+F9+L9) -> 0.42557064 | BA9: =AP9/(I9+F9+L9) -> 0.34018351 | BB9: =AX9/O9 -> 0.43389166 | BC9: =H9+W9+Z9+AC9+AF9+T9+K9+N9 -> 707974 | BD9: =H9+AF9+T9+K9+N9 -> 686408 | BE9: =H9+W9+Z9+AC9+AF9+T9+K9+N9 -> 707974 | BF9: =H9+W9+Z9+AC9+AF9+AI9+T9+K9+N9 -> 709054 | BG9: 824216 | BH9: 552617.61 | BI9: =+BH9/BG9% -> 67.047668 | BJ9: =SUM(BY9+BZ9+CA9+CB9) -> 55735 | BK9: =SUM(CF9+CG9+CH9+CI9) -> 0.067621837 | BL9: =B9 -> 5 | BM9: =CC9 -> 71152 | BN9: =+BU9/BM9 -> 2.9207821 | BO9: =CD9 -> 1062.5 | BP9: =+BU9/BO9 -> 195.59481 | BQ9: =CE9 -> 31500 | BR9: =+BU9/BQ9 -> 6.5974441 | BS9: =BU9-BM9-BO9-BQ9-BY9-BZ9-CA9-CB9 -> 48369.99 | BT9: =+BU9/BS9 -> 4.2964551 | BU9: 207819.49 | BV9: =+BU9/BG9% -> 25.214202 | BW9: =SUM(BG9-BH9-BU9) -> 63778.9 | BX9: =+BW9/BG9% -> 7.7381293 | BY9: 22133 | BZ9: 12728 | CA9: 15744 | CB9: 5130 | CC9: 71152 | CD9: 1062.5 | CE9: 31500 | CF9: =BY9/BG9 -> 0.026853398 | CG9: =BZ9/BG9 -> 0.015442554 | CH9: =CA9/BG9 -> 0.019101789 | CI9: =CB9/BG9 -> 0.0062240966 | CJ9: =CC9/BG9 -> 0.086326885 | CK9: =+BW9*20% -> 12755.78
A10: =A9+1 -> 3 | B10: 4 | C10: BACONG 1 | G10: 40 | H10: =SUM(F10*G10) -> 0 | I10: 8461 | J10: 50 | K10: =J10*I10 -> 423050 | M10: 60 | N10: =M10*L10 -> 0 | O10: 5149 | P10: 12 | Q10: =O10*P10 -> 61788 | R10: 4313 | S10: 12 | T10: =R10*S10 -> 51756 | U10: 1115 | V10: 8 | W10: =U10*V10 -> 8920 | X10: 245 | Y10: 12 | Z10: =X10*Y10 -> 2940 | AA10: 1011 | AB10: 10 | AC10: =AA10*AB10 -> 10110 | AD10: 415 | AE10: 25 | AF10: =AD10*AE10 -> 10375 | AG10: 724 | AH10: 7.5 | AI10: =AG10*AH10 -> 5430 | AK10: 15 | AL10: =AJ10*AK10 -> 0 | AM10: 297 | AN10: 10 | AO10: =AM10*AN10 -> 2970 | AP10: =R10+U10+X10+AA10+AD10+AG10+AM10 -> 8120 | AX10: =294+983+136+177+114 -> 1704 | AZ10: =O10/(I10+F10+L10) -> 0.60855691 | BA10: =AP10/(I10+F10+L10) -> 0.95969744 | BB10: =AX10/O10 -> 0.33093805 | BC10: =H10+W10+Z10+AC10+AF10+T10+K10+N10 -> 507151 | BD10: =H10+AF10+T10+K10+N10 -> 485181 | BE10: =H10+W10+Z10+AC10+AF10+T10+K10+N10 -> 507151 | BF10: =H10+W10+Z10+AC10+AF10+AI10+T10+K10+N10 -> 512581 | BG10: 610111 | BH10: 411472.29 | BI10: =+BH10/BG10% -> 67.442202 | BJ10: =SUM(BY10+BZ10+CA10+CB10) -> 34941.5 | BK10: =SUM(CF10+CG10+CH10+CI10) -> 0.057270726 | BL10: =B10 -> 4 | BM10: =CC10 -> 70525 | BN10: =+BU10/BM10 -> 2.2182603 | BO10: =CD10 -> 750 | BP10: =+BU10/BO10 -> 208.59041 | BQ10: =CE10 -> 16000 | BR10: =+BU10/BQ10 -> 9.7776756 | BS10: =BU10-BM10-BO10-BQ10-BY10-BZ10-CA10-CB10 -> 34226.31 | BT10: =+BU10/BS10 -> 4.5708348 | BU10: 156442.81 | BV10: =+BU10/BG10% -> 25.641696 | BW10: =SUM(BG10-BH10-BU10) -> 42195.9 | BX10: =+BW10/BG10% -> 6.9161022 | BY10: 11119.5 | BZ10: 9546 | CA10: 10496 | CB10: 3780 | CC10: 70525 | CD10: 750 | CE10: 16000 | CF10: =BY10/BG10 -> 0.018225372 | CG10: =BZ10/BG10 -> 0.015646333 | CH10: =CA10/BG10 -> 0.017203427 | CI10: =CB10/BG10 -> 0.0061955939 | CJ10: =CC10/BG10 -> 0.11559372 | CK10: =+BW10*20% -> 8439.18
A11: =A10+1 -> 4 | B11: 2 | C11: BACONG2 | G11: 40 | H11: =SUM(F11*G11) -> 0 | I11: 3994 | J11: 50 | K11: =J11*I11 -> 199700 | M11: 60 | N11: =M11*L11 -> 0 | O11: 2381 | P11: 12 | Q11: =O11*P11 -> 28572 | R11: 3438 | S11: 12 | T11: =R11*S11 -> 41256 | U11: 371 | V11: 8 | W11: =U11*V11 -> 2968 | X11: 130 | Y11: 12 | Z11: =X11*Y11 -> 1560 | AA11: 370 | AB11: 10 | AC11: =AA11*AB11 -> 3700 | AD11: 174 | AE11: 25 | AF11: =AD11*AE11 -> 4350 | AG11: 197 | AH11: 7.5 | AI11: =AG11*AH11 -> 1477.5 | AK11: 15 | AL11: =AJ11*AK11 -> 0 | AM11: 172 | AN11: 10 | AO11: =AM11*AN11 -> 1720 | AP11: =R11+U11+X11+AA11+AD11+AG11+AM11 -> 4852 | AX11: 1014 | AZ11: =O11/(I11+F11+L11) -> 0.59614422 | BA11: =AP11/(I11+F11+L11) -> 1.2148222 | BB11: =AX11/O11 -> 0.42587148 | BC11: =H11+W11+Z11+AC11+AF11+T11+K11+N11 -> 253534 | BD11: =H11+AF11+T11+K11+N11 -> 245306 | BE11: =H11+W11+Z11+AC11+AF11+T11+K11+N11 -> 253534 | BF11: =H11+W11+Z11+AC11+AF11+AI11+T11+K11+N11 -> 255011.5 | BG11: 304710.5 | BH11: 203245.08 | BI11: =+BH11/BG11% -> 66.701042 | BJ11: =SUM(BY11+BZ11+CA11+CB11) -> 21455 | BK11: =SUM(CF11+CG11+CH11+CI11) -> 0.070411095 | BL11: =B11 -> 2 | BM11: =CC11 -> 35637.5 | BN11: =+BU11/BM11 -> 2.6343119 | BO11: =CD11 -> 3156.25 | BP11: =+BU11/BO11 -> 29.74425 | BQ11: =CE11 -> 8269 | BR11: =+BU11/BQ11 -> 11.353282 | BS11: =BU11-BM11-BO11-BQ11-BY11-BZ11-CA11-CB11 -> 25362.54 | BT11: =+BU11/BS11 -> 3.7015334 | BU11: 93880.29 | BV11: =+BU11/BG11% -> 30.809667 | BW11: =SUM(BG11-BH11-BU11) -> 7585.13 | BX11: =+BW11/BG11% -> 2.4892907 | BY11: 7413 | BZ11: 6364 | CA11: 5248 | CB11: 2430 | CC11: 35637.5 | CD11: 3156.25 | CE11: 8269 | CF11: =BY11/BG11 -> 0.02432801 | CG11: =BZ11/BG11 -> 0.020885398 | CH11: =CA11/BG11 -> 0.017222905 | CI11: =CB11/BG11 -> 0.0079747826 | CJ11: =CC11/BG11 -> 0.11695527 | CK11: =+BW11*20% -> 1517.026
A12: =A11+1 -> 5 | B12: 4 | C12: BAGACAY | G12: 40 | H12: =SUM(F12*G12) -> 0 | I12: 7383 | J12: 50 | K12: =J12*I12 -> 369150 | M12: 60 | N12: =M12*L12 -> 0 | O12: 6567 | P12: 12 | Q12: =O12*P12 -> 78804 | R12: 1880 | S12: 12 | T12: =R12*S12 -> 22560 | U12: 1209 | V12: 8 | W12: =U12*V12 -> 9672 | X12: 523 | Y12: 12 | Z12: =X12*Y12 -> 6276 | AA12: 919 | AB12: 10 | AC12: =AA12*AB12 -> 9190 | AD12: 315 | AE12: 25 | AF12: =AD12*AE12 -> 7875 | AG12: 540 | AH12: 7.5 | AI12: =AG12*AH12 -> 4050 | AK12: 15 | AL12: =AJ12*AK12 -> 0 | AM12: 226 | AN12: 10 | AO12: =AM12*AN12 -> 2260 | AP12: =R12+U12+X12+AA12+AD12+AG12+AM12 -> 5612 | AX12: 2175 | AZ12: =O12/(I12+F12+L12) -> 0.88947582 | BA12: =AP12/(I12+F12+L12) -> 0.76012461 | BB12: =AX12/O12 -> 0.33120146 | BC12: =H12+W12+Z12+AC12+AF12+T12+K12+N12 -> 424723 | BD12: =H12+AF12+T12+K12+N12 -> 399585 | BE12: =H12+W12+Z12+AC12+AF12+T12+K12+N12 -> 424723 | BF12: =H12+W12+Z12+AC12+AF12+AI12+T12+K12+N12 -> 428773 | BG12: 550265 | BH12: 369484.17 | BI12: =+BH12/BG12% -> 67.146588 | BJ12: =SUM(BY12+BZ12+CA12+CB12) -> 36833.75 | BK12: =SUM(CF12+CG12+CH12+CI12) -> 0.066938203 | BL12: =B12 -> 4 | BM12: =CC12 -> 62525 | BN12: =+BU12/BM12 -> 2.8214887 | BO12: =CD12 -> 375 | BP12: =+BU12/BO12 -> 470.43621 | BQ12: =CE12 -> 28000 | BR12: =+BU12/BQ12 -> 6.300485 | BS12: =BU12-BM12-BO12-BQ12-BY12-BZ12-CA12-CB12 -> 48679.83 | BT12: =+BU12/BS12 -> 3.6239564 | BU12: 176413.58 | BV12: =+BU12/BG12% -> 32.059749 | BW12: =SUM(BG12-BH12-BU12) -> 4367.25 | BX12: =+BW12/BG12% -> 0.79366305 | BY12: 11119.5 | BZ12: 11137 | CA12: 10797.25 | CB12: 3780 | CC12: 62525 | CD12: 375 | CE12: 28000 | CF12: =BY12/BG12 -> 0.020207536 | CG12: =BZ12/BG12 -> 0.020239339 | CH12: =CA12/BG12 -> 0.019621909 | CI12: =CB12/BG12 -> 0.0068694175 | CJ12: =CC12/BG12 -> 0.11362707 | CK12: =+BW12*20% -> 873.45
A13: =A12+1 -> 6 | B13: 4 | C13: BAYAWAN | G13: 40 | H13: =SUM(F13*G13) -> 0 | I13: 10401 | J13: 50 | K13: =J13*I13 -> 520050 | M13: 60 | N13: =M13*L13 -> 0 | O13: 3494 | P13: 12 | Q13: =O13*P13 -> 41928 | S13: 12 | T13: =R13*S13 -> 0 | U13: 800 | V13: 8 | W13: =U13*V13 -> 6400 | X13: 522 | Y13: 12 | Z13: =X13*Y13 -> 6264 | AA13: 1086 | AB13: 10 | AC13: =AA13*AB13 -> 10860 | AD13: 340 | AE13: 25 | AF13: =AD13*AE13 -> 8500 | AG13: 369 | AH13: 7.5 | AI13: =AG13*AH13 -> 2767.5 | AK13: 15 | AL13: =AJ13*AK13 -> 0 | AN13: 10 | AO13: =AM13*AN13 -> 0 | AP13: =R13+U13+X13+AA13+AD13+AG13+AM13 -> 3117 | AX13: 1309 | AZ13: =O13/(I13+F13+L13) -> 0.33592924 | BA13: =AP13/(I13+F13+L13) -> 0.29968272 | BB13: =AX13/O13 -> 0.37464224 | BC13: =H13+W13+Z13+AC13+AF13+T13+K13+N13 -> 552074 | BD13: =H13+AF13+T13+K13+N13 -> 528550 | BE13: =H13+W13+Z13+AC13+AF13+T13+K13+N13 -> 552074 | BF13: =H13+W13+Z13+AC13+AF13+AI13+T13+K13+N13 -> 554841.5 | BG13: 623237 | BH13: 419147.42 | BI13: =+BH13/BG13% -> 67.253295 | BJ13: =SUM(BY13+BZ13+CA13+CB13) -> 53815 | BK13: =SUM(CF13+CG13+CH13+CI13) -> 0.086347569 | BL13: =B13 -> 4 | BM13: =CC13 -> 62339 | BN13: =+BU13/BM13 -> 2.928256 | BO13: =CD13 -> 4687 | BP13: =+BU13/BO13 -> 38.946992 | BQ13: =CE13 -> 13000 | BR13: =+BU13/BQ13 -> 14.041888 | BS13: =BU13-BM13-BO13-BQ13-BY13-BZ13-CA13-CB13 -> 48703.55 | BT13: =+BU13/BS13 -> 3.7480748 | BU13: 182544.55 | BV13: =+BU13/BG13% -> 29.289749 | BW13: =SUM(BG13-BH13-BU13) -> 21545.03 | BX13: =+BW13/BG13% -> 3.4569562 | BY13: 18314 | BZ13: 14319 | CA13: 16862 | CB13: 4320 | CC13: 62339 | CD13: 4687 | CE13: 13000 | CF13: =BY13/BG13 -> 0.02938529 | CG13: =BZ13/BG13 -> 0.022975208 | CH13: =CA13/BG13 -> 0.027055518 | CI13: =CB13/BG13 -> 0.0069315525 | CJ13: =CC13/BG13 -> 0.10002455 | CK13: =+BW13*20% -> 4309.006
A14: =A13+1 -> 7 | B14: 7 | C14: BINDOY1 | G14: 40 | H14: =SUM(F14*G14) -> 0 | I14: 18741 | J14: 50 | K14: =J14*I14 -> 937050 | M14: 60 | N14: =M14*L14 -> 0 | O14: 6194 | P14: 12 | Q14: =O14*P14 -> 74328 | S14: 12 | T14: =R14*S14 -> 0 | U14: 1048 | V14: 8 | W14: =U14*V14 -> 8384 | X14: 436 | Y14: 12 | Z14: =X14*Y14 -> 5232 | AA14: 1294 | AB14: 10 | AC14: =AA14*AB14 -> 12940 | AD14: 350 | AE14: 25 | AF14: =AD14*AE14 -> 8750 | AG14: 292 | AH14: 7.5 | AI14: =AG14*AH14 -> 2190 | AK14: 15 | AL14: =AJ14*AK14 -> 0 | AM14: 360 | AN14: 10 | AO14: =AM14*AN14 -> 3600 | AP14: =R14+U14+X14+AA14+AD14+AG14+AM14 -> 3780 | AX14: 2224 | AZ14: =O14/(I14+F14+L14) -> 0.33050531 | BA14: =AP14/(I14+F14+L14) -> 0.20169681 | BB14: =AX14/O14 -> 0.35905715 | BC14: =H14+W14+Z14+AC14+AF14+T14+K14+N14 -> 972356 | BD14: =H14+AF14+T14+K14+N14 -> 945800 | BE14: =H14+W14+Z14+AC14+AF14+T14+K14+N14 -> 972356 | BF14: =H14+W14+Z14+AC14+AF14+AI14+T14+K14+N14 -> 974546 | BG14: 1092355 | BH14: 740138.61 | BI14: =+BH14/BG14% -> 67.756234 | BJ14: =SUM(BY14+BZ14+CA14+CB14) -> 67338 | BK14: =SUM(CF14+CG14+CH14+CI14) -> 0.061644795 | BL14: =B14 -> 7 | BM14: =CC14 -> 92737.5 | BN14: =+BU14/BM14 -> 2.5075088 | BO14: =CD14 -> 2750 | BP14: =+BU14/BO14 -> 84.560036 | BQ14: =CE14 -> 14500 | BR14: =+BU14/BQ14 -> 16.037248 | BS14: =BU14-BM14-BO14-BQ14-BY14-BZ14-CA14-CB14 -> 55214.6 | BT14: =+BU14/BS14 -> 4.211569 | BU14: 232540.1 | BV14: =+BU14/BG14% -> 21.28796 | BW14: =SUM(BG14-BH14-BU14) -> 119676.29 | BX14: =+BW14/BG14% -> 10.955806 | BY14: 22133 | BZ14: 17501 | CA14: 22304 | CB14: 5400 | CC14: 92737.5 | CD14: 2750 | CE14: 14500 | CF14: =BY14/BG14 -> 0.020261728 | CG14: =BZ14/BG14 -> 0.016021348 | CH14: =CA14/BG14 -> 0.020418271 | CI14: =CB14/BG14 -> 0.0049434479 | CJ14: =CC14/BG14 -> 0.084896851 | CK14: =+BW14*20% -> 23935.258
A15: =A14+1 -> 8 | B15: 3 | C15: BINDOY2 | G15: 40 | H15: =SUM(F15*G15) -> 0 | I15: 7410 | J15: 50 | K15: =J15*I15 -> 370500 | M15: 60 | N15: =M15*L15 -> 0 | O15: 2269 | P15: 12 | Q15: =O15*P15 -> 27228 | R15: 3120 | S15: 12 | T15: =R15*S15 -> 37440 | U15: 506 | V15: 8 | W15: =U15*V15 -> 4048 | X15: 299 | Y15: 12 | Z15: =X15*Y15 -> 3588 | AA15: 722 | AB15: 10 | AC15: =AA15*AB15 -> 7220 | AD15: 140 | AE15: 25 | AF15: =AD15*AE15 -> 3500 | AG15: 122 | AH15: 7.5 | AI15: =AG15*AH15 -> 915 | AK15: 15 | AL15: =AJ15*AK15 -> 0 | AM15: 148 | AN15: 10 | AO15: =AM15*AN15 -> 1480 | AP15: =R15+U15+X15+AA15+AD15+AG15+AM15 -> 5057 | AX15: 677 | AZ15: =O15/(I15+F15+L15) -> 0.30620783 | BA15: =AP15/(I15+F15+L15) -> 0.68245614 | BB15: =AX15/O15 -> 0.29836933 | BC15: =H15+W15+Z15+AC15+AF15+T15+K15+N15 -> 426296 | BD15: =H15+AF15+T15+K15+N15 -> 411440 | BE15: =H15+W15+Z15+AC15+AF15+T15+K15+N15 -> 426296 | BF15: =H15+W15+Z15+AC15+AF15+AI15+T15+K15+N15 -> 427211 | BG15: 468779 | BH15: 316349.25 | BI15: =+BH15/BG15% -> 67.483665 | BJ15: =SUM(BY15+BZ15+CA15+CB15) -> 33854 | BK15: =SUM(CF15+CG15+CH15+CI15) -> 0.072217399 | BL15: =B15 -> 3 | BM15: =CC15 -> 49012.5 | BN15: =+BU15/BM15 -> 2.6190258 | BO15: =CD15 -> 3687.5 | BP15: =+BU15/BO15 -> 34.810847 | BQ15: =CE15 -> 15000 | BR15: =+BU15/BQ15 -> 8.5576667 | BS15: =BU15-BM15-BO15-BQ15-BY15-BZ15-CA15-CB15 -> 26811 | BT15: =+BU15/BS15 -> 4.7877737 | BU15: 128365 | BV15: =+BU15/BG15% -> 27.382839 | BW15: =SUM(BG15-BH15-BU15) -> 24064.75 | BX15: =+BW15/BG15% -> 5.1334957 | BY15: 11121 | BZ15: 7955 | CA15: 11808 | CB15: 2970 | CC15: 49012.5 | CD15: 3687.5 | CE15: 15000 | CF15: =BY15/BG15 -> 0.023723332 | CG15: =BZ15/BG15 -> 0.016969617 | CH15: =CA15/BG15 -> 0.025188842 | CI15: =CB15/BG15 -> 0.006335608 | CJ15: =CC15/BG15 -> 0.10455353 | CK15: =+BW15*20% -> 4812.95
A16: =A15+1 -> 9 | B16: 4 | C16: CADIZ 3 | G16: 40 | H16: =SUM(F16*G16) -> 0 | I16: 10625 | J16: 50 | K16: =J16*I16 -> 531250 | M16: 60 | N16: =M16*L16 -> 0 | O16: 4094 | P16: 12 | Q16: =O16*P16 -> 49128 | R16: 1470 | S16: 12 | T16: =R16*S16 -> 17640 | U16: 394 | V16: 8 | W16: =U16*V16 -> 3152 | X16: 210 | Y16: 12 | Z16: =X16*Y16 -> 2520 | AA16: 483 | AB16: 10 | AC16: =AA16*AB16 -> 4830 | AD16: 164 | AE16: 25 | AF16: =AD16*AE16 -> 4100 | AG16: 80 | AH16: 7.5 | AI16: =AG16*AH16 -> 600 | AK16: 15 | AL16: =AJ16*AK16 -> 0 | AN16: 12 | AO16: =AM16*AN16 -> 0 | AP16: =R16+U16+X16+AA16+AD16+AG16+AM16 -> 2801 | AX16: 1515 | AZ16: =O16/(I16+F16+L16) -> 0.38531765 | BA16: =AP16/(I16+F16+L16) -> 0.26362353 | BB16: =AX16/O16 -> 0.37005374 | BC16: =H16+W16+Z16+AC16+AF16+T16+K16+N16 -> 563492 | BD16: =H16+AF16+T16+K16+N16 -> 552990 | BE16: =H16+W16+Z16+AC16+AF16+T16+K16+N16 -> 563492 | BF16: =H16+W16+Z16+AC16+AF16+AI16+T16+K16+N16 -> 564092 | BG16: 641725 | BH16: 427735.27 | BI16: =+BH16/BG16% -> 66.653983 | BJ16: =SUM(BY16+BZ16+CA16+CB16) -> 38703 | BK16: =SUM(CF16+CG16+CH16+CI16) -> 0.060310881 | BL16: =B16 -> 4 | BM16: =CC16 -> 65997.6 | BN16: =+BU16/BM16 -> 2.6657053 | BO16: =CD16 -> 1731 | BP16: =+BU16/BO16 -> 101.63498 | BQ16: =CE16 -> 18000 | BR16: =+BU16/BQ16 -> 9.7738972 | BS16: =BU16-BM16-BO16-BQ16-BY16-BZ16-CA16-CB16 -> 51498.55 | BT16: =+BU16/BS16 -> 3.4162156 | BU16: 175930.15 | BV16: =+BU16/BG16% -> 27.415193 | BW16: =SUM(BG16-BH16-BU16) -> 38059.58 | BX16: =+BW16/BG16% -> 5.930824 | BY16: 14723 | BZ16: 10380 | CA16: 10400 | CB16: 3200 | CC16: 65997.6 | CD16: 1731 | CE16: 18000 | CF16: =BY16/BG16 -> 0.022942849 | CG16: =BZ16/BG16 -> 0.016175153 | CH16: =CA16/BG16 -> 0.016206319 | CI16: =CB16/BG16 -> 0.0049865597 | CJ16: =CC16/BG16 -> 0.10284405 | CK16: =+BW16*20% -> 7611.916
A17: =A16+1 -> 10 | B17: 6 | C17: DARO | G17: 40 | H17: =SUM(F17*G17) -> 0 | I17: 14122 | J17: 50 | K17: =J17*I17 -> 706100 | M17: 60 | N17: =M17*L17 -> 0 | O17: 9999 | P17: 12 | Q17: =O17*P17 -> 119988 | S17: 12 | T17: =R17*S17 -> 0 | U17: 1200 | V17: 8 | W17: =U17*V17 -> 9600 | X17: 622 | Y17: 12 | Z17: =X17*Y17 -> 7464 | AA17: 1131 | AB17: 10 | AC17: =AA17*AB17 -> 11310 | AD17: 481 | AE17: 25 | AF17: =AD17*AE17 -> 12025 | AG17: 1149 | AH17: 7.5 | AI17: =AG17*AH17 -> 8617.5 | AK17: 15 | AL17: =AJ17*AK17 -> 0 | AM17: 569 | AN17: 10 | AO17: =AM17*AN17 -> 5690 | AP17: =R17+U17+X17+AA17+AD17+AG17+AM17 -> 5152 | AX17: 2373 | AZ17: =O17/(I17+F17+L17) -> 0.70804419 | BA17: =AP17/(I17+F17+L17) -> 0.36482085 | BB17: =AX17/O17 -> 0.23732373 | BC17: =H17+W17+Z17+AC17+AF17+T17+K17+N17 -> 746499 | BD17: =H17+AF17+T17+K17+N17 -> 718125 | BE17: =H17+W17+Z17+AC17+AF17+T17+K17+N17 -> 746499 | BF17: =H17+W17+Z17+AC17+AF17+AI17+T17+K17+N17 -> 755116.5 | BG17: 927633.5 | BH17: 633026.54 | BI17: =+BH17/BG17% -> 68.241018 | BJ17: =SUM(BY17+BZ17+CA17+CB17) -> 52065 | BK17: =SUM(CF17+CG17+CH17+CI17) -> 0.056126692 | BL17: =B17 -> 6 | BM17: =CC17 -> 92850 | BN17: =+BU17/BM17 -> 2.5152299 | BO17: =CD17 -> 1062 | BP17: =+BU17/BO17 -> 219.90499 | BQ17: =CE17 -> 22050 | BR17: =+BU17/BQ17 -> 10.591342 | BS17: =BU17-BM17-BO17-BQ17-BY17-BZ17-CA17-CB17 -> 65512.1 | BT17: =+BU17/BS17 -> 3.5648239 | BU17: 233539.1 | BV17: =+BU17/BG17% -> 25.175794 | BW17: =SUM(BG17-BH17-BU17) -> 61067.86 | BX17: =+BW17/BG17% -> 6.5831883 | BY17: 14826 | BZ17: 14319 | CA17: 19680 | CB17: 3240 | CC17: 92850 | CD17: 1062 | CE17: 22050 | CF17: =BY17/BG17 -> 0.015982605 | CG17: =BZ17/BG17 -> 0.015436053 | CH17: =CA17/BG17 -> 0.021215275 | CI17: =CB17/BG17 -> 0.0034927587 | CJ17: =CC17/BG17 -> 0.10009341 | CK17: =+BW17*20% -> 12213.572
A18: =A17+1 -> 11 | B18: 4 | C18: GUIHULNGAN | G18: 40 | H18: =SUM(F18*G18) -> 0 | I18: 10223 | J18: 50 | K18: =J18*I18 -> 511150 | M18: 60 | N18: =M18*L18 -> 0 | O18: 3272 | P18: 12 | Q18: =O18*P18 -> 39264 | R18: 2032 | S18: 12 | T18: =R18*S18 -> 24384 | U18: 511 | V18: 8 | W18: =U18*V18 -> 4088 | X18: 894 | Y18: 12 | Z18: =X18*Y18 -> 10728 | AA18: 672 | AB18: 10 | AC18: =AA18*AB18 -> 6720 | AD18: 240 | AE18: 25 | AF18: =AD18*AE18 -> 6000 | AG18: 167 | AH18: 7.5 | AI18: =AG18*AH18 -> 1252.5 | AK18: 15 | AL18: =AJ18*AK18 -> 0 | AM18: 236 | AN18: 10 | AO18: =AM18*AN18 -> 2360 | AP18: =R18+U18+X18+AA18+AD18+AG18+AM18 -> 4752 | AX18: 1563 | AZ18: =O18/(I18+F18+L18) -> 0.3200626 | BA18: =AP18/(I18+F18+L18) -> 0.4648342 | BB18: =AX18/O18 -> 0.47768949 | BC18: =H18+W18+Z18+AC18+AF18+T18+K18+N18 -> 563070 | BD18: =H18+AF18+T18+K18+N18 -> 541534 | BE18: =H18+W18+Z18+AC18+AF18+T18+K18+N18 -> 563070 | BF18: =H18+W18+Z18+AC18+AF18+AI18+T18+K18+N18 -> 564322.5 | BG18: 635621.5 | BH18: 426238.17 | BI18: =+BH18/BG18% -> 67.058488 | BJ18: =SUM(BY18+BZ18+CA18+CB18) -> 42433 | BK18: =SUM(CF18+CG18+CH18+CI18) -> 0.066758283 | BL18: =B18 -> 4 | BM18: =CC18 -> 64783 | BN18: =+BU18/BM18 -> 3.0784678 | BO18: =CD18 -> 499 | BP18: =+BU18/BO18 -> 399.66409 | BQ18: =CE18 -> 36000 | BR18: =+BU18/BQ18 -> 5.5397883 | BS18: =BU18-BM18-BO18-BQ18-BY18-BZ18-CA18-CB18 -> 55717.38 | BT18: =+BU18/BS18 -> 3.5793567 | BU18: 199432.38 | BV18: =+BU18/BG18% -> 31.375965 | BW18: =SUM(BG18-BH18-BU18) -> 9950.95 | BX18: =+BW18/BG18% -> 1.5655465 | BY18: 14719 | BZ18: 12110 | CA18: 10854 | CB18: 4750 | CC18: 64783 | CD18: 499 | CE18: 36000 | CF18: =BY18/BG18 -> 0.023156863 | CG18: =BZ18/BG18 -> 0.019052219 | CH18: =CA18/BG18 -> 0.0170762 | CI18: =CB18/BG18 -> 0.0074730008 | CJ18: =CC18/BG18 -> 0.10192072 | CK18: =+BW18*20% -> 1990.19
A19: =A18+1 -> 12 | B19: 3 | C19: JIMALALUD | G19: 40 | H19: =SUM(F19*G19) -> 0 | I19: 9997 | J19: 50 | K19: =J19*I19 -> 499850 | M19: 60 | N19: =M19*L19 -> 0 | O19: 4497 | P19: 12 | Q19: =O19*P19 -> 53964 | R19: 2400 | S19: 12 | T19: =R19*S19 -> 28800 | U19: 700 | V19: 8 | W19: =U19*V19 -> 5600 | X19: 554 | Y19: 12 | Z19: =X19*Y19 -> 6648 | AA19: 757 | AB19: 10 | AC19: =AA19*AB19 -> 7570 | AD19: 266 | AE19: 25 | AF19: =AD19*AE19 -> 6650 | AG19: 243 | AH19: 7.5 | AI19: =AG19*AH19 -> 1822.5 | AK19: 15 | AL19: =AJ19*AK19 -> 0 | AM19: 230 | AN19: 10 | AO19: =AM19*AN19 -> 2300 | AP19: =R19+U19+X19+AA19+AD19+AG19+AM19 -> 5150 | AX19: 2227 | AZ19: =O19/(I19+F19+L19) -> 0.44983495 | BA19: =AP19/(I19+F19+L19) -> 0.51515455 | BB19: =AX19/O19 -> 0.49521903 | BC19: =H19+W19+Z19+AC19+AF19+T19+K19+N19 -> 555118 | BD19: =H19+AF19+T19+K19+N19 -> 535300 | BE19: =H19+W19+Z19+AC19+AF19+T19+K19+N19 -> 555118 | BF19: =H19+W19+Z19+AC19+AF19+AI19+T19+K19+N19 -> 556940.5 | BG19: 655174.5 | BH19: 436893.86 | BI19: =+BH19/BG19% -> 66.683587 | BJ19: =SUM(BY19+BZ19+CA19+CB19) -> 40904 | BK19: =SUM(CF19+CG19+CH19+CI19) -> 0.062432222 | BL19: =B19 -> 3 | BM19: =CC19 -> 69037.5 | BN19: =+BU19/BM19 -> 2.2163786 | BO19: =CD19 -> 187.5 | BP19: =+BU19/BO19 -> 816.07061 | BQ19: =CE19 -> 15000 | BR19: =+BU19/BQ19 -> 10.200883 | BS19: =BU19-BM19-BO19-BQ19-BY19-BZ19-CA19-CB19 -> 27884.24 | BT19: =+BU19/BS19 -> 5.4874452 | BU19: 153013.24 | BV19: =+BU19/BG19% -> 23.354578 | BW19: =SUM(BG19-BH19-BU19) -> 65267.4 | BX19: =+BW19/BG19% -> 9.9618346 | BY19: 14719 | BZ19: 11137 | CA19: 11808 | CB19: 3240 | CC19: 69037.5 | CD19: 187.5 | CE19: 15000 | CF19: =BY19/BG19 -> 0.022465771 | CG19: =BZ19/BG19 -> 0.016998525 | CH19: =CA19/BG19 -> 0.018022679 | CI19: =CB19/BG19 -> 0.0049452474 | CJ19: =CC19/BG19 -> 0.10537269 | CK19: =+BW19*20% -> 13053.48
A20: =A19+1 -> 13 | B20: 3 | C20: JUNOB | G20: 40 | H20: =SUM(F20*G20) -> 0 | I20: 8045 | J20: 50 | K20: =J20*I20 -> 402250 | M20: 60 | N20: =M20*L20 -> 0 | O20: 4108 | P20: 12 | Q20: =O20*P20 -> 49296 | R20: 920 | S20: 12 | T20: =R20*S20 -> 11040 | U20: 520 | V20: 8 | W20: =U20*V20 -> 4160 | X20: 281 | Y20: 12 | Z20: =X20*Y20 -> 3372 | AA20: 619 | AB20: 10 | AC20: =AA20*AB20 -> 6190 | AD20: 129 | AE20: 25 | AF20: =AD20*AE20 -> 3225 | AG20: 184 | AH20: 7.5 | AI20: =AG20*AH20 -> 1380 | AK20: 15 | AL20: =AJ20*AK20 -> 0 | AM20: 243 | AN20: 10 | AO20: =AM20*AN20 -> 2430 | AP20: =R20+U20+X20+AA20+AD20+AG20+AM20 -> 2896 | AX20: 1404 | AZ20: =O20/(I20+F20+L20) -> 0.51062772 | BA20: =AP20/(I20+F20+L20) -> 0.35997514 | BB20: =AX20/O20 -> 0.34177215 | BC20: =H20+W20+Z20+AC20+AF20+T20+K20+N20 -> 430237 | BD20: =H20+AF20+T20+K20+N20 -> 416515 | BE20: =H20+W20+Z20+AC20+AF20+T20+K20+N20 -> 430237 | BF20: =H20+W20+Z20+AC20+AF20+AI20+T20+K20+N20 -> 431617 | BG20: 510732 | BH20: 348854.75 | BI20: =+BH20/BG20% -> 68.304855 | BJ20: =SUM(BY20+BZ20+CA20+CB20) -> 34131.2 | BK20: =SUM(CF20+CG20+CH20+CI20) -> 0.066828004 | BL20: =B20 -> 3 | BM20: =CC20 -> 57999.5 | BN20: =+BU20/BM20 -> 2.7654913 | BO20: =CD20 -> 375 | BP20: =+BU20/BO20 -> 427.72563 | BQ20: =CE20 -> 26750 | BR20: =+BU20/BQ20 -> 5.9961536 | BS20: =BU20-BM20-BO20-BQ20-BY20-BZ20-CA20-CB20 -> 41141.41 | BT20: =+BU20/BS20 -> 3.898678 | BU20: 160397.11 | BV20: =+BU20/BG20% -> 31.405338 | BW20: =SUM(BG20-BH20-BU20) -> 1480.14 | BX20: =+BW20/BG20% -> 0.28980757 | BY20: 11119.2 | BZ20: 9546 | CA20: 10496 | CB20: 2970 | CC20: 57999.5 | CD20: 375 | CE20: 26750 | CF20: =BY20/BG20 -> 0.021771105 | CG20: =BZ20/BG20 -> 0.01869082 | CH20: =CA20/BG20 -> 0.020550896 | CI20: =CB20/BG20 -> 0.0058151829 | CJ20: =CC20/BG20 -> 0.11356152 | CK20: =+BW20*20% -> 296.028
A21: =A20+1 -> 14 | B21: 4 | C21: LARENA | G21: 40 | H21: =SUM(F21*G21) -> 0 | I21: 6500 | J21: 50 | K21: =J21*I21 -> 325000 | M21: 60 | N21: =M21*L21 -> 0 | O21: 5136 | P21: 12 | Q21: =O21*P21 -> 61632 | R21: 7932 | S21: 12 | T21: =R21*S21 -> 95184 | U21: 664 | V21: 8 | W21: =U21*V21 -> 5312 | X21: 205 | Y21: 12 | Z21: =X21*Y21 -> 2460 | AA21: 597 | AB21: 10 | AC21: =AA21*AB21 -> 5970 | AD21: 255 | AE21: 25 | AF21: =AD21*AE21 -> 6375 | AG21: 814 | AH21: 7.5 | AI21: =AG21*AH21 -> 6105 | AK21: 15 | AL21: =AJ21*AK21 -> 0 | AM21: 277 | AN21: 10 | AO21: =AM21*AN21 -> 2770 | AP21: =R21+U21+X21+AA21+AD21+AG21+AM21 -> 10744 | AX21: 1522 | AZ21: =O21/(I21+F21+L21) -> 0.79015385 | BA21: =AP21/(I21+F21+L21) -> 1.6529231 | BB21: =AX21/O21 -> 0.29633956 | BC21: =H21+W21+Z21+AC21+AF21+T21+K21+N21 -> 440301 | BD21: =H21+AF21+T21+K21+N21 -> 426559 | BE21: =H21+W21+Z21+AC21+AF21+T21+K21+N21 -> 440301 | BF21: =H21+W21+Z21+AC21+AF21+AI21+T21+K21+N21 -> 446406 | BG21: 540963 | BH21: 359062.46 | BI21: =+BH21/BG21% -> 66.37468 | BJ21: =SUM(BY21+BZ21+CA21+CB21) -> 37034.5 | BK21: =SUM(CF21+CG21+CH21+CI21) -> 0.06846032 | BL21: =B21 -> 4 | BM21: =CC21 -> 56625 | BN21: =+BU21/BM21 -> 3.2527182 | BO21: =CD21 -> 687.5 | BP21: =+BU21/BO21 -> 267.9057 | BQ21: =CE21 -> 35000 | BR21: =+BU21/BQ21 -> 5.2624334 | BS21: =BU21-BM21-BO21-BQ21-BY21-BZ21-CA21-CB21 -> 54838.17 | BT21: =+BU21/BS21 -> 3.3587038 | BU21: 184185.17 | BV21: =+BU21/BG21% -> 34.047647 | BW21: =SUM(BG21-BH21-BU21) -> -2284.63 | BX21: =+BW21/BG21% -> -0.42232648 | BY21: 11119.5 | BZ21: 11137 | CA21: 11808 | CB21: 2970 | CC21: 56625 | CD21: 687.5 | CE21: 35000 | CF21: =BY21/BG21 -> 0.02055501 | CG21: =BZ21/BG21 -> 0.02058736 | CH21: =CA21/BG21 -> 0.021827741 | CI21: =CB21/BG21 -> 0.0054902091 | CJ21: =CC21/BG21 -> 0.10467444 | CK21: =+BW21*20% -> -456.926
A22: =A21+1 -> 15 | B22: 9 | C22: LOCSIN | G22: 40 | H22: =SUM(F22*G22) -> 0 | I22: 23827 | J22: 50 | K22: =J22*I22 -> 1191350 | M22: 60 | N22: =M22*L22 -> 0 | O22: 21552 | P22: 12 | Q22: =O22*P22 -> 258624 | S22: 12 | T22: =R22*S22 -> 0 | U22: 2900 | V22: 8 | W22: =U22*V22 -> 23200 | X22: 839 | Y22: 12 | Z22: =X22*Y22 -> 10068 | AA22: 2498 | AB22: 10 | AC22: =AA22*AB22 -> 24980 | AD22: 1087 | AE22: 25 | AF22: =AD22*AE22 -> 27175 | AG22: 980 | AH22: 7.5 | AI22: =AG22*AH22 -> 7350 | AK22: 15 | AL22: =AJ22*AK22 -> 0 | AM22: 1080 | AN22: 10 | AO22: =AM22*AN22 -> 10800 | AP22: =R22+U22+X22+AA22+AD22+AG22+AM22 -> 9384 | AX22: 8423 | AZ22: =O22/(I22+F22+L22) -> 0.90452008 | BA22: =AP22/(I22+F22+L22) -> 0.39383892 | BB22: =AX22/O22 -> 0.3908222 | BC22: =H22+W22+Z22+AC22+AF22+T22+K22+N22 -> 1276773 | BD22: =H22+AF22+T22+K22+N22 -> 1218525 | BE22: =H22+W22+Z22+AC22+AF22+T22+K22+N22 -> 1276773 | BF22: =H22+W22+Z22+AC22+AF22+AI22+T22+K22+N22 -> 1284123 | BG22: 1716607 | BH22: 1158880.2 | BI22: =+BH22/BG22% -> 67.50993 | BJ22: =SUM(BY22+BZ22+CA22+CB22) -> 93796 | BK22: =SUM(CF22+CG22+CH22+CI22) -> 0.054640346 | BL22: =B22 -> 9 | BM22: =CC22 -> 144037.5 | BN22: =+BU22/BM22 -> 3.054672 | BO22: =CD22 -> 2312.5 | BP22: =+BU22/BO22 -> 190.26479 | BQ22: =CE22 -> 66150 | BR22: =+BU22/BQ22 -> 6.6513578 | BS22: =BU22-BM22-BO22-BQ22-BY22-BZ22-CA22-CB22 -> 133691.32 | BT22: =+BU22/BS22 -> 3.2910687 | BU22: 439987.32 | BV22: =+BU22/BG22% -> 25.63122 | BW22: =SUM(BG22-BH22-BU22) -> 117739.5 | BX22: =+BW22/BG22% -> 6.85885 | BY22: 22239 | BZ22: 23865 | CA22: 40672 | CB22: 7020 | CC22: 144037.5 | CD22: 2312.5 | CE22: 66150 | CF22: =BY22/BG22 -> 0.012955208 | CG22: =BZ22/BG22 -> 0.013902425 | CH22: =CA22/BG22 -> 0.023693251 | CI22: =CB22/BG22 -> 0.0040894625 | CJ22: =CC22/BG22 -> 0.083908256 | CK22: =+BW22*20% -> 23547.9
A23: =A22+1 -> 16 | B23: 6 | C23: MABINAY1 | G23: 40 | H23: =SUM(F23*G23) -> 0 | I23: 17250 | J23: 50 | K23: =J23*I23 -> 862500 | M23: 60 | N23: =M23*L23 -> 0 | O23: 6998 | P23: 12 | Q23: =O23*P23 -> 83976 | S23: 12 | T23: =R23*S23 -> 0 | U23: 852 | V23: 8 | W23: =U23*V23 -> 6816 | X23: 698 | Y23: 12 | Z23: =X23*Y23 -> 8376 | AA23: 1318 | AB23: 10 | AC23: =AA23*AB23 -> 13180 | AD23: 260 | AE23: 25 | AF23: =AD23*AE23 -> 6500 | AG23: 496 | AH23: 7.5 | AI23: =AG23*AH23 -> 3720 | AK23: 15 | AL23: =AJ23*AK23 -> 0 | AM23: 100 | AN23: 10 | AO23: =AM23*AN23 -> 1000 | AP23: =R23+U23+X23+AA23+AD23+AG23+AM23 -> 3724 | AX23: 4087 | AZ23: =O23/(I23+F23+L23) -> 0.40568116 | BA23: =AP23/(I23+F23+L23) -> 0.21588406 | BB23: =AX23/O23 -> 0.58402401 | BC23: =H23+W23+Z23+AC23+AF23+T23+K23+N23 -> 897372 | BD23: =H23+AF23+T23+K23+N23 -> 869000 | BE23: =H23+W23+Z23+AC23+AF23+T23+K23+N23 -> 897372 | BF23: =H23+W23+Z23+AC23+AF23+AI23+T23+K23+N23 -> 901092 | BG23: 1059917 | BH23: 710921.03 | BI23: =+BH23/BG23% -> 67.073274 | BJ23: =SUM(BY23+BZ23+CA23+CB23) -> 70406.3 | BK23: =SUM(CF23+CG23+CH23+CI23) -> 0.066426239 | BL23: =B23 -> 6 | BM23: =CC23 -> 96000.5 | BN23: =+BU23/BM23 -> 2.7972644 | BO23: =CD23 -> 937 | BP23: =+BU23/BO23 -> 286.59422 | BQ23: =CE23 -> 26250 | BR23: =+BU23/BQ23 -> 10.230049 | BS23: =BU23-BM23-BO23-BQ23-BY23-BZ23-CA23-CB23 -> 74944.98 | BT23: =+BU23/BS23 -> 3.5831457 | BU23: 268538.78 | BV23: =+BU23/BG23% -> 25.335831 | BW23: =SUM(BG23-BH23-BU23) -> 80457.19 | BX23: =+BW23/BG23% -> 7.5908953 | BY23: 25944.3 | BZ23: 15910 | CA23: 20992 | CB23: 7560 | CC23: 96000.5 | CD23: 937 | CE23: 26250 | CF23: =BY23/BG23 -> 0.024477671 | CG23: =BZ23/BG23 -> 0.015010609 | CH23: =CA23/BG23 -> 0.019805324 | CI23: =CB23/BG23 -> 0.007132634 | CJ23: =CC23/BG23 -> 0.090573602 | CK23: =+BW23*20% -> 16091.438
A24: =A23+1 -> 17 | B24: 4 | C24: MABINAY2 | G24: 40 | H24: =SUM(F24*G24) -> 0 | I24: 7972 | J24: 50 | K24: =J24*I24 -> 398600 | M24: 60 | N24: =M24*L24 -> 0 | O24: 3155 | P24: 12 | Q24: =O24*P24 -> 37860 | R24: 200 | S24: 12 | T24: =R24*S24 -> 2400 | U24: 380 | V24: 8 | W24: =U24*V24 -> 3040 | X24: 304 | Y24: 12 | Z24: =X24*Y24 -> 3648 | AA24: 680 | AB24: 10 | AC24: =AA24*AB24 -> 6800 | AE24: 25 | AF24: =AD24*AE24 -> 0 | AG24: 248 | AH24: 7.5 | AI24: =AG24*AH24 -> 1860 | AK24: 15 | AL24: =AJ24*AK24 -> 0 | AM24: 83 | AN24: 10 | AO24: =AM24*AN24 -> 830 | AP24: =R24+U24+X24+AA24+AD24+AG24+AM24 -> 1895 | AX24: 1314 | AZ24: =O24/(I24+F24+L24) -> 0.39576016 | BA24: =AP24/(I24+F24+L24) -> 0.23770697 | BB24: =AX24/O24 -> 0.41648177 | BC24: =H24+W24+Z24+AC24+AF24+T24+K24+N24 -> 414488 | BD24: =H24+AF24+T24+K24+N24 -> 401000 | BE24: =H24+W24+Z24+AC24+AF24+T24+K24+N24 -> 414488 | BF24: =H24+W24+Z24+AC24+AF24+AI24+T24+K24+N24 -> 416348 | BG24: 480962 | BH24: 322470.72 | BI24: =+BH24/BG24% -> 67.047027 | BJ24: =SUM(BY24+BZ24+CA24+CB24) -> 35902.5 | BK24: =SUM(CF24+CG24+CH24+CI24) -> 0.074647269 | BL24: =B24 -> 4 | BM24: =CC24 -> 63250 | BN24: =+BU24/BM24 -> 2.5535107 | BO24: =CD24 -> 1812.5 | BP24: =+BU24/BO24 -> 89.108717 | BQ24: =CE24 -> 10000 | BR24: =+BU24/BQ24 -> 16.150955 | BS24: =BU24-BM24-BO24-BQ24-BY24-BZ24-CA24-CB24 -> 50544.55 | BT24: =+BU24/BS24 -> 3.19539 | BU24: 161509.55 | BV24: =+BU24/BG24% -> 33.580522 | BW24: =SUM(BG24-BH24-BU24) -> -3018.27 | BX24: =+BW24/BG24% -> -0.62754854 | BY24: 11119.5 | BZ24: 11137 | CA24: 10676 | CB24: 2970 | CC24: 63250 | CD24: 1812.5 | CE24: 10000 | CF24: =BY24/BG24 -> 0.02311929 | CG24: =BZ24/BG24 -> 0.023155676 | CH24: =CA24/BG24 -> 0.02219718 | CI24: =CB24/BG24 -> 0.006175124 | CJ24: =CC24/BG24 -> 0.13150727 | CK24: =+BW24*20% -> -603.654
A25: =A24+1 -> 18 | B25: 6 | C25: MANJUYOD | G25: 40 | H25: =SUM(F25*G25) -> 0 | I25: 18203.08 | J25: 50 | K25: =J25*I25 -> 910154 | M25: 60 | N25: =M25*L25 -> 0 | O25: 8775 | P25: 12 | Q25: =O25*P25 -> 105300 | R25: 715 | S25: 12 | T25: =R25*S25 -> 8580 | U25: 1019 | V25: 8 | W25: =U25*V25 -> 8152 | X25: 405 | Y25: 12 | Z25: =X25*Y25 -> 4860 | AA25: 1605 | AB25: 10 | AC25: =AA25*AB25 -> 16050 | AD25: 360 | AE25: 25 | AF25: =AD25*AE25 -> 9000 | AG25: 304 | AH25: 7.5 | AI25: =AG25*AH25 -> 2280 | AK25: 15 | AL25: =AJ25*AK25 -> 0 | AM25: 263 | AN25: 10 | AO25: =AM25*AN25 -> 2630 | AP25: =R25+U25+X25+AA25+AD25+AG25+AM25 -> 4671 | AX25: 2764 | AZ25: =O25/(I25+F25+L25) -> 0.48206128 | BA25: =AP25/(I25+F25+L25) -> 0.25660493 | BB25: =AX25/O25 -> 0.31498575 | BC25: =H25+W25+Z25+AC25+AF25+T25+K25+N25 -> 956796 | BD25: =H25+AF25+T25+K25+N25 -> 927734 | BE25: =H25+W25+Z25+AC25+AF25+T25+K25+N25 -> 956796 | BF25: =H25+W25+Z25+AC25+AF25+AI25+T25+K25+N25 -> 959076 | BG25: 1123129 | BH25: 770926.53 | BI25: =+BH25/BG25% -> 68.64096 | BJ25: =SUM(BY25+BZ25+CA25+CB25) -> 68132 | BK25: =SUM(CF25+CG25+CH25+CI25) -> 0.060662667 | BL25: =B25 -> 6 | BM25: =CC25 -> 80562.3 | BN25: =+BU25/BM25 -> 2.8386604 | BO25: =CD25 -> 2250 | BP25: =+BU25/BO25 -> 101.63956 | BQ25: =CE25 -> 25000 | BR25: =+BU25/BQ25 -> 9.1475604 | BS25: =BU25-BM25-BO25-BQ25-BY25-BZ25-CA25-CB25 -> 52744.71 | BT25: =+BU25/BS25 -> 4.3357715 | BU25: 228689.01 | BV25: =+BU25/BG25% -> 20.361776 | BW25: =SUM(BG25-BH25-BU25) -> 123513.46 | BX25: =+BW25/BG25% -> 10.997264 | BY25: 22133 | BZ25: 17501 | CA25: 23098 | CB25: 5400 | CC25: 80562.3 | CD25: 2250 | CE25: 25000 | CF25: =BY25/BG25 -> 0.019706552 | CG25: =BZ25/BG25 -> 0.01558236 | CH25: =CA25/BG25 -> 0.020565759 | CI25: =CB25/BG25 -> 0.0048079962 | CJ25: =CC25/BG25 -> 0.071730229 | CK25: =+BW25*20% -> 24702.692
A26: =A25+1 -> 19 | B26: 9 | C26: NOPH | G26: 40 | H26: =SUM(F26*G26) -> 0 | I26: 22829 | J26: 50 | K26: =J26*I26 -> 1141450 | M26: 60 | N26: =M26*L26 -> 0 | O26: 20438 | P26: 12 | Q26: =O26*P26 -> 245256 | S26: 12 | T26: =R26*S26 -> 0 | U26: 2454 | V26: 8 | W26: =U26*V26 -> 19632 | X26: 1279 | Y26: 12 | Z26: =X26*Y26 -> 15348 | AA26: 2126 | AB26: 10 | AC26: =AA26*AB26 -> 21260 | AD26: 680 | AE26: 25 | AF26: =AD26*AE26 -> 17000 | AG26: 789 | AH26: 7.5 | AI26: =AG26*AH26 -> 5917.5 | AK26: 15 | AL26: =AJ26*AK26 -> 0 | AM26: 614 | AN26: 10 | AO26: =AM26*AN26 -> 6140 | AP26: =R26+U26+X26+AA26+AD26+AG26+AM26 -> 7942 | AX26: 5069 | AZ26: =O26/(I26+F26+L26) -> 0.89526479 | BA26: =AP26/(I26+F26+L26) -> 0.34789084 | BB26: =AX26/O26 -> 0.2480184 | BC26: =H26+W26+Z26+AC26+AF26+T26+K26+N26 -> 1214690 | BD26: =H26+AF26+T26+K26+N26 -> 1158450 | BE26: =H26+W26+Z26+AC26+AF26+T26+K26+N26 -> 1214690 | BF26: =H26+W26+Z26+AC26+AF26+AI26+T26+K26+N26 -> 1220607.5 | BG26: 1571502.5 | BH26: 1067451.7 | BI26: =+BH26/BG26% -> 67.925552 | BJ26: =SUM(BY26+BZ26+CA26+CB26) -> 81401 | BK26: =SUM(CF26+CG26+CH26+CI26) -> 0.051798199 | BL26: =B26 -> 9 | BM26: =CC26 -> 127975 | BN26: =+BU26/BM26 -> 2.6389159 | BO26: =CD26 -> 1562.5 | BP26: =+BU26/BO26 -> 216.13777 | BQ26: =CE26 -> 38217.86 | BR26: =+BU26/BQ26 -> 8.8365822 | BS26: =BU26-BM26-BO26-BQ26-BY26-BZ26-CA26-CB26 -> 88558.9 | BT26: =+BU26/BS26 -> 3.8134536 | BU26: 337715.26 | BV26: =+BU26/BG26% -> 21.48996 | BW26: =SUM(BG26-BH26-BU26) -> 166335.5 | BX26: =+BW26/BG26% -> 10.584488 | BY26: 22239 | BZ26: 22274 | CA26: 31488 | CB26: 5400 | CC26: 127975 | CD26: 1562.5 | CE26: 38217.86 | CF26: =BY26/BG26 -> 0.014151425 | CG26: =BZ26/BG26 -> 0.014173697 | CH26: =CA26/BG26 -> 0.020036876 | CI26: =CB26/BG26 -> 0.003436202 | CJ26: =CC26/BG26 -> 0.081434805 | CK26: =+BW26*20% -> 33267.1
A27: =A26+1 -> 20 | B27: 5 | C27: PAMPLONA | G27: 40 | H27: =SUM(F27*G27) -> 0 | I27: 10774 | J27: 50 | K27: =J27*I27 -> 538700 | M27: 60 | N27: =M27*L27 -> 0 | O27: 3439 | P27: 12 | Q27: =O27*P27 -> 41268 | R27: 2500 | S27: 12 | T27: =R27*S27 -> 30000 | U27: 771 | V27: 8 | W27: =U27*V27 -> 6168 | X27: 201 | Y27: 12 | Z27: =X27*Y27 -> 2412 | AA27: 716 | AB27: 10 | AC27: =AA27*AB27 -> 7160 | AD27: 104 | AE27: 25 | AF27: =AD27*AE27 -> 2600 | AG27: 268 | AH27: 7.5 | AI27: =AG27*AH27 -> 2010 | AK27: 15 | AL27: =AJ27*AK27 -> 0 | AM27: 162 | AN27: 10 | AO27: =AM27*AN27 -> 1620 | AP27: =R27+U27+X27+AA27+AD27+AG27+AM27 -> 4722 | AX27: 2334 | AZ27: =O27/(I27+F27+L27) -> 0.31919436 | BA27: =AP27/(I27+F27+L27) -> 0.43827733 | BB27: =AX27/O27 -> 0.67868566 | BC27: =H27+W27+Z27+AC27+AF27+T27+K27+N27 -> 587040 | BD27: =H27+AF27+T27+K27+N27 -> 571300 | BE27: =H27+W27+Z27+AC27+AF27+T27+K27+N27 -> 587040 | BF27: =H27+W27+Z27+AC27+AF27+AI27+T27+K27+N27 -> 589050 | BG27: 677210 | BH27: 454569.8 | BI27: =+BH27/BG27% -> 67.123905 | BJ27: =SUM(BY27+BZ27+CA27+CB27) -> 49354.5 | BK27: =SUM(CF27+CG27+CH27+CI27) -> 0.072879166 | BL27: =B27 -> 5 | BM27: =CC27 -> 74412.5 | BN27: =+BU27/BM27 -> 2.5922739 | BO27: =CD27 -> 1750 | BP27: =+BU27/BO27 -> 110.22719 | BQ27: =CE27 -> 16000 | BR27: =+BU27/BQ27 -> 12.056099 | BS27: =BU27-BM27-BO27-BQ27-BY27-BZ27-CA27-CB27 -> 51380.58 | BT27: =+BU27/BS27 -> 3.7542897 | BU27: 192897.58 | BV27: =+BU27/BG27% -> 28.48416 | BW27: =SUM(BG27-BH27-BU27) -> 29742.62 | BX27: =+BW27/BG27% -> 4.3919346 | BY27: 18423.5 | BZ27: 11137 | CA27: 15744 | CB27: 4050 | CC27: 74412.5 | CD27: 1750 | CE27: 16000 | CF27: =BY27/BG27 -> 0.027205003 | CG27: =BZ27/BG27 -> 0.016445416 | CH27: =CA27/BG27 -> 0.023248328 | CI27: =CB27/BG27 -> 0.0059804197 | CJ27: =CC27/BG27 -> 0.10988098 | CK27: =+BW27*20% -> 5948.524
A28: =A27+1 -> 21 | B28: 4 | C28: QUEZON | G28: 40 | H28: =SUM(F28*G28) -> 0 | I28: 9611 | J28: 50 | K28: =J28*I28 -> 480550 | M28: 60 | N28: =M28*L28 -> 0 | O28: 4221 | P28: 12 | Q28: =O28*P28 -> 50652 | R28: 1830 | S28: 12 | T28: =R28*S28 -> 21960 | U28: 1174 | V28: 8 | W28: =U28*V28 -> 9392 | X28: 931 | Y28: 12 | Z28: =X28*Y28 -> 11172 | AA28: 1887 | AB28: 10 | AC28: =AA28*AB28 -> 18870 | AD28: 315 | AE28: 25 | AF28: =AD28*AE28 -> 7875 | AG28: 360 | AH28: 7.5 | AI28: =AG28*AH28 -> 2700 | AK28: 15 | AL28: =AJ28*AK28 -> 0 | AN28: 10 | AO28: =AM28*AN28 -> 0 | AP28: =R28+U28+X28+AA28+AD28+AG28+AM28 -> 6497 | AX28: 1976 | AZ28: =O28/(I28+F28+L28) -> 0.43918427 | BA28: =AP28/(I28+F28+L28) -> 0.67599625 | BB28: =AX28/O28 -> 0.46813551 | BC28: =H28+W28+Z28+AC28+AF28+T28+K28+N28 -> 549819 | BD28: =H28+AF28+T28+K28+N28 -> 510385 | BE28: =H28+W28+Z28+AC28+AF28+T28+K28+N28 -> 549819 | BF28: =H28+W28+Z28+AC28+AF28+AI28+T28+K28+N28 -> 552519 | BG28: 641258 | BH28: 426800.29 | BI28: =+BH28/BG28% -> 66.55672 | BJ28: =SUM(BY28+BZ28+CA28+CB28) -> 42804 | BK28: =SUM(CF28+CG28+CH28+CI28) -> 0.066750044 | BL28: =B28 -> 4 | BM28: =CC28 -> 61209 | BN28: =+BU28/BM28 -> 2.4651332 | BO28: =CD28 -> 6631.5 | BP28: =+BU28/BO28 -> 22.753275 | BQ28: =CE28 -> 12000 | BR28: =+BU28/BQ28 -> 12.574028 | BS28: =BU28-BM28-BO28-BQ28-BY28-BZ28-CA28-CB28 -> 28243.84 | BT28: =+BU28/BS28 -> 5.3423451 | BU28: 150888.34 | BV28: =+BU28/BG28% -> 23.530052 | BW28: =SUM(BG28-BH28-BU28) -> 63569.37 | BX28: =+BW28/BG28% -> 9.9132284 | BY28: 18426 | BZ28: 8650 | CA28: 9648 | CB28: 6080 | CC28: 61209 | CD28: 6631.5 | CE28: 12000 | CF28: =BY28/BG28 -> 0.028734144 | CG28: =BZ28/BG28 -> 0.01348911 | CH28: =CA28/BG28 -> 0.015045426 | CI28: =CB28/BG28 -> 0.0094813632 | CJ28: =CC28/BG28 -> 0.095451441 | CK28: =+BW28*20% -> 12713.874
A29: =A28+1 -> 22 | B29: 7 | C29: SAGAY1 | G29: 40 | H29: =SUM(F29*G29) -> 0 | I29: 26010 | J29: 50 | K29: =J29*I29 -> 1300500 | M29: 60 | N29: =M29*L29 -> 0 | O29: 8655 | P29: 12 | Q29: =O29*P29 -> 103860 | R29: 330 | S29: 12 | T29: =R29*S29 -> 3960 | U29: 910 | V29: 8 | W29: =U29*V29 -> 7280 | X29: 771 | Y29: 12 | Z29: =X29*Y29 -> 9252 | AA29: 1570 | AB29: 10 | AC29: =AA29*AB29 -> 15700 | AD29: 210 | AE29: 25 | AF29: =AD29*AE29 -> 5250 | AG29: 169 | AH29: 7.5 | AI29: =AG29*AH29 -> 1267.5 | AK29: 15 | AL29: =AJ29*AK29 -> 0 | AM29: 277 | AN29: 10 | AO29: =AM29*AN29 -> 2770 | AP29: =R29+U29+X29+AA29+AD29+AG29+AM29 -> 4237 | AX29: 4357 | AZ29: =O29/(I29+F29+L29) -> 0.33275663 | BA29: =AP29/(I29+F29+L29) -> 0.16289889 | BB29: =AX29/O29 -> 0.50340843 | BC29: =H29+W29+Z29+AC29+AF29+T29+K29+N29 -> 1341942 | BD29: =H29+AF29+T29+K29+N29 -> 1309710 | BE29: =H29+W29+Z29+AC29+AF29+T29+K29+N29 -> 1341942 | BF29: =H29+W29+Z29+AC29+AF29+AI29+T29+K29+N29 -> 1343209.5 | BG29: 1534824.5 | BH29: 1031408.1 | BI29: =+BH29/BG29% -> 67.200394 | BJ29: =SUM(BY29+BZ29+CA29+CB29) -> 88738 | BK29: =SUM(CF29+CG29+CH29+CI29) -> 0.057816382 | BL29: =B29 -> 7 | BM29: =CC29 -> 114398.74 | BN29: =+BU29/BM29 -> 2.9277669 | BO29: =CD29 -> 3654.84 | BP29: =+BU29/BO29 -> 91.640904 | BQ29: =CE29 -> 20000 | BR29: =+BU29/BQ29 -> 16.746642 | BS29: =BU29-BM29-BO29-BQ29-BY29-BZ29-CA29-CB29 -> 108141.26 | BT29: =+BU29/BS29 -> 3.097179 | BU29: 334932.84 | BV29: =+BU29/BG29% -> 21.822224 | BW29: =SUM(BG29-BH29-BU29) -> 168483.55 | BX29: =+BW29/BG29% -> 10.977382 | BY29: 28582 | BZ29: 27680 | CA29: 28636 | CB29: 3840 | CC29: 114398.74 | CD29: 3654.84 | CE29: 20000 | CF29: =BY29/BG29 -> 0.018622325 | CG29: =BZ29/BG29 -> 0.018034635 | CH29: =CA29/BG29 -> 0.018657508 | CI29: =CB29/BG29 -> 0.0025019147 | CJ29: =CC29/BG29 -> 0.074535388 | CK29: =+BW29*20% -> 33696.71
A30: =A29+1 -> 23 | B30: 2 | C30: SAGAY2 | G30: 40 | H30: =SUM(F30*G30) -> 0 | I30: 7326 | J30: 50 | K30: =J30*I30 -> 366300 | M30: 60 | N30: =M30*L30 -> 0 | O30: 2712 | P30: 12 | Q30: =O30*P30 -> 32544 | R30: 2290 | S30: 12 | T30: =R30*S30 -> 27480 | U30: 222 | V30: 8 | W30: =U30*V30 -> 1776 | X30: 177 | Y30: 12 | Z30: =X30*Y30 -> 2124 | AA30: 233 | AB30: 10 | AC30: =AA30*AB30 -> 2330 | AD30: 84 | AE30: 25 | AF30: =AD30*AE30 -> 2100 | AG30: 83 | AH30: 7.5 | AI30: =AG30*AH30 -> 622.5 | AK30: 15 | AL30: =AJ30*AK30 -> 0 | AM30: 90 | AN30: 10 | AO30: =AM30*AN30 -> 900 | AP30: =R30+U30+X30+AA30+AD30+AG30+AM30 -> 3179 | AX30: 893 | AZ30: =O30/(I30+F30+L30) -> 0.37018837 | BA30: =AP30/(I30+F30+L30) -> 0.43393393 | BB30: =AX30/O30 -> 0.32927729 | BC30: =H30+W30+Z30+AC30+AF30+T30+K30+N30 -> 402110 | BD30: =H30+AF30+T30+K30+N30 -> 395880 | BE30: =H30+W30+Z30+AC30+AF30+T30+K30+N30 -> 402110 | BF30: =H30+W30+Z30+AC30+AF30+AI30+T30+K30+N30 -> 402732.5 | BG30: 453453.5 | BH30: 302381.15 | BI30: =+BH30/BG30% -> 66.684048 | BJ30: =SUM(BY30+BZ30+CA30+CB30) -> 29946 | BK30: =SUM(CF30+CG30+CH30+CI30) -> 0.066039848 | BL30: =B30 -> 2 | BM30: =CC30 -> 47705.7 | BN30: =+BU30/BM30 -> 3.0738121 | BO30: =CD30 -> 2499.72 | BP30: =+BU30/BO30 -> 58.661914 | BQ30: =CE30 -> 14000 | BR30: =+BU30/BQ30 -> 10.474169 | BS30: =BU30-BM30-BO30-BQ30-BY30-BZ30-CA30-CB30 -> 52486.94 | BT30: =+BU30/BS30 -> 2.7938066 | BU30: 146638.36 | BV30: =+BU30/BG30% -> 32.338125 | BW30: =SUM(BG30-BH30-BU30) -> 4433.99 | BX30: =+BW30/BG30% -> 0.97782683 | BY30: 10719 | BZ30: 8650 | CA30: 8907 | CB30: 1670 | CC30: 47705.7 | CD30: 2499.72 | CE30: 14000 | CF30: =BY30/BG30 -> 0.023638587 | CG30: =BZ30/BG30 -> 0.019075826 | CH30: =CA30/BG30 -> 0.019642587 | CI30: =CB30/BG30 -> 0.0036828473 | CJ30: =CC30/BG30 -> 0.10520527 | CK30: =+BW30*20% -> 886.798
A31: =A30+1 -> 24 | B31: 5 | C31: SAN CARLOS1 | G31: 40 | H31: =SUM(F31*G31) -> 0 | I31: 11174 | J31: 50 | K31: =J31*I31 -> 558700 | M31: 60 | N31: =M31*L31 -> 0 | O31: 4439 | P31: 12 | Q31: =O31*P31 -> 53268 | R31: 4685 | S31: 12 | T31: =R31*S31 -> 56220 | U31: 539 | V31: 8 | W31: =U31*V31 -> 4312 | X31: 624 | Y31: 12 | Z31: =X31*Y31 -> 7488 | AA31: 761 | AB31: 10 | AC31: =AA31*AB31 -> 7610 | AD31: 145 | AE31: 25 | AF31: =AD31*AE31 -> 3625 | AH31: 7.5 | AI31: =AG31*AH31 -> 0 | AK31: 15 | AL31: =AJ31*AK31 -> 0 | AM31: 212 | AN31: 10 | AO31: =AM31*AN31 -> 2120 | AP31: =R31+U31+X31+AA31+AD31+AG31+AM31 -> 6966 | AX31: 1178 | AZ31: =O31/(I31+F31+L31) -> 0.3972615 | BA31: =AP31/(I31+F31+L31) -> 0.62341149 | BB31: =AX31/O31 -> 0.26537508 | BC31: =H31+W31+Z31+AC31+AF31+T31+K31+N31 -> 637955 | BD31: =H31+AF31+T31+K31+N31 -> 618545 | BE31: =H31+W31+Z31+AC31+AF31+T31+K31+N31 -> 637955 | BF31: =H31+W31+Z31+AC31+AF31+AI31+T31+K31+N31 -> 637955 | BG31: 716363 | BH31: 477019.61 | BI31: =+BH31/BG31% -> 66.589091 | BJ31: =SUM(BY31+BZ31+CA31+CB31) -> 58059 | BK31: =SUM(CF31+CG31+CH31+CI31) -> 0.081046899 | BL31: =B31 -> 5 | BM31: =CC31 -> 76549.98 | BN31: =+BU31/BM31 -> 2.453618 | BO31: =CD31 -> 3462.48 | BP31: =+BU31/BO31 -> 54.24563 | BQ31: =CE31 -> 15000 | BR31: =+BU31/BQ31 -> 12.521627 | BS31: =BU31-BM31-BO31-BQ31-BY31-BZ31-CA31-CB31 -> 34752.95 | BT31: =+BU31/BS31 -> 5.4045602 | BU31: 187824.41 | BV31: =+BU31/BG31% -> 26.219167 | BW31: =SUM(BG31-BH31-BU31) -> 51518.98 | BX31: =+BW31/BG31% -> 7.1917422 | BY31: 22129 | BZ31: 15570 | CA31: 13320 | CB31: 7040 | CC31: 76549.98 | CD31: 3462.48 | CE31: 15000 | CF31: =BY31/BG31 -> 0.030890763 | CG31: =BZ31/BG31 -> 0.021734791 | CH31: =CA31/BG31 -> 0.018593925 | CI31: =CB31/BG31 -> 0.0098274199 | CJ31: =CC31/BG31 -> 0.1068592 | CK31: =+BW31*20% -> 10303.796
A32: =A31+1 -> 25 | B32: 6 | C32: SAN CARLOS2 | G32: 40 | H32: =SUM(F32*G32) -> 0 | I32: 13382 | J32: 50 | K32: =J32*I32 -> 669100 | M32: 60 | N32: =M32*L32 -> 0 | O32: 7809 | P32: 12 | Q32: =O32*P32 -> 93708 | R32: 3440 | S32: 12 | T32: =R32*S32 -> 41280 | U32: 839 | V32: 8 | W32: =U32*V32 -> 6712 | X32: 930 | Y32: 12 | Z32: =X32*Y32 -> 11160 | AA32: 1390 | AB32: 10 | AC32: =AA32*AB32 -> 13900 | AD32: 200 | AE32: 25 | AF32: =AD32*AE32 -> 5000 | AG32: 85 | AH32: 7.5 | AI32: =AG32*AH32 -> 637.5 | AK32: 15 | AL32: =AJ32*AK32 -> 0 | AM32: 247 | AN32: 10 | AO32: =AM32*AN32 -> 2470 | AP32: =R32+U32+X32+AA32+AD32+AG32+AM32 -> 7131 | AX32: 2874 | AZ32: =O32/(I32+F32+L32) -> 0.58354506 | BA32: =AP32/(I32+F32+L32) -> 0.53287999 | BB32: =AX32/O32 -> 0.36803688 | BC32: =H32+W32+Z32+AC32+AF32+T32+K32+N32 -> 747152 | BD32: =H32+AF32+T32+K32+N32 -> 715380 | BE32: =H32+W32+Z32+AC32+AF32+T32+K32+N32 -> 747152 | BF32: =H32+W32+Z32+AC32+AF32+AI32+T32+K32+N32 -> 747789.5 | BG32: 900413.5 | BH32: 593503.62 | BI32: =+BH32/BG32% -> 65.914563 | BJ32: =SUM(BY32+BZ32+CA32+CB32) -> 61999 | BK32: =SUM(CF32+CG32+CH32+CI32) -> 0.068856142 | BL32: =B32 -> 6 | BM32: =CC32 -> 98636.5 | BN32: =+BU32/BM32 -> 2.4609643 | BO32: =CD32 -> 7117.32 | BP32: =+BU32/BO32 -> 34.105662 | BQ32: =CE32 -> 9316.9 | BR32: =+BU32/BQ32 -> 26.053828 | BS32: =BU32-BM32-BO32-BQ32-BY32-BZ32-CA32-CB32 -> 65671.19 | BT32: =+BU32/BS32 -> 3.6963075 | BU32: 242740.91 | BV32: =+BU32/BG32% -> 26.958826 | BW32: =SUM(BG32-BH32-BU32) -> 64168.97 | BX32: =+BW32/BG32% -> 7.1266113 | BY32: 22133 | BZ32: 15570 | CA32: 18216 | CB32: 6080 | CC32: 98636.5 | CD32: 7117.32 | CE32: 9316.9 | CF32: =BY32/BG32 -> 0.024580929 | CG32: =BZ32/BG32 -> 0.017292055 | CH32: =CA32/BG32 -> 0.020230705 | CI32: =CB32/BG32 -> 0.0067524532 | CJ32: =CC32/BG32 -> 0.10954578 | CK32: =+BW32*20% -> 12833.794
A33: =A32+1 -> 26 | B33: 4 | C33: SAN CARLOS5 | G33: 40 | H33: =SUM(F33*G33) -> 0 | I33: 10252 | J33: 50 | K33: =J33*I33 -> 512600 | M33: 60 | N33: =M33*L33 -> 0 | O33: 3712 | P33: 12 | Q33: =O33*P33 -> 44544 | R33: 3657 | S33: 12 | T33: =R33*S33 -> 43884 | U33: 439 | V33: 8 | W33: =U33*V33 -> 3512 | X33: 671 | Y33: 12 | Z33: =X33*Y33 -> 8052 | AA33: 807 | AB33: 10 | AC33: =AA33*AB33 -> 8070 | AD33: 198 | AE33: 25 | AF33: =AD33*AE33 -> 4950 | AG33: 120 | AH33: 7.5 | AI33: =AG33*AH33 -> 900 | AK33: 15 | AL33: =AJ33*AK33 -> 0 | AM33: 189 | AN33: 10 | AO33: =AM33*AN33 -> 1890 | AP33: =R33+U33+X33+AA33+AD33+AG33+AM33 -> 6081 | AX33: 989 | AZ33: =O33/(I33+F33+L33) -> 0.36207569 | BA33: =AP33/(I33+F33+L33) -> 0.59315256 | BB33: =AX33/O33 -> 0.26643319 | BC33: =H33+W33+Z33+AC33+AF33+T33+K33+N33 -> 581068 | BD33: =H33+AF33+T33+K33+N33 -> 561434 | BE33: =H33+W33+Z33+AC33+AF33+T33+K33+N33 -> 581068 | BF33: =H33+W33+Z33+AC33+AF33+AI33+T33+K33+N33 -> 581968 | BG33: 647507 | BH33: 433072.03 | BI33: =+BH33/BG33% -> 66.882988 | BJ33: =SUM(BY33+BZ33+CA33+CB33) -> 47539 | BK33: =SUM(CF33+CG33+CH33+CI33) -> 0.073418511 | BL33: =B33 -> 4 | BM33: =CC33 -> 63800.78 | BN33: =+BU33/BM33 -> 2.8160629 | BO33: =CD33 -> 3398.36 | BP33: =+BU33/BO33 -> 52.86874 | BQ33: =CE33 -> 30000 | BR33: =+BU33/BQ33 -> 5.9889003 | BS33: =BU33-BM33-BO33-BQ33-BY33-BZ33-CA33-CB33 -> 34928.87 | BT33: =+BU33/BS33 -> 5.1437968 | BU33: 179667.01 | BV33: =+BU33/BG33% -> 27.747501 | BW33: =SUM(BG33-BH33-BU33) -> 34767.96 | BX33: =+BW33/BG33% -> 5.3695111 | BY33: 18426 | BZ33: 12110 | CA33: 12203 | CB33: 4800 | CC33: 63800.78 | CD33: 3398.36 | CE33: 30000 | CF33: =BY33/BG33 -> 0.028456835 | CG33: =BZ33/BG33 -> 0.018702501 | CH33: =CA33/BG33 -> 0.018846128 | CI33: =CB33/BG33 -> 0.0074130473 | CJ33: =CC33/BG33 -> 0.098532958 | CK33: =+BW33*20% -> 6953.592
A34: =A33+1 -> 27 | B34: 4 | C34: SAN CARLOS7 | G34: 40 | H34: =SUM(F34*G34) -> 0 | I34: 9962 | J34: 50 | K34: =J34*I34 -> 498100 | M34: 60 | N34: =M34*L34 -> 0 | O34: 4438 | P34: 12 | Q34: =O34*P34 -> 53256 | R34: 4531 | S34: 12 | T34: =R34*S34 -> 54372 | U34: 621 | V34: 8 | W34: =U34*V34 -> 4968 | X34: 775 | Y34: 12 | Z34: =X34*Y34 -> 9300 | AA34: 896 | AB34: 10 | AC34: =AA34*AB34 -> 8960 | AD34: 134 | AE34: 25 | AF34: =AD34*AE34 -> 3350 | AG34: 206 | AH34: 7.5 | AI34: =AG34*AH34 -> 1545 | AK34: 15 | AL34: =AJ34*AK34 -> 0 | AM34: 230 | AN34: 10 | AO34: =AM34*AN34 -> 2300 | AP34: =R34+U34+X34+AA34+AD34+AG34+AM34 -> 7393 | AX34: 1744 | AZ34: =O34/(I34+F34+L34) -> 0.44549287 | BA34: =AP34/(I34+F34+L34) -> 0.74212006 | BB34: =AX34/O34 -> 0.39296981 | BC34: =H34+W34+Z34+AC34+AF34+T34+K34+N34 -> 579050 | BD34: =H34+AF34+T34+K34+N34 -> 555822 | BE34: =H34+W34+Z34+AC34+AF34+T34+K34+N34 -> 579050 | BF34: =H34+W34+Z34+AC34+AF34+AI34+T34+K34+N34 -> 580595 | BG34: 670061 | BH34: 443869.26 | BI34: =+BH34/BG34% -> 66.243112 | BJ34: =SUM(BY34+BZ34+CA34+CB34) -> 51447 | BK34: =SUM(CF34+CG34+CH34+CI34) -> 0.076779577 | BL34: =B34 -> 4 | BM34: =CC34 -> 63906.72 | BN34: =+BU34/BM34 -> 2.8867017 | BO34: =CD34 -> 2308.32 | BP34: =+BU34/BO34 -> 79.919439 | BQ34: =CE34 -> 20000 | BR34: =+BU34/BQ34 -> 9.223982 | BS34: =BU34-BM34-BO34-BQ34-BY34-BZ34-CA34-CB34 -> 46817.6 | BT34: =+BU34/BS34 -> 3.9403908 | BU34: 184479.64 | BV34: =+BU34/BG34% -> 27.531768 | BW34: =SUM(BG34-BH34-BU34) -> 41712.1 | BX34: =+BW34/BG34% -> 6.2251198 | BY34: 22133 | BZ34: 12110 | CA34: 10854 | CB34: 6350 | CC34: 63906.72 | CD34: 2308.32 | CE34: 20000 | CF34: =BY34/BG34 -> 0.033031321 | CG34: =BZ34/BG34 -> 0.018072981 | CH34: =CA34/BG34 -> 0.016198525 | CI34: =CB34/BG34 -> 0.0094767491 | CJ34: =CC34/BG34 -> 0.095374481 | CK34: =+BW34*20% -> 8342.42
A35: =A34+1 -> 28 | B35: 2 | C35: SANTANDER | G35: 40 | H35: =SUM(F35*G35) -> 0 | I35: 3753 | J35: 50 | K35: =J35*I35 -> 187650 | M35: 60 | N35: =M35*L35 -> 0 | O35: 1739 | P35: 12 | Q35: =O35*P35 -> 20868 | R35: 870 | S35: 12 | T35: =R35*S35 -> 10440 | U35: 828 | V35: 8 | W35: =U35*V35 -> 6624 | X35: 725 | Y35: 12 | Z35: =X35*Y35 -> 8700 | AA35: 844 | AB35: 10 | AC35: =AA35*AB35 -> 8440 | AD35: 392 | AE35: 25 | AF35: =AD35*AE35 -> 9800 | AG35: 473 | AH35: 7.5 | AI35: =AG35*AH35 -> 3547.5 | AK35: 15 | AL35: =AJ35*AK35 -> 0 | AN35: 10 | AO35: =AM35*AN35 -> 0 | AP35: =R35+U35+X35+AA35+AD35+AG35+AM35 -> 4132 | AX35: 895 | AZ35: =O35/(I35+F35+L35) -> 0.46336264 | BA35: =AP35/(I35+F35+L35) -> 1.1009859 | BB35: =AX35/O35 -> 0.5146636 | BC35: =H35+W35+Z35+AC35+AF35+T35+K35+N35 -> 231654 | BD35: =H35+AF35+T35+K35+N35 -> 207890 | BE35: =H35+W35+Z35+AC35+AF35+T35+K35+N35 -> 231654 | BF35: =H35+W35+Z35+AC35+AF35+AI35+T35+K35+N35 -> 235201.5 | BG35: 273920.5 | BH35: 182620.65 | BI35: =+BH35/BG35% -> 66.669216 | BJ35: =SUM(BY35+BZ35+CA35+CB35) -> 22314 | BK35: =SUM(CF35+CG35+CH35+CI35) -> 0.081461592 | BL35: =B35 -> 2 | BM35: =CC35 -> 32843 | BN35: =+BU35/BM35 -> 2.7271824 | BO35: =CD35 -> 1500 | BP35: =+BU35/BO35 -> 59.712567 | BQ35: =CE35 -> 12000 | BR35: =+BU35/BQ35 -> 7.4640708 | BS35: =BU35-BM35-BO35-BQ35-BY35-BZ35-CA35-CB35 -> 20911.85 | BT35: =+BU35/BS35 -> 4.2831624 | BU35: 89568.85 | BV35: =+BU35/BG35% -> 32.698849 | BW35: =SUM(BG35-BH35-BU35) -> 1731 | BX35: =+BW35/BG35% -> 0.63193518 | BY35: 9082 | BZ35: 6364 | CA35: 5248 | CB35: 1620 | CC35: 32843 | CD35: 1500 | CE35: 12000 | CF35: =BY35/BG35 -> 0.033155605 | CG35: =BZ35/BG35 -> 0.023233018 | CH35: =CA35/BG35 -> 0.019158844 | CI35: =CB35/BG35 -> 0.0059141247 | CJ35: =CC35/BG35 -> 0.11989975 | CK35: =+BW35*20% -> 346.2
A36: =A35+1 -> 29 | B36: 2 | C36: STA.AGUEDA | G36: 40 | H36: =SUM(F36*G36) -> 0 | I36: 4280 | J36: 50 | K36: =J36*I36 -> 214000 | M36: 60 | N36: =M36*L36 -> 0 | O36: 1638 | P36: 12 | Q36: =O36*P36 -> 19656 | R36: 4040 | S36: 12 | T36: =R36*S36 -> 48480 | U36: 354 | V36: 8 | W36: =U36*V36 -> 2832 | X36: 239 | Y36: 12 | Z36: =X36*Y36 -> 2868 | AA36: 564 | AB36: 10 | AC36: =AA36*AB36 -> 5640 | AD36: 266 | AE36: 25 | AF36: =AD36*AE36 -> 6650 | AH36: 7.5 | AI36: =AG36*AH36 -> 0 | AK36: 15 | AL36: =AJ36*AK36 -> 0 | AN36: 10 | AO36: =AM36*AN36 -> 0 | AP36: =R36+U36+X36+AA36+AD36+AG36+AM36 -> 5463 | AX36: 476 | AZ36: =O36/(I36+F36+L36) -> 0.38271028 | BA36: =AP36/(I36+F36+L36) -> 1.2764019 | BB36: =AX36/O36 -> 0.29059829 | BC36: =H36+W36+Z36+AC36+AF36+T36+K36+N36 -> 280470 | BD36: =H36+AF36+T36+K36+N36 -> 269130 | BE36: =H36+W36+Z36+AC36+AF36+T36+K36+N36 -> 280470 | BF36: =H36+W36+Z36+AC36+AF36+AI36+T36+K36+N36 -> 280470 | BG36: 309718 | BH36: 204263.09 | BI36: =+BH36/BG36% -> 65.951314 | BJ36: =SUM(BY36+BZ36+CA36+CB36) -> 25554 | BK36: =SUM(CF36+CG36+CH36+CI36) -> 0.082507313 | BL36: =B36 -> 2 | BM36: =CC36 -> 32050 | BN36: =+BU36/BM36 -> 2.6980512 | BO36: =CD36 -> 1875 | BP36: =+BU36/BO36 -> 46.118688 | BQ36: =CE36 -> 10000 | BR36: =+BU36/BQ36 -> 8.647254 | BS36: =BU36-BM36-BO36-BQ36-BY36-BZ36-CA36-CB36 -> 16993.54 | BT36: =+BU36/BS36 -> 5.0885537 | BU36: 86472.54 | BV36: =+BU36/BG36% -> 27.919766 | BW36: =SUM(BG36-BH36-BU36) -> 18982.37 | BX36: =+BW36/BG36% -> 6.1289205 | BY36: 11010 | BZ36: 6364 | CA36: 6560 | CB36: 1620 | CC36: 32050 | CD36: 1875 | CE36: 10000 | CF36: =BY36/BG36 -> 0.035548467 | CG36: =BZ36/BG36 -> 0.020547724 | CH36: =CA36/BG36 -> 0.021180558 | CI36: =CB36/BG36 -> 0.0052305646 | CJ36: =CC36/BG36 -> 0.10348123 | CK36: =+BW36*20% -> 3796.474
A37: =A36+1 -> 30 | B37: 5 | C37: STA.ROSA | G37: 40 | H37: =SUM(F37*G37) -> 0 | I37: 9083 | J37: 50 | K37: =J37*I37 -> 454150 | M37: 60 | N37: =M37*L37 -> 0 | O37: 7994 | P37: 12 | Q37: =O37*P37 -> 95928 | R37: 8170 | S37: 12 | T37: =R37*S37 -> 98040 | U37: 539 | V37: 8 | W37: =U37*V37 -> 4312 | X37: 270 | Y37: 12 | Z37: =X37*Y37 -> 3240 | AA37: 722 | AB37: 10 | AC37: =AA37*AB37 -> 7220 | AD37: 350 | AE37: 25 | AF37: =AD37*AE37 -> 8750 | AG37: 890 | AH37: 7.5 | AI37: =AG37*AH37 -> 6675 | AK37: 15 | AL37: =AJ37*AK37 -> 0 | AM37: 406 | AN37: 10 | AO37: =AM37*AN37 -> 4060 | AP37: =R37+U37+X37+AA37+AD37+AG37+AM37 -> 11347 | AX37: 2856 | AZ37: =O37/(I37+F37+L37) -> 0.88010569 | BA37: =AP37/(I37+F37+L37) -> 1.2492569 | BB37: =AX37/O37 -> 0.35726795 | BC37: =H37+W37+Z37+AC37+AF37+T37+K37+N37 -> 575712 | BD37: =H37+AF37+T37+K37+N37 -> 560940 | BE37: =H37+W37+Z37+AC37+AF37+T37+K37+N37 -> 575712 | BF37: =H37+W37+Z37+AC37+AF37+AI37+T37+K37+N37 -> 582387 | BG37: 736294 | BH37: 487405.33 | BI37: =+BH37/BG37% -> 66.197107 | BJ37: =SUM(BY37+BZ37+CA37+CB37) -> 50581.5 | BK37: =SUM(CF37+CG37+CH37+CI37) -> 0.068697422 | BL37: =B37 -> 5 | BM37: =CC37 -> 64762.5 | BN37: =+BU37/BM37 -> 3.4637608 | BO37: =CD37 -> 4562.5 | BP37: =+BU37/BO37 -> 49.166424 | BQ37: =CE37 -> 44000 | BR37: =+BU37/BQ37 -> 5.098223 | BS37: =BU37-BM37-BO37-BQ37-BY37-BZ37-CA37-CB37 -> 60415.31 | BT37: =+BU37/BS37 -> 3.7129961 | BU37: 224321.81 | BV37: =+BU37/BG37% -> 30.466337 | BW37: =SUM(BG37-BH37-BU37) -> 24566.86 | BX37: =+BW37/BG37% -> 3.3365558 | BY37: 18532.5 | BZ37: 15910 | CA37: 13169 | CB37: 2970 | CC37: 64762.5 | CD37: 4562.5 | CE37: 44000 | CF37: =BY37/BG37 -> 0.025169973 | CG37: =BZ37/BG37 -> 0.021608216 | CH37: =CA37/BG37 -> 0.017885519 | CI37: =CB37/BG37 -> 0.0040337148 | CJ37: =CC37/BG37 -> 0.087957392 | CK37: =+BW37*20% -> 4913.372
A38: =A37+1 -> 31 | B38: ,9 | C38: TANJAY1 | G38: 40 | H38: =SUM(F38*G38) -> 0 | I38: 24837 | J38: 50 | K38: =J38*I38 -> 1241850 | M38: 60 | N38: =M38*L38 -> 0 | O38: 12398 | P38: 12 | Q38: =O38*P38 -> 148776 | S38: 12 | T38: =R38*S38 -> 0 | U38: 816 | V38: 8 | W38: =U38*V38 -> 6528 | X38: 474 | Y38: 12 | Z38: =X38*Y38 -> 5688 | AA38: 1049 | AB38: 10 | AC38: =AA38*AB38 -> 10490 | AD38: 490 | AE38: 25 | AF38: =AD38*AE38 -> 12250 | AG38: 165 | AH38: 7.5 | AI38: =AG38*AH38 -> 1237.5 | AK38: 15 | AL38: =AJ38*AK38 -> 0 | AM38: 369 | AN38: 10 | AO38: =AM38*AX37 -> 1053864 | AP38: =R38+U38+X38+AA38+AD38+AG38+AM38 -> 3363 | AX38: 3514 | AZ38: =O38/(I38+F38+L38) -> 0.49917462 | BA38: =AP38/(I38+F38+L38) -> 0.13540283 | BB38: =AX38/O38 -> 0.28343281 | BC38: =H38+W38+Z38+AC38+AF38+T38+K38+N38 -> 1276806 | BD38: =H38+AF38+T38+K38+N38 -> 1254100 | BE38: =H38+W38+Z38+AC38+AF38+T38+K38+N38 -> 1276806 | BF38: =H38+W38+Z38+AC38+AF38+AI38+T38+K38+N38 -> 1278043.5 | BG38: 1499043.5 | BH38: 1025984.2 | BI38: =+BH38/BG38% -> 68.442594 | BJ38: =SUM(BY38+BZ38+CA38+CB38) -> 91838 | BK38: =SUM(CF38+CG38+CH38+CI38) -> 0.0612644 | BL38: =B38 -> ,9 | BM38: =CC38 -> 132852.5 | BN38: =+BU38/BM38 -> 2.5794163 | BO38: =CD38 -> 2978 | BP38: =+BU38/BO38 -> 115.07116 | BQ38: =CE38 -> 30500 | BR38: =+BU38/BQ38 -> 11.235472 | BS38: =BU38-BM38-BO38-BQ38-BY38-BZ38-CA38-CB38 -> 84513.41 | BT38: =+BU38/BS38 -> 4.0547637 | BU38: 342681.91 | BV38: =+BU38/BG38% -> 22.860038 | BW38: =SUM(BG38-BH38-BU38) -> 130377.34 | BX38: =+BW38/BG38% -> 8.6973687 | BY38: 33140 | BZ38: 22274 | CA38: 28864 | CB38: 7560 | CC38: 132852.5 | CD38: 2978 | CE38: 30500 | CF38: =BY38/BG38 -> 0.022107431 | CG38: =BZ38/BG38 -> 0.014858808 | CH38: =CA38/BG38 -> 0.019254945 | CI38: =CB38/BG38 -> 0.0050432159 | CJ38: =CC38/BG38 -> 0.088624846 | CK38: =+BW38*20% -> 26075.468
A39: =A38+1 -> 32 | B39: ,2 | C39: TANJAY2 | G39: 40 | H39: =SUM(F39*G39) -> 0 | I39: 3653 | J39: 50 | K39: =J39*I39 -> 182650 | M39: 60 | N39: =M39*L39 -> 0 | O39: 2452 | P39: 12 | Q39: =O39*P39 -> 29424 | R39: 570 | S39: 12 | T39: =R39*S39 -> 6840 | U39: 234 | V39: 8 | W39: =U39*V39 -> 1872 | X39: 185 | Y39: 12 | Z39: =X39*Y39 -> 2220 | AA39: 359 | AB39: 10 | AC39: =AA39*AB39 -> 3590 | AD39: 140 | AE39: 25 | AF39: =AD39*AE39 -> 3500 | AH39: 7.5 | AI39: =AG39*AH39 -> 0 | AK39: 15 | AL39: =AJ39*AK39 -> 0 | AM39: 132 | AN39: 10 | AO39: =AM39*AN39 -> 1320 | AP39: =R39+U39+X39+AA39+AD39+AG39+AM39 -> 1620 | AX39: 1056 | AZ39: =O39/(I39+F39+L39) -> 0.67122913 | BA39: =AP39/(I39+F39+L39) -> 0.44347112 | BB39: =AX39/O39 -> 0.43066884 | BC39: =H39+W39+Z39+AC39+AF39+T39+K39+N39 -> 200672 | BD39: =H39+AF39+T39+K39+N39 -> 192990 | BE39: =H39+W39+Z39+AC39+AF39+T39+K39+N39 -> 200672 | BF39: =H39+W39+Z39+AC39+AF39+AI39+T39+K39+N39 -> 200672 | BG39: 252628 | BH39: 171210.75 | BI39: =+BH39/BG39% -> 67.771882 | BJ39: =SUM(BY39+BZ39+CA39+CB39) -> 17980.5 | BK39: =SUM(CF39+CG39+CH39+CI39) -> 0.071173821 | BL39: =B39 -> ,2 | BM39: =CC39 -> 34787.5 | BN39: =+BU39/BM39 -> 2.3514731 | BO39: =CD39 -> 0 | BP39: =+BU39/BO39 -> #DIV/0! | BQ39: =CE39 -> 15000 | BR39: =+BU39/BQ39 -> 5.453458 | BS39: =BU39-BM39-BO39-BQ39-BY39-BZ39-CA39-CB39 -> 14033.87 | BT39: =+BU39/BS39 -> 5.828889 | BU39: 81801.87 | BV39: =+BU39/BG39% -> 32.380366 | BW39: =SUM(BG39-BH39-BU39) -> -384.62 | BX39: =+BW39/BG39% -> -0.15224757 | BY39: 3706.5 | BZ39: 6364 | CA39: 6560 | CB39: 1350 | CC39: 34787.5 | CE39: 15000 | CF39: =BY39/BG39 -> 0.01467177 | CG39: =BZ39/BG39 -> 0.02519119 | CH39: =CA39/BG39 -> 0.025967035 | CI39: =CB39/BG39 -> 0.0053438257 | CJ39: =CC39/BG39 -> 0.13770247 | CK39: =+BW39*20% -> -76.924
A40: =A39+1 -> 33 | B40: 3 | C40: TAYASAN | G40: 40 | H40: =SUM(F40*G40) -> 0 | I40: 10690 | J40: 50 | K40: =J40*I40 -> 534500 | M40: 60 | N40: =M40*L40 -> 0 | O40: 3580 | P40: 12 | Q40: =O40*P40 -> 42960 | R40: 2750 | S40: 12 | T40: =R40*S40 -> 33000 | U40: 597 | V40: 8 | W40: =U40*V40 -> 4776 | X40: 416 | Y40: 12 | Z40: =X40*Y40 -> 4992 | AA40: 914 | AB40: 10 | AC40: =AA40*AB40 -> 9140 | AD40: 420 | AE40: 25 | AF40: =AD40*AE40 -> 10500 | AH40: 7.5 | AI40: =AG40*AH40 -> 0 | AK40: 15 | AL40: =AJ40*AK40 -> 0 | AM40: 198 | AN40: 10 | AO40: =AM40*AN40 -> 1980 | AP40: =R40+U40+X40+AA40+AD40+AG40+AM40 -> 5295 | AX40: 1284 | AZ40: =O40/(I40+F40+L40) -> 0.33489242 | BA40: =AP40/(I40+F40+L40) -> 0.49532273 | BB40: =AX40/O40 -> 0.35865922 | BC40: =H40+W40+Z40+AC40+AF40+T40+K40+N40 -> 596908 | BD40: =H40+AF40+T40+K40+N40 -> 578000 | BE40: =H40+W40+Z40+AC40+AF40+T40+K40+N40 -> 596908 | BF40: =H40+W40+Z40+AC40+AF40+AI40+T40+K40+N40 -> 596908 | BG40: 666770 | BH40: 447277.69 | BI40: =+BH40/BG40% -> 67.081256 | BJ40: =SUM(BY40+BZ40+CA40+CB40) -> 42084 | BK40: =SUM(CF40+CG40+CH40+CI40) -> 0.063116217 | BL40: =B40 -> 3 | BM40: =CC40 -> 60512.5 | BN40: =+BU40/BM40 -> 2.5465899 | BO40: =CD40 -> 937 | BP40: =+BU40/BO40 -> 164.4616 | BQ40: =CE40 -> 16500 | BR40: =+BU40/BQ40 -> 9.3394255 | BS40: =BU40-BM40-BO40-BQ40-BY40-BZ40-CA40-CB40 -> 34067.02 | BT40: =+BU40/BS40 -> 4.5234517 | BU40: 154100.52 | BV40: =+BU40/BG40% -> 23.111496 | BW40: =SUM(BG40-BH40-BU40) -> 65391.79 | BX40: =+BW40/BG40% -> 9.8072484 | BY40: 14828 | BZ40: 9546 | CA40: 13120 | CB40: 4590 | CC40: 60512.5 | CD40: 937 | CE40: 16500 | CF40: =BY40/BG40 -> 0.022238553 | CG40: =BZ40/BG40 -> 0.014316781 | CH40: =CA40/BG40 -> 0.01967695 | CI40: =CB40/BG40 -> 0.006883933 | CJ40: =CC40/BG40 -> 0.090754683 | CK40: =+BW40*20% -> 13078.358
A41: =A40+1 -> 34 | B41: 2 | C41: TINAGO | G41: 40 | H41: =SUM(F41*G41) -> 0 | I41: 4158 | J41: 50 | K41: =J41*I41 -> 207900 | M41: 60 | N41: =M41*L41 -> 0 | O41: 3949 | P41: 12 | Q41: =O41*P41 -> 47388 | R41: 3916 | S41: 12 | T41: =R41*S41 -> 46992 | U41: 211 | V41: 8 | W41: =U41*V41 -> 1688 | X41: 102 | Y41: 12 | Z41: =X41*Y41 -> 1224 | AA41: 280 | AB41: 10 | AC41: =AA41*AB41 -> 2800 | AD41: 106 | AE41: 25 | AF41: =AD41*AE41 -> 2650 | AG41: 84 | AH41: 7.5 | AI41: =AG41*AH41 -> 630 | AK41: 15 | AL41: =AJ41*AK41 -> 0 | AM41: 171 | AN41: 10 | AO41: =AM41*AN41 -> 1710 | AP41: =R41+U41+X41+AA41+AD41+AG41+AM41 -> 4870 | AX41: 881 | AZ41: =O41/(I41+F41+L41) -> 0.94973545 | BA41: =AP41/(I41+F41+L41) -> 1.1712362 | BB41: =AX41/O41 -> 0.22309445 | BC41: =H41+W41+Z41+AC41+AF41+T41+K41+N41 -> 263254 | BD41: =H41+AF41+T41+K41+N41 -> 257542 | BE41: =H41+W41+Z41+AC41+AF41+T41+K41+N41 -> 263254 | BF41: =H41+W41+Z41+AC41+AF41+AI41+T41+K41+N41 -> 263884 | BG41: 330541 | BH41: 217829.62 | BI41: =+BH41/BG41% -> 65.900938 | BJ41: =SUM(BY41+BZ41+CA41+CB41) -> 20645 | BK41: =SUM(CF41+CG41+CH41+CI41) -> 0.062458212 | BL41: =B41 -> 2 | BM41: =CC41 -> 42700 | BN41: =+BU41/BM41 -> 2.6268354 | BO41: =CD41 -> 2187.5 | BP41: =+BU41/BO41 -> 51.275826 | BQ41: =CE41 -> 20000 | BR41: =+BU41/BQ41 -> 5.6082935 | BS41: =BU41-BM41-BO41-BQ41-BY41-BZ41-CA41-CB41 -> 26633.37 | BT41: =+BU41/BS41 -> 4.2114787 | BU41: 112165.87 | BV41: =+BU41/BG41% -> 33.934026 | BW41: =SUM(BG41-BH41-BU41) -> 545.51 | BX41: =+BW41/BG41% -> 0.1650355 | BY41: 7413 | BZ41: 6364 | CA41: 5248 | CB41: 1620 | CC41: 42700 | CD41: 2187.5 | CE41: 20000 | CF41: =BY41/BG41 -> 0.02242687 | CG41: =BZ41/BG41 -> 0.019253285 | CH41: =CA41/BG41 -> 0.015877002 | CI41: =CB41/BG41 -> 0.0049010561 | CJ41: =CC41/BG41 -> 0.12918216 | CK41: =+BW41*20% -> 109.102
A42: =A41+1 -> 35 | B42: 6 | C42: ZAMBO | G42: 40 | H42: =SUM(F42*G42) -> 0 | I42: 15814 | J42: 50 | K42: =J42*I42 -> 790700 | M42: 60 | N42: =M42*L42 -> 0 | O42: 5225 | P42: 12 | Q42: =O42*P42 -> 62700 | S42: 12 | T42: =R42*S42 -> 0 | U42: 750 | V42: 8 | W42: =U42*V42 -> 6000 | X42: 249 | Y42: 12 | Z42: =X42*Y42 -> 2988 | AA42: 854 | AB42: 10 | AC42: =AA42*AB42 -> 8540 | AD42: 318 | AE42: 25 | AF42: =AD42*AE42 -> 7950 | AG42: 395 | AH42: 7.5 | AI42: =AG42*AH42 -> 2962.5 | AK42: 15 | AL42: =AJ42*AK42 -> 0 | AM42: 147 | AN42: 10 | AO42: =AM42*AN42 -> 1470 | AP42: =R42+U42+X42+AA42+AD42+AG42+AM42 -> 2713 | AX42: 2043 | AZ42: =O42/(I42+F42+L42) -> 0.33040344 | BA42: =AP42/(I42+F42+L42) -> 0.17155685 | BB42: =AX42/O42 -> 0.39100478 | BC42: =H42+W42+Z42+AC42+AF42+T42+K42+N42 -> 816178 | BD42: =H42+AF42+T42+K42+N42 -> 798650 | BE42: =H42+W42+Z42+AC42+AF42+T42+K42+N42 -> 816178 | BF42: =H42+W42+Z42+AC42+AF42+AI42+T42+K42+N42 -> 819140.5 | BG42: 919274.5 | BH42: 623433.83 | BI42: =+BH42/BG42% -> 67.818027 | BJ42: =SUM(BY42+BZ42+CA42+CB42) -> 67959.5 | BK42: =SUM(CF42+CG42+CH42+CI42) -> 0.07392732 | BL42: =B42 -> 6 | BM42: =CC42 -> 83162.5 | BN42: =+BU42/BM42 -> 2.7479497 | BO42: =CD42 -> 0 | BP42: =+BU42/BO42 -> #DIV/0! | BQ42: =CE42 -> 10000 | BR42: =+BU42/BQ42 -> 22.852637 | BS42: =BU42-BM42-BO42-BQ42-BY42-BZ42-CA42-CB42 -> 67404.37 | BT42: =+BU42/BS42 -> 3.3903791 | BU42: 228526.37 | BV42: =+BU42/BG42% -> 24.859427 | BW42: =SUM(BG42-BH42-BU42) -> 67314.3 | BX42: =+BW42/BG42% -> 7.3225462 | BY42: 22239 | BZ42: 20683 | CA42: 20717.5 | CB42: 4320 | CC42: 83162.5 | CE42: 10000 | CF42: =BY42/BG42 -> 0.024191904 | CG42: =BZ42/BG42 -> 0.022499264 | CH42: =CA42/BG42 -> 0.022536794 | CI42: =CB42/BG42 -> 0.004699358 | CJ42: =CC42/BG42 -> 0.090465362 | CK42: =+BW42*20% -> 13462.86
A44: TOTAL MANPOWER | C44: TOTAL NUMBER OF PARTNER STORES | F44: TOTAL QUANTITY SOLD | BC44: TOTAL AMOUNT LPG | BD44: TOTAL AMOUNT BREADING MIX | BE44: TOTAL AMOUNT OIL | BF44: TOTAL AMOUNT SAUCE | BG44: TOTAL GROSS | BH44: TOTAL COGS | BU44: TOTAL OPEX | BW44: TOTAL NET | CK44: 20% ROYALTY SHARE
F45: CHICKEN PCS. | G45: UNIT PRICE | H45: TOTAL AMOUNT | I45: CHICKEN 50 (PCS) | J45: UNIT PRICE | K45: TOTAL AMOUNT | L45: J -CUT 60 (PCS) | M45: UNIT PRICE | N45: TOTAL AMOUNT | O45: RICE PCS. | P45: UNIT PRICE | Q45: TOTAL AMOUNT | R45: NECK(PCS) | S45: UNIT PRICE | T45: TOTAL AMOUNT | U45: LUMPIA PCS. | V45: UNIT PRICE | W45: TOTAL AMOUNT | X45: NGOHIONG PCS. | Y45: UNIT PRICE | Z45: TOTAL AMOUNT | AA45: BOLA2X PCS. | AB45: UNIT PRICE | AC45: TOTAL AMOUNT | AD45: C. FILLET PCS. | AE45: UNIT PRICE | AF45: TOTAL AMOUNT | AG45: SIOMAI PCS. | AH45: UNIT PRICE | AI45: TOTAL AMOUNT | AJ45: ATSARA( 15 ) | AK45: UNIT PRICE | AL45: TOTAL AMOUNT | AM45: ATSARA( 12 ) | AN45: UNIT PRICE | AO45: TOTAL AMOUNT | AP45: OTHER PRODUCTS(PCS) | AQ45: 1 LITER | AR45: PCS *4 | AS45: TOTAL PCS | AT45: 1.5 LITER | AU45: PCS *6 | AV45: TOTAL PCS | AW45: OTHER DRINKS SOLD | AX45: TOTAL QTY SOLD S.DRINKSPCS) | AY45: TOTAL AMOUNT
A46: =SUM(B8:B42) -> 148 | F46: =SUM(F8:F42) -> 0 | G46: 40 | H46: =F46*G46 -> 0 | I46: =SUM(I8:I42) -> 402962.08 | J46: 50 | K46: =J46*I46 -> 20148104 | L46: =SUM(L8:L42) -> 0 | M46: 60 | N46: =M46*L46 -> 0 | O46: =SUM(O8:O42) -> 205220 | P46: 12 | Q46: =O46*P46 -> 2462640 | R46: =SUM(R8:R42) -> 75291 | S46: 12 | T46: =R46*S46 -> 903492 | U46: =SUM(U8:U42) -> 28065 | V46: 8 | W46: =U46*V46 -> 224520 | X46: =SUM(X8:X42) -> 17231 | Y46: 12 | Z46: =X46*Y46 -> 206772 | AA46: =SUM(AA8:AA42) -> 33826 | AB46: 10 | AC46: =AA46*AB46 -> 338260 | AD46: =SUM(AD8:AD42) -> 10038 | AE46: 25 | AF46: =AD46*AE46 -> 250950 | AG46: =SUM(AG8:AG42) -> 11397 | AH46: 7.5 | AI46: =AG46*AH46 -> 85477.5 | AJ46: =SUM(AJ8:AJ42) -> 0 | AK46: 15 | AL46: =AJ46*AK46 -> 0 | AM46: =SUM(AM8:AM42) -> 8088 | AN46: 12 | AO46: =AM46*AN46 -> 97056 | AP46: =SUM(AM46,AG46,AD46,AA46,X46,U46,R46) -> 183936 | AQ46: =SUM(AQ8:AQ42) -> 0 | AR46: 4 | AS46: =SUM(AQ46*AR46) -> 0 | AT46: =SUM(AT8:AT42) -> 0 | AU46: 6 | AV46: =SUM(AT46*AU46) -> 0 | AW46: =SUM(AW8:AW42) -> 0 | AX46: =SUM(AS46+AV46+AW46) -> 0 | AY46: =SUM(AY8:AY42) -> 0 | BC46: =SUM(BC8:BC42) -> 22072098 | BD46: =SUM(BD8:BD42) -> 21302546 | BE46: =SUM(BE8:BE42) -> 22072098 | BF46: =SUM(BF8:BF42) -> 22157576 | BG46: =SUM(BG8:BG42) -> 26142610 | BH46: =SUM(BH8:BH42) -> 17582749 | BU46: =SUM(BU8:BU45) -> 6801706.4 | BW46: =SUM(BW8:BW45) -> 1758154.7 | CK46: =SUM(CK8:CK42) -> 351630.93
BW47: =BW46*20% -> 351630.93 | BX47: 0.2

Sheet FEB
A1: CRISPY KING FRANCHISE PERFORMANCE REPORT
A3: MONTH 2026 - AREA/REGION | BU3: CONSOLIDATED REPORT FOR THE MONTH OF FEBRUARY 2026
G5: DO NOT EDIT! | J5: DO NOT EDIT! | M5: DO NOT EDIT! | P5: DO NOT EDIT! | S5: DO NOT EDIT! | V5: DO NOT EDIT! | Y5: DO NOT EDIT! | AB5: DO NOT EDIT! | AE5: DO NOT EDIT! | AH5: DO NOT EDIT! | AK5: DO NOT EDIT! | AN5: DO NOT EDIT! | AR5: DO NOT EDIT! | AU5: DO NOT EDIT! | AX5: ! | AZ5: CAUTION! AUTO-FORMULA! DO NOT EDIT! | BI5: CAUTION! AUTO-FORMULA! DO NOT EDIT! | BV5: DO NOT EDIT! | CF5: CAUTION! AUTO-FORMULA! DO NOT EDIT!
A6: GROSS RANK | B6: MAN POWER | C6: BRANCH | D6: OWNER | E6: SALES SUPERVISOR | F6: QUANTITY SOLD | I6: S-CUT | L6: J-CUT | O6: RICE | R6: NECK(PCS) | U6: LUMPIA | X6: NGOHIONG | AA6: BOLA2X | AD6: C-FILLET | AG6: SIOMAI | AJ6: ATSARA (15) | AM6: ATSARA (12) | AP6: TOTAL OTHER PRODUCT | AW6: OTHER DRINKS SOLD | AX6: TOTAL QTY SOLD S.DRINKSPCS) | AZ6: CHICKEN VS RICE (50%) | BA6: CHICKEN VS OTHER PRODUCTS (20%) | BB6: RICE VS DRINKS (40%) | BC6: TOTAL AMOUNT FOR LPG % | BD6: TOTAL AMOUNT FOR BREADING% | BE6: TOTAL AMOUNT FOR OIL % | BF6: TOTAL AMOUNT FOR SAUCE % | BG6: TOTAL GROSS SALES | BH6: COST OF GOODS SOLD | BI6: COGS (%) | BJ6: TOTAL AMOUNT USAGES | BK6: USAGES (%) | BL6: MAN POWER | BM6: SALARY | BN6: SALARY (%) | BO6: OVERTIME | BP6: OVERTIME (%) | BQ6: RENT | BR6: RENT (%) | BS6: OPERATIONAL EXPENSES | BT6: OPERATION (%) | BU6: TOTAL OPEX | BV6: OPEX (%) | BW6: NET INCOME | BX6: NET (%) | BY6: NON - SALES ITEM | CK6: 20% ROYALTY SHARE
F7: CHICKEN 40(PCS) | G7: UNIT PRICE | H7: TOTAL AMOUNT | I7: QNTY | J7: UNIT PRICE | K7: TOTAL AMOUNT | L7: J -CUT 60 (PCS) | M7: UNIT PRICE | N7: TOTAL AMOUNT | O7: RICE(PCS) | P7: UNIT PRICE | Q7: TOTAL AMOUNT | R7: NECK(PCS) | S7: UNIT PRICE | T7: TOTAL AMOUNT | U7: LUMPIA(PCS) | V7: UNIT PRICE | W7: TOTAL AMOUNT | X7: NGOHIONG(PCS) | Y7: UNIT PRICE | Z7: TOTAL AMOUNT | AA7: BOLA2X(PCS) | AB7: UNIT PRICE | AC7: TOTAL AMOUNT | AD7: C. FILLET(PCS) | AE7: UNIT PRICE | AF7: TOTAL AMOUNT | AG7: SIOMAI(PCS) | AH7: UNIT PRICE | AI7: TOTAL AMOUNT | AJ7: ATSARA( 15 ) | AK7: UNIT PRICE | AL7: TOTAL AMOUNT | AM7: ATSARA( 12 ) | AN7: UNIT PRICE | AO7: TOTAL AMOUNT | AQ7: 1 LITER | AR7: PCS *4 | AS7: TOTAL PCS | AT7: 1.5 LITER | AU7: PCS * 6 | AV7: TOTAL PCS | AY7: TOTAL AMOUNT | BY7: LPG | BZ7: BREADING | CA7: OIL | CB7: SAUCE | CC7: SALARY | CD7: OVERTIME | CE7: RENT | CF7: LPG | CG7: BREADING | CH7: OIL | CI7: SAUCE | CJ7: SALARY
A8: 1 | B8: 4 | C8: AYUNGON 2 | G8: 40 | H8: =SUM(F8*G8) -> 0 | I8: 7776 | J8: 50 | K8: =J8*I8 -> 388800 | M8: 60 | N8: =M8*L8 -> 0 | O8: 2834 | P8: 12 | Q8: =O8*P8 -> 34008 | R8: 1170 | S8: 12 | T8: =R8*S8 -> 14040 | U8: 925 | V8: 8 | W8: =U8*V8 -> 7400 | X8: 463 | Y8: 12 | Z8: =X8*Y8 -> 5556 | AA8: 959 | AB8: 10 | AC8: =AA8*AB8 -> 9590 | AD8: 178 | AE8: 25 | AF8: =AD8*AE8 -> 4450 | AG8: 249 | AH8: 7.5 | AI8: =AG8*AH8 -> 1867.5 | AK8: 15 | AL8: =AJ8*AK8 -> 0 | AM8: 187 | AN8: 10 | AO8: =AM8*AN8 -> 1870 | AP8: =R8+U8+X8+AA8+AD8+AG8+AM8 -> 4131 | AX8: 1349 | AZ8: =O8/(I8+F8+L8) -> 0.36445473 | BA8: =AP8/(I8+F8+L8) -> 0.53125 | BB8: =AX8/O8 -> 0.47600565 | BC8: =H8+W8+Z8+AC8+AF8+T8+K8+N8 -> 429836 | BD8: =H8+AF8+T8+K8+N8 -> 407290 | BE8: =H8+W8+Z8+AC8+AF8+T8+K8+N8 -> 429836 | BF8: =H8+W8+Z8+AC8+AF8+AI8+T8+K8+N8 -> 431703.5 | BG8: 494977.5 | BH8: 331160.57 | BI8: =+BH8/BG8% -> 66.904166 | BJ8: =SUM(BY8+BZ8+CA8+CB8) -> 32317 | BK8: =SUM(CF8+CG8+CH8+CI8) -> 0.065289836 | BL8: 3 | BM8: =CC8 -> 41150 | BN8: =+BU8/BM8 -> 3.2966535 | BO8: =CD8 -> 1687.5 | BP8: =+BU8/BO8 -> 80.389505 | BQ8: =CE8 -> 20000 | BR8: =+BU8/BQ8 -> 6.7828645 | BS8: =BU8-BM8-BO8-BQ8-BY8-BZ8-CA8-CB8 -> 40502.79 | BT8: =+BU8/BS8 -> 3.349332 | BU8: 135657.29 | BV8: =+BU8/BG8% -> 27.406759 | BW8: =SUM(BG8-BH8-BU8) -> 28159.64 | BX8: =+BW8/BG8% -> 5.6890748 | BY8: 11346 | BZ8: 7955 | CA8: 9776 | CB8: 3240 | CC8: 41150 | CD8: 1687.5 | CE8: 20000 | CF8: =BY8/BG8 -> 0.022922254 | CG8: =BZ8/BG8 -> 0.016071438 | CH8: =CA8/BG8 -> 0.019750393 | CI8: =CB8/BG8 -> 0.0065457521 | CJ8: =CC8/BG8 -> 0.083135092 | CK8: =+BW8*20% -> 5631.928
A9: =A8+1 -> 2 | B9: 5 | C9: AYUNGON 1 | G9: 40 | H9: =SUM(F9*G9) -> 0 | I9: 10659 | J9: 50 | K9: =J9*I9 -> 532950 | M9: 60 | N9: =M9*L9 -> 0 | O9: 4524 | P9: 12 | Q9: =O9*P9 -> 54288 | R9: 1140 | S9: 12 | T9: =R9*S9 -> 13680 | U9: 636 | V9: 8 | W9: =U9*V9 -> 5088 | X9: 404 | Y9: 12 | Z9: =X9*Y9 -> 4848 | AA9: 897 | AB9: 10 | AC9: =AA9*AB9 -> 8970 | AD9: 319 | AE9: 25 | AF9: =AD9*AE9 -> 7975 | AG9: 126 | AH9: 7.5 | AI9: =AG9*AH9 -> 945 | AK9: 15 | AL9: =AJ9*AK9 -> 0 | AM9: 186 | AN9: 10 | AO9: =AM9*AN9 -> 1860 | AP9: =R9+U9+X9+AA9+AD9+AG9+AM9 -> 3708 | AX9: 2187 | AZ9: =O9/(I9+F9+L9) -> 0.42443006 | BA9: =AP9/(I9+F9+L9) -> 0.34787504 | BB9: =AX9/O9 -> 0.48342175 | BC9: =H9+W9+Z9+AC9+AF9+T9+K9+N9 -> 573511 | BD9: =H9+AF9+T9+K9+N9 -> 554605 | BE9: =H9+W9+Z9+AC9+AF9+T9+K9+N9 -> 573511 | BF9: =H9+W9+Z9+AC9+AF9+AI9+T9+K9+N9 -> 574456 | BG9: 668379 | BH9: 448218.2 | BI9: =+BH9/BG9% -> 67.060485 | BJ9: =SUM(BY9+BZ9+CA9+CB9) -> 46941 | BK9: =SUM(CF9+CG9+CH9+CI9) -> 0.070231111 | BL9: =B9 -> 5 | BM9: =CC9 -> 57450 | BN9: =+BU9/BM9 -> 3.5458341 | BO9: =CD9 -> 0 | BP9: =+BU9/BO9 -> #DIV/0! | BQ9: =CE9 -> 31500 | BR9: =+BU9/BQ9 -> 6.466926 | BS9: =BU9-BM9-BO9-BQ9-BY9-BZ9-CA9-CB9 -> 67817.17 | BT9: =+BU9/BS9 -> 3.0037846 | BU9: 203708.17 | BV9: =+BU9/BG9% -> 30.477943 | BW9: =SUM(BG9-BH9-BU9) -> 16452.63 | BX9: =+BW9/BG9% -> 2.461572 | BY9: 18925 | BZ9: 12728 | CA9: 10968 | CB9: 4320 | CC9: 57450 | CE9: 31500 | CF9: =BY9/BG9 -> 0.028314774 | CG9: =BZ9/BG9 -> 0.019043088 | CH9: =CA9/BG9 -> 0.016409851 | CI9: =CB9/BG9 -> 0.0064633988 | CJ9: =CC9/BG9 -> 0.085954227 | CK9: =+BW9*20% -> 3290.526
A10: =A9+1 -> 3 | B10: 4 | C10: BACONG 1 | G10: 40 | H10: =SUM(F10*G10) -> 0 | I10: 7694 | J10: 50 | K10: =J10*I10 -> 384700 | M10: 60 | N10: =M10*L10 -> 0 | O10: 4452 | P10: 12 | Q10: =O10*P10 -> 53424 | R10: 3280 | S10: 12 | T10: =R10*S10 -> 39360 | U10: 1173 | V10: 8 | W10: =U10*V10 -> 9384 | X10: 276 | Y10: 12 | Z10: =X10*Y10 -> 3312 | AA10: 968 | AB10: 10 | AC10: =AA10*AB10 -> 9680 | AD10: 384 | AE10: 25 | AF10: =AD10*AE10 -> 9600 | AG10: 691 | AH10: 7.5 | AI10: =AG10*AH10 -> 5182.5 | AK10: 15 | AL10: =AJ10*AK10 -> 0 | AM10: 248 | AN10: 10 | AO10: =AM10*AN10 -> 2480 | AP10: =R10+U10+X10+AA10+AD10+AG10+AM10 -> 7020 | AX10: 1532 | AZ10: =O10/(I10+F10+L10) -> 0.5786327 | BA10: =AP10/(I10+F10+L10) -> 0.91239927 | BB10: =AX10/O10 -> 0.344115 | BC10: =H10+W10+Z10+AC10+AF10+T10+K10+N10 -> 456036 | BD10: =H10+AF10+T10+K10+N10 -> 433660 | BE10: =H10+W10+Z10+AC10+AF10+T10+K10+N10 -> 456036 | BF10: =H10+W10+Z10+AC10+AF10+AI10+T10+K10+N10 -> 461218.5 | BG10: 545964.5 | BH10: 368801.04 | BI10: =+BH10/BG10% -> 67.55037 | BJ10: =SUM(BY10+BZ10+CA10+CB10) -> 35437 | BK10: =SUM(CF10+CG10+CH10+CI10) -> 0.064907151 | BL10: 5 | BM10: =CC10 -> 56575 | BN10: =+BU10/BM10 -> 2.9630533 | BO10: =CD10 -> 0 | BP10: =+BU10/BO10 -> #DIV/0! | BQ10: =CE10 -> 16000 | BR10: =+BU10/BQ10 -> 10.477171 | BS10: =BU10-BM10-BO10-BQ10-BY10-BZ10-CA10-CB10 -> 59622.74 | BT10: =+BU10/BS10 -> 2.8115907 | BU10: 167634.74 | BV10: =+BU10/BG10% -> 30.70433 | BW10: =SUM(BG10-BH10-BU10) -> 9528.72 | BX10: =+BW10/BG10% -> 1.7453003 | BY10: 15126 | BZ10: 7955 | CA10: 9656 | CB10: 2700 | CC10: 56575 | CE10: 16000 | CF10: =BY10/BG10 -> 0.027705098 | CG10: =BZ10/BG10 -> 0.014570544 | CH10: =CA10/BG10 -> 0.017686132 | CI10: =CB10/BG10 -> 0.0049453765 | CJ10: =CC10/BG10 -> 0.10362395 | CK10: =+BW10*20% -> 1905.744
A11: =A10+1 -> 4 | B11: 2 | C11: BACONG2 | G11: 40 | H11: =SUM(F11*G11) -> 0 | I11: 3905 | J11: 50 | K11: =J11*I11 -> 195250 | M11: 60 | N11: =M11*L11 -> 0 | O11: 2173 | P11: 12 | Q11: =O11*P11 -> 26076 | R11: 2745 | S11: 12 | T11: =R11*S11 -> 32940 | U11: 370 | V11: 8 | W11: =U11*V11 -> 2960 | X11: 155 | Y11: 12 | Z11: =X11*Y11 -> 1860 | AA11: 431 | AB11: 10 | AC11: =AA11*AB11 -> 4310 | AD11: 183 | AE11: 25 | AF11: =AD11*AE11 -> 4575 | AG11: 290 | AH11: 7.5 | AI11: =AG11*AH11 -> 2175 | AK11: 15 | AL11: =AJ11*AK11 -> 0 | AM11: 142 | AN11: 10 | AO11: =AM11*AN11 -> 1420 | AP11: =R11+U11+X11+AA11+AD11+AG11+AM11 -> 4316 | AX11: 902 | AZ11: =O11/(I11+F11+L11) -> 0.55646607 | BA11: =AP11/(I11+F11+L11) -> 1.1052497 | BB11: =AX11/O11 -> 0.41509434 | BC11: =H11+W11+Z11+AC11+AF11+T11+K11+N11 -> 241895 | BD11: =H11+AF11+T11+K11+N11 -> 232765 | BE11: =H11+W11+Z11+AC11+AF11+T11+K11+N11 -> 241895 | BF11: =H11+W11+Z11+AC11+AF11+AI11+T11+K11+N11 -> 244070 | BG11: 288500 | BH11: 193568.3 | BI11: =+BH11/BG11% -> 67.094731 | BJ11: =SUM(BY11+BZ11+CA11+CB11) -> 22167 | BK11: =SUM(CF11+CG11+CH11+CI11) -> 0.076835355 | BL11: =B11 -> 2 | BM11: =CC11 -> 31843.75 | BN11: =+BU11/BM11 -> 3.1373004 | BO11: =CD11 -> 125 | BP11: =+BU11/BO11 -> 799.22728 | BQ11: =CE11 -> 8269 | BR11: =+BU11/BQ11 -> 12.08168 | BS11: =BU11-BM11-BO11-BQ11-BY11-BZ11-CA11-CB11 -> 37498.66 | BT11: =+BU11/BS11 -> 2.6641861 | BU11: 99903.41 | BV11: =+BU11/BG11% -> 34.628565 | BW11: =SUM(BG11-BH11-BU11) -> -4971.71 | BX11: =+BW11/BG11% -> -1.7232964 | BY11: 7563 | BZ11: 6364 | CA11: 6080 | CB11: 2160 | CC11: 31843.75 | CD11: 125 | CE11: 8269 | CF11: =BY11/BG11 -> 0.026214905 | CG11: =BZ11/BG11 -> 0.022058925 | CH11: =CA11/BG11 -> 0.021074523 | CI11: =CB11/BG11 -> 0.0074870017 | CJ11: =CC11/BG11 -> 0.11037695 | CK11: =+BW11*20% -> -994.342
A12: =A11+1 -> 5 | B12: 4 | C12: BAGACAY | G12: 40 | H12: =SUM(F12*G12) -> 0 | I12: 6726 | J12: 50 | K12: =J12*I12 -> 336300 | M12: 60 | N12: =M12*L12 -> 0 | O12: 6110 | P12: 12 | Q12: =O12*P12 -> 73320 | R12: 1880 | S12: 12 | T12: =R12*S12 -> 22560 | U12: 1249 | V12: 8 | W12: =U12*V12 -> 9992 | X12: 374 | Y12: 12 | Z12: =X12*Y12 -> 4488 | AA12: 1030 | AB12: 10 | AC12: =AA12*AB12 -> 10300 | AD12: 278 | AE12: 25 | AF12: =AD12*AE12 -> 6950 | AG12: 448 | AH12: 7.5 | AI12: =AG12*AH12 -> 3360 | AK12: 15 | AL12: =AJ12*AK12 -> 0 | AM12: 195 | AN12: 10 | AO12: =AM12*AN12 -> 1950 | AP12: =R12+U12+X12+AA12+AD12+AG12+AM12 -> 5454 | AX12: 1939 | AZ12: =O12/(I12+F12+L12) -> 0.90841511 | BA12: =AP12/(I12+F12+L12) -> 0.81088314 | BB12: =AX12/O12 -> 0.31734861 | BC12: =H12+W12+Z12+AC12+AF12+T12+K12+N12 -> 390590 | BD12: =H12+AF12+T12+K12+N12 -> 365810 | BE12: =H12+W12+Z12+AC12+AF12+T12+K12+N12 -> 390590 | BF12: =H12+W12+Z12+AC12+AF12+AI12+T12+K12+N12 -> 393950 | BG12: 505422 | BH12: 338901.17 | BI12: =+BH12/BG12% -> 67.05311 | BJ12: =SUM(BY12+BZ12+CA12+CB12) -> 37700 | BK12: =SUM(CF12+CG12+CH12+CI12) -> 0.074591134 | BL12: =B12 -> 4 | BM12: =CC12 -> 46700 | BN12: =+BU12/BM12 -> 3.4678809 | BO12: =CD12 -> 125 | BP12: =+BU12/BO12 -> 1295.6003 | BQ12: =CE12 -> 28000 | BR12: =+BU12/BQ12 -> 5.78393 | BS12: =BU12-BM12-BO12-BQ12-BY12-BZ12-CA12-CB12 -> 49425.04 | BT12: =+BU12/BS12 -> 3.27668 | BU12: 161950.04 | BV12: =+BU12/BG12% -> 32.042539 | BW12: =SUM(BG12-BH12-BU12) -> 4570.79 | BX12: =+BW12/BG12% -> 0.90435122 | BY12: 15051 | BZ12: 9546 | CA12: 10376 | CB12: 2727 | CC12: 46700 | CD12: 125 | CE12: 28000 | CF12: =BY12/BG12 -> 0.029779076 | CG12: =BZ12/BG12 -> 0.018887187 | CH12: =CA12/BG12 -> 0.020529379 | CI12: =CB12/BG12 -> 0.0053954913 | CJ12: =CC12/BG12 -> 0.092398036 | CK12: =+BW12*20% -> 914.158
A13: =A12+1 -> 6 | B13: 4 | C13: BAYAWAN | G13: 40 | H13: =SUM(F13*G13) -> 0 | I13: 8633 | J13: 50 | K13: =J13*I13 -> 431650 | M13: 60 | N13: =M13*L13 -> 0 | O13: 2976 | P13: 12 | Q13: =O13*P13 -> 35712 | R13: 110 | S13: 12 | T13: =R13*S13 -> 1320 | U13: 601 | V13: 8 | W13: =U13*V13 -> 4808 | X13: 501 | Y13: 12 | Z13: =X13*Y13 -> 6012 | AA13: 796 | AB13: 10 | AC13: =AA13*AB13 -> 7960 | AD13: 260 | AE13: 25 | AF13: =AD13*AE13 -> 6500 | AG13: 243 | AH13: 7.5 | AI13: =AG13*AH13 -> 1822.5 | AK13: 15 | AL13: =AJ13*AK13 -> 0 | AN13: 10 | AO13: =AM13*AN13 -> 0 | AP13: =R13+U13+X13+AA13+AD13+AG13+AM13 -> 2511 | AX13: 1200 | AZ13: =O13/(I13+F13+L13) -> 0.34472373 | BA13: =AP13/(I13+F13+L13) -> 0.29086065 | BB13: =AX13/O13 -> 0.40322581 | BC13: =H13+W13+Z13+AC13+AF13+T13+K13+N13 -> 458250 | BD13: =H13+AF13+T13+K13+N13 -> 439470 | BE13: =H13+W13+Z13+AC13+AF13+T13+K13+N13 -> 458250 | BF13: =H13+W13+Z13+AC13+AF13+AI13+T13+K13+N13 -> 460072.5 | BG13: 519687.5 | BH13: 349199.05 | BI13: =+BH13/BG13% -> 67.194044 | BJ13: =SUM(BY13+BZ13+CA13+CB13) -> 42428 | BK13: =SUM(CF13+CG13+CH13+CI13) -> 0.081641371 | BL13: =B13 -> 4 | BM13: =CC13 -> 48637.5 | BN13: =+BU13/BM13 -> 2.8087552 | BO13: =CD13 -> 687.5 | BP13: =+BU13/BO13 -> 198.70666 | BQ13: =CE13 -> 13000 | BR13: =+BU13/BQ13 -> 10.508525 | BS13: =BU13-BM13-BO13-BQ13-BY13-BZ13-CA13-CB13 -> 31857.83 | BT13: =+BU13/BS13 -> 4.2881398 | BU13: 136610.83 | BV13: =+BU13/BG13% -> 26.287111 | BW13: =SUM(BG13-BH13-BU13) -> 33877.62 | BX13: =+BW13/BG13% -> 6.5188445 | BY13: 15051 | BZ13: 9546 | CA13: 13781 | CB13: 4050 | CC13: 48637.5 | CD13: 687.5 | CE13: 13000 | CF13: =BY13/BG13 -> 0.028961636 | CG13: =BZ13/BG13 -> 0.018368731 | CH13: =CA13/BG13 -> 0.026517859 | CI13: =CB13/BG13 -> 0.0077931449 | CJ13: =CC13/BG13 -> 0.093589898 | CK13: =+BW13*20% -> 6775.524
A14: =A13+1 -> 7 | B14: 7 | C14: BINDOY1 | G14: 40 | H14: =SUM(F14*G14) -> 0 | I14: 16295 | J14: 50 | K14: =J14*I14 -> 814750 | M14: 60 | N14: =M14*L14 -> 0 | O14: 5451 | P14: 12 | Q14: =O14*P14 -> 65412 | S14: 12 | T14: =R14*S14 -> 0 | U14: 969 | V14: 8 | W14: =U14*V14 -> 7752 | X14: 411 | Y14: 12 | Z14: =X14*Y14 -> 4932 | AA14: 1178 | AB14: 10 | AC14: =AA14*AB14 -> 11780 | AD14: 330 | AE14: 25 | AF14: =AD14*AE14 -> 8250 | AG14: 301 | AH14: 7.5 | AI14: =AG14*AH14 -> 2257.5 | AK14: 15 | AL14: =AJ14*AK14 -> 0 | AM14: 249 | AN14: 10 | AO14: =AM14*AN14 -> 2490 | AP14: =R14+U14+X14+AA14+AD14+AG14+AM14 -> 3438 | AX14: 1784 | AZ14: =O14/(I14+F14+L14) -> 0.33451979 | BA14: =AP14/(I14+F14+L14) -> 0.21098496 | BB14: =AX14/O14 -> 0.3272794 | BC14: =H14+W14+Z14+AC14+AF14+T14+K14+N14 -> 847464 | BD14: =H14+AF14+T14+K14+N14 -> 823000 | BE14: =H14+W14+Z14+AC14+AF14+T14+K14+N14 -> 847464 | BF14: =H14+W14+Z14+AC14+AF14+AI14+T14+K14+N14 -> 849721.5 | BG14: 949506.5 | BH14: 643565.89 | BI14: =+BH14/BG14% -> 67.778987 | BJ14: =SUM(BY14+BZ14+CA14+CB14) -> 55300 | BK14: =SUM(CF14+CG14+CH14+CI14) -> 0.058240781 | BL14: =B14 -> 7 | BM14: =CC14 -> 71350 | BN14: =+BU14/BM14 -> 2.9309191 | BO14: =CD14 -> 312.5 | BP14: =+BU14/BO14 -> 669.18746 | BQ14: =CE14 -> 14500 | BR14: =+BU14/BQ14 -> 14.422143 | BS14: =BU14-BM14-BO14-BQ14-BY14-BZ14-CA14-CB14 -> 67658.58 | BT14: =+BU14/BS14 -> 3.0908287 | BU14: 209121.08 | BV14: =+BU14/BG14% -> 22.024186 | BW14: =SUM(BG14-BH14-BU14) -> 96819.53 | BX14: =+BW14/BG14% -> 10.196826 | BY14: 15218 | BZ14: 15910 | CA14: 19312 | CB14: 4860 | CC14: 71350 | CD14: 312.5 | CE14: 14500 | CF14: =BY14/BG14 -> 0.016027273 | CG14: =BZ14/BG14 -> 0.016756073 | CH14: =CA14/BG14 -> 0.020338987 | CI14: =CB14/BG14 -> 0.0051184484 | CJ14: =CC14/BG14 -> 0.075144299 | CK14: =+BW14*20% -> 19363.906
A15: =A14+1 -> 8 | B15: 3 | C15: BINDOY2 | G15: 40 | H15: =SUM(F15*G15) -> 0 | I15: 6190 | J15: 50 | K15: =J15*I15 -> 309500 | M15: 60 | N15: =M15*L15 -> 0 | O15: 1690 | P15: 12 | Q15: =O15*P15 -> 20280 | R15: 2455 | S15: 12 | T15: =R15*S15 -> 29460 | U15: 453 | V15: 8 | W15: =U15*V15 -> 3624 | X15: 275 | Y15: 12 | Z15: =X15*Y15 -> 3300 | AA15: 645 | AB15: 10 | AC15: =AA15*AB15 -> 6450 | AD15: 182 | AE15: 25 | AF15: =AD15*AE15 -> 4550 | AG15: 79 | AH15: 7.5 | AI15: =AG15*AH15 -> 592.5 | AK15: 15 | AL15: =AJ15*AK15 -> 0 | AM15: 70 | AN15: 10 | AO15: =AM15*AN15 -> 700 | AP15: =R15+U15+X15+AA15+AD15+AG15+AM15 -> 4159 | AX15: =25+320+179+25+8 -> 557 | AZ15: =O15/(I15+F15+L15) -> 0.273021 | BA15: =AP15/(I15+F15+L15) -> 0.67189015 | BB15: =AX15/O15 -> 0.3295858 | BC15: =H15+W15+Z15+AC15+AF15+T15+K15+N15 -> 356884 | BD15: =H15+AF15+T15+K15+N15 -> 343510 | BE15: =H15+W15+Z15+AC15+AF15+T15+K15+N15 -> 356884 | BF15: =H15+W15+Z15+AC15+AF15+AI15+T15+K15+N15 -> 357476.5 | BG15: 389125.5 | BH15: 263201.18 | BI15: =+BH15/BG15% -> 67.63915 | BJ15: =SUM(BY15+BZ15+CA15+CB15) -> 31245 | BK15: =SUM(CF15+CG15+CH15+CI15) -> 0.080295432 | BL15: =B15 -> 3 | BM15: =CC15 -> 35725 | BN15: =+BU15/BM15 -> 3.2544437 | BO15: =CD15 -> 312.5 | BP15: =+BU15/BO15 -> 372.048 | BQ15: =CE15 -> 15000 | BR15: =+BU15/BQ15 -> 7.751 | BS15: =BU15-BM15-BO15-BQ15-BY15-BZ15-CA15-CB15 -> 33982.5 | BT15: =+BU15/BS15 -> 3.4213198 | BU15: 116265 | BV15: =+BU15/BG15% -> 29.878535 | BW15: =SUM(BG15-BH15-BU15) -> 9659.32 | BX15: =+BW15/BG15% -> 2.4823148 | BY15: 11346 | BZ15: 7955 | CA15: 8704 | CB15: 3240 | CC15: 35725 | CD15: 312.5 | CE15: 15000 | CF15: =BY15/BG15 -> 0.029157688 | CG15: =BZ15/BG15 -> 0.020443276 | CH15: =CA15/BG15 -> 0.022368105 | CI15: =CB15/BG15 -> 0.0083263626 | CJ15: =CC15/BG15 -> 0.091808427 | CK15: =+BW15*20% -> 1931.864
A16: =A15+1 -> 9 | B16: 4 | C16: CADIZ 3 | G16: 40 | H16: =SUM(F16*G16) -> 0 | I16: 6894 | J16: 50 | K16: =J16*I16 -> 344700 | M16: 60 | N16: =M16*L16 -> 0 | O16: 2479 | P16: 12 | Q16: =O16*P16 -> 29748 | R16: 1320 | S16: 12 | T16: =R16*S16 -> 15840 | U16: 221 | V16: 8 | W16: =U16*V16 -> 1768 | X16: 142 | Y16: 12 | Z16: =X16*Y16 -> 1704 | AA16: 340 | AB16: 10 | AC16: =AA16*AB16 -> 3400 | AD16: 156 | AE16: 25 | AF16: =AD16*AE16 -> 3900 | AG16: 32 | AH16: 7.5 | AI16: =AG16*AH16 -> 240 | AK16: 15 | AL16: =AJ16*AK16 -> 0 | AM16: 56 | AN16: 12 | AO16: =AM16*AN16 -> 672 | AP16: =R16+U16+X16+AA16+AD16+AG16+AM16 -> 2267 | AX16: =201+487+61+44 -> 793 | AZ16: =O16/(I16+F16+L16) -> 0.35958805 | BA16: =AP16/(I16+F16+L16) -> 0.32883667 | BB16: =AX16/O16 -> 0.31988705 | BC16: =H16+W16+Z16+AC16+AF16+T16+K16+N16 -> 371312 | BD16: =H16+AF16+T16+K16+N16 -> 364440 | BE16: =H16+W16+Z16+AC16+AF16+T16+K16+N16 -> 371312 | BF16: =H16+W16+Z16+AC16+AF16+AI16+T16+K16+N16 -> 371552 | BG16: 417047 | BH16: 277927.56 | BI16: =+BH16/BG16% -> 66.641784 | BJ16: =SUM(BY16+BZ16+CA16+CB16) -> 36499 | BK16: =SUM(CF16+CG16+CH16+CI16) -> 0.087517714 | BL16: =B16 -> 4 | BM16: =CC16 -> 47468 | BN16: =+BU16/BM16 -> 2.8550491 | BO16: =CD16 -> 0 | BP16: =+BU16/BO16 -> #DIV/0! | BQ16: =CE16 -> 18000 | BR16: =+BU16/BQ16 -> 7.5290817 | BS16: =BU16-BM16-BO16-BQ16-BY16-BZ16-CA16-CB16 -> 33556.47 | BT16: =+BU16/BS16 -> 4.0386688 | BU16: 135523.47 | BV16: =+BU16/BG16% -> 32.49597 | BW16: =SUM(BG16-BH16-BU16) -> 3595.97 | BX16: =+BW16/BG16% -> 0.86224574 | BY16: 15049 | BZ16: 8650 | CA16: 10240 | CB16: 2560 | CC16: 47468 | CD16: 0 | CE16: 18000 | CF16: =BY16/BG16 -> 0.036084662 | CG16: =BZ16/BG16 -> 0.020741068 | CH16: =CA16/BG16 -> 0.024553587 | CI16: =CB16/BG16 -> 0.0061383969 | CJ16: =CC16/BG16 -> 0.11381931 | CK16: =+BW16*20% -> 719.194
A17: =A16+1 -> 10 | B17: 6 | C17: DARO | G17: 40 | H17: =SUM(F17*G17) -> 0 | I17: 13027 | J17: 50 | K17: =J17*I17 -> 651350 | M17: 60 | N17: =M17*L17 -> 0 | O17: 9451 | P17: 12 | Q17: =O17*P17 -> 113412 | S17: 12 | T17: =R17*S17 -> 0 | U17: 1262 | V17: 8 | W17: =U17*V17 -> 10096 | X17: 715 | Y17: 12 | Z17: =X17*Y17 -> 8580 | AA17: 1094 | AB17: 10 | AC17: =AA17*AB17 -> 10940 | AD17: 458 | AE17: 25 | AF17: =AD17*AE17 -> 11450 | AG17: 754 | AH17: 7.5 | AI17: =AG17*AH17 -> 5655 | AK17: 15 | AL17: =AJ17*AK17 -> 0 | AM17: 459 | AN17: 10 | AO17: =AM17*AN17 -> 4590 | AP17: =R17+U17+X17+AA17+AD17+AG17+AM17 -> 4742 | AX17: =48+1415+211+244+110+73 -> 2101 | AZ17: =O17/(I17+F17+L17) -> 0.72549321 | BA17: =AP17/(I17+F17+L17) -> 0.3640132 | BB17: =AX17/O17 -> 0.22230452 | BC17: =H17+W17+Z17+AC17+AF17+T17+K17+N17 -> 692416 | BD17: =H17+AF17+T17+K17+N17 -> 662800 | BE17: =H17+W17+Z17+AC17+AF17+T17+K17+N17 -> 692416 | BF17: =H17+W17+Z17+AC17+AF17+AI17+T17+K17+N17 -> 698071 | BG17: 857516 | BH17: 585143.92 | BI17: =+BH17/BG17% -> 68.237085 | BJ17: =SUM(BY17+BZ17+CA17+CB17) -> 47797 | BK17: =SUM(CF17+CG17+CH17+CI17) -> 0.055738902 | BL17: =B17 -> 6 | BM17: =CC17 -> 68950 | BN17: =+BU17/BM17 -> 2.6744445 | BO17: =CD17 -> 625 | BP17: =+BU17/BO17 -> 295.04472 | BQ17: =CE17 -> 22050 | BR17: =+BU17/BQ17 -> 8.3629456 | BS17: =BU17-BM17-BO17-BQ17-BY17-BZ17-CA17-CB17 -> 44980.95 | BT17: =+BU17/BS17 -> 4.0995788 | BU17: 184402.95 | BV17: =+BU17/BG17% -> 21.504316 | BW17: =SUM(BG17-BH17-BU17) -> 87969.13 | BX17: =+BW17/BG17% -> 10.258599 | BY17: 15051 | BZ17: 12728 | CA17: 17048 | CB17: 2970 | CC17: 68950 | CD17: 625 | CE17: 22050 | CF17: =BY17/BG17 -> 0.017551859 | CG17: =BZ17/BG17 -> 0.014842872 | CH17: =CA17/BG17 -> 0.019880679 | CI17: =CB17/BG17 -> 0.0034634922 | CJ17: =CC17/BG17 -> 0.080406663 | CK17: =+BW17*20% -> 17593.826
A18: =A17+1 -> 11 | B18: 4 | C18: GUIHULNGAN | G18: 40 | H18: =SUM(F18*G18) -> 0 | I18: 8078 | J18: 50 | K18: =J18*I18 -> 403900 | M18: 60 | N18: =M18*L18 -> 0 | O18: 3173 | P18: 12 | Q18: =O18*P18 -> 38076 | R18: 1560 | S18: 12 | T18: =R18*S18 -> 18720 | U18: 394 | V18: 8 | W18: =U18*V18 -> 3152 | X18: 746 | Y18: 12 | Z18: =X18*Y18 -> 8952 | AA18: 551 | AB18: 10 | AC18: =AA18*AB18 -> 5510 | AD18: 278 | AE18: 25 | AF18: =AD18*AE18 -> 6950 | AG18: 906 | AH18: 7.5 | AI18: =AG18*AH18 -> 6795 | AK18: 15 | AL18: =AJ18*AK18 -> 0 | AM18: 273 | AN18: 10 | AO18: =AM18*AN18 -> 2730 | AP18: =R18+U18+X18+AA18+AD18+AG18+AM18 -> 4708 | AX18: =217+698+126+139+56+24 -> 1260 | AZ18: =O18/(I18+F18+L18) -> 0.39279525 | BA18: =AP18/(I18+F18+L18) -> 0.58281753 | BB18: =AX18/O18 -> 0.39710054 | BC18: =H18+W18+Z18+AC18+AF18+T18+K18+N18 -> 447184 | BD18: =H18+AF18+T18+K18+N18 -> 429570 | BE18: =H18+W18+Z18+AC18+AF18+T18+K18+N18 -> 447184 | BF18: =H18+W18+Z18+AC18+AF18+AI18+T18+K18+N18 -> 453979 | BG18: 518457 | BH18: 348023.98 | BI18: =+BH18/BG18% -> 67.126875 | BJ18: =SUM(BY18+BZ18+CA18+CB18) -> 32278 | BK18: =SUM(CF18+CG18+CH18+CI18) -> 0.062257815 | BL18: =B18 -> 4 | BM18: =CC18 -> 44248 | BN18: =+BU18/BM18 -> 3.3180625 | BO18: =CD18 -> 0 | BP18: =+BU18/BO18 -> #DIV/0! | BQ18: =CE18 -> 36000 | BR18: =+BU18/BQ18 -> 4.0782675 | BS18: =BU18-BM18-BO18-BQ18-BY18-BZ18-CA18-CB18 -> 34291.63 | BT18: =+BU18/BS18 -> 4.2814421 | BU18: 146817.63 | BV18: =+BU18/BG18% -> 28.318188 | BW18: =SUM(BG18-BH18-BU18) -> 23615.39 | BX18: =+BW18/BG18% -> 4.5549371 | BY18: 11346 | BZ18: 8650 | CA18: 8442 | CB18: 3840 | CC18: 44248 | CD18: 0 | CE18: 36000 | CF18: =BY18/BG18 -> 0.021884168 | CG18: =BZ18/BG18 -> 0.016684122 | CH18: =CA18/BG18 -> 0.016282932 | CI18: =CB18/BG18 -> 0.007406593 | CJ18: =CC18/BG18 -> 0.085345554 | CK18: =+BW18*20% -> 4723.078
A19: =A18+1 -> 12 | B19: 3 | C19: JIMALALUD | G19: 40 | H19: =SUM(F19*G19) -> 0 | I19: 6608 | J19: 50 | K19: =J19*I19 -> 330400 | M19: 60 | N19: =M19*L19 -> 0 | O19: 2623 | P19: 12 | Q19: =O19*P19 -> 31476 | R19: 2380 | S19: 12 | T19: =R19*S19 -> 28560 | U19: 626 | V19: 8 | W19: =U19*V19 -> 5008 | X19: 459 | Y19: 12 | Z19: =X19*Y19 -> 5508 | AA19: 639 | AB19: 10 | AC19: =AA19*AB19 -> 6390 | AD19: 230 | AE19: 25 | AF19: =AD19*AE19 -> 5750 | AG19: 156 | AH19: 7.5 | AI19: =AG19*AH19 -> 1170 | AK19: 15 | AL19: =AJ19*AK19 -> 0 | AM19: 167 | AN19: 10 | AO19: =AM19*AN19 -> 1670 | AP19: =R19+U19+X19+AA19+AD19+AG19+AM19 -> 4657 | AX19: =109+468+138+533+81+43 -> 1372 | AZ19: =O19/(I19+F19+L19) -> 0.3969431 | BA19: =AP19/(I19+F19+L19) -> 0.70475182 | BB19: =AX19/O19 -> 0.52306519 | BC19: =H19+W19+Z19+AC19+AF19+T19+K19+N19 -> 381616 | BD19: =H19+AF19+T19+K19+N19 -> 364710 | BE19: =H19+W19+Z19+AC19+AF19+T19+K19+N19 -> 381616 | BF19: =H19+W19+Z19+AC19+AF19+AI19+T19+K19+N19 -> 382786 | BG19: 441305 | BH19: 294338.75 | BI19: =+BH19/BG19% -> 66.697352 | BJ19: =SUM(BY19+BZ19+CA19+CB19) -> 26953 | BK19: =SUM(CF19+CG19+CH19+CI19) -> 0.061075673 | BL19: 4 | BM19: =CC19 -> 43625 | BN19: =+BU19/BM19 -> 2.9288053 | BO19: =CD19 -> 0 | BP19: =+BU19/BO19 -> #DIV/0! | BQ19: =CE19 -> 15000 | BR19: =+BU19/BQ19 -> 8.517942 | BS19: =BU19-BM19-BO19-BQ19-BY19-BZ19-CA19-CB19 -> 42191.13 | BT19: =+BU19/BS19 -> 3.028341 | BU19: 127769.13 | BV19: =+BU19/BG19% -> 28.952568 | BW19: =SUM(BG19-BH19-BU19) -> 19197.12 | BX19: =+BW19/BG19% -> 4.3500799 | BY19: 7564 | BZ19: 7955 | CA19: 8464 | CB19: 2970 | CC19: 43625 | CD19: 0 | CE19: 15000 | CF19: =BY19/BG19 -> 0.017140073 | CG19: =BZ19/BG19 -> 0.018026082 | CH19: =CA19/BG19 -> 0.019179479 | CI19: =CB19/BG19 -> 0.0067300393 | CJ19: =CC19/BG19 -> 0.098854534 | CK19: =+BW19*20% -> 3839.424
A20: =A19+1 -> 13 | B20: 3 | C20: JUNOB | G20: 40 | H20: =SUM(F20*G20) -> 0 | I20: 7230 | J20: 50 | K20: =J20*I20 -> 361500 | M20: 60 | N20: =M20*L20 -> 0 | O20: 3774 | P20: 12 | Q20: =O20*P20 -> 45288 | R20: 830 | S20: 12 | T20: =R20*S20 -> 9960 | U20: 609 | V20: 8 | W20: =U20*V20 -> 4872 | X20: 300 | Y20: 12 | Z20: =X20*Y20 -> 3600 | AA20: 686 | AB20: 10 | AC20: =AA20*AB20 -> 6860 | AD20: 136 | AE20: 25 | AF20: =AD20*AE20 -> 3400 | AG20: 112 | AH20: 7.5 | AI20: =AG20*AH20 -> 840 | AK20: 15 | AL20: =AJ20*AK20 -> 0 | AM20: 143 | AN20: 10 | AO20: =AM20*AN20 -> 1430 | AP20: =R20+U20+X20+AA20+AD20+AG20+AM20 -> 2816 | AX20: =272+569+96+98+54+71 -> 1160 | AZ20: =O20/(I20+F20+L20) -> 0.5219917 | BA20: =AP20/(I20+F20+L20) -> 0.38948824 | BB20: =AX20/O20 -> 0.30736619 | BC20: =H20+W20+Z20+AC20+AF20+T20+K20+N20 -> 390192 | BD20: =H20+AF20+T20+K20+N20 -> 374860 | BE20: =H20+W20+Z20+AC20+AF20+T20+K20+N20 -> 390192 | BF20: =H20+W20+Z20+AC20+AF20+AI20+T20+K20+N20 -> 391032 | BG20: 459714 | BH20: 313454.75 | BI20: =+BH20/BG20% -> 68.18473 | BJ20: =SUM(BY20+BZ20+CA20+CB20) -> 34309.5 | BK20: =SUM(CF20+CG20+CH20+CI20) -> 0.074632271 | BL20: =B20 -> 3 | BM20: =CC20 -> 41287.5 | BN20: =+BU20/BM20 -> 3.6690696 | BO20: =CD20 -> 0 | BP20: =+BU20/BO20 -> #DIV/0! | BQ20: =CE20 -> 26750 | BR20: =+BU20/BQ20 -> 5.6630546 | BS20: =BU20-BM20-BO20-BQ20-BY20-BZ20-CA20-CB20 -> 49139.71 | BT20: =+BU20/BS20 -> 3.0827758 | BU20: 151486.71 | BV20: =+BU20/BG20% -> 32.952381 | BW20: =SUM(BG20-BH20-BU20) -> -5227.46 | BX20: =+BW20/BG20% -> -1.1371113 | BY20: 11344.5 | BZ20: 7955 | CA20: 12040 | CB20: 2970 | CC20: 41287.5 | CD20: 0 | CE20: 26750 | CF20: =BY20/BG20 -> 0.024677299 | CG20: =BZ20/BG20 -> 0.017304237 | CH20: =CA20/BG20 -> 0.026190197 | CI20: =CB20/BG20 -> 0.0064605385 | CJ20: =CC20/BG20 -> 0.089811274 | CK20: =+BW20*20% -> -1045.492
A21: =A20+1 -> 14 | B21: 4 | C21: LARENA | G21: 40 | H21: =SUM(F21*G21) -> 0 | I21: 5935 | J21: 50 | K21: =J21*I21 -> 296750 | M21: 60 | N21: =M21*L21 -> 0 | O21: 4815 | P21: 12 | Q21: =O21*P21 -> 57780 | R21: 6158 | S21: 12 | T21: =R21*S21 -> 73896 | U21: 594 | V21: 8 | W21: =U21*V21 -> 4752 | X21: 185 | Y21: 12 | Z21: =X21*Y21 -> 2220 | AA21: 560 | AB21: 10 | AC21: =AA21*AB21 -> 5600 | AD21: 261 | AE21: 25 | AF21: =AD21*AE21 -> 6525 | AG21: 726 | AH21: 7.5 | AI21: =AG21*AH21 -> 5445 | AK21: 15 | AL21: =AJ21*AK21 -> 0 | AM21: 210 | AN21: 10 | AO21: =AM21*AN21 -> 2100 | AP21: =R21+U21+X21+AA21+AD21+AG21+AM21 -> 8694 | AX21: =863+108+167+63 -> 1201 | AZ21: =O21/(I21+F21+L21) -> 0.81128896 | BA21: =AP21/(I21+F21+L21) -> 1.4648694 | BB21: =AX21/O21 -> 0.24942887 | BC21: =H21+W21+Z21+AC21+AF21+T21+K21+N21 -> 389743 | BD21: =H21+AF21+T21+K21+N21 -> 377171 | BE21: =H21+W21+Z21+AC21+AF21+T21+K21+N21 -> 389743 | BF21: =H21+W21+Z21+AC21+AF21+AI21+T21+K21+N21 -> 395188 | BG21: 478890 | BH21: 318786.13 | BI21: =+BH21/BG21% -> 66.567715 | BJ21: =SUM(BY21+BZ21+CA21+CB21) -> 38535 | BK21: =SUM(CF21+CG21+CH21+CI21) -> 0.080467331 | BL21: 3 | BM21: =CC21 -> 40800 | BN21: =+BU21/BM21 -> 3.7934782 | BO21: =CD21 -> 0 | BP21: =+BU21/BO21 -> #DIV/0! | BQ21: =CE21 -> 35000 | BR21: =+BU21/BQ21 -> 4.4221117 | BS21: =BU21-BM21-BO21-BQ21-BY21-BZ21-CA21-CB21 -> 40438.91 | BT21: =+BU21/BS21 -> 3.8273512 | BU21: 154773.91 | BV21: =+BU21/BG21% -> 32.319303 | BW21: =SUM(BG21-BH21-BU21) -> 5329.96 | BX21: =+BW21/BG21% -> 1.1129821 | BY21: 15051 | BZ21: 9546 | CA21: 10968 | CB21: 2970 | CC21: 40800 | CD21: 0 | CE21: 35000 | CF21: =BY21/BG21 -> 0.031428929 | CG21: =BZ21/BG21 -> 0.019933596 | CH21: =CA21/BG21 -> 0.022902963 | CI21: =CB21/BG21 -> 0.0062018418 | CJ21: =CC21/BG21 -> 0.085197018 | CK21: =+BW21*20% -> 1065.992
A22: =A21+1 -> 15 | B22: 9 | C22: LOCSIN | G22: 40 | H22: =SUM(F22*G22) -> 0 | I22: 20930 | J22: 50 | K22: =J22*I22 -> 1046500 | M22: 60 | N22: =M22*L22 -> 0 | O22: 19374 | P22: 12 | Q22: =O22*P22 -> 232488 | R22: 0 | S22: 12 | T22: =R22*S22 -> 0 | U22: 3213 | V22: 8 | W22: =U22*V22 -> 25704 | X22: 863 | Y22: 12 | Z22: =X22*Y22 -> 10356 | AA22: 2642 | AB22: 10 | AC22: =AA22*AB22 -> 26420 | AD22: 1153 | AE22: 25 | AF22: =AD22*AE22 -> 28825 | AG22: 647 | AH22: 7.5 | AI22: =AG22*AH22 -> 4852.5 | AK22: 15 | AL22: =AJ22*AK22 -> 0 | AM22: 828 | AN22: 10 | AO22: =AM22*AN22 -> 8280 | AP22: =R22+U22+X22+AA22+AD22+AG22+AM22 -> 9346 | AX22: =773+4442+807+633+323+132 -> 7110 | AZ22: =O22/(I22+F22+L22) -> 0.92565695 | BA22: =AP22/(I22+F22+L22) -> 0.44653607 | BB22: =AX22/O22 -> 0.36698668 | BC22: =H22+W22+Z22+AC22+AF22+T22+K22+N22 -> 1137805 | BD22: =H22+AF22+T22+K22+N22 -> 1075325 | BE22: =H22+W22+Z22+AC22+AF22+T22+K22+N22 -> 1137805 | BF22: =H22+W22+Z22+AC22+AF22+AI22+T22+K22+N22 -> 1142657.5 | BG22: 1523258.5 | BH22: 1027295.8 | BI22: =+BH22/BG22% -> 67.440677 | BJ22: =SUM(BY22+BZ22+CA22+CB22) -> 84114 | BK22: =SUM(CF22+CG22+CH22+CI22) -> 0.05521978 | BL22: =B22 -> 9 | BM22: =CC22 -> 109437.5 | BN22: =+BU22/BM22 -> 3.0266997 | BO22: =CD22 -> 0 | BP22: =+BU22/BO22 -> #DIV/0! | BQ22: =CE22 -> 66150 | BR22: =+BU22/BQ22 -> 5.0073235 | BS22: =BU22-BM22-BO22-BQ22-BY22-BZ22-CA22-CB22 -> 71532.95 | BT22: =+BU22/BS22 -> 4.6305157 | BU22: 331234.45 | BV22: =+BU22/BG22% -> 21.745124 | BW22: =SUM(BG22-BH22-BU22) -> 164728.21 | BX22: =+BW22/BG22% -> 10.814199 | BY22: 22689 | BZ22: 20683 | CA22: 33992 | CB22: 6750 | CC22: 109437.5 | CD22: 0 | CE22: 66150 | CF22: =BY22/BG22 -> 0.014895042 | CG22: =BZ22/BG22 -> 0.013578129 | CH22: =CA22/BG22 -> 0.022315319 | CI22: =CB22/BG22 -> 0.0044312899 | CJ22: =CC22/BG22 -> 0.071844339 | CK22: =+BW22*20% -> 32945.642
A23: =A22+1 -> 16 | B23: 6 | C23: MABINAY1 | G23: 40 | H23: =SUM(F23*G23) -> 0 | I23: 14186 | J23: 50 | K23: =J23*I23 -> 709300 | M23: 60 | N23: =M23*L23 -> 0 | O23: 5704 | P23: 12 | Q23: =O23*P23 -> 68448 | S23: 12 | T23: =R23*S23 -> 0 | U23: 918 | V23: 8 | W23: =U23*V23 -> 7344 | X23: 523 | Y23: 12 | Z23: =X23*Y23 -> 6276 | AA23: 1256 | AB23: 10 | AC23: =AA23*AB23 -> 12560 | AD23: 180 | AE23: 25 | AF23: =AD23*AE23 -> 4500 | AG23: 435 | AH23: 7.5 | AI23: =AG23*AH23 -> 3262.5 | AK23: 15 | AL23: =AJ23*AK23 -> 0 | AN23: 10 | AO23: =AM23*AN23 -> 0 | AP23: =R23+U23+X23+AA23+AD23+AG23+AM23 -> 3312 | AX23: 2771 | AZ23: =O23/(I23+F23+L23) -> 0.40208656 | BA23: =AP23/(I23+F23+L23) -> 0.23346962 | BB23: =AX23/O23 -> 0.48579944 | BC23: =H23+W23+Z23+AC23+AF23+T23+K23+N23 -> 739980 | BD23: =H23+AF23+T23+K23+N23 -> 713800 | BE23: =H23+W23+Z23+AC23+AF23+T23+K23+N23 -> 739980 | BF23: =H23+W23+Z23+AC23+AF23+AI23+T23+K23+N23 -> 743242.5 | BG23: 865277.5 | BH23: 576217.25 | BI23: =+BH23/BG23% -> 66.593347 | BJ23: =SUM(BY23+BZ23+CA23+CB23) -> 62361 | BK23: =SUM(CF23+CG23+CH23+CI23) -> 0.072070521 | BL23: =B23 -> 6 | BM23: =CC23 -> 68450.5 | BN23: =+BU23/BM23 -> 3.3185761 | BO23: =CD23 -> 375 | BP23: =+BU23/BO23 -> 605.75517 | BQ23: =CE23 -> 26250 | BR23: =+BU23/BQ23 -> 8.6536453 | BS23: =BU23-BM23-BO23-BQ23-BY23-BZ23-CA23-CB23 -> 69721.69 | BT23: =+BU23/BS23 -> 3.2580706 | BU23: 227158.19 | BV23: =+BU23/BG23% -> 26.25264 | BW23: =SUM(BG23-BH23-BU23) -> 61902.06 | BX23: =+BW23/BG23% -> 7.1540124 | BY23: 22614 | BZ23: 14319 | CA23: 18138 | CB23: 7290 | CC23: 68450.5 | CD23: 375 | CE23: 26250 | CF23: =BY23/BG23 -> 0.026134968 | CG23: =BZ23/BG23 -> 0.016548448 | CH23: =CA23/BG23 -> 0.020962061 | CI23: =CB23/BG23 -> 0.0084250428 | CJ23: =CC23/BG23 -> 0.079108147 | CK23: =+BW23*20% -> 12380.412
A24: =A23+1 -> 17 | B24: 4 | C24: MABINAY2 | G24: 40 | H24: =SUM(F24*G24) -> 0 | I24: 7380 | J24: 50 | K24: =J24*I24 -> 369000 | M24: 60 | N24: =M24*L24 -> 0 | O24: 2781 | P24: 12 | Q24: =O24*P24 -> 33372 | R24: 320 | S24: 12 | T24: =R24*S24 -> 3840 | U24: 400 | V24: 8 | W24: =U24*V24 -> 3200 | X24: 275 | Y24: 12 | Z24: =X24*Y24 -> 3300 | AA24: 675 | AB24: 10 | AC24: =AA24*AB24 -> 6750 | AD24: 25 | AE24: 25 | AF24: =AD24*AE24 -> 625 | AG24: 121 | AH24: 7.5 | AI24: =AG24*AH24 -> 907.5 | AK24: 15 | AL24: =AJ24*AK24 -> 0 | AM24: 41 | AN24: 10 | AO24: =AM24*AN24 -> 410 | AP24: =R24+U24+X24+AA24+AD24+AG24+AM24 -> 1857 | AX24: 1116 | AZ24: =O24/(I24+F24+L24) -> 0.37682927 | BA24: =AP24/(I24+F24+L24) -> 0.25162602 | BB24: =AX24/O24 -> 0.4012945 | BC24: =H24+W24+Z24+AC24+AF24+T24+K24+N24 -> 386715 | BD24: =H24+AF24+T24+K24+N24 -> 373465 | BE24: =H24+W24+Z24+AC24+AF24+T24+K24+N24 -> 386715 | BF24: =H24+W24+Z24+AC24+AF24+AI24+T24+K24+N24 -> 387622.5 | BG24: 443728.5 | BH24: 297820.02 | BI24: =+BH24/BG24% -> 67.117623 | BJ24: =SUM(BY24+BZ24+CA24+CB24) -> 33485.5 | BK24: =SUM(CF24+CG24+CH24+CI24) -> 0.075463938 | BL24: =B24 -> 4 | BM24: =CC24 -> 48350 | BN24: =+BU24/BM24 -> 2.7352691 | BO24: =CD24 -> 437 | BP24: =+BU24/BO24 -> 302.63217 | BQ24: =CE24 -> 10000 | BR24: =+BU24/BQ24 -> 13.225026 | BS24: =BU24-BM24-BO24-BQ24-BY24-BZ24-CA24-CB24 -> 39977.76 | BT24: =+BU24/BS24 -> 3.3080958 | BU24: 132250.26 | BV24: =+BU24/BG24% -> 29.80432 | BW24: =SUM(BG24-BH24-BU24) -> 13658.22 | BX24: =+BW24/BG24% -> 3.0780579 | BY24: 11269.5 | BZ24: 9546 | CA24: 9700 | CB24: 2970 | CC24: 48350 | CD24: 437 | CE24: 10000 | CF24: =BY24/BG24 -> 0.025397287 | CG24: =BZ24/BG24 -> 0.021513155 | CH24: =CA24/BG24 -> 0.021860214 | CI24: =CB24/BG24 -> 0.006693282 | CJ24: =CC24/BG24 -> 0.10896303 | CK24: =+BW24*20% -> 2731.644
A25: =A24+1 -> 18 | B25: 6 | C25: MANJUYOD | G25: 40 | H25: =SUM(F25*G25) -> 0 | I25: 15297 | J25: 50 | K25: =J25*I25 -> 764850 | M25: 60 | N25: =M25*L25 -> 0 | O25: 7934 | P25: 12 | Q25: =O25*P25 -> 95208 | R25: 570 | S25: 12 | T25: =R25*S25 -> 6840 | U25: 882 | V25: 8 | W25: =U25*V25 -> 7056 | X25: 343 | Y25: 12 | Z25: =X25*Y25 -> 4116 | AA25: 1414 | AB25: 10 | AC25: =AA25*AB25 -> 14140 | AD25: 255 | AE25: 25 | AF25: =AD25*AE25 -> 6375 | AG25: 238 | AH25: 7.5 | AI25: =AG25*AH25 -> 1785 | AK25: 15 | AL25: =AJ25*AK25 -> 0 | AM25: 236 | AN25: 10 | AO25: =AM25*AN25 -> 2360 | AP25: =R25+U25+X25+AA25+AD25+AG25+AM25 -> 3938 | AX25: 2238 | AZ25: =O25/(I25+F25+L25) -> 0.51866379 | BA25: =AP25/(I25+F25+L25) -> 0.2574361 | BB25: =AX25/O25 -> 0.28207714 | BC25: =H25+W25+Z25+AC25+AF25+T25+K25+N25 -> 803377 | BD25: =H25+AF25+T25+K25+N25 -> 778065 | BE25: =H25+W25+Z25+AC25+AF25+T25+K25+N25 -> 803377 | BF25: =H25+W25+Z25+AC25+AF25+AI25+T25+K25+N25 -> 805162 | BG25: 949112 | BH25: 651073.29 | BI25: =+BH25/BG25% -> 68.598152 | BJ25: =SUM(BY25+BZ25+CA25+CB25) -> 56647 | BK25: =SUM(CF25+CG25+CH25+CI25) -> 0.05968421 | BL25: =B25 -> 6 | BM25: =CC25 -> 67037.5 | BN25: =+BU25/BM25 -> 2.8291526 | BO25: =CD25 -> 0 | BP25: =+BU25/BO25 -> #DIV/0! | BQ25: =CE25 -> 25000 | BR25: =+BU25/BQ25 -> 7.5863728 | BS25: =BU25-BM25-BO25-BQ25-BY25-BZ25-CA25-CB25 -> 40974.82 | BT25: =+BU25/BS25 -> 4.6286798 | BU25: 189659.32 | BV25: =+BU25/BG25% -> 19.982818 | BW25: =SUM(BG25-BH25-BU25) -> 108379.39 | BX25: =+BW25/BG25% -> 11.419031 | BY25: 15053 | BZ25: 14319 | CA25: 21875 | CB25: 5400 | CC25: 67037.5 | CE25: 25000 | CF25: =BY25/BG25 -> 0.015860088 | CG25: =BZ25/BG25 -> 0.015086734 | CH25: =CA25/BG25 -> 0.023047859 | CI25: =CB25/BG25 -> 0.0056895287 | CJ25: =CC25/BG25 -> 0.070631812 | CK25: =+BW25*20% -> 21675.878
A26: =A25+1 -> 19 | B26: 9 | C26: NOPH | G26: 40 | H26: =SUM(F26*G26) -> 0 | I26: 20605 | J26: 50 | K26: =J26*I26 -> 1030250 | M26: 60 | N26: =M26*L26 -> 0 | O26: 19010 | P26: 12 | Q26: =O26*P26 -> 228120 | S26: 12 | T26: =R26*U26 -> 0 | U26: 2538 | V26: 8 | W26: =U26*V26 -> 20304 | X26: 1112 | Y26: 12 | Z26: =X26*Y26 -> 13344 | AA26: 2586 | AB26: 10 | AC26: =AA26*AB26 -> 25860 | AD26: 650 | AE26: 25 | AF26: =AD26*AE26 -> 16250 | AG26: 823 | AH26: 7.5 | AI26: =AG26*AH26 -> 6172.5 | AK26: 15 | AL26: =AJ26*AK26 -> 0 | AM26: 528 | AN26: 10 | AO26: =AM26*AN26 -> 5280 | AP26: =R26+U26+X26+AA26+AD26+AG26+AM26 -> 8237 | AX26: 4529 | AZ26: =O26/(I26+F26+L26) -> 0.9225916 | BA26: =AP26/(I26+F26+L26) -> 0.39975734 | BB26: =AX26/O26 -> 0.23824303 | BC26: =H26+W26+Z26+AC26+AF26+T26+K26+N26 -> 1106008 | BD26: =H26+AF26+T26+K26+N26 -> 1046500 | BE26: =H26+W26+Z26+AC26+AF26+T26+K26+N26 -> 1106008 | BF26: =H26+W26+Z26+AC26+AF26+AI26+T26+K26+N26 -> 1112180.5 | BG26: 1435576.5 | BH26: 974732.79 | BI26: =+BH26/BG26% -> 67.898352 | BJ26: =SUM(BY26+BZ26+CA26+CB26) -> 82235.5 | BK26: =SUM(CF26+CG26+CH26+CI26) -> 0.057283955 | BL26: =B26 -> 9 | BM26: =CC26 -> 103590 | BN26: =+BU26/BM26 -> 2.7905323 | BO26: =CD26 -> 62.5 | BP26: =+BU26/BO26 -> 4625.1398 | BQ26: =CE26 -> 38217.86 | BR26: =+BU26/BQ26 -> 7.5637736 | BS26: =BU26-BM26-BO26-BQ26-BY26-BZ26-CA26-CB26 -> 64965.38 | BT26: =+BU26/BS26 -> 4.4496198 | BU26: 289071.24 | BV26: =+BU26/BG26% -> 20.136248 | BW26: =SUM(BG26-BH26-BU26) -> 171772.47 | BX26: =+BW26/BG26% -> 11.9654 | BY26: 26395.5 | BZ26: 22274 | CA26: 27896 | CB26: 5670 | CC26: 103590 | CD26: 62.5 | CE26: 38217.86 | CF26: =BY26/BG26 -> 0.01838669 | CG26: =BZ26/BG26 -> 0.015515718 | CH26: =CA26/BG26 -> 0.019431915 | CI26: =CB26/BG26 -> 0.0039496328 | CJ26: =CC26/BG26 -> 0.072159164 | CK26: =+BW26*20% -> 34354.494
A27: =A26+1 -> 20 | B27: 5 | C27: PAMPLONA | G27: 40 | H27: =SUM(F27*G27) -> 0 | I27: 10752 | J27: 50 | K27: =J27*I27 -> 537600 | M27: 60 | N27: =M27*L27 -> 0 | O27: 3337 | P27: 12 | Q27: =O27*P27 -> 40044 | R27: 1860 | S27: 12 | T27: =R27*S27 -> 22320 | U27: 874 | V27: 8 | W27: =U27*V27 -> 6992 | X27: 250 | Y27: 12 | Z27: =X27*Y27 -> 3000 | AA27: 857 | AB27: 10 | AC27: =AA27*AB27 -> 8570 | AD27: 101 | AE27: 25 | AF27: =AD27*AE27 -> 2525 | AG27: 136 | AH27: 7.5 | AI27: =AG27*AH27 -> 1020 | AK27: 15 | AL27: =AJ27*AK27 -> 0 | AM27: 214 | AN27: 10 | AO27: =AM27*AN27 -> 2140 | AP27: =R27+U27+X27+AA27+AD27+AG27+AM27 -> 4292 | AX27: 2530 | AZ27: =O27/(I27+F27+L27) -> 0.31036086 | BA27: =AP27/(I27+F27+L27) -> 0.39918155 | BB27: =AX27/O27 -> 0.75816602 | BC27: =H27+W27+Z27+AC27+AF27+T27+K27+N27 -> 581007 | BD27: =H27+AF27+T27+K27+N27 -> 562445 | BE27: =H27+W27+Z27+AC27+AF27+T27+K27+N27 -> 581007 | BF27: =H27+W27+Z27+AC27+AF27+AI27+T27+K27+N27 -> 582027 | BG27: 673856 | BH27: 452949.99 | BI27: =+BH27/BG27% -> 67.217624 | BJ27: =SUM(BY27+BZ27+CA27+CB27) -> 49373.5 | BK27: =SUM(CF27+CG27+CH27+CI27) -> 0.073270105 | BL27: 4 | BM27: =CC27 -> 47426 | BN27: =+BU27/BM27 -> 3.3108474 | BO27: =CD27 -> 437 | BP27: =+BU27/BO27 -> 359.31407 | BQ27: =CE27 -> 16000 | BR27: =+BU27/BQ27 -> 9.8137656 | BS27: =BU27-BM27-BO27-BQ27-BY27-BZ27-CA27-CB27 -> 43783.75 | BT27: =+BU27/BS27 -> 3.5862677 | BU27: 157020.25 | BV27: =+BU27/BG27% -> 23.301751 | BW27: =SUM(BG27-BH27-BU27) -> 63885.76 | BX27: =+BW27/BG27% -> 9.4806249 | BY27: 18832.5 | BZ27: 11137 | CA27: 14544 | CB27: 4860 | CC27: 47426 | CD27: 437 | CE27: 16000 | CF27: =BY27/BG27 -> 0.027947366 | CG27: =BZ27/BG27 -> 0.01652727 | CH27: =CA27/BG27 -> 0.021583246 | CI27: =CB27/BG27 -> 0.0072122234 | CJ27: =CC27/BG27 -> 0.070380022 | CK27: =+BW27*20% -> 12777.152
A28: =A27+1 -> 21 | B28: 4 | C28: QUEZON | G28: 40 | H28: =SUM(F28*G28) -> 0 | I28: 8421 | J28: 50 | K28: =J28*I28 -> 421050 | M28: 60 | N28: =M28*L28 -> 0 | O28: 3758 | P28: 12 | Q28: =O28*P28 -> 45096 | R28: 2160 | S28: 12 | T28: =R28*S28 -> 25920 | U28: 984 | V28: 8 | W28: =U28*V28 -> 7872 | X28: 907 | Y28: 12 | Z28: =X28*Y28 -> 10884 | AA28: 1468 | AB28: 10 | AC28: =AA28*AB28 -> 14680 | AD28: 295 | AE28: 25 | AF28: =AD28*AE28 -> 7375 | AG28: 750 | AH28: 7.5 | AI28: =AG28*AH28 -> 5625 | AK28: 15 | AL28: =AJ28*AK28 -> 0 | AN28: 10 | AO28: =AM28*AN28 -> 0 | AP28: =R28+U28+X28+AA28+AD28+AG28+AM28 -> 6564 | AX28: 1804 | AZ28: =O28/(I28+F28+L28) -> 0.44626529 | BA28: =AP28/(I28+F28+L28) -> 0.77947987 | BB28: =AX28/O28 -> 0.48004258 | BC28: =H28+W28+Z28+AC28+AF28+T28+K28+N28 -> 487781 | BD28: =H28+AF28+T28+K28+N28 -> 454345 | BE28: =H28+W28+Z28+AC28+AF28+T28+K28+N28 -> 487781 | BF28: =H28+W28+Z28+AC28+AF28+AI28+T28+K28+N28 -> 493406 | BG28: 572889 | BH28: 382958.92 | BI28: =+BH28/BG28% -> 66.846967 | BJ28: =SUM(BY28+BZ28+CA28+CB28) -> 35928 | BK28: =SUM(CF28+CG28+CH28+CI28) -> 0.062713719 | BL28: =B28 -> 4 | BM28: =CC28 -> 49444 | BN28: =+BU28/BM28 -> 2.5249691 | BO28: =CD28 -> 256 | BP28: =+BU28/BO28 -> 487.6741 | BQ28: =CE28 -> 12000 | BR28: =+BU28/BQ28 -> 10.403714 | BS28: =BU28-BM28-BO28-BQ28-BY28-BZ28-CA28-CB28 -> 27216.57 | BT28: =+BU28/BS28 -> 4.5870795 | BU28: 124844.57 | BV28: =+BU28/BG28% -> 21.792105 | BW28: =SUM(BG28-BH28-BU28) -> 65085.51 | BX28: =+BW28/BG28% -> 11.360929 | BY28: 11346 | BZ28: 10380 | CA28: 8442 | CB28: 5760 | CC28: 49444 | CD28: 256 | CE28: 12000 | CF28: =BY28/BG28 -> 0.019804884 | CG28: =BZ28/BG28 -> 0.018118693 | CH28: =CA28/BG28 -> 0.014735839 | CI28: =CB28/BG28 -> 0.010054304 | CJ28: =CC28/BG28 -> 0.086306422 | CK28: =+BW28*20% -> 13017.102
A29: =A28+1 -> 22 | B29: 7 | C29: SAGAY1 | G29: 40 | H29: =SUM(F29*G29) -> 0 | I29: 23401 | J29: 50 | K29: =J29*I29 -> 1170050 | M29: 60 | N29: =M29*L29 -> 0 | O29: 7801 | P29: 12 | Q29: =O29*P29 -> 93612 | R29: 1270 | S29: 12 | T29: =R29*S29 -> 15240 | U29: 960 | V29: 8 | W29: =U29*V29 -> 7680 | X29: 629 | Y29: 12 | Z29: =X29*Y29 -> 7548 | AA29: 1231 | AB29: 10 | AC29: =AA29*AB29 -> 12310 | AD29: 370 | AE29: 25 | AF29: =AD29*AE29 -> 9250 | AG29: 269 | AH29: 7.5 | AI29: =AG29*AH29 -> 2017.5 | AK29: 15 | AL29: =AJ29*AK29 -> 0 | AM29: 309 | AN29: 10 | AO29: =AM29*AN29 -> 3090 | AP29: =R29+U29+X29+AA29+AD29+AG29+AM29 -> 5038 | AX29: 3723 | AZ29: =O29/(I29+F29+L29) -> 0.33336182 | BA29: =AP29/(I29+F29+L29) -> 0.21528994 | BB29: =AX29/O29 -> 0.47724651 | BC29: =H29+W29+Z29+AC29+AF29+T29+K29+N29 -> 1222078 | BD29: =H29+AF29+T29+K29+N29 -> 1194540 | BE29: =H29+W29+Z29+AC29+AF29+T29+K29+N29 -> 1222078 | BF29: =H29+W29+Z29+AC29+AF29+AI29+T29+K29+N29 -> 1224095.5 | BG29: 1392269.5 | BH29: 935146.07 | BI29: =+BH29/BG29% -> 67.16703 | BJ29: =SUM(BY29+BZ29+CA29+CB29) -> 87351 | BK29: =SUM(CF29+CG29+CH29+CI29) -> 0.062740008 | BL29: =B29 -> 7 | BM29: =CC29 -> 76163 | BN29: =+BU29/BM29 -> 3.54087 | BO29: =CD29 -> 1602.12 | BP29: =+BU29/BO29 -> 168.32901 | BQ29: =CE29 -> 20000 | BR29: =+BU29/BQ29 -> 13.484164 | BS29: =BU29-BM29-BO29-BQ29-BY29-BZ29-CA29-CB29 -> 84567.16 | BT29: =+BU29/BS29 -> 3.1889835 | BU29: 269683.28 | BV29: =+BU29/BG29% -> 19.370049 | BW29: =SUM(BG29-BH29-BU29) -> 187440.15 | BX29: =+BW29/BG29% -> 13.462922 | BY29: 32157 | BZ29: 22490 | CA29: 26304 | CB29: 6400 | CC29: 76163 | CD29: 1602.12 | CE29: 20000 | CF29: =BY29/BG29 -> 0.023096821 | CG29: =BZ29/BG29 -> 0.016153482 | CH29: =CA29/BG29 -> 0.018892894 | CI29: =CB29/BG29 -> 0.0045968112 | CJ29: =CC29/BG29 -> 0.054704208 | CK29: =+BW29*20% -> 37488.03
A30: =A29+1 -> 23 | B30: 2 | C30: SAGAY2 | G30: 40 | H30: =SUM(F30*G30) -> 0 | I30: 5773 | J30: 50 | K30: =J30*I30 -> 288650 | M30: 60 | N30: =M30*L30 -> 0 | O30: 2122 | P30: 12 | Q30: =O30*P30 -> 25464 | R30: 2400 | S30: 12 | T30: =R30*S30 -> 28800 | U30: 280 | V30: 8 | W30: =U30*V30 -> 2240 | X30: 201 | Y30: 12 | Z30: =X30*Y30 -> 2412 | AA30: 276 | AB30: 10 | AC30: =AA30*AB30 -> 2760 | AD30: 85 | AE30: 25 | AF30: =AD30*AE30 -> 2125 | AG30: 145 | AH30: 7.5 | AI30: =AG30*AH30 -> 1087.5 | AK30: 15 | AL30: =AJ30*AK30 -> 0 | AM30: 78 | AN30: 10 | AO30: =AM30*AN30 -> 780 | AP30: =R30+U30+X30+AA30+AD30+AG30+AM30 -> 3465 | AX30: 767 | AZ30: =O30/(I30+F30+L30) -> 0.36757319 | BA30: =AP30/(I30+F30+L30) -> 0.60020786 | BB30: =AX30/O30 -> 0.36145146 | BC30: =H30+W30+Z30+AC30+AF30+T30+K30+N30 -> 326987 | BD30: =H30+AF30+T30+K30+N30 -> 319575 | BE30: =H30+W30+Z30+AC30+AF30+T30+K30+N30 -> 326987 | BF30: =H30+W30+Z30+AC30+AF30+AI30+T30+K30+N30 -> 328074.5 | BG30: 368695.5 | BH30: 245318.33 | BI30: =+BH30/BG30% -> 66.536839 | BJ30: =SUM(BY30+BZ30+CA30+CB30) -> 26662 | BK30: =SUM(CF30+CG30+CH30+CI30) -> 0.072314417 | BL30: 3 | BM30: =CC30 -> 33277 | BN30: =+BU30/BM30 -> 3.256378 | BO30: =CD30 -> 1920 | BP30: =+BU30/BO30 -> 56.438797 | BQ30: =CE30 -> 14000 | BR30: =+BU30/BQ30 -> 7.7401779 | BS30: =BU30-BM30-BO30-BQ30-BY30-BZ30-CA30-CB30 -> 32503.49 | BT30: =+BU30/BS30 -> 3.3338725 | BU30: 108362.49 | BV30: =+BU30/BG30% -> 29.390782 | BW30: =SUM(BG30-BH30-BU30) -> 15014.68 | BX30: =+BW30/BG30% -> 4.0723795 | BY30: 10719 | BZ30: 6781 | CA30: 6732 | CB30: 2430 | CC30: 33277 | CD30: 1920 | CE30: 14000 | CF30: =BY30/BG30 -> 0.029072771 | CG30: =BZ30/BG30 -> 0.018391871 | CH30: =CA30/BG30 -> 0.01825897 | CI30: =CB30/BG30 -> 0.0065908046 | CJ30: =CC30/BG30 -> 0.090256051 | CK30: =+BW30*20% -> 3002.936
A31: =A30+1 -> 24 | B31: 5 | C31: SAN CARLOS1 | G31: 40 | H31: =SUM(F31*G31) -> 0 | I31: 8913 | J31: 50 | K31: =J31*I31 -> 445650 | M31: 60 | N31: =M31*L31 -> 0 | O31: 3432 | P31: 12 | Q31: =O31*P31 -> 41184 | R31: 3030 | S31: 12 | T31: =R31*S31 -> 36360 | U31: 475 | V31: 8 | W31: =U31*V31 -> 3800 | X31: 529 | Y31: 12 | Z31: =X31*Y31 -> 6348 | AA31: 657 | AB31: 10 | AC31: =AA31*AB31 -> 6570 | AD31: 97 | AE31: 25 | AF31: =AD31*AE31 -> 2425 | AG31: 230 | AH31: 7.5 | AI31: =AG31*AH31 -> 1725 | AK31: 15 | AL31: =AJ31*AK31 -> 0 | AM31: 162 | AN31: 10 | AO31: =AM31*AN31 -> 1620 | AP31: =R31+U31+X31+AA31+AD31+AG31+AM31 -> 5180 | AX31: 941 | AZ31: =O31/(I31+F31+L31) -> 0.38505554 | BA31: =AP31/(I31+F31+L31) -> 0.58117357 | BB31: =AX31/O31 -> 0.27418415 | BC31: =H31+W31+Z31+AC31+AF31+T31+K31+N31 -> 501153 | BD31: =H31+AF31+T31+K31+N31 -> 484435 | BE31: =H31+W31+Z31+AC31+AF31+T31+K31+N31 -> 501153 | BF31: =H31+W31+Z31+AC31+AF31+AI31+T31+K31+N31 -> 502878 | BG31: 563654 | BH31: 376468.59 | BI31: =+BH31/BG31% -> 66.790724 | BJ31: =SUM(BY31+BZ31+CA31+CB31) -> 41635 | BK31: =SUM(CF31+CG31+CH31+CI31) -> 0.073866237 | BL31: =B31 -> 5 | BM31: =CC31 -> 58516.48 | BN31: =+BU31/BM31 -> 2.5116506 | BO31: =CD31 -> 512.96 | BP31: =+BU31/BO31 -> 286.51932 | BQ31: =CE31 -> 15000 | BR31: =+BU31/BQ31 -> 9.7981967 | BS31: =BU31-BM31-BO31-BQ31-BY31-BZ31-CA31-CB31 -> 31308.51 | BT31: =+BU31/BS31 -> 4.6943451 | BU31: 146972.95 | BV31: =+BU31/BG31% -> 26.07503 | BW31: =SUM(BG31-BH31-BU31) -> 40212.46 | BX31: =+BW31/BG31% -> 7.1342455 | BY31: 15053 | BZ31: 12110 | CA31: 8442 | CB31: 6030 | CC31: 58516.48 | CD31: 512.96 | CE31: 15000 | CF31: =BY31/BG31 -> 0.0267061 | CG31: =BZ31/BG31 -> 0.021484812 | CH31: =CA31/BG31 -> 0.014977273 | CI31: =CB31/BG31 -> 0.010698052 | CJ31: =CC31/BG31 -> 0.10381631 | CK31: =+BW31*20% -> 8042.492
A32: =A31+1 -> 25 | B32: 6 | C32: SAN CARLOS2 | G32: 40 | H32: =SUM(F32*G32) -> 0 | I32: 9814 | J32: 50 | K32: =J32*I32 -> 490700 | M32: 60 | N32: =M32*L32 -> 0 | O32: 5470 | P32: 12 | Q32: =O32*P32 -> 65640 | R32: 3070 | S32: 12 | T32: =R32*S32 -> 36840 | U32: 920 | V32: 8 | W32: =U32*V32 -> 7360 | X32: 909 | Y32: 12 | Z32: =X32*Y32 -> 10908 | AA32: 1358 | AB32: 10 | AC32: =AA32*AB32 -> 13580 | AD32: 205 | AE32: 25 | AF32: =AD32*AE32 -> 5125 | AG32: 189 | AH32: 7.5 | AI32: =AG32*AH32 -> 1417.5 | AK32: 15 | AL32: =AJ32*AK32 -> 0 | AM32: 206 | AN32: 10 | AO32: =AM32*AN32 -> 2060 | AP32: =R32+U32+X32+AA32+AD32+AG32+AM32 -> 6857 | AX32: 2260 | AZ32: =O32/(I32+F32+L32) -> 0.55736703 | BA32: =AP32/(I32+F32+L32) -> 0.69869574 | BB32: =AX32/O32 -> 0.41316271 | BC32: =H32+W32+Z32+AC32+AF32+T32+K32+N32 -> 564513 | BD32: =H32+AF32+T32+K32+N32 -> 532665 | BE32: =H32+W32+Z32+AC32+AF32+T32+K32+N32 -> 564513 | BF32: =H32+W32+Z32+AC32+AF32+AI32+T32+K32+N32 -> 565930.5 | BG32: 677837.5 | BH32: 446638.85 | BI32: =+BH32/BG32% -> 65.891729 | BJ32: =SUM(BY32+BZ32+CA32+CB32) -> 46351 | BK32: =SUM(CF32+CG32+CH32+CI32) -> 0.068380696 | BL32: =B32 -> 6 | BM32: =CC32 -> 75783 | BN32: =+BU32/BM32 -> 2.2261885 | BO32: =CD32 -> 0 | BP32: =+BU32/BO32 -> #DIV/0! | BQ32: =CE32 -> 9316.9 | BR32: =+BU32/BQ32 -> 18.107658 | BS32: =BU32-BM32-BO32-BQ32-BY32-BZ32-CA32-CB32 -> 37256.34 | BT32: =+BU32/BS32 -> 4.5282827 | BU32: 168707.24 | BV32: =+BU32/BG32% -> 24.889039 | BW32: =SUM(BG32-BH32-BU32) -> 62491.41 | BX32: =+BW32/BG32% -> 9.2192317 | BY32: 15128 | BZ32: 13840 | CA32: 12583 | CB32: 4800 | CC32: 75783 | CE32: 9316.9 | CF32: =BY32/BG32 -> 0.022318033 | CG32: =BZ32/BG32 -> 0.020417873 | CH32: =CA32/BG32 -> 0.018563446 | CI32: =CB32/BG32 -> 0.0070813432 | CJ32: =CC32/BG32 -> 0.11180113 | CK32: =+BW32*20% -> 12498.282
A33: =A32+1 -> 26 | B33: 4 | C33: SAN CARLOS5 | G33: 40 | H33: =SUM(F33*G33) -> 0 | I33: 8895 | J33: 50 | K33: =J33*I33 -> 444750 | M33: 60 | N33: =M33*L33 -> 0 | O33: 2923 | P33: 12 | Q33: =O33*P33 -> 35076 | R33: 2250 | S33: 12 | T33: =R33*S33 -> 27000 | U33: 454 | V33: 8 | W33: =U33*V33 -> 3632 | X33: 737 | Y33: 12 | Z33: =X33*Y33 -> 8844 | AA33: 755 | AB33: 10 | AC33: =AA33*AB33 -> 7550 | AD33: 227 | AE33: 25 | AF33: =AD33*AE33 -> 5675 | AG33: 132 | AH33: 7.5 | AI33: =AG33*AH33 -> 990 | AK33: 15 | AL33: =AJ33*AK33 -> 0 | AM33: 225 | AN33: 10 | AO33: =AM33*AN33 -> 2250 | AP33: =R33+U33+X33+AA33+AD33+AG33+AM33 -> 4780 | AX33: 757 | AZ33: =O33/(I33+F33+L33) -> 0.32861158 | BA33: =AP33/(I33+F33+L33) -> 0.53738055 | BB33: =AX33/O33 -> 0.2589805 | BC33: =H33+W33+Z33+AC33+AF33+T33+K33+N33 -> 497451 | BD33: =H33+AF33+T33+K33+N33 -> 477425 | BE33: =H33+W33+Z33+AC33+AF33+T33+K33+N33 -> 497451 | BF33: =H33+W33+Z33+AC33+AF33+AI33+T33+K33+N33 -> 498441 | BG33: 550572 | BH33: 370404.38 | BI33: =+BH33/BG33% -> 67.276284 | BJ33: =SUM(BY33+BZ33+CA33+CB33) -> 39424 | BK33: =SUM(CF33+CG33+CH33+CI33) -> 0.07160553 | BL33: =B33 -> 4 | BM33: =CC33 -> 50813 | BN33: =+BU33/BM33 -> 3.0027251 | BO33: =CD33 -> 0 | BP33: =+BU33/BO33 -> #DIV/0! | BQ33: =CE33 -> 30000 | BR33: =+BU33/BQ33 -> 5.0859157 | BS33: =BU33-BM33-BO33-BQ33-BY33-BZ33-CA33-CB33 -> 32340.47 | BT33: =+BU33/BS33 -> 4.7178495 | BU33: 152577.47 | BV33: =+BU33/BG33% -> 27.712537 | BW33: =SUM(BG33-BH33-BU33) -> 27590.15 | BX33: =+BW33/BG33% -> 5.0111793 | BY33: 15128 | BZ33: 10380 | CA33: 9756 | CB33: 4160 | CC33: 50813 | CE33: 30000 | CF33: =BY33/BG33 -> 0.027476879 | CG33: =BZ33/BG33 -> 0.01885312 | CH33: =CA33/BG33 -> 0.017719753 | CI33: =CB33/BG33 -> 0.0075557784 | CJ33: =CC33/BG33 -> 0.09229129 | CK33: =+BW33*20% -> 5518.03
A34: =A33+1 -> 27 | B34: 4 | C34: SAN CARLOS7 | G34: 40 | H34: =SUM(F34*G34) -> 0 | I34: 8500 | J34: 50 | K34: =J34*I34 -> 425000 | M34: 60 | N34: =M34*L34 -> 0 | O34: 3764 | P34: 12 | Q34: =O34*P34 -> 45168 | R34: 2630 | S34: 12 | T34: =R34*S34 -> 31560 | U34: 600 | V34: 8 | W34: =U34*V34 -> 4800 | X34: 734 | Y34: 12 | Z34: =X34*Y34 -> 8808 | AA34: 950 | AB34: 10 | AC34: =AA34*AB34 -> 9500 | AD34: 148 | AE34: 25 | AF34: =AD34*AE34 -> 3700 | AG34: 356 | AH34: 7.5 | AI34: =AG34*AH34 -> 2670 | AK34: 15 | AL34: =AJ34*AK34 -> 0 | AM34: 242 | AN34: 10 | AO34: =AM34*AN34 -> 2420 | AP34: =R34+U34+X34+AA34+AD34+AG34+AM34 -> 5660 | AX34: 1777 | AZ34: =O34/(I34+F34+L34) -> 0.44282353 | BA34: =AP34/(I34+F34+L34) -> 0.66588235 | BB34: =AX34/O34 -> 0.47210414 | BC34: =H34+W34+Z34+AC34+AF34+T34+K34+N34 -> 483368 | BD34: =H34+AF34+T34+K34+N34 -> 460260 | BE34: =H34+W34+Z34+AC34+AF34+T34+K34+N34 -> 483368 | BF34: =H34+W34+Z34+AC34+AF34+AI34+T34+K34+N34 -> 486038 | BG34: 568715 | BH34: 378633.21 | BI34: =+BH34/BG34% -> 66.576969 | BJ34: =SUM(BY34+BZ34+CA34+CB34) -> 35928 | BK34: =SUM(CF34+CG34+CH34+CI34) -> 0.063173998 | BL34: =B34 -> 4 | BM34: =CC34 -> 39865.29 | BN34: =+BU34/BM34 -> 3.2805556 | BO34: =CD34 -> 0 | BP34: =+BU34/BO34 -> #DIV/0! | BQ34: =CE34 -> 20000 | BR34: =+BU34/BQ34 -> 6.539015 | BS34: =BU34-BM34-BO34-BQ34-BY34-BZ34-CA34-CB34 -> 34987.01 | BT34: =+BU34/BS34 -> 3.7379673 | BU34: 130780.3 | BV34: =+BU34/BG34% -> 22.995754 | BW34: =SUM(BG34-BH34-BU34) -> 59301.49 | BX34: =+BW34/BG34% -> 10.427277 | BY34: 11346 | BZ34: 10380 | CA34: 8442 | CB34: 5760 | CC34: 39865.29 | CE34: 20000 | CF34: =BY34/BG34 -> 0.019950239 | CG34: =BZ34/BG34 -> 0.018251673 | CH34: =CA34/BG34 -> 0.01484399 | CI34: =CB34/BG34 -> 0.010128096 | CJ34: =CC34/BG34 -> 0.070097131 | CK34: =+BW34*20% -> 11860.298
A35: =A34+1 -> 28 | B35: 2 | C35: SANTANDER | G35: 40 | H35: =SUM(F35*G35) -> 0 | I35: 3440 | J35: 50 | K35: =J35*I35 -> 172000 | M35: 60 | N35: =M35*L35 -> 0 | O35: 1788 | P35: 12 | Q35: =O35*P35 -> 21456 | R35: 930 | S35: 12 | T35: =R35*S35 -> 11160 | U35: 743 | V35: 8 | W35: =U35*V35 -> 5944 | X35: 656 | Y35: 12 | Z35: =X35*Y35 -> 7872 | AA35: 760 | AB35: 10 | AC35: =AA35*AB35 -> 7600 | AD35: 204 | AE35: 25 | AF35: =AD35*AE35 -> 5100 | AG35: 498 | AH35: 7.5 | AI35: =AG35*AH35 -> 3735 | AK35: 15 | AL35: =AJ35*AK35 -> 0 | AN35: 10 | AO35: =AM35*AN35 -> 0 | AP35: =R35+U35+X35+AA35+AD35+AG35+AM35 -> 3791 | AX35: 877 | AZ35: =O35/(I35+F35+L35) -> 0.51976744 | BA35: =AP35/(I35+F35+L35) -> 1.1020349 | BB35: =AX35/O35 -> 0.49049217 | BC35: =H35+W35+Z35+AC35+AF35+T35+K35+N35 -> 209676 | BD35: =H35+AF35+T35+K35+N35 -> 188260 | BE35: =H35+W35+Z35+AC35+AF35+T35+K35+N35 -> 209676 | BF35: =H35+W35+Z35+AC35+AF35+AI35+T35+K35+N35 -> 213411 | BG35: 252221 | BH35: 167198.12 | BI35: =+BH35/BG35% -> 66.290325 | BJ35: =SUM(BY35+BZ35+CA35+CB35) -> 16089 | BK35: =SUM(CF35+CG35+CH35+CI35) -> 0.063789296 | BL35: =B35 -> 2 | BM35: =CC35 -> 24500 | BN35: =+BU35/BM35 -> 3.0308416 | BO35: =CD35 -> 5061 | BP35: =+BU35/BO35 -> 14.672124 | BQ35: =CE35 -> 12000 | BR35: =+BU35/BQ35 -> 6.1879683 | BS35: =BU35-BM35-BO35-BQ35-BY35-BZ35-CA35-CB35 -> 16605.62 | BT35: =+BU35/BS35 -> 4.4717162 | BU35: 74255.62 | BV35: =+BU35/BG35% -> 29.440697 | BW35: =SUM(BG35-BH35-BU35) -> 10767.26 | BX35: =+BW35/BG35% -> 4.2689784 | BY35: 3877 | BZ35: 6364 | CA35: 4768 | CB35: 1080 | CC35: 24500 | CD35: 5061 | CE35: 12000 | CF35: =BY35/BG35 -> 0.01537144 | CG35: =BZ35/BG35 -> 0.02523184 | CH35: =CA35/BG35 -> 0.018904056 | CI35: =CB35/BG35 -> 0.0042819591 | CJ35: =CC35/BG35 -> 0.097137035 | CK35: =+BW35*20% -> 2153.452
A36: =A35+1 -> 29 | B36: 2 | C36: STA.AGUEDA | G36: 40 | H36: =SUM(F36*G36) -> 0 | I36: 4079 | J36: 50 | K36: =J36*I36 -> 203950 | M36: 60 | N36: =M36*L36 -> 0 | O36: 1480 | P36: 12 | Q36: =O36*P36 -> 17760 | R36: 3350 | S36: 12 | T36: =R36*S36 -> 40200 | U36: 383 | V36: 8 | W36: =U36*V36 -> 3064 | X36: 227 | Y36: 12 | Z36: =X36*Y36 -> 2724 | AA36: 470 | AB36: 10 | AC36: =AA36*AB36 -> 4700 | AD36: 191 | AE36: 25 | AF36: =AD36*AE36 -> 4775 | AH36: 7.5 | AI36: =AG36*AH36 -> 0 | AK36: 15 | AL36: =AJ36*AK36 -> 0 | AN36: 10 | AO36: =AM36*AN36 -> 0 | AP36: =R36+U36+X36+AA36+AD36+AG36+AM36 -> 4621 | AX36: =588+12 -> 600 | AZ36: =O36/(I36+F36+L36) -> 0.36283403 | BA36: =AP36/(I36+F36+L36) -> 1.1328757 | BB36: =AX36/O36 -> 0.40540541 | BC36: =H36+W36+Z36+AC36+AF36+T36+K36+N36 -> 259413 | BD36: =H36+AF36+T36+K36+N36 -> 248925 | BE36: =H36+W36+Z36+AC36+AF36+T36+K36+N36 -> 259413 | BF36: =H36+W36+Z36+AC36+AF36+AI36+T36+K36+N36 -> 259413 | BG36: 287898 | BH36: 190176.33 | BI36: =+BH36/BG36% -> 66.056843 | BJ36: =SUM(BY36+BZ36+CA36+CB36) -> 23750 | BK36: =SUM(CF36+CG36+CH36+CI36) -> 0.082494495 | BL36: =B36 -> 2 | BM36: =CC36 -> 24750 | BN36: =+BU36/BM36 -> 2.8980776 | BO36: =CD36 -> 0 | BP36: =+BU36/BO36 -> #DIV/0! | BQ36: =CE36 -> 10000 | BR36: =+BU36/BQ36 -> 7.172742 | BS36: =BU36-BM36-BO36-BQ36-BY36-BZ36-CA36-CB36 -> 13227.42 | BT36: =+BU36/BS36 -> 5.4226312 | BU36: 71727.42 | BV36: =+BU36/BG36% -> 24.914178 | BW36: =SUM(BG36-BH36-BU36) -> 25994.25 | BX36: =+BW36/BG36% -> 9.028979 | BY36: 11268 | BZ36: 6364 | CA36: 4768 | CB36: 1350 | CC36: 24750 | CE36: 10000 | CF36: =BY36/BG36 -> 0.039138862 | CG36: =BZ36/BG36 -> 0.022105051 | CH36: =CA36/BG36 -> 0.016561421 | CI36: =CB36/BG36 -> 0.0046891607 | CJ36: =CC36/BG36 -> 0.085967947 | CK36: =+BW36*20% -> 5198.85
A37: =A36+1 -> 30 | B37: 5 | C37: STA.ROSA | G37: 40 | H37: =SUM(F37*G37) -> 0 | I37: 8169 | J37: 50 | K37: =J37*I37 -> 408450 | M37: 60 | N37: =M37*L37 -> 0 | O37: 7457 | P37: 12 | Q37: =O37*P37 -> 89484 | R37: 7311 | S37: 12 | T37: =R37*S37 -> 87732 | U37: 599 | V37: 8 | W37: =U37*V37 -> 4792 | X37: 269 | Y37: 12 | Z37: =X37*Y37 -> 3228 | AA37: 762 | AB37: 10 | AC37: =AA37*AB37 -> 7620 | AD37: 343 | AE37: 25 | AF37: =AD37*AE37 -> 8575 | AG37: 692 | AH37: 7.5 | AI37: =AG37*AH37 -> 5190 | AK37: 15 | AL37: =AJ37*AK37 -> 0 | AM37: 362 | AN37: 10 | AO37: =AM37*AN37 -> 3620 | AP37: =R37+U37+X37+AA37+AD37+AG37+AM37 -> 10338 | AX37: 2701 | AZ37: =O37/(I37+F37+L37) -> 0.91284123 | BA37: =AP37/(I37+F37+L37) -> 1.265516 | BB37: =AX37/O37 -> 0.36221 | BC37: =H37+W37+Z37+AC37+AF37+T37+K37+N37 -> 520397 | BD37: =H37+AF37+T37+K37+N37 -> 504757 | BE37: =H37+W37+Z37+AC37+AF37+T37+K37+N37 -> 520397 | BF37: =H37+W37+Z37+AC37+AF37+AI37+T37+K37+N37 -> 525587 | BG37: 668798 | BH37: 441940.75 | BI37: =+BH37/BG37% -> 66.079855 | BJ37: =SUM(BY37+BZ37+CA37+CB37) -> 44235 | BK37: =SUM(CF37+CG37+CH37+CI37) -> 0.066141047 | BL37: 5 | BM37: =CC37 -> 53750 | BN37: =+BU37/BM37 -> 3.3538765 | BO37: =CD37 -> 3000 | BP37: =+BU37/BO37 -> 60.090287 | BQ37: =CE37 -> 44000 | BR37: =+BU37/BQ37 -> 4.097065 | BS37: =BU37-BM37-BO37-BQ37-BY37-BZ37-CA37-CB37 -> 35285.86 | BT37: =+BU37/BS37 -> 5.1088697 | BU37: 180270.86 | BV37: =+BU37/BG37% -> 26.954456 | BW37: =SUM(BG37-BH37-BU37) -> 46586.39 | BX37: =+BW37/BG37% -> 6.9656892 | BY37: 15126 | BZ37: 12728 | CA37: 13141 | CB37: 3240 | CC37: 53750 | CD37: 3000 | CE37: 44000 | CF37: =BY37/BG37 -> 0.022616694 | CG37: =BZ37/BG37 -> 0.019031157 | CH37: =CA37/BG37 -> 0.019648683 | CI37: =CB37/BG37 -> 0.0048445121 | CJ37: =CC37/BG37 -> 0.080368063 | CK37: =+BW37*20% -> 9317.278
A38: =A37+1 -> 31 | B38: ,9 | C38: TANJAY1 | G38: 40 | H38: =SUM(F38*G38) -> 0 | I38: 22672 | J38: 50 | K38: =J38*I38 -> 1133600 | M38: 60 | N38: =M38*L38 -> 0 | O38: 11021 | P38: 12 | Q38: =O38*P38 -> 132252 | S38: 12 | T38: =R38*S38 -> 0 | U38: 992 | V38: 8 | W38: =U38*V38 -> 7936 | X38: 556 | Y38: 12 | Z38: =X38*Y38 -> 6672 | AA38: 1086 | AB38: 10 | AC38: =AA38*AB38 -> 10860 | AD38: 568 | AE38: 25 | AF38: =AD38*AE38 -> 14200 | AG38: 389 | AH38: 7.5 | AI38: =AG38*AH38 -> 2917.5 | AK38: 15 | AL38: =AJ38*AK38 -> 0 | AM38: 992 | AN38: 10 | AO38: =AM38*AX37 -> 2679392 | AP38: =R38+U38+X38+AA38+AD38+AG38+AM38 -> 4583 | AX38: 3121 | AZ38: =O38/(I38+F38+L38) -> 0.48610621 | BA38: =AP38/(I38+F38+L38) -> 0.20214361 | BB38: =AX38/O38 -> 0.28318664 | BC38: =H38+W38+Z38+AC38+AF38+T38+K38+N38 -> 1173268 | BD38: =H38+AF38+T38+K38+N38 -> 1147800 | BE38: =H38+W38+Z38+AC38+AF38+T38+K38+N38 -> 1173268 | BF38: =H38+W38+Z38+AC38+AF38+AI38+T38+K38+N38 -> 1176185.5 | BG38: 1370820.5 | BH38: 938743.63 | BI38: =+BH38/BG38% -> 68.48042 | BJ38: =SUM(BY38+BZ38+CA38+CB38) -> 82275 | BK38: =SUM(CF38+CG38+CH38+CI38) -> 0.060018799 | BL38: =B38 -> ,9 | BM38: =CC38 -> 105424.5 | BN38: =+BU38/BM38 -> 2.9586604 | BO38: =CD38 -> 0 | BP38: =+BU38/BO38 -> #DIV/0! | BQ38: =CE38 -> 30500 | BR38: =+BU38/BQ38 -> 10.226731 | BS38: =BU38-BM38-BO38-BQ38-BY38-BZ38-CA38-CB38 -> 93715.79 | BT38: =+BU38/BS38 -> 3.3283109 | BU38: 311915.29 | BV38: =+BU38/BG38% -> 22.753912 | BW38: =SUM(BG38-BH38-BU38) -> 120161.58 | BX38: =+BW38/BG38% -> 8.7656684 | BY38: 30102 | BZ38: 20683 | CA38: 24200 | CB38: 7290 | CC38: 105424.5 | CE38: 30500 | CF38: =BY38/BG38 -> 0.021959111 | CG38: =BZ38/BG38 -> 0.015088044 | CH38: =CA38/BG38 -> 0.017653661 | CI38: =CB38/BG38 -> 0.0053179829 | CJ38: =CC38/BG38 -> 0.07690613 | CK38: =+BW38*20% -> 24032.316
A39: =A38+1 -> 32 | B39: ,2 | C39: TANJAY2 | G39: 40 | H39: =SUM(F39*G39) -> 0 | I39: 3409 | J39: 50 | K39: =J39*I39 -> 170450 | M39: 60 | N39: =M39*L39 -> 0 | O39: 2357 | P39: 12 | Q39: =O39*P39 -> 28284 | R39: 740 | S39: 12 | T39: =R39*S39 -> 8880 | U39: 226 | V39: 8 | W39: =U39*V39 -> 1808 | X39: 139 | Y39: 12 | Z39: =X39*Y39 -> 1668 | AA39: 369 | AB39: 10 | AC39: =AA39*AB39 -> 3690 | AD39: 91 | AE39: 25 | AF39: =AD39*AE39 -> 2275 | AG39: 0 | AH39: 7.5 | AI39: =AG39*AH39 -> 0 | AK39: 15 | AL39: =AJ39*AK39 -> 0 | AM39: 129 | AN39: 10 | AO39: =AM39*AN39 -> 1290 | AP39: =R39+U39+X39+AA39+AD39+AG39+AM39 -> 1694 | AX39: =595+143+108+60 -> 906 | AZ39: =O39/(I39+F39+L39) -> 0.6914051 | BA39: =AP39/(I39+F39+L39) -> 0.49691992 | BB39: =AX39/O39 -> 0.38438693 | BC39: =H39+W39+Z39+AC39+AF39+T39+K39+N39 -> 188771 | BD39: =H39+AF39+T39+K39+N39 -> 181605 | BE39: =H39+W39+Z39+AC39+AF39+T39+K39+N39 -> 188771 | BF39: =H39+W39+Z39+AC39+AF39+AI39+T39+K39+N39 -> 188771 | BG39: 236012 | BH39: 159304.67 | BI39: =+BH39/BG39% -> 67.498547 | BJ39: =SUM(BY39+BZ39+CA39+CB39) -> 18574 | BK39: =SUM(CF39+CG39+CH39+CI39) -> 0.078699388 | BL39: =B39 -> ,2 | BM39: =CC39 -> 24456.5 | BN39: =+BU39/BM39 -> 3.4152765 | BO39: =CD39 -> 0 | BP39: =+BU39/BO39 -> #DIV/0! | BQ39: =CE39 -> 15000 | BR39: =+BU39/BQ39 -> 5.5683807 | BS39: =BU39-BM39-BO39-BQ39-BY39-BZ39-CA39-CB39 -> 25495.21 | BT39: =+BU39/BS39 -> 3.2761334 | BU39: 83525.71 | BV39: =+BU39/BG39% -> 35.39045 | BW39: =SUM(BG39-BH39-BU39) -> -6818.38 | BX39: =+BW39/BG39% -> -2.8889972 | BY39: 7563 | BZ39: 4773 | CA39: 4888 | CB39: 1350 | CC39: 24456.5 | CD39: 0 | CE39: 15000 | CF39: =BY39/BG39 -> 0.032044981 | CG39: =BZ39/BG39 -> 0.020223548 | CH39: =CA39/BG39 -> 0.020710811 | CI39: =CB39/BG39 -> 0.0057200481 | CJ39: =CC39/BG39 -> 0.10362397 | CK39: =+BW39*20% -> -1363.676
A40: =A39+1 -> 33 | B40: 3 | C40: TAYASAN | G40: 40 | H40: =SUM(F40*G40) -> 0 | I40: 9115 | J40: 50 | K40: =J40*I40 -> 455750 | M40: 60 | N40: =M40*L40 -> 0 | O40: 3108 | P40: 12 | Q40: =O40*P40 -> 37296 | R40: 1920 | S40: 12 | T40: =R40*S40 -> 23040 | U40: 598 | V40: 8 | W40: =U40*V40 -> 4784 | X40: 469 | Y40: 12 | Z40: =X40*Y40 -> 5628 | AA40: 826 | AB40: 10 | AC40: =AA40*AB40 -> 8260 | AD40: 350 | AE40: 25 | AF40: =AD40*AE40 -> 8750 | AG40: 0 | AH40: 7.5 | AI40: =AG40*AH40 -> 0 | AK40: 15 | AL40: =AJ40*AK40 -> 0 | AM40: 169 | AN40: 10 | AO40: =AM40*AN40 -> 1690 | AP40: =R40+U40+X40+AA40+AD40+AG40+AM40 -> 4332 | AX40: =982+152+69 -> 1203 | AZ40: =O40/(I40+F40+L40) -> 0.34097641 | BA40: =AP40/(I40+F40+L40) -> 0.47526056 | BB40: =AX40/O40 -> 0.38706564 | BC40: =H40+W40+Z40+AC40+AF40+T40+K40+N40 -> 506212 | BD40: =H40+AF40+T40+K40+N40 -> 487540 | BE40: =H40+W40+Z40+AC40+AF40+T40+K40+N40 -> 506212 | BF40: =H40+W40+Z40+AC40+AF40+AI40+T40+K40+N40 -> 506212 | BG40: 569147 | BH40: 380511.7 | BI40: =+BH40/BG40% -> 66.856489 | BJ40: =SUM(BY40+BZ40+CA40+CB40) -> 41708 | BK40: =SUM(CF40+CG40+CH40+CI40) -> 0.073281595 | BL40: 4 | BM40: =CC40 -> 39460.48 | BN40: =+BU40/BM40 -> 3.3897003 | BO40: =CD40 -> 1560.48 | BP40: =+BU40/BO40 -> 85.716703 | BQ40: =CE40 -> 16500 | BR40: =+BU40/BQ40 -> 8.1066182 | BS40: =BU40-BM40-BO40-BQ40-BY40-BZ40-CA40-CB40 -> 34530.24 | BT40: =+BU40/BS40 -> 3.8736829 | BU40: 133759.2 | BV40: =+BU40/BG40% -> 23.501696 | BW40: =SUM(BG40-BH40-BU40) -> 54876.1 | BX40: =+BW40/BG40% -> 9.6418149 | BY40: 15133 | BZ40: 11137 | CA40: 10848 | CB40: 4590 | CC40: 39460.48 | CD40: 1560.48 | CE40: 16500 | CF40: =BY40/BG40 -> 0.026588913 | CG40: =BZ40/BG40 -> 0.01956788 | CH40: =CA40/BG40 -> 0.019060102 | CI40: =CB40/BG40 -> 0.0080647003 | CJ40: =CC40/BG40 -> 0.069332668 | CK40: =+BW40*20% -> 10975.22
A41: =A40+1 -> 34 | B41: 2 | C41: TINAGO | G41: 40 | H41: =SUM(F41*G41) -> 0 | I41: 3803 | J41: 50 | K41: =J41*I41 -> 190150 | M41: 60 | N41: =M41*L41 -> 0 | O41: 3444 | P41: 12 | Q41: =O41*P41 -> 41328 | R41: 2885 | S41: 12 | T41: =R41*S41 -> 34620 | U41: 267 | V41: 8 | W41: =U41*V41 -> 2136 | X41: 110 | Y41: 12 | Z41: =X41*Y41 -> 1320 | AA41: 336 | AB41: 10 | AC41: =AA41*AB41 -> 3360 | AD41: 110 | AE41: 25 | AF41: =AD41*AE41 -> 2750 | AG41: 128 | AH41: 7.5 | AI41: =AG41*AH41 -> 960 | AK41: 15 | AL41: =AJ41*AK41 -> 0 | AM41: 159 | AN41: 10 | AO41: =AM41*AN41 -> 1590 | AP41: =R41+U41+X41+AA41+AD41+AG41+AM41 -> 3995 | AX41: =638+23+30+31 -> 722 | AZ41: =O41/(I41+F41+L41) -> 0.90560084 | BA41: =AP41/(I41+F41+L41) -> 1.0504865 | BB41: =AX41/O41 -> 0.20963995 | BC41: =H41+W41+Z41+AC41+AF41+T41+K41+N41 -> 234336 | BD41: =H41+AF41+T41+K41+N41 -> 227520 | BE41: =H41+W41+Z41+AC41+AF41+T41+K41+N41 -> 234336 | BF41: =H41+W41+Z41+AC41+AF41+AI41+T41+K41+N41 -> 235296 | BG41: 292650 | BH41: 98707.55 | BI41: =+BH41/BG41% -> 33.728874 | BJ41: =SUM(BY41+BZ41+CA41+CB41) -> 21598.5 | BK41: =SUM(CF41+CG41+CH41+CI41) -> 0.073803178 | BL41: =B41 -> 2 | BM41: =CC41 -> 29412.5 | BN41: =+BU41/BM41 -> 3.3165742 | BO41: =CD41 -> 1250 | BP41: =+BU41/BO41 -> 78.038992 | BQ41: =CE41 -> 20000 | BR41: =+BU41/BQ41 -> 4.877437 | BS41: =BU41-BM41-BO41-BQ41-BY41-BZ41-CA41-CB41 -> 25287.74 | BT41: =+BU41/BS41 -> 3.8575507 | BU41: 97548.74 | BV41: =+BU41/BG41% -> 33.332903 | BW41: =SUM(BG41-BH41-BU41) -> 96393.71 | BX41: =+BW41/BG41% -> 32.938223 | BY41: 11269.5 | BZ41: 4773 | CA41: 3936 | CB41: 1620 | CC41: 29412.5 | CD41: 1250 | CE41: 20000 | CF41: =BY41/BG41 -> 0.038508457 | CG41: =BZ41/BG41 -> 0.016309585 | CH41: =CA41/BG41 -> 0.013449513 | CI41: =CB41/BG41 -> 0.0055356228 | CJ41: =CC41/BG41 -> 0.10050402 | CK41: =+BW41*20% -> 19278.742
A42: =A41+1 -> 35 | B42: 6 | C42: ZAMBO | G42: 40 | H42: =SUM(F42*G42) -> 0 | I42: 16099 | J42: 50 | K42: =J42*I42 -> 804950 | M42: 60 | N42: =M42*L42 -> 0 | O42: 6781 | P42: 12 | Q42: =O42*P42 -> 81372 | R42: 0 | S42: 12 | T42: =R42*S42 -> 0 | U42: 780 | V42: 8 | W42: =U42*V42 -> 6240 | X42: 266 | Y42: 12 | Z42: =X42*Y42 -> 3192 | AA42: 856 | AB42: 10 | AC42: =AA42*AB42 -> 8560 | AD42: 327 | AE42: 25 | AF42: =AD42*AE42 -> 8175 | AG42: 265 | AH42: 7.5 | AI42: =AG42*AH42 -> 1987.5 | AK42: 15 | AL42: =AJ42*AK42 -> 0 | AM42: 300 | AN42: 10 | AO42: =AM42*AN42 -> 3000 | AP42: =R42+U42+X42+AA42+AD42+AG42+AM42 -> 2794 | AX42: =1432+299+834+260 -> 2825 | AZ42: =O42/(I42+F42+L42) -> 0.42120629 | BA42: =AP42/(I42+F42+L42) -> 0.17355115 | BB42: =AX42/O42 -> 0.41660522 | BC42: =H42+W42+Z42+AC42+AF42+T42+K42+N42 -> 831117 | BD42: =H42+AF42+T42+K42+N42 -> 813125 | BE42: =H42+W42+Z42+AC42+AF42+T42+K42+N42 -> 831117 | BF42: =H42+W42+Z42+AC42+AF42+AI42+T42+K42+N42 -> 833104.5 | BG42: 967219.5 | BH42: 651526.97 | BI42: =+BH42/BG42% -> 67.360818 | BJ42: =SUM(BY42+BZ42+CA42+CB42) -> 56658 | BK42: =SUM(CF42+CG42+CH42+CI42) -> 0.058578223 | BL42: =B42 -> 6 | BM42: =CC42 -> 68975 | BN42: =+BU42/BM42 -> 3.0488352 | BO42: =CD42 -> 0 | BP42: =+BU42/BO42 -> #DIV/0! | BQ42: =CE42 -> 10000 | BR42: =+BU42/BQ42 -> 21.029341 | BS42: =BU42-BM42-BO42-BQ42-BY42-BZ42-CA42-CB42 -> 74660.41 | BT42: =+BU42/BS42 -> 2.8166656 | BU42: 210293.41 | BV42: =+BU42/BG42% -> 21.742056 | BW42: =SUM(BG42-BH42-BU42) -> 105399.12 | BX42: =+BW42/BG42% -> 10.897125 | BY42: 15126 | BZ42: 19092 | CA42: 18120 | CB42: 4320 | CC42: 68975 | CD42: 0 | CE42: 10000 | CF42: =BY42/BG42 -> 0.015638643 | CG42: =BZ42/BG42 -> 0.019739056 | CH42: =CA42/BG42 -> 0.018734114 | CI42: =CB42/BG42 -> 0.0044664112 | CJ42: =CC42/BG42 -> 0.071312665 | CK42: =+BW42*20% -> 21079.824
A44: TOTAL MANPOWER | C44: TOTAL NUMBER OF PARTNER STORES | F44: TOTAL QUANTITY SOLD | BC44: TOTAL AMOUNT LPG | BD44: TOTAL AMOUNT BREADING MIX | BE44: TOTAL AMOUNT OIL | BF44: TOTAL AMOUNT SAUCE | BG44: TOTAL GROSS | BH44: TOTAL COGS | BU44: TOTAL OPEX | BW44: TOTAL NET | CK44: 20% ROYALTY SHARE
F45: CHICKEN PCS. | G45: UNIT PRICE | H45: TOTAL AMOUNT | I45: CHICKEN 50 (PCS) | J45: UNIT PRICE | K45: TOTAL AMOUNT | L45: J -CUT 60 (PCS) | M45: UNIT PRICE | N45: TOTAL AMOUNT | O45: RICE PCS. | P45: UNIT PRICE | Q45: TOTAL AMOUNT | R45: NECK(PCS) | S45: UNIT PRICE | T45: TOTAL AMOUNT | U45: LUMPIA PCS. | V45: UNIT PRICE | W45: TOTAL AMOUNT | X45: NGOHIONG PCS. | Y45: UNIT PRICE | Z45: TOTAL AMOUNT | AA45: BOLA2X PCS. | AB45: UNIT PRICE | AC45: TOTAL AMOUNT | AD45: C. FILLET PCS. | AE45: UNIT PRICE | AF45: TOTAL AMOUNT | AG45: SIOMAI PCS. | AH45: UNIT PRICE | AI45: TOTAL AMOUNT | AJ45: ATSARA( 15 ) | AK45: UNIT PRICE | AL45: TOTAL AMOUNT | AM45: ATSARA( 12 ) | AN45: UNIT PRICE | AO45: TOTAL AMOUNT | AP45: OTHER PRODUCTS(PCS) | AQ45: 1 LITER | AR45: PCS *4 | AS45: TOTAL PCS | AT45: 1.5 LITER | AU45: PCS *6 | AV45: TOTAL PCS | AW45: OTHER DRINKS SOLD | AX45: TOTAL QTY SOLD S.DRINKSPCS) | AY45: TOTAL AMOUNT | BL45: TOTAL EMPLOYEES
A46: =SUM(B8:B42) -> 148 | F46: =SUM(F8:F42) -> 0 | G46: 40 | H46: =F46*G46 -> 0 | I46: =SUM(I8:I42) -> 349303 | J46: 50 | K46: =J46*I46 -> 17465150 | L46: =SUM(L8:L42) -> 0 | M46: 60 | N46: =M46*L46 -> 0 | O46: =SUM(O8:O42) -> 181371 | P46: 12 | Q46: =O46*P46 -> 2176452 | R46: =SUM(R8:R42) -> 61724 | S46: 12 | T46: =R46*S46 -> 740688 | U46: =SUM(U8:U42) -> 28168 | V46: 8 | W46: =U46*V46 -> 225344 | X46: =SUM(X8:X42) -> 16110 | Y46: 12 | Z46: =X46*Y46 -> 193320 | AA46: =SUM(AA8:AA42) -> 32364 | AB46: 10 | AC46: =AA46*AB46 -> 323640 | AD46: =SUM(AD8:AD42) -> 9608 | AE46: 25 | AF46: =AD46*AE46 -> 240200 | AG46: =SUM(AG8:AG42) -> 11556 | AH46: 7.5 | AI46: =AG46*AH46 -> 86670 | AJ46: =SUM(AJ8:AJ42) -> 0 | AK46: 15 | AL46: =AJ46*AK46 -> 0 | AM46: =SUM(AM8:AM42) -> 7765 | AN46: 12 | AO46: =AM46*AN46 -> 93180 | AP46: =SUM(AM46,AG46,AD46,AA46,X46,U46,R46) -> 167295 | AQ46: =SUM(AQ8:AQ42) -> 0 | AR46: 4 | AS46: =SUM(AQ46*AR46) -> 0 | AT46: =SUM(AT8:AT42) -> 0 | AU46: 6 | AV46: =SUM(AT46*AU46) -> 0 | AW46: =SUM(AW8:AW42) -> 0 | AX46: =SUM(AS46+AV46+AW46) -> 0 | AY46: =SUM(AY8:AY42) -> 0 | BC46: =SUM(BC8:BC42) -> 19188342 | BD46: =SUM(BD8:BD42) -> 18446038 | BE46: =SUM(BE8:BE42) -> 19188342 | BF46: =SUM(BF8:BF42) -> 19275012 | BG46: =SUM(BG8:BG42) -> 22764699 | BH46: =SUM(BH8:BH42) -> 15218058 | BL46: =SUM(BL8:BL42) -> 149 | BU46: =SUM(BU8:BU45) -> 5723242.6 | BW46: =SUM(BW8:BW45) -> 1823398.6 | CK46: =SUM(CK8:CK42) -> 364679.73
BW47: =BW46*20% -> 364679.73 | BX47: 0.2

Sheet mar
A1: CRISPY KING FRANCHISE PERFORMANCE REPORT
A3: MONTH 2026 - AREA/REGION | BU3: CONSOLIDATED REPORT FOR THE MONTH OF JANUARY 2026
G5: DO NOT EDIT! | J5: DO NOT EDIT! | M5: DO NOT EDIT! | P5: DO NOT EDIT! | S5: DO NOT EDIT! | V5: DO NOT EDIT! | Y5: DO NOT EDIT! | AB5: DO NOT EDIT! | AE5: DO NOT EDIT! | AH5: DO NOT EDIT! | AK5: DO NOT EDIT! | AN5: DO NOT EDIT! | AR5: DO NOT EDIT! | AU5: DO NOT EDIT! | AX5: ! | AZ5: CAUTION! AUTO-FORMULA! DO NOT EDIT! | BI5: CAUTION! AUTO-FORMULA! DO NOT EDIT! | BV5: DO NOT EDIT! | CF5: CAUTION! AUTO-FORMULA! DO NOT EDIT!
A6: GROSS RANK | B6: MAN POWER | C6: BRANCH | D6: OWNER | E6: SALES SUPERVISOR | F6: QUANTITY SOLD | I6: S-CUT | L6: J-CUT | O6: RICE | R6: NECK(PCS) | U6: LUMPIA | X6: NGOHIONG | AA6: BOLA2X | AD6: C-FILLET | AG6: SIOMAI | AJ6: ATSARA (15) | AM6: ATSARA (12) | AP6: TOTAL OTHER PRODUCT | AW6: OTHER DRINKS SOLD | AX6: TOTAL QTY SOLD S.DRINKSPCS) | AZ6: CHICKEN VS RICE (50%) | BA6: CHICKEN VS OTHER PRODUCTS (20%) | BB6: RICE VS DRINKS (40%) | BC6: TOTAL AMOUNT FOR LPG % | BD6: TOTAL AMOUNT FOR BREADING% | BE6: TOTAL AMOUNT FOR OIL % | BF6: TOTAL AMOUNT FOR SAUCE % | BG6: TOTAL GROSS SALES | BH6: COST OF GOODS SOLD | BI6: COGS (%) | BJ6: TOTAL AMOUNT USAGES | BK6: USAGES (%) | BL6: MAN POWER | BM6: SALARY | BN6: SALARY (%) | BO6: OVERTIME | BP6: OVERTIME (%) | BQ6: RENT | BR6: RENT (%) | BS6: OPERATIONAL EXPENSES | BT6: OPERATION (%) | BU6: TOTAL OPEX | BV6: OPEX (%) | BW6: NET INCOME | BX6: NET (%) | BY6: NON - SALES ITEM | CK6: 20% ROYALTY SHARE | CL6: 80% SHARE
F7: CHICKEN 40(PCS) | G7: UNIT PRICE | H7: TOTAL AMOUNT | I7: QNTY | J7: UNIT PRICE | K7: TOTAL AMOUNT | L7: J -CUT 60 (PCS) | M7: UNIT PRICE | N7: TOTAL AMOUNT | O7: RICE(PCS) | P7: UNIT PRICE | Q7: TOTAL AMOUNT | R7: NECK(PCS) | S7: UNIT PRICE | T7: TOTAL AMOUNT | U7: LUMPIA(PCS) | V7: UNIT PRICE | W7: TOTAL AMOUNT | X7: NGOHIONG(PCS) | Y7: UNIT PRICE | Z7: TOTAL AMOUNT | AA7: BOLA2X(PCS) | AB7: UNIT PRICE | AC7: TOTAL AMOUNT | AD7: C. FILLET(PCS) | AE7: UNIT PRICE | AF7: TOTAL AMOUNT | AG7: SIOMAI(PCS) | AH7: UNIT PRICE | AI7: TOTAL AMOUNT | AJ7: ATSARA( 15 ) | AK7: UNIT PRICE | AL7: TOTAL AMOUNT | AM7: ATSARA( 12 ) | AN7: UNIT PRICE | AO7: TOTAL AMOUNT | AQ7: 1 LITER | AR7: PCS *4 | AS7: TOTAL PCS | AT7: 1.5 LITER | AU7: PCS * 6 | AV7: TOTAL PCS | AY7: TOTAL AMOUNT | BY7: LPG | BZ7: BREADING | CA7: OIL | CB7: SAUCE | CC7: SALARY | CD7: OVERTIME | CE7: RENT | CF7: LPG | CG7: BREADING | CH7: OIL | CI7: SAUCE | CJ7: SALARY
A9: 1 | B9: 9 | C9: LOCSIN | G9: 40 | H9: =SUM(F9*G9) -> 0 | I9: 23847 | J9: 50 | K9: =J9*I9 -> 1192350 | M9: 60 | N9: =M9*L9 -> 0 | O9: 22769 | P9: 12 | Q9: =O9*P9 -> 273228 | S9: 12 | T9: =R9*S9 -> 0 | U9: 4180 | V9: 8 | W9: =U9*V9 -> 33440 | X9: 822 | Y9: 12 | Z9: =X9*Y9 -> 9864 | AA9: 2701 | AB9: 10 | AC9: =AA9*AB9 -> 27010 | AD9: 1290 | AE9: 25 | AF9: =AD9*AE9 -> 32250 | AG9: 853 | AH9: 7.5 | AI9: =AG9*AH9 -> 6397.5 | AK9: 15 | AL9: =AJ9*AK9 -> 0 | AM9: 838 | AN9: 10 | AO9: =AM9*AN9 -> 8380 | AP9: =R9+U9+X9+AA9+AD9+AG9+AM9 -> 10684 | AX9: 8809 | AZ9: =O9/(I9+F9+L9) -> 0.95479515 | BA9: =AP9/(I9+F9+L9) -> 0.44802281 | BB9: =AX9/O9 -> 0.38688568 | BC9: =H9+W9+Z9+AC9+AF9+T9+K9+N9 -> 1294914 | BD9: =H9+AF9+T9+K9+N9 -> 1224600 | BE9: =H9+W9+Z9+AC9+AF9+T9+K9+N9 -> 1294914 | BF9: =H9+W9+Z9+AC9+AF9+AI9+T9+K9+N9 -> 1301311.5 | BG9: 1752146.5 | BH9: 1181854.8 | BI9: =+BH9/BG9% -> 67.451824 | BJ9: =SUM(BY9+BZ9+CA9+CB9) -> 87912.5 | BK9: =SUM(CF9+CG9+CH9+CI9) -> 0.050174172 | BL9: =B9 -> 9 | BM9: =CC9 -> 115100 | BN9: =+BU9/BM9 -> 3.0981098 | BO9: =CD9 -> 312.5 | BP9: =+BU9/BO9 -> 1141.0958 | BQ9: =CE9 -> 66150 | BR9: =+BU9/BQ9 -> 5.3906642 | BS9: =BU9-BM9-BO9-BQ9-BY9-BZ9-CA9-CB9 -> 87117.44 | BT9: =+BU9/BS9 -> 4.0932383 | BU9: 356592.44 | BV9: =+BU9/BG9% -> 20.351748 | BW9: =SUM(BG9-BH9-BU9) -> 213699.28 | BX9: =+BW9/BG9% -> 12.196428 | BY9: 26582.5 | BZ9: 22274 | CA9: 32036 | CB9: 7020 | CC9: 115100 | CD9: 312.5 | CE9: 66150 | CF9: =BY9/BG9 -> 0.015171391 | CG9: =BZ9/BG9 -> 0.012712407 | CH9: =CA9/BG9 -> 0.018283859 | CI9: =CB9/BG9 -> 0.0040065143 | CJ9: =CC9/BG9 -> 0.065690854 | CK9: =+BW9*20% -> 42739.856 | CL9: =BW9*80% -> 170959.42
A10: =A9+1 -> 2 | B10: 7 | C10: SAGAY1 | G10: 40 | H10: =SUM(F10*G10) -> 0 | I10: 28729 | J10: 50 | K10: =J10*I10 -> 1436450 | M10: 60 | N10: =M10*L10 -> 0 | O10: 9953 | P10: 12 | Q10: =O10*P10 -> 119436 | R10: 1240 | S10: 12 | T10: =R10*S10 -> 14880 | U10: 1187 | V10: 8 | W10: =U10*V10 -> 9496 | X10: 746 | Y10: 12 | Z10: =X10*Y10 -> 8952 | AA10: 1523 | AB10: 10 | AC10: =AA10*AB10 -> 15230 | AD10: 439 | AE10: 25 | AF10: =AD10*AE10 -> 10975 | AG10: 239 | AH10: 7.5 | AI10: =AG10*AH10 -> 1792.5 | AK10: 15 | AL10: =AJ10*AK10 -> 0 | AM10: 411 | AN10: 12 | AO10: =AM10*AN10 -> 4932 | AP10: =R10+U10+X10+AA10+AD10+AG10+AM10 -> 5785 | AX10: 5103 | AZ10: =O10/(I10+F10+L10) -> 0.34644436 | BA10: =AP10/(I10+F10+L10) -> 0.20136447 | BB10: =AX10/O10 -> 0.51270974 | BC10: =H10+W10+Z10+AC10+AF10+T10+K10+N10 -> 1495983 | BD10: =H10+AF10+T10+K10+N10 -> 1462305 | BE10: =H10+W10+Z10+AC10+AF10+T10+K10+N10 -> 1495983 | BF10: =H10+W10+Z10+AC10+AF10+AI10+T10+K10+N10 -> 1497775.5 | BG10: 1697110.5 | BH10: 1138762.5 | BI10: =+BH10/BG10% -> 67.100081 | BJ10: =SUM(BY10+BZ10+CA10+CB10) -> 113669 | BK10: =SUM(CF10+CG10+CH10+CI10) -> 0.06697796 | BL10: =B10 -> 7 | BM10: =CC10 -> 87418 | BN10: =+BU10/BM10 -> 3.7937673 | BO10: =CD10 -> 2295.25 | BP10: =+BU10/BO10 -> 144.49125 | BQ10: =CE10 -> 20000 | BR10: =+BU10/BQ10 -> 16.582178 | BS10: =BU10-BM10-BO10-BQ10-BY10-BZ10-CA10-CB10 -> 108261.3 | BT10: =+BU10/BS10 -> 3.063362 | BU10: 331643.55 | BV10: =+BU10/BG10% -> 19.541659 | BW10: =SUM(BG10-BH10-BU10) -> 226704.43 | BX10: =+BW10/BG10% -> 13.35826 | BY10: 43168 | BZ10: 31140 | CA10: 32321 | CB10: 7040 | CC10: 87418 | CD10: 2295.25 | CE10: 20000 | CF10: =BY10/BG10 -> 0.025436175 | CG10: =BZ10/BG10 -> 0.018348835 | CH10: =CA10/BG10 -> 0.019044723 | CI10: =CB10/BG10 -> 0.0041482272 | CJ10: =CC10/BG10 -> 0.051509905 | CK10: =+BW10*20% -> 45340.886 | CL10: =BW10*80% -> 181363.54
A11: =A10+1 -> 3 | B11: 9 | C11: NOPH | G11: 40 | H11: =SUM(F11*G11) -> 0 | I11: 23022 | J11: 50 | K11: =J11*I11 -> 1151100 | M11: 60 | N11: =M11*L11 -> 0 | O11: 21366 | P11: 12 | Q11: =O11*P11 -> 256392 | S11: 12 | T11: =R11*S11 -> 0 | U11: 3027 | V11: 8 | W11: =U11*V11 -> 24216 | X11: 1323 | Y11: 12 | Z11: =X11*Y11 -> 15876 | AA11: 2568 | AB11: 10 | AC11: =AA11*AB11 -> 25680 | AD11: 710 | AE11: 25 | AF11: =AD11*AE11 -> 17750 | AG11: 849 | AH11: 7.5 | AI11: =AG11*AH11 -> 6367.5 | AK11: 15 | AL11: =AJ11*AK11 -> 0 | AM11: 631 | AN11: 10 | AO11: =AM11*AN11 -> 6310 | AP11: =R11+U11+X11+AA11+AD11+AG11+AM11 -> 9108 | AX11: 5243 | AZ11: =O11/(I11+F11+L11) -> 0.9280688 | BA11: =AP11/(I11+F11+L11) -> 0.39562158 | BB11: =AX11/O11 -> 0.24538987 | BC11: =H11+W11+Z11+AC11+AF11+T11+K11+N11 -> 1234622 | BD11: =H11+AF11+T11+K11+N11 -> 1168850 | BE11: =H11+W11+Z11+AC11+AF11+T11+K11+N11 -> 1234622 | BF11: =H11+W11+Z11+AC11+AF11+AI11+T11+K11+N11 -> 1240989.5 | BG11: 1607727.5 | BH11: 1093163.1 | BI11: =+BH11/BG11% -> 67.9943 | BJ11: =SUM(BY11+BZ11+CA11+CB11) -> 83227 | BK11: =SUM(CF11+CG11+CH11+CI11) -> 0.051766857 | BL11: =B11 -> 9 | BM11: =CC11 -> 102062.5 | BN11: =+BU11/BM11 -> 2.9005997 | BO11: =CD11 -> 0 | BP11: =+BU11/BO11 -> #DIV/0! | BQ11: =CE11 -> 38217.86 | BR11: =+BU11/BQ11 -> 7.746181 | BS11: =BU11-BM11-BO11-BQ11-BY11-BZ11-CA11-CB11 -> 72535.1 | BT11: =+BU11/BS11 -> 4.0813683 | BU11: 296042.46 | BV11: =+BU11/BG11% -> 18.413721 | BW11: =SUM(BG11-BH11-BU11) -> 218521.98 | BX11: =+BW11/BG11% -> 13.591979 | BY11: 23361 | BZ11: 22274 | CA11: 31382 | CB11: 6210 | CC11: 102062.5 | CE11: 38217.86 | CF11: =BY11/BG11 -> 0.014530447 | CG11: =BZ11/BG11 -> 0.013854338 | CH11: =CA11/BG11 -> 0.019519477 | CI11: =CB11/BG11 -> 0.0038625949 | CJ11: =CC11/BG11 -> 0.063482462 | CK11: =+BW11*20% -> 43704.396 | CL11: =BW11*80% -> 174817.58
A12: =A11+1 -> 4 | B12: ,9 | C12: TANJAY1 | G12: 40 | H12: =SUM(F12*G12) -> 0 | I12: 23663 | J12: 50 | K12: =J12*I12 -> 1183150 | M12: 60 | N12: =M12*L12 -> 0 | O12: 11689 | P12: 12 | Q12: =O12*P12 -> 140268 | S12: 12 | T12: =R12*S12 -> 0 | U12: 1170 | V12: 8 | W12: =U12*V12 -> 9360 | X12: 555 | Y12: 12 | Z12: =X12*Y12 -> 6660 | AA12: 1175 | AB12: 10 | AC12: =AA12*AB12 -> 11750 | AD12: 612 | AE12: 25 | AF12: =AD12*AE12 -> 15300 | AG12: 211 | AH12: 7.5 | AI12: =AG12*AH12 -> 1582.5 | AK12: 15 | AL12: =AJ12*AK12 -> 0 | AM12: 437 | AN12: 10 | AO12: =AM12*AX11 -> 2291191 | AP12: =R12+U12+X12+AA12+AD12+AG12+AM12 -> 4160 | AX12: 3375 | AZ12: =O12/(I12+F12+L12) -> 0.49397794 | BA12: =AP12/(I12+F12+L12) -> 0.17580188 | BB12: =AX12/O12 -> 0.288733 | BC12: =H12+W12+Z12+AC12+AF12+T12+K12+N12 -> 1226220 | BD12: =H12+AF12+T12+K12+N12 -> 1198450 | BE12: =H12+W12+Z12+AC12+AF12+T12+K12+N12 -> 1226220 | BF12: =H12+W12+Z12+AC12+AF12+AI12+T12+K12+N12 -> 1227802.5 | BG12: 1437574.5 | BH12: 983971.04 | BI12: =+BH12/BG12% -> 68.446612 | BJ12: =SUM(BY12+BZ12+CA12+CB12) -> 89568 | BK12: =SUM(CF12+CG12+CH12+CI12) -> 0.062304945 | BL12: =B12 -> ,9 | BM12: =CC12 -> 108475 | BN12: =+BU12/BM12 -> 2.6821105 | BO12: =CD12 -> 862.5 | BP12: =+BU12/BO12 -> 337.32399 | BQ12: =CE12 -> 30500 | BR12: =+BU12/BQ12 -> 9.53908 | BS12: =BU12-BM12-BO12-BQ12-BY12-BZ12-CA12-CB12 -> 61536.44 | BT12: =+BU12/BS12 -> 4.7279618 | BU12: 290941.94 | BV12: =+BU12/BG12% -> 20.23839 | BW12: =SUM(BG12-BH12-BU12) -> 162661.52 | BX12: =+BW12/BG12% -> 11.314998 | BY12: 30476 | BZ12: 22274 | CA12: 28718 | CB12: 8100 | CC12: 108475 | CD12: 862.5 | CE12: 30500 | CF12: =BY12/BG12 -> 0.021199597 | CG12: =BZ12/BG12 -> 0.015494154 | CH12: =CA12/BG12 -> 0.019976704 | CI12: =CB12/BG12 -> 0.0056344906 | CJ12: =CC12/BG12 -> 0.075456959 | CK12: =+BW12*20% -> 32532.304 | CL12: =BW12*80% -> 130129.22
A13: =A12+1 -> 5 | B13: 7 | C13: BINDOY1 | G13: 40 | H13: =SUM(F13*G13) -> 0 | I13: 18542 | J13: 50 | K13: =J13*I13 -> 927100 | M13: 60 | N13: =M13*L13 -> 0 | O13: 6067 | P13: 12 | Q13: =O13*P13 -> 72804 | S13: 12 | T13: =R13*S13 -> 0 | U13: 1085 | V13: 8 | W13: =U13*V13 -> 8680 | X13: 441 | Y13: 12 | Z13: =X13*Y13 -> 5292 | AA13: 1176 | AB13: 10 | AC13: =AA13*AB13 -> 11760 | AD13: 415 | AE13: 25 | AF13: =AD13*AE13 -> 10375 | AG13: 296 | AH13: 7.5 | AI13: =AG13*AH13 -> 2220 | AK13: 15 | AL13: =AJ13*AK13 -> 0 | AM13: 367 | AN13: 10 | AO13: =AM13*AN13 -> 3670 | AP13: =R13+U13+X13+AA13+AD13+AG13+AM13 -> 3780 | AX13: 2360 | AZ13: =O13/(I13+F13+L13) -> 0.32720311 | BA13: =AP13/(I13+F13+L13) -> 0.2038615 | BB13: =AX13/O13 -> 0.38898962 | BC13: =H13+W13+Z13+AC13+AF13+T13+K13+N13 -> 963207 | BD13: =H13+AF13+T13+K13+N13 -> 937475 | BE13: =H13+W13+Z13+AC13+AF13+T13+K13+N13 -> 963207 | BF13: =H13+W13+Z13+AC13+AF13+AI13+T13+K13+N13 -> 965427 | BG13: 1085109 | BH13: 734897.5 | BI13: =+BH13/BG13% -> 67.725685 | BJ13: =SUM(BY13+BZ13+CA13+CB13) -> 71947 | BK13: =SUM(CF13+CG13+CH13+CI13) -> 0.066303938 | BL13: =B13 -> 7 | BM13: =CC13 -> 72875 | BN13: =+BU13/BM13 -> 2.8483779 | BO13: =CD13 -> 0 | BP13: =+BU13/BO13 -> #DIV/0! | BQ13: =CE13 -> 14500 | BR13: =+BU13/BQ13 -> 14.315554 | BS13: =BU13-BM13-BO13-BQ13-BY13-BZ13-CA13-CB13 -> 48253.54 | BT13: =+BU13/BS13 -> 4.3017681 | BU13: 207575.54 | BV13: =+BU13/BG13% -> 19.129464 | BW13: =SUM(BG13-BH13-BU13) -> 142635.96 | BX13: =+BW13/BG13% -> 13.144851 | BY13: 23364 | BZ13: 17501 | CA13: 25142 | CB13: 5940 | CC13: 72875 | CE13: 14500 | CF13: =BY13/BG13 -> 0.021531477 | CG13: =BZ13/BG13 -> 0.016128334 | CH13: =CA13/BG13 -> 0.023170023 | CI13: =CB13/BG13 -> 0.0054741044 | CJ13: =CC13/BG13 -> 0.067159152 | CK13: =+BW13*20% -> 28527.192 | CL13: =BW13*80% -> 114108.77
A14: =A13+1 -> 6 | B14: 6 | C14: MANJUYOD | G14: 40 | H14: =SUM(F14*G14) -> 0 | I14: 17087 | J14: 50 | K14: =J14*I14 -> 854350 | M14: 60 | N14: =M14*L14 -> 0 | O14: 8581 | P14: 12 | Q14: =O14*P14 -> 102972 | R14: 744 | S14: 12 | T14: =R14*S14 -> 8928 | U14: 1087 | V14: 8 | W14: =U14*V14 -> 8696 | X14: 376 | Y14: 12 | Z14: =X14*Y14 -> 4512 | AA14: 1322 | AB14: 10 | AC14: =AA14*AB14 -> 13220 | AD14: 308 | AE14: 25 | AF14: =AD14*AE14 -> 7700 | AG14: 279 | AH14: 7.5 | AI14: =AG14*AH14 -> 2092.5 | AK14: 15 | AL14: =AJ14*AK14 -> 0 | AM14: 302 | AN14: 10 | AO14: =AM14*AN14 -> 3020 | AP14: =R14+U14+X14+AA14+AD14+AG14+AM14 -> 4418 | AX14: 2834 | AZ14: =O14/(I14+F14+L14) -> 0.50219465 | BA14: =AP14/(I14+F14+L14) -> 0.25855914 | BB14: =AX14/O14 -> 0.33026454 | BC14: =H14+W14+Z14+AC14+AF14+T14+K14+N14 -> 897406 | BD14: =H14+AF14+T14+K14+N14 -> 870978 | BE14: =H14+W14+Z14+AC14+AF14+T14+K14+N14 -> 897406 | BF14: =H14+W14+Z14+AC14+AF14+AI14+T14+K14+N14 -> 899498.5 | BG14: 1063329.5 | BH14: 727550.14 | BI14: =+BH14/BG14% -> 68.42189 | BJ14: =SUM(BY14+BZ14+CA14+CB14) -> 66471 | BK14: =SUM(CF14+CG14+CH14+CI14) -> 0.062512138 | BL14: =B14 -> 6 | BM14: =CC14 -> 72512.5 | BN14: =+BU14/BM14 -> 2.8725071 | BO14: =CD14 -> 0 | BP14: =+BU14/BO14 -> #DIV/0! | BQ14: =CE14 -> 25000 | BR14: =+BU14/BQ14 -> 8.3317068 | BS14: =BU14-BM14-BO14-BQ14-BY14-BZ14-CA14-CB14 -> 44309.17 | BT14: =+BU14/BS14 -> 4.7008931 | BU14: 208292.67 | BV14: =+BU14/BG14% -> 19.588723 | BW14: =SUM(BG14-BH14-BU14) -> 127486.69 | BX14: =+BW14/BG14% -> 11.989387 | BY14: 23130 | BZ14: 17501 | CA14: 20170 | CB14: 5670 | CC14: 72512.5 | CE14: 25000 | CF14: =BY14/BG14 -> 0.02175243 | CG14: =BZ14/BG14 -> 0.01645868 | CH14: =CA14/BG14 -> 0.01896872 | CI14: =CB14/BG14 -> 0.0053323076 | CJ14: =CC14/BG14 -> 0.06819382 | CK14: =+BW14*20% -> 25497.338 | CL14: =BW14*80% -> 101989.35
A15: =A14+1 -> 7 | B15: 6 | C15: ZAMBO | G15: 40 | H15: =SUM(F15*G15) -> 0 | I15: 16800 | J15: 50 | K15: =J15*I15 -> 840000 | M15: 60 | N15: =M15*L15 -> 0 | O15: 5351 | P15: 12 | Q15: =O15*P15 -> 64212 | S15: 12 | T15: =R15*S15 -> 0 | U15: 680 | V15: 8 | W15: =U15*V15 -> 5440 | X15: 228 | Y15: 12 | Z15: =X15*Y15 -> 2736 | AA15: 783 | AB15: 10 | AC15: =AA15*AB15 -> 7830 | AD15: 278 | AE15: 25 | AF15: =AD15*AE15 -> 6950 | AG15: 315 | AH15: 7.5 | AI15: =AG15*AH15 -> 2362.5 | AK15: 15 | AL15: =AJ15*AK15 -> 0 | AM15: 301 | AN15: 10 | AO15: =AM15*AN15 -> 3010 | AP15: =R15+U15+X15+AA15+AD15+AG15+AM15 -> 2585 | AX15: 2219 | AZ15: =O15/(I15+F15+L15) -> 0.3185119 | BA15: =AP15/(I15+F15+L15) -> 0.15386905 | BB15: =AX15/O15 -> 0.41468884 | BC15: =H15+W15+Z15+AC15+AF15+T15+K15+N15 -> 862956 | BD15: =H15+AF15+T15+K15+N15 -> 846950 | BE15: =H15+W15+Z15+AC15+AF15+T15+K15+N15 -> 862956 | BF15: =H15+W15+Z15+AC15+AF15+AI15+T15+K15+N15 -> 865318.5 | BG15: 971924.5 | BH15: 661250.58 | BI15: =+BH15/BG15% -> 68.03518 | BJ15: =SUM(BY15+BZ15+CA15+CB15) -> 67807.7 | BK15: =SUM(CF15+CG15+CH15+CI15) -> 0.069766427 | BL15: =B15 -> 6 | BM15: =CC15 -> 72625 | BN15: =+BU15/BM15 -> 2.798121 | BO15: =CD15 -> 625 | BP15: =+BU15/BO15 -> 325.14166 | BQ15: =CE15 -> 10000 | BR15: =+BU15/BQ15 -> 20.321354 | BS15: =BU15-BM15-BO15-BQ15-BY15-BZ15-CA15-CB15 -> 52155.84 | BT15: =+BU15/BS15 -> 3.8962759 | BU15: 203213.54 | BV15: =+BU15/BG15% -> 20.908367 | BW15: =SUM(BG15-BH15-BU15) -> 107460.38 | BX15: =+BW15/BG15% -> 11.056453 | BY15: 24200.7 | BZ15: 20683 | CA15: 18874 | CB15: 4050 | CC15: 72625 | CD15: 625 | CE15: 10000 | CF15: =BY15/BG15 -> 0.024899774 | CG15: =BZ15/BG15 -> 0.02128046 | CH15: =CA15/BG15 -> 0.019419204 | CI15: =CB15/BG15 -> 0.0041669903 | CJ15: =CC15/BG15 -> 0.074722882 | CK15: =+BW15*20% -> 21492.076 | CL15: =BW15*80% -> 85968.304
A16: =A15+1 -> 8 | B16: 6 | C16: MABINAY1 | G16: 40 | H16: =SUM(F16*G16) -> 0 | I16: 15050 | J16: 50 | K16: =J16*I16 -> 752500 | M16: 60 | N16: =M16*L16 -> 0 | O16: 6002 | P16: 12 | Q16: =O16*P16 -> 72024 | S16: 12 | T16: =R16*S16 -> 0 | U16: 759 | V16: 8 | W16: =U16*V16 -> 6072 | X16: 582 | Y16: 12 | Z16: =X16*Y16 -> 6984 | AA16: 1357 | AB16: 10 | AC16: =AA16*AB16 -> 13570 | AD16: 172 | AE16: 25 | AF16: =AD16*AE16 -> 4300 | AG16: 408 | AH16: 7.5 | AI16: =AG16*AH16 -> 3060 | AK16: 15 | AL16: =AJ16*AK16 -> 0 | AN16: 10 | AO16: =AM16*AN16 -> 0 | AP16: =R16+U16+X16+AA16+AD16+AG16+AM16 -> 3278 | AX16: 3311 | AZ16: =O16/(I16+F16+L16) -> 0.39880399 | BA16: =AP16/(I16+F16+L16) -> 0.21780731 | BB16: =AX16/O16 -> 0.55164945 | BC16: =H16+W16+Z16+AC16+AF16+T16+K16+N16 -> 783426 | BD16: =H16+AF16+T16+K16+N16 -> 756800 | BE16: =H16+W16+Z16+AC16+AF16+T16+K16+N16 -> 783426 | BF16: =H16+W16+Z16+AC16+AF16+AI16+T16+K16+N16 -> 786486 | BG16: 922653 | BH16: 614717.25 | BI16: =+BH16/BG16% -> 66.624966 | BJ16: =SUM(BY16+BZ16+CA16+CB16) -> 72731.5 | BK16: =SUM(CF16+CG16+CH16+CI16) -> 0.07882866 | BL16: =B16 -> 6 | BM16: =CC16 -> 71912.5 | BN16: =+BU16/BM16 -> 3.2147952 | BO16: =CD16 -> 0 | BP16: =+BU16/BO16 -> #DIV/0! | BQ16: =CE16 -> 26250 | BR16: =+BU16/BQ16 -> 8.807008 | BS16: =BU16-BM16-BO16-BQ16-BY16-BZ16-CA16-CB16 -> 60289.96 | BT16: =+BU16/BS16 -> 3.834535 | BU16: 231183.96 | BV16: =+BU16/BG16% -> 25.056436 | BW16: =SUM(BG16-BH16-BU16) -> 76751.79 | BX16: =+BW16/BG16% -> 8.3185976 | BY16: 27982.5 | BZ16: 15910 | CA16: 21819 | CB16: 7020 | CC16: 71912.5 | CE16: 26250 | CF16: =BY16/BG16 -> 0.030328303 | CG16: =BZ16/BG16 -> 0.017243753 | CH16: =CA16/BG16 -> 0.02364811 | CI16: =CB16/BG16 -> 0.0076084942 | CJ16: =CC16/BG16 -> 0.077941003 | CK16: =+BW16*20% -> 15350.358 | CL16: =BW16*80% -> 61401.432
A17: =A16+1 -> 9 | B17: 6 | C17: DARO | G17: 40 | H17: =SUM(F17*G17) -> 0 | I17: 13367 | J17: 50 | K17: =J17*I17 -> 668350 | M17: 60 | N17: =M17*L17 -> 0 | O17: 10054 | P17: 12 | Q17: =O17*P17 -> 120648 | S17: 12 | T17: =R17*S17 -> 0 | U17: 1219 | V17: 8 | W17: =U17*V17 -> 9752 | X17: 682 | Y17: 12 | Z17: =X17*Y17 -> 8184 | AA17: 1046 | AB17: 10 | AC17: =AA17*AB17 -> 10460 | AD17: 454 | AE17: 25 | AF17: =AD17*AE17 -> 11350 | AG17: 801 | AH17: 7.5 | AI17: =AG17*AH17 -> 6007.5 | AK17: 15 | AL17: =AJ17*AK17 -> 0 | AM17: 510 | AN17: 10 | AO17: =AM17*AN17 -> 5100 | AP17: =R17+U17+X17+AA17+AD17+AG17+AM17 -> 4712 | AX17: 2050 | AZ17: =O17/(I17+F17+L17) -> 0.75215082 | BA17: =AP17/(I17+F17+L17) -> 0.35250991 | BB17: =AX17/O17 -> 0.20389895 | BC17: =H17+W17+Z17+AC17+AF17+T17+K17+N17 -> 708096 | BD17: =H17+AF17+T17+K17+N17 -> 679700 | BE17: =H17+W17+Z17+AC17+AF17+T17+K17+N17 -> 708096 | BF17: =H17+W17+Z17+AC17+AF17+AI17+T17+K17+N17 -> 714103.5 | BG17: 880472.5 | BH17: 600584.21 | BI17: =+BH17/BG17% -> 68.211581 | BJ17: =SUM(BY17+BZ17+CA17+CB17) -> 53143 | BK17: =SUM(CF17+CG17+CH17+CI17) -> 0.060357365 | BL17: =B17 -> 6 | BM17: =CC17 -> 71462.5 | BN17: =+BU17/BM17 -> 2.7488298 | BO17: =CD17 -> 437.5 | BP17: =+BU17/BO17 -> 449.00171 | BQ17: =CE17 -> 22050 | BR17: =+BU17/BQ17 -> 8.9087642 | BS17: =BU17-BM17-BO17-BQ17-BY17-BZ17-CA17-CB17 -> 49345.25 | BT17: =+BU17/BS17 -> 3.9808948 | BU17: 196438.25 | BV17: =+BU17/BG17% -> 22.310549 | BW17: =SUM(BG17-BH17-BU17) -> 83450.04 | BX17: =+BW17/BG17% -> 9.4778701 | BY17: 19091.5 | BZ17: 12728 | CA17: 18083.5 | CB17: 3240 | CC17: 71462.5 | CD17: 437.5 | CE17: 22050 | CF17: =BY17/BG17 -> 0.021683244 | CG17: =BZ17/BG17 -> 0.014455875 | CH17: =CA17/BG17 -> 0.020538404 | CI17: =CB17/BG17 -> 0.0036798424 | CJ17: =CC17/BG17 -> 0.081163807 | CK17: =+BW17*20% -> 16690.008 | CL17: =BW17*80% -> 66760.032
A18: =A17+1 -> 10 | B18: 5 | C18: PAMPLONA | G18: 40 | H18: =SUM(F18*G18) -> 0 | I18: 11902 | J18: 50 | K18: =J18*I18 -> 595100 | M18: 60 | N18: =M18*L18 -> 0 | O18: 4510 | P18: 12 | Q18: =O18*P18 -> 54120 | R18: 2310 | S18: 12 | T18: =R18*S18 -> 27720 | U18: 1141 | V18: 8 | W18: =U18*V18 -> 9128 | X18: 331 | Y18: 12 | Z18: =X18*Y18 -> 3972 | AA18: 970 | AB18: 10 | AC18: =AA18*AB18 -> 9700 | AD18: 153 | AE18: 25 | AF18: =AD18*AE18 -> 3825 | AG18: 144 | AH18: 7.5 | AI18: =AG18*AH18 -> 1080 | AK18: 15 | AL18: =AJ18*AK18 -> 0 | AM18: 180 | AN18: 10 | AO18: =AM18*AN18 -> 1800 | AP18: =R18+U18+X18+AA18+AD18+AG18+AM18 -> 5229 | AX18: 3031 | AZ18: =O18/(I18+F18+L18) -> 0.37892791 | BA18: =AP18/(I18+F18+L18) -> 0.43933793 | BB18: =AX18/O18 -> 0.67206208 | BC18: =H18+W18+Z18+AC18+AF18+T18+K18+N18 -> 649445 | BD18: =H18+AF18+T18+K18+N18 -> 626645 | BE18: =H18+W18+Z18+AC18+AF18+T18+K18+N18 -> 649445 | BF18: =H18+W18+Z18+AC18+AF18+AI18+T18+K18+N18 -> 650525 | BG18: 766539 | BH18: 512978.52 | BI18: =+BH18/BG18% -> 66.921386 | BJ18: =SUM(BY18+BZ18+CA18+CB18) -> 53511.5 | BK18: =SUM(CF18+CG18+CH18+CI18) -> 0.069809233 | BL18: =B18 -> 5 | BM18: =CC18 -> 51499.5 | BN18: =+BU18/BM18 -> 4.0173493 | BO18: =CD18 -> 187.5 | BP18: =+BU18/BO18 -> 1103.4212 | BQ18: =CE18 -> 16000 | BR18: =+BU18/BQ18 -> 12.930718 | BS18: =BU18-BM18-BO18-BQ18-BY18-BZ18-CA18-CB18 -> 85692.98 | BT18: =+BU18/BS18 -> 2.4143341 | BU18: 206891.48 | BV18: =+BU18/BG18% -> 26.99034 | BW18: =SUM(BG18-BH18-BU18) -> 46669 | BX18: =+BW18/BG18% -> 6.0882747 | BY18: 19019.5 | BZ18: 12728 | CA18: 16364 | CB18: 5400 | CC18: 51499.5 | CD18: 187.5 | CE18: 16000 | CF18: =BY18/BG18 -> 0.024812175 | CG18: =BZ18/BG18 -> 0.016604504 | CH18: =CA18/BG18 -> 0.021347903 | CI18: =CB18/BG18 -> 0.0070446513 | CJ18: =CC18/BG18 -> 0.067184449 | CK18: =+BW18*20% -> 9333.8 | CL18: =BW18*80% -> 37335.2
A19: =A18+1 -> 11 | B19: 5 | C19: STA.ROSA | G19: 40 | H19: =SUM(F19*G19) -> 0 | I19: 9185 | J19: 50 | K19: =J19*I19 -> 459250 | M19: 60 | N19: =M19*L19 -> 0 | O19: 8122 | P19: 12 | Q19: =O19*P19 -> 97464 | R19: 8050 | S19: 12 | T19: =R19*S19 -> 96600 | U19: 703 | V19: 8 | W19: =U19*V19 -> 5624 | X19: 376 | Y19: 12 | Z19: =X19*Y19 -> 4512 | AA19: 818 | AB19: 10 | AC19: =AA19*AB19 -> 8180 | AD19: 292 | AE19: 25 | AF19: =AD19*AE19 -> 7300 | AG19: 826 | AH19: 7.5 | AI19: =AG19*AH19 -> 6195 | AK19: 15 | AL19: =AJ19*AK19 -> 0 | AM19: 353 | AN19: 10 | AO19: =AM19*AN19 -> 3530 | AP19: =R19+U19+X19+AA19+AD19+AG19+AM19 -> 11418 | AX19: 2740 | AZ19: =O19/(I19+F19+L19) -> 0.88426783 | BA19: =AP19/(I19+F19+L19) -> 1.2431138 | BB19: =AX19/O19 -> 0.33735533 | BC19: =H19+W19+Z19+AC19+AF19+T19+K19+N19 -> 581466 | BD19: =H19+AF19+T19+K19+N19 -> 563150 | BE19: =H19+W19+Z19+AC19+AF19+T19+K19+N19 -> 581466 | BF19: =H19+W19+Z19+AC19+AF19+AI19+T19+K19+N19 -> 587661 | BG19: 739938 | BH19: 489888.38 | BI19: =+BH19/BG19% -> 66.206679 | BJ19: =SUM(BY19+BZ19+CA19+CB19) -> 45668 | BK19: =SUM(CF19+CG19+CH19+CI19) -> 0.061718685 | BL19: =B19 -> 5 | BM19: =CC19 -> 58250 | BN19: =+BU19/BM19 -> 3.4412815 | BO19: =CD19 -> 1812.5 | BP19: =+BU19/BO19 -> 110.59567 | BQ19: =CE19 -> 44000 | BR19: =+BU19/BQ19 -> 4.5557875 | BS19: =BU19-BM19-BO19-BQ19-BY19-BZ19-CA19-CB19 -> 50724.15 | BT19: =+BU19/BS19 -> 3.9518582 | BU19: 200454.65 | BV19: =+BU19/BG19% -> 27.090736 | BW19: =SUM(BG19-BH19-BU19) -> 49594.97 | BX19: =+BW19/BG19% -> 6.7025845 | BY19: 15238 | BZ19: 12728 | CA19: 14462 | CB19: 3240 | CC19: 58250 | CD19: 1812.5 | CE19: 44000 | CF19: =BY19/BG19 -> 0.020593617 | CG19: =BZ19/BG19 -> 0.017201441 | CH19: =CA19/BG19 -> 0.019544881 | CI19: =CB19/BG19 -> 0.0043787452 | CJ19: =CC19/BG19 -> 0.078722812 | CK19: =+BW19*20% -> 9918.994 | CL19: =BW19*80% -> 39675.976
A20: =A19+1 -> 12 | B20: 6 | C20: SAN CARLOS2 | G20: 40 | H20: =SUM(F20*G20) -> 0 | I20: 10677 | J20: 50 | K20: =J20*I20 -> 533850 | M20: 60 | N20: =M20*L20 -> 0 | O20: 6177 | P20: 12 | Q20: =O20*P20 -> 74124 | R20: 2730 | S20: 12 | T20: =R20*S20 -> 32760 | U20: 982 | V20: 8 | W20: =U20*V20 -> 7856 | X20: 849 | Y20: 12 | Z20: =X20*Y20 -> 10188 | AA20: 1365 | AB20: 10 | AC20: =AA20*AB20 -> 13650 | AD20: 177 | AE20: 25 | AF20: =AD20*AE20 -> 4425 | AG20: 171 | AH20: 7.5 | AI20: =AG20*AH20 -> 1282.5 | AK20: 15 | AL20: =AJ20*AK20 -> 0 | AM20: 188 | AN20: 12 | AO20: =AM20*AN20 -> 2256 | AP20: =R20+U20+X20+AA20+AD20+AG20+AM20 -> 6462 | AX20: 2748 | AZ20: =O20/(I20+F20+L20) -> 0.5785333 | BA20: =AP20/(I20+F20+L20) -> 0.60522619 | BB20: =AX20/O20 -> 0.44487615 | BC20: =H20+W20+Z20+AC20+AF20+T20+K20+N20 -> 602729 | BD20: =H20+AF20+T20+K20+N20 -> 571035 | BE20: =H20+W20+Z20+AC20+AF20+T20+K20+N20 -> 602729 | BF20: =H20+W20+Z20+AC20+AF20+AI20+T20+K20+N20 -> 604011.5 | BG20: 732728.5 | BH20: 483983.74 | BI20: =+BH20/BG20% -> 66.052261 | BJ20: =SUM(BY20+BZ20+CA20+CB20) -> 48627 | BK20: =SUM(CF20+CG20+CH20+CI20) -> 0.066364281 | BL20: =B20 -> 6 | BM20: =CC20 -> 76930 | BN20: =+BU20/BM20 -> 2.4167317 | BO20: =CD20 -> 0 | BP20: =+BU20/BO20 -> #DIV/0! | BQ20: =CE20 -> 9316.9 | BR20: =+BU20/BQ20 -> 19.955046 | BS20: =BU20-BM20-BO20-BQ20-BY20-BZ20-CA20-CB20 -> 51045.27 | BT20: =+BU20/BS20 -> 3.6422409 | BU20: 185919.17 | BV20: =+BU20/BG20% -> 25.373541 | BW20: =SUM(BG20-BH20-BU20) -> 62825.59 | BX20: =+BW20/BG20% -> 8.5741977 | BY20: 15296 | BZ20: 13840 | CA20: 13781 | CB20: 5710 | CC20: 76930 | CE20: 9316.9 | CF20: =BY20/BG20 -> 0.020875399 | CG20: =BZ20/BG20 -> 0.018888306 | CH20: =CA20/BG20 -> 0.018807785 | CI20: =CB20/BG20 -> 0.0077927909 | CJ20: =CC20/BG20 -> 0.10499114 | CK20: =+BW20*20% -> 12565.118 | CL20: =BW20*80% -> 50260.472
A21: =A20+1 -> 13 | B21: 5 | C21: AYUNGON 1 | G21: 40 | H21: =SUM(F21*G21) -> 0 | I21: 11604 | J21: 50 | K21: =J21*I21 -> 580200 | M21: 60 | N21: =M21*L21 -> 0 | O21: 4996 | P21: 12 | Q21: =O21*P21 -> 59952 | R21: 1470 | S21: 12 | T21: =R21*S21 -> 17640 | U21: 779 | V21: 8 | W21: =U21*V21 -> 6232 | X21: 515 | Y21: 12 | Z21: =X21*Y21 -> 6180 | AA21: 973 | AB21: 10 | AC21: =AA21*AB21 -> 9730 | AD21: 311 | AE21: 25 | AF21: =AD21*AE21 -> 7775 | AG21: 116 | AH21: 7.5 | AI21: =AG21*AH21 -> 870 | AK21: 15 | AL21: =AJ21*AK21 -> 0 | AM21: 256 | AN21: 10 | AO21: =AM21*AN21 -> 2560 | AP21: =R21+U21+X21+AA21+AD21+AG21+AM21 -> 4420 | AX21: 2217 | AZ21: =O21/(I21+F21+L21) -> 0.43054119 | BA21: =AP21/(I21+F21+L21) -> 0.38090314 | BB21: =AX21/O21 -> 0.443755 | BC21: =H21+W21+Z21+AC21+AF21+T21+K21+N21 -> 627757 | BD21: =H21+AF21+T21+K21+N21 -> 605615 | BE21: =H21+W21+Z21+AC21+AF21+T21+K21+N21 -> 627757 | BF21: =H21+W21+Z21+AC21+AF21+AI21+T21+K21+N21 -> 628627 | BG21: 730344 | BH21: 489400.4 | BI21: =+BH21/BG21% -> 67.009574 | BJ21: =SUM(BY21+BZ21+CA21+CB21) -> 50208 | BK21: =SUM(CF21+CG21+CH21+CI21) -> 0.068745687 | BL21: =B21 -> 5 | BM21: =CC21 -> 53800 | BN21: =+BU21/BM21 -> 3.2783892 | BO21: =CD21 -> 0 | BP21: =+BU21/BO21 -> #DIV/0! | BQ21: =CE21 -> 31500 | BR21: =+BU21/BQ21 -> 5.5992806 | BS21: =BU21-BM21-BO21-BQ21-BY21-BZ21-CA21-CB21 -> 40869.34 | BT21: =+BU21/BS21 -> 4.3156395 | BU21: 176377.34 | BV21: =+BU21/BG21% -> 24.149899 | BW21: =SUM(BG21-BH21-BU21) -> 64566.26 | BX21: =+BW21/BG21% -> 8.8405272 | BY21: 19022 | BZ21: 12728 | CA21: 13868 | CB21: 4590 | CC21: 53800 | CE21: 31500 | CF21: =BY21/BG21 -> 0.026045261 | CG21: =BZ21/BG21 -> 0.017427404 | CH21: =CA21/BG21 -> 0.018988312 | CI21: =CB21/BG21 -> 0.0062847097 | CJ21: =CC21/BG21 -> 0.073663917 | CK21: =+BW21*20% -> 12913.252 | CL21: =BW21*80% -> 51653.008
A22: =A21+1 -> 14 | B22: 5 | C22: SAN CARLOS1 | G22: 40 | H22: =SUM(F22*G22) -> 0 | I22: 10179 | J22: 50 | K22: =J22*I22 -> 508950 | M22: 60 | N22: =M22*L22 -> 0 | O22: 4079 | P22: 12 | Q22: =O22*P22 -> 48948 | R22: 3700 | S22: 12 | T22: =R22*S22 -> 44400 | U22: 534 | V22: 8 | W22: =U22*V22 -> 4272 | X22: 672 | Y22: 12 | Z22: =X22*Y22 -> 8064 | AA22: 743 | AB22: 10 | AC22: =AA22*AB22 -> 7430 | AD22: 273 | AE22: 25 | AF22: =AD22*AE22 -> 6825 | AG22: 186 | AH22: 7.5 | AI22: =AG22*AH22 -> 1395 | AK22: 15 | AL22: =AJ22*AK22 -> 0 | AM22: 222 | AN22: 12 | AO22: =AM22*AN22 -> 2664 | AP22: =R22+U22+X22+AA22+AD22+AG22+AM22 -> 6330 | AX22: 1041 | AZ22: =O22/(I22+F22+L22) -> 0.40072699 | BA22: =AP22/(I22+F22+L22) -> 0.62186855 | BB22: =AX22/O22 -> 0.25520961 | BC22: =H22+W22+Z22+AC22+AF22+T22+K22+N22 -> 579941 | BD22: =H22+AF22+T22+K22+N22 -> 560175 | BE22: =H22+W22+Z22+AC22+AF22+T22+K22+N22 -> 579941 | BF22: =H22+W22+Z22+AC22+AF22+AI22+T22+K22+N22 -> 581336 | BG22: 654873 | BH22: 436782.76 | BI22: =+BH22/BG22% -> 66.697323 | BJ22: =SUM(BY22+BZ22+CA22+CB22) -> 48122 | BK22: =SUM(CF22+CG22+CH22+CI22) -> 0.07348295 | BL22: =B22 -> 5 | BM22: =CC22 -> 59440 | BN22: =+BU22/BM22 -> 3.0131726 | BO22: =CD22 -> 343.75 | BP22: =+BU22/BO22 -> 521.02685 | BQ22: =CE22 -> 15000 | BR22: =+BU22/BQ22 -> 11.940199 | BS22: =BU22-BM22-BO22-BQ22-BY22-BZ22-CA22-CB22 -> 56197.23 | BT22: =+BU22/BS22 -> 3.1870428 | BU22: 179102.98 | BV22: =+BU22/BG22% -> 27.349269 | BW22: =SUM(BG22-BH22-BU22) -> 38987.26 | BX22: =+BW22/BG22% -> 5.9534078 | BY22: 20422 | BZ22: 12110 | CA22: 9830 | CB22: 5760 | CC22: 59440 | CD22: 343.75 | CE22: 15000 | CF22: =BY22/BG22 -> 0.031184672 | CG22: =BZ22/BG22 -> 0.018492135 | CH22: =CA22/BG22 -> 0.015010544 | CI22: =CB22/BG22 -> 0.0087955985 | CJ22: =CC22/BG22 -> 0.09076569 | CK22: =+BW22*20% -> 7797.452 | CL22: =BW22*80% -> 31189.808
A23: =A22+1 -> 15 | B23: 3 | C23: TAYASAN | G23: 40 | H23: =SUM(F23*G23) -> 0 | I23: 9807 | J23: 50 | K23: =J23*I23 -> 490350 | M23: 60 | N23: =M23*L23 -> 0 | O23: 3648 | P23: 12 | Q23: =O23*P23 -> 43776 | R23: 2550 | S23: 12 | T23: =R23*S23 -> 30600 | U23: 701 | V23: 8 | W23: =U23*V23 -> 5608 | X23: 518 | Y23: 12 | Z23: =X23*Y23 -> 6216 | AA23: 969 | AB23: 10 | AC23: =AA23*AB23 -> 9690 | AD23: 350 | AE23: 25 | AF23: =AD23*AE23 -> 8750 | AH23: 7.5 | AI23: =AG23*AH23 -> 0 | AK23: 15 | AL23: =AJ23*AK23 -> 0 | AM23: 172 | AN23: 10 | AO23: =AM23*AN23 -> 1720 | AP23: =R23+U23+X23+AA23+AD23+AG23+AM23 -> 5260 | AX23: 1301 | AZ23: =O23/(I23+F23+L23) -> 0.3719792 | BA23: =AP23/(I23+F23+L23) -> 0.53635159 | BB23: =AX23/O23 -> 0.35663377 | BC23: =H23+W23+Z23+AC23+AF23+T23+K23+N23 -> 551214 | BD23: =H23+AF23+T23+K23+N23 -> 529700 | BE23: =H23+W23+Z23+AC23+AF23+T23+K23+N23 -> 551214 | BF23: =H23+W23+Z23+AC23+AF23+AI23+T23+K23+N23 -> 551214 | BG23: 622892 | BH23: 416735.97 | BI23: =+BH23/BG23% -> 66.903407 | BJ23: =SUM(BY23+BZ23+CA23+CB23) -> 41481 | BK23: =SUM(CF23+CG23+CH23+CI23) -> 0.066594209 | BL23: =B23 -> 3 | BM23: =CC23 -> 44187.5 | BN23: =+BU23/BM23 -> 2.8876857 | BO23: =CD23 -> 125 | BP23: =+BU23/BO23 -> 1020.7969 | BQ23: =CE23 -> 16500 | BR23: =+BU23/BQ23 -> 7.7333097 | BS23: =BU23-BM23-BO23-BQ23-BY23-BZ23-CA23-CB23 -> 25306.11 | BT23: =+BU23/BS23 -> 5.0422451 | BU23: 127599.61 | BV23: =+BU23/BG23% -> 20.48503 | BW23: =SUM(BG23-BH23-BU23) -> 78556.42 | BX23: =+BW23/BG23% -> 12.611563 | BY23: 11514 | BZ23: 11137 | CA23: 13700 | CB23: 5130 | CC23: 44187.5 | CD23: 125 | CE23: 16500 | CF23: =BY23/BG23 -> 0.018484745 | CG23: =BZ23/BG23 -> 0.017879504 | CH23: =CA23/BG23 -> 0.021994182 | CI23: =CB23/BG23 -> 0.0082357776 | CJ23: =CC23/BG23 -> 0.070939264 | CK23: =+BW23*20% -> 15711.284 | CL23: =BW23*80% -> 62845.136
A24: =A23+1 -> 16 | B24: 4 | C24: BACONG 1 | G24: 40 | H24: =SUM(F24*G24) -> 0 | I24: 8491 | J24: 50 | K24: =J24*I24 -> 424550 | M24: 60 | N24: =M24*L24 -> 0 | O24: 5512 | P24: 12 | Q24: =O24*P24 -> 66144 | R24: 3750 | S24: 12 | T24: =R24*S24 -> 45000 | U24: 1227 | V24: 8 | W24: =U24*V24 -> 9816 | X24: 280 | Y24: 12 | Z24: =X24*Y24 -> 3360 | AA24: 1029 | AB24: 10 | AC24: =AA24*AB24 -> 10290 | AD24: 390 | AE24: 25 | AF24: =AD24*AE24 -> 9750 | AG24: 576 | AH24: 7.5 | AI24: =AG24*AH24 -> 4320 | AK24: 15 | AL24: =AJ24*AK24 -> 0 | AM24: 271 | AN24: 10 | AO24: =AM24*AN24 -> 2710 | AP24: =R24+U24+X24+AA24+AD24+AG24+AM24 -> 7523 | AX24: 1945 | AZ24: =O24/(I24+F24+L24) -> 0.64915793 | BA24: =AP24/(I24+F24+L24) -> 0.88599694 | BB24: =AX24/O24 -> 0.35286647 | BC24: =H24+W24+Z24+AC24+AF24+T24+K24+N24 -> 502766 | BD24: =H24+AF24+T24+K24+N24 -> 479300 | BE24: =H24+W24+Z24+AC24+AF24+T24+K24+N24 -> 502766 | BF24: =H24+W24+Z24+AC24+AF24+AI24+T24+K24+N24 -> 507086 | BG24: 612575 | BH24: 412999.13 | BI24: =+BH24/BG24% -> 67.420174 | BJ24: =SUM(BY24+BZ24+CA24+CB24) -> 34608.5 | BK24: =SUM(CF24+CG24+CH24+CI24) -> 0.056496755 | BL24: =B24 -> 4 | BM24: =CC24 -> 57300 | BN24: =+BU24/BM24 -> 2.5085241 | BO24: =CD24 -> 62.5 | BP24: =+BU24/BO24 -> 2299.8149 | BQ24: =CE24 -> 16000 | BR24: =+BU24/BQ24 -> 8.9836519 | BS24: =BU24-BM24-BO24-BQ24-BY24-BZ24-CA24-CB24 -> 35767.43 | BT24: =+BU24/BS24 -> 4.0186961 | BU24: 143738.43 | BV24: =+BU24/BG24% -> 23.464626 | BW24: =SUM(BG24-BH24-BU24) -> 55837.44 | BX24: =+BW24/BG24% -> 9.1152006 | BY24: 11456.5 | BZ24: 9546 | CA24: 10096 | CB24: 3510 | CC24: 57300 | CD24: 62.5 | CE24: 16000 | CF24: =BY24/BG24 -> 0.0187022 | CG24: =BZ24/BG24 -> 0.015583398 | CH24: =CA24/BG24 -> 0.016481247 | CI24: =CB24/BG24 -> 0.0057299106 | CJ24: =CC24/BG24 -> 0.093539567 | CK24: =+BW24*20% -> 11167.488 | CL24: =BW24*80% -> 44669.952
A25: =A24+1 -> 17 | B25: 4 | C25: GUIHULNGAN | G25: 40 | H25: =SUM(F25*G25) -> 0 | I25: 9518 | J25: 50 | K25: =J25*I25 -> 475900 | M25: 60 | N25: =M25*L25 -> 0 | O25: 3681 | P25: 12 | Q25: =O25*P25 -> 44172 | R25: 1460 | S25: 12 | T25: =R25*S25 -> 17520 | U25: 573 | V25: 8 | W25: =U25*V25 -> 4584 | X25: 849 | Y25: 12 | Z25: =X25*Y25 -> 10188 | AA25: 679 | AB25: 10 | AC25: =AA25*AB25 -> 6790 | AD25: 278 | AE25: 25 | AF25: =AD25*AE25 -> 6950 | AG25: 1530 | AH25: 7.5 | AI25: =AG25*AH25 -> 11475 | AK25: 15 | AL25: =AJ25*AK25 -> 0 | AM25: 402 | AN25: 10 | AO25: =AM25*AN25 -> 4020 | AP25: =R25+U25+X25+AA25+AD25+AG25+AM25 -> 5771 | AX25: 1639 | AZ25: =O25/(I25+F25+L25) -> 0.38674091 | BA25: =AP25/(I25+F25+L25) -> 0.60632486 | BB25: =AX25/O25 -> 0.44525944 | BC25: =H25+W25+Z25+AC25+AF25+T25+K25+N25 -> 521932 | BD25: =H25+AF25+T25+K25+N25 -> 500370 | BE25: =H25+W25+Z25+AC25+AF25+T25+K25+N25 -> 521932 | BF25: =H25+W25+Z25+AC25+AF25+AI25+T25+K25+N25 -> 533407 | BG25: 611948 | BH25: 411984.75 | BI25: =+BH25/BG25% -> 67.32349 | BJ25: =SUM(BY25+BZ25+CA25+CB25) -> 36148 | BK25: =SUM(CF25+CG25+CH25+CI25) -> 0.059070379 | BL25: =B25 -> 4 | BM25: =CC25 -> 48748 | BN25: =+BU25/BM25 -> 3.6738157 | BO25: =CD25 -> 0 | BP25: =+BU25/BO25 -> #DIV/0! | BQ25: =CE25 -> 36000 | BR25: =+BU25/BQ25 -> 4.9747547 | BS25: =BU25-BM25-BO25-BQ25-BY25-BZ25-CA25-CB25 -> 58195.17 | BT25: =+BU25/BS25 -> 3.0774233 | BU25: 179091.17 | BV25: =+BU25/BG25% -> 29.26575 | BW25: =SUM(BG25-BH25-BU25) -> 20872.08 | BX25: =+BW25/BG25% -> 3.4107604 | BY25: 11458 | BZ25: 10380 | CA25: 9830 | CB25: 4480 | CC25: 48748 | CE25: 36000 | CF25: =BY25/BG25 -> 0.018723813 | CG25: =BZ25/BG25 -> 0.016962226 | CH25: =CA25/BG25 -> 0.016063456 | CI25: =CB25/BG25 -> 0.0073208835 | CJ25: =CC25/BG25 -> 0.079660363 | CK25: =+BW25*20% -> 4174.416 | CL25: =BW25*80% -> 16697.664
A26: =A25+1 -> 18 | B26: 4 | C26: SAN CARLOS7 | G26: 40 | H26: =SUM(F26*G26) -> 0 | I26: 8657 | J26: 50 | K26: =J26*I26 -> 432850 | M26: 60 | N26: =M26*L26 -> 0 | O26: 3794 | P26: 12 | Q26: =O26*P26 -> 45528 | R26: 2720 | S26: 12 | T26: =R26*S26 -> 32640 | U26: 648 | V26: 8 | W26: =U26*V26 -> 5184 | X26: 965 | Y26: 12 | Z26: =X26*Y26 -> 11580 | AA26: 1032 | AB26: 10 | AC26: =AA26*AB26 -> 10320 | AD26: 226 | AE26: 25 | AF26: =AD26*AE26 -> 5650 | AG26: 345 | AH26: 7.5 | AI26: =AG26*AH26 -> 2587.5 | AK26: 15 | AL26: =AJ26*AK26 -> 0 | AM26: 194 | AN26: 12 | AO26: =AM26*AN26 -> 2328 | AP26: =R26+U26+X26+AA26+AD26+AG26+AM26 -> 6130 | AX26: 1764 | AZ26: =O26/(I26+F26+L26) -> 0.43825806 | BA26: =AP26/(I26+F26+L26) -> 0.70809749 | BB26: =AX26/O26 -> 0.46494465 | BC26: =H26+W26+Z26+AC26+AF26+T26+K26+N26 -> 498224 | BD26: =H26+AF26+T26+K26+N26 -> 471140 | BE26: =H26+W26+Z26+AC26+AF26+T26+K26+N26 -> 498224 | BF26: =H26+W26+Z26+AC26+AF26+AI26+T26+K26+N26 -> 500811.5 | BG26: 584447.5 | BH26: 389286.66 | BI26: =+BH26/BG26% -> 66.607635 | BJ26: =SUM(BY26+BZ26+CA26+CB26) -> 36918 | BK26: =SUM(CF26+CG26+CH26+CI26) -> 0.06316735 | BL26: =B26 -> 4 | BM26: =CC26 -> 51512 | BN26: =+BU26/BM26 -> 2.8455917 | BO26: =CD26 -> 0 | BP26: =+BU26/BO26 -> #DIV/0! | BQ26: =CE26 -> 20000 | BR26: =+BU26/BQ26 -> 7.329106 | BS26: =BU26-BM26-BO26-BQ26-BY26-BZ26-CA26-CB26 -> 38152.12 | BT26: =+BU26/BS26 -> 3.8420439 | BU26: 146582.12 | BV26: =+BU26/BG26% -> 25.08046 | BW26: =SUM(BG26-BH26-BU26) -> 48578.72 | BX26: =+BW26/BG26% -> 8.3119048 | BY26: 11514 | BZ26: 10380 | CA26: 8624 | CB26: 6400 | CC26: 51512 | CE26: 20000 | CF26: =BY26/BG26 -> 0.019700657 | CG26: =BZ26/BG26 -> 0.017760363 | CH26: =CA26/BG26 -> 0.014755816 | CI26: =CB26/BG26 -> 0.010950513 | CJ26: =CC26/BG26 -> 0.088137942 | CK26: =+BW26*20% -> 9715.744 | CL26: =BW26*80% -> 38862.976
A27: =A26+1 -> 19 | B27: 4 | C27: QUEZON | G27: 40 | H27: =SUM(F27*G27) -> 0 | I27: 8217 | J27: 50 | K27: =J27*I27 -> 410850 | M27: 60 | N27: =M27*L27 -> 0 | O27: 3983 | P27: 12 | Q27: =O27*P27 -> 47796 | R27: 3070 | S27: 12 | T27: =R27*S27 -> 36840 | U27: 806 | V27: 8 | W27: =U27*V27 -> 6448 | X27: 844 | Y27: 12 | Z27: =X27*Y27 -> 10128 | AA27: 1440 | AB27: 10 | AC27: =AA27*AB27 -> 14400 | AD27: 370 | AE27: 25 | AF27: =AD27*AE27 -> 9250 | AG27: 510 | AH27: 7.5 | AI27: =AG27*AH27 -> 3825 | AK27: 15 | AL27: =AJ27*AK27 -> 0 | AM27: 126 | AN27: 10 | AO27: =AM27*AN27 -> 1260 | AP27: =R27+U27+X27+AA27+AD27+AG27+AM27 -> 7166 | AX27: 1745 | AZ27: =O27/(I27+F27+L27) -> 0.48472679 | BA27: =AP27/(I27+F27+L27) -> 0.87209444 | BB27: =AX27/O27 -> 0.43811198 | BC27: =H27+W27+Z27+AC27+AF27+T27+K27+N27 -> 487916 | BD27: =H27+AF27+T27+K27+N27 -> 456940 | BE27: =H27+W27+Z27+AC27+AF27+T27+K27+N27 -> 487916 | BF27: =H27+W27+Z27+AC27+AF27+AI27+T27+K27+N27 -> 491741 | BG27: 581045 | BH27: 387794.17 | BI27: =+BH27/BG27% -> 66.740815 | BJ27: =SUM(BY27+BZ27+CA27+CB27) -> 36404 | BK27: =SUM(CF27+CG27+CH27+CI27) -> 0.062652634 | BL27: =B27 -> 4 | BM27: =CC27 -> 50412 | BN27: =+BU27/BM27 -> 2.732233 | BO27: =CD27 -> 0 | BP27: =+BU27/BO27 -> #DIV/0! | BQ27: =CE27 -> 12000 | BR27: =+BU27/BQ27 -> 11.478111 | BS27: =BU27-BM27-BO27-BQ27-BY27-BZ27-CA27-CB27 -> 38921.33 | BT27: =+BU27/BS27 -> 3.5388649 | BU27: 137737.33 | BV27: =+BU27/BG27% -> 23.705105 | BW27: =SUM(BG27-BH27-BU27) -> 55513.5 | BX27: =+BW27/BG27% -> 9.5540793 | BY27: 11458 | BZ27: 10380 | CA27: 8806 | CB27: 5760 | CC27: 50412 | CE27: 12000 | CF27: =BY27/BG27 -> 0.019719643 | CG27: =BZ27/BG27 -> 0.017864365 | CH27: =CA27/BG27 -> 0.015155453 | CI27: =CB27/BG27 -> 0.0099131737 | CJ27: =CC27/BG27 -> 0.086760922 | CK27: =+BW27*20% -> 11102.7 | CL27: =BW27*80% -> 44410.8
A28: =A27+1 -> 20 | B28: 4 | C28: SAN CARLOS5 | G28: 40 | H28: =SUM(F28*G28) -> 0 | I28: 9237 | J28: 50 | K28: =J28*I28 -> 461850 | M28: 60 | N28: =M28*L28 -> 0 | O28: 3304 | P28: 12 | Q28: =O28*P28 -> 39648 | R28: 2670 | S28: 12 | T28: =R28*S28 -> 32040 | U28: 492 | V28: 8 | W28: =U28*V28 -> 3936 | X28: 693 | Y28: 12 | Z28: =X28*Y28 -> 8316 | AA28: 725 | AB28: 10 | AC28: =AA28*AB28 -> 7250 | AD28: 230 | AE28: 25 | AF28: =AD28*AE28 -> 5750 | AG28: 249 | AH28: 7.5 | AI28: =AG28*AH28 -> 1867.5 | AK28: 15 | AL28: =AJ28*AK28 -> 0 | AM28: 150 | AN28: 12 | AO28: =AM28*AN28 -> 1800 | AP28: =R28+U28+X28+AA28+AD28+AG28+AM28 -> 5209 | AX28: 948 | AZ28: =O28/(I28+F28+L28) -> 0.35769189 | BA28: =AP28/(I28+F28+L28) -> 0.56392768 | BB28: =AX28/O28 -> 0.28692494 | BC28: =H28+W28+Z28+AC28+AF28+T28+K28+N28 -> 519142 | BD28: =H28+AF28+T28+K28+N28 -> 499640 | BE28: =H28+W28+Z28+AC28+AF28+T28+K28+N28 -> 519142 | BF28: =H28+W28+Z28+AC28+AF28+AI28+T28+K28+N28 -> 521009.5 | BG28: 580461.5 | BH28: 389908.14 | BI28: =+BH28/BG28% -> 67.172093 | BJ28: =SUM(BY28+BZ28+CA28+CB28) -> 41952 | BK28: =SUM(CF28+CG28+CH28+CI28) -> 0.072273527 | BL28: =B28 -> 4 | BM28: =CC28 -> 45684 | BN28: =+BU28/BM28 -> 3.5068654 | BO28: =CD28 -> 0 | BP28: =+BU28/BO28 -> #DIV/0! | BQ28: =CE28 -> 30000 | BR28: =+BU28/BQ28 -> 5.3402547 | BS28: =BU28-BM28-BO28-BQ28-BY28-BZ28-CA28-CB28 -> 42571.64 | BT28: =+BU28/BS28 -> 3.763248 | BU28: 160207.64 | BV28: =+BU28/BG28% -> 27.600046 | BW28: =SUM(BG28-BH28-BU28) -> 30345.72 | BX28: =+BW28/BG28% -> 5.2278609 | BY28: 15296 | BZ28: 12110 | CA28: 10066 | CB28: 4480 | CC28: 45684 | CE28: 30000 | CF28: =BY28/BG28 -> 0.026351446 | CG28: =BZ28/BG28 -> 0.02086271 | CH28: =CA28/BG28 -> 0.017341374 | CI28: =CB28/BG28 -> 0.0077179968 | CJ28: =CC28/BG28 -> 0.078702894 | CK28: =+BW28*20% -> 6069.144 | CL28: =BW28*80% -> 24276.576
A29: =A28+1 -> 21 | B29: 4 | C29: BAGACAY | G29: 40 | H29: =SUM(F29*G29) -> 0 | I29: 7603 | J29: 50 | K29: =J29*I29 -> 380150 | M29: 60 | N29: =M29*L29 -> 0 | O29: 6517 | P29: 12 | Q29: =O29*P29 -> 78204 | R29: 1707 | S29: 12 | T29: =R29*S29 -> 20484 | U29: 1555 | V29: 8 | W29: =U29*V29 -> 12440 | X29: 465 | Y29: 12 | Z29: =X29*Y29 -> 5580 | AA29: 1291 | AB29: 10 | AC29: =AA29*AB29 -> 12910 | AD29: 316 | AE29: 25 | AF29: =AD29*AE29 -> 7900 | AG29: 402 | AH29: 7.5 | AI29: =AG29*AH29 -> 3015 | AK29: 15 | AL29: =AJ29*AK29 -> 0 | AM29: 264 | AN29: 10 | AO29: =AM29*AN29 -> 2640 | AP29: =R29+U29+X29+AA29+AD29+AG29+AM29 -> 6000 | AX29: 2462 | AZ29: =O29/(I29+F29+L29) -> 0.85716165 | BA29: =AP29/(I29+F29+L29) -> 0.78916217 | BB29: =AX29/O29 -> 0.37778119 | BC29: =H29+W29+Z29+AC29+AF29+T29+K29+N29 -> 439464 | BD29: =H29+AF29+T29+K29+N29 -> 408534 | BE29: =H29+W29+Z29+AC29+AF29+T29+K29+N29 -> 439464 | BF29: =H29+W29+Z29+AC29+AF29+AI29+T29+K29+N29 -> 442479 | BG29: 569205 | BH29: 382404.08 | BI29: =+BH29/BG29% -> 67.182136 | BJ29: =SUM(BY29+BZ29+CA29+CB29) -> 35534.5 | BK29: =SUM(CF29+CG29+CH29+CI29) -> 0.062428299 | BL29: =B29 -> 4 | BM29: =CC29 -> 48250 | BN29: =+BU29/BM29 -> 3.3070435 | BO29: =CD29 -> 62.5 | BP29: =+BU29/BO29 -> 2553.0376 | BQ29: =CE29 -> 28000 | BR29: =+BU29/BQ29 -> 5.6987446 | BS29: =BU29-BM29-BO29-BQ29-BY29-BZ29-CA29-CB29 -> 47717.85 | BT29: =+BU29/BS29 -> 3.3439237 | BU29: 159564.85 | BV29: =+BU29/BG29% -> 28.032932 | BW29: =SUM(BG29-BH29-BU29) -> 27236.07 | BX29: =+BW29/BG29% -> 4.7849316 | BY29: 11456.5 | BZ29: 9546 | CA29: 11292 | CB29: 3240 | CC29: 48250 | CD29: 62.5 | CE29: 28000 | CF29: =BY29/BG29 -> 0.020127195 | CG29: =BZ29/BG29 -> 0.016770759 | CH29: =CA29/BG29 -> 0.019838195 | CI29: =CB29/BG29 -> 0.0056921496 | CJ29: =CC29/BG29 -> 0.084767351 | CK29: =+BW29*20% -> 5447.214 | CL29: =BW29*80% -> 21788.856
A30: =A29+1 -> 22 | B30: 4 | C30: BAYAWAN | G30: 40 | H30: =SUM(F30*G30) -> 0 | I30: 9282 | J30: 50 | K30: =J30*I30 -> 464100 | M30: 60 | N30: =M30*L30 -> 0 | O30: 3147 | P30: 12 | Q30: =O30*P30 -> 37764 | R30: 340 | S30: 12 | T30: =R30*S30 -> 4080 | U30: 710 | V30: 8 | W30: =U30*V30 -> 5680 | X30: 536 | Y30: 12 | Z30: =X30*Y30 -> 6432 | AA30: 798 | AB30: 10 | AC30: =AA30*AB30 -> 7980 | AD30: 255 | AE30: 25 | AF30: =AD30*AE30 -> 6375 | AG30: 330 | AH30: 7.5 | AI30: =AG30*AH30 -> 2475 | AK30: 15 | AL30: =AJ30*AK30 -> 0 | AN30: 10 | AO30: =AM30*AN30 -> 0 | AP30: =R30+U30+X30+AA30+AD30+AG30+AM30 -> 2969 | AX30: 1296 | AZ30: =O30/(I30+F30+L30) -> 0.33904331 | BA30: =AP30/(I30+F30+L30) -> 0.31986641 | BB30: =AX30/O30 -> 0.41182078 | BC30: =H30+W30+Z30+AC30+AF30+T30+K30+N30 -> 494647 | BD30: =H30+AF30+T30+K30+N30 -> 474555 | BE30: =H30+W30+Z30+AC30+AF30+T30+K30+N30 -> 494647 | BF30: =H30+W30+Z30+AC30+AF30+AI30+T30+K30+N30 -> 497122 | BG30: 560768 | BH30: 376312.23 | BI30: =+BH30/BG30% -> 67.106581 | BJ30: =SUM(BY30+BZ30+CA30+CB30) -> 50009.5 | BK30: =SUM(CF30+CG30+CH30+CI30) -> 0.089180374 | BL30: =B30 -> 4 | BM30: =CC30 -> 44325 | BN30: =+BU30/BM30 -> 3.404481 | BO30: =CD30 -> 500 | BP30: =+BU30/BO30 -> 301.80724 | BQ30: =CE30 -> 13000 | BR30: =+BU30/BQ30 -> 11.607971 | BS30: =BU30-BM30-BO30-BQ30-BY30-BZ30-CA30-CB30 -> 43069.12 | BT30: =+BU30/BS30 -> 3.5037544 | BU30: 150903.62 | BV30: =+BU30/BG30% -> 26.91017 | BW30: =SUM(BG30-BH30-BU30) -> 33552.15 | BX30: =+BW30/BG30% -> 5.9832498 | BY30: 19019.5 | BZ30: 12728 | CA30: 13672 | CB30: 4590 | CC30: 44325 | CD30: 500 | CE30: 13000 | CF30: =BY30/BG30 -> 0.033916878 | CG30: =BZ30/BG30 -> 0.022697444 | CH30: =CA30/BG30 -> 0.024380849 | CI30: =CB30/BG30 -> 0.0081852031 | CJ30: =CC30/BG30 -> 0.079043383 | CK30: =+BW30*20% -> 6710.43 | CL30: =BW30*80% -> 26841.72
A31: =A30+1 -> 23 | B31: 4 | C31: AYUNGON 2 | G31: 40 | H31: =SUM(F31*G31) -> 0 | I31: 8132 | J31: 50 | K31: =J31*I31 -> 406600 | M31: 60 | N31: =M31*L31 -> 0 | O31: 2903 | P31: 12 | Q31: =O31*P31 -> 34836 | R31: 1510 | S31: 12 | T31: =R31*S31 -> 18120 | U31: 888 | V31: 8 | W31: =U31*V31 -> 7104 | X31: 442 | Y31: 12 | Z31: =X31*Y31 -> 5304 | AA31: 1053 | AB31: 10 | AC31: =AA31*AB31 -> 10530 | AD31: 206 | AE31: 25 | AF31: =AD31*AE31 -> 5150 | AG31: 247 | AH31: 7.5 | AI31: =AG31*AH31 -> 1852.5 | AK31: 15 | AL31: =AJ31*AK31 -> 0 | AM31: 191 | AN31: 10 | AO31: =AM31*AN31 -> 1910 | AP31: =R31+U31+X31+AA31+AD31+AG31+AM31 -> 4537 | AX31: 1365 | AZ31: =O31/(I31+F31+L31) -> 0.35698475 | BA31: =AP31/(I31+F31+L31) -> 0.55791933 | BB31: =AX31/O31 -> 0.47020324 | BC31: =H31+W31+Z31+AC31+AF31+T31+K31+N31 -> 452808 | BD31: =H31+AF31+T31+K31+N31 -> 429870 | BE31: =H31+W31+Z31+AC31+AF31+T31+K31+N31 -> 452808 | BF31: =H31+W31+Z31+AC31+AF31+AI31+T31+K31+N31 -> 454660.5 | BG31: 519613.5 | BH31: 347500.32 | BI31: =+BH31/BG31% -> 66.876692 | BJ31: =SUM(BY31+BZ31+CA31+CB31) -> 36662 | BK31: =SUM(CF31+CG31+CH31+CI31) -> 0.070556288 | BL31: =B31 -> 4 | BM31: =CC31 -> 40050 | BN31: =+BU31/BM31 -> 3.1586327 | BO31: =CD31 -> 1364 | BP31: =+BU31/BO31 -> 92.744311 | BQ31: =CE31 -> 20000 | BR31: =+BU31/BQ31 -> 6.325162 | BS31: =BU31-BM31-BO31-BQ31-BY31-BZ31-CA31-CB31 -> 28427.24 | BT31: =+BU31/BS31 -> 4.4500711 | BU31: 126503.24 | BV31: =+BU31/BG31% -> 24.345642 | BW31: =SUM(BG31-BH31-BU31) -> 45609.94 | BX31: =+BW31/BG31% -> 8.7776665 | BY31: 11402 | BZ31: 9546 | CA31: 12474 | CB31: 3240 | CC31: 40050 | CD31: 1364 | CE31: 20000 | CF31: =BY31/BG31 -> 0.021943233 | CG31: =BZ31/BG31 -> 0.018371347 | CH31: =CA31/BG31 -> 0.024006305 | CI31: =CB31/BG31 -> 0.0062354038 | CJ31: =CC31/BG31 -> 0.077076519 | CK31: =+BW31*20% -> 9121.988 | CL31: =BW31*80% -> 36487.952
A32: =A31+1 -> 24 | B32: 4 | C32: LARENA | G32: 40 | H32: =SUM(F32*G32) -> 0 | I32: 6140 | J32: 50 | K32: =J32*I32 -> 307000 | M32: 60 | N32: =M32*L32 -> 0 | O32: 4984 | P32: 12 | Q32: =O32*P32 -> 59808 | R32: 5990 | S32: 12 | T32: =R32*S32 -> 71880 | U32: 712 | V32: 8 | W32: =U32*V32 -> 5696 | X32: 226 | Y32: 12 | Z32: =X32*Y32 -> 2712 | AA32: 688 | AB32: 10 | AC32: =AA32*AB32 -> 6880 | AD32: 306 | AE32: 25 | AF32: =AD32*AE32 -> 7650 | AG32: 830 | AH32: 7.5 | AI32: =AG32*AH32 -> 6225 | AK32: 15 | AL32: =AJ32*AK32 -> 0 | AM32: 217 | AN32: 10 | AO32: =AM32*AN32 -> 2170 | AP32: =R32+U32+X32+AA32+AD32+AG32+AM32 -> 8969 | AX32: 1286 | AZ32: =O32/(I32+F32+L32) -> 0.81172638 | BA32: =AP32/(I32+F32+L32) -> 1.4607492 | BB32: =AX32/O32 -> 0.25802568 | BC32: =H32+W32+Z32+AC32+AF32+T32+K32+N32 -> 401818 | BD32: =H32+AF32+T32+K32+N32 -> 386530 | BE32: =H32+W32+Z32+AC32+AF32+T32+K32+N32 -> 401818 | BF32: =H32+W32+Z32+AC32+AF32+AI32+T32+K32+N32 -> 408043 | BG32: 495109 | BH32: 329923.08 | BI32: =+BH32/BG32% -> 66.636454 | BJ32: =SUM(BY32+BZ32+CA32+CB32) -> 35487 | BK32: =SUM(CF32+CG32+CH32+CI32) -> 0.071675126 | BL32: =B32 -> 4 | BM32: =CC32 -> 44000 | BN32: =+BU32/BM32 -> 3.4205334 | BO32: =CD32 -> 0 | BP32: =+BU32/BO32 -> #DIV/0! | BQ32: =CE32 -> 35000 | BR32: =+BU32/BQ32 -> 4.3000991 | BS32: =BU32-BM32-BO32-BQ32-BY32-BZ32-CA32-CB32 -> 36016.47 | BT32: =+BU32/BS32 -> 4.1787402 | BU32: 150503.47 | BV32: =+BU32/BG32% -> 30.398048 | BW32: =SUM(BG32-BH32-BU32) -> 14682.45 | BX32: =+BW32/BG32% -> 2.9654985 | BY32: 11683 | BZ32: 9546 | CA32: 11288 | CB32: 2970 | CC32: 44000 | CE32: 35000 | CF32: =BY32/BG32 -> 0.023596824 | CG32: =BZ32/BG32 -> 0.019280603 | CH32: =CA32/BG32 -> 0.02279902 | CI32: =CB32/BG32 -> 0.0059986791 | CJ32: =CC32/BG32 -> 0.08886932 | CK32: =+BW32*20% -> 2936.49 | CL32: =BW32*80% -> 11745.96
A33: =A32+1 -> 25 | B33: 3 | C33: JUNOB | G33: 40 | H33: =SUM(F33*G33) -> 0 | I33: 7487 | J33: 50 | K33: =J33*I33 -> 374350 | M33: 60 | N33: =M33*L33 -> 0 | O33: 4009 | P33: 12 | Q33: =O33*P33 -> 48108 | R33: 850 | S33: 12 | T33: =R33*S33 -> 10200 | U33: 724 | V33: 8 | W33: =U33*V33 -> 5792 | X33: 335 | Y33: 12 | Z33: =X33*Y33 -> 4020 | AA33: 700 | AB33: 10 | AC33: =AA33*AB33 -> 7000 | AD33: 90 | AE33: 25 | AF33: =AD33*AE33 -> 2250 | AG33: 113 | AH33: 7.5 | AI33: =AG33*AH33 -> 847.5 | AK33: 15 | AL33: =AJ33*AK33 -> 0 | AM33: 154 | AN33: 10 | AO33: =AM33*AN33 -> 1540 | AP33: =R33+U33+X33+AA33+AD33+AG33+AM33 -> 2966 | AX33: 1159 | AZ33: =O33/(I33+F33+L33) -> 0.53546147 | BA33: =AP33/(I33+F33+L33) -> 0.39615333 | BB33: =AX33/O33 -> 0.28909953 | BC33: =H33+W33+Z33+AC33+AF33+T33+K33+N33 -> 403612 | BD33: =H33+AF33+T33+K33+N33 -> 386800 | BE33: =H33+W33+Z33+AC33+AF33+T33+K33+N33 -> 403612 | BF33: =H33+W33+Z33+AC33+AF33+AI33+T33+K33+N33 -> 404459.5 | BG33: 476253.5 | BH33: 324943.64 | BI33: =+BH33/BG33% -> 68.229134 | BJ33: =SUM(BY33+BZ33+CA33+CB33) -> 30877 | BK33: =SUM(CF33+CG33+CH33+CI33) -> 0.064833119 | BL33: =B33 -> 3 | BM33: =CC33 -> 43750 | BN33: =+BU33/BM33 -> 3.1948571 | BO33: =CD33 -> 0 | BP33: =+BU33/BO33 -> #DIV/0! | BQ33: =CE33 -> 26750 | BR33: =+BU33/BQ33 -> 5.2252336 | BS33: =BU33-BM33-BO33-BQ33-BY33-BZ33-CA33-CB33 -> 38398 | BT33: =+BU33/BS33 -> 3.6401636 | BU33: 139775 | BV33: =+BU33/BG33% -> 29.348866 | BW33: =SUM(BG33-BH33-BU33) -> 11534.86 | BX33: =+BW33/BG33% -> 2.422 | BY33: 6775 | BZ33: 9546 | CA33: 11316 | CB33: 3240 | CC33: 43750 | CE33: 26750 | CF33: =BY33/BG33 -> 0.014225617 | CG33: =BZ33/BG33 -> 0.020043947 | CH33: =CA33/BG33 -> 0.023760455 | CI33: =CB33/BG33 -> 0.0068030996 | CJ33: =CC33/BG33 -> 0.091862842 | CK33: =+BW33*20% -> 2306.972 | CL33: =BW33*80% -> 9227.888
A34: =A33+1 -> 26 | B34: 6 | C34: DALAGUETE | G34: 40 | H34: =SUM(F34*G34) -> 0 | I34: 7002 | J34: 50 | K34: =J34*I34 -> 350100 | M34: 60 | N34: =M34*L34 -> 0 | O34: 3641 | P34: 12 | Q34: =O34*P34 -> 43692 | S34: 12 | T34: =R34*S34 -> 0 | U34: 1000 | V34: 8 | W34: =U34*V34 -> 8000 | X34: 1424 | Y34: 12 | Z34: =X34*Y34 -> 17088 | AA34: 1154 | AB34: 10 | AC34: =AA34*AB34 -> 11540 | AD34: 726 | AE34: 25 | AF34: =AD34*AE34 -> 18150 | AG34: 540 | AH34: 7.5 | AI34: =AG34*AH34 -> 4050 | AK34: 15 | AL34: =AJ34*AK34 -> 0 | AN34: 10 | AO34: =AM34*AN34 -> 0 | AP34: =R34+U34+X34+AA34+AD34+AG34+AM34 -> 4844 | AX34: =596+152+11+614+50 -> 1423 | AZ34: =O34/(I34+F34+L34) -> 0.51999429 | BA34: =AP34/(I34+F34+L34) -> 0.69180234 | BB34: =AX34/O34 -> 0.3908267 | BC34: =H34+W34+Z34+AC34+AF34+T34+K34+N34 -> 404878 | BD34: =H34+AF34+T34+K34+N34 -> 368250 | BE34: =H34+W34+Z34+AC34+AF34+T34+K34+N34 -> 404878 | BF34: =H34+W34+Z34+AC34+AF34+AI34+T34+K34+N34 -> 408928 | BG34: 476087 | BH34: 318967.88 | BI34: =+BH34/BG34% -> 66.997813 | BJ34: =SUM(BY34+BZ34+CA34+CB34) -> 35910 | BK34: =SUM(CF34+CG34+CH34+CI34) -> 0.07542739 | BL34: 4 | BM34: =CC34 -> 30137 | BN34: =+BU34/BM34 -> 3.5250124 | BO34: =CD34 -> 1187.5 | BP34: =+BU34/BO34 -> 89.459621 | BQ34: =CE34 -> 0 | BR34: =+BU34/BQ34 -> #DIV/0! | BS34: =BU34-BM34-BO34-BQ34-BY34-BZ34-CA34-CB34 -> 38998.8 | BT34: =+BU34/BS34 -> 2.7240146 | BU34: 106233.3 | BV34: =+BU34/BG34% -> 22.313842 | BW34: =SUM(BG34-BH34-BU34) -> 50885.82 | BX34: =+BW34/BG34% -> 10.688345 | BY34: 4016 | BZ34: 12728 | CA34: 14306 | CB34: 4860 | CC34: 30137 | CD34: 1187.5 | CE34: 0 | CF34: =BY34/BG34 -> 0.008435433 | CG34: =BZ34/BG34 -> 0.026734609 | CH34: =CA34/BG34 -> 0.03004913 | CI34: =CB34/BG34 -> 0.010208218 | CJ34: =CC34/BG34 -> 0.063301455 | CK34: =+BW34*20% -> 10177.164 | CL34: =BW34*80% -> 40708.656
A35: =A34+1 -> 27 | B35: 3 | C35: JIMALALUD | G35: 40 | H35: =SUM(F35*G35) -> 0 | I35: 6808 | J35: 50 | K35: =J35*I35 -> 340400 | M35: 60 | N35: =M35*L35 -> 0 | O35: 3144 | P35: 12 | Q35: =O35*P35 -> 37728 | R35: 2669 | S35: 12 | T35: =R35*S35 -> 32028 | U35: 654 | V35: 8 | W35: =U35*V35 -> 5232 | X35: 405 | Y35: 12 | Z35: =X35*Y35 -> 4860 | AA35: 578 | AB35: 10 | AC35: =AA35*AB35 -> 5780 | AD35: 282 | AE35: 25 | AF35: =AD35*AE35 -> 7050 | AG35: 809 | AH35: 7.5 | AI35: =AG35*AH35 -> 6067.5 | AK35: 15 | AL35: =AJ35*AK35 -> 0 | AM35: 229 | AN35: 10 | AO35: =AM35*AN35 -> 2290 | AP35: =R35+U35+X35+AA35+AD35+AG35+AM35 -> 5626 | AX35: 1554 | AZ35: =O35/(I35+F35+L35) -> 0.46180964 | BA35: =AP35/(I35+F35+L35) -> 0.82638073 | BB35: =AX35/O35 -> 0.49427481 | BC35: =H35+W35+Z35+AC35+AF35+T35+K35+N35 -> 395350 | BD35: =H35+AF35+T35+K35+N35 -> 379478 | BE35: =H35+W35+Z35+AC35+AF35+T35+K35+N35 -> 395350 | BF35: =H35+W35+Z35+AC35+AF35+AI35+T35+K35+N35 -> 401417.5 | BG35: 471839.5 | BH35: 312389.29 | BI35: =+BH35/BG35% -> 66.206685 | BJ35: =SUM(BY35+BZ35+CA35+CB35) -> 35058 | BK35: =SUM(CF35+CG35+CH35+CI35) -> 0.074300689 | BL35: =B35 -> 3 | BM35: =CC35 -> 45825 | BN35: =+BU35/BM35 -> 2.857157 | BO35: =CD35 -> 0 | BP35: =+BU35/BO35 -> #DIV/0! | BQ35: =CE35 -> 15000 | BR35: =+BU35/BQ35 -> 8.7286147 | BS35: =BU35-BM35-BO35-BQ35-BY35-BZ35-CA35-CB35 -> 35046.22 | BT35: =+BU35/BS35 -> 3.7359013 | BU35: 130929.22 | BV35: =+BU35/BG35% -> 27.748677 | BW35: =SUM(BG35-BH35-BU35) -> 28520.99 | BX35: =+BW35/BG35% -> 6.0446381 | BY35: 11906 | BZ35: 9546 | CA35: 10096 | CB35: 3510 | CC35: 45825 | CE35: 15000 | CF35: =BY35/BG35 -> 0.025233157 | CG35: =BZ35/BG35 -> 0.020231456 | CH35: =CA35/BG35 -> 0.021397106 | CI35: =CB35/BG35 -> 0.0074389702 | CJ35: =CC35/BG35 -> 0.097119889 | CK35: =+BW35*20% -> 5704.198 | CL35: =BW35*80% -> 22816.792
A36: =A35+1 -> 28 | B36: 4 | C36: MABINAY2 | G36: 40 | H36: =SUM(F36*G36) -> 0 | I36: 7785 | J36: 50 | K36: =J36*I36 -> 389250 | M36: 60 | N36: =M36*L36 -> 0 | O36: 3104 | P36: 12 | Q36: =O36*P36 -> 37248 | R36: 290 | S36: 12 | T36: =R36*S36 -> 3480 | U36: 360 | V36: 8 | W36: =U36*V36 -> 2880 | X36: 257 | Y36: 12 | Z36: =X36*Y36 -> 3084 | AA36: 666 | AB36: 10 | AC36: =AA36*AB36 -> 6660 | AD36: 35 | AE36: 25 | AF36: =AD36*AE36 -> 875 | AG36: 120 | AH36: 7.5 | AI36: =AG36*AH36 -> 900 | AK36: 15 | AL36: =AJ36*AK36 -> 0 | AN36: 10 | AO36: =AM36*AN36 -> 0 | AP36: =R36+U36+X36+AA36+AD36+AG36+AM36 -> 1728 | AX36: 1270 | AZ36: =O36/(I36+F36+L36) -> 0.39871548 | BA36: =AP36/(I36+F36+L36) -> 0.22196532 | BB36: =AX36/O36 -> 0.40914948 | BC36: =H36+W36+Z36+AC36+AF36+T36+K36+N36 -> 406229 | BD36: =H36+AF36+T36+K36+N36 -> 393605 | BE36: =H36+W36+Z36+AC36+AF36+T36+K36+N36 -> 406229 | BF36: =H36+W36+Z36+AC36+AF36+AI36+T36+K36+N36 -> 407129 | BG36: 469699 | BH36: 313337.98 | BI36: =+BH36/BG36% -> 66.710378 | BJ36: =SUM(BY36+BZ36+CA36+CB36) -> 41699 | BK36: =SUM(CF36+CG36+CH36+CI36) -> 0.088778132 | BL36: =B36 -> 4 | BM36: =CC36 -> 47700 | BN36: =+BU36/BM36 -> 2.8242757 | BO36: =CD36 -> 0 | BP36: =+BU36/BO36 -> #DIV/0! | BQ36: =CE36 -> 10000 | BR36: =+BU36/BQ36 -> 13.471795 | BS36: =BU36-BM36-BO36-BQ36-BY36-BZ36-CA36-CB36 -> 35318.95 | BT36: =+BU36/BS36 -> 3.8143249 | BU36: 134717.95 | BV36: =+BU36/BG36% -> 28.681762 | BW36: =SUM(BG36-BH36-BU36) -> 21643.07 | BX36: =+BW36/BG36% -> 4.6078595 | BY36: 15798 | BZ36: 11137 | CA36: 11254 | CB36: 3510 | CC36: 47700 | CE36: 10000 | CF36: =BY36/BG36 -> 0.033634306 | CG36: =BZ36/BG36 -> 0.02371093 | CH36: =CA36/BG36 -> 0.023960025 | CI36: =CB36/BG36 -> 0.0074728709 | CJ36: =CC36/BG36 -> 0.1015544 | CK36: =+BW36*20% -> 4328.614 | CL36: =BW36*80% -> 17314.456
A37: =A36+1 -> 29 | B37: 4 | C37: CADIZ 3 | G37: 40 | H37: =SUM(F37*G37) -> 0 | I37: 7391 | J37: 50 | K37: =J37*I37 -> 369550 | M37: 60 | N37: =M37*L37 -> 0 | O37: 2715 | P37: 12 | Q37: =O37*P37 -> 32580 | R37: 1300 | S37: 12 | T37: =R37*S37 -> 15600 | U37: 230 | V37: 8 | W37: =U37*V37 -> 1840 | X37: 158 | Y37: 12 | Z37: =X37*Y37 -> 1896 | AA37: 386 | AB37: 10 | AC37: =AA37*AB37 -> 3860 | AD37: 156 | AE37: 25 | AF37: =AD37*AE37 -> 3900 | AG37: 68 | AH37: 7.5 | AI37: =AG37*AH37 -> 510 | AK37: 15 | AL37: =AJ37*AK37 -> 0 | AM37: 44 | AN37: 12 | AO37: =AM37*AN37 -> 528 | AP37: =R37+U37+X37+AA37+AD37+AG37+AM37 -> 2342 | AX37: 905 | AZ37: =O37/(I37+F37+L37) -> 0.36733866 | BA37: =AP37/(I37+F37+L37) -> 0.31687187 | BB37: =AX37/O37 -> 0.33333333 | BC37: =H37+W37+Z37+AC37+AF37+T37+K37+N37 -> 396646 | BD37: =H37+AF37+T37+K37+N37 -> 389050 | BE37: =H37+W37+Z37+AC37+AF37+T37+K37+N37 -> 396646 | BF37: =H37+W37+Z37+AC37+AF37+AI37+T37+K37+N37 -> 397156 | BG37: 447154 | BH37: 298492.17 | BI37: =+BH37/BG37% -> 66.753774 | BJ37: =SUM(BY37+BZ37+CA37+CB37) -> 31270 | BK37: =SUM(CF37+CG37+CH37+CI37) -> 0.069931165 | BL37: =B37 -> 4 | BM37: =CC37 -> 45312 | BN37: =+BU37/BM37 -> 2.8857894 | BO37: =CD37 -> 0 | BP37: =+BU37/BO37 -> #DIV/0! | BQ37: =CE37 -> 18000 | BR37: =+BU37/BQ37 -> 7.2644939 | BS37: =BU37-BM37-BO37-BQ37-BY37-BZ37-CA37-CB37 -> 36178.89 | BT37: =+BU37/BS37 -> 3.614287 | BU37: 130760.89 | BV37: =+BU37/BG37% -> 29.242921 | BW37: =SUM(BG37-BH37-BU37) -> 17900.94 | BX37: =+BW37/BG37% -> 4.0033053 | BY37: 7678 | BZ37: 10380 | CA37: 10012 | CB37: 3200 | CC37: 45312 | CE37: 18000 | CF37: =BY37/BG37 -> 0.017170818 | CG37: =BZ37/BG37 -> 0.023213479 | CH37: =CA37/BG37 -> 0.022390496 | CI37: =CB37/BG37 -> 0.0071563712 | CJ37: =CC37/BG37 -> 0.10133422 | CK37: =+BW37*20% -> 3580.188 | CL37: =BW37*80% -> 14320.752
