Workbook

Sheet checklist
A1: TO DO | B1: REMARKS
A2: Loans | B2: done
A3: Customer List | B3: done
A4: Customer Balance | B4: done
A5: Customer Payments | B5: done
A6: Expenses
A7: Assigned per collector | B7: done
A8: Payroll | B8: exclude

Sheet SUMMARY
A1: Member ID | B1: Full Name | C1: Gender | D1: Birthdate | E1: Contact No. | F1: Baranggay | G1: Complete Address | H1: Source of Income | I1: Date Joined | J1: Membership Status | K1: Collector Assigned | L1: Cycle | M1: Loan Amount
A2: AG00001 | B2: Jeniffer C. Navarro | C2: Female | D2: 32573 | E2: 9610328020 | F2: Alinguigan 3rd | G2: Alinguigan 3rd, City of Ilagan | H2: Salary/Furniture | I2: 45919 | J2: Active | K2: Ralph L. Lopez | L2: =VLOOKUP(A2,Sheet1!G:I,3,0) -> 1 | M2: ₱30,000.00
A3: AG00002 | B3: Rhealyn R. Malana | C3: Female | D3: 34496 | E3: 9752063588 | F3: Alinguigan 3rd | G3: Alinguigan 3rd, City of Ilagan | H3: Vendor | I3: 45924 | J3: Active | K3: Ralph L. Lopez | L3: =VLOOKUP(A3,Sheet1!G:I,3,0) -> 1 | M3: ₱10,000.00
A4: AG00003 | B4: Mary Ann A. Roqued | C4: Female | D4: 34380 | E4: 9671799266 | F4: Palacian | G4: Purok 5, Brgy. Palacian, San Agustin, Isabela | H4: Mini Talipapa/Rolling Vendor | I4: 45934 | J4: Active | K4: Jason Ian R. Contawe | L4: =VLOOKUP(A4,Sheet1!G:I,3,0) -> 1 | M4: ₱30,000.00
A5: AG00004 | B5: Jovilyn D. Patacsil | C5: Female | D5: 27381 | E5: 9531406143 | F5: Palacian | G5: Purok 7, Brgy. Palacian, San Agustin, Isabela | H5: Store/Banana | I5: 45934 | J5: Active | K5: Ralph L. Lopez | L5: =VLOOKUP(A5,Sheet1!G:I,3,0) -> 2 | M5: ₱30,000.00
A6: AG00005 | B6: Teresa Agustin | C6: Female | D6: 29923 | E6: 9979859147 | F6: Palacian | G6: Purok 7, Brgy. Palacian, San Agustin, Isabela | H6: Sari Sari Store | I6: 45934 | J6: Inactive | K6: Ralph L. Lopez | L6: =VLOOKUP(A6,Sheet1!G:I,3,0) -> 1 | M6: ₱30,000.00
A7: AG00006 | B7: Juliet Agpalza | C7: Female | D7: 29741 | E7: 9268959314 | F7: Palacian | G7: Purok 6, Brgy. Palacian, San Agustin, Isabela | H7: Piggery | I7: 45934 | J7: Active | K7: Ralph L. Lopez | L7: =VLOOKUP(A7,Sheet1!G:I,3,0) -> 2 | M7: ₱12,000.00
A8: AG00007 | B8: Juvy C. Acoba | C8: Female | D8: 23805 | E8: 9263425321 | F8: Palacian | G8: Purok 5, Brgy. Palacian, San Agustin, Isabela | H8: Sari Sari Store | I8: 45934 | J8: Active | K8: Ralph L. Lopez | L8: =VLOOKUP(A8,Sheet1!G:I,3,0) -> 3 | M8: ₱20,000.00
A9: AG00008 | B9: Arlene Mae T. Batarao | C9: Female | D9: 32997 | E9: 9365351339 | F9: Palacian | G9: Purok 5, Brgy. Palacian, San Agustin, Isabela | H9: Farming | I9: 45934 | J9: Active | K9: Ralph L. Lopez | L9: =VLOOKUP(A9,Sheet1!G:I,3,0) -> 2 | M9: ₱8,000.00
A10: AG00009 | B10: Babylyn M. Manuel | C10: Female | D10: 26433 | E10: 9758964284 | F10: Palacian | G10: Purok 4, Brgy. Palacian, San Agustin, Isabela | H10: Administrative Clerk | I10: 45941 | J10: Active | K10: Ralph L. Lopez | L10: =VLOOKUP(A10,Sheet1!G:I,3,0) -> 2 | M10: ₱15,000.00
A11: AG00010 | B11: Novelyn U. Garrote | C11: Female | D11: 27726 | E11: 9352707530 | F11: Palacian | G11: Purok 6, Brgy. Palacian, San Agustin, Isabela | H11: Farming | I11: 45941 | J11: Active | K11: Ralph L. Lopez | L11: =VLOOKUP(A11,Sheet1!G:I,3,0) -> 2 | M11: ₱15,000.00
A12: AG00011 | B12: Florita L. Dadiz | C12: Female | D12: 25610 | E12: 9369393039 | F12: Palacian | G12: Purok 6, Brgy. Palacian, San Agustin, Isabela | H12: Farming | I12: 45941 | J12: Active | K12: Ralph L. Lopez | L12: =VLOOKUP(A12,Sheet1!G:I,3,0) -> 2 | M12: ₱35,000.00
A13: AG00012 | B13: Rebylen R. Tumaneng | C13: Female | D13: 24863 | E13: 9365351339 | F13: Palacian | G13: Purok 5, Brgy. Palacian, San Agustin, Isabela | H13: Farming | I13: 45941 | J13: Active | K13: Jason Ian R. Contawe | L13: =VLOOKUP(A13,Sheet1!G:I,3,0) -> 1 | M13: ₱6,000.00
... A28: AG00027 | B28: Leonora G. Bugarin | C28: Female | D28: 23170 | E28: 9532997796 | F28: Masaya Centro | G28: Masaya Centro, San Agustin, Isabela | H28: Online Seller | I28: 45969 | J28: Active | K28: Jan Mark T. Pascual | L28: =VLOOKUP(A28,Sheet1!G:I,3,0) -> 2 | M28: ₱15,000.00
A29: AG00028 | B29: Noralyn Pascual | C29: Female | D29: 26798 | E29: 9672741699 | F29: Palacian | G29: Purok 4, Brgy. Palacian, San Agustin, Isabela | I29: 45969 | J29: Active | K29: Ralph L. Lopez | L29: =VLOOKUP(A29,Sheet1!G:I,3,0) -> 2 | M29: ₱25,000.00
A30: AG00029 | B30: Emylou P. Zuniega | C30: Female | D30: 32039 | E30: 9058075130 | F30: Salay | G30: Salay, San Agustin, Isabela | H30: Government Employee | I30: 45969 | J30: Active | K30: Jan Mark T. Pascual | L30: =VLOOKUP(A30,Sheet1!G:I,3,0) -> 2 | M30: ₱30,000.00
A31: AG00030 | B31: Vilma S. Lumot | C31: Female | D31: 25327 | E31: 9679554166 | F31: Palacian | G31: Purok 4, Brgy. Palacian, San Agustin, Isabela | H31: Sari Sari Store | I31: 45969 | J31: Active | K31: Ralph L. Lopez | L31: =VLOOKUP(A31,Sheet1!G:I,3,0) -> 2 | M31: ₱20,000.00
A32: AG00031 | B32: Angelita Pacag | C32: Female | D32: 27505 | E32: 9551231524 | F32: Masaya Sur | G32: Purok 6, Brgy. Masaya Sur, San Agustin, Isabela | H32: Vendor | I32: 45969 | J32: Active | K32: Jan Mark T. Pascual | L32: =VLOOKUP(A32,Sheet1!G:I,3,0) -> 2 | M32: ₱30,000.00
A33: AG00032 | B33: Alvie A. Pascual | C33: Female | D33: 35874 | E33: 9750668212 | F33: Santos | G33: Santos, San Agustin, Isabela | H33: Office Staff | I33: 45969 | J33: Inactive | K33: Ralph L. Lopez | L33: =VLOOKUP(A33,Sheet1!G:I,3,0) -> 1 | M33: ₱20,000.00
A34: AG00033 | B34: Renz Marion Q. Navarro | C34: Male | F34: Alinguigan 3rd | G34: Alinguigan 3rd, City of Ilagan | I34: 45969 | J34: Active | K34: Ralph L. Lopez | L34: =VLOOKUP(A34,Sheet1!G:I,3,0) -> 1 | M34: ₱20,000.00
A35: AG00034 | B35: Marie Fe Melad | C35: Female | F35: Ilagan | I35: 45975 | J35: Active | K35: Ralph L. Lopez | L35: =VLOOKUP(A35,Sheet1!G:I,3,0) -> 1 | M35: ₱20,000.00
A36: AG00035 | B36: Alma Jane Awayang | C36: Female | D36: 30441 | F36: San Dionisio | G36: San Dionisio 1, Maddela Quirino | H36: Hog Raiser | I36: 45975 | J36: Active | K36: Jason Ian R. Contawe | L36: =VLOOKUP(A36,Sheet1!G:I,3,0) -> 2 | M36: ₱22,000.00
A37: AG00036 | B37: Flordeliza Awayang | C37: Female | D37: 23893 | E37: 9068682290 | F37: San Dionisio | G37: San Dionisio 1, Maddela Quirino | H37: Sari Sari Store | I37: 45975 | J37: Active | K37: Jason Ian R. Contawe | L37: =VLOOKUP(A37,Sheet1!G:I,3,0) -> 2 | M37: ₱25,000.00
A38: AG00037 | B38: Rosemarie Andres | C38: Female | D38: 29797 | E38: 9068678369 | F38: San Dionisio | G38: San Dionisio 1, Maddela Quirino | H38: Sari Sari Store | I38: 45975 | J38: Active | K38: Jan Mark T. Pascual | L38: =VLOOKUP(A38,Sheet1!G:I,3,0) -> 2 | M38: ₱30,000.00
A39: AG00038 | B39: Gracielyn Pineda | C39: Female | D39: 28482 | F39: San Dionisio | G39: San Dionisio 1, Maddela Quirino | H39: Hog Raiser | I39: 45975 | J39: Active | K39: Jan Mark T. Pascual | L39: =VLOOKUP(A39,Sheet1!G:I,3,0) -> 1 | M39: ₱20,000.00
A40: AG00039 | B40: Jhona Flores | C40: Female | D40: 30931 | F40: San Dionisio | G40: San Dionisio 1, Maddela Quirino | H40: Hog Raiser/Ukay Ukay | I40: 45982 | J40: Active | K40: Jan Mark T. Pascual | L40: =VLOOKUP(A40,Sheet1!G:I,3,0) -> 2 | M40: ₱25,000.00
A41: AG00040 | B41: Mary Jane Flores | C41: Female | D41: 28954 | F41: San Dionisio | G41: San Dionisio 1, Maddela Quirino | H41: Hog Raiser/Ukay Ukay/Hallow Blocks | I41: 45982 | J41: Active | K41: Jan Mark T. Pascual | L41: =VLOOKUP(A41,Sheet1!G:I,3,0) -> 2 | M41: ₱25,000.00
A42: AG00041 | B42: JANETH ANDRES | C42: Female | D42: 29219 | F42: San Dionisio | G42: San Dionisio 1, Maddela Quirino | H42: Hog Raiser | I42: 45982 | J42: Active | K42: Jason Ian R. Contawe | L42: =VLOOKUP(A42,Sheet1!G:I,3,0) -> 2 | M42: ₱20,000.00
A43: AG00042 | B43: RONALYN A. FLORES | C43: Female | D43: 31467 | F43: San Dionisio | G43: San Dionisio 1, Maddela Quirino | H43: Laborer/Hog Raiser | I43: 45982 | J43: Active | K43: Jan Mark T. Pascual | L43: =VLOOKUP(A43,Sheet1!G:I,3,0) -> 2 | M43: ₱35,000.00
A44: AG00043 | B44: JULIETA C. FLORES | C44: Female | D44: 25038 | F44: San Dionisio | G44: San Dionisio 1, Maddela Quirino | H44: Food Processing/Walking Vendor | I44: 45982 | J44: Active | K44: Jan Mark T. Pascual | L44: =VLOOKUP(A44,Sheet1!G:I,3,0) -> 2 | M44: ₱30,000.00
A45: AG00044 | B45: CHERRY ANN D. FLORES | C45: Female | D45: 31305 | E45: 9603879549 | F45: San Dionisio | G45: San Dionisio 1, Maddela Quirino | H45: Hog Raiser/Laborer | I45: 45982 | J45: Active | K45: Jason Ian R. Contawe | L45: =VLOOKUP(A45,Sheet1!G:I,3,0) -> 2 | M45: ₱20,000.00
A46: AG00045 | B46: GINA V. DELA CRUZ | C46: Female | D46: 28856 | F46: San Dionisio | G46: San Dionisio 1, Maddela Quirino | H46: Hog Raiser | I46: 45982 | J46: Active | K46: Jason Ian R. Contawe | L46: =VLOOKUP(A46,Sheet1!G:I,3,0) -> 2 | M46: ₱20,000.00
A47: AG00046 | B47: CARMENCITA A. MALAB | C47: Female | D47: 22103 | E47: 9525633134 | F47: Palacian | G47: Purok 4, Palacian, San Agustin, Isabela | H47: Pastor | I47: 45982 | J47: Active | K47: Ralph L. Lopez | L47: =VLOOKUP(A47,Sheet1!G:I,3,0) -> 1 | M47: ₱20,000.00
A48: AG00047 | B48: JONALYN S. PINEDA | C48: Female | D48: 29063 | F48: San Dionisio | G48: San Dionisio 1, Maddela Quirino | I48: 45982 | J48: Active | K48: Jan Mark T. Pascual | L48: =VLOOKUP(A48,Sheet1!G:I,3,0) -> 2 | M48: ₱20,000.00
A49: AG00048 | B49: ARDIE P. PAJARA | C49: Female | D49: 36492 | E49: 9064589475 | F49: Salay | G49: Salay, San Agustin, Isabela | H49: Delivery Rider | I49: 45982 | J49: Active | K49: Jan Mark T. Pascual | L49: =VLOOKUP(A49,Sheet1!G:I,3,0) -> 2 | M49: ₱20,000.00
A50: AG00049 | B50: MARILYN S. DOMINGO | C50: Female | D50: 23867 | F50: San Dionisio | G50: San Dionisio 1, Maddela Quirino | I50: 45992 | J50: Active | K50: Jason Ian R. Contawe | L50: =VLOOKUP(A50,Sheet1!G:I,3,0) -> 2 | M50: ₱20,000.00
A51: AG00050 | B51: HANNY HAIZEL ALDA | C51: Female | D51: 34129 | F51: San Dionisio | G51: San Dionisio 1, Maddela Quirino | I51: 45992 | J51: Active | K51: Jan Mark T. Pascual | L51: =VLOOKUP(A51,Sheet1!G:I,3,0) -> 1 | M51: ₱25,000.00
A52: AG00051 | B52: BEATE APRIL U. GARROTE | C52: Female | D52: 35521 | E52: 9757684032 | F52: Palacian | G52: Purok 6, Palacian, San Agustin, Isabela | H52: Caregiver | I52: 45992 | J52: Active | K52: Jason Ian R. Contawe | L52: =VLOOKUP(A52,Sheet1!G:I,3,0) -> 1 | M52: ₱15,000.00
A53: AG00052 | B53: ANALYN BULLOS | C53: Female | D53: 28128 | E53: 9673052815 | F53: Masaya Centro | G53: Purok 3, Masaya Centro, San Agustin, Isabela | H53: Direct Seller | I53: 45992 | J53: Active | K53: Jason Ian R. Contawe | L53: =VLOOKUP(A53,Sheet1!G:I,3,0) -> 1 | M53: ₱15,000.00
A54: AG00053 | B54: MONICA L. ESTIFANIO | C54: Female | D54: 34315 | E54: 9756142964 | F54: Masaya Centro | G54: Purok 3, Masaya Centro, San Agustin, Isabela | H54: Online Business | I54: 45992 | J54: Active | K54: Jason Ian R. Contawe | L54: =VLOOKUP(A54,Sheet1!G:I,3,0) -> 1 | M54: ₱15,000.00
A55: AG00054 | B55: ADORACION M. LAZATIN | C55: Female | D55: 17642 | E55: 9068641121 | F55: Masaya Centro | G55: Masaya Centro, San Agustin, Isabela | H55: Retired Teacher | I55: 45992 | J55: Active | K55: Jason Ian R. Contawe | L55: =VLOOKUP(A55,Sheet1!G:I,3,0) -> 1 | M55: ₱15,000.00
A56: AG00055 | B56: MARK MELLAN M. GABRIEL | C56: Male | D56: 36527 | E56: 9671492119 | F56: Masaya Centro | G56: Dabubu Grande, San Agustin, Isabela | H56: Beautician | I56: 45992 | J56: Active | K56: Jason Ian R. Contawe | L56: =VLOOKUP(A56,Sheet1!G:I,3,0) -> 1 | M56: ₱10,000.00
A57: AG00056 | B57: ROSENDA GARANES | C57: Female | D57: 25442 | E57: 9358244250 | F57: Masaya Centro | G57: Purok 4, Masaya Centro, San Agustin, Isabela | H57: Sari Sari Store/Vendor Frozen Foods | I57: 45992 | J57: Active | K57: Jason Ian R. Contawe | L57: =VLOOKUP(A57,Sheet1!G:I,3,0) -> 1 | M57: ₱7,000.00
A58: AG00057 | B58: PRELY SALCEDO | C58: Female | D58: 29327 | E58: 9350676857 | F58: Masaya Centro | G58: Masaya Centro, San Agustin, Isabela | H58: Sari Sari Store | I58: 45992 | J58: Active | K58: Jason Ian R. Contawe | L58: =VLOOKUP(A58,Sheet1!G:I,3,0) -> 1 | M58: ₱15,000.00
A59: AG00058 | B59: WARLIE RESPICIO | C59: Male | D59: 28504 | E59: 9532405531 | F59: Masaya Centro | G59: Masaya Centro, San Agustin, Isabela | H59: Tricycle Driver | I59: 45992 | J59: Active | K59: Jason Ian R. Contawe | L59: =VLOOKUP(A59,Sheet1!G:I,3,0) -> 1 | M59: ₱15,000.00
A60: AG00059 | B60: LOURDES MAMAUAG | C60: Female | D60: 22323 | E60: 9757535595 | F60: Masaya Centro | G60: Purok 1, Masaya Centro, San Agustin, Isabela | H60: Tailoring/Dressmaking | I60: 45992 | J60: Active | K60: Jason Ian R. Contawe | L60: =VLOOKUP(A60,Sheet1!G:I,3,0) -> 1 | M60: ₱10,000.00
A61: AG00060 | B61: MARIVIC VALDEZ | C61: Female | D61: 26326 | E61: 9357262190 | F61: Masaya Centro | G61: Purok 2, Masaya Centro, San Agustin, Isabela | H61: Piggery | I61: 45992 | J61: Inactive | K61: Jan Mark T. Pascual | L61: =VLOOKUP(A61,Sheet1!G:I,3,0) -> 1 | M61: ₱20,000.00
A62: AG00061 | B62: MERLIE ENRIQUEZ | C62: Female | D62: 22744 | E62: 9757559837 | F62: Masaya Centro | G62: Purok 2, Masaya Centro, San Agustin, Isabela | H62: Butcher | I62: 45992 | J62: Active | K62: Jason Ian R. Contawe | L62: =VLOOKUP(A62,Sheet1!G:I,3,0) -> 1 | M62: ₱15,000.00
A63: AG00062 | B63: NORMA D. GERARDO | C63: Female | D63: 22041 | E63: 9066862072 | F63: Masaya Centro | G63: Purok 3, Masaya Centro, San Agustin, Isabela | H63: Piggery | I63: 45992 | J63: Active | K63: Jan Mark T. Pascual | L63: =VLOOKUP(A63,Sheet1!G:I,3,0) -> 2 | M63: ₱20,000.00
... A72: AG00071 | B72: MILAGROS VALMONTE | C72: Female | D72: 24806 | E72: 9930847578 | F72: Santos | G72: Purok 1, Santos, San Agustin, Isabela | H72: Lugawan | I72: 45992 | J72: Active | K72: Ralph L. Lopez | L72: =VLOOKUP(A72,Sheet1!G:I,3,0) -> 2 | M72: ₱10,000.00
A73: AG00072 | B73: AMELIA M. TARACATAC | C73: Female | D73: 25378 | F73: Masaya Sur | G73: Purok 1, Masaya Sur, San Agustin, Isabela | H73: Vendor | I73: 45992 | J73: Active | K73: Jan Mark T. Pascual | L73: =VLOOKUP(A73,Sheet1!G:I,3,0) -> 2 | M73: ₱20,000.00
A74: AG00073 | B74: MELBA B. MARTIN | C74: Female | D74: 24436 | F74: Masaya Sur | G74: Purok 1, Masaya Sur, San Agustin, Isabela | H74: Vendor | I74: 45992 | J74: Active | K74: Jan Mark T. Pascual | L74: =VLOOKUP(A74,Sheet1!G:I,3,0) -> 2 | M74: ₱25,000.00
A75: AG00074 | B75: VILMA B. LORENZO | C75: Female | D75: 24802 | E75: 9976190574 | F75: Masaya Norte | G75: Purok 7, Masaya Norte, San Agustin, Isabela | H75: Caretaker/Pedicure/Manicute | I75: 45992 | J75: Active | K75: Jason Ian R. Contawe | L75: =VLOOKUP(A75,Sheet1!G:I,3,0) -> 1 | M75: ₱10,000.00
A76: AG00075 | B76: AMELIA ESPINUEVA | C76: Female | D76: 19751 | E76: 9177343826 | F76: Masaya Sur | G76: Purok 7, Masaya Norte, San Agustin, Isabela | H76: Laborer | I76: 45992 | J76: Active | K76: Jan Mark T. Pascual | L76: =VLOOKUP(A76,Sheet1!G:I,3,0) -> 2 | M76: ₱10,000.00
A77: AG00076 | B77: BJAY V. DAYSON | C77: Male | D77: 38086 | E77: 9083934865 | F77: San Antonio | G77: Purok 1, San Antonio, San Agustin, Isabela | H77: Beautician | I77: 46000 | J77: Inactive | K77: Jan Mark T. Pascual | L77: =VLOOKUP(A77,Sheet1!G:I,3,0) -> 1 | M77: ₱10,000.00
A78: AG00077 | B78: MARK ANTHONY SILVESTRE | C78: Male | D78: 31751 | E78: 9363223967 | F78: Masaya Centro | G78: Masaya Centro, San Agustin, Isabela | H78: Beautician | I78: 46000 | J78: Inactive | K78: Jan Mark T. Pascual | L78: =VLOOKUP(A78,Sheet1!G:I,3,0) -> 1 | M78: ₱10,000.00
A79: AG00078 | B79: RIONALINE D. BASILIO | C79: Female | D79: 33804 | E79: 9641541644 | F79: Masaya Centro | G79: Purok 4, Masaya Centro, San Agustin, Isabela | H79: Business Owner/Habibti Salon by bhenz | I79: 46000 | J79: Active | K79: Jan Mark T. Pascual | L79: =VLOOKUP(A79,Sheet1!G:I,3,0) -> 2 | M79: ₱35,000.00
A80: AG00079 | B80: JILMA M. CUGAY | C80: Female | D80: 23721 | E80: 9675117341 | F80: Santos | G80: Purok 4, Santos, San Agustin, Isabela | H80: Vendor/Piggery | I80: 46000 | J80: Active | K80: Ralph L. Lopez | L80: =VLOOKUP(A80,Sheet1!G:I,3,0) -> 2 | M80: ₱10,000.00
A81: AG00080 | B81: KRISTIAN M. AGPAOA | C81: Male | D81: 33714 | E81: 9770318866 | F81: Masaya Sur | G81: Purok 1, Masaya Sur, San Agustin, Isabela | H81: Admin. Assistant | I81: 46000 | J81: Active | K81: Jan Mark T. Pascual | L81: =VLOOKUP(A81,Sheet1!G:I,3,0) -> 2 | M81: ₱17,000.00
A82: AG00081 | B82: NORILYN APOSTOL | C82: Female | D82: 27411 | E82: 9553375359 | F82: Masaya Sur | G82: Purok 5, Masaya Sur, San Agustin, Isabela | H82: Farming | I82: 46000 | J82: Active | K82: Jason Ian R. Contawe | L82: =VLOOKUP(A82,Sheet1!G:I,3,0) -> 1 | M82: ₱12,000.00
A83: AG00082 | B83: GELLY MAE C. TALAMAYAN | C83: Female | D83: 34103 | E83: 9755630248 | F83: Masaya Norte | G83: Purok 1, Masaya Norte, San Agustin, Isabela | H83: Brgy. Secretary | I83: 46000 | J83: Inactive | K83: Ralph L. Lopez | L83: =VLOOKUP(A83,Sheet1!G:I,3,0) -> 1 | M83: ₱10,000.00
A84: AG00083 | B84: MARLO S. ANGEL | C84: Female | D84: 26016 | E84: 9169418189 | F84: Masaya Centro | G84: Purok 1, Masaya Centro, San Agustin, Isabela | H84: Angel's Food Hub | I84: 46000 | J84: Active | K84: Jan Mark T. Pascual | L84: =VLOOKUP(A84,Sheet1!G:I,3,0) -> 2 | M84: ₱20,000.00
A85: AG00084 | B85: ROWENA M. LUIS | C85: Female | D85: 24581 | E85: 9553377631 | F85: Masaya Centro | G85: Purok 3, Masaya Centro, San Agustin, Isabela | H85: Online Seller/Retailer | I85: 46000 | J85: Active | K85: Jan Mark T. Pascual | L85: =VLOOKUP(A85,Sheet1!G:I,3,0) -> 2 | M85: ₱10,000.00
A86: AG00085 | B86: JULIE A. CASTILLO | C86: Female | D86: 24444 | F86: Santos | G86: Purok 6, Santos, San Agustin, Isabela | H86: Vendor | I86: 46000 | J86: Active | K86: Ralph L. Lopez | L86: =VLOOKUP(A86,Sheet1!G:I,3,0) -> 2 | M86: ₱10,000.00
A87: AG00086 | B87: PERLITA D. TOMAS | C87: Female | D87: 23979 | F87: Santos | G87: Purok 2, Santos, San Agustin, Isabela | H87: Piggery | I87: 46000 | J87: Active | K87: Ralph L. Lopez | L87: =VLOOKUP(A87,Sheet1!G:I,3,0) -> 2 | M87: ₱10,000.00
A88: AG00087 | B88: JANET S. DALLORAN | C88: Female | D88: 25832 | E88: 9953514025 | F88: Palacian | G88: Purok 7, Palacian, San Agustin, Isabela | H88: Sari Sari Store | I88: 46000 | J88: Inactive | K88: Ralph L. Lopez | L88: =VLOOKUP(A88,Sheet1!G:I,3,0) -> 1 | M88: ₱15,000.00
A89: AG00088 | B89: CHARILYN TUMOMBA | C89: Female | D89: 28324 | E89: 9531509824 | F89: Palacian | G89: Purok 7, Palacian, San Agustin, Isabela | H89: Farming | I89: 46000 | J89: Active | K89: Jason Ian R. Contawe | L89: =VLOOKUP(A89,Sheet1!G:I,3,0) -> 1 | M89: ₱12,000.00
A90: AG00089 | B90: VIOLETA CASTRICIONES | C90: Female | D90: 22841 | F90: Palacian | G90: Purok 7, Palacian, San Agustin, Isabela | H90: Farming | I90: 46000 | J90: Active | K90: Jason Ian R. Contawe | L90: =VLOOKUP(A90,Sheet1!G:I,3,0) -> 1 | M90: ₱8,000.00
A91: AG00090 | B91: LUVY J. ANTONIO | C91: Female | D91: 25530 | F91: Sinaoangan Norte | G91: Purok 4, Sinaoangan Norte, San Agustin, isabela | I91: 46000 | J91: Active | K91: Jason Ian R. Contawe | L91: =VLOOKUP(A91,Sheet1!G:I,3,0) -> 2 | M91: ₱30,000.00
A92: AG00091 | B92: SHEREL N. VALDEZ | C92: Female | D92: 32449 | E92: 9264638093 | F92: Sinaoangan Norte | G92: Purok 4, Sinaoangan Norte, San Agustin, isabela | I92: 46000 | J92: Active | K92: Ralph L. Lopez | L92: =VLOOKUP(A92,Sheet1!G:I,3,0) -> 2 | M92: ₱30,000.00
A93: AG00092 | B93: EMELY C. ALEJO | C93: Female | D93: 26490 | F93: Sinaoangan Norte | G93: Purok 4, Sinaoangan Norte, San Agustin, isabela | I93: 46000 | J93: Active | K93: Ralph L. Lopez | L93: =VLOOKUP(A93,Sheet1!G:I,3,0) -> 2 | M93: ₱30,000.00
A94: AG00093 | B94: SUSAN N. ANDRES | C94: Female | D94: 23510 | F94: Sinaoangan Norte | G94: Sinaoangan Norte, San Agustin, Isabela | I94: 46000 | J94: Active | K94: Jason Ian R. Contawe | L94: =VLOOKUP(A94,Sheet1!G:I,3,0) -> 1 | M94: ₱15,000.00
A95: AG00094 | B95: CRISELDA B. DELA CRUZ | C95: Female | D95: 31031 | E95: 9532414268 | F95: Masaya Centro | G95: Purok 3, Masaya Centro, San Agustin, Isabela | H95: Online Business/Baby sitter | I95: 46000 | J95: Active | K95: Jason Ian R. Contawe | L95: =VLOOKUP(A95,Sheet1!G:I,3,0) -> 1 | M95: ₱10,000.00
A96: AG00095 | B96: LIEZEL B. DELOS SANTOS | C96: Female | D96: 28712 | E96: 9358246506 | F96: Masaya Norte | G96: Purok 1, Masaya Norte, San Agustin, Isabela | H96: Sari Sari Store | I96: 46000 | J96: Active | K96: Ralph L. Lopez | L96: =VLOOKUP(A96,Sheet1!G:I,3,0) -> 2 | M96: ₱15,000.00
A97: AG00096 | B97: JANE R. MABATAN | C97: Female | D97: 32225 | E97: 9279411780 | F97: Masaya Norte | G97: Purok 1, Masaya Norte, San Agustin, Isabela | H97: Ukay Ukay | I97: 46000 | J97: Active | K97: Jason Ian R. Contawe | L97: =VLOOKUP(A97,Sheet1!G:I,3,0) -> 1 | M97: ₱10,000.00
A98: AG00097 | B98: Lovejoy B. Andres | C98: Female | D98: 29367 | F98: San Dionisio | G98: San Dionisio 1, Maddela Quirino | H98: Laborer | I98: 46006 | J98: Active | K98: Jan Mark T. Pascual | L98: =VLOOKUP(A98,Sheet1!G:I,3,0) -> 2 | M98: ₱23,000.00
A99: AG00098 | B99: Jennifer M. Andres | C99: Female | D99: 33119 | E99: 9686572723 | F99: San Dionisio | G99: San Dionisio 1, Maddela Quirino | H99: Walking Vendor | I99: 46006 | J99: Active | K99: Jan Mark T. Pascual | L99: =VLOOKUP(A99,Sheet1!G:I,3,0) -> 2 | M99: ₱35,000.00
A100: AG00099 | B100: Charles L. Domingo Jr. | C100: Male | D100: 32256 | E100: 9532740973 | F100: San Dionisio | G100: San Dionisio 1, Maddela Quirino | H100: Internet Provider | I100: 46006 | J100: Active | K100: Jan Mark T. Pascual | L100: =VLOOKUP(A100,Sheet1!G:I,3,0) -> 2 | M100: ₱30,000.00
A101: AG00100 | B101: Eden Myrah P. Flores | C101: Female | D101: 27760 | E101: 975896764 | F101: San Dionisio | G101: San Dionisio 1, Maddela Quirino | H101: Rice Retailer | I101: 46006 | J101: Active | K101: Jan Mark T. Pascual | L101: =VLOOKUP(A101,Sheet1!G:I,3,0) -> 2 | M101: ₱30,000.00
A102: AG00101 | B102: Mayrose M. Dumlao | C102: Female | D102: 29742 | E102: 9614603689 | F102: San Dionisio | G102: San Dionisio 1, Maddela Quirino | H102: Buy and Sell | I102: 46006 | J102: Active | K102: Jan Mark T. Pascual | L102: =VLOOKUP(A102,Sheet1!G:I,3,0) -> 2 | M102: ₱50,000.00
A103: AG00102 | B103: Kathleen Gay T. Manuel | C103: Female | D103: 33254 | E103: 9765094748 | F103: Panang | G103: Purok 1, Panang, San Agustin, Isabela | H103: Banana Dealer | I103: 46006 | J103: Active | K103: Ralph L. Lopez | L103: =VLOOKUP(A103,Sheet1!G:I,3,0) -> 2 | M103: ₱15,000.00
A104: AG00103 | B104: Jess Mark Alejo | C104: Male | D104: 35781 | F104: Sinaoangan Norte | G104: Purok 3, Sinaongan Norte, San Agustin, Isabela | I104: 46006 | J104: Active | K104: Ralph L. Lopez | L104: =VLOOKUP(A104,Sheet1!G:I,3,0) -> 2 | M104: ₱15,000.00
A105: AG00104 | B105: Vilma Bareng | C105: Female | D105: 24861 | F105: Sinaoangan Norte | G105: Purok 3, Sinaongan Norte, San Agustin, Isabela | I105: 46006 | J105: Active | K105: Ralph L. Lopez | L105: =VLOOKUP(A105,Sheet1!G:I,3,0) -> 2 | M105: ₱18,000.00
A106: AG00105 | B106: Maria Celeste Espela | C106: Female | D106: 32161 | E106: 9562380605 | F106: Sinaoangan Norte | G106: Sinaoangan Norte, San Agustin, Isabela | I106: 46006 | J106: Active | K106: Ralph L. Lopez | L106: =VLOOKUP(A106,Sheet1!G:I,3,0) -> 2 | M106: ₱12,000.00
A107: AG00106 | B107: Daisy J. Fernando | C107: Female | D107: 23369 | F107: Sinaoangan Norte | G107: Sinaoangan Norte, San Agustin, Isabela | I107: 46006 | J107: Inactive | K107: Ralph L. Lopez | L107: =VLOOKUP(A107,Sheet1!G:I,3,0) -> 1 | M107: ₱15,000.00
A108: AG00107 | B108: Jacqueline M. Pascua | C108: Female | D108: 33091 | E108: 9552938850 | F108: Masaya Sur | G108: Purok 4, Masaya Sur, San Agustin, Isabela | I108: 46006 | J108: Inactive | K108: Jan Mark T. Pascual | L108: =VLOOKUP(A108,Sheet1!G:I,3,0) -> 1 | M108: ₱10,000.00
A109: AG00108 | B109: Donnalyn T. Castillo | C109: Female | D109: 31126 | E109: 9568602616 | F109: Masaya Sur | G109: Purok 2, Masaya Sur, San Agustin, Isabela | H109: Teacher | I109: 46006 | J109: Active | K109: Jan Mark T. Pascual | L109: =VLOOKUP(A109,Sheet1!G:I,3,0) -> 2 | M109: ₱15,000.00
A110: AG00109 | B110: Anna Maria B. Lutaria | C110: Female | D110: 32672 | E110: 9930996084 | F110: Masaya Sur | G110: Purok 5, Masaya Sur, San Agustin, Isabela | H110: Rolling Dry Goods/Vegetables | I110: 46006 | J110: Active | K110: Jan Mark T. Pascual | L110: =VLOOKUP(A110,Sheet1!G:I,3,0) -> 2 | M110: ₱8,000.00
A111: AG00110 | B111: Madonna C. Antonio | C111: Female | D111: 29480 | E111: 9677188804 | F111: Masaya Sur | G111: Purok 6, Masaya Sur, San Agustin, Isabela | H111: Tailoring/Furniture | I111: 46006 | J111: Active | K111: Jason Ian R. Contawe | L111: =VLOOKUP(A111,Sheet1!G:I,3,0) -> 1 | M111: ₱10,000.00
A112: AG00111 | B112: Mary Ann D. Eramis | C112: Female | D112: 30667 | E112: 9752523975 | F112: Nemmatan | G112: Purok 6, Nemmatan, San Agustin, Isabela | H112: Teacher | I112: 46006 | J112: Active | K112: Ralph L. Lopez | L112: =VLOOKUP(A112,Sheet1!G:I,3,0) -> 2 | M112: ₱15,000.00
A113: AG00112 | B113: Ben Joe O. Alejandro | C113: Male | D113: 34058 | E113: 9108490337 | F113: Nemmatan | G113: Purok 2, Nemmatan, San Agustin, Isabela | H113: Tricycle Driver | I113: 46006 | J113: Active | K113: Jason Ian R. Contawe | L113: =VLOOKUP(A113,Sheet1!G:I,3,0) -> 1 | M113: ₱10,000.00
A114: AG00113 | B114: Nerry S. Tiburcio | C114: Female | D114: 31007 | F114: Palacian | G114: Purok 2, Palacian, San Agustin, Isabela | I114: 46006 | J114: Active | K114: Ralph L. Lopez | L114: =VLOOKUP(A114,Sheet1!G:I,3,0) -> 2 | M114: ₱20,000.00
A115: AG00114 | B115: Felicita T. Castillo | C115: Female | D115: 21842 | E115: 9758749267 | F115: Santos | G115: Purok 1, Santos, San Agustin, Isabela | H115: Sari Sari Store | I115: 46006 | J115: Active | K115: Ralph L. Lopez | L115: =VLOOKUP(A115,Sheet1!G:I,3,0) -> 2 | M115: ₱12,000.00
A116: AG00115 | B116: Leilani O. Manuel | C116: Female | D116: 31833 | E116: 9757589890 | F116: Dappig | G116: Dappig, San Agustin, Isabela | H116: Grocery Store | I116: 46014 | J116: Active | K116: Ralph L. Lopez | L116: =VLOOKUP(A116,Sheet1!G:I,3,0) -> 2 | M116: ₱10,000.00
A117: AG00116 | B117: Elizabeth M. Domingo | C117: Female | D117: 26104 | F117: Masaya Sur | G117: Purok 2, Masaya Sur, San Agustin, Isabela | H117: Housekeeper | I117: 46014 | J117: Active | K117: Jan Mark T. Pascual | L117: =VLOOKUP(A117,Sheet1!G:I,3,0) -> 2 | M117: ₱12,000.00
A118: AG00117 | B118: Aida A. Mangaoil | C118: Female | D118: 21464 | E118: 9752524984 | F118: Masaya Sur | G118: Purok 1, Masaya Sur, San Agustin, Isabela | H118: Vegetable Vendor | I118: 46014 | J118: Active | K118: Jason Ian R. Contawe | L118: =VLOOKUP(A118,Sheet1!G:I,3,0) -> 1 | M118: ₱15,000.00
A119: AG00118 | B119: Mades S. Awingan | C119: Female | E119: 9369491814 | F119: Masaya Sur | G119: Purok 1, Masaya Sur, San Agustin, Isabela | I119: 46014 | J119: Active | K119: Jason Ian R. Contawe | L119: =VLOOKUP(A119,Sheet1!G:I,3,0) -> 1 | M119: ₱15,000.00
A120: AG00119 | B120: Glydel M. Paguyo | C120: Female | D120: 35276 | E120: 9772377670 | F120: Masaya Sur | G120: Purok 1, Masaya Sur, San Agustin, Isabela | H120: Besties Bites Food House | I120: 46014 | J120: Active | K120: Jan Mark T. Pascual | L120: =VLOOKUP(A120,Sheet1!G:I,3,0) -> 2 | M120: ₱10,000.00
A121: AG00120 | B121: Flordeliza Pascual | C121: Female | D121: 22338 | E121: 9063629573 | F121: Masaya Centro | G121: Masaya Centro, San Agustin, Isabela | H121: Flordeliza Food Service | I121: 46014 | J121: Inactive | K121: Jan Mark T. Pascual | L121: =VLOOKUP(A121,Sheet1!G:I,3,0) -> 1 | M121: ₱15,000.00
A122: AG00121 | B122: Vivian G. Parel | C122: Female | D122: 26022 | E122: 9452248612 | F122: Masaya Sur | G122: Masaya Sur, San Agustin, Isabela | H122: Sari Sari Store | I122: 46014 | J122: Active | K122: Jan Mark T. Pascual | L122: =VLOOKUP(A122,Sheet1!G:I,3,0) -> 2 | M122: ₱10,000.00
...

Sheet Sheet1
A1: AG00001 | B1: Jeniffer C. Navarro | D1: =VLOOKUP(A1,SUMMARY!A:I,9,0) -> 45919 | G1: Member ID | H1: Member Name | I1: Cycle ID | J1: Collector | K1: Barangay | L1: Loan Code | M1: Loan Amount
A2: AG00002 | B2: Rhealyn R. Malana | D2: =VLOOKUP(A2,SUMMARY!A:I,9,0) -> 45924 | G2: AG00001 | H2: Jeniffer C. Navarro | I2: 1 | J2: Collector 1 | K2: Alinguigan 3rd | L2: LC30K | M2: ₱30,000.00
A3: AG00003 | B3: Mary Ann A. Roqued | D3: =VLOOKUP(A3,SUMMARY!A:I,9,0) -> 45934 | G3: AG00002 | H3: Rhealyn R. Malana | I3: 1 | J3: Collector 1 | K3: Alinguigan 3rd | L3: LC10K | M3: ₱10,000.00
A4: AG00004 | B4: Jovilyn D. Patacsil | D4: =VLOOKUP(A4,SUMMARY!A:I,9,0) -> 45934 | G4: AG00003 | H4: Mary Ann A. Roqued | I4: 1 | J4: Collector 1 | K4: Palacian | L4: LC30K | M4: ₱30,000.00
A5: AG00005 | B5: Teresa Agustin | D5: =VLOOKUP(A5,SUMMARY!A:I,9,0) -> 45934 | G5: AG00004 | H5: Jovilyn D. Patacsil | I5: 2 | J5: Collector 1 | K5: Palacian | L5: LC30K | M5: ₱30,000.00
A6: AG00006 | B6: Juliet Agpalza | D6: =VLOOKUP(A6,SUMMARY!A:I,9,0) -> 45934 | G6: AG00005 | H6: Teresa Agustin | I6: 1 | J6: Collector 1 | K6: Palacian | L6: LC30K | M6: ₱30,000.00
A7: AG00007 | B7: Juvy C. Acoba | D7: =VLOOKUP(A7,SUMMARY!A:I,9,0) -> 45934 | G7: AG00006 | H7: Juliet Agpalza | I7: 2 | J7: Collector 1 | K7: Palacian | L7: LC12K | M7: ₱12,000.00
A8: AG00008 | B8: Arlene Mae T. Batarao | D8: =VLOOKUP(A8,SUMMARY!A:I,9,0) -> 45934 | G8: AG00007 | H8: Juvy C. Acoba | I8: 3 | J8: Collector 1 | K8: Palacian | L8: LC20K | M8: ₱20,000.00
A9: AG00009 | B9: Babylyn M. Manuel | D9: =VLOOKUP(A9,SUMMARY!A:I,9,0) -> 45941 | G9: AG00008 | H9: Arlene Mae T. Batarao | I9: 2 | J9: Collector 1 | K9: Palacian | L9: LC08K | M9: ₱8,000.00
A10: AG00010 | B10: Novelyn U. Garrote | D10: =VLOOKUP(A10,SUMMARY!A:I,9,0) -> 45941 | G10: AG00009 | H10: Babylyn M. Manuel | I10: 2 | J10: Collector 1 | K10: Palacian | L10: LC15K | M10: ₱15,000.00
A11: AG00011 | B11: Florita L. Dadiz | D11: =VLOOKUP(A11,SUMMARY!A:I,9,0) -> 45941 | G11: AG00010 | H11: Novelyn U. Garrote | I11: 2 | J11: Collector 1 | K11: Palacian | L11: LC15K | M11: ₱15,000.00
A12: AG00012 | B12: Rebylen R. Tumaneng | D12: =VLOOKUP(A12,SUMMARY!A:I,9,0) -> 45941 | G12: AG00011 | H12: Florita L. Dadiz | I12: 2 | J12: Collector 1 | K12: Palacian | L12: LC35K | M12: ₱35,000.00
A13: AG00013 | B13: Grace A. Agcaoili | D13: =VLOOKUP(A13,SUMMARY!A:I,9,0) -> 45941 | G13: AG00012 | H13: Rebylen R. Tumaneng | I13: 1 | J13: Collector 1 | K13: Palacian | L13: LC06K | M13: ₱6,000.00
... A151: AG00151 | B151: Kristele Mae P. Alili | D151: =VLOOKUP(A151,SUMMARY!A:I,9,0) -> 46035 | G151: AG00150 | H151: Anna Rose Fampo | I151: 1 | J151: Collector 1 | K151: Palacian | L151: LC15K | M151: ₱15,000.00
G152: AG00151 | H152: Kristele Mae P. Alili | I152: 1 | J152: Collector 1 | K152: Palacian | L152: LC15K | M152: ₱15,000.00
A153: AG00018 | B153: Julie A. Agcaoili | D153: =VLOOKUP(A153,SUMMARY!A:I,9,0) -> 45941
A154: AG00152 | B154: Adona Marie A. Esteban | D154: =VLOOKUP(A154,SUMMARY!A:I,9,0) -> 46043
A155: AG00153 | B155: Jemilyn Miguel Jereza | D155: =VLOOKUP(A155,SUMMARY!A:I,9,0) -> 46043 | G155: AG00152 | H155: Adona Marie A. Esteban | I155: 1 | J155: Collector 1 | K155: Masaya Sur | L155: LC07K | M155: ₱7,000.00
A156: AG00154 | B156: Reybie D. Tinaza | D156: =VLOOKUP(A156,SUMMARY!A:I,9,0) -> 46043 | G156: AG00153 | H156: Jemilyn Miguel Jereza | I156: 1 | J156: Collector 1 | K156: Masaya Sur | L156: LC07K | M156: ₱7,000.00
A157: AG00155 | B157: Diolylla M. Garcia | D157: =VLOOKUP(A157,SUMMARY!A:I,9,0) -> 46043 | G157: AG00154 | H157: Reybie D. Tinaza | I157: 1 | J157: Collector 1 | K157: Masaya Sur | L157: LC07K | M157: ₱7,000.00
A158: AG00156 | B158: Mark Lester R. Asuncion | D158: =VLOOKUP(A158,SUMMARY!A:I,9,0) -> 46043 | G158: AG00155 | H158: Diolylla M. Garcia | I158: 1 | J158: Collector 1 | K158: Palacian | L158: LC10K | M158: ₱10,000.00
A159: AG00157 | B159: Larie Jade T. Andres | D159: =VLOOKUP(A159,SUMMARY!A:I,9,0) -> 46043 | G159: AG00156 | H159: Mark Lester R. Asuncion | I159: 1 | J159: Collector 1 | K159: Palacian | L159: LC10K | M159: ₱10,000.00
A160: AG00158 | B160: Relegin A. Libunao | D160: =VLOOKUP(A160,SUMMARY!A:I,9,0) -> 46043 | G160: AG00157 | H160: Larie Jade T. Andres | I160: 1 | J160: Collector 1 | K160: San Dionisio | L160: LC15K | M160: ₱15,000.00
A161: AG00159 | B161: Hanielyn Badua | D161: =VLOOKUP(A161,SUMMARY!A:I,9,0) -> 46043 | G161: AG00158 | H161: Relegin A. Libunao | I161: 2 | J161: Collector 1 | K161: San Dionisio | L161: LC20K | M161: ₱20,000.00
A162: AG00160 | B162: Grace R. Daguro | D162: =VLOOKUP(A162,SUMMARY!A:I,9,0) -> 46043 | G162: AG00159 | H162: Hanielyn Badua | I162: 1 | J162: Collector 1 | K162: San Dionisio | L162: LC15K | M162: ₱15,000.00
A163: AG00161 | B163: Kenneth James C. Alejo | D163: =VLOOKUP(A163,SUMMARY!A:I,9,0) -> 46043 | G163: AG00160 | H163: Grace R. Daguro | I163: 1 | J163: Collector 1 | K163: Dabubu Grande | L163: LC18K | M163: ₱18,000.00
A164: AG00162 | B164: Christopher F. Rayos | D164: =VLOOKUP(A164,SUMMARY!A:I,9,0) -> 46043 | G164: AG00161 | H164: Kenneth James C. Alejo | I164: 2 | J164: Collector 1 | K164: Sinaoangan Norte | L164: LC12K | M164: ₱12,000.00
A165: AG00163 | B165: Dorothy D. Domingo | D165: =VLOOKUP(A165,SUMMARY!A:I,9,0) -> 46043 | G165: AG00162 | H165: Christopher F. Rayos | I165: 2 | J165: Collector 1 | K165: Echague | L165: LC35K | M165: ₱35,000.00
A166: AG00164 | B166: Rocky Pascual | D166: =VLOOKUP(A166,SUMMARY!A:I,9,0) -> 46049 | G166: AG00163 | H166: Dorothy D. Domingo | I166: 1 | J166: Collector 1 | K166: San Dionisio | L166: LC18K | M166: ₱18,000.00
... A199: AG00197 | B199: Helen Joy P. Bulusan | D199: =VLOOKUP(A199,SUMMARY!A:I,9,0) -> 46057 | G199: AG00196 | H199: Jennifer Malab | I199: 2 | J199: Collector 1 | K199: Palacian | L199: LC18K | M199: ₱18,000.00
G200: AG00197 | H200: Helen Joy P. Bulusan | I200: 1 | J200: Collector 1 | K200: Masaya Sur | L200: LC15K | M200: ₱15,000.00
A201: AG00198 | B201: Margie P. Juan | D201: =VLOOKUP(A201,SUMMARY!A:I,9,0) -> 46064
A202: AG00199 | B202: Mary Jane D. Baluna | D202: =VLOOKUP(A202,SUMMARY!A:I,9,0) -> 46064 | G202: AG00198 | H202: Margie P. Juan | I202: 2 | J202: Collector 1 | K202: Bautista | L202: LC25K | M202: ₱25,000.00
A203: AG00200 | B203: Hanz A. Payadon | D203: =VLOOKUP(A203,SUMMARY!A:I,9,0) -> 46064 | G203: AG00199 | H203: Mary Jane D. Baluna | I203: 1 | J203: Collector 1 | K203: Bautista | L203: LC10K | M203: ₱10,000.00
A204: AG00201 | B204: Gloria D. Abe | D204: =VLOOKUP(A204,SUMMARY!A:I,9,0) -> 46064 | G204: AG00200 | H204: Hanz A. Payadon | I204: 1 | J204: Collector 1 | K204: Bautista | L204: LC10K | M204: ₱10,000.00
A205: AG00202 | B205: Marilou E. Biagan | D205: =VLOOKUP(A205,SUMMARY!A:I,9,0) -> 46064 | G205: AG00201 | H205: Gloria D. Abe | I205: 1 | J205: Collector 1 | K205: Masaya Sur | L205: LC10K | M205: ₱10,000.00
A206: AG00203 | B206: Eddie M. Gallardo | D206: =VLOOKUP(A206,SUMMARY!A:I,9,0) -> 46064 | G206: AG00202 | H206: Marilou E. Biagan | I206: 2 | J206: Collector 1 | K206: Quimalabasa Sur | L206: LC20K | M206: ₱20,000.00
A207: AG00204 | B207: Fredelita R. Magaoay | D207: =VLOOKUP(A207,SUMMARY!A:I,9,0) -> 46064 | G207: AG00203 | H207: Eddie M. Gallardo | I207: 1 | J207: Collector 1 | K207: Quimalabasa Sur | L207: LC08K | M207: ₱8,000.00
A208: AG00205 | B208: Joy A. Manuel | D208: =VLOOKUP(A208,SUMMARY!A:I,9,0) -> 46064 | G208: AG00204 | H208: Fredelita R. Magaoay | I208: 1 | J208: Collector 1 | K208: Quimalabasa Sur | L208: LC07K | M208: ₱7,000.00
A209: AG00206 | B209: Myrna Aguinaldo | D209: =VLOOKUP(A209,SUMMARY!A:I,9,0) -> 46064 | G209: AG00205 | H209: Joy A. Manuel | I209: 1 | J209: Collector 1 | K209: Quimalabasa Sur | L209: LC05K | M209: ₱5,000.00
A210: AG00207 | B210: Trishia Mae S. Toquero | D210: =VLOOKUP(A210,SUMMARY!A:I,9,0) -> 46064 | G210: AG00206 | H210: Myrna Aguinaldo | I210: 2 | J210: Collector 1 | K210: Quimalabasa Sur | L210: LC08K | M210: ₱8,000.00
A211: AG00208 | B211: Josie Paguyo | D211: =VLOOKUP(A211,SUMMARY!A:I,9,0) -> 46064 | G211: AG00207 | H211: Trishia Mae S. Toquero | I211: 1 | J211: Collector 1 | K211: San Dionisio | L211: LC12K | M211: ₱12,000.00
A212: AG00209 | B212: Janina S. Capistrano | D212: =VLOOKUP(A212,SUMMARY!A:I,9,0) -> 46064 | G212: AG00208 | H212: Josie Paguyo | I212: 1 | J212: Collector 1 | K212: Sinaoangan Norte | L212: LC12K | M212: ₱12,000.00
A213: AG00210 | B213: Jay Smart C. Malab | D213: =VLOOKUP(A213,SUMMARY!A:I,9,0) -> 46069 | G213: AG00209 | H213: Janina S. Capistrano | I213: 1 | J213: Collector 1 | K213: Masaya Sur | L213: LC07K | M213: ₱7,000.00
... A288: AG00285 | B288: Wenilyn M. Karganilla | D288: =VLOOKUP(A288,SUMMARY!A:I,9,0) -> 46184 | G288: AG00284 | H288: Kevin P. Root | I288: 1 | J288: Collector 1 | K288: Masaya Sur | L288: LC07K | M288: ₱7,000.00
G289: AG00285 | H289: Wenilyn M. Karganilla | I289: 1 | J289: Collector 1 | K289: Dappig | L289: LC18K | M289: ₱18,000.00
